{"type":"FeatureCollection","data_type":"Dataset","url_type":null,"permissions":[{"permissions":{"download":true,"view":true},"group_id":"everyone"}],"classification":null,"title":"Japan Tsunami","count":2,"stream_id":100118,"contributor":{"url":"http://geocommons.com/users/23473","name":"Aljazeera"},"data_attributes":null,"calculation_params":null,"icon_link":null,"link":"http://geocommons.com/overlays/100118.json","extent":[139.702,35.5792,141.03,37.3822],"geometry_types":["point"],"unique_name":null,"name":"Japan Tsunami","feature_count":2,"description":"Friday's massive earthquake is Japan's biggest ever and the seventh largest on record, according to data from the US Geological Survey.","next_feature":null,"is_raster":false,"short_classification":"Y","stats":{},"features":[{"properties":{"name":"Fukushima nuclear power plant","description":"There is a risk of a second explosion at the Fukushima plant, but reactor 3 could withstand it as reactor 1 did yesterday.","id":"a62p2teflclm"},"type":"Feature","geometry":{"type":"Point","coordinates":[141.030121,37.38216]}},{"properties":{"name":"Tokyo","description":"","id":"a62p2t8gsmvu"},"type":"Feature","geometry":{"type":"Point","coordinates":[139.702148,35.579151]}}],"is_temporal":false,"author":{"url":"","metadata":"","contact_name":"","contact_address":"","source":"","contact_phone":""},"source":"","pagination":{"sort":null,"start":0,"total":2,"limit":1000000},"state":"complete","tags":"","published":"2014-08-12T21:04:40-04:00","id":100118}