{"type":"FeatureCollection","url":"http://maps.google.com/maps/ms?hl=en&georestrict=input_srcid:a13c4c58e73a6e7d&ie=UTF8&vps=2&jsv=323a&msa=0&output=georss&msid=215974000720194479436.00049dfa40b42d01c51ec","data_type":"Data Feed","url_type":"rss","permissions":[{"permissions":{"download":true,"view":true},"group_id":"everyone"}],"classification":null,"title":"Duane Graden - Allstate Agent","count":1,"stream_id":103011,"contributor":{"url":"http://geocommons.com/users/24148","name":"duanegraden"},"data_attributes":null,"calculation_params":null,"icon_link":null,"link":"http://geocommons.com/overlays/103011.json","extent":[-96.6828,33.0891,-96.6828,33.0891],"geometry_types":["point"],"unique_name":null,"name":"Duane Graden - Allstate Agent","feature_count":1,"description":"Allstate Insurance agent Duane Graden providing free insurance quotes for auto insurance, home insurance, life insurance, renters insurance, business insurance and car insurance in Allen, TX. \n\nAddress: 825 Market St Bldg M Ste 250, Allen, TX 75013\nPhone: (972) 359-8825\nWebsite: http://www.allstateagencies.com/DUANEGRADEN/Welcome","next_feature":null,"is_raster":false,"short_classification":"Y","stats":{"published":{"max":"2011/03/08 10:27:40 -0500","min":"2011/03/08 10:27:40 -0500","median":"2011/03/08 10:27:40 -0500"},"georss:elev":{"max":0.0,"min":0.0,"median":0.0}},"features":[{"properties":{"title":"Duane Graden - Allstate Agent","guid":"00049dfa40bb06ee32951","published":{"end_time":"2011/03/08 10:27:41 -0500","original":"Tue, 08 Mar 2011 15:27:40 +0000","granularity":"sec","time":"2011/03/08 10:27:40 -0500"},"description":"Allstate Insurance agent Duane Graden providing free insurance quotes for auto insurance, home insurance, life insurance, renters insurance, business insurance and car insurance in Allen, TX. <a href=\"http://www.allstateagencies.com/DUANEGRADEN/Welcome\">Allen TX Auto Insurance</a>, <a href=\"http://www.allstateagencies.com/DUANEGRADEN/Welcome\">Allen TX Home Insurance</a>, <a href=\"http://www.allstateagencies.com/DUANEGRADEN/Welcome\">Allen TX Renters Insurance</a>.Address: 825 Market St Bldg M Ste 250, Allen, TX 75013Phone: (972) 359-8825Website: <a href=\"http://www.allstateagencies.com/DUANEGRADEN/Welcome\">http://www.allstateagencies.com/DUANEGRADEN/Welcome</a>","id":"a629by0id2gc","georss:elev":0.0},"type":"Feature","geometry":{"type":"Point","coordinates":[-96.68277,33.089142]}}],"is_temporal":true,"author":{"url":"","metadata":"","contact_name":"","contact_address":"","source":"","contact_phone":""},"source":"","pagination":{"sort":null,"start":0,"total":1,"limit":1000000},"state":"complete","tags":"allen,allstate,insurance,tx","published":"2014-08-13T01:33:27-04:00","id":103011}