{"type":"FeatureCollection","data_type":"Dataset","url_type":null,"permissions":[{"permissions":{"download":true,"view":true},"group_id":"everyone"}],"classification":null,"title":"detour3","count":1,"stream_id":103568,"contributor":{"url":"http://geocommons.com/users/18705","name":"fmina"},"data_attributes":null,"calculation_params":null,"icon_link":null,"link":"http://geocommons.com/overlays/103568.json","extent":[-122.211,37.8374,-122.211,37.8374],"geometry_types":["point"],"unique_name":null,"name":"detour3","feature_count":1,"description":"","next_feature":null,"is_raster":false,"short_classification":"Y","stats":{},"features":[{"properties":{"name":"detour3","description":"<b>Detour #3: Marathon miles 7 &amp; 8:  Montclair – northbound of Thornhill, Cabot and Colton</b>\n<i>8am to 9:30am:</i>  Coming down Thornhill, Cabot or Colton, take right on Mountain, left on Broadway Terrace (be aware: runners will be on the other side heading toward you) Vehicles will be redirected onto Highway 13 northbound.  If needed, exit at Highway 24 to return to Highway 13 southbound. Use this detour to get to other end of Montclair Village, exit at Joaquin Miller/Lincoln exit, left over 13, left on Mountain to return to Village.    \n<i>Of special note:</i>  The only way to go up Thornhill is to approach from the southbound side of Montclair Village on Mountain Blvd, then take right on Thornhill (at the Montclair Women’s Cultural Arts Center).\n<i>After 9:45am:</i>  Runners will have cleared area; streets will be reopened to normal traffic.","id":"a73itxjesfzw"},"type":"Feature","geometry":{"type":"Point","coordinates":[-122.211077,37.837365]}}],"is_temporal":false,"author":{"url":"","metadata":"","contact_name":"","contact_address":"","source":"","contact_phone":""},"source":"","pagination":{"sort":null,"start":0,"total":1,"limit":1000000},"state":"complete","tags":"","published":"2014-08-13T02:17:22-04:00","id":103568}