{"type":"FeatureCollection","data_type":"Dataset","url_type":null,"permissions":[{"permissions":{"download":true,"view":true},"group_id":"everyone"}],"classification":null,"title":"PWC HGs - 7","count":6,"stream_id":104871,"contributor":{"url":"http://geocommons.com/users/24568","name":"srfr"},"data_attributes":null,"calculation_params":null,"icon_link":null,"link":"http://geocommons.com/overlays/104871.json","extent":[-1.374,50.8879,-1.3199,50.9629],"geometry_types":["point"],"unique_name":null,"name":"PWC HGs - 7","feature_count":6,"description":"","next_feature":null,"is_raster":false,"short_classification":"Y","stats":{"latitude":{"max":50.9629,"mean":50.9244333333333,"variance":0.000598474666666582,"stdev":0.0244637418778604,"min":50.8879,"median":50.9213},"longitude":{"max":-1.3199,"mean":-1.3551,"variance":0.000349239999999999,"stdev":0.0186879640410613,"min":-1.374,"median":-1.3588},"housegroup":{"max":7,"mean":7.0,"variance":0.0,"stdev":0.0,"min":7,"median":7}},"features":[{"properties":{"latitude":50.9213,"postal code":"SO18 6PL","longitude":-1.353,"id":"a6o14o2df1fq","housegroup":7},"type":"Feature","geometry":{"type":"Point","coordinates":[-1.353,50.9213]}},{"properties":{"latitude":50.8879,"postal code":"SO31 8FQ","longitude":-1.3199,"id":"a6o14o18901l","housegroup":7},"type":"Feature","geometry":{"type":"Point","coordinates":[-1.3199,50.8879]}},{"properties":{"latitude":50.9209,"postal code":"SO18 1GS","longitude":-1.374,"id":"a6o14nqz0swf","housegroup":7},"type":"Feature","geometry":{"type":"Point","coordinates":[-1.374,50.9209]}},{"properties":{"latitude":50.9183,"postal code":"SO18 6TL","longitude":-1.359,"id":"a6o14nmc1qsf","housegroup":7},"type":"Feature","geometry":{"type":"Point","coordinates":[-1.359,50.9183]}},{"properties":{"latitude":50.9353,"postal code":"SO18 2DR","longitude":-1.3659,"id":"a6o14o07h7u4","housegroup":7},"type":"Feature","geometry":{"type":"Point","coordinates":[-1.3659,50.9353]}},{"properties":{"latitude":50.9629,"postal code":"SO50 5HX","longitude":-1.3588,"id":"a6o14o1nk6a0","housegroup":7},"type":"Feature","geometry":{"type":"Point","coordinates":[-1.3588,50.9629]}}],"is_temporal":false,"author":{"url":"","metadata":"","contact_name":"","contact_address":"","source":"","contact_phone":""},"source":"","pagination":{"sort":null,"start":0,"total":6,"limit":1000000},"state":"complete","tags":"","published":"2014-08-13T04:03:19-04:00","id":104871}