{"type":"FeatureCollection","data_type":"Dataset","url_type":null,"permissions":[{"permissions":{"download":true,"view":true},"group_id":"everyone"}],"classification":null,"title":"May2009","count":1,"stream_id":105686,"contributor":{"url":"http://geocommons.com/users/8981","name":"mgilbert"},"data_attributes":null,"calculation_params":null,"icon_link":null,"link":"http://geocommons.com/overlays/105686.json","extent":[102.525,47.5746,102.525,47.5746],"geometry_types":["point"],"unique_name":null,"name":"May2009","feature_count":1,"description":"","next_feature":null,"is_raster":false,"short_classification":"Y","stats":{"latitude":{"max":47.574617,"min":47.574617,"median":47.574617},"longitude":{"max":102.525055,"min":102.525055,"median":102.525055}},"features":[{"properties":{"latitude":47.574617,"longitude":102.525055,"lake":"Doitin Tsagaan Nuur","id":"a6gmobm35dtk"},"type":"Feature","geometry":{"type":"Point","coordinates":[102.525055,47.574617]}}],"is_temporal":false,"author":{"url":"","metadata":"","contact_name":"","contact_address":"","source":"","contact_phone":""},"source":"","pagination":{"sort":null,"start":0,"total":1,"limit":1000000},"state":"complete","tags":"","published":"2014-08-13T05:46:54-04:00","id":105686}