{"type":"FeatureCollection","data_type":"Dataset","url_type":null,"permissions":[{"permissions":{"download":true,"view":true},"group_id":"everyone"}],"classification":null,"title":"23447 315 seq","count":12,"stream_id":106349,"contributor":{"url":"http://geocommons.com/users/24629","name":"ihelewa"},"data_attributes":null,"calculation_params":null,"icon_link":null,"link":"http://geocommons.com/overlays/106349.json","extent":[-112.535,34.5557,-112.429,34.5934],"geometry_types":["point"],"unique_name":null,"name":"23447 315 seq","feature_count":12,"description":"","next_feature":null,"is_raster":false,"short_classification":"Y","stats":{"logon_id":{"max":23447315,"mean":23447315.0,"variance":0.0,"stdev":0.0,"min":23447315,"median":23447315},"lat":{"max":34.59336,"mean":34.58128225,"variance":0.000104564604750001,"stdev":0.0102256835835068,"min":34.555676,"median":34.583578},"seq":{"max":12,"mean":6.5,"variance":13.0,"stdev":3.60555127546399,"min":1,"median":7},"long":{"max":-112.429441,"mean":-112.480195416667,"variance":0.000978815238992422,"stdev":0.0312860230613036,"min":-112.535033,"median":-112.471234}},"features":[{"properties":{"est_enroute":"05-Apr-11 8:00:00 AM","logon_id":23447315,"id":"a7bow8h8pn5j","est_onsite":"05-Apr-11 8:00:00 AM","lat":34.587831,"seq":1,"long":-112.467858,"order_num":"2344710917008J0322"},"type":"Feature","geometry":{"type":"Point","coordinates":[-112.467858,34.587831]}},{"properties":{"est_enroute":"05-Apr-11 8:09:05 AM","logon_id":23447315,"id":"a7bow86h32bx","est_onsite":"05-Apr-11 8:13:16 AM","lat":34.577581,"seq":2,"long":-112.468702,"order_num":"2344717485104E0403"},"type":"Feature","geometry":{"type":"Point","coordinates":[-112.468702,34.577581]}},{"properties":{"est_enroute":"05-Apr-11 8:49:37 AM","logon_id":23447315,"id":"a7bow84xwijd","est_onsite":"05-Apr-11 8:53:37 AM","lat":34.583578,"seq":3,"long":-112.47758,"order_num":"2344717046202P0401"},"type":"Feature","geometry":{"type":"Point","coordinates":[-112.47758,34.583578]}},{"properties":{"est_enroute":"05-Apr-11 9:02:42 AM","logon_id":23447315,"id":"a7bow8ffs4km","est_onsite":"05-Apr-11 9:08:14 AM","lat":34.571304,"seq":4,"long":-112.490046,"order_num":"234471118640180404"},"type":"Feature","geometry":{"type":"Point","coordinates":[-112.490046,34.571304]}},{"properties":{"est_enroute":"05-Apr-11 9:40:03 AM","logon_id":23447315,"id":"a7bow8jutpfj","est_onsite":"05-Apr-11 9:47:33 AM","lat":34.555676,"seq":5,"long":-112.512776,"order_num":"234471943520160329"},"type":"Feature","geometry":{"type":"Point","coordinates":[-112.512776,34.555676]}},{"properties":{"est_enroute":"05-Apr-11 11:18:27 AM","logon_id":23447315,"id":"a7bow8gifp7a","est_onsite":"05-Apr-11 11:26:36 AM","lat":34.575788,"seq":6,"long":-112.535033,"order_num":"2344711177905T0401"},"type":"Feature","geometry":{"type":"Point","coordinates":[-112.535033,34.575788]}},{"properties":{"est_enroute":"05-Apr-11 11:54:06 AM","logon_id":23447315,"id":"a7bow8fb3edn","est_onsite":"05-Apr-11 1:00:00 PM","lat":34.582075,"seq":7,"long":-112.515163,"order_num":"2344711263701V0404"},"type":"Feature","geometry":{"type":"Point","coordinates":[-112.515163,34.582075]}},{"properties":{"est_enroute":"05-Apr-11 1:27:16 PM","logon_id":23447315,"id":"a7bow86juy5x","est_onsite":"05-Apr-11 1:33:43 PM","lat":34.586832,"seq":8,"long":-112.491699,"order_num":"234471134770180330"},"type":"Feature","geometry":{"type":"Point","coordinates":[-112.491699,34.586832]}},{"properties":{"est_enroute":"05-Apr-11 1:47:21 PM","logon_id":23447315,"id":"a7bow8gtmuem","est_onsite":"05-Apr-11 1:53:07 PM","lat":34.588752,"seq":9,"long":-112.471234,"order_num":"2344710920402M0404"},"type":"Feature","geometry":{"type":"Point","coordinates":[-112.471234,34.588752]}},{"properties":{"est_enroute":"05-Apr-11 2:20:23 PM","logon_id":23447315,"id":"a7bow8j1701o","est_onsite":"05-Apr-11 2:21:23 PM","lat":34.589417,"seq":10,"long":-112.469311,"order_num":"2344710915704Q0331"},"type":"Feature","geometry":{"type":"Point","coordinates":[-112.469311,34.589417]}},{"properties":{"est_enroute":"05-Apr-11 2:30:28 PM","logon_id":23447315,"id":"a7bow86p5lr5","est_onsite":"05-Apr-11 2:39:46 PM","lat":34.583193,"seq":11,"long":-112.429441,"order_num":"2344716870008N0330"},"type":"Feature","geometry":{"type":"Point","coordinates":[-112.429441,34.583193]}},{"properties":{"est_enroute":"05-Apr-11 4:42:29 PM","logon_id":23447315,"id":"a7bow8i8cqdb","est_onsite":"05-Apr-11 4:46:46 PM","lat":34.59336,"seq":12,"long":-112.433502,"order_num":"2344716058903B0329"},"type":"Feature","geometry":{"type":"Point","coordinates":[-112.433502,34.59336]}}],"is_temporal":false,"author":{"url":"","metadata":"","contact_name":"","contact_address":"","source":"","contact_phone":""},"source":"","pagination":{"sort":null,"start":0,"total":12,"limit":1000000},"state":"complete","tags":"","published":"2014-08-13T06:45:30-04:00","id":106349}