{"type":"FeatureCollection","data_type":"Dataset","url_type":null,"permissions":[{"permissions":{"download":true,"view":true},"group_id":"everyone"}],"classification":null,"title":"City of Newcomb","count":1,"stream_id":107316,"contributor":{"url":"http://geocommons.com/users/17413","name":"h4ck3rm1k3"},"data_attributes":null,"calculation_params":null,"icon_link":null,"link":"http://geocommons.com/overlays/107316.json","extent":[-74.1646,43.9695,-74.1646,43.9695],"geometry_types":["point"],"unique_name":null,"name":"City of Newcomb","feature_count":1,"description":"the centerpoint of the city in newcomb","next_feature":null,"is_raster":false,"short_classification":"Y","stats":{"population":{"max":483,"min":483,"median":483},"osm_id":{"max":158905886.0,"min":158905886.0,"median":158905886.0}},"features":[{"properties":{"name":"Newcomb","type":"village","population":483,"osm_id":158905886.0,"id":"a65ltxgvb4vg"},"type":"Feature","geometry":{"type":"Point","coordinates":[-74.1645952,43.9695074]}}],"is_temporal":false,"author":{"url":"","metadata":"","contact_name":"","contact_address":"","source":"","contact_phone":""},"source":"","pagination":{"sort":null,"start":0,"total":1,"limit":1000000},"state":"complete","tags":"newcomb","published":"2014-08-13T08:23:21-04:00","id":107316}