{"type":"FeatureCollection","url":"http://maps.google.com/maps/ms?ie=UTF8&hl=en&msa=0&output=nl&msid=203825070990119861068.0004a1499064897ad12a2","data_type":"Data Feed","url_type":"kml","permissions":[{"permissions":{"download":true,"view":true},"group_id":"everyone"}],"classification":null,"title":"Tennessee Insurance Services, LLC - Cleveland","count":1,"stream_id":109446,"contributor":{"url":"http://geocommons.com/users/25517","name":"weinsuretn3"},"data_attributes":null,"calculation_params":null,"icon_link":null,"link":"http://geocommons.com/overlays/109446.json","extent":[-84.8754,35.1851,-84.8754,35.1851],"geometry_types":["point"],"unique_name":null,"name":"Tennessee Insurance Services, LLC - Cleveland","feature_count":1,"description":"Tennessee Insurance Services LLC finds competitive rates on various Tennessee Insurance products including auto insurance, home insurance, renters insurance, health insurance, commercial insurance and more. There are 6 locations across Tennessee in Nashville, Chattanooga, Memphis, Jackson, Murfreesboro and Cleveland. The Cleveland location is at 915 25th Street NW, Suite B, Cleveland, TN 37311.\nWebsite: http://www.weinsuretennessee.com","next_feature":null,"is_raster":false,"short_classification":"Y","stats":{},"features":[{"properties":{"name":"Tennessee Insurance Services, LLC","description":"Tennessee Insurance Services LLC finds competitive rates on various Tennessee Insurance products including auto insurance, home insurance, renters insurance, health insurance, commercial insurance and more. There are 6 locations across Tennessee in Nashville, Chattanooga, Memphis, Jackson, Murfreesboro and Cleveland. The Cleveland location is at 915 25th Street NW, Suite B, Cleveland, TN 37311. <a href=\"http://www.weinsuretennessee.com\">Cleveland TN Home Insurance</a>, <a href=\"http://www.weinsuretennessee.com\">Cleveland Auto Insurance</a>Website: <a href=\"http://www.weinsuretennessee.com\">http://www.weinsuretennessee.com</a>","id":"a673poxvta1o"},"type":"Feature","geometry":{"type":"Point","coordinates":[-84.875435,35.18507]}}],"is_temporal":false,"author":{"url":"","metadata":"","contact_name":"","contact_address":"","source":"","contact_phone":""},"source":"","pagination":{"sort":null,"start":0,"total":1,"limit":1000000},"state":"complete","tags":"cleveland,insurance,services,tennessee,tn","published":"2014-08-13T11:35:44-04:00","id":109446}