{"type":"FeatureCollection","data_type":"Dataset","url_type":null,"permissions":[{"permissions":{"download":true,"view":true},"group_id":"everyone"}],"classification":null,"title":"sant","count":10,"stream_id":109674,"contributor":{"url":"http://geocommons.com/users/25088","name":"skil"},"data_attributes":null,"calculation_params":null,"icon_link":null,"link":"http://geocommons.com/overlays/109674.json","extent":[21.1175,54.4,25.6,55.9814],"geometry_types":null,"unique_name":null,"name":"sant","feature_count":10,"description":"","next_feature":null,"is_raster":false,"short_classification":"Y","stats":{"pard/gyv":{"max":2.81,"variance":0.474312222222222,"mean":1.453,"stdev":0.68870329041048,"min":0.63,"median":1.3},"pardavimai":{"max":1468409.72,"variance":143835246266.473,"mean":429763.273,"stdev":379256.174987927,"min":161918.08,"median":355497.45},"marza":{"max":465872.85,"variance":14816044610.4337,"mean":132807.783,"stdev":121721.175686212,"min":49691.43,"median":110409.33},"marz/gyv":{"max":0.99,"variance":0.0562,"mean":0.45,"stdev":0.237065391822594,"min":0.18,"median":0.41},"gyventojai":{"max":838891,"variance":57070441982.3222,"mean":324450.9,"stdev":238894.206673838,"min":120692,"median":270798}},"features":[{"properties":{"apskritis":"Alytus","geo_score":1.0,"pard/gyv":1.3,"pardavimai":217047.13,"id":"a62dxfxyrhua","marza":69206.5,"geo_precision":"zip","marz/gyv":0.41,"gyventojai":167262},"type":"Feature","geometry":{"type":"Point","coordinates":[24.05,54.4]}},{"properties":{"apskritis":"Kaunas","geo_score":1.0,"pard/gyv":0.63,"pardavimai":406421.27,"id":"a62dxg5p2c2w","marza":117069.21,"geo_precision":"zip","marz/gyv":0.18,"gyventojai":647509},"type":"Feature","geometry":{"type":"Point","coordinates":[23.9,54.9]}},{"properties":{"apskritis":"Klaipeda","geo_score":1.0,"pard/gyv":1.2,"pardavimai":440865.51,"id":"a62dxg0aptrf","marza":124948.42,"geo_precision":"zip","marz/gyv":0.34,"gyventojai":366935},"type":"Feature","geometry":{"type":"Point","coordinates":[21.1175,55.7172222]}},{"properties":{"apskritis":"Marijampole","geo_score":1.0,"pard/gyv":0.93,"pardavimai":161918.08,"id":"a62dxg1cmup5","marza":49691.43,"geo_precision":"zip","marz/gyv":0.29,"gyventojai":173686},"type":"Feature","geometry":{"type":"Point","coordinates":[23.35,54.5666667]}},{"properties":{"apskritis":"Panevezys","geo_score":1.0,"pard/gyv":0.76,"pardavimai":206214.71,"id":"a62dxfxv6s2i","marza":65266.6,"geo_precision":"zip","marz/gyv":0.24,"gyventojai":270798},"type":"Feature","geometry":{"type":"Point","coordinates":[24.35,55.7333333]}},{"properties":{"apskritis":"Siauliai","geo_score":1.0,"pard/gyv":1.08,"pardavimai":355497.45,"id":"a62dxfw27jdy","marza":110409.33,"geo_precision":"zip","marz/gyv":0.34,"gyventojai":329063},"type":"Feature","geometry":{"type":"Point","coordinates":[23.3166667,55.9333333]}},{"properties":{"apskritis":"Taurage","geo_score":1.0,"pard/gyv":2.08,"pardavimai":251249.6,"id":"a62dxg6043xv","marza":73924.71,"geo_precision":"zip","marz/gyv":0.61,"gyventojai":120692},"type":"Feature","geometry":{"type":"Point","coordinates":[22.2897222,55.2522222]}},{"properties":{"apskritis":"Telsiai","geo_score":1.0,"pard/gyv":1.99,"pardavimai":330581.69,"id":"a62dxfzy5rja","marza":90337.75,"geo_precision":"zip","marz/gyv":0.54,"gyventojai":166322},"type":"Feature","geometry":{"type":"Point","coordinates":[22.2472222,55.9813889]}},{"properties":{"apskritis":"Utena","geo_score":1.0,"pard/gyv":2.81,"pardavimai":459427.57,"id":"a62dxg2q6sdf","marza":161351.03,"geo_precision":"zip","marz/gyv":0.99,"gyventojai":163351},"type":"Feature","geometry":{"type":"Point","coordinates":[25.6,55.5]}},{"properties":{"apskritis":"Vilnius","geo_score":1.0,"pard/gyv":1.75,"pardavimai":1468409.72,"id":"a62dxg8tvc6y","marza":465872.85,"geo_precision":"zip","marz/gyv":0.56,"gyventojai":838891},"type":"Feature","geometry":{"type":"Point","coordinates":[25.3166667,54.6833333]}}],"is_temporal":false,"author":{"url":"","metadata":"","contact_name":"","contact_address":"","source":"","contact_phone":""},"source":"","pagination":{"sort":null,"start":0,"total":10,"limit":1000000},"state":"complete","tags":"","published":"2014-08-13T11:47:34-04:00","id":109674}