{"type":"FeatureCollection","data_type":"Dataset","url_type":null,"permissions":[{"permissions":{"download":true,"view":true},"group_id":"everyone"}],"classification":null,"title":"PWC HGs - Stakesby-Lewis","count":6,"stream_id":109826,"contributor":{"url":"http://geocommons.com/users/24568","name":"srfr"},"data_attributes":null,"calculation_params":null,"icon_link":null,"link":"http://geocommons.com/overlays/109826.json","extent":[-1.5007,50.915,-1.3772,50.9754],"geometry_types":null,"unique_name":null,"name":"PWC HGs - Stakesby-Lewis","feature_count":6,"description":"","next_feature":null,"is_raster":false,"short_classification":"Y","stats":{"latitude":{"max":50.9754,"variance":0.000457860000000017,"mean":50.9354,"stdev":0.0213976634238418,"min":50.915,"median":50.9336},"longitude":{"max":-1.3772,"variance":0.00166652566666666,"mean":-1.43408333333333,"stdev":0.0408231021195923,"min":-1.5007,"median":-1.4208},"hg":{"max":3,"variance":0.0,"mean":3.0,"stdev":0.0,"min":3,"median":3}},"features":[{"properties":{"latitude":50.9324,"postcode":"SO15 7RX","longitude":-1.4208,"id":"a6lhs3ro75uq","hg":3},"type":"Feature","geometry":{"type":"Point","coordinates":[-1.4208,50.9324]}},{"properties":{"latitude":50.9367,"postcode":"SO16 5HX","longitude":-1.4336,"id":"a6lhs3lmvmuy","hg":3},"type":"Feature","geometry":{"type":"Point","coordinates":[-1.4336,50.9367]}},{"properties":{"latitude":50.9336,"postcode":"SO16 6TW","longitude":-1.4207,"id":"a6lhs3t1j31o","hg":3},"type":"Feature","geometry":{"type":"Point","coordinates":[-1.4207,50.9336]}},{"properties":{"latitude":50.9193,"postcode":"SO18 1BF","longitude":-1.3772,"id":"a6lhs3qfsovo","hg":3},"type":"Feature","geometry":{"type":"Point","coordinates":[-1.3772,50.9193]}},{"properties":{"latitude":50.915,"postcode":"SO40 8BQ","longitude":-1.5007,"id":"a6lhs3yw31r7","hg":3},"type":"Feature","geometry":{"type":"Point","coordinates":[-1.5007,50.915]}},{"properties":{"latitude":50.9754,"postcode":"SO52 9ND","longitude":-1.4515,"id":"a6lhs3v5eef6","hg":3},"type":"Feature","geometry":{"type":"Point","coordinates":[-1.4515,50.9754]}}],"is_temporal":false,"author":{"url":"","metadata":"","contact_name":"","contact_address":"","source":"","contact_phone":""},"source":"","pagination":{"sort":null,"start":0,"total":6,"limit":1000000},"state":"complete","tags":"","published":"2014-08-13T11:57:55-04:00","id":109826}