{"type":"FeatureCollection","data_type":"Dataset","url_type":null,"permissions":[{"permissions":{"download":true,"view":true},"group_id":"everyone"}],"classification":null,"title":"PWC Size","count":19,"stream_id":109843,"contributor":{"url":"http://geocommons.com/users/24568","name":"srfr"},"data_attributes":null,"calculation_params":null,"icon_link":null,"link":"http://geocommons.com/overlays/109843.json","extent":[-1.3945,50.9236,-1.3945,50.9236],"geometry_types":null,"unique_name":null,"name":"PWC Size","feature_count":19,"description":"","next_feature":null,"is_raster":false,"short_classification":"Y","stats":{"size":{"max":100,"variance":0.0,"mean":100.0,"stdev":0.0,"min":100,"median":100},"latitude":{"max":50.9236,"variance":2.13167746833056e-28,"mean":50.9236,"stdev":1.46002653000915e-14,"min":50.9236,"median":50.9236},"longitude":{"max":-1.3945,"variance":2.08171627766656e-31,"mean":-1.3945,"stdev":4.56258290627859e-16,"min":-1.3945,"median":-1.3945}},"features":[{"properties":{"size":100,"latitude":50.9236,"postcode":"SO17 2FY","longitude":-1.3945,"id":"a69zn00uhsv0"},"type":"Feature","geometry":{"type":"Point","coordinates":[-1.3945,50.9236]}},{"properties":{"size":100,"latitude":50.9236,"postcode":"SO17 2FY","longitude":-1.3945,"id":"a69zmzvg4389"},"type":"Feature","geometry":{"type":"Point","coordinates":[-1.3945,50.9236]}},{"properties":{"size":100,"latitude":50.9236,"postcode":"SO17 2FY","longitude":-1.3945,"id":"a69zmzykv0s0"},"type":"Feature","geometry":{"type":"Point","coordinates":[-1.3945,50.9236]}},{"properties":{"size":100,"latitude":50.9236,"postcode":"SO17 2FY","longitude":-1.3945,"id":"a69zmzrlrftl"},"type":"Feature","geometry":{"type":"Point","coordinates":[-1.3945,50.9236]}},{"properties":{"size":100,"latitude":50.9236,"postcode":"SO17 2FY","longitude":-1.3945,"id":"a69zmzymgzdr"},"type":"Feature","geometry":{"type":"Point","coordinates":[-1.3945,50.9236]}},{"properties":{"size":100,"latitude":50.9236,"postcode":"SO17 2FY","longitude":-1.3945,"id":"a69zmzu1qwtk"},"type":"Feature","geometry":{"type":"Point","coordinates":[-1.3945,50.9236]}},{"properties":{"size":100,"latitude":50.9236,"postcode":"SO17 2FY","longitude":-1.3945,"id":"a69zmzsv6jy6"},"type":"Feature","geometry":{"type":"Point","coordinates":[-1.3945,50.9236]}},{"properties":{"size":100,"latitude":50.9236,"postcode":"SO17 2FY","longitude":-1.3945,"id":"a69zmzqi1owm"},"type":"Feature","geometry":{"type":"Point","coordinates":[-1.3945,50.9236]}},{"properties":{"size":100,"latitude":50.9236,"postcode":"SO17 2FY","longitude":-1.3945,"id":"a69zmzp6j1nt"},"type":"Feature","geometry":{"type":"Point","coordinates":[-1.3945,50.9236]}},{"properties":{"size":100,"latitude":50.9236,"postcode":"SO17 2FY","longitude":-1.3945,"id":"a69zmzxm16zf"},"type":"Feature","geometry":{"type":"Point","coordinates":[-1.3945,50.9236]}},{"properties":{"size":100,"latitude":50.9236,"postcode":"SO17 2FY","longitude":-1.3945,"id":"a69zmznqbw0y"},"type":"Feature","geometry":{"type":"Point","coordinates":[-1.3945,50.9236]}},{"properties":{"size":100,"latitude":50.9236,"postcode":"SO17 2FY","longitude":-1.3945,"id":"a69zmzzjcvva"},"type":"Feature","geometry":{"type":"Point","coordinates":[-1.3945,50.9236]}},{"properties":{"size":100,"latitude":50.9236,"postcode":"SO17 2FY","longitude":-1.3945,"id":"a69zmzoxl0yn"},"type":"Feature","geometry":{"type":"Point","coordinates":[-1.3945,50.9236]}},{"properties":{"size":100,"latitude":50.9236,"postcode":"SO17 2FY","longitude":-1.3945,"id":"a69zmzw9yb13"},"type":"Feature","geometry":{"type":"Point","coordinates":[-1.3945,50.9236]}},{"properties":{"size":100,"latitude":50.9236,"postcode":"SO17 2FY","longitude":-1.3945,"id":"a69zmzvo0uby"},"type":"Feature","geometry":{"type":"Point","coordinates":[-1.3945,50.9236]}},{"properties":{"size":100,"latitude":50.9236,"postcode":"SO17 2FY","longitude":-1.3945,"id":"a69zmznk8eeu"},"type":"Feature","geometry":{"type":"Point","coordinates":[-1.3945,50.9236]}},{"properties":{"size":100,"latitude":50.9236,"postcode":"SO17 2FY","longitude":-1.3945,"id":"a69zmzw2mf4r"},"type":"Feature","geometry":{"type":"Point","coordinates":[-1.3945,50.9236]}},{"properties":{"size":100,"latitude":50.9236,"postcode":"SO17 2FY","longitude":-1.3945,"id":"a69zmzmn50o7"},"type":"Feature","geometry":{"type":"Point","coordinates":[-1.3945,50.9236]}},{"properties":{"size":100,"latitude":50.9236,"postcode":"SO17 2FY","longitude":-1.3945,"id":"a69zmzzl7wfb"},"type":"Feature","geometry":{"type":"Point","coordinates":[-1.3945,50.9236]}}],"is_temporal":false,"author":{"url":"","metadata":"","contact_name":"","contact_address":"","source":"","contact_phone":""},"source":"","pagination":{"sort":null,"start":0,"total":19,"limit":1000000},"state":"complete","tags":"","published":"2014-08-13T11:58:06-04:00","id":109843}