{"type":"FeatureCollection","data_type":"Dataset","url_type":null,"permissions":[{"permissions":{"download":true,"view":true},"group_id":"everyone"}],"classification":null,"title":"NSW SS 2011 By AusPost Presort Code","count":19,"stream_id":111372,"contributor":{"url":"http://geocommons.com/users/26082","name":"mjcardio"},"data_attributes":null,"calculation_params":null,"icon_link":null,"link":"http://geocommons.com/overlays/111372.json","extent":[144.729,-36.2454,153.539,-28.1775],"geometry_types":["point"],"unique_name":null,"name":"NSW SS 2011 By AusPost Presort Code","feature_count":19,"description":"","next_feature":null,"is_raster":false,"short_classification":"Y","stats":{"sumofsumofpaid":{"max":63545.0,"mean":16308.1578947368,"variance":459761478.362573,"stdev":21442.0493041727,"min":150.0,"median":3950.0},"lat":{"max":-28.177537,"mean":-33.3398855552632,"variance":5.35087182994088,"stdev":2.31319515604302,"min":-36.24540767,"median":-33.79852512},"long":{"max":153.538538,"mean":150.091124610526,"variance":5.60040626911322,"stdev":2.36651775170042,"min":144.728548,"median":150.8443667}},"features":[{"properties":{"sumofsumofpaid":3950.0,"id":"a6c2rm3rq1sf","lat":-35.19987286,"long":149.1723561},"type":"Feature","geometry":{"type":"Point","coordinates":[149.1723561,-35.19987286]}},{"properties":{"sumofsumofpaid":2975.0,"id":"a6c2rm870ch7","lat":-36.03529483,"long":146.8464638},"type":"Feature","geometry":{"type":"Point","coordinates":[146.8464638,-36.03529483]}},{"properties":{"sumofsumofpaid":4225.0,"id":"a6c2rm2ex2dg","lat":-34.70634886,"long":146.9789961},"type":"Feature","geometry":{"type":"Point","coordinates":[146.9789961,-34.70634886]}},{"properties":{"sumofsumofpaid":48155.0,"id":"a6c2rm6h0xj0","lat":-33.71706909,"long":150.8314878},"type":"Feature","geometry":{"type":"Point","coordinates":[150.8314878,-33.71706909]}},{"properties":{"sumofsumofpaid":42395.0,"id":"a6c2rm4mzuzq","lat":-33.98512263,"long":150.8443667},"type":"Feature","geometry":{"type":"Point","coordinates":[150.8443667,-33.98512263]}},{"properties":{"sumofsumofpaid":48925.0,"id":"a6c2rlzcdwhf","lat":-33.76044752,"long":151.2392089},"type":"Feature","geometry":{"type":"Point","coordinates":[151.2392089,-33.76044752]}},{"properties":{"sumofsumofpaid":45835.0,"id":"a6c2rm2eh0ct","lat":-33.79852512,"long":151.0947494},"type":"Feature","geometry":{"type":"Point","coordinates":[151.0947494,-33.79852512]}},{"properties":{"sumofsumofpaid":21525.0,"id":"a6c2rm29peqs","lat":-33.90415839,"long":151.2217379},"type":"Feature","geometry":{"type":"Point","coordinates":[151.2217379,-33.90415839]}},{"properties":{"sumofsumofpaid":63545.0,"id":"a6c2rlw4c1av","lat":-33.88265793,"long":151.1256782},"type":"Feature","geometry":{"type":"Point","coordinates":[151.1256782,-33.88265793]}},{"properties":{"sumofsumofpaid":4200.0,"id":"a6c2rm573dn3","lat":-33.1357679,"long":149.2916675},"type":"Feature","geometry":{"type":"Point","coordinates":[149.2916675,-33.1357679]}},{"properties":{"sumofsumofpaid":11390.0,"id":"a6c2rlzb9lmd","lat":-32.76498325,"long":151.5653714},"type":"Feature","geometry":{"type":"Point","coordinates":[151.5653714,-32.76498325]}},{"properties":{"sumofsumofpaid":1600.0,"id":"a6c2rm5izdde","lat":-35.4765385,"long":150.3658318},"type":"Feature","geometry":{"type":"Point","coordinates":[150.3658318,-35.4765385]}},{"properties":{"sumofsumofpaid":2400.0,"id":"a6c2rm5qoe07","lat":-31.929828,"long":148.891618},"type":"Feature","geometry":{"type":"Point","coordinates":[148.891618,-31.929828]}},{"properties":{"sumofsumofpaid":2075.0,"id":"a6c2rm6p4s2v","lat":-30.8069685,"long":151.1793908},"type":"Feature","geometry":{"type":"Point","coordinates":[151.1793908,-30.8069685]}},{"properties":{"sumofsumofpaid":2525.0,"id":"a6c2rluwgznj","lat":-28.83336,"long":153.1490282},"type":"Feature","geometry":{"type":"Point","coordinates":[153.1490282,-28.83336]}},{"properties":{"sumofsumofpaid":2635.0,"id":"a6c2rm83f4c7","lat":-30.9667835,"long":152.8600163},"type":"Feature","geometry":{"type":"Point","coordinates":[152.8600163,-30.9667835]}},{"properties":{"sumofsumofpaid":150.0,"id":"a6c2rm7lujxz","lat":-36.131154,"long":144.728548},"type":"Feature","geometry":{"type":"Point","coordinates":[144.728548,-36.131154]}},{"properties":{"sumofsumofpaid":1050.0,"id":"a6c2rlsz1mmz","lat":-36.24540767,"long":146.8063127},"type":"Feature","geometry":{"type":"Point","coordinates":[146.8063127,-36.24540767]}},{"properties":{"sumofsumofpaid":300.0,"id":"a6c2rlya2cxg","lat":-28.177537,"long":153.538538},"type":"Feature","geometry":{"type":"Point","coordinates":[153.538538,-28.177537]}}],"is_temporal":false,"author":{"url":"","metadata":"","contact_name":"","contact_address":"","source":"","contact_phone":""},"source":"","pagination":{"sort":null,"start":0,"total":19,"limit":1000000},"state":"complete","tags":"","published":"2014-08-12T23:05:33-04:00","id":111372}