{"type":"FeatureCollection","data_type":"Dataset","url_type":null,"permissions":[{"permissions":{"download":true,"view":true},"group_id":"everyone"}],"classification":null,"title":"Heliport.kml","count":1,"stream_id":111625,"contributor":{"url":"http://geocommons.com/users/2246","name":"eliana"},"data_attributes":null,"calculation_params":null,"icon_link":null,"link":"http://geocommons.com/overlays/111625.json","extent":[-159.633,22.1896,-159.633,22.1896],"geometry_types":["point"],"unique_name":null,"name":"Heliport.kml","feature_count":1,"description":"","next_feature":null,"is_raster":false,"short_classification":"Y","stats":{},"features":[{"properties":{"name":"Heliport","id":"a6789cy3sjux"},"type":"Feature","geometry":{"type":"Point","coordinates":[-159.633388,22.189553]}}],"is_temporal":false,"author":{"url":"","metadata":"","contact_name":"","contact_address":"","source":"","contact_phone":""},"source":"","pagination":{"sort":null,"start":0,"total":1,"limit":1000000},"state":"complete","tags":"","published":"2014-08-12T23:34:40-04:00","id":111625}