{"type":"FeatureCollection","data_type":"Dataset","url_type":null,"permissions":[{"permissions":{"download":true,"view":true},"group_id":"everyone"}],"classification":null,"title":"survey up20","count":3,"stream_id":113612,"contributor":{"url":"http://geocommons.com/users/25855","name":"katrinabeach"},"data_attributes":null,"calculation_params":null,"icon_link":null,"link":"http://geocommons.com/overlays/113612.json","extent":[-122.351,47.5677,-122.35,47.568],"geometry_types":["point"],"unique_name":null,"name":"survey up20","feature_count":3,"description":"","next_feature":null,"is_raster":false,"short_classification":"Y","stats":{"X":{"max":548909.885819596,"mean":548876.552486263,"variance":933.333333333333,"stdev":30.5505046330389,"min":548849.885819596,"median":548869.885819596},"Y":{"max":5268276.1773062,"mean":5268262.84397287,"variance":533.333333333333,"stdev":23.094010767585,"min":5268236.1773062,"median":5268276.1773062},"ID":{"max":47,"mean":38.6666666666667,"variance":184.333333333333,"stdev":13.5769412362775,"min":23,"median":46}},"features":[{"properties":{"X":548909.885819596,"CELL_ID":"K4","Y":5268236.1773062,"ID":23,"id":"a67fzqsasc8y"},"type":"Feature","geometry":{"type":"Point","coordinates":[-122.349765225197,47.5676675906781]}},{"properties":{"X":548849.885819596,"CELL_ID":"H2","Y":5268276.1773062,"ID":46,"id":"a67fzqqsh4zr"},"type":"Feature","geometry":{"type":"Point","coordinates":[-122.350558396368,47.568032002549]}},{"properties":{"X":548869.885819596,"CELL_ID":"I2","Y":5268276.1773062,"ID":47,"id":"a67fzqs16uy5"},"type":"Feature","geometry":{"type":"Point","coordinates":[-122.350292521203,47.5680304967367]}}],"is_temporal":false,"author":{"url":"","metadata":"","contact_name":"","contact_address":"","source":"","contact_phone":""},"source":"","pagination":{"sort":null,"start":0,"total":3,"limit":1000000},"state":"complete","tags":"","published":"2014-08-13T02:32:04-04:00","id":113612}