{"type":"FeatureCollection","data_type":"Dataset","url_type":null,"permissions":[{"permissions":{"download":true,"view":true},"group_id":"everyone"}],"classification":null,"title":"Test","count":5,"stream_id":114165,"contributor":{"url":"http://geocommons.com/users/2611","name":"vasile33"},"data_attributes":null,"calculation_params":null,"icon_link":null,"link":"http://geocommons.com/overlays/114165.json","extent":[23.0703,47.1769,23.0709,47.1773],"geometry_types":["point"],"unique_name":null,"name":"Test","feature_count":5,"description":"","next_feature":null,"is_raster":false,"short_classification":"Y","stats":{"lon":{"max":23.07087323535,"mean":23.070548886084,"variance":5.19502455306325e-08,"stdev":0.000227925965020733,"min":23.07033240259,"median":23.07056466298},"lat":{"max":47.17728307332,"mean":47.177084884878,"variance":2.11965064183785e-08,"stdev":0.000145590200282775,"min":47.17691911844,"median":47.1770197967}},"features":[{"properties":{"lon":23.07033240259,"id":"a67z5cmpsijb","lat":47.1770197967},"type":"Feature","geometry":{"type":"Point","coordinates":[23.07033240259,47.1770197967]}},{"properties":{"lon":23.07064172691,"id":"a67z5ca9pw7x","lat":47.17691911844},"type":"Feature","geometry":{"type":"Point","coordinates":[23.07064172691,47.17691911844]}},{"properties":{"lon":23.07087323535,"id":"a67z5c821yob","lat":47.17718263923},"type":"Feature","geometry":{"type":"Point","coordinates":[23.07087323535,47.17718263923]}},{"properties":{"lon":23.07056466298,"id":"a67z5cnemuin","lat":47.17728307332},"type":"Feature","geometry":{"type":"Point","coordinates":[23.07056466298,47.17728307332]}},{"properties":{"lon":23.07033240259,"id":"a67z5cnuwt39","lat":47.1770197967},"type":"Feature","geometry":{"type":"Point","coordinates":[23.07033240259,47.1770197967]}}],"is_temporal":false,"author":{"url":"","metadata":"","contact_name":"","contact_address":"","source":"","contact_phone":""},"source":"","pagination":{"sort":null,"start":0,"total":5,"limit":1000000},"state":"complete","tags":"","published":"2014-08-13T03:17:38-04:00","id":114165}