{"type":"FeatureCollection","data_type":"Dataset","url_type":null,"permissions":[{"permissions":{"download":true,"view":true},"group_id":"everyone"}],"classification":null,"title":"other ky closings","count":3,"stream_id":11476,"contributor":{"url":"http://geocommons.com/users/3995","name":"amazon"},"data_attributes":null,"calculation_params":null,"icon_link":null,"link":"http://geocommons.com/overlays/11476.json","extent":[-85.7664,37.1624,-83.3737,38.2549],"geometry_types":["point"],"unique_name":null,"name":"other ky closings","feature_count":3,"description":"ky closings","next_feature":null,"is_raster":false,"short_classification":"Y","stats":{"lat":{"max":38.25486,"mean":37.8219433333333,"variance":0.336909102308335,"stdev":0.580438715376856,"min":37.162375,"median":38.048595},"long":{"max":-83.373674,"mean":-84.546799,"variance":1.432909506025,"stdev":1.19704198173038,"min":-85.766404,"median":-84.500319}},"features":[{"properties":{"name":"Begley Lumber","city":"Hyden","id":"a644fna9hblh","lat":37.162375,"state":"KY","long":-83.373674},"type":"Feature","geometry":{"type":"Point","coordinates":[-83.373674,37.162375]}},{"properties":{"name":"Boland Maloney Lumber","city":"Louisville","id":"a644fna4rdo0","lat":38.25486,"state":"KY","long":-85.766404},"type":"Feature","geometry":{"type":"Point","coordinates":[-85.766404,38.25486]}},{"properties":{"name":"Stock Building Supply","city":"Lexington","id":"a644fnbwcaa9","lat":38.048595,"state":"KY","long":-84.500319},"type":"Feature","geometry":{"type":"Point","coordinates":[-84.500319,38.048595]}}],"is_temporal":false,"author":{"url":"","metadata":"","contact_name":"","contact_address":"","source":"","contact_phone":""},"source":"","pagination":{"sort":null,"start":0,"total":3,"limit":1000000},"state":"complete","tags":"closings,ky","published":"2009-04-02T12:00:00Z","id":11476}