{"type":"FeatureCollection","data_type":"Dataset","url_type":null,"permissions":[{"permissions":{"download":true,"view":true},"group_id":"everyone"}],"classification":null,"title":"PROBLEMS","count":2,"stream_id":115088,"contributor":{"url":"http://geocommons.com/users/26368","name":"carolinebins"},"data_attributes":null,"calculation_params":null,"icon_link":null,"link":"http://geocommons.com/overlays/115088.json","extent":[-122.42,37.7584,-122.42,37.7624],"geometry_types":["point"],"unique_name":null,"name":"PROBLEMS","feature_count":2,"description":"","next_feature":null,"is_raster":false,"short_classification":"Y","stats":{"4. square feet":{"max":2400,"min":2400,"median":2400},"8. longitude":{"max":-122.42,"mean":-122.42,"variance":0.0,"stdev":0.0,"min":-122.42,"median":-122.42},"7. latitude":{"max":37.762418,"mean":37.760393,"variance":8.20124999999774e-06,"stdev":0.00286378246380512,"min":37.758368,"median":37.762418}},"features":[{"properties":{"9. zip code":"94110","2. status":"Problems","4. square feet":2400,"3. description":"Description Renovating 2,000 sq. ft. for $6,000 or $3 a sq. ft. Problems: Fire Damage. Agent: Mark Kaplan of Rockwell Properties. Will remain vacant and off the market while the owner acquires a loan to fix up the space.","8. longitude":-122.42,"5. city":"SAN FRANCISCO","id":"a621ia2mxz43","6. state":"CA","1. address":"657 VALENCIA STREET","7. latitude":37.762418},"type":"Feature","geometry":{"type":"Point","coordinates":[-122.42,37.762418]}},{"properties":{"9. zip code":"94110","2. status":"PROBLEMS","4. square feet":null,"3. description":"La Rondalla. Carlos Barrio ran out of funds and hopes to continue renovations soon so La Rondalla can open up.","8. longitude":-122.42,"5. city":"SAN FRANCISCO","id":"a621i9u3milt","6. state":"CA","1. address":"901 VALENCIA STREET","7. latitude":37.758368},"type":"Feature","geometry":{"type":"Point","coordinates":[-122.42,37.758368]}}],"is_temporal":false,"author":{"url":"","metadata":"","contact_name":"","contact_address":"","source":"","contact_phone":""},"source":"","pagination":{"sort":null,"start":0,"total":2,"limit":1000000},"state":"complete","tags":"vacancy,valencia","published":"2014-08-13T04:27:17-04:00","id":115088}