{"type":"FeatureCollection","data_type":"Dataset","url_type":null,"permissions":[{"permissions":{"download":true,"view":true},"group_id":"everyone"}],"classification":null,"title":"Best Tucson Movers","count":1,"stream_id":115532,"contributor":{"url":"http://geocommons.com/users/20620","name":"befoundsmaps"},"data_attributes":null,"calculation_params":null,"icon_link":null,"link":"http://geocommons.com/overlays/115532.json","extent":[-110.959,32.2318,-110.959,32.2318],"geometry_types":["point"],"unique_name":null,"name":"Best Tucson Movers","feature_count":1,"description":"\nBest Tucson Movers has only the most experienced, highly trained movers and packers for both your residential and commercial moving needs. Best Tucson Movers is one of Tucson`s leading moving services\n","next_feature":null,"is_raster":false,"short_classification":"Y","stats":{},"features":[{"properties":{"city":"Tucson","name":"Best Tucson Movers","region":"US-AZ","balloon_text":"<b><a href=\"http://maps.google.com/maps/place?cid=4067257489339334237&amp;q=Best+Tucson+Movers&amp;hl=en&amp;cad=src:kml_balloon&amp;ei=WuHPTZm-M4OAvQPryOy_BQ\">$[name]</a></b>4 reviews825 East University BoulevardTucson, AZ 85719(520) 549-2235<a href=\"http://moverstucsonaz.com/\">moverstucsonaz.com</a><a href=\"/maps/place?cid=4067257489339334237&amp;q=Best+Tucson+Movers&amp;hl=en&amp;cd=1&amp;cad=src:ppphoto&amp;ei=WuHPTZm-M4OAvQPryOy_BQ\"><img src=\"http://lh5.googleusercontent.com/public/Sfr6snQyE3d7ghxI6Tsrr8HXM1mdpKGaqeFbGFifMRsdRThPDeegyQBS3sDMpnTI9UmNGNU7oJaUdrzlfhHIYIwG1fKQhDWqJXUx83w_u8VtuIHTi9u2xws\"></a>  $[geDirections]","contents":"Best Tucson Movers","id":"a62nafbu157e"},"type":"Feature","geometry":{"type":"Point","coordinates":[-110.959,32.231805]}}],"is_temporal":false,"author":{"url":"http://bbs.keyhole.com/ubb/ubbthreads.php?ubb=showflat&Number=1420196&#Post1420196","metadata":"","contact_name":"Cesar Ismael","contact_address":"825 East University Boulevard, \nTucson, AZ 85719","source":"Google Earth Community","contact_phone":"(520) 549-2235"},"source":"http://bbs.keyhole.com/ubb/ubbthreads.php?ubb=showflat&Number=1420196&#Post1420196","pagination":{"sort":null,"start":0,"total":1,"limit":1000000},"state":"complete","tags":"affordable,company,movers,moving","published":"2014-08-13T05:24:24-04:00","id":115532}