{"type":"FeatureCollection","data_type":"Dataset","url_type":null,"permissions":[{"permissions":{"download":true,"view":true},"group_id":"everyone"}],"classification":null,"title":"Office Locations","count":8,"stream_id":118124,"contributor":{"url":"http://geocommons.com/users/9343","name":"9343"},"data_attributes":null,"calculation_params":null,"icon_link":null,"link":"http://geocommons.com/overlays/118124.json","extent":[-122.246,29.7325,-77.3667,47.4593],"geometry_types":["point"],"unique_name":null,"name":"Office Locations","feature_count":8,"description":"","next_feature":null,"is_raster":false,"short_classification":"Y","stats":{},"features":[{"properties":{"name":"Lee Technologies","description":"HQ - Fairfax Office","id":"a6i9caunry4w"},"type":"Feature","geometry":{"type":"Point","coordinates":[-77.366669,38.86401]}},{"properties":{"name":"Lee Technologies","description":"Atlanta Office","id":"a6i9caqn5tn3"},"type":"Feature","geometry":{"type":"Point","coordinates":[-84.386406,33.777416]}},{"properties":{"name":"Lee Technologies","description":"Houston Office","id":"a6i9caukmxk1"},"type":"Feature","geometry":{"type":"Point","coordinates":[-95.429451,29.73245]}},{"properties":{"name":"Lee Technologies","description":"Denver Office","id":"a6i9catisub7"},"type":"Feature","geometry":{"type":"Point","coordinates":[-104.984703,39.739155]}},{"properties":{"name":"Lee Technologies","description":"Dallas Presence","id":"a6i9cb38499g"},"type":"Feature","geometry":{"type":"Point","coordinates":[-96.76992,32.802956]}},{"properties":{"name":"Lee Technologies","description":"LA Presence","id":"a6i9cawo37nv"},"type":"Feature","geometry":{"type":"Point","coordinates":[-118.243683,34.052235]}},{"properties":{"name":"Lee Technologies","description":"Chicago Presence","id":"a6i9caxl0qzq"},"type":"Feature","geometry":{"type":"Point","coordinates":[-87.629799,41.878113]}},{"properties":{"name":"Lee Technologies","description":"Seattle Office\r\n<a href=\"http://maps.google.com/maps/place?ftid=0x54905d2995af0719:0x9fd897dbbe5daa28&amp;q=16040+Christensen+Road,+Suite+202,+Seattle,+WA&amp;hl=en&amp;cad=src:ppiwlink&amp;ei=0LvfTcTDLI_-ywSYzejFBg&amp;dtab=5\"><img src=\"http://cbk0.google.com/cbk?output=thumbnail&amp;w=90&amp;h=68&amp;ll=47.459278,-122.246109&amp;thumb=0\"></a>","id":"a6i9cb45aprg"},"type":"Feature","geometry":{"type":"Point","coordinates":[-122.246109,47.459278]}}],"is_temporal":false,"author":{"url":null,"metadata":null,"contact_name":null,"contact_address":null,"source":null,"contact_phone":null},"source":null,"pagination":{"sort":null,"start":0,"total":8,"limit":1000000},"state":"complete","tags":"","published":"2014-08-13T08:23:36-04:00","id":118124}