{"type":"FeatureCollection","data_type":"Dataset","url_type":null,"permissions":[{"permissions":{"download":true,"view":true},"group_id":"everyone"}],"classification":null,"title":"1520","count":7,"stream_id":12211,"contributor":{"url":"http://geocommons.com/users/6287","name":"sickelsaz"},"data_attributes":null,"calculation_params":null,"icon_link":null,"link":"http://geocommons.com/overlays/12211.json","extent":[-98.9673,28.9044,-82.31,41.41],"geometry_types":["point"],"unique_name":null,"name":"1520","feature_count":7,"description":"","next_feature":null,"is_raster":false,"short_classification":"Y","stats":{"latitude":{"max":41.41,"mean":32.7589714285714,"variance":35.0278091290476,"stdev":5.91842961680272,"min":28.9044,"median":29.5769},"x":{"max":-82.31,"mean":-89.6677285714286,"variance":34.6631168123809,"stdev":5.88753911344807,"min":-98.9673,"median":-91.0204},"y":{"max":41.41,"mean":32.7589714285714,"variance":35.0278091290476,"stdev":5.91842961680272,"min":28.9044,"median":29.5769},"end":{"max":215.0,"mean":130.571428571429,"variance":3846.95238095238,"stdev":62.0238049538432,"min":38.0,"median":135.0},"start":{"max":205.0,"mean":120.714285714286,"variance":3896.90476190476,"stdev":62.4251933269314,"min":27.0,"median":124.0},"index":{"max":6.0,"mean":3.0,"variance":4.66666666666667,"stdev":2.16024689946929,"min":0.0,"median":3.0},"longitude":{"max":-82.31,"mean":-89.6677285714286,"variance":34.6631168123809,"stdev":5.88753911344807,"min":-98.9673,"median":-91.0204},"geoconfidence":{"max":0.653913,"mean":0.434675285714286,"variance":0.0191654327135714,"stdev":0.138439274462023,"min":0.282014,"median":0.404565}},"features":[{"properties":{"latitude":29.7724,"x":-92.7393,"georef":"HIGH ISLAND","y":29.7724,"end":38.0,"start":27.0,"index":0.0,"xpath":"","offset":"","longitude":-92.7393,"id":"a6vvgqimz0z3","geoconfidence":0.653913,"style":"loc"},"type":"Feature","geometry":{"type":"Point","coordinates":[-92.7393,29.7724]}},{"properties":{"latitude":28.9044,"x":-91.0204,"georef":"SHIP SHOAL","y":28.9044,"end":75.0,"start":65.0,"index":1.0,"xpath":"","offset":"","longitude":-91.0204,"id":"a6vvgqiq3x98","geoconfidence":0.404565,"style":"loc"},"type":"Feature","geometry":{"type":"Point","coordinates":[-91.0204,28.9044]}},{"properties":{"latitude":29.3347,"x":-89.3067,"georef":"MAIN PASS","y":29.3347,"end":107.0,"start":98.0,"index":2.0,"xpath":"","offset":"","longitude":-89.3067,"id":"a6vvgqe4gwmf","geoconfidence":0.282014,"style":"loc"},"type":"Feature","geometry":{"type":"Point","coordinates":[-89.3067,29.3347]}},{"properties":{"latitude":29.5769,"x":-98.9673,"georef":"South Texas","y":29.5769,"end":135.0,"start":124.0,"index":3.0,"xpath":"","offset":"","longitude":-98.9673,"id":"a6vvgqewjl79","geoconfidence":0.591065,"style":"loc"},"type":"Feature","geometry":{"type":"Point","coordinates":[-98.9673,29.5769]}},{"properties":{"latitude":41.41,"x":-82.31,"georef":"VERMILION","y":41.41,"end":160.0,"start":151.0,"index":4.0,"xpath":"","offset":"","longitude":-82.31,"id":"a6vvgq7ry3kk","geoconfidence":0.32525,"style":"loc"},"type":"Feature","geometry":{"type":"Point","coordinates":[-82.31,41.41]}},{"properties":{"latitude":41.41,"x":-82.31,"georef":"VERMILION","y":41.41,"end":184.0,"start":175.0,"index":5.0,"xpath":"","offset":"","longitude":-82.31,"id":"a6vvgqecleba","geoconfidence":0.430399,"style":"loc"},"type":"Feature","geometry":{"type":"Point","coordinates":[-82.31,41.41]}},{"properties":{"latitude":28.9044,"x":-91.0204,"georef":"SHIP SHOAL","y":28.9044,"end":215.0,"start":205.0,"index":6.0,"xpath":"","offset":"","longitude":-91.0204,"id":"a6vvgqh0fqck","geoconfidence":0.355521,"style":"loc"},"type":"Feature","geometry":{"type":"Point","coordinates":[-91.0204,28.9044]}}],"is_temporal":false,"author":{"url":"","metadata":"","contact_name":"","contact_address":"","source":"","contact_phone":""},"source":"","pagination":{"sort":null,"start":0,"total":7,"limit":1000000},"state":"complete","tags":"","published":"2009-04-28T12:00:00Z","id":12211}