{"type":"FeatureCollection","data_type":"Dataset","url_type":null,"permissions":[{"permissions":{"download":true,"view":true},"group_id":"everyone"}],"classification":null,"title":"Cauldwell Cabin","count":1,"stream_id":123819,"contributor":{"url":"http://geocommons.com/users/28172","name":"Murph"},"data_attributes":null,"calculation_params":null,"icon_link":null,"link":"http://geocommons.com/overlays/123819.json","extent":[-109.37,33.7446,-109.37,33.7446],"geometry_types":["point"],"unique_name":null,"name":"Cauldwell Cabin","feature_count":1,"description":"","next_feature":null,"is_raster":false,"short_classification":"Y","stats":{"GIS_ID":{"max":319934,"min":319934,"median":319934},"WFDSS_ID":{"max":319711,"min":319711,"median":319711},"DATE_CREAT":{"max":null,"min":null,"median":null}},"features":[{"properties":{"GIS_ID":319934,"WFDSS_ID":319711,"DATE_CREAT":"2011/05/30 00:00:00 +0000","USER_ID":"rbigelow","id":"a6hvsdsaebpf","LABEL":"Cauldwell Cabin"},"type":"Feature","geometry":{"type":"Point","coordinates":[-109.369926353968,33.7446111120441]}}],"is_temporal":true,"author":{"url":"","metadata":"","contact_name":"","contact_address":"","source":"","contact_phone":""},"source":"","pagination":{"sort":null,"start":0,"total":1,"limit":1000000},"state":"complete","tags":"","published":"2014-08-13T03:09:43-04:00","id":123819}