{"type":"FeatureCollection","data_type":"Dataset","url_type":null,"permissions":[{"permissions":{"download":true,"view":true},"group_id":"everyone"}],"classification":null,"title":"7221","count":16,"stream_id":12660,"contributor":{"url":"http://geocommons.com/users/6254","name":"isidorotapia"},"data_attributes":null,"calculation_params":null,"icon_link":null,"link":"http://geocommons.com/overlays/12660.json","extent":[-6.43503,36.6205,-6.1756,36.8695],"geometry_types":["point"],"unique_name":null,"name":"7221","feature_count":16,"description":"","next_feature":null,"is_raster":false,"short_classification":"Y","stats":{"tam":{"max":11.0,"mean":4.8125,"variance":6.42916666666667,"stdev":2.53558014400387,"min":1.0,"median":4.0},"ent":{"max":1297.0,"mean":1210.5,"variance":3038.66666666667,"stdev":55.1241024114377,"min":1140.0,"median":1234.0},"lat":{"max":36.869453,"mean":36.7511264375,"variance":0.00541334324999566,"stdev":0.0735754255848762,"min":36.62051,"median":36.778372},"long":{"max":-6.175604,"mean":-6.349308125,"variance":0.00290878262865001,"stdev":0.0539331310851689,"min":-6.435034,"median":-6.354095}},"features":[{"properties":{"tam":4.0,"ent":1147.0,"id":"a6maev35fn2q","lat":36.62051,"long":-6.361016},"type":"Feature","geometry":{"type":"Point","coordinates":[-6.361016,36.62051]}},{"properties":{"tam":3.0,"ent":1263.0,"id":"a6maeuucb6bw","lat":36.62183,"long":-6.357274},"type":"Feature","geometry":{"type":"Point","coordinates":[-6.357274,36.62183]}},{"properties":{"tam":4.0,"ent":1297.0,"id":"a6maeuuxluw5","lat":36.622472,"long":-6.364448},"type":"Feature","geometry":{"type":"Point","coordinates":[-6.364448,36.622472]}},{"properties":{"tam":1.0,"ent":1140.0,"id":"a6maeuv7fq0e","lat":36.693085,"long":-6.415314},"type":"Feature","geometry":{"type":"Point","coordinates":[-6.415314,36.693085]}},{"properties":{"tam":7.0,"ent":1149.0,"id":"a6maeunrtcfi","lat":36.737565,"long":-6.435034},"type":"Feature","geometry":{"type":"Point","coordinates":[-6.435034,36.737565]}},{"properties":{"tam":7.0,"ent":1279.0,"id":"a6maeupcu0zp","lat":36.77528,"long":-6.353289},"type":"Feature","geometry":{"type":"Point","coordinates":[-6.353289,36.77528]}},{"properties":{"tam":4.0,"ent":1249.0,"id":"a6maev1aetxp","lat":36.77772,"long":-6.357599},"type":"Feature","geometry":{"type":"Point","coordinates":[-6.357599,36.77772]}},{"properties":{"tam":3.0,"ent":1199.0,"id":"a6maeunwzpuy","lat":36.77772,"long":-6.357599},"type":"Feature","geometry":{"type":"Point","coordinates":[-6.357599,36.77772]}},{"properties":{"tam":11.0,"ent":1234.0,"id":"a6maeuts4sqf","lat":36.778372,"long":-6.354095},"type":"Feature","geometry":{"type":"Point","coordinates":[-6.354095,36.778372]}},{"properties":{"tam":6.0,"ent":1145.0,"id":"a6maeuxbajzw","lat":36.77867,"long":-6.352169},"type":"Feature","geometry":{"type":"Point","coordinates":[-6.352169,36.77867]}},{"properties":{"tam":7.0,"ent":1245.0,"id":"a6maeuq4qlfl","lat":36.78004,"long":-6.354139},"type":"Feature","geometry":{"type":"Point","coordinates":[-6.354139,36.78004]}},{"properties":{"tam":3.0,"ent":1197.0,"id":"a6maeuug9wh2","lat":36.783365,"long":-6.352154},"type":"Feature","geometry":{"type":"Point","coordinates":[-6.352154,36.783365]}},{"properties":{"tam":5.0,"ent":1255.0,"id":"a6maeuod5l90","lat":36.78402,"long":-6.343604},"type":"Feature","geometry":{"type":"Point","coordinates":[-6.343604,36.78402]}},{"properties":{"tam":3.0,"ent":1174.0,"id":"a6maeup0c86l","lat":36.79973,"long":-6.336434},"type":"Feature","geometry":{"type":"Point","coordinates":[-6.336434,36.79973]}},{"properties":{"tam":2.0,"ent":1254.0,"id":"a6maeurcjkfp","lat":36.818191,"long":-6.319158},"type":"Feature","geometry":{"type":"Point","coordinates":[-6.319158,36.818191]}},{"properties":{"tam":7.0,"ent":1141.0,"id":"a6maeuuo06ut","lat":36.869453,"long":-6.175604},"type":"Feature","geometry":{"type":"Point","coordinates":[-6.175604,36.869453]}}],"is_temporal":false,"author":{"url":"","metadata":"","contact_name":"","contact_address":"","source":"","contact_phone":""},"source":"","pagination":{"sort":null,"start":0,"total":16,"limit":1000000},"state":"complete","tags":"","published":"2014-08-10T15:21:48-04:00","id":12660}