{"type":"FeatureCollection","data_type":"Dataset","url_type":null,"permissions":[{"permissions":{"download":true,"view":true},"group_id":"everyone"}],"classification":null,"title":"noise2","count":3,"stream_id":127344,"contributor":{"url":"http://geocommons.com/users/19886","name":"hrickards"},"data_attributes":null,"calculation_params":null,"icon_link":null,"link":"http://geocommons.com/overlays/127344.json","extent":[0.005115,50.8744,0.017403,50.8752],"geometry_types":["point"],"unique_name":null,"name":"noise2","feature_count":3,"description":"","next_feature":null,"is_raster":false,"short_classification":"Y","stats":{"score":{"max":9,"mean":6.66666666666667,"variance":4.33333333333333,"stdev":2.08166599946613,"min":5,"median":6},"lng":{"max":0.017403,"mean":0.010789,"variance":3.8411436e-05,"stdev":0.00619769602352358,"min":0.005115,"median":0.009849},"lat":{"max":50.875189,"mean":50.87469,"variance":1.93722999998157e-07,"stdev":0.000440139750531756,"min":50.874357,"median":50.874524}},"features":[{"properties":{"score":6,"lng":0.009849,"id":"a69z4pyz9itq","lat":50.875189},"type":"Feature","geometry":{"type":"Point","coordinates":[0.009849,50.875189]}},{"properties":{"score":9,"lng":0.005115,"id":"a69z4pteeg2p","lat":50.874524},"type":"Feature","geometry":{"type":"Point","coordinates":[0.005115,50.874524]}},{"properties":{"score":5,"lng":0.017403,"id":"a69z4pt132v0","lat":50.874357},"type":"Feature","geometry":{"type":"Point","coordinates":[0.017403,50.874357]}}],"is_temporal":false,"author":{"url":"","metadata":"","contact_name":"","contact_address":"","source":"","contact_phone":""},"source":"","pagination":{"sort":null,"start":0,"total":3,"limit":1000000},"state":"complete","tags":"","published":"2014-08-13T09:04:27-04:00","id":127344}