{"type":"FeatureCollection","data_type":"Dataset","url_type":null,"permissions":[{"permissions":{"download":true,"view":true},"group_id":"everyone"}],"classification":null,"title":"FortiusOne World Headquarters","count":2,"stream_id":12784,"contributor":{"url":"http://geocommons.com/users/1842","name":"geomatt1"},"data_attributes":null,"calculation_params":null,"icon_link":null,"link":"http://geocommons.com/overlays/12784.json","extent":[-77.0859,38.8911,-77.0859,38.8911],"geometry_types":["point"],"unique_name":null,"name":"FortiusOne World Headquarters","feature_count":2,"description":"FortiusOne World Headquarters","next_feature":null,"is_raster":false,"short_classification":"Y","stats":{"zip":{"max":22201.0,"mean":22201.0,"variance":0.0,"stdev":0.0,"min":22201.0,"median":22201.0},"latitude":{"max":38.891143,"mean":38.891143,"variance":0.0,"stdev":0.0,"min":38.891143,"median":38.891143},"longitude":{"max":-77.085855,"mean":-77.085855,"variance":0.0,"stdev":0.0,"min":-77.085855,"median":-77.085855}},"features":[{"properties":{"company":"FortiusOne","city":"Arlington","zip":22201.0,"latitude":38.891143,"longitude":-77.085855,"id":"a621x968cacj","address":"2200 Wilson Blvd","state":"VA"},"type":"Feature","geometry":{"type":"Point","coordinates":[-77.085855,38.891143]}},{"properties":{"company":"FortiusOne 3rd Floor","city":"Arlington","zip":22201.0,"latitude":38.891143,"longitude":-77.085855,"id":"a621x9e18uu3","address":"2200 Wilson Blvd","state":"VA"},"type":"Feature","geometry":{"type":"Point","coordinates":[-77.085855,38.891143]}}],"is_temporal":false,"author":{"url":"","metadata":"","contact_name":"","contact_address":"","source":"","contact_phone":""},"source":"","pagination":{"sort":null,"start":0,"total":2,"limit":1000000},"state":"complete","tags":"fortiusone","published":"2009-05-21T14:48:35Z","id":12784}