{"type":"FeatureCollection","data_type":"Dataset","url_type":null,"permissions":[{"permissions":{"download":true,"view":true},"group_id":"everyone"}],"classification":null,"title":"7236","count":17,"stream_id":12800,"contributor":{"url":"http://geocommons.com/users/6716","name":"isidorotapia2"},"data_attributes":null,"calculation_params":null,"icon_link":null,"link":"http://geocommons.com/overlays/12800.json","extent":[-6.00181,37.3608,-5.89871,37.3877],"geometry_types":["point"],"unique_name":null,"name":"7236","feature_count":17,"description":"","next_feature":null,"is_raster":false,"short_classification":"Y","stats":{"tam":{"max":7.0,"mean":4.55882352941176,"variance":1.99632352941176,"stdev":1.41291313583382,"min":2.0,"median":4.5},"ent":{"max":976.0,"mean":545.470588235294,"variance":128282.764705882,"stdev":358.16583408511,"min":116.0,"median":378.0},"lat":{"max":37.387699,"mean":37.375756408222,"variance":7.60715026802544e-05,"stdev":0.00872189788292974,"min":37.360821,"median":37.37297},"long":{"max":-5.898714,"mean":-5.95833636505845,"variance":0.000496017446211024,"stdev":0.022271449126876,"min":-6.001813,"median":-5.956649}},"features":[{"properties":{"tam":5.0,"ent":932.0,"id":"a6nmzze4b71c","lat":37.360821,"long":-5.96933},"type":"Feature","geometry":{"type":"Point","coordinates":[-5.96933,37.360821]}},{"properties":{"tam":3.0,"ent":958.0,"id":"a6nmzzhddxlj","lat":37.36299,"long":-5.965329},"type":"Feature","geometry":{"type":"Point","coordinates":[-5.965329,37.36299]}},{"properties":{"tam":6.0,"ent":905.0,"id":"a6nmzzex8nvt","lat":37.366699,"long":-5.95},"type":"Feature","geometry":{"type":"Point","coordinates":[-5.95,37.366699]}},{"properties":{"tam":4.5,"ent":177.0,"id":"a6nmzzlpru5d","lat":37.366964,"long":-5.951251},"type":"Feature","geometry":{"type":"Point","coordinates":[-5.951251,37.366964]}},{"properties":{"tam":4.0,"ent":371.0,"id":"a6nmzz9qvcuo","lat":37.370964,"long":-5.951251},"type":"Feature","geometry":{"type":"Point","coordinates":[-5.951251,37.370964]}},{"properties":{"tam":4.5,"ent":378.0,"id":"a6nmzzpnhwd7","lat":37.372118261979,"long":-5.95782995223999},"type":"Feature","geometry":{"type":"Point","coordinates":[-5.95782995223999,37.372118261979]}},{"properties":{"tam":4.0,"ent":160.0,"id":"a6nmzzk7pt2i","lat":37.372215,"long":-5.958954},"type":"Feature","geometry":{"type":"Point","coordinates":[-5.958954,37.372215]}},{"properties":{"tam":4.0,"ent":937.0,"id":"a6nmzzkvtzo5","lat":37.372599,"long":-5.949121},"type":"Feature","geometry":{"type":"Point","coordinates":[-5.949121,37.372599]}},{"properties":{"tam":2.0,"ent":976.0,"id":"a6nmzzdhl7fy","lat":37.37297,"long":-5.963794},"type":"Feature","geometry":{"type":"Point","coordinates":[-5.963794,37.37297]}},{"properties":{"tam":7.0,"ent":393.0,"id":"a6nmzzfkzao5","lat":37.3761766777954,"long":-5.94804525375366},"type":"Feature","geometry":{"type":"Point","coordinates":[-5.94804525375366,37.3761766777954]}},{"properties":{"tam":5.5,"ent":162.0,"id":"a6nmzzbsxe39","lat":37.38121,"long":-5.956649},"type":"Feature","geometry":{"type":"Point","coordinates":[-5.956649,37.38121]}},{"properties":{"tam":3.0,"ent":971.0,"id":"a6nmzzhazlbt","lat":37.38214,"long":-5.953884},"type":"Feature","geometry":{"type":"Point","coordinates":[-5.953884,37.38214]}},{"properties":{"tam":4.5,"ent":116.0,"id":"a6nmzzbhf2g9","lat":37.38445,"long":-5.959789},"type":"Feature","geometry":{"type":"Point","coordinates":[-5.959789,37.38445]}},{"properties":{"tam":6.0,"ent":357.0,"id":"a6nmzzhzzco8","lat":37.384736,"long":-5.898714},"type":"Feature","geometry":{"type":"Point","coordinates":[-5.898714,37.384736]}},{"properties":{"tam":3.0,"ent":961.0,"id":"a6nmzzaluyjj","lat":37.38541,"long":-5.954174},"type":"Feature","geometry":{"type":"Point","coordinates":[-5.954174,37.38541]}},{"properties":{"tam":7.0,"ent":345.0,"id":"a6nmzz9zkk9v","lat":37.387697,"long":-6.001813},"type":"Feature","geometry":{"type":"Point","coordinates":[-6.001813,37.387697]}},{"properties":{"tam":4.5,"ent":174.0,"id":"a6nmzzbawmya","lat":37.387699,"long":-6.00179},"type":"Feature","geometry":{"type":"Point","coordinates":[-6.00179,37.387699]}}],"is_temporal":false,"author":{"url":"","metadata":"","contact_name":"","contact_address":"","source":"","contact_phone":""},"source":"","pagination":{"sort":null,"start":0,"total":17,"limit":1000000},"state":"complete","tags":"","published":"2014-08-10T15:26:44-04:00","id":12800}