{"type":"FeatureCollection","data_type":"Dataset","url_type":null,"permissions":[{"permissions":{"download":true,"view":true},"group_id":"everyone"}],"classification":null,"title":"gctest1","count":6,"stream_id":128192,"contributor":{"url":"http://geocommons.com/users/11257","name":"tshortho"},"data_attributes":null,"calculation_params":null,"icon_link":null,"link":"http://geocommons.com/overlays/128192.json","extent":[-122.676,30.05,140.383,47.6062],"geometry_types":["point"],"unique_name":null,"name":"gctest1","feature_count":6,"description":"","next_feature":null,"is_raster":false,"short_classification":"Y","stats":{},"features":[{"properties":{"poc 2":"Skagway, USA","vessel":"Seven Seas Navigator","poc 3":"Juneau, USA","poc 4":"Sitka, USA","poc 5":"Seward, USA","destination":"Vancouver, Canada","geo_score":0.786,"id":"a65t1r1ce8up","geo_precision":"zip","poc 1":"Ketchikan, USA"},"type":"Feature","geometry":{"type":"Point","coordinates":[140.3833333,37.2833333]}},{"properties":{"poc 2":"Ulsan, South Korea","vessel":"STELLAR LILAC","poc 3":"Ulsan, South Korea","poc 4":"Jiangyin, China","poc 5":"Zhenjiang, China","destination":"Vancouver, Canada","geo_score":0.733,"id":"a65t1qxerfr8","geo_precision":"zip","poc 1":"Kalama, USA"},"type":"Feature","geometry":{"type":"Point","coordinates":[31.25,30.05]}},{"properties":{"poc 2":"Shanghai, China","vessel":"APL IRIS","poc 3":"Yantian, China","poc 4":"Saigon, Vietnam","poc 5":"Laem Chabang, Thailand","destination":"Vancouver, Canada","geo_score":0.802,"id":"a65t1r46fdrl","geo_precision":"zip","poc 1":"Seattle, USA"},"type":"Feature","geometry":{"type":"Point","coordinates":[121.4580556,31.2222222]}},{"properties":{"poc 2":"Skagway, USA","vessel":"Silver Shadow","poc 3":"Juneau, USA","poc 4":"Sitka, USA","poc 5":"Seward, USA","destination":"Vancouver, Canada","geo_score":0.786,"id":"a65t1qz237p7","geo_precision":"zip","poc 1":"Ketchikan, USA"},"type":"Feature","geometry":{"type":"Point","coordinates":[140.3833333,37.2833333]}},{"properties":{"poc 2":"Portland, USA","vessel":"Amsterdam","poc 3":"Pyeongtaek, South Korea","poc 4":"Osaka, Japan","poc 5":"Tokyo, Japan","destination":"Vancouver, Canada","geo_score":0.818,"id":"a65t1r89ep3s","geo_precision":"zip","poc 1":"Tacoma, USA"},"type":"Feature","geometry":{"type":"Point","coordinates":[-122.6762071,45.5234515]}},{"properties":{"poc 2":"Seattle, USA","vessel":"NORWEGIAN STAR","poc 3":"Prince Rupert, Canada","poc 4":"Skagway, USA","poc 5":"Juneau, USA","destination":"Prince Rupert, Canada","geo_score":0.814,"id":"a65t1rb7bdra","geo_precision":"zip","poc 1":"Ketchikan, USA"},"type":"Feature","geometry":{"type":"Point","coordinates":[-122.3320708,47.6062095]}}],"is_temporal":false,"author":{"url":"","metadata":"","contact_name":"","contact_address":"","source":"","contact_phone":""},"source":"","pagination":{"sort":null,"start":0,"total":6,"limit":1000000},"state":"complete","tags":"","published":"2014-08-13T10:14:39-04:00","id":128192}