{"type":"FeatureCollection","data_type":"Dataset","url_type":null,"permissions":[{"permissions":{"download":true,"view":true},"group_id":"everyone"}],"classification":null,"title":"Extremadura","count":13,"stream_id":12894,"contributor":{"url":"http://geocommons.com/users/6716","name":"isidorotapia2"},"data_attributes":null,"calculation_params":null,"icon_link":null,"link":"http://geocommons.com/overlays/12894.json","extent":[-6.9775,38.4246,-5.3263,40.0291],"geometry_types":["point"],"unique_name":null,"name":"Extremadura","feature_count":13,"description":"","next_feature":null,"is_raster":false,"short_classification":"Y","stats":{"tam":{"max":7.0,"mean":3.76923076923077,"variance":1.15064102564103,"stdev":1.07267936758429,"min":3.0,"median":3.5},"ent":{"max":430.0,"mean":258.692307692308,"variance":7702.39743589743,"stdev":87.7633034696019,"min":132.0,"median":234.0},"lat":{"max":40.02906,"mean":39.0989084615385,"variance":0.220261015647437,"stdev":0.469319737116858,"min":38.42457,"median":38.91703},"long":{"max":-5.3263,"mean":-6.31076923076923,"variance":0.320106920291026,"stdev":0.565779922134946,"min":-6.9775,"median":-6.37965}},"features":[{"properties":{"tam":4.0,"ent":288.0,"id":"a671hss8tc4p","lat":38.42457,"long":-6.4121},"type":"Feature","geometry":{"type":"Point","coordinates":[-6.4121,38.42457]}},{"properties":{"tam":4.0,"ent":234.0,"id":"a671hsm99vnc","lat":38.6827,"long":-6.40367},"type":"Feature","geometry":{"type":"Point","coordinates":[-6.40367,38.6827]}},{"properties":{"tam":3.5,"ent":157.0,"id":"a671hsh7kiru","lat":38.87158,"long":-6.9775},"type":"Feature","geometry":{"type":"Point","coordinates":[-6.9775,38.87158]}},{"properties":{"tam":4.0,"ent":186.0,"id":"a671hsj787n8","lat":38.87483,"long":-6.97262},"type":"Feature","geometry":{"type":"Point","coordinates":[-6.97262,38.87483]}},{"properties":{"tam":3.0,"ent":232.0,"id":"a671hsk4mdnn","lat":38.87831,"long":-6.97034},"type":"Feature","geometry":{"type":"Point","coordinates":[-6.97034,38.87831]}},{"properties":{"tam":4.0,"ent":132.0,"id":"a671hsnrx610","lat":38.87853,"long":-6.96283},"type":"Feature","geometry":{"type":"Point","coordinates":[-6.96283,38.87853]}},{"properties":{"tam":4.0,"ent":237.0,"id":"a671hshcahy4","lat":38.91703,"long":-6.34594},"type":"Feature","geometry":{"type":"Point","coordinates":[-6.34594,38.91703]}},{"properties":{"tam":3.0,"ent":225.0,"id":"a671hspk75lb","lat":38.95551,"long":-5.86148},"type":"Feature","geometry":{"type":"Point","coordinates":[-5.86148,38.95551]}},{"properties":{"tam":3.0,"ent":231.0,"id":"a671hssw98te","lat":38.97328,"long":-5.79475},"type":"Feature","geometry":{"type":"Point","coordinates":[-5.79475,38.97328]}},{"properties":{"tam":7.0,"ent":430.0,"id":"a671hsvmjwyz","lat":39.45094,"long":-5.3263},"type":"Feature","geometry":{"type":"Point","coordinates":[-5.3263,39.45094]}},{"properties":{"tam":3.5,"ent":263.0,"id":"a671hsvqw3n1","lat":39.45752,"long":-6.37965},"type":"Feature","geometry":{"type":"Point","coordinates":[-6.37965,39.45752]}},{"properties":{"tam":3.0,"ent":385.0,"id":"a671hsousy7j","lat":39.89195,"long":-5.54483},"type":"Feature","geometry":{"type":"Point","coordinates":[-5.54483,39.89195]}},{"properties":{"tam":3.0,"ent":363.0,"id":"a671hss3ty9v","lat":40.02906,"long":-6.08799},"type":"Feature","geometry":{"type":"Point","coordinates":[-6.08799,40.02906]}}],"is_temporal":false,"author":{"url":"","metadata":"","contact_name":"","contact_address":"","source":"","contact_phone":""},"source":"","pagination":{"sort":null,"start":0,"total":13,"limit":1000000},"state":"complete","tags":"","published":"2014-08-10T15:34:54-04:00","id":12894}