{"type":"FeatureCollection","data_type":"Dataset","url_type":null,"permissions":[{"permissions":{"download":true,"view":true},"group_id":"everyone"}],"classification":null,"title":"minneapolis_DMA","count":1,"stream_id":129267,"contributor":{"url":"http://geocommons.com/users/28449","name":"williamstentz"},"data_attributes":null,"calculation_params":null,"icon_link":null,"link":"http://geocommons.com/overlays/129267.json","extent":[-94.199,46.0198,-94.199,46.0198],"geometry_types":["point"],"unique_name":null,"name":"minneapolis_DMA","feature_count":1,"description":"","next_feature":null,"is_raster":false,"short_classification":"Y","stats":{"tvperc":{"max":81.9,"min":81.9,"median":81.9},"latitude":{"max":46.0197555,"min":46.0197555,"median":46.0197555},"dma":{"max":613,"min":613,"median":613},"cableperc":{"max":54.9,"min":54.9,"median":54.9},"adsperc":{"max":27.5,"min":27.5,"median":27.5},"longitude":{"max":-94.199023,"min":-94.199023,"median":-94.199023}},"features":[{"properties":{"name":"dma:","tvperc":81.9,"latitude":46.0197555,"dma":613,"cableperc":54.9,"dma1":"Minneapolis-St. Paul, MN","adsperc":27.5,"longitude":-94.199023,"id":"a62gn6i045gw"},"type":"Feature","geometry":{"type":"Point","coordinates":[-94.199023,46.0197555]}}],"is_temporal":false,"author":{"url":null,"metadata":null,"contact_name":null,"contact_address":null,"source":null,"contact_phone":null},"source":null,"pagination":{"sort":null,"start":0,"total":1,"limit":1000000},"state":"complete","tags":"","published":"2014-08-13T11:44:49-04:00","id":129267}