{"type":"FeatureCollection","data_type":"Dataset","url_type":null,"permissions":[{"permissions":{"download":true,"view":true},"group_id":"everyone"}],"classification":null,"title":"7213","count":17,"stream_id":12948,"contributor":{"url":"http://geocommons.com/users/6716","name":"isidorotapia2"},"data_attributes":null,"calculation_params":null,"icon_link":null,"link":"http://geocommons.com/overlays/12948.json","extent":[-5.98618,37.3546,-5.95953,37.3825],"geometry_types":["point"],"unique_name":null,"name":"7213","feature_count":17,"description":"","next_feature":null,"is_raster":false,"short_classification":"Y","stats":{"tam":{"max":9.0,"mean":4.67647058823529,"variance":4.37316176470588,"stdev":2.09121059788484,"min":2.0,"median":4.0},"ent":{"max":1120.0,"mean":569.529411764706,"variance":128189.889705882,"stdev":358.036156981222,"min":6.0,"median":383.0},"lat":{"max":37.382469,"mean":37.3716340152941,"variance":7.65038539487148e-05,"stdev":0.00874664815507717,"min":37.354599,"median":37.37338015},"long":{"max":-5.959525,"mean":-5.97741512870588,"variance":4.17702503466471e-05,"stdev":0.00646299082056033,"min":-5.986175537,"median":-5.9784}},"features":[{"properties":{"tam":4.0,"ent":6.0,"id":"a64occvycbot","lat":37.354599,"long":-5.98142},"type":"Feature","geometry":{"type":"Point","coordinates":[-5.98142,37.354599]}},{"properties":{"tam":9.0,"ent":344.0,"id":"a64occpsnh3z","lat":37.359062,"long":-5.985968},"type":"Feature","geometry":{"type":"Point","coordinates":[-5.985968,37.359062]}},{"properties":{"tam":4.0,"ent":939.0,"id":"a64occw5ol49","lat":37.359558,"long":-5.97809},"type":"Feature","geometry":{"type":"Point","coordinates":[-5.97809,37.359558]}},{"properties":{"tam":5.0,"ent":346.0,"id":"a64occscsjcj","lat":37.36200537,"long":-5.979437828},"type":"Feature","geometry":{"type":"Point","coordinates":[-5.979437828,37.36200537]}},{"properties":{"tam":3.5,"ent":1120.0,"id":"a64occqtq1e6","lat":37.36494,"long":-5.980489},"type":"Feature","geometry":{"type":"Point","coordinates":[-5.980489,37.36494]}},{"properties":{"tam":4.0,"ent":915.0,"id":"a64occnw4aei","lat":37.369695,"long":-5.976894},"type":"Feature","geometry":{"type":"Point","coordinates":[-5.976894,37.369695]}},{"properties":{"tam":3.0,"ent":176.0,"id":"a64occmy1bw8","lat":37.3706176,"long":-5.959525},"type":"Feature","geometry":{"type":"Point","coordinates":[-5.959525,37.3706176]}},{"properties":{"tam":6.0,"ent":340.0,"id":"a64occw0f1s5","lat":37.37251047,"long":-5.974781513},"type":"Feature","geometry":{"type":"Point","coordinates":[-5.974781513,37.37251047]}},{"properties":{"tam":5.0,"ent":365.0,"id":"a64occva7flx","lat":37.37338015,"long":-5.971348286},"type":"Feature","geometry":{"type":"Point","coordinates":[-5.971348286,37.37338015]}},{"properties":{"tam":8.0,"ent":384.0,"id":"a64occw7vv8p","lat":37.37344,"long":-5.98247},"type":"Feature","geometry":{"type":"Point","coordinates":[-5.98247,37.37344]}},{"properties":{"tam":4.5,"ent":383.0,"id":"a64occn9zzir","lat":37.37714862,"long":-5.981240273},"type":"Feature","geometry":{"type":"Point","coordinates":[-5.981240273,37.37714862]}},{"properties":{"tam":8.5,"ent":934.0,"id":"a64occkq43bm","lat":37.378532,"long":-5.972663},"type":"Feature","geometry":{"type":"Point","coordinates":[-5.972663,37.378532]}},{"properties":{"tam":2.0,"ent":979.0,"id":"a64occhrlcb5","lat":37.37876849,"long":-5.981326103},"type":"Feature","geometry":{"type":"Point","coordinates":[-5.981326103,37.37876849]}},{"properties":{"tam":4.0,"ent":221.0,"id":"a64occlb24o1","lat":37.37885375,"long":-5.974459648},"type":"Feature","geometry":{"type":"Point","coordinates":[-5.974459648,37.37885375]}},{"properties":{"tam":4.0,"ent":342.0,"id":"a64occgptlh7","lat":37.37987681,"long":-5.986175537},"type":"Feature","geometry":{"type":"Point","coordinates":[-5.986175537,37.37987681]}},{"properties":{"tam":3.0,"ent":966.0,"id":"a64occrka1ur","lat":37.382322,"long":-5.971369},"type":"Feature","geometry":{"type":"Point","coordinates":[-5.971369,37.382322]}},{"properties":{"tam":2.0,"ent":922.0,"id":"a64occmaxfge","lat":37.382469,"long":-5.9784},"type":"Feature","geometry":{"type":"Point","coordinates":[-5.9784,37.382469]}}],"is_temporal":false,"author":{"url":"","metadata":"","contact_name":"","contact_address":"","source":"","contact_phone":""},"source":"","pagination":{"sort":null,"start":0,"total":17,"limit":1000000},"state":"complete","tags":"","published":"2014-08-10T15:36:33-04:00","id":12948}