{"type":"FeatureCollection","data_type":"Dataset","url_type":null,"permissions":[{"permissions":{"download":true,"view":true},"group_id":"everyone"}],"classification":null,"title":"PUB","count":4,"stream_id":130541,"contributor":{"url":"http://geocommons.com/users/29271","name":"pepmaspla"},"data_attributes":null,"calculation_params":null,"icon_link":null,"link":"http://geocommons.com/overlays/130541.json","extent":[1.09,42.16,2.3,44.9],"geometry_types":["point"],"unique_name":null,"name":"PUB","feature_count":4,"description":"","next_feature":null,"is_raster":false,"short_classification":"Y","stats":{"any":{"max":2011,"mean":2008.25,"variance":9.58333333333333,"stdev":3.09569593683445,"min":2004,"median":2010}},"features":[{"properties":{"any":2010,"autor":"Roque","id":"a62c1qegmyjd"},"type":"Feature","geometry":{"type":"Point","coordinates":[1.09,42.16]}},{"properties":{"any":2008,"autor":"Brusi","id":"a62c1qje5odm"},"type":"Feature","geometry":{"type":"Point","coordinates":[1.29,42.45]}},{"properties":{"any":2004,"autor":"Mencio","id":"a62c1qih0zzh"},"type":"Feature","geometry":{"type":"Point","coordinates":[2.3,43.45]}},{"properties":{"any":2011,"autor":"Mas","id":"a62c1qsp7gas"},"type":"Feature","geometry":{"type":"Point","coordinates":[1.2,44.9]}}],"is_temporal":false,"author":{"url":"","metadata":"","contact_name":"","contact_address":"","source":"","contact_phone":""},"source":"","pagination":{"sort":null,"start":0,"total":4,"limit":1000000},"state":"complete","tags":"","published":"2014-08-12T21:46:09-04:00","id":130541}