{"type":"FeatureCollection","data_type":"Dataset","url_type":null,"permissions":[{"permissions":{"download":true,"edit":true,"view":true},"group_id":"everyone"}],"classification":null,"title":"NK-MDA","count":1,"stream_id":131040,"contributor":{"url":"http://geocommons.com/users/23583","name":"dmorgan"},"data_attributes":null,"calculation_params":null,"icon_link":null,"link":"http://geocommons.com/overlays/131040.json","extent":[126.683,38.6167,126.683,38.6167],"geometry_types":["point"],"unique_name":null,"name":"NK-MDA","feature_count":1,"description":"","next_feature":null,"is_raster":false,"short_classification":"Y","stats":{"radius":{"max":120,"min":120,"median":120},"latitude":{"max":38.616667,"min":38.616667,"median":38.616667},"longitude":{"max":126.683333,"min":126.683333,"median":126.683333}},"features":[{"properties":{"radius":120,"latitude":38.616667,"facility":"Chiha-ri","longitude":126.683333,"id":"a6y3hnmpskae"},"type":"Feature","geometry":{"type":"Point","coordinates":[126.683333,38.616667]}}],"is_temporal":false,"author":{"url":null,"metadata":null,"contact_name":null,"contact_address":null,"source":null,"contact_phone":null},"source":null,"pagination":{"sort":null,"start":0,"total":1,"limit":1000000},"state":"complete","tags":"","published":"2014-08-12T22:24:00-04:00","id":131040}