{"type":"FeatureCollection","data_type":"Dataset","url_type":null,"permissions":[{"permissions":{"download":true,"view":true},"group_id":"everyone"}],"classification":null,"title":"Chicago60643","count":1,"stream_id":131830,"contributor":{"url":"http://geocommons.com/users/29375","name":"cwallace600"},"data_attributes":null,"calculation_params":null,"icon_link":null,"link":"http://geocommons.com/overlays/131830.json","extent":[-87.7013,41.7037,-87.7013,41.7037],"geometry_types":["point"],"unique_name":null,"name":"Chicago60643","feature_count":1,"description":"","next_feature":null,"is_raster":false,"short_classification":"Y","stats":{"mail_zip4":{"max":2017,"min":2017,"median":2017},"location_zip4":{"max":2017,"min":2017,"median":2017}},"features":[{"properties":{"id":"a660x8dg02qc","mh":null,"rs":null,"location_state":"IL","dm":null,"mail_city":"Chicago","mi":null,"pa":null,"wn":null,"mhsa":null,"geo_score":0.915,"mail_zip":"60655","ad":null,"location_zip4":2017,"phone":"(773) 239-2830","services_text1":"Primary Focus: Substance abuse treatment services","tx":"X","gh":null,"services_text2":"Services Provided: Substance abuse treatment","pw":null,"sp":null,"location_zip":"60655","services_text3":"Type of Care: Outpatient","website":null,"mail_state":"IL","mm":null,"nx":null,"services_text4":"Special Programs/Groups: DUI/DWI offenders","ah":null,"mn":null,"cj":null,"dt":null,"gl":null,"hv":null,"ph":null,"op":"X","services_text5":"Forms of Payment Accepted: Self payment","du":"X","sa":"X","pi":null,"services_text6":"Payment Assistance: Sliding fee scale (fee is based on income and other factors)","ss":"X","intake1":null,"location_street1":"10435 South Kedzie Avenue","bu":null,"services_text7":null,"intake2":null,"location_street2":null,"fx":null,"mail_zip4":2017,"rl":null,"bc":null,"mail_street1":"10435 South Kedzie Avenue","name1":"Prevention Classes Inc","location_city":"Chicago","name2":null,"se":null,"co":null,"mail_street2":null,"hh":null,"geo_precision":"range","sf":"X","hotline1":null,"hi":null,"mc":null,"hotline2":null,"md":null,"ar":null,"si":null},"type":"Feature","geometry":{"type":"Point","coordinates":[-87.701262,41.703719]}}],"is_temporal":false,"author":{"url":"","metadata":"","contact_name":"","contact_address":"","source":"","contact_phone":""},"source":"","pagination":{"sort":null,"start":0,"total":1,"limit":1000000},"state":"complete","tags":"addiction,chicago,illinois,treatment","published":"2014-08-12T23:25:34-04:00","id":131830}