{"type":"FeatureCollection","data_type":"Dataset","url_type":null,"permissions":[{"permissions":{"download":true,"view":true},"group_id":"everyone"}],"classification":null,"title":"Passcar","count":6,"stream_id":132682,"contributor":{"url":"http://geocommons.com/users/3995","name":"amazon"},"data_attributes":null,"calculation_params":null,"icon_link":null,"link":"http://geocommons.com/overlays/132682.json","extent":[-77.05,-34.5761,-47.9297,10.5],"geometry_types":["point"],"unique_name":null,"name":"Passcar","feature_count":6,"description":"","next_feature":null,"is_raster":false,"short_classification":"Y","stats":{"million vehicles":{"max":21.9,"mean":7.26666666666667,"variance":56.0426666666667,"stdev":7.48616501732808,"min":1.0,"median":6.1}},"features":[{"properties":{"city":"Brasilia","column_10":null,"column_5":null,"column_11":null,"column_6":null,"column_12":null,"column_7":null,"vehicle type":"Passenger cars","geo_score":1.0,"column_8":null,"country":"Brazil","column_9":null,"million vehicles":21.9,"id":"a7h93gk5df5i","geo_precision":"zip"},"type":"Feature","geometry":{"type":"Point","coordinates":[-47.92972,-15.77972]}},{"properties":{"city":"Buenos Aires","column_10":null,"column_5":null,"column_11":null,"column_6":null,"column_12":null,"column_7":null,"vehicle type":"Passenger cars","geo_score":1.0,"column_8":null,"country":"Argentina","column_9":null,"million vehicles":6.7,"id":"a7h93gbzfy19","geo_precision":"zip"},"type":"Feature","geometry":{"type":"Point","coordinates":[-58.4088134765625,-34.5761256318848]}},{"properties":{"city":"Caracas","column_10":null,"column_5":null,"column_11":null,"column_6":null,"column_12":null,"column_7":null,"vehicle type":"Passenger cars/ Motorcycles","geo_score":1.0,"column_8":null,"country":"Venezuela","column_9":null,"million vehicles":6.1,"id":"a7h93g5jhfcz","geo_precision":"zip"},"type":"Feature","geometry":{"type":"Point","coordinates":[-66.9166667,10.5]}},{"properties":{"city":"bogota","column_10":null,"column_5":null,"column_11":null,"column_6":null,"column_12":null,"column_7":null,"vehicle type":"Passenger cars","geo_score":0.857,"column_8":null,"country":"Colombia","column_9":null,"million vehicles":5.2,"id":"a7h93gfgr0vq","geo_precision":"zip"},"type":"Feature","geometry":{"type":"Point","coordinates":[-74.0833333,4.6]}},{"properties":{"city":"Santiago","column_10":null,"column_5":null,"column_11":null,"column_6":null,"column_12":null,"column_7":null,"vehicle type":"Passenger cars","geo_score":1.0,"column_8":null,"country":"Chile","column_9":null,"million vehicles":2.7,"id":"a7h93gbl6bq8","geo_precision":"zip"},"type":"Feature","geometry":{"type":"Point","coordinates":[-70.5665588378906,-33.4262838490987]}},{"properties":{"city":"Lima","column_10":null,"column_5":null,"column_11":null,"column_6":null,"column_12":null,"column_7":null,"vehicle type":"Passenger cars","geo_score":1.0,"column_8":null,"country":"Peru","column_9":null,"million vehicles":1.0,"id":"a7h93gd31o8y","geo_precision":"zip"},"type":"Feature","geometry":{"type":"Point","coordinates":[-77.05,-12.05]}}],"is_temporal":false,"author":{"url":"","metadata":"","contact_name":"","contact_address":"","source":"","contact_phone":""},"source":"","pagination":{"sort":null,"start":0,"total":6,"limit":1000000},"state":"complete","tags":"","published":"2014-08-13T00:36:28-04:00","id":132682}