{"type":"FeatureCollection","data_type":"Dataset","url_type":null,"permissions":[{"permissions":{"download":true,"view":true},"group_id":"everyone"}],"classification":null,"title":"commercial other","count":6,"stream_id":132681,"contributor":{"url":"http://geocommons.com/users/3995","name":"amazon"},"data_attributes":null,"calculation_params":null,"icon_link":null,"link":"http://geocommons.com/overlays/132681.json","extent":[-77.05,-34.5761,-47.9297,10.5],"geometry_types":["point"],"unique_name":null,"name":"commercial other","feature_count":6,"description":"","next_feature":null,"is_raster":false,"short_classification":"Y","stats":{"million vehicles":{"max":5.06,"mean":1.46,"variance":3.6608,"stdev":1.91332171889622,"min":0.2,"median":0.6}},"features":[{"properties":{"city":"Brasilia","vehicle type":"Commercial / Other","geo_score":1.0,"country":"Brazil","million vehicles":5.06,"id":"0","geo_precision":"zip"},"type":"Feature","geometry":{"type":"Point","coordinates":[-47.92972,-15.77972]}},{"properties":{"city":"Buenos Aires","vehicle type":"Commercial / Other","geo_score":1.0,"country":"Argentina","million vehicles":2.2,"id":"1","geo_precision":"zip"},"type":"Feature","geometry":{"type":"Point","coordinates":[-58.4088134765625,-34.5761256318848]}},{"properties":{"city":"Caracas","vehicle type":"Commercial / Other","geo_score":1.0,"country":"Venezuela","million vehicles":0.3,"id":"2","geo_precision":"zip"},"type":"Feature","geometry":{"type":"Point","coordinates":[-66.9166667,10.5]}},{"properties":{"city":"bogota","vehicle type":"Commercial / Other","geo_score":0.857,"country":"Colombia","million vehicles":0.2,"id":"3","geo_precision":"zip"},"type":"Feature","geometry":{"type":"Point","coordinates":[-74.0833333,4.6]}},{"properties":{"city":"Santiago","vehicle type":"Commercial / Other","geo_score":1.0,"country":"Chile","million vehicles":0.4,"id":"4","geo_precision":"zip"},"type":"Feature","geometry":{"type":"Point","coordinates":[-70.5665588378906,-33.4262838490987]}},{"properties":{"city":"Lima","vehicle type":"Commercial / Other","geo_score":1.0,"country":"Peru","million vehicles":0.6,"id":"5","geo_precision":"zip"},"type":"Feature","geometry":{"type":"Point","coordinates":[-77.05,-12.05]}}],"is_temporal":false,"author":{"url":"","metadata":"","contact_name":"","contact_address":"","source":"","contact_phone":""},"source":"","pagination":{"sort":null,"start":0,"total":6,"limit":1000000},"state":"complete","tags":"","published":"2014-08-13T00:36:27-04:00","id":132681}