{"type":"FeatureCollection","data_type":"Dataset","url_type":null,"permissions":[{"permissions":{"download":true,"view":true},"group_id":"everyone"}],"classification":null,"title":"sot geoiq 2","count":2,"stream_id":140559,"contributor":{"url":"http://geocommons.com/users/30467","name":"markwmccall"},"data_attributes":null,"calculation_params":null,"icon_link":null,"link":"http://geocommons.com/overlays/140559.json","extent":[-98.8667,34.8676,-77.0908,38.7646],"geometry_types":["point"],"unique_name":null,"name":"sot geoiq 2","feature_count":2,"description":"","next_feature":null,"is_raster":false,"short_classification":"Y","stats":{},"features":[{"properties":{"name":"John Doe","city":"cupertino","zip":"95014","geo_score":0.444,"street":"1 infinite circle","id":"0","geo_precision":"city","state":"ca"},"type":"Feature","geometry":{"type":"Point","coordinates":[-98.866738,34.867562]}},{"properties":{"city":"ALEXANDRIA","zip":"22306","street":"3419 SPRING DR","id":"a6886c50yea9","state":"VA"},"type":"Feature","geometry":{"type":"Point","coordinates":[-77.090815,38.764567]}}],"is_temporal":false,"author":{"url":"","metadata":"","contact_name":"","contact_address":"","source":"","contact_phone":""},"source":"","pagination":{"sort":null,"start":0,"total":2,"limit":1000000},"state":"complete","tags":"","published":"2014-08-12T21:48:14-04:00","id":140559}