{"type":"FeatureCollection","data_type":"Dataset","url_type":null,"permissions":[{"permissions":{"download":true,"view":true},"group_id":"everyone"}],"classification":null,"title":"tester","count":2,"stream_id":14110,"contributor":{"url":"http://geocommons.com/users/7445","name":"hannes"},"data_attributes":null,"calculation_params":null,"icon_link":null,"link":"http://geocommons.com/overlays/14110.json","extent":[9.18103,45.4689,11.3545,46.4951],"geometry_types":["point"],"unique_name":null,"name":"tester","feature_count":2,"description":"","next_feature":null,"is_raster":false,"short_classification":"Y","stats":{"latitude":{"max":46.495052,"mean":45.9819985,"variance":0.526447787724503,"stdev":0.725567217922987,"min":45.468945,"median":46.495052},"longitude":{"max":11.354466,"mean":10.267748,"variance":2.361912023048,"stdev":1.53685133407497,"min":9.18103,"median":11.354466},"peso":{"max":100.0,"mean":75.0,"variance":1250.0,"stdev":35.3553390593274,"min":50.0,"median":100.0}},"features":[{"properties":{"latitude":46.495052,"citya":"rome, italy","longitude":11.354466,"id":"a6m2jz2twmgv","cityp":"bolzano, italy","peso":50.0},"type":"Feature","geometry":{"type":"Point","coordinates":[11.354466,46.495052]}},{"properties":{"latitude":45.468945,"citya":"paris, france","longitude":9.18103,"id":"a6m2jz2ek396","cityp":"milan, italy","peso":100.0},"type":"Feature","geometry":{"type":"Point","coordinates":[9.18103,45.468945]}}],"is_temporal":false,"author":{"url":"","metadata":"","contact_name":"","contact_address":"","source":"","contact_phone":""},"source":"","pagination":{"sort":null,"start":0,"total":2,"limit":1000000},"state":"complete","tags":"","published":"2014-08-10T18:00:41-04:00","id":14110}