{"type":"FeatureCollection","data_type":"Dataset","url_type":null,"permissions":[{"permissions":{"download":true,"view":true},"group_id":"everyone"}],"classification":null,"title":"main_tank","count":3,"stream_id":141730,"contributor":{"url":"http://geocommons.com/users/29139","name":"sabyasachi"},"data_attributes":null,"calculation_params":null,"icon_link":null,"link":"http://geocommons.com/overlays/141730.json","extent":[79.0519,10.7728,79.0541,10.7753],"geometry_types":["point"],"unique_name":null,"name":"main_tank","feature_count":3,"description":"","next_feature":null,"is_raster":false,"short_classification":"Y","stats":{"-29.1":{"max":-33.3,"mean":-37.0,"variance":12.67,"stdev":3.55949434611154,"min":-40.4,"median":-37.3},"79.0418527":{"max":79.05414201,"mean":79.0531726966667,"variance":1.25819737373517e-06,"stdev":0.00112169397508196,"min":79.05194405,"median":79.05343203},"1":{"max":1,"mean":1.0,"variance":0.0,"stdev":0.0,"min":1,"median":1},"10.76834163":{"max":10.77534276,"mean":10.7742261566667,"variance":1.65123285303304e-06,"stdev":0.00128500305565124,"min":10.77282161,"median":10.7745141},"4":{"max":6,"mean":4.66666666666667,"variance":1.33333333333333,"stdev":1.15470053837925,"min":4,"median":4}},"features":[{"properties":{"-29.1":-33.3,"79.0418527":79.05194405,"tuesday, june 21, 2011 1:05:17 pm utc":"Tuesday, June 21, 2011 12:09:09 PM UTC","1":1,"10.76834163":10.77282161,"kurkkukolai":"Main Tank","http://sughavazhvu.appspot.com/imageviewer?blobkey=agtzdwdoyxzhemh2dxiscxikymxvyl9zdg9yzri84gkm":"http://sughavazhvu.appspot.com/imageViewer?blobKey=agtzdWdoYXZhemh2dXISCxIKYmxvYl9zdG9yZRjr6QkM","alakkudi":"Alakkudi","id":"a6cr8xj9pql5","4":4},"type":"Feature","geometry":{"type":"Point","coordinates":[79.05194405,10.77282161]}},{"properties":{"-29.1":-37.3,"79.0418527":79.05343203,"tuesday, june 21, 2011 1:05:17 pm utc":"Tuesday, June 21, 2011 12:51:27 PM UTC","1":1,"10.76834163":10.7745141,"kurkkukolai":"Arunthiyar.st","http://sughavazhvu.appspot.com/imageviewer?blobkey=agtzdwdoyxzhemh2dxiscxikymxvyl9zdg9yzri84gkm":"http://sughavazhvu.appspot.com/imageViewer?blobKey=agtzdWdoYXZhemh2dXISCxIKYmxvYl9zdG9yZRjd8QkM","alakkudi":"Alakudi","id":"a6cr8xeqflx5","4":4},"type":"Feature","geometry":{"type":"Point","coordinates":[79.05343203,10.7745141]}},{"properties":{"-29.1":-40.4,"79.0418527":79.05414201,"tuesday, june 21, 2011 1:05:17 pm utc":"Tuesday, June 21, 2011 12:53:05 PM UTC","1":1,"10.76834163":10.77534276,"kurkkukolai":"Vetti.st","http://sughavazhvu.appspot.com/imageviewer?blobkey=agtzdwdoyxzhemh2dxiscxikymxvyl9zdg9yzri84gkm":"http://sughavazhvu.appspot.com/imageViewer?blobKey=agtzdWdoYXZhemh2dXISCxIKYmxvYl9zdG9yZRjl8QkM","alakkudi":"Alakkudi","id":"a6cr8xoiqijj","4":6},"type":"Feature","geometry":{"type":"Point","coordinates":[79.05414201,10.77534276]}}],"is_temporal":false,"author":{"url":"","metadata":"","contact_name":"","contact_address":"","source":"","contact_phone":""},"source":"","pagination":{"sort":null,"start":0,"total":3,"limit":1000000},"state":"complete","tags":"","published":"2014-08-12T23:42:00-04:00","id":141730}