{"type":"FeatureCollection","data_type":"Dataset","url_type":null,"permissions":[{"permissions":{"download":true,"view":true},"group_id":"everyone"}],"classification":null,"title":"CHM ASEAN Reptile Diversity Status","count":9,"stream_id":146691,"contributor":{"url":"http://geocommons.com/users/30728","name":"jeejay70"},"data_attributes":null,"calculation_params":null,"icon_link":null,"link":"http://geocommons.com/overlays/146691.json","extent":[100.786,-0.968432,120.739,21.9198],"geometry_types":["point"],"unique_name":null,"name":"CHM ASEAN Reptile Diversity Status","feature_count":9,"description":"","next_feature":null,"is_raster":false,"short_classification":"Y","stats":{"REPTBD_T":{"max":749.0,"mean":269.222222222222,"variance":48696.6944444445,"stdev":220.673275329036,"min":0.0,"median":274.0},"REPTBD_TH":{"max":28.0,"mean":14.3333333333333,"variance":78.75,"stdev":8.87411967464942,"min":4.0,"median":11.0},"REPTBD_E":{"max":227.0,"mean":63.6666666666667,"variance":6537.0,"stdev":80.8517161227886,"min":0.0,"median":47.0}},"features":[{"properties":{"REPTBD_T":73.0,"REPTBD_TH":4.0,"id":"0","REPTBD_E":0.0},"type":"Feature","geometry":{"type":"Point","coordinates":[114.71545,4.52513]}},{"properties":{"REPTBD_T":749.0,"REPTBD_TH":28.0,"id":"1","REPTBD_E":227.0},"type":"Feature","geometry":{"type":"Point","coordinates":[114.470890812727,-0.9684319207582]}},{"properties":{"REPTBD_T":116.0,"REPTBD_TH":10.0,"id":"2","REPTBD_E":3.0},"type":"Feature","geometry":{"type":"Point","coordinates":[105.101594560108,12.6912373606499]}},{"properties":{"REPTBD_T":0.0,"REPTBD_TH":11.0,"id":"3","REPTBD_E":1.0},"type":"Feature","geometry":{"type":"Point","coordinates":[102.57881791805,19.7357592814081]}},{"properties":{"REPTBD_T":388.0,"REPTBD_TH":21.0,"id":"4","REPTBD_E":82.0},"type":"Feature","geometry":{"type":"Point","coordinates":[102.333967588898,4.29838368032494]}},{"properties":{"REPTBD_T":274.0,"REPTBD_TH":8.0,"id":"5","REPTBD_E":160.0},"type":"Feature","geometry":{"type":"Point","coordinates":[120.73905,15.59305]}},{"properties":{"REPTBD_T":196.0,"REPTBD_TH":4.0,"id":"6","REPTBD_E":1.0},"type":"Feature","geometry":{"type":"Point","coordinates":[103.86416,1.31766]}},{"properties":{"REPTBD_T":341.0,"REPTBD_TH":19.0,"id":"7","REPTBD_E":47.0},"type":"Feature","geometry":{"type":"Point","coordinates":[100.78609263935,15.5090257622746]}},{"properties":{"REPTBD_T":286.0,"REPTBD_TH":24.0,"id":"8","REPTBD_E":52.0},"type":"Feature","geometry":{"type":"Point","coordinates":[105.336756957671,21.9198152854699]}}],"is_temporal":false,"author":{"url":"","metadata":"","contact_name":"","contact_address":"","source":"","contact_phone":""},"source":"","pagination":{"sort":null,"start":0,"total":9,"limit":1000000},"state":"complete","tags":"chm","published":"2014-08-13T08:28:55-04:00","id":146691}