{"type":"FeatureCollection","data_type":"Dataset","url_type":null,"permissions":[{"permissions":{"download":true,"view":true},"group_id":"everyone"}],"classification":null,"title":"geocode_IPG2","count":2,"stream_id":147334,"contributor":{"url":"http://geocommons.com/users/31665","name":"nhall"},"data_attributes":null,"calculation_params":null,"icon_link":null,"link":"http://geocommons.com/overlays/147334.json","extent":[-71.0598,42.3584,-0.125533,51.5084],"geometry_types":["point"],"unique_name":null,"name":"geocode_IPG2","feature_count":2,"description":"","next_feature":null,"is_raster":false,"short_classification":"Y","stats":{},"features":[{"properties":{"city":"London","geo_score":0.857,"country":"England","id":"a6a3ahtuj277","geo_precision":"zip"},"type":"Feature","geometry":{"type":"Point","coordinates":[-0.125532746315002,51.5084152563931]}},{"properties":{"city":"Boston","geo_score":0.857,"country":null,"id":"a6a3ahoi1zj1","geo_precision":"zip"},"type":"Feature","geometry":{"type":"Point","coordinates":[-71.0597732,42.3584308]}}],"is_temporal":false,"author":{"url":"","metadata":null,"contact_name":null,"contact_address":null,"source":null,"contact_phone":null},"source":"","pagination":{"sort":null,"start":0,"total":2,"limit":1000000},"state":"complete","tags":"","published":"2014-08-13T09:15:52-04:00","id":147334}