{"type":"FeatureCollection","data_type":"Dataset","url_type":null,"permissions":[{"permissions":{"download":true,"view":true},"group_id":"everyone"}],"classification":null,"title":"bike_crossing","count":10,"stream_id":147404,"contributor":{"url":"http://geocommons.com/users/26659","name":"openlands"},"data_attributes":null,"calculation_params":null,"icon_link":null,"link":"http://geocommons.com/overlays/147404.json","extent":[-88.4702,42.1829,-88.3675,42.3052],"geometry_types":["point"],"unique_name":null,"name":"bike_crossing","feature_count":10,"description":"","next_feature":null,"is_raster":false,"short_classification":"Y","stats":{"NAME":{"max":9,"mean":5.0,"variance":7.5,"stdev":2.73861278752583,"min":1,"median":5}},"features":[{"properties":{"NAME":9,"id":"a69re4d3cs2h"},"type":"Feature","geometry":{"type":"Point","coordinates":[-88.4225796494589,42.1829269803903]}},{"properties":{"NAME":8,"id":"a69re4gx1tur"},"type":"Feature","geometry":{"type":"Point","coordinates":[-88.4224793449337,42.2045215098454]}},{"properties":{"NAME":7,"id":"a69re4g72o5f"},"type":"Feature","geometry":{"type":"Point","coordinates":[-88.4224874064671,42.2298179738313]}},{"properties":{"NAME":6,"id":"a69re4bn8qvq"},"type":"Feature","geometry":{"type":"Point","coordinates":[-88.4324759714829,42.2545888374676]}},{"properties":{"NAME":5,"id":"a69re4jq65nw"},"type":"Feature","geometry":{"type":"Point","coordinates":[-88.3674956103898,42.2547242191113]}},{"properties":{"NAME":1,"id":"a69re4mxqlg6"},"type":"Feature","geometry":{"type":"Point","coordinates":[-88.4701659197366,42.3051651339614]}},{"properties":{"NAME":2,"id":"a69re4cnh9is"},"type":"Feature","geometry":{"type":"Point","coordinates":[-88.4464271982121,42.297220787472]}},{"properties":{"NAME":3,"id":"a69re4k0t2wc"},"type":"Feature","geometry":{"type":"Point","coordinates":[-88.4331090682863,42.2838135633926]}},{"properties":{"NAME":4,"id":"a69re4lozozs"},"type":"Feature","geometry":{"type":"Point","coordinates":[-88.3865065512137,42.2750108105681]}},{"properties":{"NAME":null,"id":"a69re4983scp"},"type":"Feature","geometry":{"type":"Point","coordinates":[-88.4283360681776,42.2940049635706]}}],"is_temporal":false,"author":{"url":"","metadata":null,"contact_name":null,"contact_address":null,"source":null,"contact_phone":null},"source":"","pagination":{"sort":null,"start":0,"total":10,"limit":1000000},"state":"complete","tags":"","published":"2014-08-13T09:20:24-04:00","id":147404}