{"type":"FeatureCollection","data_type":"Dataset Analysis","url_type":null,"permissions":[{"permissions":{"download":true,"view":true},"group_id":"everyone"}],"classification":null,"title":"Difference between Amphbd T and Amphbd Th from CHM ASEAN Amphibian Diversity Status","count":9,"stream_id":147658,"contributor":{"url":"http://geocommons.com/users/30728","name":"jeejay70"},"data_attributes":null,"calculation_params":{"input":{"columns":[{"column":"AMPHBD_TH","id":"146684"},{"column":"AMPHBD_T","id":"146684"}]},"calculation":"difference"},"icon_link":null,"link":"http://geocommons.com/overlays/147658.json","extent":[100.786,-0.968432,120.739,21.9198],"geometry_types":["point"],"unique_name":null,"name":"Difference between Amphbd T and Amphbd Th from CHM ASEAN Amphibian Diversity Status","feature_count":9,"description":"Dataset derived by applying Refinement module/difference analysis to 'CHM ASEAN Amphibian Diversity Status' ","next_feature":null,"is_raster":false,"short_classification":"Y","stats":{"AMPHBD_E":{"max":143.0,"mean":40.2222222222222,"variance":2657.69444444444,"stdev":51.5528315851268,"min":0.0,"median":12.0},"AMPHBD_TH":{"max":48.0,"mean":17.1111111111111,"variance":381.361111111111,"stdev":19.5284692464901,"min":0.0,"median":4.0},"AMPHBD_T minus AMPHBD_TH":{"max":252.0,"mean":78.0,"variance":7563.5,"stdev":86.9683850603195,"min":-4.0,"median":62.0},"AMPHBD_T":{"max":285.0,"mean":95.1111111111111,"variance":10025.1111111111,"stdev":100.125476833377,"min":0.0,"median":103.0}},"features":[{"properties":{"AMPHBD_E":0.0,"AMPHBD_TH":3.0,"ISO_2":"BN","AMPHBD_T minus AMPHBD_TH":1.0,"ISO_3":"BRN","id":"0","AMPHBD_T":4.0},"type":"Feature","geometry":{"type":"Point","coordinates":[114.71545,4.52513]}},{"properties":{"AMPHBD_E":143.0,"AMPHBD_TH":33.0,"ISO_2":"ID","AMPHBD_T minus AMPHBD_TH":252.0,"ISO_3":"IDN","id":"1","AMPHBD_T":285.0},"type":"Feature","geometry":{"type":"Point","coordinates":[114.470890812727,-0.9684319207582]}},{"properties":{"AMPHBD_E":3.0,"AMPHBD_TH":3.0,"ISO_2":"KH","AMPHBD_T minus AMPHBD_TH":8.0,"ISO_3":"KHM","id":"2","AMPHBD_T":11.0},"type":"Feature","geometry":{"type":"Point","coordinates":[105.101594560108,12.6912373606499]}},{"properties":{"AMPHBD_E":1.0,"AMPHBD_TH":4.0,"ISO_2":"LA","AMPHBD_T minus AMPHBD_TH":-4.0,"ISO_3":"LAO","id":"3","AMPHBD_T":0.0},"type":"Feature","geometry":{"type":"Point","coordinates":[102.57881791805,19.7357592814081]}},{"properties":{"AMPHBD_E":89.0,"AMPHBD_TH":45.0,"ISO_2":"MY","AMPHBD_T minus AMPHBD_TH":155.0,"ISO_3":"MYS","id":"4","AMPHBD_T":200.0},"type":"Feature","geometry":{"type":"Point","coordinates":[102.333967588898,4.29838368032494]}},{"properties":{"AMPHBD_E":77.0,"AMPHBD_TH":48.0,"ISO_2":"PH","AMPHBD_T minus AMPHBD_TH":62.0,"ISO_3":"PHL","id":"5","AMPHBD_T":110.0},"type":"Feature","geometry":{"type":"Point","coordinates":[120.73905,15.59305]}},{"properties":{"AMPHBD_E":0.0,"AMPHBD_TH":0.0,"ISO_2":"SG","AMPHBD_T minus AMPHBD_TH":11.0,"ISO_3":"SGP","id":"6","AMPHBD_T":11.0},"type":"Feature","geometry":{"type":"Point","coordinates":[103.86416,1.31766]}},{"properties":{"AMPHBD_E":12.0,"AMPHBD_TH":3.0,"ISO_2":"TH","AMPHBD_T minus AMPHBD_TH":100.0,"ISO_3":"THA","id":"7","AMPHBD_T":103.0},"type":"Feature","geometry":{"type":"Point","coordinates":[100.78609263935,15.5090257622746]}},{"properties":{"AMPHBD_E":37.0,"AMPHBD_TH":15.0,"ISO_2":"VN","AMPHBD_T minus AMPHBD_TH":117.0,"ISO_3":"VNM","id":"8","AMPHBD_T":132.0},"type":"Feature","geometry":{"type":"Point","coordinates":[105.336756957671,21.9198152854699]}}],"is_temporal":false,"author":{"url":null,"metadata":null,"contact_name":null,"contact_address":null,"source":null,"contact_phone":null},"source":null,"pagination":{"sort":null,"start":0,"total":9,"limit":1000000},"state":"complete","tags":"","published":"2014-08-13T09:31:13-04:00","id":147658}