{"type":"FeatureCollection","data_type":"Dataset","url_type":null,"permissions":[{"permissions":{"download":true,"view":true},"group_id":"everyone"}],"classification":null,"title":"test","count":4,"stream_id":15266,"contributor":{"url":"http://geocommons.com/users/8017","name":"james.hickman"},"data_attributes":null,"calculation_params":null,"icon_link":null,"link":"http://geocommons.com/overlays/15266.json","extent":[-87.0377,31.8987,-67.0377,138.899],"geometry_types":["point"],"unique_name":null,"name":"test","feature_count":4,"description":"","next_feature":null,"is_raster":false,"short_classification":"Y","stats":{"latitude":{"max":138.898748,"mean":67.148748,"variance":2418.91666666667,"stdev":49.1824833316361,"min":31.898748,"median":58.898748},"value":{"max":null,"min":null,"median":null},"longitude":{"max":-67.037684,"mean":-77.037684,"variance":66.6666666666667,"stdev":8.16496580927726,"min":-87.037684,"median":-77.037684}},"features":[{"properties":{"latitude":38.898748,"project title":"DC Project 2","value":"$243,436","description":"Desciption of project","longitude":-87.037684,"id":"a66smqqho5ll"},"type":"Feature","geometry":{"type":"Point","coordinates":[-87.037684,38.898748]}},{"properties":{"latitude":31.898748,"project title":"DC Project","value":"$1,323,435","description":"Desciption of project","longitude":-77.037684,"id":"a66smqz0g5q1"},"type":"Feature","geometry":{"type":"Point","coordinates":[-77.037684,31.898748]}},{"properties":{"latitude":138.898748,"project title":"DC Project 4","value":"$1,623,438","description":"Desciption of project","longitude":-77.037684,"id":"a66smqzsg2uq"},"type":"Feature","geometry":{"type":"Point","coordinates":[-77.037684,138.898748]}},{"properties":{"latitude":58.898748,"project title":"DC Project 3","value":"$6,323,437","description":"Desciption of project","longitude":-67.037684,"id":"a66smqvnbrsc"},"type":"Feature","geometry":{"type":"Point","coordinates":[-67.037684,58.898748]}}],"is_temporal":false,"author":{"url":"","metadata":"","contact_name":"","contact_address":"","source":"","contact_phone":""},"source":"","pagination":{"sort":null,"start":0,"total":4,"limit":1000000},"state":"complete","tags":"","published":"2014-08-10T20:02:55-04:00","id":15266}