{"type":"FeatureCollection","data_type":"Dataset","url_type":null,"permissions":[{"permissions":{"download":true,"view":true},"group_id":"everyone"}],"classification":null,"title":"BayAreaCreeks","count":5,"stream_id":156196,"contributor":{"url":"http://geocommons.com/users/32251","name":"WendiJonassen"},"data_attributes":null,"calculation_params":null,"icon_link":null,"link":"http://geocommons.com/overlays/156196.json","extent":[-122.359,37.24,-119.503,37.9628],"geometry_types":["point"],"unique_name":null,"name":"BayAreaCreeks","feature_count":5,"description":"","next_feature":null,"is_raster":false,"short_classification":"Y","stats":{"latitude":{"max":37.96275534,"mean":37.799965744,"variance":0.0991103815263182,"stdev":0.314818013344723,"min":37.24004895,"median":37.95232509},"longitude":{"max":-119.5032355,"mean":-121.75464964,"variance":1.58685123379399,"stdev":1.25970283551082,"min":-122.3591085,"median":-122.3423966}},"features":[{"properties":{"latitude":37.881944,"four most commonly littered items":"Styrofoam (pieces or pellets) --  61.8%\rConvenience/Fast Food Items --  10.2%\rOther Plastic Products --  9.0%\rBottles (Plastic or Glass)  -- 3.6%","creek":"Wildcat Creek Staging Area","longitude":-122.226111,"id":"a696b4v4tkzu"},"type":"Feature","geometry":{"type":"Point","coordinates":[-122.226111,37.881944]}},{"properties":{"latitude":37.95232509,"four most commonly littered items":"Plastic Products/pieces --  29.8%\rConvenience/Fast Food Items --  21.1%\rPlastic Bags --  10.1%\rStyrofoam (pieces or pellets) -- 9.0%","creek":"Wildcat Creek near Verde Elementary","longitude":-122.3591085,"id":"a696b4otf03s"},"type":"Feature","geometry":{"type":"Point","coordinates":[-122.3591085,37.95232509]}},{"properties":{"latitude":37.24004895,"four most commonly littered items":"Convenience/Fast Food Items -- 22.7%\rCigarette Butts -- 13.6%\rOther Plastic Products -- 13.1%\rPaper and Cardboard--  10.1%","creek":"San Pablo Creek near El Sobrante Library","longitude":-119.5032355,"id":"a696b4os0mjl"},"type":"Feature","geometry":{"type":"Point","coordinates":[-119.5032355,37.24004895]}},{"properties":{"latitude":37.96275534,"four most commonly littered items":"Plastic Bags -- 29.7%\rStyrofoam (pieces or pellets) -- 13.6%\rOther Plastic Products -- 13.1%\rCigarette Butts -- 101%","creek":"San Pablo Creek near Kennedy Plaza","longitude":-122.3423966,"id":"a696b4myf6d7"},"type":"Feature","geometry":{"type":"Point","coordinates":[-122.3423966,37.96275534]}},{"properties":{"latitude":37.96275534,"four most commonly littered items":"Styrofoam-- 32.1%\rOther plastic -- 25.8%\rPaper -- 20.6%\rPlastic bags --  10.8%","creek":"Baxter Creek's remaining problem area","longitude":-122.3423966,"id":"a696b4nm7knw"},"type":"Feature","geometry":{"type":"Point","coordinates":[-122.3423966,37.96275534]}}],"is_temporal":false,"author":{"url":"","metadata":"","contact_name":"","contact_address":"","source":"","contact_phone":""},"source":"","pagination":{"sort":null,"start":0,"total":5,"limit":1000000},"state":"complete","tags":"","published":"2014-08-13T05:49:33-04:00","id":156196}