{"type":"FeatureCollection","data_type":"Dataset Analysis","url_type":null,"permissions":[{"permissions":{"download":true,"edit":true,"view":true},"group_id":"everyone"}],"classification":null,"title":"Intersection of 'Oakland Middle Schools' and 'Oakland High Schools'","count":1,"stream_id":156728,"contributor":{"url":"http://geocommons.com/users/441","name":"adcl"},"data_attributes":null,"calculation_params":{"input":{"columns":[{"id":"156721"},{"id":"156720"}],"merge":"prefer_1"},"calculation":"intersect"},"icon_link":null,"link":"http://geocommons.com/overlays/156728.json","extent":[-122.217,37.7842,-122.217,37.7842],"geometry_types":["point"],"unique_name":null,"name":"Intersection of 'Oakland Middle Schools' and 'Oakland High Schools'","feature_count":1,"description":"Dataset created by the intersection of 1) Oakland Middle Schools and 2) Oakland High Schools","next_feature":null,"is_raster":false,"short_classification":"Y","stats":{"geo_score":{"max":0.721,"min":0.721,"median":0.721}},"features":[{"properties":{"city":"Oakland","zip":"94601","geo_score":0.721,"street address":"2101 35th Avenue","school type":"Middle School","phone":"879-1494","fax":"879-1493","principal":"Elia Bustamante","link":"<a href=\"http://ousdms.ousd.k12.ca.us/ufs\">UNITED FOR SUCCESS</a>","id":"12","school":"UNITED FOR SUCCESS","geo_precision":"range","state":"CA"},"type":"Feature","geometry":{"type":"Point","coordinates":[-122.216797,37.78423]}}],"is_temporal":false,"author":{"url":"","metadata":"","contact_name":"","contact_address":"","source":"","contact_phone":""},"source":"","pagination":{"sort":null,"start":0,"total":1,"limit":1000000},"state":"complete","tags":"int","published":"2014-08-13T06:35:47-04:00","id":156728}