{"type":"FeatureCollection","data_type":"Dataset","url_type":null,"permissions":[{"permissions":{"download":true,"view":true},"group_id":"everyone"}],"classification":null,"title":"mapexperiment","count":3,"stream_id":156718,"contributor":{"url":"http://geocommons.com/users/32444","name":"layceelee13"},"data_attributes":null,"calculation_params":null,"icon_link":null,"link":"http://geocommons.com/overlays/156718.json","extent":[0.05,48.5,25.03,60.15],"geometry_types":["point"],"unique_name":null,"name":"mapexperiment","feature_count":3,"description":"","next_feature":null,"is_raster":false,"short_classification":"Y","stats":{"latitude":{"max":60.15,"mean":53.3233333333333,"variance":36.9406333333333,"stdev":6.07788066132705,"min":48.5,"median":51.32},"longitude":{"max":25.03,"mean":9.09333333333333,"variance":191.638633333333,"stdev":13.843360622816,"min":0.05,"median":2.2}},"features":[{"properties":{"city":"London","timestamp":"01/01/1750 16:00","latitude":51.32,"longitude":0.05,"id":"a6dpi9boupio"},"type":"Feature","geometry":{"type":"Point","coordinates":[0.05,51.32]}},{"properties":{"city":"Paris","timestamp":"02/02/1754 16:00","latitude":48.5,"longitude":2.2,"id":"a6dpi9dlln48"},"type":"Feature","geometry":{"type":"Point","coordinates":[2.2,48.5]}},{"properties":{"city":"Helsinki","timestamp":"03/03/1760 16:00","latitude":60.15,"longitude":25.03,"id":"a6dpi9e7fmdd"},"type":"Feature","geometry":{"type":"Point","coordinates":[25.03,60.15]}}],"is_temporal":false,"author":{"url":"","metadata":"","contact_name":"","contact_address":"","source":"","contact_phone":""},"source":"","pagination":{"sort":null,"start":0,"total":3,"limit":1000000},"state":"complete","tags":"","published":"2014-08-13T06:35:12-04:00","id":156718}