{"type":"FeatureCollection","data_type":"Dataset","url_type":null,"permissions":[{"permissions":{"download":true,"view":true},"group_id":"everyone"}],"classification":null,"title":"SavATree Chicago offices","count":3,"stream_id":157478,"contributor":{"url":"http://geocommons.com/users/16943","name":"mgalvin60@gmail.com"},"data_attributes":null,"calculation_params":null,"icon_link":null,"link":"http://geocommons.com/overlays/157478.json","extent":[-88.213,41.825,-87.8654,42.1584],"geometry_types":["point"],"unique_name":null,"name":"SavATree Chicago offices","feature_count":3,"description":"","next_feature":null,"is_raster":false,"short_classification":"Y","stats":{},"features":[{"properties":{"city":"Northbrook","name":"Northbrook IL","zip":"60062","geo_score":1.0,"id":"a65si3051twt","geo_precision":"range","address":"3520 Commercial Avenue","state":"IL"},"type":"Feature","geometry":{"type":"Point","coordinates":[-87.865386,42.146572]}},{"properties":{"city":"Palatine","name":"Barrington IL","zip":"60074","geo_score":1.0,"id":"a65si3fjpfmb","geo_precision":"range","address":"20278 North Rand Road","state":"IL"},"type":"Feature","geometry":{"type":"Point","coordinates":[-88.045358,42.158393]}},{"properties":{"city":"Warrenville","name":"Warrenville IL","zip":"60555","geo_score":0.641,"id":"a65si3dldjrt","geo_precision":"street","address":"30W210 Calumet Avenue West","state":"IL"},"type":"Feature","geometry":{"type":"Point","coordinates":[-88.212949,41.82495]}}],"is_temporal":false,"author":{"url":"","metadata":"","contact_name":"","contact_address":"","source":"","contact_phone":""},"source":"","pagination":{"sort":null,"start":0,"total":3,"limit":1000000},"state":"complete","tags":"","published":"2014-08-13T07:53:35-04:00","id":157478}