{"type":"FeatureCollection","data_type":"Dataset","url_type":null,"permissions":[{"permissions":{"download":true,"view":true},"group_id":"everyone"}],"classification":null,"title":"mm_ramsarpoints","count":1,"stream_id":158049,"contributor":{"url":"http://geocommons.com/users/30728","name":"jeejay70"},"data_attributes":null,"calculation_params":null,"icon_link":null,"link":"http://geocommons.com/overlays/158049.json","extent":[96.6167,17.55,96.6167,17.55],"geometry_types":["point"],"unique_name":null,"name":"mm_ramsarpoints","feature_count":1,"description":"","next_feature":null,"is_raster":false,"short_classification":"Y","stats":{"LON":{"max":96.6167,"min":96.6167,"median":96.6167},"LAT":{"max":17.55,"min":17.55,"median":17.55}},"features":[{"properties":{"LON":96.6167,"SITENAME":"Moyingyi Wetland Wildlife Sanctuary","ISO3":"MMR","id":"0","LAT":17.55},"type":"Feature","geometry":{"type":"Point","coordinates":[96.6167,17.55]}}],"is_temporal":false,"author":{"url":"","metadata":null,"contact_name":null,"contact_address":null,"source":null,"contact_phone":null},"source":"","pagination":{"sort":null,"start":0,"total":1,"limit":1000000},"state":"complete","tags":"","published":"2014-08-13T08:39:22-04:00","id":158049}