{"type":"FeatureCollection","data_type":"Dataset","url_type":null,"permissions":[{"permissions":{"download":true,"edit":true,"view":true},"group_id":30838},{"permissions":{"download":true,"view":true},"group_id":"everyone"}],"classification":null,"title":"la ahp2009","count":1,"stream_id":158120,"contributor":{"url":"http://geocommons.com/users/30728","name":"jeejay70"},"data_attributes":null,"calculation_params":null,"icon_link":null,"link":"http://geocommons.com/overlays/158120.json","extent":[101.247,20.9036,101.247,20.9036],"geometry_types":["point"],"unique_name":null,"name":"la ahp2009","feature_count":1,"description":"","next_feature":null,"is_raster":false,"short_classification":"Y","stats":{"NOTES":{"max":"2003/12/01 00:00:00 -0500","min":"2003/12/01 00:00:00 -0500","median":"2003/12/01 00:00:00 -0500"},"STATUS_YR":{"max":2003,"min":2003,"median":2003},"DOC_AREA_H":{"max":222400.0,"min":222400.0,"median":222400.0}},"features":[{"properties":{"NOTES":{"end_time":"2003/12/02 00:00:00 -0500","original":"Declared by Member States of the South East Asian Nations (ASEAN) in December 2003.","granularity":"day","time":"2003/12/01 00:00:00 -0500"},"ISO3":"LAO","COUNTRY":"Lao PDR","STATUS_YR":2003,"DOC_AREA_H":222400.0,"id":"0","SOURCE":"Latest Info: ASEAN Declaration on Heritage Parks and Reserves, Yangon Myanmar, 18/12/2003 &amp; ASEAN Heritage Park list (see doc link), accessed 29/07/2005","PAGE_URL":"<a href=\"http://bim.aseanbiodiversity.org/biss/initiatives/pa/ahp/ahpteaser.php?ahp=7\">View Profile</a>","NAME_ENG":"Nam Ha National Biodiversity Conservation Area"},"type":"Feature","geometry":{"type":"Point","coordinates":[101.24707,20.90363]}}],"is_temporal":true,"author":{"url":"","metadata":"","contact_name":"","contact_address":"","source":"","contact_phone":""},"source":"","pagination":{"sort":null,"start":0,"total":1,"limit":1000000},"state":"complete","tags":"","published":"2014-08-13T08:44:36-04:00","id":158120}