{"type":"FeatureCollection","data_type":"Dataset","url_type":null,"permissions":[{"permissions":{"download":true,"view":true},"group_id":"everyone"}],"classification":null,"title":"Vashi-EIG point","count":3,"stream_id":158667,"contributor":{"url":"http://geocommons.com/users/33359","name":"rusky12us"},"data_attributes":null,"calculation_params":null,"icon_link":null,"link":"http://geocommons.com/overlays/158667.json","extent":[72.8736,19.0389,73.0318,19.0699],"geometry_types":["point"],"unique_name":null,"name":"Vashi-EIG point","feature_count":3,"description":"","next_feature":null,"is_raster":false,"short_classification":"Y","stats":{},"features":[{"properties":{"NAME":null,"id":"a665g36jjzga"},"type":"Feature","geometry":{"type":"Point","coordinates":[72.87359,19.069948]}},{"properties":{"NAME":null,"id":"a665g3gz0k6c"},"type":"Feature","geometry":{"type":"Point","coordinates":[73.031214,19.039391]}},{"properties":{"NAME":null,"id":"a665g3bzwf85"},"type":"Feature","geometry":{"type":"Point","coordinates":[73.031778,19.038947]}}],"is_temporal":false,"author":{"url":"","metadata":"","contact_name":"","contact_address":"","source":"","contact_phone":""},"source":"","pagination":{"sort":null,"start":0,"total":3,"limit":1000000},"state":"complete","tags":"","published":"2014-08-13T09:45:01-04:00","id":158667}