{"type":"FeatureCollection","data_type":"Dataset","url_type":null,"permissions":[{"permissions":{"download":true,"view":true},"group_id":"everyone"}],"classification":null,"title":"Sports","count":4,"stream_id":161369,"contributor":{"url":"http://geocommons.com/users/33606","name":"Mission Local Education"},"data_attributes":null,"calculation_params":null,"icon_link":null,"link":"http://geocommons.com/overlays/161369.json","extent":[-122.424,37.7573,-122.407,37.7639],"geometry_types":["point"],"unique_name":null,"name":"Sports","feature_count":4,"description":"","next_feature":null,"is_raster":false,"short_classification":"Y","stats":{},"features":[{"properties":{"description":"San Francisco Rec and Parks offers numerous after school programs involving arts and sports for youth of all ages. Check their current seasonal schedule for up-to-date classes.","categories":"elementary school, middle school, high school, arts, sports, accepts volunteers","telephone #":"415-695-5013","organization":"Mission Recreation Center","web site":"www.sfrecpark.org","id":"0","address":"745 Treat, San Francisco, CA 94110"},"type":"Feature","geometry":{"type":"Point","coordinates":[-122.413517,37.758222]}},{"properties":{"description":"Like any other Boys &amp; Girls Club, the Mission branch offers a wealth of activities. Membership is open to kids 6-18 and costs $10 for the year. The club is open Monday-Friday after school and in the evening.","categories":"elementary school, middle school, high school, tutoring, arts, sports, leadership/empowerment, free/low cost, accepts volunteers","telephone #":"415-400-8911","organization":"Boys and Girls Club, Mission","web site":"www.kidsclub.org/programs/find-a-club/mission-clubhouse/","id":"1","address":"901 Alabama Street\rSan Francisco, CA 94110"},"type":"Feature","geometry":{"type":"Point","coordinates":[-122.411386,37.757335]}},{"properties":{"description":"Like any other Boys &amp; Girls Club, the Columbia Park branch offers a wealth of activities. Membership is open to kids 6-18 and costs $10 for the year. The club is open Monday-Friday after school and in the evening.","categories":"elementary school, middle school, high school, tutoring, arts, sports, leadership/empowerment, free/low cost, accepts volunteers","telephone #":"415-983-3901","organization":"Boys and Girls Club, Columbia Park","web site":"www.kidsclub.org/programs/find-a-club/columbia-park-clubhouse","id":"2","address":"450 Guerrero St\rSan Francisco, CA 94110"},"type":"Feature","geometry":{"type":"Point","coordinates":[-122.424011,37.763814]}},{"properties":{"description":"Horizons offers a broad range of programs and services, including music and employment programs, that are designed to meet the diverse needs of youth.","categories":"middle school, high school, arts, sports, health/wellness, counseling, leadership/empowerment, tutoring/mentoring","telephone #":"415-487-6700","organization":"Horizons Unlimited","web site":"www.horizons-sf.org","id":"3","address":"440 Potrero Ave San Francisco, CA 94110"},"type":"Feature","geometry":{"type":"Point","coordinates":[-122.407398,37.763942]}}],"is_temporal":false,"author":{"url":"","metadata":"","contact_name":"","contact_address":"","source":"","contact_phone":""},"source":"","pagination":{"sort":null,"start":0,"total":4,"limit":1000000},"state":"complete","tags":"","published":"2014-08-12T23:15:20-04:00","id":161369}