{"type":"FeatureCollection","data_type":"Dataset","url_type":null,"permissions":[{"permissions":{"download":true,"view":true},"group_id":"everyone"}],"classification":null,"title":"BALE","count":1,"stream_id":162967,"contributor":{"url":"http://geocommons.com/users/33861","name":"Crossley"},"data_attributes":null,"calculation_params":null,"icon_link":null,"link":"http://geocommons.com/overlays/162967.json","extent":[-2.61204,9.09362,-2.61204,9.09362],"geometry_types":["point"],"unique_name":null,"name":"BALE","feature_count":1,"description":"","next_feature":null,"is_raster":false,"short_classification":"Y","stats":{},"features":[{"properties":{"name":"BALE","description":"26-JUN-11 12:15:07PM","id":"0"},"type":"Feature","geometry":{"type":"Point","coordinates":[-2.61204330615972,9.09361993605296]}}],"is_temporal":false,"author":{"url":"","metadata":null,"contact_name":null,"contact_address":null,"source":null,"contact_phone":null},"source":"","pagination":{"sort":null,"start":0,"total":1,"limit":1000000},"state":"complete","tags":"","published":"2014-08-13T01:34:42-04:00","id":162967}