{"type":"FeatureCollection","data_type":"Dataset","url_type":null,"permissions":[{"permissions":{"download":true,"view":true},"group_id":"everyone"}],"classification":null,"title":"hello","count":1,"stream_id":163235,"contributor":{"url":"http://geocommons.com/users/33959","name":"juliette"},"data_attributes":null,"calculation_params":null,"icon_link":null,"link":"http://geocommons.com/overlays/163235.json","extent":[18.0294,46.8814,18.0294,46.8814],"geometry_types":["point"],"unique_name":null,"name":"hello","feature_count":1,"description":"","next_feature":null,"is_raster":false,"short_classification":"Y","stats":{},"features":[{"properties":{"name":"Balaton lake","id":"0"},"type":"Feature","geometry":{"type":"Point","coordinates":[18.0294246014925,46.8813960582905]}}],"is_temporal":false,"author":{"url":"","metadata":null,"contact_name":null,"contact_address":null,"source":null,"contact_phone":null},"source":"","pagination":{"sort":null,"start":0,"total":1,"limit":1000000},"state":"complete","tags":"","published":"2014-08-13T01:59:55-04:00","id":163235}