{"type":"FeatureCollection","data_type":"Dataset","url_type":null,"permissions":[{"permissions":{"download":true,"view":true},"group_id":"everyone"}],"classification":null,"title":"scitanie-201110","count":10,"stream_id":163567,"contributor":{"url":"http://geocommons.com/users/34018","name":"cyklokoalicia"},"data_attributes":null,"calculation_params":null,"icon_link":null,"link":"http://geocommons.com/overlays/163567.json","extent":[17.0754,48.1397,17.1469,48.1582],"geometry_types":["point"],"unique_name":null,"name":"scitanie-201110","feature_count":10,"description":"cycling coalition bratislava october 2011","next_feature":null,"is_raster":false,"short_classification":"Y","stats":{"number":{"max":233,"mean":114.9,"variance":2711.43333333333,"stdev":52.0714253053758,"min":57,"median":119},"lat":{"max":48.158221,"mean":48.1468816,"variance":5.38990204888803e-05,"stdev":0.00734159522780167,"min":48.139659,"median":48.144671},"long":{"max":17.146852,"mean":17.1193663,"variance":0.000375510562899988,"stdev":0.019378094924424,"min":17.075412,"median":17.125646}},"features":[{"properties":{"number":57,"lokalita":"racianske","id":"a62oud7aklhh","lat":48.157612,"long":17.119938},"type":"Feature","geometry":{"type":"Point","coordinates":[17.119938,48.157612]}},{"properties":{"number":61,"lokalita":"trnavske","id":"a62oud9ww5zu","lat":48.158221,"long":17.127802},"type":"Feature","geometry":{"type":"Point","coordinates":[17.127802,48.158221]}},{"properties":{"number":70,"lokalita":"dulovo","id":"a62oudbmuwjy","lat":48.149395,"long":17.134293},"type":"Feature","geometry":{"type":"Point","coordinates":[17.134293,48.149395]}},{"properties":{"number":91,"lokalita":"karadzicova","id":"a62oudg4ey6d","lat":48.153819,"long":17.125646},"type":"Feature","geometry":{"type":"Point","coordinates":[17.125646,48.153819]}},{"properties":{"number":132,"lokalita":"pristavny","id":"a62ouda6i8vd","lat":48.140404,"long":17.146852},"type":"Feature","geometry":{"type":"Point","coordinates":[17.146852,48.140404]}},{"properties":{"number":123,"lokalita":"apollo","id":"a62oudhm4mv7","lat":48.140304,"long":17.129096},"type":"Feature","geometry":{"type":"Point","coordinates":[17.129096,48.140304]}},{"properties":{"number":113,"lokalita":"stary","id":"a62oud84pilz","lat":48.140977,"long":17.11672},"type":"Feature","geometry":{"type":"Point","coordinates":[17.11672,48.140977]}},{"properties":{"number":233,"lokalita":"novy","id":"a62oudbozibj","lat":48.139659,"long":17.104489},"type":"Feature","geometry":{"type":"Point","coordinates":[17.104489,48.139659]}},{"properties":{"number":150,"lokalita":"lafranconi","id":"a62ouddzb701","lat":48.143754,"long":17.075412},"type":"Feature","geometry":{"type":"Point","coordinates":[17.075412,48.143754]}},{"properties":{"number":119,"lokalita":"kamenne","id":"a62oudj42hsg","lat":48.144671,"long":17.113415},"type":"Feature","geometry":{"type":"Point","coordinates":[17.113415,48.144671]}}],"is_temporal":false,"author":{"url":"","metadata":"","contact_name":"","contact_address":"","source":"","contact_phone":""},"source":"","pagination":{"sort":null,"start":0,"total":10,"limit":1000000},"state":"complete","tags":"cycling,cyklokoalicia","published":"2011-10-06T10:28:22Z","id":163567}