{"type":"FeatureCollection","data_type":"Dataset","url_type":null,"permissions":[{"permissions":{"download":true,"view":true},"group_id":"everyone"}],"classification":null,"title":"kml","count":3,"stream_id":165766,"contributor":{"url":"http://geocommons.com/users/34282","name":"rabrageeta"},"data_attributes":null,"calculation_params":null,"icon_link":null,"link":"http://geocommons.com/overlays/165766.json","extent":[-0.010017,51.481,-0.003747,51.4828],"geometry_types":["point"],"unique_name":null,"name":"kml","feature_count":3,"description":"","next_feature":null,"is_raster":false,"short_classification":"Y","stats":{},"features":[{"properties":{"name":"The National Maritime Museum","description":"\r\n\t\t\t\tPark Row, Greenwich, London SE10 9NF \r\n\t\t\t\t<img src=\"http://farm1.static.flickr.com/64/219245600_c55558fa2d_m.jpg\" alt=\"National Maritime Museum. From Flickr (by Denisol)\" title=\"National Maritime Museum. From Flickr (by Denisol)\">Park Row, Greenwich, London SE10 9NF. <a href=\"http://www.nmm.ac.uk/\">Visit website</a>\r\n\t\t\t","id":"0"},"type":"Feature","geometry":{"type":"Point","coordinates":[-0.003747,51.481154]}},{"properties":{"name":"St. Alfege church","description":"\r\n\t\t\tGreenwich Church Street, Greenwich, London SE10 9BJ.\r\n\t\t\t\t<img src=\"http://farm1.static.flickr.com/66/227672764_65cd5a9530_m.jpg\" alt=\"St. Alfege. From Flickr (by Simon Crubellier)\" title=\"St. Alfege. From Flickr (by Simon Crubellier)\"><a href=\"http://st-alfege.org/\">Visit website</a>\r\n\t\t\t","id":"1"},"type":"Feature","geometry":{"type":"Point","coordinates":[-0.010017,51.481045]}},{"properties":{"name":"The Cutty Sark","description":"\r\n\t\t\t\t<img src=\"http://farm1.static.flickr.com/35/70564673_b012dfbfd1_m.jpg\" alt=\"Cutty Sark (pre-fire). From Flickr (by PG63)\" title=\"Cutty Sark (pre-fire). From Flickr (by PG63)\"><a href=\"http://www.cuttysark.org\">Visit website</a>\r\n\t\t\t","id":"2"},"type":"Feature","geometry":{"type":"Point","coordinates":[-0.00622272491455078,51.4827993702064]}}],"is_temporal":false,"author":{"url":"","metadata":null,"contact_name":null,"contact_address":null,"source":null,"contact_phone":null},"source":"","pagination":{"sort":null,"start":0,"total":3,"limit":1000000},"state":"complete","tags":"","published":"2014-08-13T05:34:16-04:00","id":165766}