{"type":"FeatureCollection","data_type":"Dataset","url_type":null,"permissions":[{"permissions":{"download":true,"view":true},"group_id":"everyone"}],"classification":null,"title":"Trend of Elephant lose in Africa","count":7,"stream_id":16913,"contributor":{"url":"http://geocommons.com/users/8989","name":"tibsal"},"data_attributes":null,"calculation_params":null,"icon_link":null,"link":"http://geocommons.com/overlays/16913.json","extent":[15.8005,2.07079,15.8005,2.07079],"geometry_types":["point"],"unique_name":null,"name":"Trend of Elephant lose in Africa","feature_count":7,"description":"interested","next_feature":null,"is_raster":false,"short_classification":"Y","stats":{"No":{"max":5000000.0,"mean":1347571.42857143,"variance":2673314952380.95,"stdev":1635027.50814197,"min":487000.0,"median":652000.0},"Latitude":{"max":2.07079,"mean":2.07079,"variance":0.0,"stdev":0.0,"min":2.07079,"median":2.07079},"year ":{"max":1998.0,"mean":1980.85714285714,"variance":551.809523809524,"stdev":23.490626296664,"min":1930.0,"median":1989.0},"Longtude":{"max":15.80048,"mean":15.80048,"variance":1.47254035641256e-29,"stdev":3.83736935466545e-15,"min":15.80048,"median":15.80048}},"features":[{"properties":{"No":5000000.0,"Latitude":2.07079,"year ":1930.0,"Longtude":15.80048,"id":"a64mv723j0z0"},"type":"Feature","geometry":{"type":"Point","coordinates":[15.80048,2.07079]}},{"properties":{"No":1341000.0,"Latitude":2.07079,"year ":1976.0,"Longtude":15.80048,"id":"a64mv6sqqnh7"},"type":"Feature","geometry":{"type":"Point","coordinates":[15.80048,2.07079]}},{"properties":{"No":764000.0,"Latitude":2.07079,"year ":1987.0,"Longtude":15.80048,"id":"a64mv6qwt6d6"},"type":"Feature","geometry":{"type":"Point","coordinates":[15.80048,2.07079]}},{"properties":{"No":609000.0,"Latitude":2.07079,"year ":1989.0,"Longtude":15.80048,"id":"a64mv71l48gh"},"type":"Feature","geometry":{"type":"Point","coordinates":[15.80048,2.07079]}},{"properties":{"No":652000.0,"Latitude":2.07079,"year ":1991.0,"Longtude":15.80048,"id":"a64mv6sqden1"},"type":"Feature","geometry":{"type":"Point","coordinates":[15.80048,2.07079]}},{"properties":{"No":580000.0,"Latitude":2.07079,"year ":1995.0,"Longtude":15.80048,"id":"a64mv6tukfw0"},"type":"Feature","geometry":{"type":"Point","coordinates":[15.80048,2.07079]}},{"properties":{"No":487000.0,"Latitude":2.07079,"year ":1998.0,"Longtude":15.80048,"id":"a64mv6we10ou"},"type":"Feature","geometry":{"type":"Point","coordinates":[15.80048,2.07079]}}],"is_temporal":false,"author":{"url":"","metadata":"http://finder.geocommons.com/overlays/16913/edit","contact_name":"tibebu salehu","contact_address":"CEU, Depoartment of Environmental science and policy","source":"Geocommons","contact_phone":"+36 588 3641"},"source":"","pagination":{"sort":null,"start":0,"total":7,"limit":1000000},"state":"complete","tags":"elephant","published":"2009-10-11T12:00:00Z","id":16913}