{"type":"FeatureCollection","data_type":"Dataset","url_type":null,"permissions":[{"permissions":{"download":true,"view":true},"group_id":"everyone"}],"classification":null,"title":"geo test","count":4,"stream_id":169578,"contributor":{"url":"http://geocommons.com/users/34770","name":"vitorlopes"},"data_attributes":null,"calculation_params":null,"icon_link":null,"link":"http://geocommons.com/overlays/169578.json","extent":[-87.3804,32.4392,-87.3804,32.4392],"geometry_types":["point"],"unique_name":null,"name":"geo test","feature_count":4,"description":"","next_feature":null,"is_raster":false,"short_classification":"Y","stats":{},"features":[{"properties":{"city":"Brasilia","zip":"71720023","geo_score":0.679,"country":"Brazil","id":"a6k1dk7md96a","geo_precision":"range","address":"3 Av. Bloco 1780 casa 23","state":"DF"},"type":"Feature","geometry":{"type":"Point","coordinates":[-87.380384,32.439222]}},{"properties":{"city":"Brasilia","zip":"71320023","geo_score":0.679,"country":"Brazil","id":"a6k1dk7wqsgg","geo_precision":"range","address":"3 Av. Bloco 1680 casa 23","state":"DF"},"type":"Feature","geometry":{"type":"Point","coordinates":[-87.380384,32.439222]}},{"properties":{"city":"Brasilia","zip":"71220023","geo_score":0.679,"country":"Brazil","id":"a6k1dklwb1gd","geo_precision":"range","address":"3 Av. Bloco 1580 casa 23","state":"DF"},"type":"Feature","geometry":{"type":"Point","coordinates":[-87.380384,32.439222]}},{"properties":{"city":"Brasilia","zip":"71110023","geo_score":0.679,"country":"Brazil","id":"a6k1dkkbs0i0","geo_precision":"range","address":"3 Av. Bloco 1280 casa 23","state":"DF"},"type":"Feature","geometry":{"type":"Point","coordinates":[-87.380384,32.439222]}}],"is_temporal":false,"author":{"url":"","metadata":"","contact_name":"","contact_address":"","source":"","contact_phone":""},"source":"","pagination":{"sort":null,"start":0,"total":4,"limit":1000000},"state":"complete","tags":"","published":"2014-08-13T10:59:27-04:00","id":169578}