{"type":"FeatureCollection","data_type":"Dataset","url_type":null,"permissions":[{"permissions":{"download":true,"view":true},"group_id":"everyone"}],"classification":null,"title":"GIS","count":6,"stream_id":169946,"contributor":{"url":"http://geocommons.com/users/34997","name":"snavarro"},"data_attributes":null,"calculation_params":null,"icon_link":null,"link":"http://geocommons.com/overlays/169946.json","extent":[-117.396,33.7529,-116.056,33.9534],"geometry_types":["point"],"unique_name":null,"name":"GIS","feature_count":6,"description":"","next_feature":null,"is_raster":false,"short_classification":"Y","stats":{},"features":[{"properties":{"city":"Riverside","industry":"Medical","geo_score":0.857,"id":"a6be58ceyevy","geo_precision":"city","school":"UC Riverside","state":"CA"},"type":"Feature","geometry":{"type":"Point","coordinates":[-117.396156,33.953349]}},{"properties":{"city":"Temecula","industry":"Education","geo_score":0.857,"id":"a6be58q72trd","geo_precision":"city","school":"University of Redlands","state":"CA"},"type":"Feature","geometry":{"type":"Point","coordinates":[-116.055617,33.752886]}},{"properties":{"city":"Riverside","industry":"Manufacturing","geo_score":0.857,"id":"a6be58dmw08g","geo_precision":"city","school":"UC Riverside","state":"CA"},"type":"Feature","geometry":{"type":"Point","coordinates":[-117.396156,33.953349]}},{"properties":{"city":"Menifee","industry":"Retail","geo_score":0.857,"id":"a6be58n7o6re","geo_precision":"city","school":"Mt San Jacinto","state":"CA"},"type":"Feature","geometry":{"type":"Point","coordinates":[-116.055617,33.752886]}},{"properties":{"city":"Temecula","industry":"Banking","geo_score":0.857,"id":"a6be58lgfu3y","geo_precision":"city","school":"University of Redlands","state":"CA"},"type":"Feature","geometry":{"type":"Point","coordinates":[-116.055617,33.752886]}},{"properties":{"city":"Temecula","industry":"Real Estate","geo_score":0.857,"id":"a6be58gswgyi","geo_precision":"city","school":"Mt San Jacinto","state":"CA"},"type":"Feature","geometry":{"type":"Point","coordinates":[-116.055617,33.752886]}}],"is_temporal":false,"author":{"url":"","metadata":"","contact_name":"","contact_address":"","source":"","contact_phone":""},"source":"","pagination":{"sort":null,"start":0,"total":6,"limit":1000000},"state":"complete","tags":"","published":"2014-08-13T11:27:31-04:00","id":169946}