{"type":"FeatureCollection","data_type":"Dataset","url_type":null,"permissions":[{"permissions":{"download":true,"view":true},"group_id":"everyone"}],"classification":null,"title":"857","count":1,"stream_id":17156,"contributor":{"url":"http://geocommons.com/users/9206","name":"Zeppen"},"data_attributes":null,"calculation_params":null,"icon_link":null,"link":"http://geocommons.com/overlays/17156.json","extent":[-86.013,34.028,-86.013,34.028],"geometry_types":["point"],"unique_name":null,"name":"857","feature_count":1,"description":"857","next_feature":null,"is_raster":false,"short_classification":"Y","stats":{"geo_score":{"max":0.488,"min":0.488,"median":0.488}},"features":[{"properties":{"address\tcity\tstate\tzipcode\tname\turl\tcolor\timage\tkundnr\tpoint\truttnr\tlatitud\tlongitud\tbg_lat\tbg_long":"1600 Pennsylvania Avenue NW\tWashington\tDC\t20500\tThe White House\thttp://www.whitehouse.gov/\tFF0000\thttp://www.batchgeocode.com/images/whitehouse.jpg\tkundnr\tpoint\truttnr\tlatitud\tlongitud\t\t\t\t\t\t\t\t\t\t\t\t\t\t\t\t\t\t\t\t\t\t38.89859\t-77.035971","geo_score":0.488,"id":"a6oqxexg9mgs","geo_precision":"street"},"type":"Feature","geometry":{"type":"Point","coordinates":[-86.012971,34.027952]}}],"is_temporal":false,"author":{"url":"","metadata":"","contact_name":"","contact_address":"","source":"","contact_phone":""},"source":"","pagination":{"sort":null,"start":0,"total":1,"limit":1000000},"state":"complete","tags":"857","published":"2010-10-19T12:00:00Z","id":17156}