{"type":"FeatureCollection","data_type":"Dataset","url_type":null,"permissions":[{"permissions":{"download":true,"view":true},"group_id":"everyone"}],"classification":null,"title":"ASEAN-CMS","count":1,"stream_id":174190,"contributor":{"url":"http://geocommons.com/users/30728","name":"jeejay70"},"data_attributes":null,"calculation_params":null,"icon_link":null,"link":"http://geocommons.com/overlays/174190.json","extent":[120.739,15.5931,120.739,15.5931],"geometry_types":["point"],"unique_name":null,"name":"ASEAN-CMS","feature_count":1,"description":"","next_feature":null,"is_raster":false,"short_classification":"Y","stats":{},"features":[{"properties":{"COUNTRY":"Philippines","ISO_2":"PH","ISO_3":"PHL","id":"0"},"type":"Feature","geometry":{"type":"Point","coordinates":[120.73905,15.59305]}}],"is_temporal":false,"author":{"url":"","metadata":"","contact_name":"","contact_address":"","source":"","contact_phone":""},"source":"","pagination":{"sort":null,"start":0,"total":1,"limit":1000000},"state":"complete","tags":"ams,asean,mea,parties","published":"2014-08-13T03:52:12-04:00","id":174190}