{"type":"FeatureCollection","data_type":"Dataset","url_type":null,"permissions":[{"permissions":{"download":true,"view":true},"group_id":"everyone"}],"classification":null,"title":"Location_of_Home_Depot_Center","count":1,"stream_id":174827,"contributor":{"url":"http://geocommons.com/users/27072","name":"apenza"},"data_attributes":null,"calculation_params":null,"icon_link":null,"link":"http://geocommons.com/overlays/174827.json","extent":[-118.261,33.8643,-118.261,33.8643],"geometry_types":["point"],"unique_name":null,"name":"Location_of_Home_Depot_Center","feature_count":1,"description":"","next_feature":null,"is_raster":false,"short_classification":"Y","stats":{"lat":{"max":33.864296,"min":33.864296,"median":33.864296},"long":{"max":-118.261061,"min":-118.261061,"median":-118.261061}},"features":[{"properties":{"description":"Home Depot Center","id":"a6ii41yg2f8h","lat":33.864296,"long":-118.261061},"type":"Feature","geometry":{"type":"Point","coordinates":[-118.261061,33.864296]}}],"is_temporal":false,"author":{"url":"","metadata":null,"contact_name":null,"contact_address":null,"source":null,"contact_phone":null},"source":"","pagination":{"sort":null,"start":0,"total":1,"limit":1000000},"state":"complete","tags":"","published":"2014-08-13T04:50:16-04:00","id":174827}