{"type":"FeatureCollection","data_type":"Dataset","url_type":null,"permissions":[{"permissions":{"download":true,"view":true},"group_id":"everyone"}],"classification":null,"title":"Locations of U of M Libraries and Germanic/Scandinavian Heritage Centers in Minneapolis/St. Paul ","count":4,"stream_id":176969,"contributor":{"url":"http://geocommons.com/users/32867","name":"mjensen7"},"data_attributes":null,"calculation_params":null,"icon_link":null,"link":"http://geocommons.com/overlays/176969.json","extent":[-93.2658,44.9445,-93.1125,44.9735],"geometry_types":["point"],"unique_name":null,"name":"Locations of U of M Libraries and Germanic/Scandinavian Heritage Centers in Minneapolis/St. Paul ","feature_count":4,"description":"","next_feature":null,"is_raster":false,"short_classification":"Y","stats":{"latitude":{"max":44.973512,"mean":44.96104075,"variance":0.000187296070249982,"stdev":0.0136856154501718,"min":44.944496,"median":44.970962},"longitude":{"max":-93.112503,"mean":-93.21628125,"variance":0.00489791373091642,"stdev":0.0699850964914418,"min":-93.265789,"median":-93.243138}},"features":[{"properties":{"name":"GAI","latitude":44.944496,"longitude":-93.112503,"id":"a62kwqb7bn65"},"type":"Feature","geometry":{"type":"Point","coordinates":[-93.112503,44.944496]}},{"properties":{"name":"Wilson Lib","latitude":44.970962,"longitude":-93.243695,"id":"a62kwql8f0n8"},"type":"Feature","geometry":{"type":"Point","coordinates":[-93.243695,44.970962]}},{"properties":{"name":"Andersen Lib","latitude":44.973512,"longitude":-93.243138,"id":"a62kwqgebcb2"},"type":"Feature","geometry":{"type":"Point","coordinates":[-93.243138,44.973512]}},{"properties":{"name":"ASI","latitude":44.955193,"longitude":-93.265789,"id":"a62kwqi5ho2m"},"type":"Feature","geometry":{"type":"Point","coordinates":[-93.265789,44.955193]}}],"is_temporal":false,"author":{"url":"","metadata":"","contact_name":"","contact_address":"","source":"","contact_phone":""},"source":"","pagination":{"sort":null,"start":0,"total":4,"limit":1000000},"state":"complete","tags":"","published":"2011-11-15T11:00:00Z","id":176969}