{"type":"FeatureCollection","data_type":"Dataset","url_type":null,"permissions":[{"permissions":{"download":true,"view":true},"group_id":"everyone"}],"classification":null,"title":"UB GPS Intersections","count":16,"stream_id":179532,"contributor":{"url":"http://geocommons.com/users/36044","name":"cmneer"},"data_attributes":null,"calculation_params":null,"icon_link":null,"link":"http://geocommons.com/overlays/179532.json","extent":[-80.7114,53.0391,-80.7066,53.0449],"geometry_types":["point"],"unique_name":null,"name":"UB GPS Intersections","feature_count":16,"description":"","next_feature":null,"is_raster":false,"short_classification":"Y","stats":{"Northing":{"max":4764165,"mean":4763153.5,"variance":509068.0,"stdev":713.490013945535,"min":4762000,"median":4763499},"Easting":{"max":681132,"mean":680524.25,"variance":151577.0,"stdev":389.328909792222,"min":680042,"median":680594}},"features":[{"properties":{"NoName__13":null,"NoName":null,"Northing":4764165,"NoName_1":null,"id":"a6345ic3r8qz","NoName_12":null,"Easting":680195},"type":"Feature","geometry":{"type":"Point","coordinates":[-80.7109537051736,53.0449503173738]}},{"properties":{"NoName__13":null,"NoName":null,"Northing":4763816,"NoName_1":null,"id":"a6345ioaf2zq","NoName_12":null,"Easting":680820},"type":"Feature","geometry":{"type":"Point","coordinates":[-80.7080680608073,53.0440458042472]}},{"properties":{"NoName__13":null,"NoName":null,"Northing":4763499,"NoName_1":null,"id":"a6345im8pe7d","NoName_12":null,"Easting":680132},"type":"Feature","geometry":{"type":"Point","coordinates":[-80.7111500322231,53.0431222569212]}},{"properties":{"NoName__13":null,"NoName":null,"Northing":4762716,"NoName_1":null,"id":"a6345igq2sqj","NoName_12":null,"Easting":680825},"type":"Feature","geometry":{"type":"Point","coordinates":[-80.7078972524619,53.0410353398363]}},{"properties":{"NoName__13":null,"NoName":null,"Northing":4762465,"NoName_1":null,"id":"a6345ifwg3ti","NoName_12":null,"Easting":680042},"type":"Feature","geometry":{"type":"Point","coordinates":[-80.7114193400559,53.0402847304579]}},{"properties":{"NoName__13":null,"NoName":null,"Northing":4762002,"NoName_1":null,"id":"a6345imxx2o8","NoName_12":null,"Easting":680962},"type":"Feature","geometry":{"type":"Point","coordinates":[-80.7071789883359,53.0390921240363]}},{"properties":{"NoName__13":null,"NoName":null,"Northing":4762957,"NoName_1":null,"id":"a6345ikpydh2","NoName_12":null,"Easting":680594},"type":"Feature","geometry":{"type":"Point","coordinates":[-80.7089787835046,53.0416762461155]}},{"properties":{"NoName__13":null,"NoName":null,"Northing":4763611,"NoName_1":null,"id":"a6345ibfj8as","NoName_12":null,"Easting":680125},"type":"Feature","geometry":{"type":"Point","coordinates":[-80.711196926174,53.0434282487067]}},{"properties":{"NoName__13":null,"NoName":null,"Northing":4764163,"NoName_1":null,"id":"a6345ipg6epo","NoName_12":null,"Easting":680193},"type":"Feature","geometry":{"type":"Point","coordinates":[-80.7109625191665,53.0449446805575]}},{"properties":{"NoName__13":null,"NoName":null,"Northing":4763817,"NoName_1":null,"id":"a6345ii5rvdp","NoName_12":null,"Easting":680821},"type":"Feature","geometry":{"type":"Point","coordinates":[-80.7080636537094,53.0440486225495]}},{"properties":{"NoName__13":null,"NoName":null,"Northing":4763499,"NoName_1":null,"id":"a6345ila8nxv","NoName_12":null,"Easting":681132},"type":"Feature","geometry":{"type":"Point","coordinates":[-80.7066083802553,53.0432034355434]}},{"properties":{"NoName__13":null,"NoName":null,"Northing":4762714,"NoName_1":null,"id":"a6345iq9yrr1","NoName_12":null,"Easting":680825},"type":"Feature","geometry":{"type":"Point","coordinates":[-80.707896983214,53.0410298655253]}},{"properties":{"NoName__13":null,"NoName":null,"Northing":4762468,"NoName_1":null,"id":"a6345ig7zyja","NoName_12":null,"Easting":680043},"type":"Feature","geometry":{"type":"Point","coordinates":[-80.7114152032432,53.0402930231792]}},{"properties":{"NoName__13":null,"NoName":null,"Northing":4762000,"NoName_1":null,"id":"a6345ifivnh4","NoName_12":null,"Easting":680961},"type":"Feature","geometry":{"type":"Point","coordinates":[-80.7071832604265,53.0390865686115]}},{"properties":{"NoName__13":null,"NoName":null,"Northing":4762958,"NoName_1":null,"id":"a6345icfy99h","NoName_12":null,"Easting":680594},"type":"Feature","geometry":{"type":"Point","coordinates":[-80.7089789182002,53.0416789832688]}},{"properties":{"NoName__13":null,"NoName":null,"Northing":4763606,"NoName_1":null,"id":"a6345ilnr0mu","NoName_12":null,"Easting":680124},"type":"Feature","geometry":{"type":"Point","coordinates":[-80.7112007936226,53.0434144816966]}}],"is_temporal":false,"author":{"url":"","metadata":"","contact_name":"","contact_address":", , , ","source":"","contact_phone":""},"source":"","pagination":{"sort":null,"start":0,"total":16,"limit":1000000},"state":"complete","tags":"","published":"2014-08-13T11:57:09-04:00","id":179532}