{"type":"FeatureCollection","data_type":"Dataset","url_type":null,"permissions":[{"permissions":{"download":true,"view":true},"group_id":"everyone"}],"classification":null,"title":"MyAddressInfo","count":3,"stream_id":182927,"contributor":{"url":"http://geocommons.com/users/31147","name":"bmoothedan"},"data_attributes":null,"calculation_params":null,"icon_link":null,"link":"http://geocommons.com/overlays/182927.json","extent":[-87.7328,34.5059,-86.8977,34.7698],"geometry_types":["point"],"unique_name":null,"name":"MyAddressInfo","feature_count":3,"description":"","next_feature":null,"is_raster":false,"short_classification":"Y","stats":{},"features":[{"properties":{"city":"Pune","department":"<a href=\"http://opensale.co.uk/images/2011/12/09/642/thumb_short-term-accommodation-needed_1.jpg\"><img src=\"http://opensale.co.uk/images/2011/12/09/642/thumb_short-term-accommodation-needed_1.jpg\"></a>","name":"Binu Moothedan","zip":"411001","geo_score":0.514,"country":"India","street address":"E3, Eastern Court, B T Kawde Road, Ghorpadi","office":"EHP","id":"0","geo_precision":"street","state":"Maharashtra"},"type":"Feature","geometry":{"type":"Point","coordinates":[-86.897669,34.769826]}},{"properties":{"city":"Pune","department":"Graphics","name":"Rashmi Raj","zip":"411001","geo_score":0.557,"country":"India","street address":"Lane E, North Main Road, Koregaon Park","office":"ETP","id":"1","geo_precision":"street","state":"Maharashtra"},"type":"Feature","geometry":{"type":"Point","coordinates":[-87.723998,34.505898]}},{"properties":{"city":"Pune","department":"QA","name":"Pankaja Dingare","zip":"411052","geo_score":0.557,"country":"India","street address":"Dhanashri Niwas, Karve Nagar","office":"EHP","id":"2","geo_precision":"street","state":"Maharashtra"},"type":"Feature","geometry":{"type":"Point","coordinates":[-87.732847,34.525378]}}],"is_temporal":false,"author":{"url":"","metadata":"","contact_name":"","contact_address":"","source":"","contact_phone":""},"source":"","pagination":{"sort":null,"start":0,"total":3,"limit":1000000},"state":"complete","tags":"","published":"2014-08-13T01:36:42-04:00","id":182927}