{"type":"FeatureCollection","data_type":"Dataset","url_type":null,"permissions":[{"permissions":{"download":true,"view":true},"group_id":"everyone"}],"classification":null,"title":"Michigan School District Information","count":3,"stream_id":185355,"contributor":{"url":"http://geocommons.com/users/5925","name":"afdomas"},"data_attributes":null,"calculation_params":null,"icon_link":null,"link":"http://geocommons.com/overlays/185355.json","extent":[-84.6406,42.5093,-84.2743,43.3011],"geometry_types":["point"],"unique_name":null,"name":"Michigan School District Information","feature_count":3,"description":"Data about three school districts in michigan, including enrollment and number of football wins","next_feature":null,"is_raster":false,"short_classification":"Y","stats":{"wins over 5 years (2008-2012)":{"max":52,"mean":31.3333333333333,"variance":609.333333333333,"stdev":24.6846781087648,"min":4,"median":38},"population":{"max":5124,"mean":4020.66666666667,"variance":1061233.33333333,"stdev":1030.16179958943,"min":3084,"median":3854},"enrollment school year 2011-2012":{"max":2623,"mean":2258.0,"variance":266450.0,"stdev":516.18795026618,"min":1893,"median":2623},"enrollment school year 2010-2011":{"max":2770,"mean":2309.5,"variance":424120.5,"stdev":651.24534547281,"min":1849,"median":2770},"enrollment school year 2009-2010":{"max":2850,"mean":2075.33333333333,"variance":485425.333333333,"stdev":696.724718474473,"min":1500,"median":1876},"enrollment school year 2008-2009":{"max":2921,"mean":2406.0,"variance":530450.0,"stdev":728.319984622144,"min":1891,"median":2921},"enrollment school year 2007-2008":{"max":1937,"min":1937,"median":1937}},"features":[{"properties":{"column_10":null,"wins over 5 years (2008-2012)":4,"column_11":null,"column_12":null,"district":"Eaton Rapids","geo_score":0.911,"column_13":null,"population":5124,"id":"a65xlmzo3jsn","geo_precision":"range","enrollment school year 2011-2012":2623,"enrollment school year 2010-2011":2770,"enrollment school year 2009-2010":2850,"enrollment school year 2008-2009":2921,"enrollment school year 2007-2008":null,"address":"800 State Street, Eaton Rapids, MI, 48827"},"type":"Feature","geometry":{"type":"Point","coordinates":[-84.640611,42.509297]}},{"properties":{"column_10":null,"wins over 5 years (2008-2012)":38,"column_11":null,"column_12":null,"district":"Williamston","geo_score":1.0,"column_13":null,"population":3854,"id":"a65xln9c59yv","geo_precision":"range","enrollment school year 2011-2012":1893,"enrollment school year 2010-2011":1849,"enrollment school year 2009-2010":1876,"enrollment school year 2008-2009":1891,"enrollment school year 2007-2008":1937,"address":"3939 Vanneter Rd, Williamston, MI, 48895"},"type":"Feature","geometry":{"type":"Point","coordinates":[-84.274278,42.70082]}},{"properties":{"column_10":null,"wins over 5 years (2008-2012)":52,"column_11":null,"column_12":null,"district":"Ithaca","geo_score":0.92,"column_13":null,"population":3084,"id":"a65xlnblrbp8","geo_precision":"range","enrollment school year 2011-2012":null,"enrollment school year 2010-2011":null,"enrollment school year 2009-2010":1500,"enrollment school year 2008-2009":null,"enrollment school year 2007-2008":null,"address":"710 Union Street, MI, 48847"},"type":"Feature","geometry":{"type":"Point","coordinates":[-84.597617,43.301058]}}],"is_temporal":false,"author":{"url":"","metadata":"","contact_name":"","contact_address":"","source":"the school districts","contact_phone":""},"source":"","pagination":{"sort":null,"start":0,"total":3,"limit":1000000},"state":"complete","tags":"michigan,schools","published":"2011-12-07T17:00:00Z","id":185355}