{"type":"FeatureCollection","data_type":"Dataset","url_type":null,"permissions":[{"permissions":{"download":true,"view":true},"group_id":"everyone"}],"classification":null,"title":"TestKML","count":1,"stream_id":186802,"contributor":{"url":"http://geocommons.com/users/35111","name":"noxdroid"},"data_attributes":null,"calculation_params":null,"icon_link":null,"link":"http://geocommons.com/overlays/186802.json","extent":[-122.082,37.4223,-122.082,37.4223],"geometry_types":["point"],"unique_name":null,"name":"TestKML","feature_count":1,"description":"","next_feature":null,"is_raster":false,"short_classification":"Y","stats":{},"features":[{"properties":{"name":"Simple placemark","description":"Attached to the ground. Intelligently places itself \r\n       at the height of the underlying terrain.","id":"0"},"type":"Feature","geometry":{"type":"Point","coordinates":[-122.082203542568,37.4222899014025]}}],"is_temporal":false,"author":{"url":"","metadata":"","contact_name":"","contact_address":"","source":"","contact_phone":""},"source":"","pagination":{"sort":null,"start":0,"total":1,"limit":1000000},"state":"complete","tags":"","published":"2014-08-13T07:39:13-04:00","id":186802}