{"type":"FeatureCollection","data_type":"Dataset","url_type":null,"permissions":[{"permissions":{"download":true,"view":true},"group_id":"everyone"}],"classification":null,"title":"2 group.kmz","count":1,"stream_id":192453,"contributor":{"url":"http://geocommons.com/users/37444","name":"kadarusman"},"data_attributes":null,"calculation_params":null,"icon_link":null,"link":"http://geocommons.com/overlays/192453.json","extent":[125.72,-24.4052,151.477,-0.417667],"geometry_types":["point"],"unique_name":null,"name":"2 group.kmz","feature_count":1,"description":"","next_feature":null,"is_raster":false,"short_classification":"Y","stats":{},"features":[{"properties":{"name":"2 M.sp. Kuweri","description":null,"id":"69"},"type":"Feature","geometry":{"type":"Point","coordinates":[133.866481,-3.55665]}}],"is_temporal":false,"author":{"url":"","metadata":"","contact_name":"","contact_address":"","source":"","contact_phone":""},"source":"","pagination":{"sort":null,"start":0,"total":1,"limit":1000000},"state":"complete","tags":"","published":"2014-08-13T00:06:25-04:00","id":192453}