{"type":"FeatureCollection","data_type":"Dataset","url_type":null,"permissions":[{"permissions":{"download":true,"view":true},"group_id":"everyone"}],"classification":null,"title":"Evergreen Pasture Points","count":13,"stream_id":192810,"contributor":{"url":"http://geocommons.com/users/16842","name":"david@villageearth.org"},"data_attributes":null,"calculation_params":null,"icon_link":null,"link":"http://geocommons.com/overlays/192810.json","extent":[-102.367,43.297,-102.342,43.3079],"geometry_types":["point"],"unique_name":null,"name":"Evergreen Pasture Points","feature_count":13,"description":"","next_feature":null,"is_raster":false,"short_classification":"Y","stats":{"latitude":{"max":43.30786,"mean":43.3024761538462,"variance":1.622652564102e-05,"stdev":0.00402821618598356,"min":43.29699,"median":43.30286},"longitude":{"max":-102.3423,"mean":-102.354030769231,"variance":8.09656410256919e-05,"stdev":0.00899809096562664,"min":-102.3668,"median":-102.3541}},"features":[{"properties":{"name":"Point 1","latitude":43.30658,"longitude":-102.3668,"id":"a6k70xqo2hj3"},"type":"Feature","geometry":{"type":"Point","coordinates":[-102.3668,43.30658]}},{"properties":{"name":"Point 2","latitude":43.30702,"longitude":-102.3618,"id":"a6k70xl321jx"},"type":"Feature","geometry":{"type":"Point","coordinates":[-102.3618,43.30702]}},{"properties":{"name":"Point 3","latitude":43.30695,"longitude":-102.3553,"id":"a6k70xm6na3z"},"type":"Feature","geometry":{"type":"Point","coordinates":[-102.3553,43.30695]}},{"properties":{"name":"Point 4","latitude":43.30786,"longitude":-102.3499,"id":"a6k70xmkjycj"},"type":"Feature","geometry":{"type":"Point","coordinates":[-102.3499,43.30786]}},{"properties":{"name":"Point 5","latitude":43.30577,"longitude":-102.3453,"id":"a6k70xseygt1"},"type":"Feature","geometry":{"type":"Point","coordinates":[-102.3453,43.30577]}},{"properties":{"name":"Point 6","latitude":43.30302,"longitude":-102.3427,"id":"a6k70xpw7xjn"},"type":"Feature","geometry":{"type":"Point","coordinates":[-102.3427,43.30302]}},{"properties":{"name":"Point 7","latitude":43.30071,"longitude":-102.3423,"id":"a6k70xljqyiy"},"type":"Feature","geometry":{"type":"Point","coordinates":[-102.3423,43.30071]}},{"properties":{"name":"Point 8","latitude":43.29939,"longitude":-102.3453,"id":"a6k70xxqprei"},"type":"Feature","geometry":{"type":"Point","coordinates":[-102.3453,43.29939]}},{"properties":{"name":"Point 9","latitude":43.2979,"longitude":-102.3487,"id":"a6k70xt2lqeo"},"type":"Feature","geometry":{"type":"Point","coordinates":[-102.3487,43.2979]}},{"properties":{"name":"Point 10","latitude":43.2974,"longitude":-102.3541,"id":"a6k70xuj12tk"},"type":"Feature","geometry":{"type":"Point","coordinates":[-102.3541,43.2974]}},{"properties":{"name":"Point 11","latitude":43.29699,"longitude":-102.3602,"id":"a6k70xwa6hsg"},"type":"Feature","geometry":{"type":"Point","coordinates":[-102.3602,43.29699]}},{"properties":{"name":"Point 12","latitude":43.29974,"longitude":-102.3636,"id":"a6k70xvr68dg"},"type":"Feature","geometry":{"type":"Point","coordinates":[-102.3636,43.29974]}},{"properties":{"name":"Point 13","latitude":43.30286,"longitude":-102.3664,"id":"a6k70xq9cgan"},"type":"Feature","geometry":{"type":"Point","coordinates":[-102.3664,43.30286]}}],"is_temporal":false,"author":{"url":"","metadata":"","contact_name":"","contact_address":"","source":"","contact_phone":""},"source":"","pagination":{"sort":null,"start":0,"total":13,"limit":1000000},"state":"complete","tags":"","published":"2014-08-13T00:37:52-04:00","id":192810}