{"type":"FeatureCollection","data_type":"Dataset","url_type":null,"permissions":[{"permissions":{"download":true,"view":true},"group_id":"everyone"}],"classification":null,"title":"Omzet thuis","count":2,"stream_id":193042,"contributor":{"url":"http://geocommons.com/users/38153","name":"evwoe"},"data_attributes":null,"calculation_params":null,"icon_link":null,"link":"http://geocommons.com/overlays/193042.json","extent":[-74.0776,40.7282,-71.0898,43.7486],"geometry_types":["point"],"unique_name":null,"name":"Omzet thuis","feature_count":2,"description":"","next_feature":null,"is_raster":false,"short_classification":"Y","stats":{"omzet":{"max":100.0,"mean":90.0,"variance":200.0,"stdev":14.142135623731,"min":80.0,"median":100.0}},"features":[{"properties":{"omzet":100.0,"city":"Amersfoort","geo_score":0.729,"adress":"Celsiusstraat 23","zip code":"3817 XD","id":"a68rg5dlo75z","geo_precision":"zip"},"type":"Feature","geometry":{"type":"Point","coordinates":[-71.089796,43.74858]}},{"properties":{"omzet":80.0,"city":"Apeldoorn","geo_score":0.714,"adress":"Gunninglaan 26","zip code":"7314 NH","id":"a68rg5fv0pdo","geo_precision":"zip"},"type":"Feature","geometry":{"type":"Point","coordinates":[-74.077642,40.728158]}}],"is_temporal":false,"author":{"url":"","metadata":"","contact_name":"","contact_address":"","source":"","contact_phone":""},"source":"","pagination":{"sort":null,"start":0,"total":2,"limit":1000000},"state":"complete","tags":"","published":"2014-08-13T00:51:01-04:00","id":193042}