{"type":"FeatureCollection","data_type":"Dataset","url_type":null,"permissions":[{"permissions":{"download":true,"view":true},"group_id":"everyone"}],"classification":null,"title":"African Development Programme (ADP)","count":1,"stream_id":193561,"contributor":{"url":"http://geocommons.com/users/38201","name":"jonathan.yu"},"data_attributes":null,"calculation_params":null,"icon_link":null,"link":"http://geocommons.com/overlays/193561.json","extent":[-0.216667,5.55,-0.216667,5.55],"geometry_types":["point"],"unique_name":null,"name":"African Development Programme (ADP)","feature_count":1,"description":"","next_feature":null,"is_raster":false,"short_classification":"Y","stats":{},"features":[{"properties":{"city":"Accra","ngo name":"African Development Programme (ADP)","country":"Ghana","geo_score":1.0,"mission":"ADP encourages dialogue as a tool to prevent, manage, and resolve conflict and to promote good governance","street":"5th Circular Road","id":"a6k71flhufv1","phone number":"+233 (21) 306345","email address":"chasadp@africaonline.com.gh","geo_precision":"zip"},"type":"Feature","geometry":{"type":"Point","coordinates":[-0.2166667,5.55]}}],"is_temporal":false,"author":{"url":"","metadata":"","contact_name":"","contact_address":"","source":"","contact_phone":""},"source":"","pagination":{"sort":null,"start":0,"total":1,"limit":1000000},"state":"complete","tags":"","published":"2014-08-13T01:36:08-04:00","id":193561}