{"type":"FeatureCollection","data_type":"Dataset","url_type":null,"permissions":[{"permissions":{"download":true,"view":true},"group_id":"everyone"}],"classification":null,"title":"Seizures in Kabul","count":1,"stream_id":194497,"contributor":{"url":"http://geocommons.com/users/6","name":"seagor"},"data_attributes":null,"calculation_params":[{"input":{"atr":"district name","equals":"Kabul"},"calculation":"filter"}],"icon_link":null,"link":"http://geocommons.com/overlays/194497.json","extent":[62.086,30.1648,70.9794,36.7106],"geometry_types":["point"],"unique_name":null,"name":"Seizures in Kabul","feature_count":1,"description":"","next_feature":null,"is_raster":false,"short_classification":"Y","stats":{"latitude":{"max":34.51759149,"min":34.51759149,"median":34.51759149},"district id":{"max":101,"min":101,"median":101},"size of seizure (in kg)":{"max":15247,"min":15247,"median":15247},"longitude":{"max":69.16954092,"min":69.16954092,"median":69.16954092}},"features":[{"properties":{"latitude":34.51759149,"district id":101,"size of seizure (in kg)":15247,"province name":"Kabul","district name":"Kabul","longitude":69.16954092,"id":"1"},"type":"Feature","geometry":{"type":"Point","coordinates":[69.16954092,34.51759149]}}],"is_temporal":false,"author":{"url":"","metadata":"","contact_name":"","contact_address":"","source":"","contact_phone":""},"source":"","pagination":{"sort":null,"start":0,"total":1,"limit":1000000},"state":"complete","tags":"","published":"2014-08-13T03:09:31-04:00","id":194497}