{"type":"FeatureCollection","data_type":"Dataset","url_type":null,"permissions":[{"permissions":{"download":true,"view":true},"group_id":"everyone"}],"classification":null,"title":"Rss Test","count":2,"stream_id":19504,"contributor":{"url":"http://geocommons.com/users/10279","name":"wmsmith"},"data_attributes":null,"calculation_params":null,"icon_link":null,"link":"http://geocommons.com/overlays/19504.json","extent":[-3.0,51.0833,-2.63083,51.3561],"geometry_types":["point"],"unique_name":null,"name":"Rss Test","feature_count":2,"description":"","next_feature":null,"is_raster":false,"short_classification":"Y","stats":{"latitude":{"max":51.3561,"mean":51.2197,"variance":0.0372099199999991,"stdev":0.192898729907688,"min":51.0833,"median":51.3561},"x":{"max":-2.63083,"mean":-2.815415,"variance":0.06814324445,"stdev":0.261042610410638,"min":-3.0,"median":-2.63083},"y":{"max":51.3561,"mean":51.2197,"variance":0.0372099199999991,"stdev":0.192898729907688,"min":51.0833,"median":51.3561},"end":{"max":486.0,"mean":481.0,"variance":50.0,"stdev":7.07106781186548,"min":476.0,"median":486.0},"start":{"max":478.0,"mean":472.0,"variance":72.0,"stdev":8.48528137423857,"min":466.0,"median":478.0},"index":{"max":1.0,"mean":0.5,"variance":0.5,"stdev":0.707106781186548,"min":0.0,"median":1.0},"longitude":{"max":-2.63083,"mean":-2.815415,"variance":0.06814324445,"stdev":0.261042610410638,"min":-3.0,"median":-2.63083},"geoconfidence":{"max":0.938856,"mean":0.65451,"variance":0.161705295432,"stdev":0.40212596960654,"min":0.370164,"median":0.938856}},"features":[{"properties":{"latitude":51.3561,"georef":"Chew Stoke","x":-2.63083,"y":51.3561,"end":476.0,"start":466.0,"xpath":null,"index":0.0,"longitude":-2.63083,"offset":null,"id":"a637t926mlo5","geoconfidence":0.938856,"style":"loc"},"type":"Feature","geometry":{"type":"Point","coordinates":[-2.63083,51.3561]}},{"properties":{"latitude":51.0833,"georef":"Somerset","x":-3.0,"y":51.0833,"end":486.0,"start":478.0,"xpath":null,"index":1.0,"longitude":-3.0,"offset":null,"id":"a637t8w9vyi2","geoconfidence":0.370164,"style":"loc"},"type":"Feature","geometry":{"type":"Point","coordinates":[-3.0,51.0833]}}],"is_temporal":false,"author":{"url":"","metadata":"","contact_name":"","contact_address":"","source":"","contact_phone":""},"source":"","pagination":{"sort":null,"start":0,"total":2,"limit":1000000},"state":"complete","tags":"rss","published":"2009-12-27T17:00:00Z","id":19504}