{"type":"FeatureCollection","data_type":"Dataset","url_type":null,"permissions":[{"permissions":{"download":true,"view":true},"group_id":"everyone"}],"classification":null,"title":"Coahuila Cash Seizures $(USD)10,000+","count":1,"stream_id":195340,"contributor":{"url":"http://geocommons.com/users/36594","name":"mfain19"},"data_attributes":null,"calculation_params":null,"icon_link":null,"link":"http://geocommons.com/overlays/195340.json","extent":[-100.517,28.7,-100.517,28.7],"geometry_types":["point"],"unique_name":null,"name":"Coahuila Cash Seizures $(USD)10,000+","feature_count":1,"description":"This data presents seizures of $(USD)10,000 or more in Coahuila, Mexico.","next_feature":null,"is_raster":false,"short_classification":"Y","stats":{"latitude":{"max":28.70000076,"min":28.70000076,"median":28.70000076},"event id":{"max":3829737,"min":3829737,"median":3829737},"dto injuries":{"max":0,"min":0,"median":0},"dto deaths":{"max":0,"min":0,"median":0},"civilian involved":{"max":0,"min":0,"median":0},"government involved":{"max":0,"min":0,"median":0},"government injuries":{"max":0,"min":0,"median":0},"civilian deaths":{"max":0,"min":0,"median":0},"civilian injuries":{"max":0,"min":0,"median":0},"government deaths":{"max":0,"min":0,"median":0},"involved":{"max":2,"min":2,"median":2},"dto involved":{"max":2,"min":2,"median":2},"longitude":{"max":-100.5166702,"min":-100.5166702,"median":-100.5166702},"deaths":{"max":0,"min":0,"median":0},"injuries":{"max":0,"min":0,"median":0}},"features":[{"properties":{"city":"Piedras Negras","event type":"Police Operation","latitude":28.70000076,"operation information":"Customs personnel of Piedras Negras, Coahuila, Mexico arrested the two women.","event id":3829737,"property":"Border Station","dto injuries":0,"dto deaths":0,"civilian involved":0,"government involved":0,"government injuries":0,"police nationality":"Mexico","specific contraband":"U.S. Dollars","contraband":"Financial","event summary":"09/24/2011: On Saturday in Piedras Negras, Coahuila, Mexico, two female American citizens were arrested at the Tactic Center named Puente Internacional II. They were found in the trunk of a truck where customs found $(USD) 94,860. The seized vehicle was a black Chevrolet Avalanche, with Texas license plates. The two women were identified by their U.S. passports as Nikki Aguilera and Bobbie Jo Aguilera. No casualties were reported.","agency":"Federal/National Agency","civilian deaths":0,"division":"Unknown","civilian injuries":0,"government deaths":0,"involved":2,"event title":"Two American Citizens Arrested by Coahuila Customs","date of event":"9/24/2011","dto involved":2,"longitude":-100.5166702,"contraband type":"Currency","id":"a68cx6onc8js","deaths":0,"injuries":0,"state":"Coahuila"},"type":"Feature","geometry":{"type":"Point","coordinates":[-100.5166702,28.70000076]}}],"is_temporal":false,"author":{"url":"","metadata":"","contact_name":"","contact_address":"","source":"","contact_phone":""},"source":"","pagination":{"sort":null,"start":0,"total":1,"limit":1000000},"state":"complete","tags":"","published":"2012-01-13T16:22:53Z","id":195340}