{"type":"FeatureCollection","data_type":"Dataset","url_type":null,"permissions":[{"permissions":{"download":true,"view":true},"group_id":"everyone"}],"classification":null,"title":"Book1","count":17,"stream_id":195440,"contributor":{"url":"http://geocommons.com/users/38441","name":"butleret"},"data_attributes":null,"calculation_params":null,"icon_link":null,"link":"http://geocommons.com/overlays/195440.json","extent":[-104.985,30.3322,-81.6556,44.98],"geometry_types":["point"],"unique_name":null,"name":"Book1","feature_count":17,"description":"","next_feature":null,"is_raster":false,"short_classification":"Y","stats":{},"features":[{"properties":{"ia":"IA","geo_score":0.857,"des moines":"des moines","id":"a65p8ddbgdm0","geo_precision":"city"},"type":"Feature","geometry":{"type":"Point","coordinates":[-93.609106,41.600545]}},{"properties":{"ia":"IA","geo_score":0.857,"des moines":"des moines","id":"a65p8d3hafxe","geo_precision":"city"},"type":"Feature","geometry":{"type":"Point","coordinates":[-93.609106,41.600545]}},{"properties":{"ia":"IA","geo_score":0.857,"des moines":"des moines","id":"a65p8d5ljuf8","geo_precision":"city"},"type":"Feature","geometry":{"type":"Point","coordinates":[-93.609106,41.600545]}},{"properties":{"ia":"IA","geo_score":0.857,"des moines":"des moines","id":"a65p8d9d7joi","geo_precision":"city"},"type":"Feature","geometry":{"type":"Point","coordinates":[-93.609106,41.600545]}},{"properties":{"ia":"IA","geo_score":0.857,"des moines":"des moines","id":"a65p8dfngly0","geo_precision":"city"},"type":"Feature","geometry":{"type":"Point","coordinates":[-93.609106,41.600545]}},{"properties":{"ia":"IA","geo_score":0.857,"des moines":"des moines","id":"a65p8dgrpp7m","geo_precision":"city"},"type":"Feature","geometry":{"type":"Point","coordinates":[-93.609106,41.600545]}},{"properties":{"ia":"IA","geo_score":0.857,"des moines":"des moines","id":"a65p8diss2rz","geo_precision":"city"},"type":"Feature","geometry":{"type":"Point","coordinates":[-93.609106,41.600545]}},{"properties":{"ia":"IA","geo_score":0.857,"des moines":"des moines","id":"a65p8d9w6qtp","geo_precision":"city"},"type":"Feature","geometry":{"type":"Point","coordinates":[-93.609106,41.600545]}},{"properties":{"ia":"CO","geo_score":0.857,"des moines":"denver","id":"a65p8d3qhnte","geo_precision":"city"},"type":"Feature","geometry":{"type":"Point","coordinates":[-104.984703,39.739154]}},{"properties":{"ia":"CO","geo_score":0.857,"des moines":"denver","id":"a65p8dfhyqut","geo_precision":"city"},"type":"Feature","geometry":{"type":"Point","coordinates":[-104.984703,39.739154]}},{"properties":{"ia":"CO","geo_score":0.857,"des moines":"denver","id":"a65p8dduojt0","geo_precision":"city"},"type":"Feature","geometry":{"type":"Point","coordinates":[-104.984703,39.739154]}},{"properties":{"ia":"FL","geo_score":0.857,"des moines":"jacksonville","id":"a65p8detpqoe","geo_precision":"city"},"type":"Feature","geometry":{"type":"Point","coordinates":[-81.655651,30.332184]}},{"properties":{"ia":"MN","geo_score":0.857,"des moines":"minneapolis","id":"a65p8dc99kyo","geo_precision":"city"},"type":"Feature","geometry":{"type":"Point","coordinates":[-93.263836,44.979965]}},{"properties":{"ia":"MN","geo_score":0.835,"des moines":"minneapolis, mn","id":"a65p8d9qoof9","geo_precision":"city"},"type":"Feature","geometry":{"type":"Point","coordinates":[-93.263836,44.979965]}},{"properties":{"ia":"MN","geo_score":0.835,"des moines":"minneapolis, mn","id":"a65p8d8k4e4e","geo_precision":"city"},"type":"Feature","geometry":{"type":"Point","coordinates":[-93.263836,44.979965]}},{"properties":{"ia":"MN","geo_score":0.835,"des moines":"minneapolis, mn","id":"a65p8dbfvngb","geo_precision":"city"},"type":"Feature","geometry":{"type":"Point","coordinates":[-93.263836,44.979965]}},{"properties":{"ia":"MN","geo_score":0.835,"des moines":"minneapolis, mn","id":"a65p8dhe0kfe","geo_precision":"city"},"type":"Feature","geometry":{"type":"Point","coordinates":[-93.263836,44.979965]}}],"is_temporal":false,"author":{"url":"","metadata":"","contact_name":"","contact_address":"","source":"","contact_phone":""},"source":"","pagination":{"sort":null,"start":0,"total":17,"limit":1000000},"state":"complete","tags":"","published":"2014-08-13T04:20:59-04:00","id":195440}