{"type":"FeatureCollection","data_type":"Dataset","url_type":null,"permissions":[{"permissions":{"download":true,"view":true},"group_id":"everyone"}],"classification":null,"title":"Barcelona placa Espanya","count":1,"stream_id":19586,"contributor":{"url":"http://geocommons.com/users/6902","name":"ICCgeocommons"},"data_attributes":null,"calculation_params":null,"icon_link":null,"link":"http://geocommons.com/overlays/19586.json","extent":[2.14914,41.375,2.14914,41.375],"geometry_types":["point"],"unique_name":null,"name":"Barcelona placa Espanya","feature_count":1,"description":"Plaça d'Espanya de Barcelona","next_feature":null,"is_raster":false,"short_classification":"Y","stats":{},"features":[{"properties":{"name":"OpenLayers.Feature.Vector_204","description":"No description available","id":"a62pa4t4kz3p"},"type":"Feature","geometry":{"type":"Point","coordinates":[2.14914066781746,41.3750296638975]}}],"is_temporal":false,"author":{"url":"","metadata":"","contact_name":"","contact_address":"","source":"","contact_phone":""},"source":"","pagination":{"sort":null,"start":0,"total":1,"limit":1000000},"state":"complete","tags":"barcelona,square","published":"2014-08-11T01:21:14-04:00","id":19586}