{"type":"FeatureCollection","data_type":"Dataset","url_type":null,"permissions":[{"permissions":{"download":true,"view":true},"group_id":"everyone"}],"classification":null,"title":"Fundraising Call Nights at FCDC HQ (Lee District) / Thursday, July 10, 2008 at 06:00 PM       ","count":1,"stream_id":19627,"contributor":{"url":"http://geocommons.com/users/10302","name":"melissapbr"},"data_attributes":null,"calculation_params":null,"icon_link":null,"link":"http://geocommons.com/overlays/19627.json","extent":[-77.2225,38.8768,-77.2225,38.8768],"geometry_types":["point"],"unique_name":null,"name":"Fundraising Call Nights at FCDC HQ (Lee District) / Thursday, July 10, 2008 at 06:00 PM       ","feature_count":1,"description":"","next_feature":null,"is_raster":false,"short_classification":"Y","stats":{},"features":[{"properties":{"name":"Fundraising Call Nights at FCDC HQ (Lee District) / Thursday, July 10, 2008 at 06:00 PM","description":"Lee District has two fundraising call nights at FCDC HQ (Fairfax County Democratic Committee Headquarters). Funds raised will help all our efforts this year to elect/re-elect our Democrats: White House (Obama), Senate (Mark Warner) and Congress (Jim Moran, Judy Feder, Gerry Connolly)! Please help by signing up today to help our efforts on behalf of FCDC. Contact Lee District Democratic Committee co-chair: Hugh Robertson 703.924.1433 HughRbrtsn@aol.com","id":"a6eu3v65yosm"},"type":"Feature","geometry":{"type":"Point","coordinates":[-77.222511,38.876804]}}],"is_temporal":false,"author":{"url":"http://my.barackobama.com/page/event/detail/447rm","metadata":"","contact_name":"","contact_address":"","source":"","contact_phone":""},"source":"http://my.barackobama.com/page/event/detail/447rm","pagination":{"sort":null,"start":0,"total":1,"limit":1000000},"state":"complete","tags":"","published":"2014-08-11T01:21:59-04:00","id":19627}