{"type":"FeatureCollection","data_type":"Dataset","url_type":null,"permissions":[{"permissions":{"download":true,"view":true},"group_id":"everyone"}],"classification":null,"title":"Ban Yuan Thong","count":10,"stream_id":197942,"contributor":{"url":"http://geocommons.com/users/38169","name":"blewislao"},"data_attributes":null,"calculation_params":null,"icon_link":null,"link":"http://geocommons.com/overlays/197942.json","extent":[103.323,19.5018,103.34,19.5122],"geometry_types":["point"],"unique_name":null,"name":"Ban Yuan Thong","feature_count":10,"description":"Ban Yuan Thong, Paek district, XK province","next_feature":null,"is_raster":false,"short_classification":"Y","stats":{"latitude":{"max":19.5122,"mean":19.507017,"variance":1.65135566666698e-05,"stdev":0.00406368757001197,"min":19.5018,"median":19.5077},"longitude":{"max":103.34,"mean":103.33082,"variance":4.45506666666771e-05,"stdev":0.0066746285789306,"min":103.3226,"median":103.3306}},"features":[{"properties":{"name":"Point 1","latitude":19.512,"longitude":103.3226,"id":"a647lqhqfwgv"},"type":"Feature","geometry":{"type":"Point","coordinates":[103.3226,19.512]}},{"properties":{"name":"Point 2","latitude":19.5122,"longitude":103.3308,"id":"a647lqcpjyse"},"type":"Feature","geometry":{"type":"Point","coordinates":[103.3308,19.5122]}},{"properties":{"name":"Point 3","latitude":19.5118,"longitude":103.3392,"id":"a647lqafrfwx"},"type":"Feature","geometry":{"type":"Point","coordinates":[103.3392,19.5118]}},{"properties":{"name":"Point 4","latitude":19.5077,"longitude":103.3241,"id":"a647lq8vnbmk"},"type":"Feature","geometry":{"type":"Point","coordinates":[103.3241,19.5077]}},{"properties":{"name":"Point 5","latitude":19.5082,"longitude":103.3305,"id":"a647lqb2biqm"},"type":"Feature","geometry":{"type":"Point","coordinates":[103.3305,19.5082]}},{"properties":{"name":"Point 6","latitude":19.50557,"longitude":103.3273,"id":"a647lqg62hgh"},"type":"Feature","geometry":{"type":"Point","coordinates":[103.3273,19.50557]}},{"properties":{"name":"Point 7","latitude":19.506,"longitude":103.34,"id":"a647lq3iag20"},"type":"Feature","geometry":{"type":"Point","coordinates":[103.34,19.506]}},{"properties":{"name":"Point 8","latitude":19.5018,"longitude":103.3238,"id":"a647lqcfitfl"},"type":"Feature","geometry":{"type":"Point","coordinates":[103.3238,19.5018]}},{"properties":{"name":"Point 9","latitude":19.5027,"longitude":103.3306,"id":"a647lqe2b6ae"},"type":"Feature","geometry":{"type":"Point","coordinates":[103.3306,19.5027]}},{"properties":{"name":"Point 10","latitude":19.5022,"longitude":103.3393,"id":"a647lqfjx9hp"},"type":"Feature","geometry":{"type":"Point","coordinates":[103.3393,19.5022]}}],"is_temporal":false,"author":{"url":"","metadata":"","contact_name":"","contact_address":"","source":"","contact_phone":""},"source":"","pagination":{"sort":null,"start":0,"total":10,"limit":1000000},"state":"complete","tags":"xk","published":"2012-01-22T09:00:35Z","id":197942}