{"type":"FeatureCollection","data_type":"Dataset","url_type":null,"permissions":[{"permissions":{"download":true,"view":true},"group_id":"everyone"}],"classification":null,"title":"Boma Mountain","count":1,"stream_id":198690,"contributor":{"url":"http://geocommons.com/users/38884","name":"paulshaffner"},"data_attributes":null,"calculation_params":null,"icon_link":null,"link":"http://geocommons.com/overlays/198690.json","extent":[34.4395,6.12516,34.4395,6.12516],"geometry_types":["point"],"unique_name":null,"name":"Boma Mountain","feature_count":1,"description":"","next_feature":null,"is_raster":false,"short_classification":"Y","stats":{},"features":[{"properties":{"name":"Boma Mountain","id":"0"},"type":"Feature","geometry":{"type":"Point","coordinates":[34.4394774996697,6.12515674355342]}}],"is_temporal":false,"author":{"url":"","metadata":null,"contact_name":null,"contact_address":null,"source":null,"contact_phone":null},"source":"","pagination":{"sort":null,"start":0,"total":1,"limit":1000000},"state":"complete","tags":"","published":"2014-08-13T09:38:16-04:00","id":198690}