{"type":"FeatureCollection","data_type":"Dataset","url_type":null,"permissions":[{"permissions":{"download":true,"edit":true,"view":true},"group_id":37832},{"permissions":{"download":true,"view":true},"group_id":"everyone"}],"classification":null,"title":"start point","count":1,"stream_id":198760,"contributor":{"url":"http://geocommons.com/users/36758","name":"rashmiraj"},"data_attributes":null,"calculation_params":null,"icon_link":null,"link":"http://geocommons.com/overlays/198760.json","extent":[-73.9412,40.8087,-73.9412,40.8087],"geometry_types":["point"],"unique_name":null,"name":"start point","feature_count":1,"description":"","next_feature":null,"is_raster":false,"short_classification":"Y","stats":{"latitude":{"max":40.808656,"min":40.808656,"median":40.808656},"longitude":{"max":-73.941247,"min":-73.941247,"median":-73.941247}},"features":[{"properties":{"city":"New York City","latitude":40.808656,"participant":null,"zip":"10027-3111","notes":null,"street address":"17 West 128th Street, between Lenox Avenue and Fifth Avenue","property image":"<img src=\"http://www.clker.com/cliparts/l/j/T/V/5/v/home-icon-th.png\">","longitude":-73.941247,"tour details":"Start  point","program":"Christ Temple Church","id":"a67h9fxipeh9","state":"New York"},"type":"Feature","geometry":{"type":"Point","coordinates":[-73.941247,40.808656]}}],"is_temporal":false,"author":{"url":"","metadata":"","contact_name":"","contact_address":"","source":"","contact_phone":""},"source":"","pagination":{"sort":null,"start":0,"total":1,"limit":1000000},"state":"complete","tags":"","published":"2014-08-13T09:43:48-04:00","id":198760}