{"type":"FeatureCollection","data_type":"Dataset","url_type":null,"permissions":[{"permissions":{"download":true,"view":true},"group_id":"everyone"}],"classification":null,"title":"Santa Ana Indviduals","count":2,"stream_id":198944,"contributor":{"url":"http://geocommons.com/users/34351","name":"ACTA"},"data_attributes":null,"calculation_params":null,"icon_link":null,"link":"http://geocommons.com/overlays/198944.json","extent":[-117.866,33.748,-117.842,33.7581],"geometry_types":["point"],"unique_name":null,"name":"Santa Ana Indviduals","feature_count":2,"description":"","next_feature":null,"is_raster":false,"short_classification":"Y","stats":{"number":{"max":2,"mean":1.5,"variance":0.5,"stdev":0.707106781186548,"min":1,"median":2}},"features":[{"properties":{"city":"Santa Ana","name":"Sonia Velazquez-Miskulin","number":1,"geo_score":0.902,"zip code":"92701","street address":"220 E 4th Street","id":"a66n2tf8w7r1","geo_precision":"range","state":"California"},"type":"Feature","geometry":{"type":"Point","coordinates":[-117.866403,33.748]}},{"properties":{"city":"Santa Ana","name":"Sumona Vohra","number":2,"geo_score":1.0,"zip code":"92701","street address":"1345 Cabrillo Park Drive","id":"a66n2tskm11o","geo_precision":"range","state":"California"},"type":"Feature","geometry":{"type":"Point","coordinates":[-117.84169,33.758097]}}],"is_temporal":false,"author":{"url":"","metadata":"","contact_name":"","contact_address":"","source":"","contact_phone":""},"source":"","pagination":{"sort":null,"start":0,"total":2,"limit":1000000},"state":"complete","tags":"","published":"2014-08-13T09:52:58-04:00","id":198944}