{"type":"FeatureCollection","data_type":"Dataset","url_type":null,"permissions":[{"permissions":{"download":true,"view":true},"group_id":"everyone"}],"classification":null,"title":"Airports in Western, Kenya","count":3,"stream_id":201344,"contributor":{"url":"http://geocommons.com/users/36594","name":"mfain19"},"data_attributes":null,"calculation_params":null,"icon_link":null,"link":"http://geocommons.com/overlays/201344.json","extent":[34.1288,0.271181,34.7869,0.57814],"geometry_types":["point"],"unique_name":null,"name":"Airports in Western, Kenya","feature_count":3,"description":"This data presents airports in Western, Kenya.","next_feature":null,"is_raster":false,"short_classification":"Y","stats":{"lon":{"max":34.786921,"mean":34.4911446666667,"variance":0.111612040670333,"stdev":0.33408388268567,"min":34.128782,"median":34.557731},"lat":{"max":0.57814,"mean":0.435229666666667,"variance":0.0238910787723333,"stdev":0.154567392332061,"min":0.271181,"median":0.456368}},"features":[{"properties":{"lon":34.557731,"airport name":"Bungoma Airstrip","city":"Bungoma","surface":"Paved","code":"N/A","international":"No","country":"Kenya","id":"a6bk8ft118xc","lat":0.57814,"state":"Western"},"type":"Feature","geometry":{"type":"Point","coordinates":[34.557731,0.57814]}},{"properties":{"lon":34.128782,"airport name":"Busia","city":"Busia","surface":"Unpaved","code":"N/A","international":"No","country":"Kenya","id":"a6bk8frzcvho","lat":0.456368,"state":"Western"},"type":"Feature","geometry":{"type":"Point","coordinates":[34.128782,0.456368]}},{"properties":{"lon":34.786921,"airport name":"Kakamega Airport","city":"Kakamega","surface":"Paved","code":"N/A","international":"No","country":"Kenya","id":"a6bk8fvl0yn3","lat":0.271181,"state":"Western"},"type":"Feature","geometry":{"type":"Point","coordinates":[34.786921,0.271181]}}],"is_temporal":false,"author":{"url":"","metadata":"","contact_name":"","contact_address":"","source":"","contact_phone":""},"source":"","pagination":{"sort":null,"start":0,"total":3,"limit":1000000},"state":"complete","tags":"","published":"2012-02-01T16:49:10Z","id":201344}