{"type":"FeatureCollection","data_type":"Dataset","url_type":null,"permissions":[{"permissions":{"download":true,"view":true},"group_id":"everyone"}],"classification":null,"title":"Airports in Nyanza, Kenya","count":2,"stream_id":201570,"contributor":{"url":"http://geocommons.com/users/36594","name":"mfain19"},"data_attributes":null,"calculation_params":[{"input":{"atr":"international","equals":"No"},"calculation":"filter"}],"icon_link":null,"link":"http://geocommons.com/overlays/201570.json","extent":[34.4768,-0.672243,34.7304,-0.084919],"geometry_types":["point"],"unique_name":null,"name":"Airports in Nyanza, Kenya","feature_count":2,"description":"This data provides airports in Nyanza, Kenya.","next_feature":null,"is_raster":false,"short_classification":"Y","stats":{"lon":{"max":34.688494,"mean":34.582665,"variance":0.022399554482,"stdev":0.149664807092382,"min":34.476836,"median":34.688494},"lat":{"max":-0.587694,"mean":-0.6299685,"variance":0.0035742667005,"stdev":0.0597851712425414,"min":-0.672243,"median":-0.587694}},"features":[{"properties":{"lon":34.476836,"airport name":"Homa Bay Airport","city":"Homa Bay","surface":"Paved","code":"N/A","international":"No","country":"Kenya","id":"1","lat":-0.587694,"state":"Nyanza"},"type":"Feature","geometry":{"type":"Point","coordinates":[34.476836,-0.587694]}},{"properties":{"lon":34.688494,"airport name":"Kisii Airport","city":"Kisii","surface":"Paved","code":"N/A","international":"No","country":"Kenya","id":"2","lat":-0.672243,"state":"Nyanza"},"type":"Feature","geometry":{"type":"Point","coordinates":[34.688494,-0.672243]}}],"is_temporal":false,"author":{"url":"","metadata":"","contact_name":"","contact_address":"","source":"","contact_phone":""},"source":"","pagination":{"sort":null,"start":0,"total":2,"limit":1000000},"state":"complete","tags":"","published":"2012-02-02T17:00:00Z","id":201570}