{"type":"FeatureCollection","data_type":"Dataset","url_type":null,"permissions":[{"permissions":{"download":true,"view":true},"group_id":"everyone"}],"classification":null,"title":"Main_House","count":1,"stream_id":201553,"contributor":{"url":"http://geocommons.com/users/38961","name":"aurora6853"},"data_attributes":null,"calculation_params":null,"icon_link":null,"link":"http://geocommons.com/overlays/201553.json","extent":[-2.67918,51.8879,-2.67918,51.8879],"geometry_types":["point"],"unique_name":null,"name":"Main_House","feature_count":1,"description":"","next_feature":null,"is_raster":false,"short_classification":"Y","stats":{},"features":[{"properties":{"name":"Main House","description":"https://picasaweb.google.com/116678304312364306424/EnglandAndWales?authkey=Gv1sRgCKmQ9efGwoPkUA#5691665161987309730","id":"0"},"type":"Feature","geometry":{"type":"Point","coordinates":[-2.67917538020074,51.8879137711609]}}],"is_temporal":false,"author":{"url":"","metadata":null,"contact_name":null,"contact_address":null,"source":null,"contact_phone":null},"source":"","pagination":{"sort":null,"start":0,"total":1,"limit":1000000},"state":"complete","tags":"","published":"2014-08-14T16:50:46-04:00","id":201553}