{"type":"FeatureCollection","data_type":"Dataset","url_type":null,"permissions":[{"permissions":{"download":true,"view":true},"group_id":"everyone"}],"classification":null,"title":"agencylistgeocode","count":2,"stream_id":201623,"contributor":{"url":"http://geocommons.com/users/37028","name":"foodlink"},"data_attributes":null,"calculation_params":null,"icon_link":null,"link":"http://geocommons.com/overlays/201623.json","extent":[-77.6213,43.1384,-77.6134,43.1763],"geometry_types":["point"],"unique_name":null,"name":"agencylistgeocode","feature_count":2,"description":"","next_feature":null,"is_raster":false,"short_classification":"Y","stats":{"latitude":{"max":43.192731,"mean":43.1656005,"variance":0.00147212806050021,"stdev":0.038368321053966,"min":43.13847,"median":43.192731},"longitude":{"max":-77.621374,"mean":-77.640607,"variance":0.000739816577999987,"stdev":0.0271995694451215,"min":-77.65984,"median":-77.621374}},"features":[{"properties":{"city":"Rochester","agency description":"food bank","latitude":43.192731,"zip":"14615","url":"www.foodlinkny.org","agencyname":"Foodlink","phone":null,"area(s) served":"10 counties","longitude":-77.65984,"hoo":"9:00-5:00","id":"a6801gfi94wn","address":"1999 Mt. Read Blvd.","state":"NY","email":"coolcan@foodlinkny.org"},"type":"Feature","geometry":{"type":"Point","coordinates":[-77.613356,43.176309]}},{"properties":{"city":"Rochester","agency description":"foodbank","latitude":43.13847,"zip":null,"url":null,"agencyname":"Old Foodlink","phone":null,"area(s) served":null,"longitude":-77.621374,"hoo":null,"id":"a6801g31zhlw","address":"936 Exchange St.","state":"NY","email":null},"type":"Feature","geometry":{"type":"Point","coordinates":[-77.621267,43.13844]}}],"is_temporal":false,"author":{"url":"","metadata":"","contact_name":"","contact_address":"","source":"","contact_phone":""},"source":"","pagination":{"sort":null,"start":0,"total":2,"limit":1000000},"state":"complete","tags":"","published":"2014-08-14T16:55:31-04:00","id":201623}