{"type":"FeatureCollection","data_type":"Dataset Analysis","url_type":null,"permissions":[{"permissions":{"download":true,"view":true},"group_id":"everyone"}],"classification":null,"title":"Filtered Features of 'Chicago_police_stations' based on 'Chicago Homicides 2011'","count":1,"stream_id":203583,"contributor":{"url":"http://geocommons.com/users/39734","name":"carlosevc"},"data_attributes":null,"calculation_params":{"input":{"min_distance":"10","unit":"m","near_id":"189398","distance":"100","include_distance":true,"id":"190514"},"calculation":"buffer_intersect"},"icon_link":null,"link":"http://geocommons.com/overlays/203583.json","extent":[-87.6927,41.9795,-87.6927,41.9795],"geometry_types":["point"],"unique_name":null,"name":"Filtered Features of 'Chicago_police_stations' based on 'Chicago Homicides 2011'","feature_count":1,"description":"Dataset created by filtering features of 'Chicago_police_stations' that are within a buffer of 10 to 100 m around the features in 'Chicago Homicides 2011'","next_feature":null,"is_raster":false,"short_classification":"Y","stats":{"district":{"max":null,"min":null,"median":null},"geo_score":{"max":0.805,"min":0.805,"median":0.805},"distance":{"max":96.5085577834243,"min":96.5085577834243,"median":96.5085577834243}},"features":[{"properties":{"zip":"60625","tty":"312-742-8841","district":"20","geo_score":0.805,"website":"https://portal.chicagopolice.org/portal/page/portal/ClearPath/Communities/Districts/District20","fax":"312-742-8803","phone":"312-742-8714","id":"20","geo_precision":"range","address":"5400 N Lincoln Ave","location":"5400 N Lincoln Ave\nChicago, IL 60625\n(41.97954202254066, -87.69301593304144)","distance":96.5085577834243},"type":"Feature","geometry":{"type":"Point","coordinates":[-87.692694,41.97951]}}],"is_temporal":false,"author":{"url":null,"metadata":null,"contact_name":null,"contact_address":null,"source":null,"contact_phone":null},"source":null,"pagination":{"sort":null,"start":0,"total":1,"limit":1000000},"state":"complete","tags":"","published":"2014-08-14T19:27:13-04:00","id":203583}