{"type":"FeatureCollection","data_type":"Dataset","url_type":null,"permissions":[{"permissions":{"download":true,"view":true},"group_id":"everyone"}],"classification":null,"title":"Population growth of Manitoba's 9 cities","count":9,"stream_id":203771,"contributor":{"url":"http://geocommons.com/users/39756","name":"tessavanderhart"},"data_attributes":null,"calculation_params":null,"icon_link":null,"link":"http://geocommons.com/overlays/203771.json","extent":[-101.85,49.1817,-96.6839,55.7449],"geometry_types":["point"],"unique_name":null,"name":"Population growth of Manitoba's 9 cities","feature_count":9,"description":"","next_feature":null,"is_raster":false,"short_classification":"Y","stats":{"latitude":{"max":55.744925,"mean":51.0868512222222,"variance":5.9510048809317,"stdev":2.43946815534282,"min":49.181667,"median":49.899754},"2011 population":{"max":663617,"mean":87016.1111111111,"variance":46898335141.6111,"stdev":216560.234442086,"min":5363,"median":12829},"longitude":{"max":-96.683889,"mean":-98.5141562222222,"variance":3.03672163069444,"stdev":1.74261918694086,"min":-101.849544,"median":-97.940278},"population growth (% increase)":{"max":22.2,"mean":6.26666666666667,"variance":81.5725,"stdev":9.03174955365792,"min":-4.6,"median":4.4}},"features":[{"properties":{"manitoba cities total:":"783,145, 5.2% growth","latitude":49.899754,"2011 population":663617,"longitude":-97.137494,"column_1":"Winnipeg, Manitoba","id":"a63qd2jt5i29","population growth (% increase)":4.8},"type":"Feature","geometry":{"type":"Point","coordinates":[-97.137494,49.899754]}},{"properties":{"manitoba cities total:":"783,145, 5.2% growth","latitude":49.843355,"2011 population":46061,"longitude":-99.950442,"column_1":"Brandon, Manitoba","id":"a63qd2jur9sa","population growth (% increase)":11.0},"type":"Feature","geometry":{"type":"Point","coordinates":[-99.950442,49.843355]}},{"properties":{"manitoba cities total:":"783,145, 5.2% growth","latitude":49.525833,"2011 population":13524,"longitude":-96.683889,"column_1":"Steinbach, Manitoba","id":"a63qd2k9n34b","population growth (% increase)":22.2},"type":"Feature","geometry":{"type":"Point","coordinates":[-96.683889,49.525833]}},{"properties":{"manitoba cities total:":"783,145, 5.2% growth","latitude":49.525833,"2011 population":12996,"longitude":-98.290325,"column_1":"Portage la Prairie, Manitoba","id":"a63qd2wqsyrp","population growth (% increase)":2.1},"type":"Feature","geometry":{"type":"Point","coordinates":[-98.290325,49.525833]}},{"properties":{"manitoba cities total:":"783,145, 5.2% growth","latitude":55.744925,"2011 population":12829,"longitude":-97.850871,"column_1":"Thompson, Manitoba","id":"a63qd2m92jt1","population growth (% increase)":-4.6},"type":"Feature","geometry":{"type":"Point","coordinates":[-97.850871,55.744925]}},{"properties":{"manitoba cities total:":"783,145, 5.2% growth","latitude":49.181667,"2011 population":10670,"longitude":-97.940278,"column_1":"Winkler, Manitoba","id":"a63qd2ocmv0y","population growth (% increase)":17.2},"type":"Feature","geometry":{"type":"Point","coordinates":[-97.940278,49.181667]}},{"properties":{"manitoba cities total:":"783,145, 5.2% growth","latitude":50.143528,"2011 population":9834,"longitude":-96.875429,"column_1":"Selkirk, Manitoba","id":"a63qd2sve789","population growth (% increase)":3.4},"type":"Feature","geometry":{"type":"Point","coordinates":[-96.875429,50.143528]}},{"properties":{"manitoba cities total:":"783,145, 5.2% growth","latitude":51.147789,"2011 population":8251,"longitude":-100.049134,"column_1":"Dauphin, Manitoba","id":"a63qd2novz3r","population growth (% increase)":4.4},"type":"Feature","geometry":{"type":"Point","coordinates":[-100.049134,51.147789]}},{"properties":{"manitoba cities total:":"783,145, 5.2% growth","latitude":54.768977,"2011 population":5363,"longitude":-101.849544,"column_1":"Flin Flon, Manitoba","id":"a63qd2vn61bn","population growth (% increase)":-4.1},"type":"Feature","geometry":{"type":"Point","coordinates":[-101.849544,54.768977]}}],"is_temporal":false,"author":{"url":"","metadata":"","contact_name":"","contact_address":"","source":"","contact_phone":""},"source":"","pagination":{"sort":null,"start":0,"total":9,"limit":1000000},"state":"complete","tags":"census,cities,growth,manitoba,population,winnipeg","published":"2012-02-08T17:26:12Z","id":203771}