{"type":"FeatureCollection","data_type":"Dataset","url_type":null,"permissions":[{"permissions":{"download":true,"view":true},"group_id":"everyone"}],"classification":null,"title":"American_Fork_Senior_Citizens_Center","count":1,"stream_id":206592,"contributor":{"url":"http://geocommons.com/users/39711","name":"altaplanning"},"data_attributes":null,"calculation_params":null,"icon_link":null,"link":"http://geocommons.com/overlays/206592.json","extent":[-111.797,40.3768,-111.797,40.3768],"geometry_types":["point"],"unique_name":null,"name":"American_Fork_Senior_Citizens_Center","feature_count":1,"description":"","next_feature":null,"is_raster":false,"short_classification":"Y","stats":{},"features":[{"properties":{"name":"American Fork Senior Citizens Center","balloon_text":"         <a href=\"/maps/place?cid=10138568419659174990&amp;q=American+Fork+Senior+Center&amp;hl=en&amp;ved=0CAoQ2QY&amp;sa=X&amp;ei=4cQ_T8y0CcefiQKjn7WBCw\">American Fork Senior Citizens Center</a>    54 East Main Street, American Fork, UT 84003   (801) 763-3090 ()    ‎   <a href=\"http://maps.google.com/local_url?q=http://afcity.org/Services/City/SeniorCenter/tabid/94/Default.aspx&amp;dq=American+Fork+Senior+Center&amp;sll=40.3734,-111.807&amp;sspn=0.0433561,0.0862717&amp;output=kml&amp;ie=utf-8&amp;v=2.2&amp;cv=6.1.0.5001&amp;hl=en&amp;ved=0CAsQ5AQ&amp;sa=X&amp;ei=4cQ_T8y0CcefiQKjn7WBCw&amp;s=ANYYN7kH_38FHB5x_rJjOY6OBqyspr_oow\">afcity.org</a>        Your rating:  Rate it<a></a><a href=\"javascript:void(0)\" title=\"Remove rating\"></a><b>Liked:</b><b>Disliked:</b><a href=\"/maps/place?cid=10138568419659174990&amp;q=American+Fork+Senior+Center&amp;hl=en&amp;action=openratings&amp;authuser=0\">Edit your review</a>             Photos <a href=\"https://www.google.com/accounts/ServiceLogin?service=local&amp;hl=en&amp;nui=1&amp;continue=http://maps.google.com/maps/place%3Fcid%3D10138568419659174990%26q%3DAmerican%2BFork%2BSenior%2BCenter%26hl%3Den\">Upload a photo</a>            <a href=\"/maps/user?uid=210985977147629245895&amp;hl=en&amp;gl=US&amp;ptab=5\">Manage photos</a> you have uploaded.       <a href=\"https://www.google.com/accounts/ServiceLogin?service=local&amp;hl=en&amp;nui=1&amp;continue=http://maps.google.com/maps/place%3Fcid%3D10138568419659174990%26q%3DAmerican%2BFork%2BSenior%2BCenter%26hl%3Den&amp;ved=0CAwQ1Qc&amp;sa=X&amp;ei=4cQ_T8y0CcefiQKjn7WBCw\">Be the first to upload a photo</a>                <a href=\"/maps/place?cid=10138568419659174990&amp;q=American+Fork+Senior+Center&amp;hl=en&amp;ui=earth&amp;ved=0CA0QtQU&amp;sa=X&amp;ei=4cQ_T8y0CcefiQKjn7WBCw\">View more information »</a>  AdsAdvertisement function google_ad_request_done(ads) {if (!ads.length) {return;}var doc = document;var par = window.parent;var e = doc.getElementById('pp-ads-container');while (!e) {doc = par.document || par.contentWindow.document || par.contentDocument;e = doc.getElementById('pp-ads-container');par = par.parent;}e = doc.getElementById('pp-text-ads-container');if (!e) {return;}var shouldDisplay = false;for (var i = 0; i &lt; ads.length; ++i) {if (ads[i].type != 'text') {continue;}shouldDisplay = true;var s = '&lt;a href=\"' + ads[i].url + '\" target=\"_blank\"&gt;';s += ads[i].line1 + '&lt;/a&gt;';s += '&lt;br&gt;';s += '&lt;span&gt;' + ads[i].line2 + '&lt;br&gt;';s += ads[i].line3 + '&lt;br&gt;&lt;/span&gt;';s += '&lt;span class=\"visurl\"&gt;' + ads[i].visible_url + '&lt;/span&gt;&lt;br&gt;';if (ads[i].line5) {}var ad = doc.createElement('DIV');ad.className = 'one-ad';ad.innerHTML = s;ad.style.cssFloat = 'left';ad.style['width'] = '50%';e.appendChild(ad);}var clear = doc.createElement('DIV');clear.style.clear = 'both';e.appendChild(clear);if (shouldDisplay) {e.style['display'] = 'block';}var iframe = doc.getElementById('pp-ads-iframe');if (iframe) {e.removeChild(iframe);}}google_ad_client = '';google_ad_output = 'js';google_max_num_ads = '';google_page_url = '';google_contents = '';google_hints = '';google_city = '';google_region = '';google_safe = '';google_language = 'en';google_ad_type = '';google_bid = 'cpc';google_ad_channel = '';google_image_size = '300x250';        ","id":"0"},"type":"Feature","geometry":{"type":"Point","coordinates":[-111.797134,40.376795]}}],"is_temporal":false,"author":{"url":"","metadata":null,"contact_name":null,"contact_address":null,"source":null,"contact_phone":null},"source":"","pagination":{"sort":null,"start":0,"total":1,"limit":1000000},"state":"complete","tags":"","published":"2014-08-14T23:05:52-04:00","id":206592}