{"type":"FeatureCollection","data_type":"Dataset","url_type":null,"permissions":[{"permissions":{"download":true,"view":true},"group_id":"everyone"}],"classification":null,"title":"AECOM_Addresses","count":2,"stream_id":207864,"contributor":{"url":"http://geocommons.com/users/40622","name":"russamyo"},"data_attributes":null,"calculation_params":null,"icon_link":null,"link":"http://geocommons.com/overlays/207864.json","extent":[-76.8702,39.084,-76.8418,39.1771],"geometry_types":["point"],"unique_name":null,"name":"AECOM_Addresses","feature_count":2,"description":"","next_feature":null,"is_raster":false,"short_classification":"Y","stats":{},"features":[{"properties":{"city":"Laurel","zip":"20708","geo_score":0.922,"id":"a71xs639zcgx","geo_precision":"range","address":"14504 Greenview Drive","state":"MD"},"type":"Feature","geometry":{"type":"Point","coordinates":[-76.841758,39.083969]}},{"properties":{"city":"Columbia","zip":"21046","geo_score":1.0,"id":"a71xs5y2vahk","geo_precision":"range","address":"8320 Guilford Rd","state":"MD"},"type":"Feature","geometry":{"type":"Point","coordinates":[-76.870215,39.177092]}}],"is_temporal":false,"author":{"url":"","metadata":null,"contact_name":null,"contact_address":null,"source":null,"contact_phone":null},"source":"","pagination":{"sort":null,"start":0,"total":2,"limit":1000000},"state":"complete","tags":"","published":"2014-08-15T01:10:57-04:00","id":207864}