{"type":"FeatureCollection","data_type":"Dataset","url_type":null,"permissions":[{"permissions":{"download":true,"view":true},"group_id":"everyone"}],"classification":null,"title":"004","count":1,"stream_id":209629,"contributor":{"url":"http://geocommons.com/users/39750","name":"chamaepetes"},"data_attributes":null,"calculation_params":null,"icon_link":null,"link":"http://geocommons.com/overlays/209629.json","extent":[-80.3509,-3.78046,-80.3509,-3.78046],"geometry_types":["point"],"unique_name":null,"name":"004","feature_count":1,"description":"","next_feature":null,"is_raster":false,"short_classification":"Y","stats":{},"features":[{"properties":{"name":"Pheucticus ludovicianus","id":"0"},"type":"Feature","geometry":{"type":"Point","coordinates":[-80.3508555555556,-3.78046388888889]}}],"is_temporal":false,"author":{"url":"","metadata":null,"contact_name":null,"contact_address":null,"source":null,"contact_phone":null},"source":"","pagination":{"sort":null,"start":0,"total":1,"limit":1000000},"state":"complete","tags":"","published":"2014-08-15T03:31:59-04:00","id":209629}