{"type":"FeatureCollection","data_type":"Dataset","url_type":null,"permissions":[{"permissions":{"download":true,"view":true},"group_id":"everyone"}],"classification":null,"title":"Salons","count":15,"stream_id":209976,"contributor":{"url":"http://geocommons.com/users/40103","name":"mellison"},"data_attributes":null,"calculation_params":null,"icon_link":null,"link":"http://geocommons.com/overlays/209976.json","extent":[-123.184,49.2079,-123.135,49.2917],"geometry_types":["point"],"unique_name":null,"name":"Salons","feature_count":15,"description":"","next_feature":null,"is_raster":false,"short_classification":"Y","stats":{"latitiude":{"max":49.291659,"mean":49.2613827333333,"variance":0.000462944293066713,"stdev":0.0215161402920392,"min":49.207885,"median":49.264191},"longitude":{"max":-123.135172,"mean":-123.15347,"variance":0.000254781173428639,"stdev":0.0159618662263734,"min":-123.183627,"median":-123.148449}},"features":[{"properties":{"business":"Tan de Soleil","latitiude":49.290201,"longitude":-123.137372,"id":"a74ax6257whs"},"type":"Feature","geometry":{"type":"Point","coordinates":[-123.137372,49.290201]}},{"properties":{"business":"Laund'rays on Denman","latitiude":49.291659,"longitude":-123.135172,"id":"a74ax62phz9i"},"type":"Feature","geometry":{"type":"Point","coordinates":[-123.135172,49.291659]}},{"properties":{"business":"Fabutan Sun Tan Studios","latitiude":49.268395,"longitude":-123.170105,"id":"a74ax5zmh4lg"},"type":"Feature","geometry":{"type":"Point","coordinates":[-123.170105,49.268395]}},{"properties":{"business":"Zen Sun Spa","latitiude":49.264047,"longitude":-123.167893,"id":"a74ax5sdsclq"},"type":"Feature","geometry":{"type":"Point","coordinates":[-123.167893,49.264047]}},{"properties":{"business":"Kix Tanning Salon","latitiude":49.257818,"longitude":-123.16867,"id":"a74ax5zpz7c4"},"type":"Feature","geometry":{"type":"Point","coordinates":[-123.16867,49.257818]}},{"properties":{"business":"Magicuts","latitiude":49.264191,"longitude":-123.176969,"id":"a74ax5wsahxt"},"type":"Feature","geometry":{"type":"Point","coordinates":[-123.176969,49.264191]}},{"properties":{"business":"Body Rays Tanning","latitiude":49.27246,"longitude":-123.147562,"id":"a74ax5y7e2rm"},"type":"Feature","geometry":{"type":"Point","coordinates":[-123.147562,49.27246]}},{"properties":{"business":"Urban Tanning Studio","latitiude":49.270659,"longitude":-123.146164,"id":"a74ax66exwcy"},"type":"Feature","geometry":{"type":"Point","coordinates":[-123.146164,49.270659]}},{"properties":{"business":"Infinity Salon and Spa","latitiude":49.269459,"longitude":-123.138195,"id":"a74ax66zawrj"},"type":"Feature","geometry":{"type":"Point","coordinates":[-123.138195,49.269459]}},{"properties":{"business":"Suntopia Tanning Studios","latitiude":49.268037,"longitude":-123.148449,"id":"a74ax60evm0v"},"type":"Feature","geometry":{"type":"Point","coordinates":[-123.148449,49.268037]}},{"properties":{"business":"Brazilian Glow Bar Tanning Studio","latitiude":49.26375,"longitude":-123.149022,"id":"a74ax5xx9qmc"},"type":"Feature","geometry":{"type":"Point","coordinates":[-123.149022,49.26375]}},{"properties":{"business":"Sunshine Tanning","latitiude":49.263565,"longitude":-123.137406,"id":"a74ax6447365"},"type":"Feature","geometry":{"type":"Point","coordinates":[-123.137406,49.263565]}},{"properties":{"business":"Hot Shots Sun Studio","latitiude":49.233838,"longitude":-123.154961,"id":"a74ax5whu0tc"},"type":"Feature","geometry":{"type":"Point","coordinates":[-123.154961,49.233838]}},{"properties":{"business":"Sunset Tanning Salon","latitiude":49.234777,"longitude":-123.183627,"id":"a74ax5smknn6"},"type":"Feature","geometry":{"type":"Point","coordinates":[-123.183627,49.234777]}},{"properties":{"business":"Touch of Paradise Studio","latitiude":49.207885,"longitude":-123.140483,"id":"a74ax5topx4s"},"type":"Feature","geometry":{"type":"Point","coordinates":[-123.140483,49.207885]}}],"is_temporal":false,"author":{"url":"","metadata":"","contact_name":"","contact_address":"","source":"","contact_phone":""},"source":"","pagination":{"sort":null,"start":0,"total":15,"limit":1000000},"state":"complete","tags":"","published":"2014-08-15T04:02:07-04:00","id":209976}