{"type":"FeatureCollection","data_type":"Dataset","url_type":null,"permissions":[{"permissions":{"download":true,"view":true},"group_id":"everyone"}],"classification":null,"title":"Birding in Richmond","count":3,"stream_id":212364,"contributor":{"url":"http://geocommons.com/users/32251","name":"WendiJonassen"},"data_attributes":null,"calculation_params":null,"icon_link":null,"link":"http://geocommons.com/overlays/212364.json","extent":[-92.9766,33.2535,-87.5915,44.9508],"geometry_types":["point"],"unique_name":null,"name":"Birding in Richmond","feature_count":3,"description":"This is a map of bird sightings during the Great American Backyard Bird Count","next_feature":null,"is_raster":false,"short_classification":"Y","stats":{},"features":[{"properties":{"1 parr blvd, richmond, ca":"Landfill Loop","geo_score":0.655,"900 dornan drive":"Miller Knox","china cove trail, richmond ca":"Point Pinole","id":"a62ioefv7wuo","geo_precision":"city","5755 mcbryde ave":"Wildcat Canyon"},"type":"Feature","geometry":{"type":"Point","coordinates":[-92.976603,44.950799]}},{"properties":{"1 parr blvd, richmond, ca":"Greater Scaup - 146","geo_score":0.612,"900 dornan drive":"American Avocet - 160","china cove trail, richmond ca":"American Robin -22","id":"a62ioen6qneg","geo_precision":"street","5755 mcbryde ave":"Least Sandpiper - 154"},"type":"Feature","geometry":{"type":"Point","coordinates":[-90.377494,35.359754]}},{"properties":{"1 parr blvd, richmond, ca":"Total Species - 48","geo_score":0.571,"900 dornan drive":"Total Species - 200","china cove trail, richmond ca":"Total Speceies - 17","id":"a62ioedwv8mb","geo_precision":"street","5755 mcbryde ave":"Total Species - 60"},"type":"Feature","geometry":{"type":"Point","coordinates":[-87.591537,33.253465]}}],"is_temporal":false,"author":{"url":"","metadata":"","contact_name":"","contact_address":"","source":"","contact_phone":""},"source":"","pagination":{"sort":null,"start":0,"total":3,"limit":1000000},"state":"complete","tags":"","published":"2014-08-14T18:43:03-04:00","id":212364}