{"type":"FeatureCollection","data_type":"Dataset","url_type":null,"permissions":[{"permissions":{"download":true,"view":true},"group_id":"everyone"}],"classification":null,"title":"VNM KBA PTS","count":3,"stream_id":216068,"contributor":{"url":"http://geocommons.com/users/30728","name":"jeejay70"},"data_attributes":null,"calculation_params":null,"icon_link":null,"link":"http://geocommons.com/overlays/216068.json","extent":[103.883,12.3833,108.45,22.2667],"geometry_types":["point"],"unique_name":null,"name":"VNM KBA PTS","feature_count":3,"description":"","next_feature":null,"is_raster":false,"short_classification":"Y","stats":{"SITAREA":{"max":59278,"mean":44554.3333333333,"variance":316139042.333333,"stdev":17780.2992756965,"min":24801,"median":49584},"SITALTMAX":{"max":3143,"mean":2027.33333333333,"variance":1879290.33333333,"stdev":1370.8721068478,"min":497,"median":2442},"SITLONG":{"max":108.45,"mean":106.105554444333,"variance":5.22481522296668,"stdev":2.2857854717726,"min":103.883333333,"median":105.98333},"SITLAT":{"max":22.2666666667,"mean":17.5777776666667,"variance":24.6117590910702,"stdev":4.96102399621996,"min":12.3833333333,"median":18.083333},"SITRECID":{"max":12060,"mean":12038.6666666667,"variance":377.333333333333,"stdev":19.4250697124446,"min":12022,"median":12034},"SITALTMIN":{"max":600,"mean":343.333333333333,"variance":76633.3333333333,"stdev":276.827262626594,"min":50,"median":380}},"features":[{"properties":{"SITAREA":59278,"SITALTMAX":2442,"IBASTATUS":"confirmed","SITLONG":108.45,"SITLAT":12.3833333333,"SITINTERNA":"Chu Yang Sin","SITRECID":12034,"SITALTMIN":600,"SITFINALCO":"VN030","CTYBIRDLIF":"Vietnam","id":"0","SUBDESC":"Dak Lak","KBASTATUS":"confirmed","SITNATIONA":"Chu Yang Sin"},"type":"Feature","geometry":{"type":"Point","coordinates":[108.45,12.3833333333333]}},{"properties":{"SITAREA":49584,"SITALTMAX":3143,"IBASTATUS":"confirmed","SITLONG":103.883333333,"SITLAT":22.2666666667,"SITINTERNA":"Fan Si Pan","SITRECID":12060,"SITALTMIN":380,"SITFINALCO":"VN057","CTYBIRDLIF":"Vietnam","id":"1","SUBDESC":"Lai Chau, Lao Cai","KBASTATUS":"confirmed","SITNATIONA":"Fan Si Pan"},"type":"Feature","geometry":{"type":"Point","coordinates":[103.883333333,22.2666666667]}},{"properties":{"SITAREA":24801,"SITALTMAX":497,"IBASTATUS":"confirmed","SITLONG":105.98333,"SITLAT":18.083333,"SITINTERNA":"Ke Go","SITRECID":12022,"SITALTMIN":50,"SITFINALCO":"VN019","CTYBIRDLIF":"Vietnam","id":"2","SUBDESC":"Ha Tinh","KBASTATUS":"confirmed","SITNATIONA":"Ke Go"},"type":"Feature","geometry":{"type":"Point","coordinates":[105.98333,18.083333]}}],"is_temporal":false,"author":{"url":"","metadata":"","contact_name":"","contact_address":"","source":"","contact_phone":""},"source":"","pagination":{"sort":null,"start":0,"total":3,"limit":1000000},"state":"complete","tags":"chm,conservation,kba,priority,vnm","published":"2014-08-15T00:21:05-04:00","id":216068}