{"type":"FeatureCollection","data_type":"Dataset","url_type":null,"permissions":[{"permissions":{"download":true,"view":true},"group_id":"everyone"}],"classification":null,"title":"ZIPS","count":13,"stream_id":216170,"contributor":{"url":"http://geocommons.com/users/41911","name":"salazar.jamesbryan"},"data_attributes":null,"calculation_params":null,"icon_link":null,"link":"http://geocommons.com/overlays/216170.json","extent":[-72.6048,42.1707,-70.1987,43.6783],"geometry_types":["point"],"unique_name":null,"name":"ZIPS","feature_count":13,"description":"","next_feature":null,"is_raster":false,"short_classification":"Y","stats":{"mean per capita (in pesos)":{"max":29669,"mean":10672.4615384615,"variance":38912417.2692308,"stdev":6237.98182661915,"min":5620,"median":10425}},"features":[{"properties":{"zip":"2900","geo_score":0.0,"mean per capita (in pesos)":6607,"id":"a69w9mybdgai","geo_precision":"unmatched"},"type":"Feature","geometry":null},{"properties":{"zip":"3500","geo_score":0.0,"mean per capita (in pesos)":6816,"id":"a69w9n3dtrqy","geo_precision":"unmatched"},"type":"Feature","geometry":null},{"properties":{"zip":"2300","geo_score":0.0,"mean per capita (in pesos)":10943,"id":"a69w9mxr90zc","geo_precision":"unmatched"},"type":"Feature","geometry":null},{"properties":{"zip":"4109","geo_score":0.714,"mean per capita (in pesos)":13260,"id":"a69w9msd3bce","geo_precision":"zip"},"type":"Feature","geometry":{"type":"Point","coordinates":[-70.198742,43.678339]}},{"properties":{"zip":"4500","geo_score":0.0,"mean per capita (in pesos)":5620,"id":"a69w9mu08juj","geo_precision":"unmatched"},"type":"Feature","geometry":null},{"properties":{"zip":"9205","geo_score":0.0,"mean per capita (in pesos)":10425,"id":"a69w9mx0w1tk","geo_precision":"unmatched"},"type":"Feature","geometry":null},{"properties":{"zip":"6000","geo_score":0.0,"mean per capita (in pesos)":11307,"id":"a69w9n080eay","geo_precision":"unmatched"},"type":"Feature","geometry":null},{"properties":{"zip":"6500","geo_score":0.0,"mean per capita (in pesos)":5809,"id":"a69w9mt0ip1v","geo_precision":"unmatched"},"type":"Feature","geometry":null},{"properties":{"zip":"7100","geo_score":0.0,"mean per capita (in pesos)":8169,"id":"a69w9n1ex2qc","geo_precision":"unmatched"},"type":"Feature","geometry":null},{"properties":{"zip":"8700","geo_score":0.0,"mean per capita (in pesos)":10543,"id":"a69w9mrmqtjy","geo_precision":"unmatched"},"type":"Feature","geometry":null},{"properties":{"zip":"8100","geo_score":0.0,"mean per capita (in pesos)":12069,"id":"a69w9n1ooxz0","geo_precision":"unmatched"},"type":"Feature","geometry":null},{"properties":{"zip":"9400","geo_score":0.0,"mean per capita (in pesos)":7505,"id":"a69w9myxj3b8","geo_precision":"unmatched"},"type":"Feature","geometry":null},{"properties":{"zip":"1101","geo_score":0.714,"mean per capita (in pesos)":29669,"id":"a69w9msam8jp","geo_precision":"zip"},"type":"Feature","geometry":{"type":"Point","coordinates":[-72.604842,42.170731]}}],"is_temporal":false,"author":{"url":"","metadata":"","contact_name":"","contact_address":"","source":"","contact_phone":""},"source":"","pagination":{"sort":null,"start":0,"total":13,"limit":1000000},"state":"complete","tags":"","published":"2014-08-15T00:29:50-04:00","id":216170}