{"type":"FeatureCollection","data_type":"Dataset","url_type":null,"permissions":[{"permissions":{"download":true,"view":true},"group_id":"everyone"}],"classification":null,"title":"Airport","count":1,"stream_id":216323,"contributor":{"url":"http://geocommons.com/users/42055","name":"market"},"data_attributes":null,"calculation_params":null,"icon_link":null,"link":"http://geocommons.com/overlays/216323.json","extent":[39.8005,40.9921,39.8005,40.9921],"geometry_types":["point"],"unique_name":null,"name":"Airport","feature_count":1,"description":"","next_feature":null,"is_raster":false,"short_classification":"Y","stats":{"Id":{"max":0,"min":0,"median":0}},"features":[{"properties":{"Id":0,"adi":"AIRPORT","id":"0"},"type":"Feature","geometry":{"type":"Point","coordinates":[39.8005119827015,40.9920781558346]}}],"is_temporal":false,"author":{"url":"","metadata":null,"contact_name":"","contact_address":", , , ","source":"","contact_phone":""},"source":"","pagination":{"sort":null,"start":0,"total":1,"limit":1000000},"state":"complete","tags":"","published":"2014-08-15T00:39:23-04:00","id":216323}