{"type":"FeatureCollection","data_type":"Dataset","url_type":null,"permissions":[{"permissions":{"download":true,"view":true},"group_id":"everyone"}],"classification":null,"title":"nations_4","count":4,"stream_id":217487,"contributor":{"url":"http://geocommons.com/users/39447","name":"sam.felipe"},"data_attributes":null,"calculation_params":null,"icon_link":null,"link":"http://geocommons.com/overlays/217487.json","extent":[-118.326,32.7617,-117.167,33.9953],"geometry_types":["point"],"unique_name":null,"name":"nations_4","feature_count":4,"description":"","next_feature":null,"is_raster":false,"short_classification":"Y","stats":{"competitor code":{"max":18,"mean":18.0,"variance":0.0,"stdev":0.0,"min":18,"median":18},"mode":{"max":4,"mean":4.0,"variance":0.0,"stdev":0.0,"min":4,"median":4},"vp code":{"max":6,"mean":2.5,"variance":5.66666666666667,"stdev":2.38047614284762,"min":1,"median":2}},"features":[{"properties":{"city":"Torrance","name of competitor":"Nations Title","zip":"90504","competitor code":18,"mode":4,"geo_score":0.902,"street address":"18411 Crenshaw Blvd.","vp name":"Ed","vp code":1,"id":"a6hqwszuf8dj","geo_precision":"range"},"type":"Feature","geometry":{"type":"Point","coordinates":[-118.326446,33.864543]}},{"properties":{"city":"Norwalk","name of competitor":"Nations Title","zip":"90650","competitor code":18,"mode":4,"geo_score":0.522,"street address":"12901 Norwalk Blvd. #200","vp name":"Ed","vp code":1,"id":"a6hqwsu0hpfm","geo_precision":"street"},"type":"Feature","geometry":{"type":"Point","coordinates":[-118.072679,33.931658]}},{"properties":{"city":"San Diego","name of competitor":"Nations Title","zip":"92108","competitor code":18,"mode":4,"geo_score":0.878,"street address":"591 Camino De La Reina # 100","vp name":"Vincent","vp code":2,"id":"a6hqwsxkreoq","geo_precision":"range"},"type":"Feature","geometry":{"type":"Point","coordinates":[-117.166631,32.761699]}},{"properties":{"city":"Riverside","name of competitor":"Nations Title","zip":"92507","competitor code":18,"mode":4,"geo_score":0.827,"street address":"1825 Chicago Ave.","vp name":"Guy","vp code":6,"id":"a6hqwsxxrsh8","geo_precision":"range"},"type":"Feature","geometry":{"type":"Point","coordinates":[-117.348422,33.995254]}}],"is_temporal":false,"author":{"url":"","metadata":null,"contact_name":null,"contact_address":null,"source":null,"contact_phone":null},"source":"","pagination":{"sort":null,"start":0,"total":4,"limit":1000000},"state":"complete","tags":"","published":"2014-08-15T02:22:42-04:00","id":217487}