{"type":"FeatureCollection","data_type":"Dataset Analysis","url_type":null,"permissions":[{"permissions":{"download":true,"view":true},"group_id":"everyone"}],"classification":null,"title":"AddressEduIntersect","count":4,"stream_id":217516,"contributor":{"url":"http://geocommons.com/users/42231","name":"jolieberman"},"data_attributes":null,"calculation_params":{"calculation":"intersect","input":{"columns":[{"id":"217512"},{"id":"203767"}],"merge":"combine"}},"icon_link":null,"link":"http://geocommons.com/overlays/217516.json","extent":[-119.808,32.7564,-75.4958,42.9621],"geometry_types":["point"],"unique_name":null,"name":"AddressEduIntersect","feature_count":4,"description":"Dataset created by the intersection of 1) AddressTest and 2) Aggregation of Highest Education Level to Lowest Income, USA, 2007 into USA Counties ","next_feature":null,"is_raster":false,"short_classification":"Y","stats":{"result":{"max":200,"mean":200.0,"variance":0.0,"stdev":0.0,"min":200,"median":200},"latitude":{"max":42.961997,"mean":38.62158985,"variance":12.6744476264637,"stdev":3.56011904667016,"min":34.83505,"median":39.8764754},"geo_score":{"max":1.0,"mean":0.77525,"variance":0.0389049166666667,"stdev":0.197243293084116,"min":0.54,"median":0.854},"CBSAFP":{"max":21700,"min":21700,"median":21700},"longitude":{"max":-75.5195004,"mean":-90.823754025,"variance":391.152749270542,"stdev":19.7775819874559,"min":-119.806685,"median":-82.2999757},"count":{"max":0,"mean":0.0,"variance":0.0,"stdev":0.0,"min":0,"median":0},"quality":{"max":9,"mean":8.25,"variance":2.25,"stdev":1.5,"min":6,"median":9}},"features":[{"properties":{"NAME":"Kent","result":200,"name":"Fort Worth","latitude":36.812837,"FUNCSTAT":"A","METDIVFP":null,"MTFCC":"G4020","CLASSFP":"H1","number":"(817) 347-3300","LSAD":"06","COUNTYNS":"01383917","geo_score":1.0,"CBSAFP":null,"STATEFP":"48","count":0,"longitude":-119.806685,"id":"a6gw445rsbb9","CSAFP":null,"COUNTYFP":"263","geo_precision":"range","quality":9,"address":"201 Main St., Ste. 1501 Fort Worth, TX 76102","NAMELSAD":"Kent County","CNTYIDFP":"48263","lead":"Buechele, Bill J (US - Fort Worth)"},"type":"Feature","geometry":{"type":"Point","coordinates":[-97.332428,32.756448]}},{"properties":{"NAME":"Humboldt","result":200,"name":"Fresno","latitude":39.8764754,"FUNCSTAT":"A","METDIVFP":null,"MTFCC":"G4020","CLASSFP":"H1","number":"(559) 449-6300","LSAD":"06","COUNTYNS":"01681908","geo_score":0.707,"CBSAFP":21700,"STATEFP":"06","count":0,"longitude":-75.5195004,"id":"a6gw443qrw9d","CSAFP":null,"COUNTYFP":"023","geo_precision":"range","quality":6,"address":"5250 N. Palm Ave., Ste. 300 Fresno, CA 93704","NAMELSAD":"Humboldt County","CNTYIDFP":"06023","lead":"Andersen, Carole (US - Fresno)"},"type":"Feature","geometry":{"type":"Point","coordinates":[-119.808401,36.812917]}},{"properties":{"NAME":"Fulton","result":200,"name":"Glen Mills","latitude":42.961997,"FUNCSTAT":"A","METDIVFP":null,"MTFCC":"G4020","CLASSFP":"H1","number":"(610) 479-3900","LSAD":"06","COUNTYNS":"01213671","geo_score":0.54,"CBSAFP":null,"STATEFP":"42","count":0,"longitude":-85.668855,"id":"a6gw4437xqkc","CSAFP":null,"COUNTYFP":"057","geo_precision":"street","quality":9,"address":"1 Braxton Way Glen Mills, PA 19342","NAMELSAD":"Fulton County","CNTYIDFP":"42057","lead":"Wiest, Tim (US - Harrisburg)"},"type":"Feature","geometry":{"type":"Point","coordinates":[-75.495756,39.916903]}},{"properties":{"NAME":"Luce","result":200,"name":"Grand Rapids","latitude":34.83505,"FUNCSTAT":"A","METDIVFP":null,"MTFCC":"G4020","CLASSFP":"H1","number":"(616) 336-7900","LSAD":"06","COUNTYNS":"01622990","geo_score":0.854,"CBSAFP":null,"STATEFP":"26","count":0,"longitude":-82.2999757,"id":"a6gw44doctz2","CSAFP":null,"COUNTYFP":"095","geo_precision":"range","quality":9,"address":"38 Commerce SW Suite 600 Grand Rapids, MI 49503","NAMELSAD":"Luce County","CNTYIDFP":"26095","lead":"Moran, Lou (US - Grand Rapids)"},"type":"Feature","geometry":{"type":"Point","coordinates":[-85.669175,42.96213]}}],"is_temporal":false,"author":{"url":"","metadata":"","contact_name":"","contact_address":"","source":"","contact_phone":""},"source":"","pagination":{"sort":null,"start":0,"total":4,"limit":1000000},"state":"complete","tags":"","published":"2014-08-15T02:24:32-04:00","id":217516}