{"type":"FeatureCollection","data_type":"Dataset","url_type":null,"permissions":[{"permissions":{"download":true,"view":true},"group_id":"everyone"}],"classification":null,"title":"16318","count":1,"stream_id":218481,"contributor":{"url":"http://geocommons.com/users/40409","name":"jecabrer"},"data_attributes":null,"calculation_params":null,"icon_link":null,"link":"http://geocommons.com/overlays/218481.json","extent":[-90.3579,-0.714804,-90.3579,-0.714804],"geometry_types":["point"],"unique_name":null,"name":"16318","feature_count":1,"description":"","next_feature":null,"is_raster":false,"short_classification":"Y","stats":{},"features":[{"properties":{"name":"Datos prediales","description":"\nClave Catastral:  2003511400048 Area:    1.22ha. Situación Legal Predio:  SIN TITULO Forma Adquisición:  SIN INFORMACION Accesibilidad a Servicios BásicosAgua:  NO TIENE Energía Eléctrica:  ENERGIA ELECTRICA PUBLICA Telefonía Fija:  NO TIENE Internet:  NO TIENE Alcantarillado:  NO TIENE Tipo de Riego:  NO TIENE Información GeneralUso de suelo:  PECUARIO Vias acceso predio:  LASTRADA Construcciones e inst.:  NO TIENE","id":"0"},"type":"Feature","geometry":{"type":"Point","coordinates":[-90.357919,-0.714804]}}],"is_temporal":false,"author":{"url":"","metadata":null,"contact_name":null,"contact_address":null,"source":null,"contact_phone":null},"source":"","pagination":{"sort":null,"start":0,"total":1,"limit":1000000},"state":"complete","tags":"","published":"2014-08-15T03:18:45-04:00","id":218481}