{"type":"FeatureCollection","data_type":"Dataset","url_type":null,"permissions":[{"permissions":{"download":true,"view":true},"group_id":"everyone"}],"classification":null,"title":"Ed_-_Orange_Coast_-_ran_March_23rd","count":1,"stream_id":219235,"contributor":{"url":"http://geocommons.com/users/39447","name":"sam.felipe"},"data_attributes":null,"calculation_params":null,"icon_link":null,"link":"http://geocommons.com/overlays/219235.json","extent":[-118.026,33.8838,-118.026,33.8838],"geometry_types":["point"],"unique_name":null,"name":"Ed_-_Orange_Coast_-_ran_March_23rd","feature_count":1,"description":"","next_feature":null,"is_raster":false,"short_classification":"Y","stats":{"competitor code":{"max":24,"min":24,"median":24},"mode":{"max":8,"min":8,"median":8},"vp code":{"max":1,"min":1,"median":1}},"features":[{"properties":{"city":"La Mirada","name of competitor":"Orange Coast Title","zip":"90638","competitor code":24,"mode":8,"geo_score":0.756,"street address":"14320 Firestone Blvd.","vp name":"Ed","vp code":1,"id":"a62ppiwfetgp","geo_precision":"range"},"type":"Feature","geometry":{"type":"Point","coordinates":[-118.025852,33.883802]}}],"is_temporal":false,"author":{"url":"","metadata":null,"contact_name":null,"contact_address":null,"source":null,"contact_phone":null},"source":"","pagination":{"sort":null,"start":0,"total":1,"limit":1000000},"state":"complete","tags":"","published":"2014-08-15T03:59:47-04:00","id":219235}