{"type":"FeatureCollection","data_type":"Dataset","url_type":null,"permissions":[{"permissions":{"download":true,"view":true},"group_id":"everyone"}],"classification":null,"title":"Ed_-_Fidelity_-_ran_March_23rd","count":4,"stream_id":219230,"contributor":{"url":"http://geocommons.com/users/39447","name":"sam.felipe"},"data_attributes":null,"calculation_params":null,"icon_link":null,"link":"http://geocommons.com/overlays/219230.json","extent":[-119.214,33.8085,-118.151,34.2728],"geometry_types":["point"],"unique_name":null,"name":"Ed_-_Fidelity_-_ran_March_23rd","feature_count":4,"description":"","next_feature":null,"is_raster":false,"short_classification":"Y","stats":{"competitor code":{"max":11,"mean":11.0,"variance":0.0,"stdev":0.0,"min":11,"median":11},"mode":{"max":42,"mean":42.0,"variance":0.0,"stdev":0.0,"min":42,"median":42},"vp code":{"max":1,"mean":1.0,"variance":0.0,"stdev":0.0,"min":1,"median":1}},"features":[{"properties":{"city":"Long Beach","name of competitor":"Fidelity National Title","zip":"90806","competitor code":11,"mode":42,"geo_score":0.511,"street address":"3760 Kilroy Airport Way","vp name":"Ed","vp code":1,"id":"a64n83mlj00h","geo_precision":"street"},"type":"Feature","geometry":{"type":"Point","coordinates":[-118.151341,33.808476]}},{"properties":{"city":"Westlake Village","name of competitor":"Fidelity National Title","zip":"91361","competitor code":11,"mode":42,"geo_score":0.824,"street address":"950 Hampshire Rd #103","vp name":"Ed","vp code":1,"id":"a64n83ubt0qt","geo_precision":"range"},"type":"Feature","geometry":{"type":"Point","coordinates":[-118.836717,34.168166]}},{"properties":{"city":"Oxnard","name of competitor":"Fidelity National Title","zip":"93035","competitor code":11,"mode":42,"geo_score":0.821,"street address":"600 South Victoria Ave. #600","vp name":"Ed","vp code":1,"id":"a64n83r8x0pi","geo_precision":"range"},"type":"Feature","geometry":{"type":"Point","coordinates":[-119.213883,34.272807]}},{"properties":{"city":"Van Nuys","name of competitor":"Fidelity National Title","zip":"91411","competitor code":11,"mode":42,"geo_score":0.707,"street address":"6060 Sepulveda Blvd. #100","vp name":"Ed","vp code":1,"id":"a64n83myggux","geo_precision":"street"},"type":"Feature","geometry":{"type":"Point","coordinates":[-118.466161,34.164847]}}],"is_temporal":false,"author":{"url":"","metadata":null,"contact_name":null,"contact_address":null,"source":null,"contact_phone":null},"source":"","pagination":{"sort":null,"start":0,"total":4,"limit":1000000},"state":"complete","tags":"","published":"2014-08-15T03:59:19-04:00","id":219230}