{"type":"FeatureCollection","data_type":"Dataset","url_type":null,"permissions":[{"permissions":{"download":true,"view":true},"group_id":"everyone"}],"classification":null,"title":"Ed_-_Old_Republic_-_ran_March_23rd","count":1,"stream_id":219234,"contributor":{"url":"http://geocommons.com/users/39447","name":"sam.felipe"},"data_attributes":null,"calculation_params":null,"icon_link":null,"link":"http://geocommons.com/overlays/219234.json","extent":[-118.255,34.1587,-118.255,34.1587],"geometry_types":["point"],"unique_name":null,"name":"Ed_-_Old_Republic_-_ran_March_23rd","feature_count":1,"description":"","next_feature":null,"is_raster":false,"short_classification":"Y","stats":{"competitor code":{"max":23,"min":23,"median":23},"mode":{"max":45,"min":45,"median":45},"vp code":{"max":1,"min":1,"median":1}},"features":[{"properties":{"city":"Glendale","name of competitor":"Old Republic Title","zip":"91203","competitor code":23,"mode":45,"geo_score":0.708,"street address":"101 North Brand Blvd. #1400","vp name":"Ed","vp code":1,"id":"a638vw9b58r2","geo_precision":"street"},"type":"Feature","geometry":{"type":"Point","coordinates":[-118.255149,34.158663]}}],"is_temporal":false,"author":{"url":"","metadata":null,"contact_name":null,"contact_address":null,"source":null,"contact_phone":null},"source":"","pagination":{"sort":null,"start":0,"total":1,"limit":1000000},"state":"complete","tags":"","published":"2014-08-15T03:59:47-04:00","id":219234}