{"type":"FeatureCollection","data_type":"Dataset","url_type":null,"permissions":[{"permissions":{"download":true,"view":true},"group_id":"everyone"}],"classification":null,"title":"Lower_North_Fork_Wildfire_5","count":1,"stream_id":221164,"contributor":{"url":"http://geocommons.com/users/28467","name":"bheberto"},"data_attributes":null,"calculation_params":null,"icon_link":null,"link":"http://geocommons.com/overlays/221164.json","extent":[-105.306,39.5194,-105.306,39.5194],"geometry_types":["point"],"unique_name":null,"name":"Lower_North_Fork_Wildfire_5","feature_count":1,"description":"","next_feature":null,"is_raster":false,"short_classification":"Y","stats":{},"features":[{"properties":{"name":"PIO Available to Answer ?'s till Early Evening","description":"Have a question?  An Incident Management Team Public Information Officer is available to answer your questions.  Location is at the Staples Parking Lot located at Highway 285 and Kitty Road.  The PIO will remain there throughout the afternoon.","id":"0"},"type":"Feature","geometry":{"type":"Point","coordinates":[-105.30584,39.519371]}}],"is_temporal":false,"author":{"url":"","metadata":null,"contact_name":null,"contact_address":null,"source":null,"contact_phone":null},"source":"","pagination":{"sort":null,"start":0,"total":1,"limit":1000000},"state":"complete","tags":"","published":"2014-08-14T16:21:38-04:00","id":221164}