{"type":"FeatureCollection","data_type":"Dataset","url_type":null,"permissions":[{"permissions":{"download":true,"view":true},"group_id":"everyone"}],"classification":null,"title":"Otogar","count":1,"stream_id":222522,"contributor":{"url":"http://geocommons.com/users/43069","name":"yukseklisanss"},"data_attributes":null,"calculation_params":null,"icon_link":null,"link":"http://geocommons.com/overlays/222522.json","extent":[39.7515,40.9969,39.7515,40.9969],"geometry_types":["point"],"unique_name":null,"name":"Otogar","feature_count":1,"description":"","next_feature":null,"is_raster":false,"short_classification":"Y","stats":{"Id":{"max":0,"min":0,"median":0}},"features":[{"properties":{"Id":0,"adi":"TRABZON OTOGARI","id":"0"},"type":"Feature","geometry":{"type":"Point","coordinates":[39.7514716176092,40.9969331489638]}}],"is_temporal":false,"author":{"url":"","metadata":"","contact_name":"","contact_address":", , , ","source":"","contact_phone":""},"source":"","pagination":{"sort":null,"start":0,"total":1,"limit":1000000},"state":"complete","tags":"","published":"2014-08-14T18:21:15-04:00","id":222522}