{"type":"FeatureCollection","data_type":"Dataset","url_type":null,"permissions":[{"permissions":{"download":true,"view":true},"group_id":"everyone"}],"classification":null,"title":"goodline","count":2,"stream_id":223738,"contributor":{"url":"http://geocommons.com/users/42001","name":"fredkeet"},"data_attributes":null,"calculation_params":null,"icon_link":null,"link":"http://geocommons.com/overlays/223738.json","extent":[-118.399,34.0293,-118.399,34.0293],"geometry_types":["point"],"unique_name":null,"name":"goodline","feature_count":2,"description":"","next_feature":null,"is_raster":false,"short_classification":"Y","stats":{"latitude":{"max":34.029334,"min":34.029334,"median":34.029334},"impressions":{"max":0,"min":0,"median":0},"clicks":{"max":0,"min":0,"median":0},"longitude":{"max":-118.399406,"min":-118.399406,"median":-118.399406}},"features":[{"properties":{"latitude":"\\N","impressions":"0","clicks":"0","location_id":"\\N","longitude":"\\N","id":"0","location_name":"-118.399406"},"type":"Feature","geometry":null},{"properties":{"latitude":34.029334,"impressions":0,"clicks":0,"location_id":"4","longitude":-118.399406,"id":"a62h7a6qoi9k","location_name":"L"},"type":"Feature","geometry":{"type":"Point","coordinates":[-118.399406,34.029334]}}],"is_temporal":false,"author":{"url":"","metadata":"","contact_name":"","contact_address":"","source":"","contact_phone":""},"source":"","pagination":{"sort":null,"start":0,"total":2,"limit":1000000},"state":"complete","tags":"","published":"2014-08-14T19:40:59-04:00","id":223738}