{"type":"FeatureCollection","data_type":"Dataset","url_type":null,"permissions":[{"permissions":{"download":true,"view":true},"group_id":"everyone"}],"classification":null,"title":"kuria.shp POINTS","count":4,"stream_id":225549,"contributor":{"url":"http://geocommons.com/users/15182","name":"xendox"},"data_attributes":null,"calculation_params":null,"icon_link":null,"link":"http://geocommons.com/overlays/225549.json","extent":[25.7711,45.7958,25.9355,45.8418],"geometry_types":["point"],"unique_name":null,"name":"kuria.shp POINTS","feature_count":4,"description":"","next_feature":null,"is_raster":false,"short_classification":"Y","stats":{"Id":{"max":0,"mean":0.0,"variance":0.0,"stdev":0.0,"min":0,"median":0}},"features":[{"properties":{"Denumire":null,"Id":0,"LAYER":"Unknown Point Feature","id":"a639ewaa4qhr","Nev":null},"type":"Feature","geometry":{"type":"Point","coordinates":[25.9355230698251,45.8417757682341]}},{"properties":{"Denumire":null,"Id":0,"LAYER":"Unknown Point Feature","id":"a639ewivgmyy","Nev":null},"type":"Feature","geometry":{"type":"Point","coordinates":[25.7711241878972,45.7958063085784]}},{"properties":{"Denumire":null,"Id":0,"LAYER":"Unknown Point Feature","id":"a639ewl9hk4g","Nev":null},"type":"Feature","geometry":{"type":"Point","coordinates":[25.9321894153444,45.8413388373382]}},{"properties":{"Denumire":null,"Id":0,"LAYER":"Unknown Point Feature","id":"a639ewab3w99","Nev":null},"type":"Feature","geometry":{"type":"Point","coordinates":[25.8449104566575,45.7989945100239]}}],"is_temporal":false,"author":{"url":"","metadata":"","contact_name":"","contact_address":"","source":"","contact_phone":""},"source":"","pagination":{"sort":null,"start":0,"total":4,"limit":1000000},"state":"complete","tags":"","published":"2014-08-14T21:44:34-04:00","id":225549}