{"type":"FeatureCollection","data_type":"Dataset","url_type":null,"permissions":[{"permissions":{"download":true,"view":true},"group_id":"everyone"}],"classification":null,"title":"test_v2","count":3,"stream_id":226921,"contributor":{"url":"http://geocommons.com/users/43759","name":"elruso"},"data_attributes":null,"calculation_params":null,"icon_link":null,"link":"http://geocommons.com/overlays/226921.json","extent":[-69.2578,-44.7155,-58.9746,-28.9216],"geometry_types":["point"],"unique_name":null,"name":"test_v2","feature_count":3,"description":"","next_feature":null,"is_raster":false,"short_classification":"Y","stats":{},"features":[{"properties":{"name":"punto 1","description":"sarasa punto 1","id":"0"},"type":"Feature","geometry":{"type":"Point","coordinates":[-58.974609,-36.03133]}},{"properties":{"name":"punto 2","description":"sarasa punto 2","id":"1"},"type":"Feature","geometry":{"type":"Point","coordinates":[-59.589844,-28.921631]}},{"properties":{"name":"punto 3","description":"sarasa punto 3","id":"2"},"type":"Feature","geometry":{"type":"Point","coordinates":[-69.257812,-44.715515]}}],"is_temporal":false,"author":{"url":"","metadata":null,"contact_name":null,"contact_address":null,"source":null,"contact_phone":null},"source":"","pagination":{"sort":null,"start":0,"total":3,"limit":1000000},"state":"complete","tags":"","published":"2014-08-14T23:32:19-04:00","id":226921}