{"type":"FeatureCollection","data_type":"Dataset","url_type":null,"permissions":[{"permissions":{"download":true,"view":true},"group_id":"everyone"}],"classification":null,"title":"Workbook6","count":4,"stream_id":227107,"contributor":{"url":"http://geocommons.com/users/42555","name":"dantzman"},"data_attributes":null,"calculation_params":null,"icon_link":null,"link":"http://geocommons.com/overlays/227107.json","extent":[-81.9748,33.471,-71.0598,43.5181],"geometry_types":["point"],"unique_name":null,"name":"Workbook6","feature_count":4,"description":"","next_feature":null,"is_raster":false,"short_classification":"Y","stats":{"date":{"max":"1801/02/20 23:59:54 -0456","mean":"1801/02/19 11:59:54 -0456","variance":12441600000.0,"stdev":111541.920370774,"min":"1801/02/17 23:59:54 -0456","median":"1801/02/19 23:59:54 -0456"}},"features":[{"properties":{"city":"New York","date":{"end_time":"1801/02/19 00:00:00 -0456","original":"2/18/1801","granularity":"day","time":"1801/02/18 00:00:00 -0456"},"geo_score":0.857,"id":"a62b2t0mardb","geo_precision":"city","state":"New York"},"type":"Feature","geometry":{"type":"Point","coordinates":[-74.005973,40.714269]}},{"properties":{"city":"Boston","date":{"end_time":"1801/02/20 00:00:00 -0456","original":"2/19/1801","granularity":"day","time":"1801/02/19 00:00:00 -0456"},"geo_score":0.857,"id":"a62b2t6qf3kt","geo_precision":"city","state":"Massachusetts"},"type":"Feature","geometry":{"type":"Point","coordinates":[-71.059773,42.358431]}},{"properties":{"city":"Augusta","date":{"end_time":"1801/02/21 00:00:00 -0456","original":"2/20/1801","granularity":"day","time":"1801/02/20 00:00:00 -0456"},"geo_score":0.857,"id":"a62b2t6krzdq","geo_precision":"city","state":"Georgia"},"type":"Feature","geometry":{"type":"Point","coordinates":[-81.974838,33.47097]}},{"properties":{"city":"Windsor","date":{"end_time":"1801/02/22 00:00:00 -0456","original":"2/21/1801","granularity":"day","time":"1801/02/21 00:00:00 -0456"},"geo_score":0.857,"id":"a62b2t8iww5c","geo_precision":"city","state":"Vermont"},"type":"Feature","geometry":{"type":"Point","coordinates":[-72.418059,43.5181]}}],"is_temporal":true,"author":{"url":"","metadata":"","contact_name":"","contact_address":"","source":"","contact_phone":""},"source":"","pagination":{"sort":null,"start":0,"total":4,"limit":1000000},"state":"complete","tags":"","published":"2014-08-14T23:46:35-04:00","id":227107}