{"type":"FeatureCollection","data_type":"Dataset","url_type":null,"permissions":[{"permissions":{"download":true,"view":true},"group_id":"everyone"}],"classification":null,"title":"Star Smiles","count":1,"stream_id":230520,"contributor":{"url":"http://geocommons.com/users/27269","name":"wadestaylor"},"data_attributes":null,"calculation_params":null,"icon_link":null,"link":"http://geocommons.com/overlays/230520.json","extent":[-115.124,36.1147,-115.124,36.1147],"geometry_types":["point"],"unique_name":null,"name":"Star Smiles","feature_count":1,"description":"","next_feature":null,"is_raster":false,"short_classification":"Y","stats":{},"features":[{"properties":{"city":"Las Vegas,","zip":"89119","geo_score":0.779,"street address":"2110 E Flamingo Rd Suite 100","provider name":"Star Smiles","id":"a63816rd0e7e","geo_precision":"range","state":"NV"},"type":"Feature","geometry":{"type":"Point","coordinates":[-115.123734,36.114649]}}],"is_temporal":false,"author":{"url":"","metadata":"","contact_name":"","contact_address":"","source":"","contact_phone":""},"source":"","pagination":{"sort":null,"start":0,"total":1,"limit":1000000},"state":"complete","tags":"","published":"2014-08-14T15:34:27-04:00","id":230520}