{"type":"FeatureCollection","data_type":"Dataset","url_type":null,"permissions":[{"permissions":{"download":true,"view":true},"group_id":"everyone"}],"classification":null,"title":"test1","count":3,"stream_id":233427,"contributor":{"url":"http://geocommons.com/users/44421","name":"fabi1986"},"data_attributes":null,"calculation_params":null,"icon_link":null,"link":"http://geocommons.com/overlays/233427.json","extent":[-72.6204,42.1015,-72.5898,42.1918],"geometry_types":["point"],"unique_name":null,"name":"test1","feature_count":3,"description":"","next_feature":null,"is_raster":false,"short_classification":"Y","stats":{},"features":[{"properties":{"city":"Vienna","name":"TU Wien","zip":"1040","geo_score":0.743,"adress":"Karlsplatz","id":"a62327dx4sb3","geo_precision":"zip","state":"Vienna"},"type":"Feature","geometry":{"type":"Point","coordinates":[-72.620368,42.191759]}},{"properties":{"city":"Vienna","name":"Wirtschaftsuni Wien","zip":"1090","geo_score":0.724,"adress":"Augasse","id":"a62327qhzmlp","geo_precision":"zip","state":"Vienna"},"type":"Feature","geometry":{"type":"Point","coordinates":[-72.604842,42.170731]}},{"properties":{"city":"Vienna","name":"Gasometer","zip":"1110","geo_score":0.727,"adress":"Guglgasse","id":"a62327hbzvii","geo_precision":"zip","state":"Vienna"},"type":"Feature","geometry":{"type":"Point","coordinates":[-72.589811,42.101483]}}],"is_temporal":false,"author":{"url":"","metadata":"","contact_name":"","contact_address":"","source":"","contact_phone":""},"source":"","pagination":{"sort":null,"start":0,"total":3,"limit":1000000},"state":"complete","tags":"","published":"2014-08-14T19:23:57-04:00","id":233427}