{"type":"FeatureCollection","data_type":"Dataset","url_type":null,"permissions":[{"permissions":{"download":true,"view":true},"group_id":"everyone"}],"classification":null,"title":"deletedplace","count":1,"stream_id":236405,"contributor":{"url":"http://geocommons.com/users/44771","name":"pesmcoe"},"data_attributes":null,"calculation_params":null,"icon_link":null,"link":"http://geocommons.com/overlays/236405.json","extent":[-2.93053,59.0147,-2.93053,59.0147],"geometry_types":["point"],"unique_name":null,"name":"deletedplace","feature_count":1,"description":"","next_feature":null,"is_raster":false,"short_classification":"Y","stats":{"woeiddeletedplace":{"max":12696205,"min":12696205,"median":12696205},"latitude":{"max":59.01469,"min":59.01469,"median":59.01469},"longitude":{"max":-2.93053,"min":-2.93053,"median":-2.93053}},"features":[{"properties":{"woeiddeletedplace":12696205,"latitude":59.01469,"countrycode":"GB","longitude":-2.93053,"id":"a6osz7n0u5xv"},"type":"Feature","geometry":{"type":"Point","coordinates":[-2.93053,59.01469]}}],"is_temporal":false,"author":{"url":"","metadata":"","contact_name":"","contact_address":"","source":"","contact_phone":""},"source":"","pagination":{"sort":null,"start":0,"total":1,"limit":1000000},"state":"complete","tags":"","published":"2014-08-15T00:10:28-04:00","id":236405}