{"type":"FeatureCollection","data_type":"Dataset","url_type":null,"permissions":[{"permissions":{"download":true,"view":true},"group_id":"everyone"}],"classification":null,"title":"Clients","count":5,"stream_id":237367,"contributor":{"url":"http://geocommons.com/users/44033","name":"purple"},"data_attributes":null,"calculation_params":null,"icon_link":null,"link":"http://geocommons.com/overlays/237367.json","extent":[-95.5562,29.6742,-95.4303,29.8739],"geometry_types":["point"],"unique_name":null,"name":"Clients","feature_count":5,"description":"","next_feature":null,"is_raster":false,"short_classification":"Y","stats":{"0":{"max":0,"mean":0.0,"variance":0.0,"stdev":0.0,"min":0,"median":0}},"features":[{"properties":{"geo_score":1.0,"0":0,"10001 richmond avenue, houston, tx, 77070":"10201 Main Street, Houston, TX, 77025","id":"a6e2m6kdkr1i","geo_precision":"range","westerngeco":"Stage Stores, Inc."},"type":"Feature","geometry":{"type":"Point","coordinates":[-95.430318,29.674241]}},{"properties":{"geo_score":0.545,"0":0,"10001 richmond avenue, houston, tx, 77070":"10300 Town Park Dr., Houston, Texas, 77072","id":"a6e2m674olv8","geo_precision":"street","westerngeco":"Veritas DGC Inc."},"type":"Feature","geometry":{"type":"Point","coordinates":[-95.536526,29.873872]}},{"properties":{"geo_score":1.0,"0":0,"10001 richmond avenue, houston, tx, 77070":"10370 Richmond Avenue, Houston, TX, 77042","id":"a6e2m66y10te","geo_precision":"range","westerngeco":"Grey Wolf"},"type":"Feature","geometry":{"type":"Point","coordinates":[-95.556077,29.727627]}},{"properties":{"geo_score":1.0,"0":0,"10001 richmond avenue, houston, tx, 77070":"10370 Richmond Avenue, Houston, TX, 77042","id":"a6e2m6icugtu","geo_precision":"range","westerngeco":"W-H Energy Services"},"type":"Feature","geometry":{"type":"Point","coordinates":[-95.556077,29.727627]}},{"properties":{"geo_score":0.92,"0":0,"10001 richmond avenue, houston, tx, 77070":"10375 Richmond, Houston, TX, 77042","id":"a6e2m6dmo9hd","geo_precision":"range","westerngeco":"Prime Staff USA"},"type":"Feature","geometry":{"type":"Point","coordinates":[-95.556185,29.727628]}}],"is_temporal":false,"author":{"url":"","metadata":"","contact_name":"","contact_address":"","source":"","contact_phone":""},"source":"","pagination":{"sort":null,"start":0,"total":5,"limit":1000000},"state":"complete","tags":"","published":"2014-08-15T01:40:30-04:00","id":237367}