{"type":"FeatureCollection","data_type":"Dataset","url_type":null,"permissions":[{"permissions":{"download":true,"view":true},"group_id":"everyone"}],"classification":null,"title":"Address_EDD","count":1,"stream_id":237467,"contributor":{"url":"http://geocommons.com/users/44657","name":"UKAppCtr"},"data_attributes":null,"calculation_params":null,"icon_link":null,"link":"http://geocommons.com/overlays/237467.json","extent":[-84.877,38.1997,-84.877,38.1997],"geometry_types":["point"],"unique_name":null,"name":"Address_EDD","feature_count":1,"description":"","next_feature":null,"is_raster":false,"short_classification":"Y","stats":{},"features":[{"properties":{"city":"Frankfort","zip":"40601","geo_score":0.849,"mission statement":"The Cabinet for Economic Development is the primary state agency in Kentucky responsible for creating new jobs and investment in the state. Programs administered by the Cabinet are designed to support and promote economic development within the state, primarily by attracting new industries to the state, assisting in the development of existing industries, and assisting communities in preparing for economic development opportunities","website":"http://www.thinkkentucky.com/","phone":"(502) 564-7140","street":"300 West Broadway Road","id":"a69ibutznw11","geo_precision":"range","state":"Kentucky"},"type":"Feature","geometry":{"type":"Point","coordinates":[-84.877018,38.199693]}}],"is_temporal":false,"author":{"url":"","metadata":null,"contact_name":null,"contact_address":null,"source":null,"contact_phone":null},"source":"","pagination":{"sort":null,"start":0,"total":1,"limit":1000000},"state":"complete","tags":"","published":"2014-08-15T02:01:04-04:00","id":237467}