{"type":"FeatureCollection","data_type":"Dataset","url_type":null,"permissions":[{"permissions":{"download":true,"view":true},"group_id":"everyone"}],"classification":null,"title":"99994","count":14,"stream_id":23929,"contributor":{"url":"http://geocommons.com/users/11204","name":"joegravellese"},"data_attributes":null,"calculation_params":null,"icon_link":null,"link":"http://geocommons.com/overlays/23929.json","extent":[-73.4134,42.1405,-71.0205,42.6549],"geometry_types":["point"],"unique_name":null,"name":"99994","feature_count":14,"description":"","next_feature":null,"is_raster":false,"short_classification":"Y","stats":{"dpcvisits":{"max":55,"mean":13.4285714285714,"variance":222.10989010989,"stdev":14.9033516401476,"min":1,"median":13},"geo_score":{"max":0.857,"mean":0.795785714285714,"variance":0.0524606428571428,"stdev":0.229042884318948,"min":0.0,"median":0.857},"lat":{"max":42.681023,"mean":42.2946492857143,"variance":0.15162096878145,"stdev":0.389385373096436,"min":41.342905,"median":42.416295},"long":{"max":-70.812889,"mean":-71.8630011428571,"variance":0.774503602742902,"stdev":0.880058863226149,"min":-73.415357,"median":-71.465799}},"features":[{"properties":{"dpcvisits":1,"geo_score":0.857,"id":"a6lz8u173tay","geo_precision":"city","community":"Ashland","lat":42.261303,"state":"Massachusetts","long":-71.465799},"type":"Feature","geometry":{"type":"Point","coordinates":[-71.459405,42.446396]}},{"properties":{"dpcvisits":1,"geo_score":0.857,"id":"a6lz8u1alsd1","geo_precision":"city","community":"Ashfield","lat":42.52616,"state":"Massachusetts","long":-72.790989},"type":"Feature","geometry":{"type":"Point","coordinates":[-72.738152,42.562391]}},{"properties":{"dpcvisits":1,"geo_score":0.857,"id":"a6lz8uctk5qi","geo_precision":"city","community":"Alford","lat":42.236366,"state":"Massachusetts","long":-73.415357},"type":"Feature","geometry":{"type":"Point","coordinates":[-73.413446,42.235644]}},{"properties":{"dpcvisits":12,"geo_score":0.0,"id":"a6lz8ubo4qs1","geo_precision":"unmatched","community":"Aquinnah","lat":41.342905,"state":"Massachusetts","long":-70.812889},"type":"Feature","geometry":null},{"properties":{"dpcvisits":13,"geo_score":0.857,"id":"a6lz8u4ie15a","geo_precision":"city","community":"Ashby","lat":42.681023,"state":"Massachusetts","long":-71.831224},"type":"Feature","geometry":{"type":"Point","coordinates":[-71.459405,42.446396]}},{"properties":{"dpcvisits":13,"geo_score":0.857,"id":"a6lz8u3vdzj2","geo_precision":"city","community":"Ashburnham","lat":42.6358,"state":"Massachusetts","long":-71.908354},"type":"Feature","geometry":{"type":"Point","coordinates":[-71.920942,42.654906]}},{"properties":{"dpcvisits":14,"geo_score":0.857,"id":"a6lz8u8fbpjc","geo_precision":"city","community":"Andover","lat":42.653565,"state":"Massachusetts","long":-71.136494},"type":"Feature","geometry":{"type":"Point","coordinates":[-71.165685,42.647991]}},{"properties":{"dpcvisits":15,"geo_score":0.857,"id":"a6lz8u8ov6p4","geo_precision":"city","community":"Malden","lat":41.682897,"state":"Massachusetts","long":-70.909483},"type":"Feature","geometry":{"type":"Point","coordinates":[-71.085396,42.436545]}},{"properties":{"dpcvisits":2,"geo_score":0.857,"id":"a6lz8u2s2uya","geo_precision":"city","community":"Arlington","lat":42.416295,"state":"Massachusetts","long":-71.156764},"type":"Feature","geometry":{"type":"Point","coordinates":[-71.167083,42.417695]}},{"properties":{"dpcvisits":22,"geo_score":0.857,"id":"a6lz8uc92vnq","geo_precision":"city","community":"Agawam","lat":42.088621,"state":"Massachusetts","long":-72.625272},"type":"Feature","geometry":{"type":"Point","coordinates":[-72.788661,42.140549]}},{"properties":{"dpcvisits":31,"geo_score":0.857,"id":"a6lz8tzfr6jt","geo_precision":"city","community":"Revere","lat":42.48582,"state":"Massachusetts","long":-71.433299},"type":"Feature","geometry":{"type":"Point","coordinates":[-71.020494,42.366303]}},{"properties":{"dpcvisits":4,"geo_score":0.857,"id":"a6lz8twvas9s","geo_precision":"city","community":"Amherst","lat":42.621441,"state":"Massachusetts","long":-73.120377},"type":"Feature","geometry":{"type":"Point","coordinates":[-72.464571,42.367092]}},{"properties":{"dpcvisits":4,"geo_score":0.857,"id":"a6lz8u3m246i","geo_precision":"city","community":"Amherst","lat":42.375265,"state":"Massachusetts","long":-72.518949},"type":"Feature","geometry":{"type":"Point","coordinates":[-72.464571,42.367092]}},{"properties":{"dpcvisits":55,"geo_score":0.857,"id":"a6lz8tx9x7br","geo_precision":"city","community":"Boston","lat":42.117629,"state":"Massachusetts","long":-70.956766},"type":"Feature","geometry":{"type":"Point","coordinates":[-71.059773,42.358431]}}],"is_temporal":false,"author":{"url":"","metadata":"","contact_name":"","contact_address":"","source":"","contact_phone":""},"source":"","pagination":{"sort":null,"start":0,"total":14,"limit":1000000},"state":"complete","tags":"","published":"2014-08-10T16:46:59-04:00","id":23929}