{"type":"FeatureCollection","data_type":"Dataset","url_type":null,"permissions":[{"permissions":{"download":true,"view":true},"group_id":"everyone"}],"classification":null,"title":"Mining_project","count":3,"stream_id":239707,"contributor":{"url":"http://geocommons.com/users/35812","name":"karenf"},"data_attributes":null,"calculation_params":null,"icon_link":null,"link":"http://geocommons.com/overlays/239707.json","extent":[-68.3333,-16.3333,-68.0,-14.5],"geometry_types":["point"],"unique_name":null,"name":"Mining_project","feature_count":3,"description":"","next_feature":null,"is_raster":false,"short_classification":"Y","stats":{"latitude":{"max":-14.5,"mean":-15.4444433333333,"variance":0.842589629633333,"stdev":0.917926810608195,"min":-16.33333,"median":-15.5},"women":{"max":11,"mean":3.66666666666667,"variance":40.3333333333333,"stdev":6.35085296108588,"min":0,"median":0},"longitude":{"max":-68.0,"mean":-68.22222,"variance":0.0370362963000008,"stdev":0.19244816522898,"min":-68.33333,"median":-68.33333},"total beneficaries":{"max":127,"mean":84.6666666666667,"variance":1346.33333333333,"stdev":36.6924152016917,"min":62,"median":65}},"features":[{"properties":{"latitude":-15.5,"women":11,"region":"Larecaja, La Paz","level":"province","project number":"Mining project BO (ABS)","beneficiary features":"40 members and 25 contracted workers","mining organization":"Senor de Mayo","longitude":-68.33333,"id":"a62jnp448p6v","total beneficaries":65},"type":"Feature","geometry":{"type":"Point","coordinates":[-68.33333,-15.5]}},{"properties":{"latitude":-16.33333,"women":0,"region":"Murillo, La Paz","level":"province","project number":"Mining project BO (ABS)","beneficiary features":"27 members and 35 contracted workers","mining organization":"Progreso Kalancha","longitude":-68.0,"id":"a62jnp4vygel","total beneficaries":62},"type":"Feature","geometry":{"type":"Point","coordinates":[-68.0,-16.33333]}},{"properties":{"latitude":-14.5,"women":0,"region":"Franz Tamayo, La Paz","level":"province","project number":"Mining project BO (ABS)","beneficiary features":"47 members and 80 contracted workers","mining organization":"Virgen del Rosario","longitude":-68.33333,"id":"a62jnp5jhymu","total beneficaries":127},"type":"Feature","geometry":{"type":"Point","coordinates":[-68.33333,-14.5]}}],"is_temporal":false,"author":{"url":"","metadata":null,"contact_name":null,"contact_address":null,"source":null,"contact_phone":null},"source":"","pagination":{"sort":null,"start":0,"total":3,"limit":1000000},"state":"complete","tags":"","published":"2014-08-15T04:52:07-04:00","id":239707}