{"type":"FeatureCollection","data_type":"Dataset","url_type":null,"permissions":[{"permissions":{"download":true,"view":true},"group_id":"everyone"}],"classification":null,"title":"12-05-09","count":8,"stream_id":239858,"contributor":{"url":"http://geocommons.com/users/37128","name":"james11son"},"data_attributes":null,"calculation_params":null,"icon_link":null,"link":"http://geocommons.com/overlays/239858.json","extent":[-12.1776,9.3034,-12.0022,9.4966],"geometry_types":["point"],"unique_name":null,"name":"12-05-09","feature_count":8,"description":"","next_feature":null,"is_raster":false,"short_classification":"Y","stats":{},"features":[{"properties":{"name":"9.4960°N, 12.1006°W","description":null,"id":"0"},"type":"Feature","geometry":{"type":"Point","coordinates":[-12.1006,9.496]}},{"properties":{"name":"9.4174°N, 12.1012°W","description":"","id":"1"},"type":"Feature","geometry":{"type":"Point","coordinates":[-12.1012,9.4174]}},{"properties":{"name":"9.4166°N, 12.0022°W","description":"","id":"2"},"type":"Feature","geometry":{"type":"Point","coordinates":[-12.0022,9.4166]}},{"properties":{"name":"9.3043°N, 12.1022°W","description":"","id":"3"},"type":"Feature","geometry":{"type":"Point","coordinates":[-12.1022,9.3043]}},{"properties":{"name":"9.3818°N, 12.1018°W","description":"","id":"4"},"type":"Feature","geometry":{"type":"Point","coordinates":[-12.1018,9.3818]}},{"properties":{"name":"9.3824°N, 12.1776°W","description":"","id":"5"},"type":"Feature","geometry":{"type":"Point","coordinates":[-12.1776,9.3824]}},{"properties":{"name":"9.4966°N, 12.1769°W","description":"","id":"6"},"type":"Feature","geometry":{"type":"Point","coordinates":[-12.1769,9.4966]}},{"properties":{"name":"9.303400, -12.003200","description":"+9° 18' 12.24\", -12° 0' 11.52\"","id":"7"},"type":"Feature","geometry":{"type":"Point","coordinates":[-12.0032,9.3034]}}],"is_temporal":false,"author":{"url":"","metadata":null,"contact_name":null,"contact_address":null,"source":null,"contact_phone":null},"source":"","pagination":{"sort":null,"start":0,"total":8,"limit":1000000},"state":"complete","tags":"","published":"2014-08-15T04:58:10-04:00","id":239858}