{"type":"FeatureCollection","url":"http://blog.outer-court.com/files/kmz-sample.kml","data_type":"Data Feed","url_type":"kml","permissions":[{"permissions":{"download":true,"view":true},"group_id":"everyone"}],"classification":null,"title":"Google Maps Overlay Sample","count":2,"stream_id":239870,"contributor":{"url":"http://geocommons.com/users/45299","name":"ryankelly415"},"data_attributes":null,"calculation_params":null,"icon_link":null,"link":"http://geocommons.com/overlays/239870.json","extent":[9.2275,48.7865,9.23343,48.7897],"geometry_types":["point"],"unique_name":null,"name":"Google Maps Overlay Sample","feature_count":2,"description":"","next_feature":null,"is_raster":false,"short_classification":"Y","stats":{},"features":[{"properties":{"name":"Football court","description":"This is just a test<img src=\"http://blog.outer-court.com/files/80-percent.gif\" alt=\"\">","id":"0"},"type":"Feature","geometry":{"type":"Point","coordinates":[9.22749702393303,48.7897277718892]}},{"properties":{"name":"A circle somewhere","description":"This is a test","id":"1"},"type":"Feature","geometry":{"type":"Point","coordinates":[9.23343330625122,48.7865204954917]}}],"is_temporal":false,"author":{"url":"","metadata":"","contact_name":"","contact_address":"","source":"","contact_phone":""},"source":"","pagination":{"sort":null,"start":0,"total":2,"limit":1000000},"state":"complete","tags":"","published":"2014-08-15T04:58:26-04:00","id":239870}