{"type":"FeatureCollection","data_type":"Dataset","url_type":null,"permissions":[{"permissions":{"download":true,"view":true},"group_id":"everyone"}],"classification":null,"title":"KU Home Location","count":1,"stream_id":240880,"contributor":{"url":"http://geocommons.com/users/45575","name":"ueng_fa@hotmail.com"},"data_attributes":null,"calculation_params":null,"icon_link":null,"link":"http://geocommons.com/overlays/240880.json","extent":[100.568,13.8451,100.568,13.8451],"geometry_types":["point"],"unique_name":null,"name":"KU Home Location","feature_count":1,"description":"เคยูโฮม ตั้งอยู่ในมหาวิทยาลัยเกษตรศาสตร์ ห่างจาก่ท่าอากาศยานดอนเมืองเพียง 10 นาที ล้อมรอบด้วยความเขียวขจีของธรรมชาติที่เงียบสงบ ห้องพัก ทั้งหมด 100 ห้อง ตกแต่งอย่างหรูหรา พร้อมสิ่งอำนวยความสะดวกครบครัน อาทิ ทีวี สัญญาณดาวเทียม ","next_feature":null,"is_raster":false,"short_classification":"Y","stats":{},"features":[{"properties":{"name":"KU Home","id":"0"},"type":"Feature","geometry":{"type":"Point","coordinates":[100.567520653885,13.8451325865669]}}],"is_temporal":false,"author":{"url":"","metadata":"","contact_name":"","contact_address":"","source":"","contact_phone":""},"source":"","pagination":{"sort":null,"start":0,"total":1,"limit":1000000},"state":"complete","tags":"hotels,thailand,venues","published":"2014-08-14T15:55:09-04:00","id":240880}