{"type":"FeatureCollection","data_type":"Dataset","url_type":null,"permissions":[{"permissions":{"download":true,"view":true},"group_id":"everyone"}],"classification":null,"title":"Jarad Soontornsing Building","count":1,"stream_id":240927,"contributor":{"url":"http://geocommons.com/users/44859","name":"sjiraphan"},"data_attributes":null,"calculation_params":null,"icon_link":null,"link":"http://geocommons.com/overlays/240927.json","extent":[100.571,13.8493,100.571,13.8493],"geometry_types":["point"],"unique_name":null,"name":"Jarad Soontornsing Building","feature_count":1,"description":"\r\nJarad Soontornsing Building\r\nFaculty of Agriculture\r\nKasetasrt University","next_feature":null,"is_raster":false,"short_classification":"Y","stats":{},"features":[{"properties":{"name":"Jarad Soontornsing Building","id":"0"},"type":"Feature","geometry":{"type":"Point","coordinates":[100.571027850024,13.8492619880715]}}],"is_temporal":false,"author":{"url":"","metadata":"","contact_name":"","contact_address":"","source":"","contact_phone":""},"source":"","pagination":{"sort":null,"start":0,"total":1,"limit":1000000},"state":"complete","tags":"bangkok,kasetsart,thailand,university","published":"2014-08-14T15:56:24-04:00","id":240927}