{"type":"FeatureCollection","data_type":"Dataset","url_type":null,"permissions":[{"permissions":{"download":true,"view":true},"group_id":"everyone"}],"classification":null,"title":"suanjit.kml","count":1,"stream_id":240922,"contributor":{"url":"http://geocommons.com/users/45200","name":"taketo.uki"},"data_attributes":null,"calculation_params":null,"icon_link":null,"link":"http://geocommons.com/overlays/240922.json","extent":[100.523,13.7664,100.523,13.7664],"geometry_types":["point"],"unique_name":null,"name":"suanjit.kml","feature_count":1,"description":"","next_feature":null,"is_raster":false,"short_classification":"Y","stats":{},"features":[{"properties":{"name":"suanjit","id":"0"},"type":"Feature","geometry":{"type":"Point","coordinates":[100.52270690094,13.7663717369737]}}],"is_temporal":false,"author":{"url":"","metadata":"","contact_name":"Taketo","contact_address":"\r\nMU,Thailand","source":"IUCN","contact_phone":"089-0921296"},"source":"","pagination":{"sort":null,"start":0,"total":1,"limit":1000000},"state":"complete","tags":"thailand","published":"2014-08-14T15:56:20-04:00","id":240922}