{"type":"FeatureCollection","data_type":"Dataset","url_type":null,"permissions":[{"permissions":{"download":true,"view":true},"group_id":"everyone"}],"classification":null,"title":"Mae Kong Esturies.kml","count":1,"stream_id":240949,"contributor":{"url":"http://geocommons.com/users/44883","name":"siriwan"},"data_attributes":null,"calculation_params":null,"icon_link":null,"link":"http://geocommons.com/overlays/240949.json","extent":[100.016,13.3489,100.016,13.3489],"geometry_types":["point"],"unique_name":null,"name":"Mae Kong Esturies.kml","feature_count":1,"description":"","next_feature":null,"is_raster":false,"short_classification":"Y","stats":{},"features":[{"properties":{"name":"Mae Kong Esturies","id":"0"},"type":"Feature","geometry":{"type":"Point","coordinates":[100.016066505051,13.3489443330691]}}],"is_temporal":false,"author":{"url":"","metadata":"","contact_name":"","contact_address":"","source":"","contact_phone":""},"source":"","pagination":{"sort":null,"start":0,"total":1,"limit":1000000},"state":"complete","tags":"","published":"2014-08-14T15:57:17-04:00","id":240949}