{"type":"FeatureCollection","data_type":"Dataset","url_type":null,"permissions":[{"permissions":{"download":true,"view":true},"group_id":"everyone"}],"classification":null,"title":"Doi Phukha National Park ","count":1,"stream_id":240909,"contributor":{"url":"http://geocommons.com/users/45575","name":"ueng_fa@hotmail.com"},"data_attributes":null,"calculation_params":null,"icon_link":null,"link":"http://geocommons.com/overlays/240909.json","extent":[100.919,19.1768,100.919,19.1768],"geometry_types":["point"],"unique_name":null,"name":"Doi Phukha National Park ","feature_count":1,"description":"","next_feature":null,"is_raster":false,"short_classification":"Y","stats":{},"features":[{"properties":{"name":"Phukha National Park","id":"0"},"type":"Feature","geometry":{"type":"Point","coordinates":[100.919238369925,19.176812536532]}}],"is_temporal":false,"author":{"url":"","metadata":"","contact_name":"","contact_address":"","source":"","contact_phone":""},"source":"","pagination":{"sort":null,"start":0,"total":1,"limit":1000000},"state":"complete","tags":"national,park","published":"2014-08-14T15:56:13-04:00","id":240909}