{"type":"FeatureCollection","data_type":"Dataset","url_type":null,"permissions":[{"permissions":{"download":true,"edit":true,"view":true},"group_id":45656},{"permissions":{"download":true,"edit":true,"view":true},"group_id":46233},{"permissions":{"download":true,"view":true},"group_id":"everyone"}],"classification":null,"title":"7_arlington_diagnostic","count":1,"stream_id":241277,"contributor":{"url":"http://geocommons.com/users/44921","name":"rhazel246"},"data_attributes":null,"calculation_params":null,"icon_link":null,"link":"http://geocommons.com/overlays/241277.json","extent":[-77.0884,38.8416,-77.0884,38.8416],"geometry_types":["point"],"unique_name":null,"name":"7_arlington_diagnostic","feature_count":1,"description":"","next_feature":null,"is_raster":false,"short_classification":"Y","stats":{},"features":[{"properties":{"name":"Insight Imaging Arlington","id":"0"},"type":"Feature","geometry":{"type":"Point","coordinates":[-77.088356,38.841625]}}],"is_temporal":false,"author":{"url":"","metadata":"","contact_name":"","contact_address":"","source":"","contact_phone":""},"source":"","pagination":{"sort":null,"start":0,"total":1,"limit":1000000},"state":"complete","tags":"","published":"2014-08-14T16:24:41-04:00","id":241277}