{"type":"FeatureCollection","data_type":"Dataset","url_type":null,"permissions":[{"permissions":{"download":true,"edit":true,"view":true},"group_id":45656},{"permissions":{"download":true,"edit":true,"view":true},"group_id":46233},{"permissions":{"download":true,"view":true},"group_id":"everyone"}],"classification":null,"title":"6 PrinceGeorges MedTransport","count":3,"stream_id":242875,"contributor":{"url":"http://geocommons.com/users/44953","name":"rhazel"},"data_attributes":null,"calculation_params":null,"icon_link":null,"link":"http://geocommons.com/overlays/242875.json","extent":[-76.905,38.9402,-76.7668,39.0361],"geometry_types":["point"],"unique_name":null,"name":"6 PrinceGeorges MedTransport","feature_count":3,"description":"","next_feature":null,"is_raster":false,"short_classification":"Y","stats":{"msa code":{"max":6,"mean":6.0,"variance":0.0,"stdev":0.0,"min":6,"median":6},"latitude":{"max":39.036114,"mean":38.9833336666667,"variance":0.00236899814233338,"stdev":0.0486723550111701,"min":38.94022,"median":38.973667},"longitude":{"max":-76.766754,"mean":-76.8445636666667,"variance":0.0050056133303328,"stdev":0.0707503592240549,"min":-76.905029,"median":-76.861908}},"features":[{"properties":{"msa code":6,"city":null,"latitude":39.036114,"key factor 1":null,"key factor 2":null,"zipcode":null,"url":null,"key resource":"Butler Medical Transport","notes":null,"longitude":-76.905029,"category code":"G04","id":"a629v3md68no","address":"Butler Medical Transport\n5002 Cook Road\nBeltsville, MD 20705\n(240) 965-6758\nbutlermedicaltransport.com"},"type":"Feature","geometry":{"type":"Point","coordinates":[-76.905029,39.036114]}},{"properties":{"msa code":6,"city":null,"latitude":38.973667,"key factor 1":null,"key factor 2":null,"zipcode":null,"url":null,"key resource":"Professional Medical Transport","notes":null,"longitude":-76.766754,"category code":"G04","id":"a629v3nwup3a","address":"Professional Medical Transport\n13710 Annapolis Road\nBowie, MD 20720"},"type":"Feature","geometry":{"type":"Point","coordinates":[-76.766754,38.973667]}},{"properties":{"msa code":6,"city":null,"latitude":38.94022,"key factor 1":null,"key factor 2":null,"zipcode":null,"url":"http://www.princegeorgescountymd.gov/Government/PublicSafety/Fire-EMS/maps_addresses.asp","key resource":"Transcend Inc-Medical Transportation","notes":null,"longitude":-76.861908,"category code":"G04","id":"a629v3k7bijj","address":"Transcend Inc-Medical Transportation\n8504 Ardwick Ardmore Road\nHyattsville, MD 20785"},"type":"Feature","geometry":{"type":"Point","coordinates":[-76.861908,38.94022]}}],"is_temporal":false,"author":{"url":"","metadata":"","contact_name":"","contact_address":"","source":"","contact_phone":""},"source":"","pagination":{"sort":null,"start":0,"total":3,"limit":1000000},"state":"complete","tags":"","published":"2014-08-14T19:11:17-04:00","id":242875}