{"type":"FeatureCollection","data_type":"Dataset","url_type":null,"permissions":[{"permissions":{"download":true,"view":true},"group_id":"everyone"}],"classification":null,"title":"Distribution Archaic Greek lead amulets","count":4,"stream_id":242927,"contributor":{"url":"http://geocommons.com/users/43624","name":"magicdatabase"},"data_attributes":null,"calculation_params":null,"icon_link":null,"link":"http://geocommons.com/overlays/242927.json","extent":[12.8063,35.501,23.5804,38.2364],"geometry_types":["point"],"unique_name":null,"name":"Distribution Archaic Greek lead amulets","feature_count":4,"description":"","next_feature":null,"is_raster":false,"short_classification":"Y","stats":{"latitude":{"max":38.236355,"mean":37.3231595,"variance":1.54979674915501,"stdev":1.2449083296191,"min":35.501003,"median":37.980254},"longitude":{"max":23.580407,"mean":16.6198305,"variance":23.6301927848857,"stdev":4.86108967052508,"min":12.806311,"median":16.259982}},"features":[{"properties":{"artifact":"Lead 1","latitude":37.980254,"date":"V BCE","provenance":"Himera, Sicily","longitude":13.832622,"id":"a62dc0m2d7z3"},"type":"Feature","geometry":{"type":"Point","coordinates":[13.832622,37.980254]}},{"properties":{"artifact":"Lead 2","latitude":38.236355,"date":"early IV BCE","provenance":"Lokroi Epizephyrioi, Calabria","longitude":16.259982,"id":"a62dc0m95etw"},"type":"Feature","geometry":{"type":"Point","coordinates":[16.259982,38.236355]}},{"properties":{"artifact":"Lead 3","latitude":37.575026,"date":"1st half IV BCE","provenance":"Selinous, Sicily","longitude":12.806311,"id":"a62dc0vcqoud"},"type":"Feature","geometry":{"type":"Point","coordinates":[12.806311,37.575026]}},{"properties":{"artifact":"Lead 4","latitude":35.501003,"date":"IV BCE","provenance":"Phalasarna, Crete","longitude":23.580407,"id":"a62dc0uz7w80"},"type":"Feature","geometry":{"type":"Point","coordinates":[23.580407,35.501003]}}],"is_temporal":false,"author":{"url":"","metadata":"","contact_name":"","contact_address":"","source":"","contact_phone":""},"source":"","pagination":{"sort":null,"start":0,"total":4,"limit":1000000},"state":"complete","tags":"","published":"2014-08-14T19:17:09-04:00","id":242927}