{"type":"FeatureCollection","data_type":"Dataset","url_type":null,"permissions":[{"permissions":{"download":true,"view":true},"group_id":"everyone"}],"classification":null,"title":"Pasta1","count":4,"stream_id":245143,"contributor":{"url":"http://geocommons.com/users/45972","name":"lvc.log@hotmail.com"},"data_attributes":null,"calculation_params":null,"icon_link":null,"link":"http://geocommons.com/overlays/245143.json","extent":[-51.23,-30.0331,-34.8811,-8.05389],"geometry_types":["point"],"unique_name":null,"name":"Pasta1","feature_count":4,"description":"","next_feature":null,"is_raster":false,"short_classification":"Y","stats":{"sales":{"max":935,"mean":446.25,"variance":143389.583333333,"stdev":378.668170478235,"min":100,"median":550}},"features":[{"properties":{"city":"Rio de Janeiro","sales":200,"geo_score":1.0,"country":"Brazil","id":"a6254ke8wjpg","geo_precision":"zip"},"type":"Feature","geometry":{"type":"Point","coordinates":[-43.2075,-22.90277778]}},{"properties":{"city":"Belo Horizonte","sales":100,"geo_score":1.0,"country":"Brazil","id":"a6254kmeerbd","geo_precision":"zip"},"type":"Feature","geometry":{"type":"Point","coordinates":[-43.93777778,-19.92083333]}},{"properties":{"city":"Porto Alegre","sales":550,"geo_score":1.0,"country":"Brazil","id":"a6254kl1ro5v","geo_precision":"zip"},"type":"Feature","geometry":{"type":"Point","coordinates":[-51.23,-30.03305556]}},{"properties":{"city":"Recife","sales":935,"geo_score":1.0,"country":"Brazil","id":"a6254kie2pbq","geo_precision":"zip"},"type":"Feature","geometry":{"type":"Point","coordinates":[-34.88111111,-8.053888889]}}],"is_temporal":false,"author":{"url":"","metadata":null,"contact_name":null,"contact_address":null,"source":null,"contact_phone":null},"source":"","pagination":{"sort":null,"start":0,"total":4,"limit":1000000},"state":"complete","tags":"","published":"2014-08-14T22:28:52-04:00","id":245143}