{"type":"FeatureCollection","data_type":"Dataset","url_type":null,"permissions":[{"permissions":{"download":true,"view":true},"group_id":"everyone"}],"classification":null,"title":"Arkusz1","count":1,"stream_id":247185,"contributor":{"url":"http://geocommons.com/users/46411","name":"Caroline86"},"data_attributes":null,"calculation_params":null,"icon_link":null,"link":"http://geocommons.com/overlays/247185.json","extent":[13.4061,52.5192,13.4061,52.5192],"geometry_types":["point"],"unique_name":null,"name":"Arkusz1","feature_count":1,"description":"Source: dane.xls&lt;br/&gt;DateTime: 2012-05-31 12:06:27 UTC&lt;br/&gt;&lt;br/&gt;&amp;copy;2012 Earth Point&lt;br/&gt;&lt;a target='_blank' href='http://www.earthpoint.us'&gt;www.earthpoint.us&lt;/a&gt;&lt;br/&gt;&lt;br/&gt;For illustration only.&amp;nbsp; User to verify all information. ","next_feature":null,"is_raster":false,"short_classification":"Y","stats":{},"features":[{"properties":{"name":"Dr. Georg Nüßlein","description":"Stellvertretendes Mitglied des Parlamentarischen Beirats für nachhaltige Entwicklung","id":"a632m0aou4c0"},"type":"Feature","geometry":{"type":"Point","coordinates":[13.406091,52.519171]}}],"is_temporal":false,"author":{"url":"","metadata":"","contact_name":"","contact_address":"","source":"","contact_phone":""},"source":"","pagination":{"sort":null,"start":0,"total":1,"limit":1000000},"state":"complete","tags":"","published":"2014-08-15T01:20:13-04:00","id":247185}