{"type":"FeatureCollection","data_type":"Dataset","url_type":null,"permissions":[{"permissions":{"download":true,"view":true},"group_id":"everyone"}],"classification":null,"title":"EarthPointExcel","count":1,"stream_id":247190,"contributor":{"url":"http://geocommons.com/users/46411","name":"Caroline86"},"data_attributes":null,"calculation_params":null,"icon_link":null,"link":"http://geocommons.com/overlays/247190.json","extent":[13.4061,52.5192,13.4061,52.5192],"geometry_types":["point"],"unique_name":null,"name":"EarthPointExcel","feature_count":1,"description":"","next_feature":null,"is_raster":false,"short_classification":"Y","stats":{},"features":[{"properties":{"name":"Andreas Wittke","id":"a6331jw3onwl"},"type":"Feature","geometry":{"type":"Point","coordinates":[13.406091,52.519171]}}],"is_temporal":false,"author":{"url":"","metadata":null,"contact_name":null,"contact_address":null,"source":null,"contact_phone":null},"source":"","pagination":{"sort":null,"start":0,"total":1,"limit":1000000},"state":"complete","tags":"","published":"2014-08-15T01:20:14-04:00","id":247190}