{"type":"FeatureCollection","data_type":"Dataset","url_type":null,"permissions":[{"permissions":{"download":true,"view":true},"group_id":"everyone"}],"classification":null,"title":"consuming countries.kmz","count":1,"stream_id":24838,"contributor":{"url":"http://geocommons.com/users/9980","name":"mikemommsen"},"data_attributes":null,"calculation_params":null,"icon_link":null,"link":"http://geocommons.com/overlays/24838.json","extent":[6.14017,49.623,6.14017,49.623],"geometry_types":["point"],"unique_name":null,"name":"consuming countries.kmz","feature_count":1,"description":"","next_feature":null,"is_raster":false,"short_classification":"Y","stats":{},"features":[{"properties":{"name":"Luxembourg","id":"a6eu51i6t795"},"type":"Feature","geometry":{"type":"Point","coordinates":[6.14016587287457,49.6230383621963]}}],"is_temporal":false,"author":{"url":"","metadata":"","contact_name":"","contact_address":"","source":"","contact_phone":""},"source":"","pagination":{"sort":null,"start":0,"total":1,"limit":1000000},"state":"complete","tags":"","published":"2014-08-10T17:53:33-04:00","id":24838}