{"type":"FeatureCollection","data_type":"Dataset","url_type":null,"permissions":[{"permissions":{"download":true,"view":true},"group_id":"everyone"}],"classification":null,"title":"closed","count":4,"stream_id":250450,"contributor":{"url":"http://geocommons.com/users/28467","name":"bheberto"},"data_attributes":null,"calculation_params":null,"icon_link":null,"link":"http://geocommons.com/overlays/250450.json","extent":[-105.387,40.6517,-105.171,40.7558],"geometry_types":["point"],"unique_name":null,"name":"closed","feature_count":4,"description":"","next_feature":null,"is_raster":false,"short_classification":"Y","stats":{},"features":[{"properties":{"name":"Closed","description":"US 287 Northbound / Southbound Fort Collins - Owl Canyon (Milemarker 355-363)Closed due to wildfire. Road closure began June 10th, 2012 at 2:59pm.","id":"a6bymbqvt1kd"},"type":"Feature","geometry":{"type":"Point","coordinates":[-105.179153,40.651733]}},{"properties":{"name":"Closed","description":"CO 14 Eastbound / Westbound Stove Prairie Rd. to Ted's Place (Milemarker 106-121)Road closed due to wildfire. Road closure began June 9th, 2012 at 1:54pm.","id":"a6bymbp6jeit"},"type":"Feature","geometry":{"type":"Point","coordinates":[-105.20079,40.665405]}},{"properties":{"name":"Closed","description":"US 287 Northbound / Southbound Fort Collins - Owl Canyon (Milemarker 355-363)Closed due to wildfire. Road closure began June 10th, 2012 at 2:59pm.","id":"a6bymbqbm0sy"},"type":"Feature","geometry":{"type":"Point","coordinates":[-105.171432,40.75584]}},{"properties":{"name":"Closed","description":"CO 14 Eastbound / Westbound Stove Prairie Rd. to Ted's Place (Milemarker 106-121)Road closed due to wildfire. Road closure began June 9th, 2012 at 1:54pm.","id":"a6bymbfrr2li"},"type":"Feature","geometry":{"type":"Point","coordinates":[-105.387039,40.684544]}}],"is_temporal":false,"author":{"url":"","metadata":null,"contact_name":null,"contact_address":null,"source":null,"contact_phone":null},"source":"","pagination":{"sort":null,"start":0,"total":4,"limit":1000000},"state":"complete","tags":"","published":"2014-08-14T15:31:25-04:00","id":250450}