{"type":"FeatureCollection","data_type":"Dataset","url_type":null,"permissions":[{"permissions":{"download":true,"view":true},"group_id":"everyone"}],"classification":null,"title":"\nenviortest\n","count":1,"stream_id":25117,"contributor":{"url":"http://geocommons.com/users/11444","name":"platial"},"data_attributes":null,"calculation_params":null,"icon_link":null,"link":"http://geocommons.com/overlays/25117.json","extent":[-84.2156,30.5632,-84.2156,30.5632],"geometry_types":["point"],"unique_name":null,"name":"\nenviortest\n","feature_count":1,"description":"","next_feature":null,"is_raster":false,"short_classification":"Y","stats":{},"features":[{"properties":{"name":"tallahassee","description":"Posted by Ffko<img src=\"http://media.geocommons.com/platial/images/categories/ICON_plain_pink_verD.gif\"> thomasville rd<a title=\"Built for Community Mapping\" href=\"http://www.platial.com\"><img src=\"http://media.geocommons.com/platial/images/logotype_small.jpg\"></a>","id":"a65k7tftg98s"},"type":"Feature","geometry":{"type":"Point","coordinates":[-84.215632,30.56317]}}],"is_temporal":false,"author":{"url":"http://www.platial.com/feed/map/44482.kml","metadata":null,"contact_name":"ffko","contact_address":null,"source":"platial:ffko","contact_phone":null},"source":"http://www.platial.com/feed/map/44482.kml","pagination":{"sort":null,"start":0,"total":1,"limit":1000000},"state":"complete","tags":"platial,platial:id=44482,platial:user=ffko","published":"2010-03-01T17:00:00Z","id":25117}