{"type":"FeatureCollection","data_type":"Dataset","url_type":null,"permissions":[{"permissions":{"download":true,"view":true},"group_id":"everyone"}],"classification":null,"title":"74_PPI","count":3,"stream_id":251521,"contributor":{"url":"http://geocommons.com/users/46617","name":"alie_sadikin"},"data_attributes":null,"calculation_params":null,"icon_link":null,"link":"http://geocommons.com/overlays/251521.json","extent":[121.537,-5.52392,122.874,-4.37313],"geometry_types":["point"],"unique_name":null,"name":"74_PPI","feature_count":3,"description":"","next_feature":null,"is_raster":false,"short_classification":"Y","stats":{"Lokasi_Pel":{"max":0.0,"variance":0.0,"mean":0.0,"stdev":0.0,"min":0.0,"median":0.0},"IDSP2010":{"max":7404011003,"variance":2902786562025.33,"mean":7402043674.33333,"stdev":1703756.60292934,"min":7401060007,"median":7401060013}},"features":[{"properties":{"Lokasi_Pel":0.0,"PROV":"SULAWESI TENGGARA","IDSP2010":7401060007,"Nama_PELAB":"TPI. Pasarwajo","Class":"TPI","NAMA":"DONGKALA","KABKOT":"BUTON","id":"a6ds7o2yssop","KEC":"PASARWAJO"},"type":"Feature","geometry":{"type":"Point","coordinates":[122.873773966953,-5.52392176820805]}},{"properties":{"Lokasi_Pel":0.0,"PROV":"SULAWESI TENGGARA","IDSP2010":7401060013,"Nama_PELAB":"PPI. Ereka","Class":"PPI","NAMA":"BANABUNGI","KABKOT":"BUTON","id":"a6ds7o9d8zfs","KEC":"PASARWAJO"},"type":"Feature","geometry":{"type":"Point","coordinates":[122.805030696508,-5.50841467302674]}},{"properties":{"Lokasi_Pel":0.0,"PROV":"SULAWESI TENGGARA","IDSP2010":7404011003,"Nama_PELAB":"TPI. Anaiwoi","Class":"TPI","NAMA":"ANAIWOI","KABKOT":"KOLAKA","id":"a6ds7o6vrk8o","KEC":"TANGGETADA"},"type":"Feature","geometry":{"type":"Point","coordinates":[121.537138205906,-4.37313144135114]}}],"is_temporal":false,"author":{"url":"","metadata":"","contact_name":"","contact_address":"","source":"","contact_phone":""},"source":"","pagination":{"sort":null,"start":0,"total":3,"limit":1000000},"state":"complete","tags":"","published":"2014-08-14T16:57:51-04:00","id":251521}