{"type":"FeatureCollection","data_type":"Dataset","url_type":null,"permissions":[{"permissions":{"download":true,"view":true},"group_id":"everyone"}],"classification":null,"title":"Book1","count":11,"stream_id":253349,"contributor":{"url":"http://geocommons.com/users/11038","name":"cmckechney"},"data_attributes":null,"calculation_params":null,"icon_link":null,"link":"http://geocommons.com/overlays/253349.json","extent":[-77.4981,43.2016,-77.4949,43.2032],"geometry_types":["point"],"unique_name":null,"name":"Book1","feature_count":11,"description":"","next_feature":null,"is_raster":false,"short_classification":"Y","stats":{"lng":{"max":-77.49484956,"variance":1.18089755401849e-06,"mean":-77.4970294672727,"stdev":0.00108669110331248,"min":-77.49812186,"median":-77.49711871},"lat":{"max":43.20319891,"variance":2.45709383187593e-07,"mean":43.2027873145455,"stdev":0.000495690814104511,"min":43.20160568,"median":43.20289314}},"features":[{"properties":{"lng":-77.49679148,"id":"a6jgrwyyl1bj","lat":43.20240498},"type":"Feature","geometry":{"type":"Point","coordinates":[-77.49679148,43.20240498]}},{"properties":{"lng":-77.49711871,"id":"a6jgrx45pfdk","lat":43.20289314},"type":"Feature","geometry":{"type":"Point","coordinates":[-77.49711871,43.20289314]}},{"properties":{"lng":-77.49592781,"id":"a6jgrwxupwj2","lat":43.20241034},"type":"Feature","geometry":{"type":"Point","coordinates":[-77.49592781,43.20241034]}},{"properties":{"lng":-77.49686122,"id":"a6jgrwsfwhic","lat":43.20286632},"type":"Feature","geometry":{"type":"Point","coordinates":[-77.49686122,43.20286632]}},{"properties":{"lng":-77.49484956,"id":"a6jgrx3uvndg","lat":43.20160568},"type":"Feature","geometry":{"type":"Point","coordinates":[-77.49484956,43.20160568]}},{"properties":{"lng":-77.49591708,"id":"a6jgrx3userg","lat":43.20263565},"type":"Feature","geometry":{"type":"Point","coordinates":[-77.49591708,43.20263565]}},{"properties":{"lng":-77.49808431,"id":"a6jgrwy5d2fy","lat":43.20315063},"type":"Feature","geometry":{"type":"Point","coordinates":[-77.49808431,43.20315063]}},{"properties":{"lng":-77.49798775,"id":"a6jgrx3ctpk0","lat":43.20312381},"type":"Feature","geometry":{"type":"Point","coordinates":[-77.49798775,43.20312381]}},{"properties":{"lng":-77.49812186,"id":"a6jgrwtwxxam","lat":43.20317209},"type":"Feature","geometry":{"type":"Point","coordinates":[-77.49812186,43.20317209]}},{"properties":{"lng":-77.49783218,"id":"a6jgrwtxtryb","lat":43.20319891},"type":"Feature","geometry":{"type":"Point","coordinates":[-77.49783218,43.20319891]}},{"properties":{"lng":-77.49783218,"id":"a6jgrwubb3lt","lat":43.20319891},"type":"Feature","geometry":{"type":"Point","coordinates":[-77.49783218,43.20319891]}}],"is_temporal":false,"author":{"url":"","metadata":"","contact_name":"","contact_address":"","source":"","contact_phone":""},"source":"","pagination":{"sort":null,"start":0,"total":11,"limit":1000000},"state":"complete","tags":"","published":"2014-08-14T19:17:45-04:00","id":253349}