{"type":"FeatureCollection","data_type":"Dataset","url_type":null,"permissions":[{"permissions":{"download":true,"view":true},"group_id":"everyone"}],"classification":null,"title":"Software Cognos v1","count":3,"stream_id":253818,"contributor":{"url":"http://geocommons.com/users/47629","name":"bwobst7531"},"data_attributes":null,"calculation_params":null,"icon_link":null,"link":"http://geocommons.com/overlays/253818.json","extent":[-77.6843,40.8521,-74.4077,43.286],"geometry_types":["point"],"unique_name":null,"name":"Software Cognos v1","feature_count":3,"description":"","next_feature":null,"is_raster":false,"short_classification":"Y","stats":{},"features":[{"properties":{"city":"Parsippany","geo_score":0.714,"customer name":"Revelwood Inc","id":"a6kbqbgc6jkh","software brands":"Cognos","geo_precision":"city","state":"NJ"},"type":"Feature","geometry":{"type":"Point","coordinates":[-74.407706,40.852118]}},{"properties":{"city":"Parsippany","geo_score":0.714,"customer name":"Fyi Systems Inc","id":"a6kbqbjawelq","software brands":"Cognos","geo_precision":"city","state":"NJ"},"type":"Feature","geometry":{"type":"Point","coordinates":[-74.407706,40.852118]}},{"properties":{"city":"Rochester","geo_score":0.714,"customer name":"Lpa Systems Inc","id":"a6kbqba1so8g","software brands":"Cognos","geo_precision":"city","state":"NY"},"type":"Feature","geometry":{"type":"Point","coordinates":[-77.684264,43.286024]}}],"is_temporal":false,"author":{"url":"","metadata":"","contact_name":"","contact_address":"","source":"","contact_phone":""},"source":"","pagination":{"sort":null,"start":0,"total":3,"limit":1000000},"state":"complete","tags":"","published":"2014-08-14T19:44:01-04:00","id":253818}