{"type":"FeatureCollection","data_type":"Dataset","url_type":null,"permissions":[{"permissions":{"download":true,"view":true},"group_id":"everyone"}],"classification":null,"title":"behoerden","count":10,"stream_id":254251,"contributor":{"url":"http://geocommons.com/users/47846","name":"pge11ecx"},"data_attributes":null,"calculation_params":null,"icon_link":null,"link":"http://geocommons.com/overlays/254251.json","extent":[12.281,50.8687,12.9421,51.3669],"geometry_types":["point"],"unique_name":null,"name":"behoerden","feature_count":10,"description":" | Created with http://batchgeo.com","next_feature":null,"is_raster":false,"short_classification":"Y","stats":{},"features":[{"properties":{"description":"&lt;div&gt;&lt;span class=\"l\"&gt;Nummer:&lt;/span&gt;&amp;nbsp;1&lt;/div&gt;&lt;div&gt;&lt;span class=\"l\"&gt;Amt:&lt;/span&gt;&amp;nbsp;Allgemeine Ordnungsbehoerde und Auslaenderbehoerde&lt;/div&gt;","id":"a6l3u26eosya"},"type":"Feature","geometry":{"type":"Point","coordinates":[12.386408415515,51.334354386703]}},{"properties":{"description":"&lt;div&gt;&lt;span class=\"l\"&gt;Nummer:&lt;/span&gt;&amp;nbsp;2&lt;/div&gt;&lt;div&gt;&lt;span class=\"l\"&gt;Amt:&lt;/span&gt;&amp;nbsp;Bundesamt für die Anerkennung auslaendischer Fluechtlinge&lt;/div&gt;","id":"a6l3u2a7cqt7"},"type":"Feature","geometry":{"type":"Point","coordinates":[12.942050956014,50.868722879501]}},{"properties":{"description":"&lt;div&gt;&lt;span class=\"l\"&gt;Nummer:&lt;/span&gt;&amp;nbsp;3&lt;/div&gt;&lt;div&gt;&lt;span class=\"l\"&gt;Amt:&lt;/span&gt;&amp;nbsp;Verwaltungsgericht Leipzig&lt;/div&gt;","id":"a6l3u2a9tdyl"},"type":"Feature","geometry":{"type":"Point","coordinates":[12.315052453767,51.353833350577]}},{"properties":{"description":"&lt;div&gt;&lt;span class=\"l\"&gt;Nummer:&lt;/span&gt;&amp;nbsp;4&lt;/div&gt;&lt;div&gt;&lt;span class=\"l\"&gt;Amt:&lt;/span&gt;&amp;nbsp;Sozialamt- Zentralstelle für Auslaender und Aussiedler&lt;/div&gt;","id":"a6l3u2demu3d"},"type":"Feature","geometry":{"type":"Point","coordinates":[12.280953984122,51.311636833601]}},{"properties":{"description":"&lt;div&gt;&lt;span class=\"l\"&gt;Nummer:&lt;/span&gt;&amp;nbsp;5&lt;/div&gt;&lt;div&gt;&lt;span class=\"l\"&gt;Amt:&lt;/span&gt;&amp;nbsp;Jugendamt&lt;/div&gt;","id":"a6l3u2k2brvp"},"type":"Feature","geometry":{"type":"Point","coordinates":[12.330466761127,51.326577955742]}},{"properties":{"description":"&lt;div&gt;&lt;span class=\"l\"&gt;Nummer:&lt;/span&gt;&amp;nbsp;6&lt;/div&gt;&lt;div&gt;&lt;span class=\"l\"&gt;Amt:&lt;/span&gt;&amp;nbsp;Standesamt&lt;/div&gt;","id":"a6l3u2htlwk3"},"type":"Feature","geometry":{"type":"Point","coordinates":[12.363452248239,51.338353002882]}},{"properties":{"description":"&lt;div&gt;&lt;span class=\"l\"&gt;Nummer:&lt;/span&gt;&amp;nbsp;7&lt;/div&gt;&lt;div&gt;&lt;span class=\"l\"&gt;Amt:&lt;/span&gt;&amp;nbsp;Referat Auslaenderbeauftragter&lt;/div&gt;","id":"a6l3u2hurau7"},"type":"Feature","geometry":{"type":"Point","coordinates":[12.37336203424,51.336152348829]}},{"properties":{"description":"&lt;div&gt;&lt;span class=\"l\"&gt;Nummer:&lt;/span&gt;&amp;nbsp;8&lt;/div&gt;&lt;div&gt;&lt;span class=\"l\"&gt;Amt:&lt;/span&gt;&amp;nbsp;Arbeitsamt&lt;/div&gt;","id":"a6l3u27d8hwb"},"type":"Feature","geometry":{"type":"Point","coordinates":[12.350940312447,51.366902325401]}},{"properties":{"description":"&lt;div&gt;&lt;span class=\"l\"&gt;Nummer:&lt;/span&gt;&amp;nbsp;9&lt;/div&gt;&lt;div&gt;&lt;span class=\"l\"&gt;Amt:&lt;/span&gt;&amp;nbsp;Regionalschulamt&lt;/div&gt;","id":"a6l3u2d4zc2k"},"type":"Feature","geometry":{"type":"Point","coordinates":[12.343115322443,51.328515206196]}},{"properties":{"description":"&lt;div&gt;&lt;span class=\"l\"&gt;Nummer:&lt;/span&gt;&amp;nbsp;10&lt;/div&gt;&lt;div&gt;&lt;span class=\"l\"&gt;Amt:&lt;/span&gt;&amp;nbsp;Flüchtlingsrat Leipzig e.V.&lt;/div&gt;","id":"a6l3u25t4mbq"},"type":"Feature","geometry":{"type":"Point","coordinates":[12.38046766786,51.334957769407]}}],"is_temporal":false,"author":{"url":"","metadata":"","contact_name":"","contact_address":"","source":"","contact_phone":""},"source":"","pagination":{"sort":null,"start":0,"total":10,"limit":1000000},"state":"complete","tags":"","published":"2014-08-14T20:33:32-04:00","id":254251}