{"type":"FeatureCollection","data_type":"Dataset","url_type":null,"permissions":[{"permissions":{"download":true,"view":true},"group_id":"everyone"}],"classification":null,"title":"cdot closed","count":2,"stream_id":255197,"contributor":{"url":"http://geocommons.com/users/28467","name":"bheberto"},"data_attributes":null,"calculation_params":null,"icon_link":null,"link":"http://geocommons.com/overlays/255197.json","extent":[-105.029,38.841,-104.86,38.9595],"geometry_types":["point"],"unique_name":null,"name":"cdot closed","feature_count":2,"description":"","next_feature":null,"is_raster":false,"short_classification":"Y","stats":{},"features":[{"properties":{"name":"Closed Road","description":"Due to wildfire. US 24 Westbound / Eastbound Woodland Park to 31st St. (Milemarker 288-303)Road closure began June 24th, 2012 at 9:41am. Alternate route is US 50 or US 285.","id":"a6nsawgz81or"},"type":"Feature","geometry":{"type":"Point","coordinates":[-104.859863,38.841045]}},{"properties":{"name":"Road Closed","description":"US 24 Westbound / Eastbound Woodland Park to 31st St. (Milemarker 288-303)due to wildfire. Road closure began June 24th, 2012 at 9:41am. Alternate route is US 50 or US 285.","id":"a6nsawcpt82j"},"type":"Feature","geometry":{"type":"Point","coordinates":[-105.028694,38.959476]}}],"is_temporal":false,"author":{"url":"","metadata":"","contact_name":"","contact_address":"","source":"","contact_phone":""},"source":"","pagination":{"sort":null,"start":0,"total":2,"limit":1000000},"state":"complete","tags":"","published":"2014-08-14T21:50:03-04:00","id":255197}