{"type":"FeatureCollection","data_type":"Dataset","url_type":null,"permissions":[{"permissions":{"download":true,"view":true},"group_id":"everyone"}],"classification":null,"title":"dirtparktest","count":1,"stream_id":255662,"contributor":{"url":"http://geocommons.com/users/48034","name":"haschomi"},"data_attributes":null,"calculation_params":null,"icon_link":null,"link":"http://geocommons.com/overlays/255662.json","extent":[12.6082,50.6524,12.6082,50.6524],"geometry_types":["point"],"unique_name":null,"name":"dirtparktest","feature_count":1,"description":"fasfa | Created with http://batchgeo.com","next_feature":null,"is_raster":false,"short_classification":"Y","stats":{},"features":[{"properties":{"name":"Dirtjump Grünau","description":"&lt;div&gt;&lt;span class=\"l\"&gt;Spezialisierung:&lt;/span&gt;&amp;nbsp;Dirtjump&lt;/div&gt;","id":"a6odl3zw0yym"},"type":"Feature","geometry":{"type":"Point","coordinates":[12.608209457809,50.652420433959]}}],"is_temporal":false,"author":{"url":"","metadata":"","contact_name":"","contact_address":"","source":"","contact_phone":""},"source":"","pagination":{"sort":null,"start":0,"total":1,"limit":1000000},"state":"complete","tags":"","published":"2014-08-14T22:22:29-04:00","id":255662}