{"type":"FeatureCollection","data_type":"Dataset","url_type":null,"permissions":[{"permissions":{"download":true,"edit":true,"view":true},"group_id":44833},{"permissions":{"download":true,"edit":true,"view":true},"group_id":"everyone"}],"classification":null,"title":"XMas Island.kml","count":1,"stream_id":258161,"contributor":{"url":"http://geocommons.com/users/40873","name":"fabianthegeocoder"},"data_attributes":null,"calculation_params":null,"icon_link":null,"link":"http://geocommons.com/overlays/258161.json","extent":[105.657,-10.4849,105.657,-10.4849],"geometry_types":["point"],"unique_name":null,"name":"XMas Island.kml","feature_count":1,"description":"This is where Santa lives","next_feature":null,"is_raster":false,"short_classification":"Y","stats":{},"features":[{"properties":{"name":"XMas Island","description":"This is where Santa lives!","id":"a6u8qyws2ttg"},"type":"Feature","geometry":{"type":"Point","coordinates":[105.656972434832,-10.4849007145327]}}],"is_temporal":false,"author":{"url":"","metadata":"","contact_name":"","contact_address":"","source":"","contact_phone":""},"source":"","pagination":{"sort":null,"start":0,"total":1,"limit":1000000},"state":"complete","tags":"santa","published":"2014-08-15T02:00:46-04:00","id":258161}