{"type":"FeatureCollection","data_type":"Dataset","url_type":null,"permissions":[{"permissions":{"download":true,"view":true},"group_id":"everyone"}],"classification":null,"title":"Sampel4.kmz","count":1,"stream_id":258140,"contributor":{"url":"http://geocommons.com/users/41143","name":"iqnaul"},"data_attributes":null,"calculation_params":null,"icon_link":null,"link":"http://geocommons.com/overlays/258140.json","extent":[106.287,-6.02938,106.287,-6.02938],"geometry_types":["point"],"unique_name":null,"name":"Sampel4.kmz","feature_count":1,"description":"","next_feature":null,"is_raster":false,"short_classification":"Y","stats":{},"features":[{"properties":{"name":"Sampel4","id":"a6u0qa4qtlzu"},"type":"Feature","geometry":{"type":"Point","coordinates":[106.286975499566,-6.02937687391674]}}],"is_temporal":false,"author":{"url":"","metadata":"","contact_name":"","contact_address":"","source":"","contact_phone":""},"source":"","pagination":{"sort":null,"start":0,"total":1,"limit":1000000},"state":"complete","tags":"","published":"2014-08-15T01:59:56-04:00","id":258140}