{"type":"FeatureCollection","data_type":"Dataset","url_type":null,"permissions":[{"permissions":{"download":true,"view":true},"group_id":"everyone"}],"classification":null,"title":"PE-M1088b","count":2,"stream_id":261961,"contributor":{"url":"http://geocommons.com/users/35812","name":"karenf"},"data_attributes":null,"calculation_params":null,"icon_link":null,"link":"http://geocommons.com/overlays/261961.json","extent":[-78.1667,-4.5,-78.0384,-4.16515],"geometry_types":["point"],"unique_name":null,"name":"PE-M1088b","feature_count":2,"description":"","next_feature":null,"is_raster":false,"short_classification":"Y","stats":{"latitude":{"max":-4.16515,"variance":0.0560622612500001,"mean":-4.332575,"stdev":0.236774705680316,"min":-4.5,"median":-4.16515},"longitude":{"max":-78.0384,"variance":0.00822659645000007,"mean":-78.102535,"stdev":0.0907005868227988,"min":-78.16667,"median":-78.0384},"oap":{"max":373,"variance":0.5,"mean":372.5,"stdev":0.707106781186548,"min":372,"median":373}},"features":[{"properties":{"city":"Condorcanqui","beneficiary characteristics":"Women, Men, Youth, Rural population, Indigenous population, Socially excluded population, Population with low educaction levels, Low income population","latitude":-4.16515,"country":"PERU","project number":"PE-M1088","oap":372,"longitude":-78.0384,"id":"a78zu4m48raq","state":"Amazonas"},"type":"Feature","geometry":{"type":"Point","coordinates":[-78.0384,-4.16515]}},{"properties":{"city":"Bagua","beneficiary characteristics":"Women, Men, Youth, Rural population, Indigenous population, Socially excluded population, Population with low educaction levels, Low income population","latitude":-4.5,"country":"PERU","project number":"PE-M1089","oap":373,"longitude":-78.16667,"id":"a78zu46er36x","state":"Amazonas"},"type":"Feature","geometry":{"type":"Point","coordinates":[-78.16667,-4.5]}}],"is_temporal":false,"author":{"url":"","metadata":null,"contact_name":null,"contact_address":null,"source":null,"contact_phone":null},"source":"","pagination":{"sort":null,"start":0,"total":2,"limit":1000000},"state":"complete","tags":"","published":"2014-08-14T17:33:37-04:00","id":261961}