{"type":"FeatureCollection","data_type":"Dataset","url_type":null,"permissions":[{"permissions":{"download":true,"view":true},"group_id":"everyone"}],"classification":null,"title":"Anglican_cathedrals","count":11,"stream_id":264413,"contributor":{"url":"http://geocommons.com/users/49790","name":"jonathanblaney"},"data_attributes":null,"calculation_params":null,"icon_link":null,"link":"http://geocommons.com/overlays/264413.json","extent":[-87.3245,-36.4167,148.067,47.7994],"geometry_types":["point"],"unique_name":null,"name":"Anglican_cathedrals","feature_count":11,"description":"","next_feature":null,"is_raster":false,"short_classification":"Y","stats":{},"features":[{"properties":{"city":"London, United Kingdom","postcode":"EC4M 8AD","geo_score":0.714,"cathedral":"St Paul's","id":"a7ixpldo4165","geo_precision":"zip"},"type":"Feature","geometry":{"type":"Point","coordinates":[-87.324482,41.580592]}},{"properties":{"city":"London, United Kingdom","postcode":"SE1 9DA","geo_score":0.714,"cathedral":"Southwark","id":"a7ixpl010m7y","geo_precision":"zip"},"type":"Feature","geometry":{"type":"Point","coordinates":[-87.324482,41.580592]}},{"properties":{"city":"York, United Kingdom","postcode":"YO1 7HH","geo_score":0.714,"cathedral":"York Minster","id":"a7ixpkxaety3","geo_precision":"zip"},"type":"Feature","geometry":{"type":"Point","coordinates":[12.4672222,-3.6730556]}},{"properties":{"city":"Lincoln, United Kingdom","postcode":"LN2 1PX","geo_score":0.857,"cathedral":"Lincoln","id":"a7ixplcwn5d0","geo_precision":"zip"},"type":"Feature","geometry":{"type":"Point","coordinates":[135.2,-36.4166667]}},{"properties":{"city":"Durham, United Kingdom","postcode":"DH1 3EH","geo_score":0.714,"cathedral":"Durham","id":"a7ixpl9vaqhl","geo_precision":"zip"},"type":"Feature","geometry":{"type":"Point","coordinates":[12.4672222,-3.6730556]}},{"properties":{"city":"Wells, United Kingdom","postcode":"BA5 2UE","geo_score":0.714,"cathedral":"Wells","id":"a7ixpl9c1hkl","geo_precision":"zip"},"type":"Feature","geometry":{"type":"Point","coordinates":[-87.324482,41.580592]}},{"properties":{"city":"Salisbury, United Kingdom","postcode":"SP1 2EJ","geo_score":0.714,"cathedral":"Salisbury","id":"a7ixpky5ipzw","geo_precision":"zip"},"type":"Feature","geometry":{"type":"Point","coordinates":[13.0439901351929,47.7994056435064]}},{"properties":{"city":"Winchester, United Kingdom","postcode":"SO23 9LS","geo_score":0.714,"cathedral":"Winchester","id":"a7ixpkxz32hf","geo_precision":"zip"},"type":"Feature","geometry":{"type":"Point","coordinates":[12.4672222,-3.6730556]}},{"properties":{"city":"Canterbury, United Kingdom","postcode":"CT1 2EH","geo_score":0.857,"cathedral":"Canterbury","id":"a7ixpkxz4b0n","geo_precision":"zip"},"type":"Feature","geometry":{"type":"Point","coordinates":[148.0666667,7.5]}},{"properties":{"city":"Ripon, United Kingdom","postcode":"HG4 1QS","geo_score":0.714,"cathedral":"Ripon","id":"a7ixpkzraq3c","geo_precision":"zip"},"type":"Feature","geometry":{"type":"Point","coordinates":[12.4672222,-3.6730556]}},{"properties":{"city":"Liverpool, United Kingdom","postcode":"L1 7AZ","geo_score":0.714,"cathedral":"Liverpool","id":"a7ixpl827o6x","geo_precision":"zip"},"type":"Feature","geometry":{"type":"Point","coordinates":[12.4672222,-3.6730556]}}],"is_temporal":false,"author":{"url":"","metadata":null,"contact_name":null,"contact_address":null,"source":null,"contact_phone":null},"source":"","pagination":{"sort":null,"start":0,"total":11,"limit":1000000},"state":"complete","tags":"","published":"2014-08-14T21:01:55-04:00","id":264413}