{"type":"FeatureCollection","data_type":"Dataset","url_type":null,"permissions":[{"permissions":{"download":true,"view":true},"group_id":"everyone"}],"classification":null,"title":"Daycares - Jamestown","count":4,"stream_id":267887,"contributor":{"url":"http://geocommons.com/users/50473","name":"KingstonGallowayANC"},"data_attributes":null,"calculation_params":null,"icon_link":null,"link":"http://geocommons.com/overlays/267887.json","extent":[-79.5949,43.7311,-79.5616,43.7446],"geometry_types":["point"],"unique_name":null,"name":"Daycares - Jamestown","feature_count":4,"description":"","next_feature":null,"is_raster":false,"short_classification":"Y","stats":{"latitude":{"max":43.74460565,"variance":3.45565611871962e-05,"mean":43.7379504875,"stdev":0.0058784828984353,"min":43.73111603,"median":43.74055535},"longitude":{"max":-79.56160881,"variance":0.000200822140184155,"mean":-79.5814163575,"stdev":0.014171172858453,"min":-79.59489232,"median":-79.58252285}},"features":[{"properties":{"neighbourhood name":"Rexdale","latitude":43.74055535,"establishment name":"Albion Child Care Centre","accessibility":null,"website":"www.toronto.ca/children/mccs","parking available":null,"postal code":"M9V 1B2","phone":"416-392-5083","fax":null,"capacity":null,"services":"- Fee Subsidy Contract\n- Public / Licensed Child Care: Infant, Toddler &amp; Pre School\n- Languages spoken by staff: Bengali, Croatian, German, and Italian","business hours":null,"longitude":-79.58664145,"id":"a7vco78l6nwx","address":"1545 Albion Rd.","personal requirements":"- serves children 0 to 6 years"},"type":"Feature","geometry":{"type":"Point","coordinates":[-79.58664145,43.74055535]}},{"properties":{"neighbourhood name":"Rexdale","latitude":43.73111603,"establishment name":"Albion Height School Age YMCA","accessibility":null,"website":"www.ymcatoronto.org","parking available":null,"postal code":"M9V 3W9","phone":"416-740-0747","fax":null,"capacity":null,"services":"- Fee Subsidy Contract\n- Licensed Child Care/Non Profit: School Age","business hours":null,"longitude":-79.59489232,"id":"a7vco6x7xew3","address":"45 Lynmont Rd.","personal requirements":"- serves children 6 years to 10 years"},"type":"Feature","geometry":{"type":"Point","coordinates":[-79.59489232,43.73111603]}},{"properties":{"neighbourhood name":"Rexdale","latitude":43.73552492,"establishment name":"Rexdale Day Nursery","accessibility":null,"website":"http://rexdaledaynursery.com/","parking available":null,"postal code":"M9V 1A6","phone":"416-743-5057","fax":null,"capacity":null,"services":"- Fee Subsidy Contract\n- Licensed Child Care / Non Profit : pre School &amp; School Age","business hours":null,"longitude":-79.56160881,"id":"a7vco6tvogfx","address":"925 Albion Rd.","personal requirements":"- serves children 2 years 6 months to 12 years"},"type":"Feature","geometry":{"type":"Point","coordinates":[-79.56160881,43.73552492]}},{"properties":{"neighbourhood name":"Rexdale","latitude":43.74460565,"establishment name":"St. Andrew Child Care Centre","accessibility":null,"website":"www.lefca.org","parking available":null,"postal code":"M9V 3A8","phone":"416-742-8253","fax":null,"capacity":null,"services":"- Fee Subsidy Contract\n- Licensed Child Care / Non Profit :  Infant, Toddler, Pre School\n &amp; School Age\n- Languages spoken by staff: Akan (Twi), Italian, Sinhala (Sinhalese), and Vietnamese","business hours":null,"longitude":-79.58252285,"id":"a7vco706nhe1","address":"2533 Kipling Ave.","personal requirements":"-  serves children 0 to 12 years"},"type":"Feature","geometry":{"type":"Point","coordinates":[-79.58252285,43.74460565]}}],"is_temporal":false,"author":{"url":"","metadata":"","contact_name":"","contact_address":"","source":"","contact_phone":""},"source":"","pagination":{"sort":null,"start":0,"total":4,"limit":1000000},"state":"complete","tags":"","published":"2014-08-15T01:28:53-04:00","id":267887}