{"type":"FeatureCollection","data_type":"Dataset","url_type":null,"permissions":[{"permissions":{"download":true,"view":true},"group_id":"everyone"}],"classification":null,"title":"Community Services-Scarborough","count":4,"stream_id":269223,"contributor":{"url":"http://geocommons.com/users/50467","name":"ScarboroughVillageANC"},"data_attributes":null,"calculation_params":null,"icon_link":null,"link":"http://geocommons.com/overlays/269223.json","extent":[-79.2208,43.7358,-79.2154,43.7438],"geometry_types":["point"],"unique_name":null,"name":"Community Services-Scarborough","feature_count":4,"description":"","next_feature":null,"is_raster":false,"short_classification":"Y","stats":{"latitude":{"max":43.74381335,"variance":1.80776756142242e-05,"mean":43.7397152375,"stdev":0.00425178499153288,"min":43.73578105,"median":43.74294592},"longitude":{"max":-79.21544799,"variance":6.48222289389887e-06,"mean":-79.219248995,"stdev":0.00254602099243091,"min":-79.22079603,"median":-79.22019498}},"features":[{"properties":{"neighbourhood name":null,"latitude":43.74381335,"establishment name":"Catholic Cross cultural Services- Settlement Integration Place (SIP)","accessibility":null,"website":"www.cathcrosscultural.org","parking available":"Parking Available","postal code":"M1J3M5","phone":"416-266-7200","fax":null,"capacity":null,"services":"Support for new comers in the integration process to the canadian society. Service offered in various languages. It also offers programs such as computer skills, conversation circles and senior's groups.","business hours":null,"longitude":-79.21544799,"id":"a80e4cja0yos","address":"3227 Eglinton Ave E Unit 135","personal requirements":"9am- 5pm"},"type":"Feature","geometry":{"type":"Point","coordinates":[-79.21544799,43.74381335]}},{"properties":{"neighbourhood name":null,"latitude":43.74294592,"establishment name":"Polycultural Immigrant and Community Services (PICS)","accessibility":null,"website":"www.polycultural.org","parking available":"Parking Available","postal code":"M1J2H3","phone":"416-261-4901","fax":null,"capacity":null,"services":"Support for new comers in the integration process to the canadian society. Service offered in various languages.Resume and job search orientation as well as, job fairs. Networking programs available. LINC classes: Monday to Friday 9:00 am- 2:30 pm","business hours":null,"longitude":-79.22055698,"id":"a80e4cgx6fay","address":"3174 Eglinton Ave E","personal requirements":"Monday 8:30pm - 6:30pm Tuesday to Friday 8.30 to 4.00"},"type":"Feature","geometry":{"type":"Point","coordinates":[-79.22055698,43.74294592]}},{"properties":{"neighbourhood name":"COOPERATIVES","latitude":43.73578105,"establishment name":"Gardenview Cooperative Homes Inc","accessibility":null,"website":null,"parking available":null,"postal code":"M1M 3W7","phone":"416-269-9669","fax":null,"capacity":null,"services":null,"business hours":null,"longitude":-79.22079603,"id":"a80e4cohj3u3","address":"3370 Kingston Rd.","personal requirements":null},"type":"Feature","geometry":{"type":"Point","coordinates":[-79.22079603,43.73578105]}},{"properties":{"neighbourhood name":null,"latitude":43.73632063,"establishment name":"Orchard Grove Housing Co-Operative Inc","accessibility":null,"website":null,"parking available":null,"postal code":"M1M 3W5","phone":"416-269-1724","fax":null,"capacity":null,"services":"Housing Programs","business hours":null,"longitude":-79.22019498,"id":"a80e4cq38rvx","address":"3392 Kingston Rd.","personal requirements":null},"type":"Feature","geometry":{"type":"Point","coordinates":[-79.22019498,43.73632063]}}],"is_temporal":false,"author":{"url":"","metadata":"","contact_name":"","contact_address":"","source":"","contact_phone":""},"source":"","pagination":{"sort":null,"start":0,"total":4,"limit":1000000},"state":"complete","tags":"","published":"2014-08-15T02:55:56-04:00","id":269223}