{"type":"FeatureCollection","data_type":"Dataset","url_type":null,"permissions":[{"permissions":{"download":true,"view":true},"group_id":"everyone"}],"classification":null,"title":"Tax Return Companies- Dorset Park","count":1,"stream_id":270781,"contributor":{"url":"http://geocommons.com/users/50470","name":"DorsetParkANC"},"data_attributes":null,"calculation_params":null,"icon_link":null,"link":"http://geocommons.com/overlays/270781.json","extent":[-79.271,43.761,-79.271,43.761],"geometry_types":["point"],"unique_name":null,"name":"Tax Return Companies- Dorset Park","feature_count":1,"description":"","next_feature":null,"is_raster":false,"short_classification":"Y","stats":{"latitude":{"max":43.761,"min":43.761,"median":43.761},"longitude":{"max":-79.271,"min":-79.271,"median":-79.271}},"features":[{"properties":{"neighbourhood name":"Dorset Park","additional information":null,"latitude":43.761,"establishment name":"M C Dilag Accounting and Tax Services","accessibility":null,"website":null,"parking available":null,"postal code":"M1P 5C7","phone":"647-342-3405","fax":null,"capacity":null,"services":null,"hours of operation":null,"longitude":-79.271,"id":"a865m5ousr7z","address":"8 Mondeo Drive, Scarborough, ON"},"type":"Feature","geometry":{"type":"Point","coordinates":[-79.271,43.761]}}],"is_temporal":false,"author":{"url":"","metadata":"","contact_name":"","contact_address":"","source":"","contact_phone":""},"source":"","pagination":{"sort":null,"start":0,"total":1,"limit":1000000},"state":"complete","tags":"","published":"2014-08-14T15:45:01-04:00","id":270781}