{"type":"FeatureCollection","data_type":"Dataset","url_type":null,"permissions":[{"permissions":{"download":true,"view":true},"group_id":"everyone"}],"classification":null,"title":"Daycares- Jane and Finch","count":4,"stream_id":270841,"contributor":{"url":"http://geocommons.com/users/50472","name":"JaneFinchANC"},"data_attributes":null,"calculation_params":null,"icon_link":null,"link":"http://geocommons.com/overlays/270841.json","extent":[-79.523,43.7511,-79.5136,43.7698],"geometry_types":["point"],"unique_name":null,"name":"Daycares- Jane and Finch","feature_count":4,"description":"","next_feature":null,"is_raster":false,"short_classification":"Y","stats":{"latitude":{"max":43.76982271,"variance":6.05824867544771e-05,"mean":43.7601400625,"stdev":0.00778347523632452,"min":43.75112165,"median":43.76160258},"longitude":{"max":-79.51355843,"variance":1.95740871167698e-05,"mean":-79.5180987975,"stdev":0.00442426119445606,"min":-79.52300458,"median":-79.51527281},"capacity":{"max":81,"min":81,"median":81}},"features":[{"properties":{"neighbourhood name":"Jane and Finch","latitude":43.75112165,"establishment name":"Tot World Daycare Centre","accessibility":null,"website":"www.totworldchildcare.com","parking available":"Yes","postal code":"M3N 1K1","phone":"416-638-3003","fax":"416-638-6087","capacity":81,"services":"- Toddlers (18-30m) $275 / week \n- Preschool (30m-6yrs) $250 / week \n- JK / SK (4-6yrs) $250 / week \n- School age (6-10yrs) $200 / week, summer: $215 / week","business hours":"M-F: 7am-6pm","longitude":-79.51355843,"id":"a868drbwjfde","address":"25 Yorkwoods Gate","personal requirements":null},"type":"Feature","geometry":{"type":"Point","coordinates":[-79.51355843,43.75112165]}},{"properties":{"neighbourhood name":"Jane and Finch","latitude":43.75801331,"establishment name":"Palisades Centre for Early Learning","accessibility":"Yes","website":"palisades@cfel.ca","parking available":"Yes","postal code":"M3N 2Y9","phone":"416-663-4431","fax":"416-663-1441","capacity":null,"services":"- Infant (0-18m) $77.25 / day \n- Toddler (18-30m) 57.75 / day \n- Preschool (2.5-4yrs) 44.25 / day \n- Kindergarten (4-6yrs) 44.25 / day \n- School age 41.72 / day","business hours":"M-F: 7am-6pm","longitude":-79.51527281,"id":"a868dqz70mrv","address":"15 San Romanoway","personal requirements":"Children school age and under"},"type":"Feature","geometry":{"type":"Point","coordinates":[-79.51527281,43.75801331]}},{"properties":{"neighbourhood name":"Jane and Finch","latitude":43.76982271,"establishment name":"Kids Kingdom Nursery School","accessibility":null,"website":null,"parking available":null,"postal code":"M3N 2Z5","phone":"416-663-2323","fax":null,"capacity":null,"services":null,"business hours":"M-F 7am-6pm","longitude":-79.52300458,"id":"a868dr68efcq","address":"225 Gosford Blvd.","personal requirements":"Ages 3-5mths, Subsidy Available"},"type":"Feature","geometry":{"type":"Point","coordinates":[-79.52300458,43.76982271]}},{"properties":{"neighbourhood name":"Jane and Finch","latitude":43.76160258,"establishment name":"Seafield Day Nursery","accessibility":null,"website":null,"parking available":null,"postal code":null,"phone":"416-663-0596","fax":null,"capacity":null,"services":null,"business hours":null,"longitude":-79.52055937,"id":"a868dqz0ztmu","address":"100 Yorkgate Blvd.","personal requirements":"Ages 3mths-5years"},"type":"Feature","geometry":{"type":"Point","coordinates":[-79.52055937,43.76160258]}}],"is_temporal":false,"author":{"url":"","metadata":"","contact_name":"","contact_address":"","source":"","contact_phone":""},"source":"","pagination":{"sort":null,"start":0,"total":4,"limit":1000000},"state":"complete","tags":"","published":"2014-08-14T15:47:58-04:00","id":270841}