{"type":"FeatureCollection","data_type":"Dataset","url_type":null,"permissions":[{"permissions":{"download":true,"view":true},"group_id":"everyone"}],"classification":null,"title":"Recreational Centres - Lotherton","count":4,"stream_id":271483,"contributor":{"url":"http://geocommons.com/users/50469","name":"LothertonANC"},"data_attributes":null,"calculation_params":null,"icon_link":null,"link":"http://geocommons.com/overlays/271483.json","extent":[-79.4752,43.7023,-79.4144,43.7225],"geometry_types":["point"],"unique_name":null,"name":"Recreational Centres - Lotherton","feature_count":4,"description":"","next_feature":null,"is_raster":false,"short_classification":"Y","stats":{"latitude":{"max":43.72254756,"variance":8.31592977953155e-05,"mean":43.7091535575,"stdev":0.00911917199066426,"min":43.70226873,"median":43.70676299},"longitude":{"max":-79.41440457,"variance":0.000650579643368881,"mean":-79.4496295675,"stdev":0.0255064627764981,"min":-79.4751796,"median":-79.45208673}},"features":[{"properties":{"neighbourhood name":"Lotherton","latitude":43.72254756,"establishment name":"Columbus Centre of Toronto","accessibility":"Yes","website":"http://www.villacharities.com/main.asp?View=Columbus","parking available":"Yes","postal code":"M6A1C3","phone":"416-789-7011","fax":null,"capacity":null,"services":"Community centre with Italian culture","business hours":null,"longitude":-79.41440457,"id":"a88vbueshk72","address":"901 Lawrence Ave. West","personal requirements":null},"type":"Feature","geometry":{"type":"Point","coordinates":[-79.41440457,43.72254756]}},{"properties":{"neighbourhood name":"Lotherton","latitude":43.70676299,"establishment name":"The Fitness Centre","accessibility":"Yes","website":"thefitnesscentre.ca","parking available":"Yes","postal code":"M6M2Y4","phone":"416-913-9033","fax":null,"capacity":null,"services":"Gym and fitness services","business hours":null,"longitude":-79.4751796,"id":"a88vbuoo4yyn","address":"32 Colville Rd.","personal requirements":null},"type":"Feature","geometry":{"type":"Point","coordinates":[-79.4751796,43.70676299]}},{"properties":{"neighbourhood name":"Lotherton","latitude":43.70503495,"establishment name":"Adrenalin FItness","accessibility":"Yes","website":"adrenalinfitness.ca","parking available":"Yes","postal code":"M6B1W3","phone":"416-782-2668","fax":null,"capacity":null,"services":"Fitness Services","business hours":"24 Hours","longitude":-79.45684737,"id":"a88vbuhjv9gj","address":"68 Tycos Dr.","personal requirements":null},"type":"Feature","geometry":{"type":"Point","coordinates":[-79.45684737,43.70503495]}},{"properties":{"neighbourhood name":"Lotherton","latitude":43.70226873,"establishment name":"Danceology","accessibility":null,"website":null,"parking available":null,"postal code":"M6B4J3","phone":"416-256-3999","fax":null,"capacity":null,"services":null,"business hours":null,"longitude":-79.45208673,"id":"a88vbukysvt1","address":"2700 Dufferin St.","personal requirements":null},"type":"Feature","geometry":{"type":"Point","coordinates":[-79.45208673,43.70226873]}}],"is_temporal":false,"author":{"url":"","metadata":"","contact_name":"","contact_address":"","source":"","contact_phone":""},"source":"","pagination":{"sort":null,"start":0,"total":4,"limit":1000000},"state":"complete","tags":"","published":"2014-08-14T16:31:54-04:00","id":271483}