{"type":"FeatureCollection","data_type":"Dataset","url_type":null,"permissions":[{"permissions":{"download":true,"view":true},"group_id":"everyone"}],"classification":null,"title":"Tax Return Companies - Lotherton","count":1,"stream_id":271488,"contributor":{"url":"http://geocommons.com/users/50469","name":"LothertonANC"},"data_attributes":null,"calculation_params":null,"icon_link":null,"link":"http://geocommons.com/overlays/271488.json","extent":[-79.4538,43.7088,-79.4538,43.7088],"geometry_types":["point"],"unique_name":null,"name":"Tax Return Companies - Lotherton","feature_count":1,"description":"","next_feature":null,"is_raster":false,"short_classification":"Y","stats":{"latitude":{"max":43.70878814,"min":43.70878814,"median":43.70878814},"longitude":{"max":-79.45377378,"min":-79.45377378,"median":-79.45377378}},"features":[{"properties":{"neighbourhood name":"Lotherton","latitude":43.70878814,"establishment name":"I.T.A Tax","accessibility":"Yes","website":null,"parking available":"Yes","postal code":"M6B 3S8","phone":"416-785-4548","fax":null,"capacity":null,"services":"Accounting Services","business hours":null,"longitude":-79.45377378,"id":"a88vdlzrf3nz","address":"2922 Dufferin Rd.","personal requirements":null},"type":"Feature","geometry":{"type":"Point","coordinates":[-79.45377378,43.70878814]}}],"is_temporal":false,"author":{"url":"","metadata":"","contact_name":"","contact_address":"","source":"","contact_phone":""},"source":"","pagination":{"sort":null,"start":0,"total":1,"limit":1000000},"state":"complete","tags":"","published":"2014-08-14T16:31:55-04:00","id":271488}