{"type":"FeatureCollection","data_type":"Dataset","url_type":null,"permissions":[{"permissions":{"download":true,"view":true},"group_id":"everyone"}],"classification":null,"title":"Banks- Lotherton","count":4,"stream_id":271471,"contributor":{"url":"http://geocommons.com/users/50469","name":"LothertonANC"},"data_attributes":null,"calculation_params":null,"icon_link":null,"link":"http://geocommons.com/overlays/271471.json","extent":[-79.4772,43.703,-79.4522,43.7089],"geometry_types":["point"],"unique_name":null,"name":"Banks- Lotherton","feature_count":4,"description":"","next_feature":null,"is_raster":false,"short_classification":"Y","stats":{"latitude":{"max":43.70888035,"variance":9.206912153173e-06,"mean":43.705947635,"stdev":0.00303428939838853,"min":43.70295857,"median":43.70822123},"longitude":{"max":-79.45225065,"variance":0.000150301750083428,"mean":-79.4588520275,"stdev":0.0122597614203307,"min":-79.47721499,"median":-79.45227797}},"features":[{"properties":{"neighbourhood name":"Lotherton","additional information":null,"latitude":43.70295857,"establishment name":"CIBC Bank","accessibility":"Yes","website":"cibc.com","parking available":"Yes","postal code":"M6B 3S6","phone":"416-781-5610","fax":null,"capacity":null,"services":"Financial Services","hours of operation":"M-W: 9:30am-4pm, Th-F: 9:30am-7pm, Sat: 9:30am-4pm","longitude":-79.45227797,"id":"a88v98623fvq","address":"2866 Dufferin Rd."},"type":"Feature","geometry":{"type":"Point","coordinates":[-79.45227797,43.70295857]}},{"properties":{"neighbourhood name":"Lotherton","additional information":null,"latitude":43.70888035,"establishment name":"Scotia Bank","accessibility":"Yes","website":"scotiabank.com","parking available":"Yes","postal code":"M6L 1A4","phone":"416-240-7600","fax":null,"capacity":null,"services":"Financial Services","hours of operation":"M-Sat: 9am-5pm, Sun: 10am-4pm","longitude":-79.47721499,"id":"a88v986lklbd","address":"1391 Lawrence Ave. West"},"type":"Feature","geometry":{"type":"Point","coordinates":[-79.47721499,43.70888035]}},{"properties":{"neighbourhood name":"Lotherton","additional information":null,"latitude":43.70822123,"establishment name":"IC Savings and Credit Union Limited","accessibility":"Yes","website":"icsavings.ca","parking available":"Yes","postal code":"M6B 3S8","phone":"416-784-4007","fax":null,"capacity":null,"services":"Credit Union with Banking Services","hours of operation":null,"longitude":-79.4536645,"id":"a88v98f7xhud","address":"2900 Dufferin St."},"type":"Feature","geometry":{"type":"Point","coordinates":[-79.4536645,43.70822123]}},{"properties":{"neighbourhood name":"Lotherton","additional information":null,"latitude":43.70373039,"establishment name":"Royal Bank of Canada","accessibility":"Yes","website":"rbcroyalbank.ca","parking available":"Yes","postal code":"M6B 3R6","phone":"416-789-7637","fax":null,"capacity":null,"services":"Financial Services","hours of operation":null,"longitude":-79.45225065,"id":"a88v98d01q86","address":"2765 Dufferin St."},"type":"Feature","geometry":{"type":"Point","coordinates":[-79.45225065,43.70373039]}}],"is_temporal":false,"author":{"url":"","metadata":"","contact_name":"","contact_address":"","source":"","contact_phone":""},"source":"","pagination":{"sort":null,"start":0,"total":4,"limit":1000000},"state":"complete","tags":"","published":"2014-08-14T16:31:52-04:00","id":271471}