{"type":"FeatureCollection","data_type":"Dataset","url_type":null,"permissions":[{"permissions":{"download":true,"view":true},"group_id":"everyone"}],"classification":null,"title":"Libraries- Victoria Village","count":1,"stream_id":271520,"contributor":{"url":"http://geocommons.com/users/50462","name":"ANCVictoriaVillage"},"data_attributes":null,"calculation_params":null,"icon_link":null,"link":"http://geocommons.com/overlays/271520.json","extent":[-79.3128,43.7361,-79.3128,43.7361],"geometry_types":["point"],"unique_name":null,"name":"Libraries- Victoria Village","feature_count":1,"description":"","next_feature":null,"is_raster":false,"short_classification":"Y","stats":{"latitude":{"max":43.73608499,"min":43.73608499,"median":43.73608499},"longitude":{"max":-79.31275,"min":-79.31275,"median":-79.31275}},"features":[{"properties":{"neighbourhood name":"Victoria Village","latitude":43.73608499,"establishment name":"Victoria Village Library","accessibility":"Yes","website":"torontopubliclibrary.ca","parking available":"Yes","postal code":"M4A 2C4","phone":"416-395-5950","fax":null,"capacity":null,"services":"meeting rooms available to rent; autobook and large print collections; Wi-Fi","business hours":"T:12:30am-8:30am W:10am- 6pm Thu: 12:30am-8:30pm    F:10am- 6pm Sat: 9am-5pm","longitude":-79.31275,"id":"a88yz7fy99lb","address":"184 Sloane Ave.","personal requirements":null},"type":"Feature","geometry":{"type":"Point","coordinates":[-79.31275,43.73608499]}}],"is_temporal":false,"author":{"url":"","metadata":"","contact_name":"","contact_address":"","source":"","contact_phone":""},"source":"","pagination":{"sort":null,"start":0,"total":1,"limit":1000000},"state":"complete","tags":"","published":"2014-08-14T16:33:10-04:00","id":271520}