{"type":"FeatureCollection","data_type":"Dataset","url_type":null,"permissions":[{"permissions":{"download":true,"view":true},"group_id":"everyone"}],"classification":null,"title":"Community Services- Kingston Galloway/ Orton Park","count":1,"stream_id":271762,"contributor":{"url":"http://geocommons.com/users/50473","name":"KingstonGallowayANC"},"data_attributes":null,"calculation_params":null,"icon_link":null,"link":"http://geocommons.com/overlays/271762.json","extent":[-79.1956,43.7637,-79.1956,43.7637],"geometry_types":["point"],"unique_name":null,"name":"Community Services- Kingston Galloway/ Orton Park","feature_count":1,"description":"","next_feature":null,"is_raster":false,"short_classification":"Y","stats":{"latitude":{"max":43.76372335,"min":43.76372335,"median":43.76372335},"longitude":{"max":-79.19561312,"min":-79.19561312,"median":-79.19561312}},"features":[{"properties":{"neighbourhood name":"Kingston - Galloway/Orton Park","latitude":43.76372335,"establishment name":"Ann Marie Hill Co-op Housing","accessibility":"Yes","website":"http://annmariehillhousingco-op.blogspot.ca/","parking available":"Yes","postal code":"M1E 5A5","phone":"416-281- 5313","fax":"416-281-5324","capacity":null,"services":null,"business hours":null,"longitude":-79.19561312,"id":"a89wnv6pjid3","address":"170 Galloway Rd.","personal requirements":null},"type":"Feature","geometry":{"type":"Point","coordinates":[-79.19561312,43.76372335]}}],"is_temporal":false,"author":{"url":"","metadata":"","contact_name":"","contact_address":"","source":"","contact_phone":""},"source":"","pagination":{"sort":null,"start":0,"total":1,"limit":1000000},"state":"complete","tags":"","published":"2014-08-14T16:54:48-04:00","id":271762}