{"type":"FeatureCollection","data_type":"Dataset","url_type":null,"permissions":[{"permissions":{"download":true,"view":true},"group_id":"everyone"}],"classification":null,"title":"CS1","count":1,"stream_id":275326,"contributor":{"url":"http://geocommons.com/users/3995","name":"amazon"},"data_attributes":null,"calculation_params":null,"icon_link":null,"link":"http://geocommons.com/overlays/275326.json","extent":[-84.5731,37.8857,-84.5731,37.8857],"geometry_types":["point"],"unique_name":null,"name":"CS1","feature_count":1,"description":"","next_feature":null,"is_raster":false,"short_classification":"Y","stats":{"total market value":{"max":1058718.67,"min":1058718.67,"median":1058718.67},"market value of real estate":{"max":708718.67,"min":708718.67,"median":708718.67},"market value of tax credits":{"max":350000,"min":350000,"median":350000},"gross income":{"max":239400,"min":239400,"median":239400}},"features":[{"properties":{"name":"Creekside Senior Apartments","city":"Nicholasville","zip":"40356","market value of real estate":708718.67,"total market value":1058718.67,"market value of tax credits":350000,"geo_score":0.927,"gross income":239400,"id":"a8ozuqnar0gr","address":"407 North 2nd Street","geo_precision":"range","state":"KY"},"type":"Feature","geometry":{"type":"Point","coordinates":[-84.573061,37.885727]}}],"is_temporal":false,"author":{"url":"","metadata":"","contact_name":"","contact_address":"","source":"","contact_phone":""},"source":"","pagination":{"sort":null,"start":0,"total":1,"limit":1000000},"state":"complete","tags":"","published":"2012-09-18T16:00:00Z","id":275326}