{"type":"FeatureCollection","data_type":"Dataset","url_type":null,"permissions":[{"permissions":{"download":true,"view":true},"group_id":"everyone"}],"classification":null,"title":"MERI_Integration_of_Roma_Immigrants","count":3,"stream_id":280674,"contributor":{"url":"http://geocommons.com/users/51733","name":"Rasenov"},"data_attributes":null,"calculation_params":null,"icon_link":null,"link":"http://geocommons.com/overlays/280674.json","extent":[2.25,48.45,10.0005,53.3355],"geometry_types":["point"],"unique_name":null,"name":"MERI_Integration_of_Roma_Immigrants","feature_count":3,"description":"","next_feature":null,"is_raster":false,"short_classification":"Y","stats":{"latitude":{"max":53.3355,"variance":7.80621626333334,"mean":50.1097666666667,"stdev":2.79396067676933,"min":48.45,"median":48.5438},"population":{"max":1800000,"variance":813500333333.333,"mean":1049666.66666667,"stdev":901942.533276557,"min":49000,"median":1300000},"share of roma population, %":{"max":1.0,"variance":0.27,"mean":0.4,"stdev":0.519615242270663,"min":0.1,"median":0.1},"longitude":{"max":10.0005,"variance":19.99169013,"mean":4.8376,"stdev":4.4712067867635,"min":2.25,"median":2.2623}},"features":[{"properties":{"award":"Gold","the municipality":null,"latitude":48.5438,"mayor":"Catherine Peyge","title":"Integration of Roma Immigrants","country":"France","population":49000,"share of roma population, %":1.0,"the mayor":null,"longitude":2.2623,"id":"a9383chvva2c","settlement":"Bobigny","the case":null,"sector":"Integration of Roma immigrants"},"type":"Feature","geometry":{"type":"Point","coordinates":[2.2623,48.5438]}},{"properties":{"award":"Silver","the municipality":null,"latitude":53.3355,"mayor":"Olaf Scholz","title":"Work-based Activities with Roma and Sinti","country":"Germany","population":1800000,"share of roma population, %":0.1,"the mayor":null,"longitude":10.0005,"id":"a9383conr0kd","settlement":"Hamburg","the case":null,"sector":"Integration of Roma immigrants"},"type":"Feature","geometry":{"type":"Point","coordinates":[10.0005,53.3355]}},{"properties":{"award":"Bronze","the municipality":null,"latitude":48.45,"mayor":"Alain Desmartes (1st Vice-President)","title":"Integration of Roma Immigrants","country":"France","population":1300000,"share of roma population, %":0.1,"the mayor":null,"longitude":2.25,"id":"a9383ce6z9sd","settlement":"Val-de-Marne department","the case":null,"sector":"Integration of Roma immigrants"},"type":"Feature","geometry":{"type":"Point","coordinates":[2.25,48.45]}}],"is_temporal":false,"author":{"url":"","metadata":null,"contact_name":null,"contact_address":null,"source":null,"contact_phone":null},"source":"","pagination":{"sort":null,"start":0,"total":3,"limit":1000000},"state":"complete","tags":"","published":"2014-08-14T15:39:55-04:00","id":280674}