{"type":"FeatureCollection","data_type":"Dataset","url_type":null,"permissions":[{"permissions":{"download":true,"view":true},"group_id":"everyone"}],"classification":null,"title":"Mobile_Food_Pantry_Sites","count":1,"stream_id":282659,"contributor":{"url":"http://geocommons.com/users/48522","name":"aedonica"},"data_attributes":null,"calculation_params":null,"icon_link":null,"link":"http://geocommons.com/overlays/282659.json","extent":[-86.1568,39.8021,-86.1568,39.8021],"geometry_types":["point"],"unique_name":null,"name":"Mobile_Food_Pantry_Sites","feature_count":1,"description":"","next_feature":null,"is_raster":false,"short_classification":"Y","stats":{},"features":[{"properties":{"city":"Indianapolis","organization name":"Flanner House","geo_score":0.783,"id":"a96qzvdi6lir","geo_precision":"range","address":"609 Edgemont Avenue","state":"IN"},"type":"Feature","geometry":{"type":"Point","coordinates":[-86.156763,39.802132]}}],"is_temporal":false,"author":{"url":"","metadata":null,"contact_name":null,"contact_address":null,"source":null,"contact_phone":null},"source":"","pagination":{"sort":null,"start":0,"total":1,"limit":1000000},"state":"complete","tags":"","published":"2014-08-14T17:55:38-04:00","id":282659}