{"type":"FeatureCollection","data_type":"Dataset","url_type":null,"permissions":[{"permissions":{"download":true,"view":true},"group_id":"everyone"}],"classification":null,"title":"Estación Biológica de Arguedas/Arguedas Biological Station","count":1,"stream_id":284214,"contributor":{"url":"http://geocommons.com/users/53706","name":"gurelur"},"data_attributes":null,"calculation_params":null,"icon_link":null,"link":"http://geocommons.com/overlays/284214.json","extent":[-1.57786,42.1517,-1.57786,42.1517],"geometry_types":["point"],"unique_name":null,"name":"Estación Biológica de Arguedas/Arguedas Biological Station","feature_count":1,"description":"","next_feature":null,"is_raster":false,"short_classification":"Y","stats":{"latitude":{"max":42.151693,"min":42.151693,"median":42.151693},"longitude":{"max":-1.577862,"min":-1.577862,"median":-1.577862}},"features":[{"properties":{"latitude":42.151693,"longitude":-1.577862,"id":"a9bynms3gat0","location":"Arguedas","state":"Spain"},"type":"Feature","geometry":{"type":"Point","coordinates":[-1.577862,42.151693]}}],"is_temporal":false,"author":{"url":"","metadata":"","contact_name":"GURELUR","contact_address":"C/Manuel de Falla, 8\r\n31005 Pamplona/Iruña\r\n\r\nwww.gurelur.org","source":"","contact_phone":""},"source":"","pagination":{"sort":null,"start":0,"total":1,"limit":1000000},"state":"complete","tags":"","published":"2014-08-14T19:57:58-04:00","id":284214}