{"type":"FeatureCollection","data_type":"Dataset","url_type":null,"permissions":[{"permissions":{"download":true,"view":true},"group_id":"everyone"}],"classification":null,"title":"geo","count":1,"stream_id":284623,"contributor":{"url":"http://geocommons.com/users/53824","name":"christineg"},"data_attributes":null,"calculation_params":null,"icon_link":null,"link":"http://geocommons.com/overlays/284623.json","extent":[-122.197,37.5121,-122.197,37.5121],"geometry_types":["point"],"unique_name":null,"name":"geo","feature_count":1,"description":"","next_feature":null,"is_raster":false,"short_classification":"Y","stats":{},"features":[{"properties":{"name":"","description":"<a href=\"http://www.flickr.com/photos/10453110@N08/8094101242/\"><img src=\"http://farm9.staticflickr.com/8470/8094101242_f752842b2a.jpg\"></a>\n\t\t\t\t\t<a href=\"http://www.flickr.com/photos/10453110@N08/8094101242/\"><img src=\"http://l.yimg.com/g/images/simple_new_window_default.gif\" height=\"10\" width=\"13\"></a> <a href=\"http://www.flickr.com/photos/10453110@N08/8094101242/\">Open photo page</a>\n&lt;a href=\"http://loc.alize.us/#/flickr:8094101242\" rel=\"nofollow\"&gt;See where this picture was taken.&lt;/a&gt; &lt;a href=\"http://www.flickr.com/groups/geotagging/discuss/72157594165549916/\"&gt;[?]&lt;/a&gt;\n&lt;a href=\"http://loc.alize.us/#/flickr:8094101242\" rel=\"nofollow\"&gt;See where this picture was taken.&lt;/a&gt; &lt;a href=\"http://www.flickr.com/groups/geotagging/discuss/72157594165549916/\"&gt;[?]&lt;/a&gt;<img src=\"http://l.yimg.com/g/images/spaceball.gif\" height=\"15\" width=\"15\">Taken on 13th October, 2012&amp;nbsp;by&amp;nbsp;<a href=\"http://api.flickr.com/services/feeds/geo/?id=10453110@N08&amp;format=kml_nl&amp;lang=en-us\"><b>cong.christine</b></a><img src=\"http://l.yimg.com/g/images/icon_tag_left.gif\" height=\"15\" width=\"15\"><a href=\"http://api.flickr.com/services/feeds/geo/?tags=geotagged&amp;format=kml_nl&amp;lang=en-us\">geotagged</a>,&amp;nbsp; <a href=\"http://api.flickr.com/services/feeds/geo/?tags=geo:lat=3751209517851206&amp;format=kml_nl&amp;lang=en-us\">geo:lat=3751209517851206</a>,&amp;nbsp; <a href=\"http://api.flickr.com/services/feeds/geo/?tags=geo:lon=12219723163178708&amp;format=kml_nl&amp;lang=en-us\">geo:lon=12219723163178708</a><img src=\"http://l.yimg.com/g/images/icon_public.gif\" height=\"15\" width=\"15\"> Anyone can see this location","id":"a9dfuea5mryj"},"type":"Feature","geometry":{"type":"Point","coordinates":[-122.197231,37.512095]}}],"is_temporal":false,"author":{"url":"","metadata":null,"contact_name":null,"contact_address":null,"source":null,"contact_phone":null},"source":"","pagination":{"sort":null,"start":0,"total":1,"limit":1000000},"state":"complete","tags":"","published":"2014-08-14T20:28:26-04:00","id":284623}