{"type":"FeatureCollection","data_type":"Dataset","url_type":null,"permissions":[{"permissions":{"download":true,"view":true},"group_id":"everyone"}],"classification":null,"title":"DTRTMIAPjustMTSO","count":1,"stream_id":284913,"contributor":{"url":"http://geocommons.com/users/12008","name":"pantheon"},"data_attributes":null,"calculation_params":null,"icon_link":null,"link":"http://geocommons.com/overlays/284913.json","extent":[-83.271,42.4428,-83.271,42.4428],"geometry_types":["point"],"unique_name":null,"name":"DTRTMIAPjustMTSO","feature_count":1,"description":"","next_feature":null,"is_raster":false,"short_classification":"Y","stats":{"int_connect_long":{"max":-83.27099,"min":-83.27099,"median":-83.27099},"int_connect_lata":{"max":340,"min":340,"median":340},"int_connect_lat":{"max":42.44276,"min":42.44276,"median":42.44276},"int_connect_zip":{"max":48219,"min":48219,"median":48219}},"features":[{"properties":{"int_connect_long":-83.27099,"int_connect_type":"MTSO","int_connect_clli":"DTRTMIAP","int_connect_address":"23201 W 8 Mile Rd","int_connect_st":"MI","int_connect_lata":340,"int_connect_lat":42.44276,"int_connect_swc":"DTRTMIRF","id":"a9e6escl043b","int_connect_city":"Detroit","int_connect_zip":48219},"type":"Feature","geometry":{"type":"Point","coordinates":[-83.27099,42.44276]}}],"is_temporal":false,"author":{"url":"","metadata":"","contact_name":"","contact_address":"","source":"","contact_phone":""},"source":"","pagination":{"sort":null,"start":0,"total":1,"limit":1000000},"state":"complete","tags":"","published":"2014-08-14T21:00:48-04:00","id":284913}