{"type":"FeatureCollection","data_type":"Dataset","url_type":null,"permissions":[{"permissions":{"download":true,"view":true},"group_id":"everyone"}],"classification":null,"title":"mtsoCRAFPAAI","count":5,"stream_id":284909,"contributor":{"url":"http://geocommons.com/users/12008","name":"pantheon"},"data_attributes":null,"calculation_params":null,"icon_link":null,"link":"http://geocommons.com/overlays/284909.json","extent":[-81.4516,39.8514,-80.8291,40.0614],"geometry_types":["point"],"unique_name":null,"name":"mtsoCRAFPAAI","feature_count":5,"description":"","next_feature":null,"is_raster":false,"short_classification":"Y","stats":{"longitude cs":{"max":-80.82907104,"variance":0.0507099974144492,"mean":-81.14823761,"stdev":0.225188803927836,"min":-81.45156097,"median":-81.15805817},"mtso lata":{"max":234,"variance":0.0,"mean":234.0,"stdev":0.0,"min":234,"median":234},"fa cs":{"max":10125310,"variance":343442564.8,"mean":10098274.4,"stdev":18532.2034523691,"min":10082074,"median":10093490},"lata cs":{"max":324,"variance":0.0,"mean":324.0,"stdev":0.0,"min":324,"median":324},"latitude cs":{"max":40.06138992,"variance":0.00936401628426209,"mean":39.990291594,"stdev":0.096767847368132,"min":39.85142899,"median":40.05443954},"zip cs":{"max":43942,"variance":9681.3,"mean":43773.4,"stdev":98.3935973526733,"min":43713,"median":43719}},"features":[{"properties":{"longitude cs":-80.82907104,"umts mtso":"CRAFPAAI","state cs":"OH","mtso lata":234,"need by date":"3/31/2013","lata cs":324,"fa cs":10093490,"latitude cs":39.85142899,"ethernet bandwidth required":"2 * 100Mb/S EVCs","zip cs":43942,"id":"a9e6bgx4tmn3","city cs":"POWHATAN POINT","address cs":"54158 POWHATAN HILL ROAD","county cs":"BELMONT","swc cs":"PWPNOHXA"},"type":"Feature","geometry":{"type":"Point","coordinates":[-80.82907104,39.85142899]}},{"properties":{"longitude cs":-81.0847168,"umts mtso":"CRAFPAAI","state cs":"OH","mtso lata":234,"need by date":"3/31/2013","lata cs":324,"fa cs":10082074,"latitude cs":40.05443954,"ethernet bandwidth required":"2 * 100Mb/S EVCs","zip cs":43719,"id":"a9e6bh3ifa7e","city cs":"BETHESDA","address cs":"66485 WILSON ROAD","county cs":"BELMONT","swc cs":"MRTWOHXA"},"type":"Feature","geometry":{"type":"Point","coordinates":[-81.0847168,40.05443954]}},{"properties":{"longitude cs":-81.15805817,"umts mtso":"CRAFPAAI","state cs":"OH","mtso lata":234,"need by date":"3/31/2013","lata cs":324,"fa cs":10082226,"latitude cs":40.06138992,"ethernet bandwidth required":"2 * 100Mb/S EVCs","zip cs":43713,"id":"a9e6bgvmjbxm","city cs":"BARNESVILLE","address cs":"5 COUNTY ROAD 108 / OLD NATIONAL PIKE","county cs":"BELMONT","swc cs":"FRVWOHXA"},"type":"Feature","geometry":{"type":"Point","coordinates":[-81.15805817,40.06138992]}},{"properties":{"longitude cs":-81.21778107,"umts mtso":"CRAFPAAI","state cs":"OH","mtso lata":234,"need by date":"9/30/2013","lata cs":324,"fa cs":10108272,"latitude cs":40.05916977,"ethernet bandwidth required":"2 * 50Mb/S EVCs","zip cs":43713,"id":"a9e6bh0qpv4j","city cs":"BARNESVILLE","address cs":"32745 OLD NATIONAL ROAD","county cs":"BELMONT","swc cs":"FRVWOHXA"},"type":"Feature","geometry":{"type":"Point","coordinates":[-81.21778107,40.05916977]}},{"properties":{"longitude cs":-81.45156097,"umts mtso":"CRAFPAAI","state cs":"OH","mtso lata":234,"need by date":"2014","lata cs":324,"fa cs":10125310,"latitude cs":39.92502975,"ethernet bandwidth required":"2 * 50Mb/S EVCs","zip cs":43780,"id":"a9e6bguqcaux","city cs":"SENECAVILLE","address cs":"15568 HATCHERY ROAD","county cs":"GUERNSEY","swc cs":"BYVLOHXA"},"type":"Feature","geometry":{"type":"Point","coordinates":[-81.45156097,39.92502975]}}],"is_temporal":false,"author":{"url":"","metadata":"","contact_name":"","contact_address":"","source":"","contact_phone":""},"source":"","pagination":{"sort":null,"start":0,"total":5,"limit":1000000},"state":"complete","tags":"","published":"2014-08-14T21:00:47-04:00","id":284909}