{"type":"FeatureCollection","data_type":"Dataset","url_type":null,"permissions":[{"permissions":{"download":true,"view":true},"group_id":"everyone"}],"classification":null,"title":"IPLYINCPjustMTSO","count":1,"stream_id":284904,"contributor":{"url":"http://geocommons.com/users/12008","name":"pantheon"},"data_attributes":null,"calculation_params":null,"icon_link":null,"link":"http://geocommons.com/overlays/284904.json","extent":[-86.0397,39.9186,-86.0397,39.9186],"geometry_types":["point"],"unique_name":null,"name":"IPLYINCPjustMTSO","feature_count":1,"description":"","next_feature":null,"is_raster":false,"short_classification":"Y","stats":{"int_connect_long":{"max":-86.03973,"min":-86.03973,"median":-86.03973},"int_connect_lata":{"max":336,"min":336,"median":336},"int_connect_lat":{"max":39.91864,"min":39.91864,"median":39.91864},"int_connect_zip":{"max":46256,"min":46256,"median":46256}},"features":[{"properties":{"int_connect_long":-86.03973,"int_connect_type":"MTSO","int_connect_clli":"IPLYINCP","int_connect_address":"7336 E 90th St","int_connect_st":"IN","int_connect_lata":336,"int_connect_lat":39.91864,"int_connect_swc":"FSHRIN01","id":"a9e5yt4z9q16","int_connect_city":"Indianapolis","int_connect_zip":46256},"type":"Feature","geometry":{"type":"Point","coordinates":[-86.03973,39.91864]}}],"is_temporal":false,"author":{"url":"","metadata":"","contact_name":"","contact_address":"","source":"","contact_phone":""},"source":"","pagination":{"sort":null,"start":0,"total":1,"limit":1000000},"state":"complete","tags":"","published":"2014-08-14T21:00:41-04:00","id":284904}