{"type":"FeatureCollection","data_type":"Dataset","url_type":null,"permissions":[{"permissions":{"download":true,"view":true},"group_id":"everyone"}],"classification":null,"title":"rhein ","count":5,"stream_id":287554,"contributor":{"url":"http://geocommons.com/users/46810","name":"marievi"},"data_attributes":null,"calculation_params":null,"icon_link":null,"link":"http://geocommons.com/overlays/287554.json","extent":[6.60151,51.5239,6.77663,51.6461],"geometry_types":["point"],"unique_name":null,"name":"rhein ","feature_count":5,"description":"","next_feature":null,"is_raster":false,"short_classification":"Y","stats":{"latitude":{"max":51.646146,"variance":0.00420120648970009,"mean":51.5750188,"stdev":0.0648167145858234,"min":51.523885,"median":51.533496},"longitude":{"max":6.77663,"variance":0.0053827403075,"mean":6.6762,"stdev":0.0733671609611548,"min":6.601514,"median":6.697193}},"features":[{"properties":{"latitude":51.533496,"longitude":6.77663,"id":"a9mybpokqbvn"},"type":"Feature","geometry":{"type":"Point","coordinates":[6.77663,51.533496]}},{"properties":{"latitude":51.646146,"longitude":6.606281,"id":"a9mybq0nx4as"},"type":"Feature","geometry":{"type":"Point","coordinates":[6.606281,51.646146]}},{"properties":{"latitude":51.64568,"longitude":6.601514,"id":"a9mybpupibum"},"type":"Feature","geometry":{"type":"Point","coordinates":[6.601514,51.64568]}},{"properties":{"latitude":51.525887,"longitude":6.699382,"id":"a9mybprmgrum"},"type":"Feature","geometry":{"type":"Point","coordinates":[6.699382,51.525887]}},{"properties":{"latitude":51.523885,"longitude":6.697193,"id":"a9mybq32g7gi"},"type":"Feature","geometry":{"type":"Point","coordinates":[6.697193,51.523885]}}],"is_temporal":false,"author":{"url":"","metadata":"","contact_name":"","contact_address":"","source":"","contact_phone":""},"source":"","pagination":{"sort":null,"start":0,"total":5,"limit":1000000},"state":"complete","tags":"","published":"2014-08-15T00:41:37-04:00","id":287554}