{"type":"FeatureCollection","data_type":"Dataset","url_type":null,"permissions":[{"permissions":{"download":true,"view":true},"group_id":"everyone"}],"classification":null,"title":"phuser8","count":10,"stream_id":292747,"contributor":{"url":"http://geocommons.com/users/55629","name":"penrorizal"},"data_attributes":null,"calculation_params":null,"icon_link":null,"link":"http://geocommons.com/overlays/292747.json","extent":[121.041,14.6493,121.046,14.6522],"geometry_types":["point"],"unique_name":null,"name":"phuser8","feature_count":10,"description":"","next_feature":null,"is_raster":false,"short_classification":"Y","stats":{"latitude":{"max":14.65222,"variance":1.33353777777745e-06,"mean":14.650874,"stdev":0.00115478906202711,"min":14.64929,"median":14.65119},"id no.":{"max":10,"variance":9.16666666666667,"mean":5.5,"stdev":3.02765035409749,"min":1,"median":6},"longitude":{"max":121.0457,"variance":2.5997433333367e-06,"mean":121.043989,"stdev":0.00161237195874175,"min":121.04135,"median":121.04506}},"features":[{"properties":{"id no.":1,"latitude":14.65217,"phuser8":"Bulwagan Gate","date recorded":"November 13 2012","locality":"DENR PAWB","longitude":121.04272,"id":"aa03q8p76vp5"},"type":"Feature","geometry":{"type":"Point","coordinates":[121.04272,14.65217]}},{"properties":{"id no.":2,"latitude":14.65222,"phuser8":"Basketball Ring","date recorded":"November 13 2012","locality":"DENR PAWB","longitude":121.04402,"id":"aa03q8i3nscd"},"type":"Feature","geometry":{"type":"Point","coordinates":[121.04402,14.65222]}},{"properties":{"id no.":3,"latitude":14.65208,"phuser8":"Gate Two","date recorded":"November 13 2012","locality":"DENR PAWB","longitude":121.04521,"id":"aa03q8m3bliv"},"type":"Feature","geometry":{"type":"Point","coordinates":[121.04521,14.65208]}},{"properties":{"id no.":4,"latitude":14.65119,"phuser8":"Rescue Gate","date recorded":"November 13 2012","locality":"DENR PAWB","longitude":121.0457,"id":"aa03q8m46jpq"},"type":"Feature","geometry":{"type":"Point","coordinates":[121.0457,14.65119]}},{"properties":{"id no.":5,"latitude":14.65035,"phuser8":"Ninoy Statue","date recorded":"November 13 2012","locality":"DENR PAWB","longitude":121.04525,"id":"aa03q8n5vdgn"},"type":"Feature","geometry":{"type":"Point","coordinates":[121.04525,14.65035]}},{"properties":{"id no.":6,"latitude":14.64944,"phuser8":"Gate One","date recorded":"November 13 2012","locality":"DENR PAWB","longitude":121.04555,"id":"aa03q8lbdjhf"},"type":"Feature","geometry":{"type":"Point","coordinates":[121.04555,14.64944]}},{"properties":{"id no.":7,"latitude":14.64998,"phuser8":"Hawk Eagle Cage","date recorded":"November 13 2012","locality":"DENR PAWB","longitude":121.04506,"id":"aa03q8vt23iy"},"type":"Feature","geometry":{"type":"Point","coordinates":[121.04506,14.64998]}},{"properties":{"id no.":8,"latitude":14.64929,"phuser8":"EDC-DENR Aboretum Site","date recorded":"November 13 2012","locality":"DENR PAWB","longitude":121.04318,"id":"aa03q8htse4w"},"type":"Feature","geometry":{"type":"Point","coordinates":[121.04318,14.64929]}},{"properties":{"id no.":9,"latitude":14.65021,"phuser8":"Tea House","date recorded":"November 13 2012","locality":"DENR PAWB","longitude":121.04185,"id":"aa03q8rv72p6"},"type":"Feature","geometry":{"type":"Point","coordinates":[121.04185,14.65021]}},{"properties":{"id no.":10,"latitude":14.65181,"phuser8":"Cottage","date recorded":"November 13 2012","locality":"DENR PAWB","longitude":121.04135,"id":"aa03q8oxozpt"},"type":"Feature","geometry":{"type":"Point","coordinates":[121.04135,14.65181]}}],"is_temporal":false,"author":{"url":"","metadata":"","contact_name":"","contact_address":"","source":"","contact_phone":""},"source":"","pagination":{"sort":null,"start":0,"total":10,"limit":1000000},"state":"complete","tags":"","published":"2014-08-14T19:21:38-04:00","id":292747}