{"type":"FeatureCollection","data_type":"Dataset","url_type":null,"permissions":[{"permissions":{"download":true,"view":true},"group_id":"everyone"}],"classification":null,"title":"Hydroelectric_Power_Plant_Information","count":4,"stream_id":296234,"contributor":{"url":"http://geocommons.com/users/55259","name":"Zaheera"},"data_attributes":null,"calculation_params":null,"icon_link":null,"link":"http://geocommons.com/overlays/296234.json","extent":[32.131,-25.21,33.493,-15.5866],"geometry_types":["point"],"unique_name":null,"name":"Hydroelectric_Power_Plant_Information","feature_count":4,"description":"","next_feature":null,"is_raster":false,"short_classification":"Y","stats":{"latitude":{"max":-15.5865807,"mean":-19.8697243725,"variance":15.8303201066554,"stdev":3.97873348022401,"median":-19.15631679,"min":-25.21},"longitude":{"max":33.493,"mean":32.86822949,"variance":0.345670548424525,"stdev":0.587937537859699,"median":33.14450741,"min":32.131}},"features":[{"properties":{"city":"Tete","latitude":-15.5865807,"region":"Tete","hydroelectric power plant":"Cahora Bassa","longitude":32.70441055,"id":"aa5b1uecxuqn"},"type":"Feature","geometry":{"type":"Point","coordinates":[32.70441055,-15.5865807]}},{"properties":{"city":null,"latitude":-19.15631679,"region":"Manica","hydroelectric power plant":"Chicamba","longitude":33.14450741,"id":"aa5b1uj8dyaf"},"type":"Feature","geometry":{"type":"Point","coordinates":[33.14450741,-19.15631679]}},{"properties":{"city":"Alizana","latitude":-25.21,"region":"Mapute","hydroelectric power plant":"Corumana","longitude":32.131,"id":"aa5b1uhj4ftz"},"type":"Feature","geometry":{"type":"Point","coordinates":[32.131,-25.21]}},{"properties":{"city":"Maria","latitude":-19.526,"region":"Manica","hydroelectric power plant":"Mavuzi","longitude":33.493,"id":"aa5b1ui23557"},"type":"Feature","geometry":{"type":"Point","coordinates":[33.493,-19.526]}}],"is_temporal":false,"author":{"url":"","metadata":null,"contact_name":null,"contact_address":null,"source":null,"contact_phone":null},"source":"","pagination":{"sort":null,"start":0,"total":4,"limit":1000000},"state":"complete","tags":"","published":"2014-08-14T23:07:12-04:00","id":296234}