{"type":"FeatureCollection","data_type":"Dataset","url_type":null,"permissions":[{"permissions":{"download":true,"view":true},"group_id":"everyone"}],"classification":null,"title":"Suppression 8","count":1,"stream_id":303479,"contributor":{"url":"http://geocommons.com/users/54770","name":"ASehon"},"data_attributes":null,"calculation_params":null,"icon_link":null,"link":"http://geocommons.com/overlays/303479.json","extent":[-84.5047,38.0383,-84.5047,38.0383],"geometry_types":["point"],"unique_name":null,"name":"Suppression 8","feature_count":1,"description":"Someone leaked plans of the sit-in to university officials days before the planned action. As a result, the main campus area was overpopulated with UKPD, Lexington police, and even unmarked special agents.\n\nThe obvious show of force both excites and upsets students; The Administration are listening, but they are forcing students out of their own spaces.\n\nThe Main Building is locked down. Tension weighs on each participant.","next_feature":null,"is_raster":false,"short_classification":"Y","stats":{},"features":[{"properties":{"name":"Suppression","description":"Someone leaked plans of the sit-in to university officials days before the planned action. As a result, the main campus area was overpopulated with UKPD, Lexington police, and even unmarked special agents.\n\nThe obvious show of force both excites and upsets students; The Administration are listening, but they are forcing students out of their own spaces.\n\nThe Main Building is locked down. Tension weighs on each participant.","id":"aal9oe9i3v0p"},"type":"Feature","geometry":{"type":"Point","coordinates":[-84.5047270871836,38.0382773228765]}}],"is_temporal":false,"author":{"url":"","metadata":null,"contact_name":null,"contact_address":null,"source":null,"contact_phone":null},"source":"","pagination":{"sort":null,"start":0,"total":1,"limit":1000000},"state":"complete","tags":"","published":"2014-08-16T17:16:25-04:00","id":303479}