{"type":"FeatureCollection","data_type":"Dataset","url_type":null,"permissions":[{"permissions":{"download":true,"view":true},"group_id":"everyone"}],"classification":null,"title":"Natural-_Parks","count":5,"stream_id":304926,"contributor":{"url":"http://geocommons.com/users/50476","name":"ThorncliffeParkANC"},"data_attributes":null,"calculation_params":null,"icon_link":null,"link":"http://geocommons.com/overlays/304926.json","extent":[-79.3595,43.7024,-79.3426,43.718],"geometry_types":["point"],"unique_name":null,"name":"Natural-_Parks","feature_count":5,"description":"","next_feature":null,"is_raster":false,"short_classification":"Y","stats":{"latitude":{"max":43.717988,"variance":5.62489567999699e-05,"mean":43.7079136,"stdev":0.00749993045300888,"min":43.702368,"median":43.70262},"longitude":{"max":-79.342578,"variance":5.2924456999995e-05,"mean":-79.349631,"stdev":0.00727491972464267,"min":-79.359531,"median":-79.350098}},"features":[{"properties":{"neighbourhood name":"Thorncliffe Park","latitude":43.702368,"column_10":null,"establishment name":"Leaside Park","column_11":null,"column_12":null,"column_13":null,"website":"http://www.toronto.ca/parks/prd/facilities/complex/425/index.htm","column_9":null,"column_14":null,"postal code":"M4H 1R1","services":"- Ball Diamond\n- Club House\n- Playground\n- Splash Pad\n- Sports Field","longitude":-79.350098,"id":"aapi5g9ds8io","address":"5 Leaside Park Dr."},"type":"Feature","geometry":{"type":"Point","coordinates":[-79.350098,43.702368]}},{"properties":{"neighbourhood name":"Thorncliffe Park","latitude":43.713972,"column_10":null,"establishment name":"Leonard Linton Park","column_11":null,"column_12":null,"column_13":null,"website":"http://www.toronto.ca/parks/prd/facilities/complex/1501/index.htm","column_9":null,"column_14":null,"postal code":"M4G 1P2","services":"basketball courts","longitude":-79.35337,"id":"aapi5fvvxb0s","address":"135 Vanderhoof Ave."},"type":"Feature","geometry":{"type":"Point","coordinates":[-79.35337,43.713972]}},{"properties":{"neighbourhood name":"Thorncliffe Park","latitude":43.70262,"column_10":null,"establishment name":"RV Burgess Park","column_11":null,"column_12":null,"column_13":null,"website":"http://www.toronto.ca/parks/prd/facilities/complex/423/index.htm","column_9":null,"column_14":null,"postal code":"M4H 1J7","services":"playgrounds; splash pad","longitude":-79.342578,"id":"aapi5fwym3f6","address":"46 Thorncliffe Park Dr."},"type":"Feature","geometry":{"type":"Point","coordinates":[-79.342578,43.70262]}},{"properties":{"neighbourhood name":"Thorncliffe Park","latitude":43.70262,"column_10":null,"establishment name":"Flemingdon Park","column_11":null,"column_12":null,"column_13":null,"website":"http://www.toronto.ca/parks/prd/facilities/complex/585/index.htm","column_9":null,"column_14":null,"postal code":"M3C 1E3","services":"baseball diamond; splash pad; playground","longitude":-79.342578,"id":"aapi5fv5kcmq","address":"150 Grenoble Dr."},"type":"Feature","geometry":{"type":"Point","coordinates":[-79.342578,43.70262]}},{"properties":{"neighbourhood name":"Thorncliffe Park","latitude":43.717988,"column_10":null,"establishment name":"Serena Gundy Park","column_11":null,"column_12":null,"column_13":null,"website":"http://www.toronto.ca/parks/prd/facilities/complex/26/index.htm","column_9":null,"column_14":null,"postal code":"M4G 2S9","services":null,"longitude":-79.359531,"id":"aapi5fu3yx8n","address":"58 Rykert Cres."},"type":"Feature","geometry":{"type":"Point","coordinates":[-79.359531,43.717988]}}],"is_temporal":false,"author":{"url":"","metadata":null,"contact_name":null,"contact_address":null,"source":null,"contact_phone":null},"source":"","pagination":{"sort":null,"start":0,"total":5,"limit":1000000},"state":"complete","tags":"","published":"2014-08-16T19:09:09-04:00","id":304926}