{"type":"FeatureCollection","url":"http://www.worldweatheronline.com/v2/rss.ashx?q=-6.1406,106.611&custom_header=Jakarta","data_type":"Data Feed","url_type":"rss","permissions":[{"permissions":{"download":true,"view":true},"group_id":"everyone"}],"classification":null,"title":"test","count":3,"stream_id":306326,"contributor":{"url":"http://geocommons.com/users/56311","name":"banjironline"},"data_attributes":null,"calculation_params":null,"icon_link":null,"link":"http://geocommons.com/overlays/306326.json","extent":[97.05,19.2333,97.05,19.2333],"geometry_types":["point"],"unique_name":null,"name":"test","feature_count":3,"description":"","next_feature":null,"is_raster":false,"short_classification":"Y","stats":{},"features":[{"properties":{"title":"Current weather: Partly Cloudy","geo_score":0.714,"description":"<img src=\"http://www.worldweatheronline.com/images/wsymbols01_png_64/wsymbol_0004_black_low_cloud.png\"><b>Temp: </b>27°c (81°f)<b>Wind: </b>W at 7 mph (11 kmph)","link":"http://www.worldweatheronline.com/weather.aspx?q=-6.1406,106.611&amp;custom_header=Jakarta","id":"aahg26o3xtlq","geo_precision":"zip"},"type":"Feature","geometry":{"type":"Point","coordinates":[97.05,19.2333333]}},{"properties":{"title":"Today's weather: Sunny","geo_score":0.714,"description":"<img src=\"http://www.worldweatheronline.com/images/wsymbols01_png_64/wsymbol_0001_sunny.png\"><b>High: </b>34°c (94°f); <b>Low: </b>27°c (80°f)<b>Wind: </b>WSW at 14 mph (22 kmph)","link":"http://www.worldweatheronline.com/weather.aspx?q=-6.1406,106.611&amp;custom_header=Jakarta&amp;day=0","id":"aahg26opqbi9","geo_precision":"zip"},"type":"Feature","geometry":{"type":"Point","coordinates":[97.05,19.2333333]}},{"properties":{"title":"Tomorrow's weather: Light rain shower","geo_score":0.714,"description":"<img src=\"http://www.worldweatheronline.com/images/wsymbols01_png_64/wsymbol_0009_light_rain_showers.png\"><b>High: </b>32°c (89°f); <b>Low: </b>28°c (82°f)<b>Wind: </b>WNW at 11 mph (18 kmph)","link":"http://www.worldweatheronline.com/weather.aspx?q=-6.1406,106.611&amp;custom_header=Jakarta&amp;day=1","id":"aahg272jx15a","geo_precision":"zip"},"type":"Feature","geometry":{"type":"Point","coordinates":[97.05,19.2333333]}}],"is_temporal":false,"author":{"url":"","metadata":"","contact_name":"","contact_address":"","source":"","contact_phone":""},"source":"","pagination":{"sort":null,"start":0,"total":3,"limit":1000000},"state":"complete","tags":"","published":"2014-08-16T20:54:48-04:00","id":306326}