{"type":"FeatureCollection","data_type":"Dataset","url_type":null,"permissions":[{"permissions":{"download":true,"view":true},"group_id":"everyone"}],"classification":null,"title":"plant_AH","count":1,"stream_id":311022,"contributor":{"url":"http://geocommons.com/users/58913","name":"xfeng33"},"data_attributes":null,"calculation_params":null,"icon_link":null,"link":"http://geocommons.com/overlays/311022.json","extent":[-117.769,33.6403,-117.769,33.6403],"geometry_types":["point"],"unique_name":null,"name":"plant_AH","feature_count":1,"description":"","next_feature":null,"is_raster":false,"short_classification":"Y","stats":{},"features":[{"properties":{"warehouse":"Anaheim","geo_score":0.714,"zip code":"92806","id":"abft87jjgylf","geo_precision":"zip"},"type":"Feature","geometry":{"type":"Point","coordinates":[-117.769442,33.640302]}}],"is_temporal":false,"author":{"url":"","metadata":null,"contact_name":null,"contact_address":null,"source":null,"contact_phone":null},"source":"","pagination":{"sort":null,"start":0,"total":1,"limit":1000000},"state":"complete","tags":"","published":"2014-08-16T14:14:45-04:00","id":311022}