{"type":"FeatureCollection","data_type":"Dataset","url_type":null,"permissions":[{"permissions":{"download":true,"view":true},"group_id":"everyone"}],"classification":null,"title":"757-300 Rons-Rads","count":17,"stream_id":312568,"contributor":{"url":"http://geocommons.com/users/38310","name":"Dlforecastdemand"},"data_attributes":null,"calculation_params":null,"icon_link":null,"link":"http://geocommons.com/overlays/312568.json","extent":[-157.922,12.131,-66.0018,47.449],"geometry_types":["point"],"unique_name":null,"name":"757-300 Rons-Rads","feature_count":17,"description":"","next_feature":null,"is_raster":false,"short_classification":"Y","stats":{"latitude":{"max":47.44900131,"mean":32.2033058058824,"variance":89.7736515651257,"stdev":9.4748958603842,"median":33.43429947,"min":12.13099957},"rons rads":{"max":365,"mean":102.941176470588,"variance":14154.8088235294,"stdev":118.97398380961,"median":62,"min":1},"longitude":{"max":-66.00180054,"mean":-98.1058645729412,"variance":581.099601502015,"stdev":24.1060075811407,"median":-93.22180176,"min":-157.9219971}},"features":[{"properties":{"latitude":33.63669968,"airport code":"ATL","rons rads":302,"longitude":-84.42810059,"id":"abkjen5i7rxg"},"type":"Feature","geometry":{"type":"Point","coordinates":[-84.42810059,33.63669968]}},{"properties":{"latitude":30.19449997,"airport code":"AUS","rons rads":1,"longitude":-97.66989899,"id":"abkjemxzgazd"},"type":"Feature","geometry":{"type":"Point","coordinates":[-97.66989899,30.19449997]}},{"properties":{"latitude":12.13099957,"airport code":"BON","rons rads":5,"longitude":-68.26850128,"id":"abkjempz3lqe"},"type":"Feature","geometry":{"type":"Point","coordinates":[-68.26850128,12.13099957]}},{"properties":{"latitude":39.17539978,"airport code":"BWI","rons rads":1,"longitude":-76.66829681,"id":"abkjen3c9638"},"type":"Feature","geometry":{"type":"Point","coordinates":[-76.66829681,39.17539978]}},{"properties":{"latitude":42.21239853,"airport code":"DTW","rons rads":146,"longitude":-83.35340118,"id":"abkjemvsanb7"},"type":"Feature","geometry":{"type":"Point","coordinates":[-83.35340118,42.21239853]}},{"properties":{"latitude":26.07259941,"airport code":"FLL","rons rads":58,"longitude":-80.15270233,"id":"abkjemttswbi"},"type":"Feature","geometry":{"type":"Point","coordinates":[-80.15270233,26.07259941]}},{"properties":{"latitude":21.31870079,"airport code":"HNL","rons rads":93,"longitude":-157.9219971,"id":"abkjen0isv8w"},"type":"Feature","geometry":{"type":"Point","coordinates":[-157.9219971,21.31870079]}},{"properties":{"latitude":36.08010101,"airport code":"LAS","rons rads":88,"longitude":-115.1520004,"id":"abkjemwv31pq"},"type":"Feature","geometry":{"type":"Point","coordinates":[-115.1520004,36.08010101]}},{"properties":{"latitude":33.94250107,"airport code":"LAX","rons rads":93,"longitude":-118.4079971,"id":"abkjemzohhwq"},"type":"Feature","geometry":{"type":"Point","coordinates":[-118.4079971,33.94250107]}},{"properties":{"latitude":28.42939949,"airport code":"MCO","rons rads":339,"longitude":-81.30899811,"id":"abkjemzyd6z6"},"type":"Feature","geometry":{"type":"Point","coordinates":[-81.30899811,28.42939949]}},{"properties":{"latitude":44.88199997,"airport code":"MSP","rons rads":365,"longitude":-93.22180176,"id":"abkjemvbek9o"},"type":"Feature","geometry":{"type":"Point","coordinates":[-93.22180176,44.88199997]}},{"properties":{"latitude":33.43429947,"airport code":"PHX","rons rads":94,"longitude":-112.012001,"id":"abkjemvowaav"},"type":"Feature","geometry":{"type":"Point","coordinates":[-112.012001,33.43429947]}},{"properties":{"latitude":26.53619957,"airport code":"RSW","rons rads":62,"longitude":-81.75520325,"id":"abkjemvm9b2d"},"type":"Feature","geometry":{"type":"Point","coordinates":[-81.75520325,26.53619957]}},{"properties":{"latitude":32.73360062,"airport code":"SAN","rons rads":1,"longitude":-117.1900024,"id":"abkjemtq1ui0"},"type":"Feature","geometry":{"type":"Point","coordinates":[-117.1900024,32.73360062]}},{"properties":{"latitude":47.44900131,"airport code":"SEA","rons rads":62,"longitude":-122.3089981,"id":"abkjemxh523j"},"type":"Feature","geometry":{"type":"Point","coordinates":[-122.3089981,47.44900131]}},{"properties":{"latitude":18.43939972,"airport code":"SJU","rons rads":10,"longitude":-66.00180054,"id":"abkjemzy1fjp"},"type":"Feature","geometry":{"type":"Point","coordinates":[-66.00180054,18.43939972]}},{"properties":{"latitude":40.78839874,"airport code":"SLC","rons rads":30,"longitude":-111.9779968,"id":"abkjen3flvkd"},"type":"Feature","geometry":{"type":"Point","coordinates":[-111.9779968,40.78839874]}}],"is_temporal":false,"author":{"url":"","metadata":"","contact_name":"","contact_address":"","source":"","contact_phone":""},"source":"","pagination":{"sort":null,"start":0,"total":17,"limit":1000000},"state":"complete","tags":"","published":"2014-08-16T16:19:01-04:00","id":312568}