{"type":"FeatureCollection","data_type":"Dataset","url_type":null,"permissions":[{"permissions":{"download":true,"view":true},"group_id":"everyone"}],"classification":null,"title":"767-300 Rons-Rads","count":14,"stream_id":312612,"contributor":{"url":"http://geocommons.com/users/38310","name":"Dlforecastdemand"},"data_attributes":null,"calculation_params":null,"icon_link":null,"link":"http://geocommons.com/overlays/312612.json","extent":[-157.922,18.5674,-68.3634,47.449],"geometry_types":["point"],"unique_name":null,"name":"767-300 Rons-Rads","feature_count":14,"description":"","next_feature":null,"is_raster":false,"short_classification":"Y","stats":{"latitude":{"max":47.44900131,"mean":32.65982151,"variance":92.9508092729791,"stdev":9.64110000326618,"median":33.94250107,"min":18.56739998},"rons rads":{"max":218,"mean":66.2857142857143,"variance":5728.52747252747,"stdev":75.6870363571429,"median":38,"min":1},"longitude":{"max":-68.36340332,"mean":-108.440035132857,"variance":744.638346921588,"stdev":27.2880623519074,"median":-111.9779968,"min":-157.9219971}},"features":[{"properties":{"latitude":33.63669968,"airport code":"ATL","rons rads":218,"longitude":-84.42810059,"id":"abkjx6clxkkb"},"type":"Feature","geometry":{"type":"Point","coordinates":[-84.42810059,33.63669968]}},{"properties":{"latitude":21.03650093,"airport code":"CUN","rons rads":4,"longitude":-86.87709808,"id":"abkjx6l4gn4a"},"type":"Feature","geometry":{"type":"Point","coordinates":[-86.87709808,21.03650093]}},{"properties":{"latitude":42.21239853,"airport code":"DTW","rons rads":184,"longitude":-83.35340118,"id":"abkjx6euwjtg"},"type":"Feature","geometry":{"type":"Point","coordinates":[-83.35340118,42.21239853]}},{"properties":{"latitude":26.07259941,"airport code":"FLL","rons rads":2,"longitude":-80.15270233,"id":"abkjx6bi1ly8"},"type":"Feature","geometry":{"type":"Point","coordinates":[-80.15270233,26.07259941]}},{"properties":{"latitude":21.31870079,"airport code":"HNL","rons rads":2,"longitude":-157.9219971,"id":"abkjx6fjrl2m"},"type":"Feature","geometry":{"type":"Point","coordinates":[-157.9219971,21.31870079]}},{"properties":{"latitude":36.08010101,"airport code":"LAS","rons rads":92,"longitude":-115.1520004,"id":"abkjx6jqzf2e"},"type":"Feature","geometry":{"type":"Point","coordinates":[-115.1520004,36.08010101]}},{"properties":{"latitude":33.94250107,"airport code":"LAX","rons rads":186,"longitude":-118.4079971,"id":"abkjx6cckbg4"},"type":"Feature","geometry":{"type":"Point","coordinates":[-118.4079971,33.94250107]}},{"properties":{"latitude":44.88199997,"airport code":"MSP","rons rads":59,"longitude":-93.22180176,"id":"abkjx6lspxww"},"type":"Feature","geometry":{"type":"Point","coordinates":[-93.22180176,44.88199997]}},{"properties":{"latitude":20.89859962,"airport code":"OGG","rons rads":1,"longitude":-156.4299927,"id":"abkjx68rco7m"},"type":"Feature","geometry":{"type":"Point","coordinates":[-156.4299927,20.89859962]}},{"properties":{"latitude":18.56739998,"airport code":"PUJ","rons rads":10,"longitude":-68.36340332,"id":"abkjx6bj7siu"},"type":"Feature","geometry":{"type":"Point","coordinates":[-68.36340332,18.56739998]}},{"properties":{"latitude":32.73360062,"airport code":"SAN","rons rads":30,"longitude":-117.1900024,"id":"abkjx6dipxht"},"type":"Feature","geometry":{"type":"Point","coordinates":[-117.1900024,32.73360062]}},{"properties":{"latitude":47.44900131,"airport code":"SEA","rons rads":38,"longitude":-122.3089981,"id":"abkjx6b9q0tt"},"type":"Feature","geometry":{"type":"Point","coordinates":[-122.3089981,47.44900131]}},{"properties":{"latitude":37.61899948,"airport code":"SFO","rons rads":37,"longitude":-122.375,"id":"abkjx6kgel0n"},"type":"Feature","geometry":{"type":"Point","coordinates":[-122.375,37.61899948]}},{"properties":{"latitude":40.78839874,"airport code":"SLC","rons rads":65,"longitude":-111.9779968,"id":"abkjx69yaogj"},"type":"Feature","geometry":{"type":"Point","coordinates":[-111.9779968,40.78839874]}}],"is_temporal":false,"author":{"url":"","metadata":"","contact_name":"","contact_address":"","source":"","contact_phone":""},"source":"","pagination":{"sort":null,"start":0,"total":14,"limit":1000000},"state":"complete","tags":"","published":"2014-08-16T16:21:38-04:00","id":312612}