{"type":"FeatureCollection","data_type":"Dataset","url_type":null,"permissions":[{"permissions":{"download":true,"view":true},"group_id":"everyone"}],"classification":null,"title":"geocode","count":18,"stream_id":313701,"contributor":{"url":"http://geocommons.com/users/59583","name":"sylco"},"data_attributes":null,"calculation_params":null,"icon_link":null,"link":"http://geocommons.com/overlays/313701.json","extent":[-117.162,31.1689,139.741,50.7323],"geometry_types":["point"],"unique_name":null,"name":"geocode","feature_count":18,"description":"","next_feature":null,"is_raster":false,"short_classification":"Y","stats":{"latitute":{"max":50.7323,"mean":41.5571542222222,"variance":34.3631863735135,"stdev":5.8620121437535,"median":42.366791,"min":31.168895},"longitude":{"max":139.740921,"mean":-24.7279121111111,"variance":5424.33380241392,"stdev":73.6500767305365,"median":-3.705774,"min":-117.16172}},"features":[{"properties":{"latitute":47.548807,"longitude":7.58782,"id":"abny1yu27n1w"},"type":"Feature","geometry":{"type":"Point","coordinates":[7.58782,47.548807]}},{"properties":{"latitute":44.836635,"longitude":-0.581039,"id":"abny1yxaa1uq"},"type":"Feature","geometry":{"type":"Point","coordinates":[-0.581039,44.836635]}},{"properties":{"latitute":42.358631,"longitude":-71.056702,"id":"abny1z3w0bnu"},"type":"Feature","geometry":{"type":"Point","coordinates":[-71.056702,42.358631]}},{"properties":{"latitute":42.376438,"longitude":-71.235321,"id":"abny1z3wi4zi"},"type":"Feature","geometry":{"type":"Point","coordinates":[-71.235321,42.376438]}},{"properties":{"latitute":35.99527,"longitude":-78.896011,"id":"abny1yv3ulu6"},"type":"Feature","geometry":{"type":"Point","coordinates":[-78.896011,35.99527]}},{"properties":{"latitute":42.440491,"longitude":-76.495453,"id":"abny1ysafjww"},"type":"Feature","geometry":{"type":"Point","coordinates":[-76.495453,42.440491]}},{"properties":{"latitute":42.366791,"longitude":-71.106018,"id":"abny1z6mhngy"},"type":"Feature","geometry":{"type":"Point","coordinates":[-71.106018,42.366791]}},{"properties":{"latitute":38.98225,"longitude":-77.087669,"id":"abny1yuw7wlm"},"type":"Feature","geometry":{"type":"Point","coordinates":[-77.087669,38.98225]}},{"properties":{"latitute":35.098129,"longitude":135.718933,"id":"abny1z5t2edf"},"type":"Feature","geometry":{"type":"Point","coordinates":[135.718933,35.098129]}},{"properties":{"latitute":39.739256,"longitude":-89.504093,"id":"abny1z48vedr"},"type":"Feature","geometry":{"type":"Point","coordinates":[-89.504093,39.739256]}},{"properties":{"latitute":40.4203,"longitude":-3.705774,"id":"abny1z7a5cal"},"type":"Feature","geometry":{"type":"Point","coordinates":[-3.705774,40.4203]}},{"properties":{"latitute":48.136415,"longitude":11.577531,"id":"abny1z4rhron"},"type":"Feature","geometry":{"type":"Point","coordinates":[11.577531,48.136415]}},{"properties":{"latitute":48.85693,"longitude":2.3412,"id":"abny1z0g4br3"},"type":"Feature","geometry":{"type":"Point","coordinates":[2.3412,48.85693]}},{"properties":{"latitute":35.670479,"longitude":139.740921,"id":"abny1z0aeysu"},"type":"Feature","geometry":{"type":"Point","coordinates":[139.740921,35.670479]}},{"properties":{"latitute":32.715679,"longitude":-117.16172,"id":"abny1yt9ti8y"},"type":"Feature","geometry":{"type":"Point","coordinates":[-117.16172,32.715679]}},{"properties":{"latitute":48.58508,"longitude":7.73643,"id":"abny1yr5xvac"},"type":"Feature","geometry":{"type":"Point","coordinates":[7.73643,48.58508]}},{"properties":{"latitute":31.168895,"longitude":-100.077148,"id":"abny1yxn8mhb"},"type":"Feature","geometry":{"type":"Point","coordinates":[-100.077148,31.168895]}},{"properties":{"latitute":50.7323,"longitude":7.101695,"id":"abny1z3kxrso"},"type":"Feature","geometry":{"type":"Point","coordinates":[7.101695,50.7323]}}],"is_temporal":false,"author":{"url":"","metadata":"","contact_name":"","contact_address":"","source":"","contact_phone":""},"source":"","pagination":{"sort":null,"start":0,"total":18,"limit":1000000},"state":"complete","tags":"","published":"2014-08-16T18:18:35-04:00","id":313701}