{"type":"FeatureCollection","data_type":"Dataset","url_type":null,"permissions":[{"permissions":{"download":true,"view":true},"group_id":"everyone"}],"classification":null,"title":"Wetland Bird Callback Survey","count":16,"stream_id":314929,"contributor":{"url":"http://geocommons.com/users/59896","name":"jfischer"},"data_attributes":null,"calculation_params":null,"icon_link":null,"link":"http://geocommons.com/overlays/314929.json","extent":[-73.2179,41.7137,-73.1952,41.7359],"geometry_types":["point"],"unique_name":null,"name":"Wetland Bird Callback Survey","feature_count":16,"description":"White Memorial conserves over 800 acreas of freshwater wetland habitat.  Marsh birds such as Virginia Rail and Sora are secretive and difficult to observe, yet are some of the best indicator species of wetland habitat viability.  Recorded calls are broadcast at various points in the marsh to elicit a callback by the resident birds in the area.\r\n\r\n&lt;img src=&quot;https://f2a527b0-a-62cb3a1a-s-sites.googlegroups.com/site/wildlifemonitorkmzfiles/config/pagetemplates/wildlife-monitor-file-cabinet/Virginia%20Rail%2C%20Little%20Pond%2C%20by%20Paul%20Fusco%5B1%5D.jpg?attachauth=ANoY7con06ynes-TSbweMNblcErFTkjLSrUYiQPtY4QSuE3wpa_wtmn2hXF3DN1H3gB1WfDsEwSF8VLOjsW2OrebAQMUd0-u1wVgufdNWcejl_tIC0x7XylrnLkPTyJpivS2gqexwYtsVkR7_oIdaqFEsGlgtw7b1I38w2bQNVgKZ4daTysv6jne-rdY1TsE2QInXILdMhcrC2B1ybhT9QapaeAYSqaVkDM0kre6y_OiAOQuAGslKyxKwWIZTpLwP_J0QovxtTFVrOYKF1g36_5ypldJzCYUT2gymATtO90QQC_LGkCb4a7Y7KtTirNaQoeP3ZfkB_ml0zpQKoVYzqe68vLThgErWqAMyv93cJ9zO6L2okVlLqk%3D&amp;attredirects=0&quot;/&gt;","next_feature":null,"is_raster":false,"short_classification":"Y","stats":{},"features":[{"properties":{"name":"Wetland Callback Survey Point #1","id":"abqmdnkily0l"},"type":"Feature","geometry":{"type":"Point","coordinates":[-73.1969109892573,41.7346333955298]}},{"properties":{"name":"Wetland Callback Survey Point #2","id":"abqmdncil3ke"},"type":"Feature","geometry":{"type":"Point","coordinates":[-73.2010567906212,41.733511667047]}},{"properties":{"name":"Wetland Callback Survey Point #3","id":"abqmdnoettjy"},"type":"Feature","geometry":{"type":"Point","coordinates":[-73.1983952416404,41.7294252421939]}},{"properties":{"name":"Wetland Callback Survey Point #4","id":"abqmdnhnvbtw"},"type":"Feature","geometry":{"type":"Point","coordinates":[-73.2018509760893,41.7359307923692]}},{"properties":{"name":"Wetland Callback Survey Point #5","id":"abqmdne6khpf"},"type":"Feature","geometry":{"type":"Point","coordinates":[-73.2081069843523,41.7338257600905]}},{"properties":{"name":"Wetland Callback Survey Point #6","id":"abqmdnlblzmx"},"type":"Feature","geometry":{"type":"Point","coordinates":[-73.2127165997923,41.7300833375239]}},{"properties":{"name":"Wetland Callback Survey Point #7","id":"abqmdndvusdl"},"type":"Feature","geometry":{"type":"Point","coordinates":[-73.2084738909454,41.7309404531114]}},{"properties":{"name":"Wetland Callback Survey Point #8","id":"abqmdng2m7dn"},"type":"Feature","geometry":{"type":"Point","coordinates":[-73.2001988112122,41.7238906893706]}},{"properties":{"name":"Wetland Callback Survey Point #9","id":"abqmdnhs67xm"},"type":"Feature","geometry":{"type":"Point","coordinates":[-73.1984803282306,41.726078817356]}},{"properties":{"name":"Wetland Callback Survey Point #10","id":"abqmdnj634ni"},"type":"Feature","geometry":{"type":"Point","coordinates":[-73.1952256697944,41.7137278467552]}},{"properties":{"name":"Wetland Callback Survey Point #11","id":"abqmdniz5ygo"},"type":"Feature","geometry":{"type":"Point","coordinates":[-73.2179163093549,41.7169284570054]}},{"properties":{"name":"Wetland Callback Survey Point #12","id":"abqmdnqkhwbj"},"type":"Feature","geometry":{"type":"Point","coordinates":[-73.2112244175249,41.7164974825683]}},{"properties":{"name":"Wetland Callback Survey Point #13","id":"abqmdnlifmod"},"type":"Feature","geometry":{"type":"Point","coordinates":[-73.2091962619968,41.719081820636]}},{"properties":{"name":"Wetland Callback Survey Point #14","id":"abqmdnbtqrn4"},"type":"Feature","geometry":{"type":"Point","coordinates":[-73.2082978970799,41.7226632598565]}},{"properties":{"name":"Wetland Callback Survey Point #15","id":"abqmdnixwaqc"},"type":"Feature","geometry":{"type":"Point","coordinates":[-73.2088054035798,41.725429352408]}},{"properties":{"name":"Wetland CAllback Survey Point #16","id":"abqmdnfmwjwm"},"type":"Feature","geometry":{"type":"Point","coordinates":[-73.2029432494861,41.7264838083767]}}],"is_temporal":false,"author":{"url":"","metadata":"","contact_name":"James Fischer","contact_address":"The White Memorial Conservation Center, Inc.\r\n80 Whitehall Rd., P.O. Box 368\r\nLitchield, CT 06759\r\n\r\njames@whitememorialcc.org\r\nwww.whitememorialcc.org","source":"","contact_phone":"8605670857"},"source":"","pagination":{"sort":null,"start":0,"total":16,"limit":1000000},"state":"complete","tags":"","published":"2014-08-16T19:43:42-04:00","id":314929}