{"type":"FeatureCollection","data_type":"Dataset","url_type":null,"permissions":[{"permissions":{"download":true,"view":true},"group_id":"everyone"}],"classification":null,"title":"landfill dumpster","count":15,"stream_id":315694,"contributor":{"url":"http://geocommons.com/users/56422","name":"chad.king"},"data_attributes":null,"calculation_params":null,"icon_link":null,"link":"http://geocommons.com/overlays/315694.json","extent":[-104.966,39.6725,-104.961,39.6847],"geometry_types":["point"],"unique_name":null,"name":"landfill dumpster","feature_count":15,"description":"Landfill dumpsters on University of Denver Campus","next_feature":null,"is_raster":false,"short_classification":"Y","stats":{},"features":[{"properties":{"name":"waste connection landfill compactor","id":"abu2vx5isc1c"},"type":"Feature","geometry":{"type":"Point","coordinates":[-104.964943,39.675842]}},{"properties":{"name":"waste connection landfill compactor","id":"abu2vwwtm6xy"},"type":"Feature","geometry":{"type":"Point","coordinates":[-104.964264,39.676876]}},{"properties":{"name":"waste connection landfill compactor","id":"abu2vx20918f"},"type":"Feature","geometry":{"type":"Point","coordinates":[-104.961655,39.679592]}},{"properties":{"name":"waste connection landfill compactor","id":"abu2vxafy7rw"},"type":"Feature","geometry":{"type":"Point","coordinates":[-104.965836,39.684673]}},{"properties":{"name":"waste connection landfill compactor","id":"abu2vx86ybeo"},"type":"Feature","geometry":{"type":"Point","coordinates":[-104.963814,39.680046]}},{"properties":{"name":"waste connection landfill compactor","id":"abu2vwxhmll2"},"type":"Feature","geometry":{"type":"Point","coordinates":[-104.964592,39.675102]}},{"properties":{"name":"waste connection landfill compactor","id":"abu2vwzzen9t"},"type":"Feature","geometry":{"type":"Point","coordinates":[-104.960724,39.682186]}},{"properties":{"name":"waste connection landfill compactor","id":"abu2vx680f7d"},"type":"Feature","geometry":{"type":"Point","coordinates":[-104.963699,39.672482]}},{"properties":{"name":"waste connection landfill dumpster","id":"abu2vwvu8r8g"},"type":"Feature","geometry":{"type":"Point","coordinates":[-104.96357,39.677639]}},{"properties":{"name":"waste connection landfill dumpster","id":"abu2vx9xhazw"},"type":"Feature","geometry":{"type":"Point","coordinates":[-104.963524,39.677738]}},{"properties":{"name":"waste connection landfill dumpster","id":"abu2vwz2husp"},"type":"Feature","geometry":{"type":"Point","coordinates":[-104.961716,39.679718]}},{"properties":{"name":"waste connection landfill dumpster","id":"abu2vx81aipt"},"type":"Feature","geometry":{"type":"Point","coordinates":[-104.962692,39.680645]}},{"properties":{"name":"waste connection landfill dumpster","id":"abu2vx0n7a0x"},"type":"Feature","geometry":{"type":"Point","coordinates":[-104.963966,39.683159]}},{"properties":{"name":"waste connection landfill dumpster","id":"abu2vx1u7wox"},"type":"Feature","geometry":{"type":"Point","coordinates":[-104.965744,39.684746]}},{"properties":{"name":"waste connection landfill dumpster","id":"abu2vx7rhwqs"},"type":"Feature","geometry":{"type":"Point","coordinates":[-104.964722,39.682961]}}],"is_temporal":false,"author":{"url":"","metadata":"","contact_name":"","contact_address":"","source":"Center for Sustainability","contact_phone":""},"source":"","pagination":{"sort":null,"start":0,"total":15,"limit":1000000},"state":"complete","tags":"","published":"2014-08-16T20:47:50-04:00","id":315694}