{"type":"FeatureCollection","data_type":"Dataset","url_type":null,"permissions":[{"permissions":{"download":true,"view":true},"group_id":"everyone"}],"classification":null,"title":"AD Biomethane injection sites","count":2,"stream_id":318015,"contributor":{"url":"http://geocommons.com/users/54257","name":"matthew.dunlevy"},"data_attributes":null,"calculation_params":null,"icon_link":null,"link":"http://geocommons.com/overlays/318015.json","extent":[-2.48295,50.7045,-1.25704,51.6194],"geometry_types":["point"],"unique_name":null,"name":"AD Biomethane injection sites","feature_count":2,"description":"","next_feature":null,"is_raster":false,"short_classification":"Y","stats":{"latitude":{"max":51.61945,"variance":0.41855357607368,"mean":51.1619822,"stdev":0.646957167108982,"min":50.7045144,"median":51.61945},"waste input (t p annum)":{"max":38000,"min":38000,"median":38000},"longitude":{"max":-1.2570374,"variance":0.751434161387045,"mean":-1.86999505,"stdev":0.866853021790341,"min":-2.4829527,"median":-1.2570374},"cost (m)":{"max":2.5,"min":2.5,"median":2.5},"commissioned":{"max":2012,"variance":2.0,"mean":2011.0,"stdev":1.4142135623731,"min":2010,"median":2012}},"features":[{"properties":{"capacity (kwe)":null,"category":"Biomethane Injection","latitude":51.61945,"postcode":"OX11 7HJ","feedstock":"Sewage","waste input (t p annum)":null,"ouput":"Biomethane to grid","company name":"Didcot Sewage Works","longitude":-1.2570374,"id":"ac0qaascw7fg","commissioned":2010,"cost (m)":2.5},"type":"Feature","geometry":{"type":"Point","coordinates":[-1.2570374,51.61945]}},{"properties":{"capacity (kwe)":null,"category":"Biomethane Injection","latitude":50.7045144,"postcode":"DT2 9JF","feedstock":"Maize, grass, slurry, manure and other farm waste","waste input (t p annum)":38000,"ouput":null,"company name":"Rainbarrow Farm (JV Energen)","longitude":-2.4829527,"id":"ac0qaaqaahfo","commissioned":2012,"cost (m)":null},"type":"Feature","geometry":{"type":"Point","coordinates":[-2.4829527,50.7045144]}}],"is_temporal":false,"author":{"url":"","metadata":"","contact_name":"","contact_address":"","source":"","contact_phone":""},"source":"","pagination":{"sort":null,"start":0,"total":2,"limit":1000000},"state":"complete","tags":"","published":"2014-08-16T23:57:07-04:00","id":318015}