{"type":"FeatureCollection","data_type":"Dataset","url_type":null,"permissions":[{"permissions":{"download":true,"view":true},"group_id":"everyone"}],"classification":null,"title":"Current_Canada_Accounts_1","count":10,"stream_id":318175,"contributor":{"url":"http://geocommons.com/users/56257","name":"aesop"},"data_attributes":null,"calculation_params":null,"icon_link":null,"link":"http://geocommons.com/overlays/318175.json","extent":[-119.871,33.6699,-117.788,36.262],"geometry_types":["point"],"unique_name":null,"name":"Current_Canada_Accounts_1","feature_count":10,"description":"","next_feature":null,"is_raster":false,"short_classification":"Y","stats":{},"features":[{"properties":{"city":"Edmonton","store name":"29 Armstrong","zipcode":"T5J 3S4","territory":"Alberta","country":"Canada","geo_score":0.356,"account status":"Current Account","telephone":"780-758-4940","id":"ac17jvoy9do6","address":"105, 10180 101 Street","geo_precision":"street"},"type":"Feature","geometry":{"type":"Point","coordinates":[-118.828738,35.211372]}},{"properties":{"city":"Toronto","store name":"Billy Bishop","zipcode":null,"territory":"Ontario","country":"Canada","geo_score":0.0,"account status":"Current Account","telephone":null,"id":"ac17jvvbi9cj","address":"Porter Lounge, Toronto City Airport","geo_precision":"unmatched"},"type":"Feature","geometry":null},{"properties":{"city":"Vancouver","store name":"Gravitypope","zipcode":"V6K 1N9","territory":"British Columbia","country":"Canada","geo_score":0.0,"account status":"Current Account","telephone":"604-731-6647","id":"ac17jvyoln5b","address":"2203 West 4th Avenue","geo_precision":"unmatched"},"type":"Feature","geometry":null},{"properties":{"city":"Edmonton","store name":"Gravitypope","zipcode":"V7Y 1E4","territory":"Alberta","country":"Canada","geo_score":0.39,"account status":"Current Account","telephone":"780-988-1637","id":"ac17jvmzsr1p","address":"8222 Gateway Boulevard","geo_precision":"street"},"type":"Feature","geometry":{"type":"Point","coordinates":[-119.871331,36.261996]}},{"properties":{"city":"Vancouver","store name":"Holt Renfrew","zipcode":null,"territory":"British Columbia","country":"Canada","geo_score":0.0,"account status":"Current Account","telephone":null,"id":"ac17jvrtcydu","address":"737 Dunsmuir Street","geo_precision":"unmatched"},"type":"Feature","geometry":null},{"properties":{"city":"Vancouver","store name":"Roden Gray","zipcode":"V6B 1A4","territory":"British Columbia","country":"Canada","geo_score":0.0,"account status":"Current Account","telephone":"(604) 689-7302","id":"ac17jvkyb4fu","address":"8 Water Street","geo_precision":"unmatched"},"type":"Feature","geometry":null},{"properties":{"city":"Toronto","store name":"Standard Apparel","zipcode":"M6B1P8","territory":"Ontario","country":"Canada","geo_score":0.0,"account status":"Current Account","telephone":null,"id":"ac17jvy6360q","address":"87 Wingold Avenue","geo_precision":"unmatched"},"type":"Feature","geometry":null},{"properties":{"city":"Westmount","store name":"Want Apothecary","zipcode":"H3Z 1H3","territory":"Quebec","country":"Canada","geo_score":0.454,"account status":"Current Account","telephone":"514-484-3555","id":"ac17jvjw1fex","address":"4960 Sherbrooke Street West","geo_precision":"street"},"type":"Feature","geometry":{"type":"Point","coordinates":[-117.787731,33.669858]}},{"properties":{"city":"Toronto","store name":"Apotheca","zipcode":"M5P2W3","territory":"Ontario","country":"Canada","geo_score":0.0,"account status":"Current Account","telephone":null,"id":"ac17jvmpnn58","address":"417 Spadina Road","geo_precision":"unmatched"},"type":"Feature","geometry":null},{"properties":{"city":"Toronto","store name":"Jacob &amp; Sebastian","zipcode":"M5A3C4","territory":"Ontario","country":"Canada","geo_score":0.0,"account status":"Current Account","telephone":"514-360-7750","id":"ac17jvwceqwq","address":"27 Tank House Lane","geo_precision":"unmatched"},"type":"Feature","geometry":null}],"is_temporal":false,"author":{"url":"","metadata":"","contact_name":"","contact_address":"","source":"","contact_phone":""},"source":"","pagination":{"sort":null,"start":0,"total":10,"limit":1000000},"state":"complete","tags":"","published":"2014-08-17T00:05:38-04:00","id":318175}