{"type":"FeatureCollection","data_type":"Dataset","url_type":null,"permissions":[{"permissions":{"download":true,"view":true},"group_id":"everyone"}],"classification":null,"title":"Location","count":1,"stream_id":321565,"contributor":{"url":"http://geocommons.com/users/33062","name":"ststoshi"},"data_attributes":null,"calculation_params":null,"icon_link":null,"link":"http://geocommons.com/overlays/321565.json","extent":[-123.143,49.2696,-123.143,49.2696],"geometry_types":["point"],"unique_name":null,"name":"Location","feature_count":1,"description":"","next_feature":null,"is_raster":false,"short_classification":"Y","stats":{"latitude":{"max":49.269568,"min":49.269568,"median":49.269568},"longitude":{"max":-123.142738,"min":-123.142738,"median":-123.142738}},"features":[{"properties":{"latitude":49.269568,"loca":"CGA office","longitude":-123.142738,"id":"ac7uojcderpu"},"type":"Feature","geometry":{"type":"Point","coordinates":[-123.142738,49.269568]}}],"is_temporal":false,"author":{"url":"","metadata":"","contact_name":"","contact_address":"","source":"","contact_phone":""},"source":"","pagination":{"sort":null,"start":0,"total":1,"limit":1000000},"state":"complete","tags":"","published":"2014-08-16T15:04:40-04:00","id":321565}