{"type":"FeatureCollection","data_type":"Dataset","url_type":null,"permissions":[{"permissions":{"download":true,"view":true},"group_id":"everyone"}],"classification":null,"title":"Jacmel River Coordinates","count":11,"stream_id":321576,"contributor":{"url":"http://geocommons.com/users/61791","name":"cribbenc"},"data_attributes":null,"calculation_params":null,"icon_link":null,"link":"http://geocommons.com/overlays/321576.json","extent":[-72.5547,18.2321,-72.5417,18.2575],"geometry_types":["point"],"unique_name":null,"name":"Jacmel River Coordinates","feature_count":11,"description":"","next_feature":null,"is_raster":false,"short_classification":"Y","stats":{"latitude":{"max":18.2575,"variance":7.9239999999999e-05,"mean":18.2467,"stdev":0.0089016852337071,"min":18.2321,"median":18.2477},"longitude":{"max":-72.5417,"variance":2.00301818181632e-05,"mean":-72.5477272727273,"stdev":0.00447550911273379,"min":-72.5547,"median":-72.5472}},"features":[{"properties":{"name":"Jacmel River Point 1","latitude":18.2575,"longitude":-72.5503,"id":"ac7vxfj7ldaf"},"type":"Feature","geometry":{"type":"Point","coordinates":[-72.5503,18.2575]}},{"properties":{"name":"Jacmel River Point 2","latitude":18.2564,"longitude":-72.5547,"id":"ac7vxfim6n1r"},"type":"Feature","geometry":{"type":"Point","coordinates":[-72.5547,18.2564]}},{"properties":{"name":"Jacmel River Point 3","latitude":18.2544,"longitude":-72.5542,"id":"ac7vxfdyozp6"},"type":"Feature","geometry":{"type":"Point","coordinates":[-72.5542,18.2544]}},{"properties":{"name":"Jacmel River Point 4","latitude":18.2536,"longitude":-72.5472,"id":"ac7vxfa08wyc"},"type":"Feature","geometry":{"type":"Point","coordinates":[-72.5472,18.2536]}},{"properties":{"name":"Jacmel River Point 5","latitude":18.2498,"longitude":-72.5507,"id":"ac7vxfezglgw"},"type":"Feature","geometry":{"type":"Point","coordinates":[-72.5507,18.2498]}},{"properties":{"name":"Jacmel River Point 6","latitude":18.2477,"longitude":-72.5455,"id":"ac7vxfaqa11z"},"type":"Feature","geometry":{"type":"Point","coordinates":[-72.5455,18.2477]}},{"properties":{"name":"Jacmel River Point 7","latitude":18.245,"longitude":-72.5489,"id":"ac7vxffv7czl"},"type":"Feature","geometry":{"type":"Point","coordinates":[-72.5489,18.245]}},{"properties":{"name":"Jacmel River Point 8","latitude":18.2446,"longitude":-72.5433,"id":"ac7vxfi82ysa"},"type":"Feature","geometry":{"type":"Point","coordinates":[-72.5433,18.2446]}},{"properties":{"name":"Jacmel River Point 9","latitude":18.24,"longitude":-72.5423,"id":"ac7vxf9luira"},"type":"Feature","geometry":{"type":"Point","coordinates":[-72.5423,18.24]}},{"properties":{"name":"Jacmel River Point 10","latitude":18.2326,"longitude":-72.5417,"id":"ac7vxfnsl19e"},"type":"Feature","geometry":{"type":"Point","coordinates":[-72.5417,18.2326]}},{"properties":{"name":"Jacmel River Point 11","latitude":18.2321,"longitude":-72.5462,"id":"ac7vxfhzz7hb"},"type":"Feature","geometry":{"type":"Point","coordinates":[-72.5462,18.2321]}}],"is_temporal":false,"author":{"url":"","metadata":"","contact_name":"","contact_address":"","source":"","contact_phone":""},"source":"","pagination":{"sort":null,"start":0,"total":11,"limit":1000000},"state":"complete","tags":"","published":"2014-08-16T15:05:02-04:00","id":321576}