{"type":"FeatureCollection","data_type":"Dataset","url_type":null,"permissions":[{"permissions":{"download":true,"view":true},"group_id":"everyone"}],"classification":null,"title":"Weds March 13 - Meeting wHigh School Students.kmz","count":1,"stream_id":321731,"contributor":{"url":"http://geocommons.com/users/61279","name":"dkertesz"},"data_attributes":null,"calculation_params":null,"icon_link":null,"link":"http://geocommons.com/overlays/321731.json","extent":[35.6023,32.9747,35.6023,32.9747],"geometry_types":["point"],"unique_name":null,"name":"Weds March 13 - Meeting wHigh School Students.kmz","feature_count":1,"description":"","next_feature":null,"is_raster":false,"short_classification":"Y","stats":{},"features":[{"properties":{"name":"Weds March 13 - Meeting w/High School Students","id":"ac8hmsyhvs5e"},"type":"Feature","geometry":{"type":"Point","coordinates":[35.602308000066,32.9746600001931]}}],"is_temporal":false,"author":{"url":"","metadata":"","contact_name":"","contact_address":"","source":"","contact_phone":""},"source":"","pagination":{"sort":null,"start":0,"total":1,"limit":1000000},"state":"complete","tags":"","published":"2014-08-16T15:11:06-04:00","id":321731}