{"type":"FeatureCollection","data_type":"Dataset","url_type":null,"permissions":[{"permissions":{"download":true,"view":true},"group_id":"everyone"}],"classification":null,"title":"Weds March 13 - Tour Safed.kmz","count":1,"stream_id":321732,"contributor":{"url":"http://geocommons.com/users/61279","name":"dkertesz"},"data_attributes":null,"calculation_params":null,"icon_link":null,"link":"http://geocommons.com/overlays/321732.json","extent":[35.496,32.9646,35.496,32.9646],"geometry_types":["point"],"unique_name":null,"name":"Weds March 13 - Tour Safed.kmz","feature_count":1,"description":"","next_feature":null,"is_raster":false,"short_classification":"Y","stats":{},"features":[{"properties":{"name":"Weds March 13 - Tour Safed","id":"ac8hmy7sq2nu"},"type":"Feature","geometry":{"type":"Point","coordinates":[35.495997000376,32.964648002071]}}],"is_temporal":false,"author":{"url":"","metadata":"","contact_name":"","contact_address":"","source":"","contact_phone":""},"source":"","pagination":{"sort":null,"start":0,"total":1,"limit":1000000},"state":"complete","tags":"","published":"2014-08-16T15:11:06-04:00","id":321732}