{"type":"FeatureCollection","data_type":"Dataset","url_type":null,"permissions":[{"permissions":{"download":true,"view":true},"group_id":"everyone"}],"classification":null,"title":"Metrotown Station.kml","count":1,"stream_id":321762,"contributor":{"url":"http://geocommons.com/users/33062","name":"ststoshi"},"data_attributes":null,"calculation_params":null,"icon_link":null,"link":"http://geocommons.com/overlays/321762.json","extent":[-123.004,49.2258,-123.004,49.2258],"geometry_types":["point"],"unique_name":null,"name":"Metrotown Station.kml","feature_count":1,"description":"","next_feature":null,"is_raster":false,"short_classification":"Y","stats":{},"features":[{"properties":{"name":"Metrotown Station","id":"ac8k7nppheda"},"type":"Feature","geometry":{"type":"Point","coordinates":[-123.003781506416,49.2258024504141]}}],"is_temporal":false,"author":{"url":"","metadata":"","contact_name":"","contact_address":"","source":"","contact_phone":""},"source":"","pagination":{"sort":null,"start":0,"total":1,"limit":1000000},"state":"complete","tags":"","published":"2014-08-16T15:12:34-04:00","id":321762}