{"type":"FeatureCollection","data_type":"Dataset","url_type":null,"permissions":[{"permissions":{"download":true,"view":true},"group_id":"everyone"}],"classification":null,"title":"plant_SSI","count":1,"stream_id":322115,"contributor":{"url":"http://geocommons.com/users/58913","name":"xfeng33"},"data_attributes":null,"calculation_params":null,"icon_link":null,"link":"http://geocommons.com/overlays/322115.json","extent":[-120.844,37.5402,-120.844,37.5402],"geometry_types":["point"],"unique_name":null,"name":"plant_SSI","feature_count":1,"description":"","next_feature":null,"is_raster":false,"short_classification":"Y","stats":{},"features":[{"properties":{"city":"turlock","warehouse":"SSI","geo_score":0.857,"zip code":"95380","id":"acafqddhq8ho","geo_precision":"zip","state":"ca"},"type":"Feature","geometry":{"type":"Point","coordinates":[-120.844063,37.540206]}}],"is_temporal":false,"author":{"url":"","metadata":null,"contact_name":null,"contact_address":null,"source":null,"contact_phone":null},"source":"","pagination":{"sort":null,"start":0,"total":1,"limit":1000000},"state":"complete","tags":"","published":"2014-08-16T15:40:06-04:00","id":322115}