{"type":"FeatureCollection","data_type":"Dataset","url_type":null,"permissions":[{"permissions":{"download":true,"view":true},"group_id":"everyone"}],"classification":null,"title":"Conference","count":4,"stream_id":323330,"contributor":{"url":"http://geocommons.com/users/38325","name":"ryancooper729"},"data_attributes":null,"calculation_params":null,"icon_link":null,"link":"http://geocommons.com/overlays/323330.json","extent":[-84.5036,38.0391,-84.4984,38.0408],"geometry_types":["point"],"unique_name":null,"name":"Conference","feature_count":4,"description":"","next_feature":null,"is_raster":false,"short_classification":"Y","stats":{"latitude":{"max":38.04082056,"variance":5.25348155066137e-07,"mean":38.04009739,"stdev":0.000724809047312557,"min":38.039113,"median":38.040386},"longitude":{"max":-84.49836847,"variance":6.25150380519855e-06,"mean":-84.5008806175,"stdev":0.00250030074295045,"min":-84.503633,"median":-84.499205}},"features":[{"properties":{"name":"Student Center","city":"Lexington","add":"404 Administrative Dr","zip":"40506","latitude":38.040386,"type":"Conference Location","longitude":-84.503633,"id":"accprf5s55uf","state":"KY"},"type":"Feature","geometry":{"type":"Point","coordinates":[-84.503633,38.040386]}},{"properties":{"name":"Gaines Center","city":"Lexington","add":"226 E Maxwell St","zip":"40506","latitude":38.04082056,"type":"Conference Location","longitude":-84.49836847,"id":"accprf5giltj","state":"KY"},"type":"Feature","geometry":{"type":"Point","coordinates":[-84.49836847,38.04082056]}},{"properties":{"name":"Conference Parking-Memorial","city":null,"add":null,"zip":null,"latitude":38.04007,"type":"Conference Location","longitude":-84.499205,"id":"accprf1hvzn9","state":null},"type":"Feature","geometry":{"type":"Point","coordinates":[-84.499205,38.04007]}},{"properties":{"name":"Conference Parking-Student Center","city":null,"add":null,"zip":null,"latitude":38.039113,"type":"Conference Location","longitude":-84.502316,"id":"accprf9lu9c0","state":null},"type":"Feature","geometry":{"type":"Point","coordinates":[-84.502316,38.039113]}}],"is_temporal":false,"author":{"url":"","metadata":"","contact_name":"","contact_address":"","source":"","contact_phone":""},"source":"","pagination":{"sort":null,"start":0,"total":4,"limit":1000000},"state":"complete","tags":"dope2013","published":"2014-08-16T16:56:49-04:00","id":323330}