{"type":"FeatureCollection","data_type":"Dataset","url_type":null,"permissions":[{"permissions":{"download":true,"view":true},"group_id":"everyone"}],"classification":null,"title":"PS_section_1","count":11,"stream_id":324037,"contributor":{"url":"http://geocommons.com/users/38169","name":"blewislao"},"data_attributes":null,"calculation_params":null,"icon_link":null,"link":"http://geocommons.com/overlays/324037.json","extent":[103.435,19.5939,103.436,19.5952],"geometry_types":["point"],"unique_name":null,"name":"PS_section_1","feature_count":11,"description":"","next_feature":null,"is_raster":false,"short_classification":"Y","stats":{"n":{"max":11,"variance":6.69090909090909,"mean":6.90909090909091,"stdev":2.58667916273145,"min":4,"median":6},"t":{"max":1,"variance":0.0,"mean":1.0,"stdev":0.0,"min":1,"median":1},"lat":{"max":19.59516998,"variance":1.63845419396452e-07,"mean":19.5947529081818,"stdev":0.000404778234835388,"min":19.59388596,"median":19.59494099},"long":{"max":103.436352,"variance":4.2842067272914e-07,"mean":103.435485545455,"stdev":0.000654538518904075,"min":103.434697,"median":103.435473}},"features":[{"properties":{"name":"PS015","tt":"OPF","b":"House","n":11,"d":null,"f":"Neng Yeir vang","id":"acdz46eovhqc","lat":19.59496496,"t":1,"long":103.436291},"type":"Feature","geometry":{"type":"Point","coordinates":[103.436291,19.59496496]}},{"properties":{"name":"PS016","tt":"OPF","b":"House","n":11,"d":null,"f":"Yong Por Vang","id":"acdz46kta2ie","lat":19.59516998,"t":1,"long":103.436108},"type":"Feature","geometry":{"type":"Point","coordinates":[103.436108,19.59516998]}},{"properties":{"name":"PS017","tt":"OPF","b":"House","n":9,"d":null,"f":"Xong Yer Vang","id":"acdz46kuzkcu","lat":19.59494099,"t":1,"long":103.435053},"type":"Feature","geometry":{"type":"Point","coordinates":[103.435053,19.59494099]}},{"properties":{"name":"PS018","tt":"OPF","b":"House","n":6,"d":null,"f":"Yong Da","id":"acdz46kb7h2s","lat":19.59501198,"t":1,"long":103.434921},"type":"Feature","geometry":{"type":"Point","coordinates":[103.434921,19.59501198]}},{"properties":{"name":"PS019","tt":null,"b":"House","n":4,"d":null,"f":"Brier Wang","id":"acdz46n6fxiz","lat":19.59483102,"t":null,"long":103.434697},"type":"Feature","geometry":{"type":"Point","coordinates":[103.434697,19.59483102]}},{"properties":{"name":"PS020","tt":null,"b":"House","n":9,"d":null,"f":"Wa Neng Va","id":"acdz46kqzcry","lat":19.59504602,"t":null,"long":103.434817},"type":"Feature","geometry":{"type":"Point","coordinates":[103.434817,19.59504602]}},{"properties":{"name":"PS021","tt":null,"b":"House","n":5,"d":null,"f":"Xay Por yang","id":"acdz46my9jzj","lat":19.59504602,"t":null,"long":103.434817},"type":"Feature","geometry":{"type":"Point","coordinates":[103.434817,19.59504602]}},{"properties":{"name":"PS022","tt":null,"b":"House","n":6,"d":null,"f":"Xier Tou Yang","id":"acdz469uu6es","lat":19.59465601,"t":null,"long":103.435473},"type":"Feature","geometry":{"type":"Point","coordinates":[103.435473,19.59465601]}},{"properties":{"name":"PS023","tt":"OPF","b":"House","n":5,"d":null,"f":"Chong Mour vue","id":"acdz46e96chh","lat":19.59456003,"t":1,"long":103.435659},"type":"Feature","geometry":{"type":"Point","coordinates":[103.435659,19.59456003]}},{"properties":{"name":"PS024","tt":null,"b":"House","n":5,"d":null,"f":"Wa Wue","id":"acdz468fuqa9","lat":19.59416902,"t":null,"long":103.436153},"type":"Feature","geometry":{"type":"Point","coordinates":[103.436153,19.59416902]}},{"properties":{"name":"PS025","tt":"OPF","b":"House","n":5,"d":null,"f":"Fa Bier Vue","id":"acdz46iq1b4c","lat":19.59388596,"t":1,"long":103.436352},"type":"Feature","geometry":{"type":"Point","coordinates":[103.436352,19.59388596]}}],"is_temporal":false,"author":{"url":"","metadata":null,"contact_name":null,"contact_address":null,"source":null,"contact_phone":null},"source":"","pagination":{"sort":null,"start":0,"total":11,"limit":1000000},"state":"complete","tags":"","published":"2014-08-16T17:53:32-04:00","id":324037}