{"type":"FeatureCollection","data_type":"Dataset","url_type":null,"permissions":[{"permissions":{"download":true,"view":true},"group_id":"everyone"}],"classification":null,"title":"Browne Airport","count":1,"stream_id":331489,"contributor":{"url":"http://geocommons.com/users/4919","name":"spicer_planners"},"data_attributes":null,"calculation_params":null,"icon_link":null,"link":"http://geocommons.com/overlays/331489.json","extent":[-83.8609,43.4291,-83.8609,43.4291],"geometry_types":["point"],"unique_name":null,"name":"Browne Airport","feature_count":1,"description":"blumfield","next_feature":null,"is_raster":false,"short_classification":"Y","stats":{},"features":[{"properties":{"name":"H. W. Browne Airport","id":"acsszyfu4806"},"type":"Feature","geometry":{"type":"Point","coordinates":[-83.8609309940405,43.4291392905849]}}],"is_temporal":false,"author":{"url":"","metadata":"","contact_name":"","contact_address":"","source":"","contact_phone":""},"source":"","pagination":{"sort":null,"start":0,"total":1,"limit":1000000},"state":"complete","tags":"blumfield","published":"2014-08-16T14:56:35-04:00","id":331489}