{"type":"FeatureCollection","data_type":"Dataset","url_type":null,"permissions":[{"permissions":{"download":true,"view":true},"group_id":"everyone"}],"classification":null,"title":"test","count":3,"stream_id":3333,"contributor":{"url":"http://geocommons.com/users/708","name":"monkeyhelper"},"data_attributes":null,"calculation_params":null,"icon_link":null,"link":"http://geocommons.com/overlays/3333.json","extent":[-4.24,53.95,-1.69,55.85],"geometry_types":["point"],"unique_name":null,"name":"test","feature_count":3,"description":"","next_feature":null,"is_raster":false,"short_classification":"Y","stats":{"latitude":{"max":55.85,"mean":54.5833333333333,"variance":1.20333333333333,"stdev":1.09696551146029,"min":53.95,"median":53.95},"longitude":{"max":-1.69,"mean":-2.54,"variance":2.1675,"stdev":1.47224318643355,"min":-4.24,"median":-1.69}},"features":[{"properties":{"latitude":55.85,"longitude":-4.24,"id":"a64f85yjiitw"},"type":"Feature","geometry":{"type":"Point","coordinates":[-4.24,55.85]}},{"properties":{"latitude":53.95,"longitude":-1.69,"id":"a64f864cnk23"},"type":"Feature","geometry":{"type":"Point","coordinates":[-1.69,53.95]}},{"properties":{"latitude":53.95,"longitude":-1.69,"id":"a64f85vbsml9"},"type":"Feature","geometry":{"type":"Point","coordinates":[-1.69,53.95]}}],"is_temporal":false,"author":{"url":"","metadata":"","contact_name":"","contact_address":"","source":"","contact_phone":""},"source":"","pagination":{"sort":null,"start":0,"total":3,"limit":1000000},"state":"complete","tags":"","published":"2014-08-11T00:50:23-04:00","id":3333}