{"type":"FeatureCollection","data_type":"Dataset","url_type":null,"permissions":[{"permissions":{"download":true,"view":true},"group_id":"everyone"}],"classification":null,"title":"Workbook1","count":1,"stream_id":334850,"contributor":{"url":"http://geocommons.com/users/66435","name":"boyless123"},"data_attributes":null,"calculation_params":null,"icon_link":null,"link":"http://geocommons.com/overlays/334850.json","extent":[119.925,-2.88194,119.925,-2.88194],"geometry_types":["point"],"unique_name":null,"name":"Workbook1","feature_count":1,"description":"","next_feature":null,"is_raster":false,"short_classification":"Y","stats":{},"features":[{"properties":{"city":"toronto","last name":"sundin","country":"ontario","geo_score":0.714,"id":"ad0gzu3wgxm8","first name":"mats","geo_precision":"zip"},"type":"Feature","geometry":{"type":"Point","coordinates":[119.9252778,-2.8819444]}}],"is_temporal":false,"author":{"url":"","metadata":null,"contact_name":null,"contact_address":null,"source":null,"contact_phone":null},"source":"","pagination":{"sort":null,"start":0,"total":1,"limit":1000000},"state":"complete","tags":"","published":"2014-08-16T19:04:04-04:00","id":334850}