{"type":"FeatureCollection","data_type":"Dataset Analysis","url_type":null,"permissions":[{"permissions":{"download":true,"view":true},"group_id":"everyone"}],"classification":null,"title":"Filtered Features of 'Westchester County Pedestrian Fatalities, 2009-2011 - latitude and longitude given' based on 'Westchester County Senior Centers'","count":2,"stream_id":335521,"contributor":{"url":"http://geocommons.com/users/34264","name":"RenataPS"},"data_attributes":null,"calculation_params":{"input":{"min_distance":"0","unit":"miles","near_id":"334114","distance":".25","include_distance":true,"id":"334139"},"calculation":"buffer_intersect"},"icon_link":null,"link":"http://geocommons.com/overlays/335521.json","extent":[-73.8673,40.9245,-73.7955,40.9462],"geometry_types":["point"],"unique_name":null,"name":"Filtered Features of 'Westchester County Pedestrian Fatalities, 2009-2011 - latitude and longitude given' based on 'Westchester County Senior Centers'","feature_count":2,"description":"Dataset created by filtering features of 'Westchester County Pedestrian Fatalities, 2009-2011 - latitude and longitude given' that are within a buffer of 0 to .25 miles around the features in 'Westchester County Senior Centers'","next_feature":null,"is_raster":false,"short_classification":"Y","stats":{"distance":{"max":0.200958678411035,"variance":0.0154900360909104,"mean":0.112952894251951,"stdev":0.124458973525055,"min":0.0249471100928678,"median":0.200958678411035}},"features":[{"properties":{"name":"YONKERS AVE","description":" xmlns:fo=\"http://www.w3.org/1999/XSL/Format\" xmlns:msxsl=\"urn:schemas-microsoft-com:xslt\"&gt;\r\r\n\r\r\nYONKERS AVE\r\r\n\r\r\nName\r\r\nYONKERS AVE\r\r\nLat\r\r\n40.924497\r\r\nLong\r\r\n-73.867264\r\r\nDesc\r\r\n58 year old male killed on 10/20/2010\r\r\n\r\r\n","id":"aczo42csam5k","distance":0.200958678411035},"type":"Feature","geometry":{"type":"Point","coordinates":[-73.867264,40.924497]}},{"properties":{"name":"NORTH AVE","description":" xmlns:fo=\"http://www.w3.org/1999/XSL/Format\" xmlns:msxsl=\"urn:schemas-microsoft-com:xslt\"&gt;\r\r\n\r\r\nNORTH AVE\r\r\n\r\r\nName\r\r\nNORTH AVE\r\r\nLat\r\r\n40.9462\r\r\nLong\r\r\n-73.7955\r\r\nDesc\r\r\n91 year old male killed on 5/18/2009\r\r\n\r\r\n","id":"aczo42f2yy3g","distance":0.0249471100928678},"type":"Feature","geometry":{"type":"Point","coordinates":[-73.7955,40.9462]}}],"is_temporal":false,"author":{"url":"","metadata":"","contact_name":"","contact_address":"","source":"","contact_phone":""},"source":"","pagination":{"sort":null,"start":0,"total":2,"limit":1000000},"state":"complete","tags":"","published":"2014-08-16T19:55:40-04:00","id":335521}