{"type":"FeatureCollection","data_type":"Dataset","url_type":null,"permissions":[{"permissions":{"download":true,"view":true},"group_id":"everyone"}],"classification":null,"title":"Dickin_Around","count":4,"stream_id":335930,"contributor":{"url":"http://geocommons.com/users/66435","name":"boyless123"},"data_attributes":null,"calculation_params":null,"icon_link":null,"link":"http://geocommons.com/overlays/335930.json","extent":[-117.877,33.7572,-79.4167,43.6667],"geometry_types":["point"],"unique_name":null,"name":"Dickin_Around","feature_count":4,"description":"","next_feature":null,"is_raster":false,"short_classification":"Y","stats":{"latitude":{"max":43.6666667,"variance":26.6562143556962,"mean":38.189190925,"stdev":5.16296565509555,"min":33.7572,"median":41.525},"player number":{"max":13,"variance":0.0,"mean":13.0,"stdev":0.0,"min":13,"median":13},"points scored in 2003-2004 nhl season":{"max":75,"variance":462.25,"mean":42.75,"stdev":21.5,"min":32,"median":32},"date":{"max":"1990/11/14 00:00:00 -0500","variance":102426824160000.0,"mean":"1990/07/22 18:30:00 -0400","stdev":10120613.8232817,"min":"1990/02/14 00:00:00 -0500","median":"1990/09/14 00:00:00 -0400"},"age at end of 2003-2004 season":{"max":35,"variance":1.66666666666667,"mean":33.5,"stdev":1.29099444873581,"min":32,"median":34},"longitude":{"max":-79.4166667,"variance":302.196212600228,"mean":-92.273050925,"stdev":17.3837916635074,"min":-117.876537,"median":-84.3963},"games played in 2003-2004 nhl season":{"max":81,"variance":196.0,"mean":74.0,"stdev":14.0,"min":53,"median":81}},"features":[{"properties":{"player number":13,"salary during 2003-2004 nhl season":"$9 M","latitude":43.6666667,"points scored in 2003-2004 nhl season":75,"last name":"Sundin","team at conclusion of 2003-2004 nhl season":"Toronto Maple Leafs","date":{"end_time":"1990/07/15 00:00:00 -0400","original":"07/14/90","granularity":"day","time":"1990/07/14 00:00:00 -0400"},"country":"Canada","province/ state":"ONT","age at end of 2003-2004 season":32,"longitude":-79.4166667,"id":"ad28mitmrg64","first name":"Mats","position":"C","games played in 2003-2004 nhl season":81},"type":"Feature","geometry":{"type":"Point","coordinates":[-79.4166667,43.6666667]}},{"properties":{"player number":13,"salary during 2003-2004 nhl season":"$9","latitude":33.807897,"points scored in 2003-2004 nhl season":32,"last name":"Sundin","team at conclusion of 2003-2004 nhl season":"Modo","date":{"end_time":"1990/09/15 00:00:00 -0400","original":"09/14/90","granularity":"day","time":"1990/09/14 00:00:00 -0400"},"country":"Sweden","province/ state":"Lanbresque","age at end of 2003-2004 season":33,"longitude":-117.876537,"id":"ad28mikpc0mp","first name":"Mats","position":"C","games played in 2003-2004 nhl season":53},"type":"Feature","geometry":{"type":"Point","coordinates":[-117.876537,33.807897]}},{"properties":{"player number":13,"salary during 2003-2004 nhl season":"$2","latitude":41.525,"points scored in 2003-2004 nhl season":32,"last name":"Sundin","team at conclusion of 2003-2004 nhl season":"Toronto Mapleleafs","date":{"end_time":"1990/11/15 00:00:00 -0500","original":"11/14/90","granularity":"day","time":"1990/11/14 00:00:00 -0500"},"country":"trete","province/ state":"erwer","age at end of 2003-2004 season":34,"longitude":-87.4027,"id":"ad28mimhv339","first name":"Mats","position":"C","games played in 2003-2004 nhl season":81},"type":"Feature","geometry":{"type":"Point","coordinates":[-87.4027,41.525]}},{"properties":{"player number":13,"salary during 2003-2004 nhl season":"$6","latitude":33.7572,"points scored in 2003-2004 nhl season":32,"last name":"Sundin","team at conclusion of 2003-2004 nhl season":"fkneflkern","date":{"end_time":"1990/02/15 00:00:00 -0500","original":"02/14/90","granularity":"day","time":"1990/02/14 00:00:00 -0500"},"country":"etert","province/ state":"ewrwer","age at end of 2003-2004 season":35,"longitude":-84.3963,"id":"ad28mii2ss3z","first name":"Mats","position":"C","games played in 2003-2004 nhl season":81},"type":"Feature","geometry":{"type":"Point","coordinates":[-84.3963,33.7572]}}],"is_temporal":true,"author":{"url":"","metadata":null,"contact_name":null,"contact_address":null,"source":null,"contact_phone":null},"source":"","pagination":{"sort":null,"start":0,"total":4,"limit":1000000},"state":"complete","tags":"","published":"2014-08-16T20:24:11-04:00","id":335930}