{"type":"FeatureCollection","data_type":"Dataset","url_type":null,"permissions":[{"permissions":{"download":true,"view":true},"group_id":"everyone"}],"classification":null,"title":"0900","count":1,"stream_id":337402,"contributor":{"url":"http://geocommons.com/users/67200","name":"hminandar"},"data_attributes":null,"calculation_params":null,"icon_link":null,"link":"http://geocommons.com/overlays/337402.json","extent":[116.251,-8.75739,116.251,-8.75739],"geometry_types":["point"],"unique_name":null,"name":"0900","feature_count":1,"description":"","next_feature":null,"is_raster":false,"short_classification":"Y","stats":{"name":{"max":90,"min":90,"median":90}},"features":[{"properties":{"name":90,"id":"ad67wmrvkppu"},"type":"Feature","geometry":{"type":"Point","coordinates":[116.251155348249,-8.75738966804186]}}],"is_temporal":false,"author":{"url":"","metadata":null,"contact_name":null,"contact_address":null,"source":null,"contact_phone":null},"source":"","pagination":{"sort":null,"start":0,"total":1,"limit":1000000},"state":"complete","tags":"","published":"2014-08-16T22:15:27-04:00","id":337402}