{"type":"FeatureCollection","data_type":"Dataset","url_type":null,"permissions":[{"permissions":{"download":true,"view":true},"group_id":"everyone"}],"classification":null,"title":"place admin","count":4,"stream_id":33761,"contributor":{"url":"http://geocommons.com/users/11718","name":"porhaaa"},"data_attributes":null,"calculation_params":null,"icon_link":null,"link":"http://geocommons.com/overlays/33761.json","extent":[100.471,6.99172,100.497,7.03252],"geometry_types":["point"],"unique_name":null,"name":"place admin","feature_count":4,"description":"place admin create website","next_feature":null,"is_raster":false,"short_classification":"Y","stats":{"latitude":{"max":7.032516,"mean":7.00676625,"variance":0.000315639186916669,"stdev":0.0177662372751427,"min":6.991722,"median":7.001756},"id":{"max":5210121112,"mean":5210121068.75,"variance":994.25,"stdev":31.5317300508551,"min":5210121040,"median":5210121071},"longitude":{"max":100.496907,"mean":100.48868275,"variance":0.000141543934916603,"stdev":0.0118972238323318,"min":100.471051,"median":100.494352}},"features":[{"properties":{"name":"Mr.Panupong Kongkawongprateep","latitude":6.991722,"id":"a6nd6kljuj9v","longitude":100.471051},"type":"Feature","geometry":{"type":"Point","coordinates":[100.471051,6.991722]}},{"properties":{"name":"Mr.Weerasak Nilchad","latitude":7.001071,"id":"a6nd6ki2gpwz","longitude":100.492421},"type":"Feature","geometry":{"type":"Point","coordinates":[100.492421,7.001071]}},{"properties":{"name":"Mr.eakkawit Jeawkok","latitude":7.001756,"id":"a6nd6kfcqxr6","longitude":100.496907},"type":"Feature","geometry":{"type":"Point","coordinates":[100.496907,7.001756]}},{"properties":{"name":"Mr.Porrawut Keawme","latitude":7.032516,"id":"a6nd6kt56lyf","longitude":100.494352},"type":"Feature","geometry":{"type":"Point","coordinates":[100.494352,7.032516]}}],"is_temporal":false,"author":{"url":"","metadata":"","contact_name":"","contact_address":"","source":"","contact_phone":""},"source":"","pagination":{"sort":null,"start":0,"total":4,"limit":1000000},"state":"complete","tags":"","published":"2014-08-10T14:25:35-04:00","id":33761}