{"type":"FeatureCollection","data_type":"Dataset","url_type":null,"permissions":[{"permissions":{"download":true,"view":true},"group_id":"everyone"}],"classification":null,"title":"Rice Mill 2.kml","count":1,"stream_id":338294,"contributor":{"url":"http://geocommons.com/users/59514","name":"joules"},"data_attributes":null,"calculation_params":null,"icon_link":null,"link":"http://geocommons.com/overlays/338294.json","extent":[124.812,6.50366,124.812,6.50366],"geometry_types":["point"],"unique_name":null,"name":"Rice Mill 2.kml","feature_count":1,"description":"","next_feature":null,"is_raster":false,"short_classification":"Y","stats":{},"features":[{"properties":{"name":"Rice Mill 2","id":"ad7up6csr0f3"},"type":"Feature","geometry":{"type":"Point","coordinates":[124.812315982478,6.5036587132731]}}],"is_temporal":false,"author":{"url":"","metadata":"","contact_name":"","contact_address":"","source":"","contact_phone":""},"source":"","pagination":{"sort":null,"start":0,"total":1,"limit":1000000},"state":"complete","tags":"","published":"2014-08-16T23:14:24-04:00","id":338294}