{"type":"FeatureCollection","data_type":"Dataset","url_type":null,"permissions":[{"permissions":{"download":true,"view":true},"group_id":"everyone"}],"classification":null,"title":"Bloc MPs","count":1,"stream_id":338650,"contributor":{"url":"http://geocommons.com/users/49830","name":"EThompson"},"data_attributes":null,"calculation_params":null,"icon_link":null,"link":"http://geocommons.com/overlays/338650.json","extent":[121.56,25.0911,121.56,25.0911],"geometry_types":["point"],"unique_name":null,"name":"Bloc MPs","feature_count":1,"description":"","next_feature":null,"is_raster":false,"short_classification":"Y","stats":{"accommodation":{"max":1663.31,"min":1663.31,"median":1663.31},"latitude":{"max":25.091075,"min":25.091075,"median":25.091075},"total/trip":{"max":5378.56,"min":5378.56,"median":5378.56},"gifts":{"max":252.54,"min":252.54,"median":252.54},"longitude":{"max":121.559834,"min":121.559834,"median":121.559834},"other":{"max":0.0,"min":0.0,"median":0.0},"transport":{"max":3462.71,"min":3462.71,"median":3462.71}},"features":[{"properties":{"accommodation":1663.31,"purpose":"Parliamentary delegation","latitude":25.091075,"mp":"Fortin, Jean-François","destination":"Taipei, Taiwan","dates":"July 19-26, 2012","total/trip":5378.56,"accompanied by":"N/a","gifts":252.54,"sponsor":"Chinese International Economic Cooperation Association","longitude":121.559834,"id":"ad8emrf9pm67","transport":3462.71,"other":0.0,"party":"Bloc"},"type":"Feature","geometry":{"type":"Point","coordinates":[121.559834,25.091075]}}],"is_temporal":false,"author":{"url":"","metadata":"","contact_name":"","contact_address":"","source":"","contact_phone":""},"source":"","pagination":{"sort":null,"start":0,"total":1,"limit":1000000},"state":"complete","tags":"","published":"2014-08-16T23:31:19-04:00","id":338650}