{"type":"FeatureCollection","data_type":"Dataset","url_type":null,"permissions":[{"permissions":{"download":true,"view":true},"group_id":"everyone"}],"classification":null,"title":"Jelly Belly Tour Locations","count":2,"stream_id":33997,"contributor":{"url":"http://geocommons.com/users/7156","name":"kate"},"data_attributes":null,"calculation_params":null,"icon_link":null,"link":"http://geocommons.com/overlays/33997.json","extent":[-122.034,38.2549,-88.3539,42.896],"geometry_types":["point"],"unique_name":null,"name":"Jelly Belly Tour Locations","feature_count":2,"description":"Jelly Belly Tour Locations","next_feature":null,"is_raster":false,"short_classification":"Y","stats":{},"features":[{"properties":{"factory_name":"California Factory, Fairfield","url":"http://www.jellybelly.com/visit_jelly_belly/california_factory_tours.aspx","id":"a64fyotrwgx3","address":"1 Jelly Belly Ln Fairfield, CA 94533"},"type":"Feature","geometry":{"type":"Point","coordinates":[-122.034191,38.254939]}},{"properties":{"factory_name":"Wisconsin Center, Pleasant Prairie","url":"http://www.jellybelly.com/visit_jelly_belly/wisconsin_factory.aspx","id":"a64fyoemz99a","address":"10100 Jelly Belly Ln Pleasant Prairie, WI 53158"},"type":"Feature","geometry":{"type":"Point","coordinates":[-88.353941,42.896048]}}],"is_temporal":false,"author":{"url":"http://www.jellybelly.com","metadata":"","contact_name":"","contact_address":"","source":"Jelly Belly","contact_phone":""},"source":"http://www.jellybelly.com","pagination":{"sort":null,"start":0,"total":2,"limit":1000000},"state":"complete","tags":"belly,jelly,jellybean","published":"2010-03-16T19:05:36Z","id":33997}