{"type":"FeatureCollection","data_type":"Dataset","url_type":null,"permissions":[{"permissions":{"download":true,"view":true},"group_id":"everyone"}],"classification":null,"title":"limonariaDic","count":5,"stream_id":343864,"contributor":{"url":"http://geocommons.com/users/69481","name":"Lizbeth"},"data_attributes":null,"calculation_params":null,"icon_link":null,"link":"http://geocommons.com/overlays/343864.json","extent":[-96.7784,18.8169,-96.339,19.1955],"geometry_types":["point"],"unique_name":null,"name":"limonariaDic","feature_count":5,"description":"","next_feature":null,"is_raster":false,"short_classification":"Y","stats":{"latitude":{"max":19.19551,"variance":0.0205375116699999,"mean":18.990118,"stdev":0.143309147195843,"min":18.81686,"median":18.97659},"diciembre":{"max":1.0,"variance":0.212,"mean":0.32,"stdev":0.460434577328854,"min":0.0,"median":0.0},"longitude":{"max":-96.33898,"variance":0.04070329267,"mean":-96.597872,"stdev":0.201750570432899,"min":-96.77835,"median":-96.72383}},"features":[{"properties":{"latitude":19.19551,"diciembre":0.0,"longitude":-96.33898,"id":"adir49ngiaol"},"type":"Feature","geometry":{"type":"Point","coordinates":[-96.33898,19.19551]}},{"properties":{"latitude":19.05006,"diciembre":0.0,"longitude":-96.42208,"id":"adir49p3om1i"},"type":"Feature","geometry":{"type":"Point","coordinates":[-96.42208,19.05006]}},{"properties":{"latitude":18.97659,"diciembre":1.0,"longitude":-96.72612,"id":"adir49m1kka4"},"type":"Feature","geometry":{"type":"Point","coordinates":[-96.72612,18.97659]}},{"properties":{"latitude":18.91157,"diciembre":0.0,"longitude":-96.77835,"id":"adir49l7sts4"},"type":"Feature","geometry":{"type":"Point","coordinates":[-96.77835,18.91157]}},{"properties":{"latitude":18.81686,"diciembre":0.6,"longitude":-96.72383,"id":"adir49nb3rcn"},"type":"Feature","geometry":{"type":"Point","coordinates":[-96.72383,18.81686]}}],"is_temporal":false,"author":{"url":"","metadata":null,"contact_name":null,"contact_address":null,"source":null,"contact_phone":null},"source":"","pagination":{"sort":null,"start":0,"total":5,"limit":1000000},"state":"complete","tags":"","published":"2014-08-16T17:36:50-04:00","id":343864}