{"type":"FeatureCollection","data_type":"Dataset","url_type":null,"permissions":[{"permissions":{"download":true,"view":true},"group_id":"everyone"}],"classification":null,"title":"Closed Out","count":6,"stream_id":344119,"contributor":{"url":"http://geocommons.com/users/54132","name":"global_water"},"data_attributes":null,"calculation_params":null,"icon_link":null,"link":"http://geocommons.com/overlays/344119.json","extent":[33.45,-19.1167,39.6806,11.6],"geometry_types":["point"],"unique_name":null,"name":"Closed Out","feature_count":6,"description":"","next_feature":null,"is_raster":false,"short_classification":"Y","stats":{"latitude":{"max":11.6,"variance":103.096875475644,"mean":-3.02619666666667,"stdev":10.1536631555141,"min":-19.116667,"median":-1.775354},"longitude":{"max":39.680552,"variance":6.73235673781626,"mean":35.9937846666667,"stdev":2.59467854228925,"min":33.45,"median":37.383333}},"features":[{"properties":{"latitude":-19.116667,"longitude":33.45,"id":"adjb81srdykf"},"type":"Feature","geometry":{"type":"Point","coordinates":[33.45,-19.116667]}},{"properties":{"latitude":-6.825534,"longitude":37.652893,"id":"adjb81yoacyi"},"type":"Feature","geometry":{"type":"Point","coordinates":[37.652893,-6.825534]}},{"properties":{"latitude":-1.775354,"longitude":34.153195,"id":"adjb81zpbrs4"},"type":"Feature","geometry":{"type":"Point","coordinates":[34.153195,-1.775354]}},{"properties":{"latitude":-4.069795,"longitude":39.680552,"id":"adjb81tug0g4"},"type":"Feature","geometry":{"type":"Point","coordinates":[39.680552,-4.069795]}},{"properties":{"latitude":11.6,"longitude":37.383333,"id":"adjb81ttid5k"},"type":"Feature","geometry":{"type":"Point","coordinates":[37.383333,11.6]}},{"properties":{"latitude":2.03017,"longitude":33.642735,"id":"adjb81q6wega"},"type":"Feature","geometry":{"type":"Point","coordinates":[33.642735,2.03017]}}],"is_temporal":false,"author":{"url":"","metadata":"","contact_name":"","contact_address":"","source":"","contact_phone":""},"source":"","pagination":{"sort":null,"start":0,"total":6,"limit":1000000},"state":"complete","tags":"","published":"2014-08-16T17:51:38-04:00","id":344119}