{"type":"FeatureCollection","data_type":"Dataset","url_type":null,"permissions":[{"permissions":{"download":true,"view":true},"group_id":"everyone"}],"classification":null,"title":"LocationsTest","count":3,"stream_id":344529,"contributor":{"url":"http://geocommons.com/users/69695","name":"austinswitser"},"data_attributes":null,"calculation_params":null,"icon_link":null,"link":"http://geocommons.com/overlays/344529.json","extent":[-1.5,13.2333,17.8556,47.7333],"geometry_types":["point"],"unique_name":null,"name":"LocationsTest","feature_count":3,"description":"","next_feature":null,"is_raster":false,"short_classification":"Y","stats":{},"features":[{"properties":{"city":"Fairfax","country":"USA","geo_score":0.714,"id":"adk2hdi71w07","geo_precision":"zip"},"type":"Feature","geometry":{"type":"Point","coordinates":[17.8555556,45.3816667]}},{"properties":{"city":"Durham","country":"USA","geo_score":0.714,"id":"adk2hdts1h7q","geo_precision":"zip"},"type":"Feature","geometry":{"type":"Point","coordinates":[11.9666667,47.7333333]}},{"properties":{"city":"New York","country":"USA","geo_score":0.714,"id":"adk2hdkkrwgw","geo_precision":"zip"},"type":"Feature","geometry":{"type":"Point","coordinates":[-1.5,13.2333333]}}],"is_temporal":false,"author":{"url":"","metadata":null,"contact_name":null,"contact_address":null,"source":null,"contact_phone":null},"source":"","pagination":{"sort":null,"start":0,"total":3,"limit":1000000},"state":"complete","tags":"","published":"2014-08-16T18:25:54-04:00","id":344529}