{"type":"FeatureCollection","data_type":"Dataset","url_type":null,"permissions":[{"permissions":{"download":true,"view":true},"group_id":"everyone"}],"classification":null,"title":"A la découverte du patrimoine 2013 - jardins","count":4,"stream_id":347000,"contributor":{"url":"http://geocommons.com/users/42827","name":"jflacou"},"data_attributes":null,"calculation_params":null,"icon_link":null,"link":"http://geocommons.com/overlays/347000.json","extent":[1.30388,46.4192,1.937,46.798],"geometry_types":["point"],"unique_name":null,"name":"A la découverte du patrimoine 2013 - jardins","feature_count":4,"description":"","next_feature":null,"is_raster":false,"short_classification":"Y","stats":{},"features":[{"properties":{"name":"Site du Moulin de Seillant","Telephone":"-","id":"adowpznj077g","Infos":"-","GPS":"1.34861 - 46.41916"},"type":"Feature","geometry":{"type":"Point","coordinates":[1.34861,46.41916]}},{"properties":{"name":"Moulin d'Angibault","Telephone":"02 54 31 11 46","id":"adowpzs9t8m6","Infos":"-","GPS":"1.90722 - 46.62472"},"type":"Feature","geometry":{"type":"Point","coordinates":[1.90722,46.62472]}},{"properties":{"name":"Parc des Parelles","Telephone":"02 54 34 17 17","id":"adowpzv9k19x","Infos":"-","GPS":"1.93700 - 46.45931"},"type":"Feature","geometry":{"type":"Point","coordinates":[1.937,46.45931]}},{"properties":{"name":"Base de loisirs de Bellebouche","Telephone":"02 54 38 32 36","id":"adowpzp32c0j","Infos":"-","GPS":"1.30388 - 46.79805"},"type":"Feature","geometry":{"type":"Point","coordinates":[1.30388,46.79805]}}],"is_temporal":false,"author":{"url":"","metadata":"","contact_name":"","contact_address":"","source":"","contact_phone":""},"source":"","pagination":{"sort":null,"start":0,"total":4,"limit":1000000},"state":"complete","tags":"","published":"2014-08-16T21:22:01-04:00","id":347000}