{"type":"FeatureCollection","data_type":"Dataset","url_type":null,"permissions":[{"permissions":{"download":true,"view":true},"group_id":"everyone"}],"classification":null,"title":"Workbook6","count":1,"stream_id":350911,"contributor":{"url":"http://geocommons.com/users/54644","name":"watson"},"data_attributes":null,"calculation_params":null,"icon_link":null,"link":"http://geocommons.com/overlays/350911.json","extent":[-84.5035,38.0398,-84.5035,38.0398],"geometry_types":["point"],"unique_name":null,"name":"Workbook6","feature_count":1,"description":"","next_feature":null,"is_raster":false,"short_classification":"Y","stats":{"latitude":{"max":38.039849,"min":38.039849,"median":38.039849},"satisfaction (1 - 5)":{"max":4,"min":4,"median":4},"longitude":{"max":-84.503486,"min":-84.503486,"median":-84.503486}},"features":[{"properties":{"restaurant":"Ovid's Express","reasons for dining":"Proximity","meal photos":null,"latitude":38.039849,"satisfaction (1 - 5)":4,"uk status":"Grad","frequency of dining [per week]":"1 -- 2","longitude":-84.503486,"id":"adv4l5ofmgkk"},"type":"Feature","geometry":{"type":"Point","coordinates":[-84.503486,38.039849]}}],"is_temporal":false,"author":{"url":"","metadata":null,"contact_name":null,"contact_address":null,"source":null,"contact_phone":null},"source":"","pagination":{"sort":null,"start":0,"total":1,"limit":1000000},"state":"complete","tags":"","published":"2014-08-16T14:49:57-04:00","id":350911}