{"type":"FeatureCollection","data_type":"Dataset","url_type":null,"permissions":[{"permissions":{"download":true,"view":true},"group_id":"everyone"}],"classification":null,"title":"Suan Mone school","count":1,"stream_id":351800,"contributor":{"url":"http://geocommons.com/users/38169","name":"blewislao"},"data_attributes":null,"calculation_params":null,"icon_link":null,"link":"http://geocommons.com/overlays/351800.json","extent":[103.641,19.7927,103.641,19.7927],"geometry_types":["point"],"unique_name":null,"name":"Suan Mone school","feature_count":1,"description":"","next_feature":null,"is_raster":false,"short_classification":"Y","stats":{"lat":{"max":19.792741,"min":19.792741,"median":19.792741},"long":{"max":103.641395,"min":103.641395,"median":103.641395}},"features":[{"properties":{"ref no.":"SM395","feature":"School","id":"adxmf7dcim1o","lat":19.792741,"long":103.641395},"type":"Feature","geometry":{"type":"Point","coordinates":[103.641395,19.792741]}}],"is_temporal":false,"author":{"url":"","metadata":"","contact_name":"","contact_address":"","source":"","contact_phone":""},"source":"","pagination":{"sort":null,"start":0,"total":1,"limit":1000000},"state":"complete","tags":"","published":"2014-08-16T16:33:50-04:00","id":351800}