{"type":"FeatureCollection","data_type":"Dataset","url_type":null,"permissions":[{"permissions":{"download":true,"view":true},"group_id":"everyone"}],"classification":null,"title":"CE_Heatmap","count":18,"stream_id":352685,"contributor":{"url":"http://geocommons.com/users/71158","name":"madsdad"},"data_attributes":null,"calculation_params":null,"icon_link":null,"link":"http://geocommons.com/overlays/352685.json","extent":[-84.2999,41.2978,-83.3783,41.7189],"geometry_types":["point"],"unique_name":null,"name":"CE_Heatmap","feature_count":18,"description":"","next_feature":null,"is_raster":false,"short_classification":"Y","stats":{"response index":{"max":314,"variance":4375.11437908497,"mean":118.944444444444,"stdev":66.1446473955751,"min":23,"median":99}},"features":[{"properties":{"response index":111,"geo_score":0.714,"zip code":"43431","id":"adzd2x9j5hdn","geo_precision":"zip"},"type":"Feature","geometry":{"type":"Point","coordinates":[-83.37826,41.340886]}},{"properties":{"response index":205,"geo_score":0.714,"zip code":"43465","id":"adzd2xe5ff6v","geo_precision":"zip"},"type":"Feature","geometry":{"type":"Point","coordinates":[-83.511321,41.558662]}},{"properties":{"response index":76,"geo_score":0.714,"zip code":"43512","id":"adzd2xkhdd19","geo_precision":"zip"},"type":"Feature","geometry":{"type":"Point","coordinates":[-84.299947,41.297826]}},{"properties":{"response index":314,"geo_score":0.714,"zip code":"43542","id":"adzd2xct8qd1","geo_precision":"zip"},"type":"Feature","geometry":{"type":"Point","coordinates":[-83.772378,41.577251]}},{"properties":{"response index":88,"geo_score":0.714,"zip code":"43551","id":"adzd2xbx2abb","geo_precision":"zip"},"type":"Feature","geometry":{"type":"Point","coordinates":[-83.577701,41.535057]}},{"properties":{"response index":89,"geo_score":0.714,"zip code":"43558","id":"adzd2xm0m6zx","geo_precision":"zip"},"type":"Feature","geometry":{"type":"Point","coordinates":[-83.911609,41.671996]}},{"properties":{"response index":184,"geo_score":0.714,"zip code":"43566","id":"adzd2xhx0lbg","geo_precision":"zip"},"type":"Feature","geometry":{"type":"Point","coordinates":[-83.765287,41.513751]}},{"properties":{"response index":84,"geo_score":0.714,"zip code":"43567","id":"adzd2xe5kw8b","geo_precision":"zip"},"type":"Feature","geometry":{"type":"Point","coordinates":[-84.206059,41.603384]}},{"properties":{"response index":77,"geo_score":0.714,"zip code":"43571","id":"adzd2xmnuogw","geo_precision":"zip"},"type":"Feature","geometry":{"type":"Point","coordinates":[-83.801789,41.509602]}},{"properties":{"response index":156,"geo_score":0.714,"zip code":"43605","id":"adzd2xavl0vv","geo_precision":"zip"},"type":"Feature","geometry":{"type":"Point","coordinates":[-83.508482,41.652548]}},{"properties":{"response index":23,"geo_score":0.714,"zip code":"43607","id":"adzd2x7af49d","geo_precision":"zip"},"type":"Feature","geometry":{"type":"Point","coordinates":[-83.606785,41.647399]}},{"properties":{"response index":140,"geo_score":0.714,"zip code":"43611","id":"adzd2xls8avk","geo_precision":"zip"},"type":"Feature","geometry":{"type":"Point","coordinates":[-83.479378,41.718937]}},{"properties":{"response index":63,"geo_score":0.714,"zip code":"43612","id":"adzd2x9ttglj","geo_precision":"zip"},"type":"Feature","geometry":{"type":"Point","coordinates":[-83.55799,41.691716]}},{"properties":{"response index":74,"geo_score":0.714,"zip code":"43613","id":"adzd2xarxojo","geo_precision":"zip"},"type":"Feature","geometry":{"type":"Point","coordinates":[-83.606235,41.703548]}},{"properties":{"response index":99,"geo_score":0.714,"zip code":"43614","id":"adzd2xi3yoqr","geo_precision":"zip"},"type":"Feature","geometry":{"type":"Point","coordinates":[-83.633941,41.609041]}},{"properties":{"response index":99,"geo_score":0.714,"zip code":"43617","id":"adzd2xasmhmy","geo_precision":"zip"},"type":"Feature","geometry":{"type":"Point","coordinates":[-83.722437,41.66765]}},{"properties":{"response index":149,"geo_score":0.714,"zip code":"43619","id":"adzd2x6v76sd","geo_precision":"zip"},"type":"Feature","geometry":{"type":"Point","coordinates":[-83.485681,41.596099]}},{"properties":{"response index":110,"geo_score":0.714,"zip code":"43623","id":"adzd2xk41btt","geo_precision":"zip"},"type":"Feature","geometry":{"type":"Point","coordinates":[-83.682686,41.702949]}}],"is_temporal":false,"author":{"url":"","metadata":null,"contact_name":null,"contact_address":null,"source":null,"contact_phone":null},"source":"","pagination":{"sort":null,"start":0,"total":18,"limit":1000000},"state":"complete","tags":"","published":"2014-08-16T17:38:17-04:00","id":352685}