{"type":"FeatureCollection","data_type":"Dataset","url_type":null,"permissions":[{"permissions":{"download":true,"view":true},"group_id":"everyone"}],"classification":null,"title":"Lat long ","count":3,"stream_id":353177,"contributor":{"url":"http://geocommons.com/users/70424","name":"sigurdo"},"data_attributes":null,"calculation_params":null,"icon_link":null,"link":"http://geocommons.com/overlays/353177.json","extent":[59.9116,10.7261,60.0247,10.8084],"geometry_types":["point"],"unique_name":null,"name":"Lat long ","feature_count":3,"description":"","next_feature":null,"is_raster":false,"short_classification":"Y","stats":{"lat":{"max":10.808435,"variance":0.00169530331033331,"mean":10.7674326666667,"stdev":0.0411740611348129,"min":10.726089,"median":10.767774},"long":{"max":60.024726,"variance":0.00334101336233329,"mean":59.9612926666667,"stdev":0.0578014996547087,"min":59.911599,"median":59.947553}},"features":[{"properties":{"id":"ae0tulm4tr46","lat":10.726089,"long":60.024726},"type":"Feature","geometry":{"type":"Point","coordinates":[60.024726,10.726089]}},{"properties":{"id":"ae0tulmumvew","lat":10.767774,"long":59.947553},"type":"Feature","geometry":{"type":"Point","coordinates":[59.947553,10.767774]}},{"properties":{"id":"ae0tuliviy2o","lat":10.808435,"long":59.911599},"type":"Feature","geometry":{"type":"Point","coordinates":[59.911599,10.808435]}}],"is_temporal":false,"author":{"url":"","metadata":"","contact_name":"","contact_address":"","source":"","contact_phone":""},"source":"","pagination":{"sort":null,"start":0,"total":3,"limit":1000000},"state":"complete","tags":"","published":"2014-08-16T18:08:42-04:00","id":353177}