{"type":"FeatureCollection","data_type":"Dataset","url_type":null,"permissions":[{"permissions":{"download":true,"view":true},"group_id":"everyone"}],"classification":null,"title":"Mason County","count":2,"stream_id":353364,"contributor":{"url":"http://geocommons.com/users/71218","name":"dr194-13ID@redcross.org"},"data_attributes":null,"calculation_params":null,"icon_link":null,"link":"http://geocommons.com/overlays/353364.json","extent":[-90.1098,37.4681,-88.7552,40.2382],"geometry_types":["point"],"unique_name":null,"name":"Mason County","feature_count":2,"description":"","next_feature":null,"is_raster":false,"short_classification":"Y","stats":{},"features":[{"properties":{"geo_score":0.531,"id":"ae16o6ymral4","address":"EAST STREET MATANZAS BEACH IL","geo_precision":"street"},"type":"Feature","geometry":{"type":"Point","coordinates":[-88.755229,37.468101]}},{"properties":{"geo_score":0.861,"id":"ae16o6zevdck","address":"12784 N. STATE ROUTE 78 MATANZAS BEACH IL","geo_precision":"range"},"type":"Feature","geometry":{"type":"Point","coordinates":[-90.10979,40.238212]}}],"is_temporal":false,"author":{"url":"","metadata":"","contact_name":"","contact_address":"","source":"","contact_phone":""},"source":"","pagination":{"sort":null,"start":0,"total":2,"limit":1000000},"state":"complete","tags":"","published":"2014-08-16T18:24:51-04:00","id":353364}