{"type":"FeatureCollection","data_type":"Dataset","url_type":null,"permissions":[{"permissions":{"download":true,"view":true},"group_id":"everyone"}],"classification":null,"title":"Projected_Power_Plants_SS_Africa","count":1,"stream_id":355700,"contributor":{"url":"http://geocommons.com/users/60532","name":"etiope"},"data_attributes":null,"calculation_params":null,"icon_link":null,"link":"http://geocommons.com/overlays/355700.json","extent":[32.239,2.242,32.239,2.242],"geometry_types":["point"],"unique_name":null,"name":"Projected_Power_Plants_SS_Africa","feature_count":1,"description":"","next_feature":null,"is_raster":false,"short_classification":"Y","stats":{"latitude":{"max":null,"min":null,"median":null},"total mw":{"max":null,"min":null,"median":null},"longitude":{"max":null,"min":null,"median":null}},"features":[{"properties":{"latitude":"2.242.912","financiers":"CHINA","plant":"KARUMA FALLS","country":"UGANDA","type":"HYDRO","total mw":"600","owner":"UEB-UGANDA ELECTRICITY BOARD","longitude":"32.239.739","id":"ae7lvl6c1tgq","budget":"$2bn"},"type":"Feature","geometry":{"type":"Point","coordinates":[32.239,2.242]}}],"is_temporal":false,"author":{"url":"","metadata":null,"contact_name":null,"contact_address":null,"source":null,"contact_phone":null},"source":"","pagination":{"sort":null,"start":0,"total":1,"limit":1000000},"state":"geocoded","tags":"","published":"2014-08-16T21:26:06-04:00","id":355700}