{"type":"FeatureCollection","data_type":"Dataset","url_type":null,"permissions":[{"permissions":{"download":true,"view":true},"group_id":"everyone"}],"classification":null,"title":"Umatilla Wells","count":11,"stream_id":35757,"contributor":{"url":"http://geocommons.com/users/12400","name":"klynch"},"data_attributes":null,"calculation_params":null,"icon_link":null,"link":"http://geocommons.com/overlays/35757.json","extent":[-119.587,45.8899,-119.551,45.8962],"geometry_types":["point"],"unique_name":null,"name":"Umatilla Wells","feature_count":11,"description":"","next_feature":null,"is_raster":false,"short_classification":"Y","stats":{"ID":{"max":11,"mean":6.0,"variance":11.0,"stdev":3.3166247903554,"min":1,"median":6},"Long":{"max":-119.5515,"mean":-119.570982454545,"variance":0.000149737683072725,"stdev":0.0122367349841665,"min":-119.587444,"median":-119.566806},"Elevation":{"max":266,"mean":256.363636363636,"variance":29.2545454545455,"stdev":5.40874712429278,"min":250,"median":257},"Lat":{"max":45.896222,"mean":45.8927523636364,"variance":3.54660325454601e-06,"stdev":0.00188324274976595,"min":45.889944,"median":45.892917}},"features":[{"properties":{"Name":"ES1","ID":1,"Long":-119.561139,"Elevation":257,"id":"a63gv8li74wg","Lat":45.890778},"type":"Feature","geometry":{"type":"Point","coordinates":[-119.561139,45.890778]}},{"properties":{"Name":"ES2","ID":2,"Long":-119.562167,"Elevation":250,"id":"a63gv8qbicf5","Lat":45.892917},"type":"Feature","geometry":{"type":"Point","coordinates":[-119.562167,45.892917]}},{"properties":{"Name":"ES3","ID":3,"Long":-119.563167,"Elevation":251,"id":"a63gv8cuwi95","Lat":45.894222},"type":"Feature","geometry":{"type":"Point","coordinates":[-119.563167,45.894222]}},{"properties":{"Name":"ES4","ID":4,"Long":-119.563,"Elevation":250,"id":"a63gv8jw8d5c","Lat":45.893972},"type":"Feature","geometry":{"type":"Point","coordinates":[-119.563,45.893972]}},{"properties":{"Name":"Nitrate1","ID":5,"Long":-119.573667,"Elevation":261,"id":"a63gv8ltiovd","Lat":45.892194},"type":"Feature","geometry":{"type":"Point","coordinates":[-119.573667,45.892194]}},{"properties":{"Name":"Nitrate2","ID":6,"Long":-119.566806,"Elevation":261,"id":"a63gv8eqf53k","Lat":45.893583},"type":"Feature","geometry":{"type":"Point","coordinates":[-119.566806,45.893583]}},{"properties":{"Name":"NitrateW","ID":7,"Long":-119.5515,"Elevation":266,"id":"a63gv8oeyz8k","Lat":45.896222},"type":"Feature","geometry":{"type":"Point","coordinates":[-119.5515,45.896222]}},{"properties":{"Name":"WS1","ID":8,"Long":-119.587444,"Elevation":252,"id":"a63gv8j7jnud","Lat":45.889944},"type":"Feature","geometry":{"type":"Point","coordinates":[-119.587444,45.889944]}},{"properties":{"Name":"WS2","ID":9,"Long":-119.58725,"Elevation":257,"id":"a63gv8ka1a3a","Lat":45.890306},"type":"Feature","geometry":{"type":"Point","coordinates":[-119.58725,45.890306]}},{"properties":{"Name":"WS3","ID":10,"Long":-119.581861,"Elevation":261,"id":"a63gv8ct70u1","Lat":45.893694},"type":"Feature","geometry":{"type":"Point","coordinates":[-119.581861,45.893694]}},{"properties":{"Name":"WS4","ID":11,"Long":-119.582806,"Elevation":254,"id":"a63gv8kcpnfu","Lat":45.892444},"type":"Feature","geometry":{"type":"Point","coordinates":[-119.582806,45.892444]}}],"is_temporal":false,"author":{"url":"","metadata":"","contact_name":"","contact_address":"","source":"","contact_phone":""},"source":"","pagination":{"sort":null,"start":0,"total":11,"limit":1000000},"state":"complete","tags":"","published":"2014-08-10T16:24:51-04:00","id":35757}