{"type":"FeatureCollection","data_type":"Dataset","url_type":null,"permissions":[{"permissions":{"download":true,"view":true},"group_id":"everyone"}],"classification":null,"title":"sediment","count":4,"stream_id":357625,"contributor":{"url":"http://geocommons.com/users/46810","name":"marievi"},"data_attributes":null,"calculation_params":null,"icon_link":null,"link":"http://geocommons.com/overlays/357625.json","extent":[8.51332,53.1164,8.71523,53.1979],"geometry_types":["point"],"unique_name":null,"name":"sediment","feature_count":4,"description":"","next_feature":null,"is_raster":false,"short_classification":"Y","stats":{"lat":{"max":53.1979341,"variance":0.00144230782944658,"mean":53.1542571,"stdev":0.0379777280711548,"min":53.1164397,"median":53.1733718},"long":{"max":8.715233,"variance":0.00758019461813663,"mean":8.61075255,"stdev":0.0870643131147121,"min":8.5133157,"median":8.6411842}},"features":[{"properties":{"column_1":null,"id":"aecs7yrliwzh","lat":53.1164397,"long":8.715233},"type":"Feature","geometry":{"type":"Point","coordinates":[8.715233,53.1164397]}},{"properties":{"column_1":null,"id":"aecs7ywc7ha4","lat":53.1292828,"long":8.6411842},"type":"Feature","geometry":{"type":"Point","coordinates":[8.6411842,53.1292828]}},{"properties":{"column_1":null,"id":"aecs7yx4dm52","lat":53.1733718,"long":8.5732773},"type":"Feature","geometry":{"type":"Point","coordinates":[8.5732773,53.1733718]}},{"properties":{"column_1":null,"id":"aecs7yroxx4h","lat":53.1979341,"long":8.5133157},"type":"Feature","geometry":{"type":"Point","coordinates":[8.5133157,53.1979341]}}],"is_temporal":false,"author":{"url":"","metadata":"","contact_name":"","contact_address":"","source":"","contact_phone":""},"source":"","pagination":{"sort":null,"start":0,"total":4,"limit":1000000},"state":"complete","tags":"","published":"2014-08-16T23:31:51-04:00","id":357625}