{"type":"FeatureCollection","data_type":"Dataset","url_type":null,"permissions":[{"permissions":{"download":true,"view":true},"group_id":"everyone"}],"classification":null,"title":"MTP 2013 septembre","count":3,"stream_id":361933,"contributor":{"url":"http://geocommons.com/users/42827","name":"jflacou"},"data_attributes":null,"calculation_params":null,"icon_link":null,"link":"http://geocommons.com/overlays/361933.json","extent":[1.43054,46.4568,1.96058,47.1236],"geometry_types":["point"],"unique_name":null,"name":"MTP 2013 septembre","feature_count":3,"description":"","next_feature":null,"is_raster":false,"short_classification":"Y","stats":{},"features":[{"properties":{"name":"LE MAGNY","description":"Dans le cadre du Festival \"Pierres qui chantent en Vallée Noire\"  avec les concerts des groupes \"Le Chœur des Hommes de la Roche\" (chants traditionnels) et \"Les Désanchés\" (quatuor de clarinettes), le 7 septembre à 20 h 30 en l'église.","id":"aemw1kumrh1i"},"type":"Feature","geometry":{"type":"Point","coordinates":[1.96058,46.56655]}},{"properties":{"name":"LUCAY-LE-MALE","description":"Spectacle \"Sodome, ma douce\" de la \"Cie des Voyageurs Ephémères\", le 6 septembre à 20 h 30, Théâtre de la Grange Aux Blas-Blas.","id":"aemw1kgo2uwp"},"type":"Feature","geometry":{"type":"Point","coordinates":[1.43636,47.12355]}},{"properties":{"name":"THENAY","description":"Concert de musique classique avec l'Association \"L''Autre Concert\", le 29 septembre à 16 h en l'Eglise.","id":"aemw1kt5tzql"},"type":"Feature","geometry":{"type":"Point","coordinates":[1.43054,46.63108]}}],"is_temporal":false,"author":{"url":"","metadata":"","contact_name":"","contact_address":"","source":"","contact_phone":""},"source":"","pagination":{"sort":null,"start":0,"total":3,"limit":1000000},"state":"complete","tags":"","published":"2014-08-16T15:47:53-04:00","id":361933}