{"type":"FeatureCollection","data_type":"Dataset","url_type":null,"permissions":[{"permissions":{"download":true,"edit":true,"view":true},"group_id":13923},{"permissions":{"download":true,"edit":true,"view":true},"group_id":27421},{"permissions":{"download":true,"view":true},"group_id":"everyone"}],"classification":null,"title":"Arlington locations","count":3,"stream_id":362738,"contributor":{"url":"http://geocommons.com/users/695","name":"Bill"},"data_attributes":null,"calculation_params":null,"icon_link":null,"link":"http://geocommons.com/overlays/362738.json","extent":[-77.0944,38.8816,-77.0861,38.8943],"geometry_types":["point"],"unique_name":"","name":"Arlington locations","feature_count":3,"description":"3 points within arlington VA","next_feature":null,"is_raster":false,"short_classification":"Y","stats":{"value":{"max":3,"variance":1.0,"mean":2.0,"stdev":1.0,"min":1,"median":2},"geo_precision":{"count":2,"counts_by_value":{"range":2,"street":1},"list":["range","street"]}},"features":[{"properties":{"city":"Arlington","zip":"22201","geo_score":1.0,"value":1,"id":"aeo5evpfv5k5","address":"820 north cleveland street","geo_precision":"range","state":"VA"},"type":"Feature","geometry":{"type":"Point","coordinates":[-77.088628,38.881595]}},{"properties":{"city":"Arlington","zip":"22201","geo_score":0.955,"value":2,"id":"aeo5evxxzvzm","address":"2200 Wilson blvd","geo_precision":"range","state":"VA"},"type":"Feature","geometry":{"type":"Point","coordinates":[-77.086145,38.891096]}},{"properties":{"city":"Arlington","zip":"22201","geo_score":0.74,"value":3,"id":"aeo5evxf522d","address":"1001 19th street north","geo_precision":"street","state":"VA"},"type":"Feature","geometry":{"type":"Point","coordinates":[-77.094383,38.894335]}}],"is_temporal":false,"author":{"url":"http://un.org","metadata":"http://un.org/metadata","contact_name":"Bill Greer","contact_address":"1001 19th road ","source":"United nations environment programme","contact_phone":"3495834-5"},"source":"http://un.org","pagination":{"sort":null,"start":0,"total":3,"limit":1000000},"state":"complete","tags":"arlington,home,office,old,work","published":"2012-07-02T16:00:00Z","id":362738}