{"type":"FeatureCollection","data_type":"Dataset","url_type":null,"permissions":[{"permissions":{"download":true,"view":true},"group_id":"everyone"}],"classification":null,"title":"Proposed Early Vote Locations","count":5,"stream_id":363890,"contributor":{"url":"http://geocommons.com/users/40268","name":"ONBoleman"},"data_attributes":null,"calculation_params":null,"icon_link":null,"link":"http://geocommons.com/overlays/363890.json","extent":[-80.9402,35.1321,-80.7279,35.3732],"geometry_types":["point"],"unique_name":null,"name":"Proposed Early Vote Locations","feature_count":5,"description":"","next_feature":null,"is_raster":false,"short_classification":"Y","stats":{},"features":[{"properties":{"name":"Charlotte Fire Department","description":null,"id":"aer0eo837iac"},"type":"Feature","geometry":{"type":"Point","coordinates":[-80.940201,35.132053]}},{"properties":{"name":"Charlotte FD Station 26","description":"","id":"aer0eofmsrme"},"type":"Feature","geometry":{"type":"Point","coordinates":[-80.940201,35.132053]}},{"properties":{"name":"Hal Marshall Annex","description":"","id":"aer0eo8jqryu"},"type":"Feature","geometry":{"type":"Point","coordinates":[-80.835823,35.230076]}},{"properties":{"name":"Charlotte Mecklenburg Library Hickory Grove branch","description":"","id":"aer0eo6jkwf0"},"type":"Feature","geometry":{"type":"Point","coordinates":[-80.727867,35.222858]}},{"properties":{"name":"North Mecklenburg High School","description":"","id":"aer0eo5xowsz"},"type":"Feature","geometry":{"type":"Point","coordinates":[-80.833961,35.373196]}}],"is_temporal":false,"author":{"url":"","metadata":"","contact_name":"","contact_address":"","source":"","contact_phone":""},"source":"","pagination":{"sort":null,"start":0,"total":5,"limit":1000000},"state":"complete","tags":"","published":"2014-08-16T18:22:55-04:00","id":363890}