{"type":"FeatureCollection","data_type":"Dataset","url_type":null,"permissions":[{"permissions":{"download":true,"view":true},"group_id":"everyone"}],"classification":null,"title":"UGM places","count":5,"stream_id":36546,"contributor":{"url":"http://geocommons.com/users/11357","name":"mrbenjohnson"},"data_attributes":null,"calculation_params":null,"icon_link":null,"link":"http://geocommons.com/overlays/36546.json","extent":[-123.091,49.1342,-122.308,49.282],"geometry_types":["point"],"unique_name":null,"name":"UGM places","feature_count":5,"description":"","next_feature":null,"is_raster":false,"short_classification":"Y","stats":{"name":{"max":5,"mean":3.0,"variance":2.5,"stdev":1.58113883008419,"min":1,"median":3},"latitude":{"max":49.281996,"mean":49.2197708,"variance":0.00394011357569994,"stdev":0.0627703240050578,"min":49.134186,"median":49.202645},"longitude":{"max":-122.308043,"mean":-122.848725,"variance":0.103201225082502,"stdev":0.321249474836149,"min":-123.090922,"median":-122.909831}},"features":[{"properties":{"name":3,"latitude":49.134186,"longitude":-122.308043,"id":"a64f4d4gm0zh"},"type":"Feature","geometry":{"type":"Point","coordinates":[-122.308043,49.134186]}},{"properties":{"name":5,"latitude":49.198475,"longitude":-122.845144,"id":"a64f4cwejb56"},"type":"Feature","geometry":{"type":"Point","coordinates":[-122.845144,49.198475]}},{"properties":{"name":2,"latitude":49.202645,"longitude":-122.909831,"id":"a64f4dadfyq1"},"type":"Feature","geometry":{"type":"Point","coordinates":[-122.909831,49.202645]}},{"properties":{"name":4,"latitude":49.281552,"longitude":-123.089685,"id":"a64f4d3utooq"},"type":"Feature","geometry":{"type":"Point","coordinates":[-123.089685,49.281552]}},{"properties":{"name":1,"latitude":49.281996,"longitude":-123.090922,"id":"a64f4czfw1gk"},"type":"Feature","geometry":{"type":"Point","coordinates":[-123.090922,49.281996]}}],"is_temporal":false,"author":{"url":"","metadata":"","contact_name":"","contact_address":"","source":"","contact_phone":""},"source":"","pagination":{"sort":null,"start":0,"total":5,"limit":1000000},"state":"complete","tags":"random","published":"2014-08-10T17:14:46-04:00","id":36546}