{"type":"FeatureCollection","data_type":"Dataset","url_type":null,"permissions":[{"permissions":{"download":true,"view":true},"group_id":"everyone"}],"classification":null,"title":"Senior Facilities - Steeles L'Amoreaux","count":3,"stream_id":367023,"contributor":{"url":"http://geocommons.com/users/50466","name":"SteelesAmoreauxANC"},"data_attributes":null,"calculation_params":null,"icon_link":null,"link":"http://geocommons.com/overlays/367023.json","extent":[-79.3327,43.7952,-79.3004,43.8039],"geometry_types":["point"],"unique_name":null,"name":"Senior Facilities - Steeles L'Amoreaux","feature_count":3,"description":"","next_feature":null,"is_raster":false,"short_classification":"Y","stats":{"latitude":{"max":43.803936,"variance":1.95188893333502e-05,"mean":43.7998266666667,"stdev":0.00441801871129472,"min":43.795154,"median":43.80039},"longitude":{"max":-79.300365,"variance":0.000274000172333278,"mean":-79.3185763333333,"stdev":0.0165529505627631,"min":-79.332708,"median":-79.322656}},"features":[{"properties":{"neighbourhood name":"Steeles-L'Amoreaux","latitude":43.803936,"establishment name":"TransCare Community Support Services","accessibility":null,"website":"tcare.ca","parking available":null,"postal code":"M1W 3W6","phone":"416-750-9885","fax":"416-750-1310","capacity":null,"services":null,"business hours":null,"longitude":-79.332708,"id":"af0e3ou6wdzi","address":"1045 McNicoll Ave.","personal requirements":null},"type":"Feature","geometry":{"type":"Point","coordinates":[-79.332708,43.803936]}},{"properties":{"neighbourhood name":"Steeles-L'Amoreaux","latitude":43.795154,"establishment name":"St. Paul's L'Amoreaux Centre","accessibility":null,"website":"http://www.splc.ca","parking available":null,"postal code":"M1W 2R9","phone":"416-493-3333","fax":null,"capacity":null,"services":"-Housing -health promotion -recreation","business hours":null,"longitude":-79.322656,"id":"af0e3oocil7w","address":"Finch Ave. E","personal requirements":null},"type":"Feature","geometry":{"type":"Point","coordinates":[-79.322656,43.795154]}},{"properties":{"neighbourhood name":"Steeles-L'Amoreaux","latitude":43.80039,"establishment name":"Centre For Information &amp; Community Services Of Ontario","accessibility":null,"website":"http://www.cicscanada.com/","parking available":null,"postal code":"M1T 3T6","phone":"416-293-4565","fax":"416-293- 5692","capacity":null,"services":"-Early Years Services -School Readiness -Recreation and Interest","business hours":null,"longitude":-79.300365,"id":"af0e3oyoxaph","address":"403-3850 Finch Ave. E","personal requirements":null},"type":"Feature","geometry":{"type":"Point","coordinates":[-79.300365,43.80039]}}],"is_temporal":false,"author":{"url":"","metadata":"","contact_name":"","contact_address":"","source":"","contact_phone":""},"source":"","pagination":{"sort":null,"start":0,"total":3,"limit":1000000},"state":"complete","tags":"","published":"2014-08-16T22:35:10-04:00","id":367023}