{"type":"FeatureCollection","data_type":"Dataset","url_type":null,"permissions":[{"permissions":{"download":true,"view":true},"group_id":"everyone"}],"classification":null,"title":"Mississauga_C","count":1,"stream_id":367125,"contributor":{"url":"http://geocommons.com/users/74787","name":"stevendosanjh"},"data_attributes":null,"calculation_params":null,"icon_link":null,"link":"http://geocommons.com/overlays/367125.json","extent":[-79.7463,43.6084,-79.7463,43.6084],"geometry_types":["point"],"unique_name":null,"name":"Mississauga_C","feature_count":1,"description":"","next_feature":null,"is_raster":false,"short_classification":"Y","stats":{"latitude":{"max":43.608446,"median":43.608446,"min":43.608446},"order":{"max":9999,"median":9999,"min":9999},"longitude":{"max":-79.746297,"median":-79.746297,"min":-79.746297},"identifying number":{"max":10927936,"median":10927936,"min":10927936}},"features":[{"properties":{"delete":null,"city":"Mississauga","category":"Contact Centre","subcategory":null,"latitude":43.608446,"photo url":null,"title":"Mississauga","directions":"FALSE","order":9999,"street1":null,"zipcode":"L5N 7Y5","photo height":null,"freeform address":"Mississauga, ON, L5N 7Y5, CA","street2":null,"country":"CA","website":null,"description":null,"photo width":null,"neighborhood":null,"photo description":null,"identifying number":10927936,"longitude":-79.746297,"link":"http://www.communitywalk.com/map/1605311#0004Y[m0","id":"af0pdf4yp2gs","phone number":null,"state":"ON","photo title":null},"type":"Feature","geometry":{"type":"Point","coordinates":[-79.746297,43.608446]}}],"is_temporal":false,"author":{"url":"","metadata":"","contact_name":"","contact_address":"","source":"","contact_phone":""},"source":"","pagination":{"sort":null,"start":0,"total":1,"limit":1000000},"state":"complete","tags":"","published":"2014-08-16T22:46:22-04:00","id":367125}