{"type":"FeatureCollection","data_type":"Dataset","url_type":null,"permissions":[{"permissions":{"download":true,"view":true},"group_id":"everyone"}],"classification":null,"title":"767-300ER Rons-Rads","count":9,"stream_id":368371,"contributor":{"url":"http://geocommons.com/users/38310","name":"Dlforecastdemand"},"data_attributes":null,"calculation_params":null,"icon_link":null,"link":"http://geocommons.com/overlays/368371.json","extent":[-122.309,25.0777,121.805,52.3086],"geometry_types":["point"],"unique_name":null,"name":"767-300ER Rons-Rads","feature_count":9,"description":"","next_feature":null,"is_raster":false,"short_classification":"Y","stats":{"latitude":{"max":52.30860138,"variance":71.2899562539838,"mean":38.49891154,"stdev":8.443337980561,"median":40.08010101,"min":25.07769966},"rons rads":{"max":251,"variance":6117.5,"mean":68.0,"stdev":78.2144487930459,"median":62,"min":2},"longitude":{"max":121.8050003,"variance":11262.9473431781,"mean":-13.0989451366667,"stdev":106.127033988415,"median":-73.77890015,"min":-122.3089981}},"features":[{"properties":{"latitude":52.30860138,"airport code":"AMS","rons rads":4,"longitude":4.76388979,"id":"af4b3fylyhpo"},"type":"Feature","geometry":{"type":"Point","coordinates":[4.76388979,52.30860138]}},{"properties":{"latitude":33.63669968,"airport code":"ATL","rons rads":251,"longitude":-84.42810059,"id":"af4b3ft8gz81"},"type":"Feature","geometry":{"type":"Point","coordinates":[-84.42810059,33.63669968]}},{"properties":{"latitude":42.21239853,"airport code":"DTW","rons rads":31,"longitude":-83.35340118,"id":"af4b3fuewu03"},"type":"Feature","geometry":{"type":"Point","coordinates":[-83.35340118,42.21239853]}},{"properties":{"latitude":40.63980103,"airport code":"JFK","rons rads":101,"longitude":-73.77890015,"id":"af4b3fkkqazy"},"type":"Feature","geometry":{"type":"Point","coordinates":[-73.77890015,40.63980103]}},{"properties":{"latitude":33.94250107,"airport code":"LAX","rons rads":93,"longitude":-118.4079971,"id":"af4b3fr4quhh"},"type":"Feature","geometry":{"type":"Point","coordinates":[-118.4079971,33.94250107]}},{"properties":{"latitude":40.08010101,"airport code":"PEK","rons rads":62,"longitude":116.5849991,"id":"af4b3flyvktv"},"type":"Feature","geometry":{"type":"Point","coordinates":[116.5849991,40.08010101]}},{"properties":{"latitude":31.14340019,"airport code":"PVG","rons rads":62,"longitude":121.8050003,"id":"af4b3frzz9jt"},"type":"Feature","geometry":{"type":"Point","coordinates":[121.8050003,31.14340019]}},{"properties":{"latitude":47.44900131,"airport code":"SEA","rons rads":2,"longitude":-122.3089981,"id":"af4b3fo1iyt6"},"type":"Feature","geometry":{"type":"Point","coordinates":[-122.3089981,47.44900131]}},{"properties":{"latitude":25.07769966,"airport code":"TPE","rons rads":6,"longitude":121.2330017,"id":"af4b3fzw0um3"},"type":"Feature","geometry":{"type":"Point","coordinates":[121.2330017,25.07769966]}}],"is_temporal":false,"author":{"url":"","metadata":"","contact_name":"","contact_address":"","source":"","contact_phone":""},"source":"","pagination":{"sort":null,"start":0,"total":9,"limit":1000000},"state":"complete","tags":"","published":"2014-08-17T00:02:24-04:00","id":368371}