{"type":"FeatureCollection","data_type":"Dataset","url_type":null,"permissions":[{"permissions":{"download":true,"view":true},"group_id":"everyone"}],"classification":null,"title":"A330-200 Rons-Rads","count":4,"stream_id":368357,"contributor":{"url":"http://geocommons.com/users/38310","name":"Dlforecastdemand"},"data_attributes":null,"calculation_params":null,"icon_link":null,"link":"http://geocommons.com/overlays/368357.json","extent":[-122.309,33.6367,4.76389,52.3086],"geometry_types":["point"],"unique_name":null,"name":"A330-200 Rons-Rads","feature_count":4,"description":"","next_feature":null,"is_raster":false,"short_classification":"Y","stats":{"latitude":{"max":52.30860138,"variance":62.6029987706465,"mean":44.569075585,"stdev":7.91220568303469,"min":33.63669968,"median":47.44900131},"rons rads":{"max":36,"variance":243.583333333333,"mean":23.75,"stdev":15.607156478146,"min":1,"median":31},"longitude":{"max":4.76388979,"variance":3005.1901917112,"mean":-73.798752665,"stdev":54.8196150270247,"min":-122.3089981,"median":-84.42810059}},"features":[{"properties":{"latitude":52.30860138,"airport code":"AMS","rons rads":27,"longitude":4.76388979,"id":"af4apodi7xrt"},"type":"Feature","geometry":{"type":"Point","coordinates":[4.76388979,52.30860138]}},{"properties":{"latitude":33.63669968,"airport code":"ATL","rons rads":36,"longitude":-84.42810059,"id":"af4apod09dp7"},"type":"Feature","geometry":{"type":"Point","coordinates":[-84.42810059,33.63669968]}},{"properties":{"latitude":44.88199997,"airport code":"MSP","rons rads":31,"longitude":-93.22180176,"id":"af4apogmc1gg"},"type":"Feature","geometry":{"type":"Point","coordinates":[-93.22180176,44.88199997]}},{"properties":{"latitude":47.44900131,"airport code":"SEA","rons rads":1,"longitude":-122.3089981,"id":"af4apoiwz406"},"type":"Feature","geometry":{"type":"Point","coordinates":[-122.3089981,47.44900131]}}],"is_temporal":false,"author":{"url":"","metadata":"","contact_name":"","contact_address":"","source":"","contact_phone":""},"source":"","pagination":{"sort":null,"start":0,"total":4,"limit":1000000},"state":"complete","tags":"","published":"2014-08-17T00:02:14-04:00","id":368357}