{"type":"FeatureCollection","data_type":"Dataset","url_type":null,"permissions":[{"permissions":{"download":true,"view":true},"group_id":"everyone"}],"classification":null,"title":"final","count":3,"stream_id":368888,"contributor":{"url":"http://geocommons.com/users/8181","name":"matts8008"},"data_attributes":null,"calculation_params":null,"icon_link":null,"link":"http://geocommons.com/overlays/368888.json","extent":[-99.8294,31.528,-73.8439,43.0493],"geometry_types":["point"],"unique_name":null,"name":"final","feature_count":3,"description":"","next_feature":null,"is_raster":false,"short_classification":"Y","stats":{"avg. cpc":{"max":3.99,"variance":0.496933333333334,"mean":3.38333333333333,"stdev":0.704934985181849,"min":2.61,"median":3.55},"latitude":{"max":43.049266,"variance":41.1369828791111,"mean":35.6605371666667,"stdev":6.41381188367036,"min":31.5279975,"median":32.404348},"avg. position":{"max":2.6,"variance":0.00333333333333334,"mean":2.53333333333333,"stdev":0.0577350269189626,"min":2.5,"median":2.5},"cost":{"max":538.99,"variance":78781.1049333333,"mean":215.496666666667,"stdev":280.67971949062,"min":36.57,"median":70.93},"dma":{"max":662,"variance":5953.0,"mean":573.0,"stdev":77.1556867638413,"min":525,"median":532},"impressions":{"max":17685,"variance":79053382.3333333,"mean":7426.33333333333,"stdev":8891.19690105519,"min":1946,"median":2648},"clicks":{"max":135,"variance":4650.33333333333,"mean":56.3333333333333,"stdev":68.1933525597131,"min":14,"median":20},"longitude":{"max":-73.8438695,"variance":172.065612740781,"mean":-85.7951185,"stdev":13.1173782723828,"min":-99.8293625,"median":-83.7121235},"avg. cpm":{"max":30.48,"variance":35.7120333333333,"mean":25.3533333333333,"stdev":5.97595459598994,"min":18.79,"median":26.79}},"features":[{"properties":{"avg. cpc":2.61,"latitude":32.404348,"ctr":"0.72%","dma":662,"cost":36.57,"avg. position":2.5,"impressions":1946,"clicks":14,"longitude":-99.8293625,"id":"af572dn97fwt","metro area":"Abilene-Sweetwater TX","avg. cpm":18.79},"type":"Feature","geometry":{"type":"Point","coordinates":[-99.8293625,32.404348]}},{"properties":{"avg. cpc":3.55,"latitude":31.5279975,"ctr":"0.76%","dma":525,"cost":70.93,"avg. position":2.6,"impressions":2648,"clicks":20,"longitude":-83.7121235,"id":"af572dqxgfw4","metro area":"Albany GA","avg. cpm":26.79},"type":"Feature","geometry":{"type":"Point","coordinates":[-83.7121235,31.5279975]}},{"properties":{"avg. cpc":3.99,"latitude":43.049266,"ctr":"0.76%","dma":532,"cost":538.99,"avg. position":2.5,"impressions":17685,"clicks":135,"longitude":-73.8438695,"id":"af572e38206h","metro area":"Albany-Schenectady-Troy NY","avg. cpm":30.48},"type":"Feature","geometry":{"type":"Point","coordinates":[-73.8438695,43.049266]}}],"is_temporal":false,"author":{"url":"","metadata":null,"contact_name":null,"contact_address":null,"source":null,"contact_phone":null},"source":"","pagination":{"sort":null,"start":0,"total":3,"limit":1000000},"state":"complete","tags":"","published":"2014-08-17T00:43:33-04:00","id":368888}