{"type":"FeatureCollection","data_type":"Dataset","url_type":null,"permissions":[{"permissions":{"download":true,"view":true},"group_id":"everyone"}],"classification":null,"title":"Churches in MaNa","count":3,"stream_id":37194,"contributor":{"url":"http://geocommons.com/users/12684","name":"bahamas"},"data_attributes":null,"calculation_params":null,"icon_link":null,"link":"http://geocommons.com/overlays/37194.json","extent":[120.948,14.6407,120.954,14.6687],"geometry_types":["point"],"unique_name":null,"name":"Churches in MaNa","feature_count":3,"description":"Famous Churches of Malabon and Navotas","next_feature":null,"is_raster":false,"short_classification":"Y","stats":{"latitude":{"max":14.66875,"mean":14.6560793333333,"variance":0.000201661541333332,"stdev":0.0142007584773959,"min":14.64073,"median":14.658758},"longitude":{"max":120.953812,"mean":120.951092133333,"variance":1.01570062533061e-05,"stdev":0.00318700584456729,"min":120.9475854,"median":120.951879}},"features":[{"properties":{"name":"San Jose de Navotas Parish Church","latitude":14.64073,"description":"Oldest Church in Natvotas","links":"http://farm2.static.flickr.com/1440/572432218_7bb131d433_s.jpg","longitude":120.953812,"id":"a62hh9qjdixx"},"type":"Feature","geometry":{"type":"Point","coordinates":[120.953812,14.64073]}},{"properties":{"name":"San Bartolome Church","latitude":14.658758,"description":"The oldest Church in malabon","links":"http://heritageconservation.wordpress.com/2008/01/14/malabon-church","longitude":120.951879,"id":"a62hha1q0x5a"},"type":"Feature","geometry":{"type":"Point","coordinates":[120.951879,14.658758]}},{"properties":{"name":"Church of Immaculate Concepcion of Malabon","latitude":14.66875,"description":"Home of Pagoda-Caracol","links":"http://wikimapia.org/838582/Immaculate-Conception-Parish-Church","longitude":120.9475854,"id":"a62hh9u3l6cf"},"type":"Feature","geometry":{"type":"Point","coordinates":[120.9475854,14.66875]}}],"is_temporal":false,"author":{"url":"","metadata":"","contact_name":"","contact_address":"","source":"","contact_phone":""},"source":"","pagination":{"sort":null,"start":0,"total":3,"limit":1000000},"state":"complete","tags":"ncca_cultural_mapping_course","published":"2010-04-15T06:34:08Z","id":37194}