{"type":"FeatureCollection","data_type":"Dataset","url_type":null,"permissions":[{"permissions":{"download":true,"view":true},"group_id":"everyone"}],"classification":null,"title":"2010_population","count":2,"stream_id":372300,"contributor":{"url":"http://geocommons.com/users/76248","name":"wickymsu"},"data_attributes":null,"calculation_params":null,"icon_link":null,"link":"http://geocommons.com/overlays/372300.json","extent":[-84.5035,42.7238,-84.4648,42.7373],"geometry_types":["point"],"unique_name":null,"name":"2010_population","feature_count":2,"description":"","next_feature":null,"is_raster":false,"short_classification":"Y","stats":{"year":{"max":2010,"variance":0.0,"mean":2010.0,"stdev":0.0,"min":2010,"median":2010},"population/enrollment":{"max":48579,"variance":5648160.5,"mean":46898.5,"stdev":2376.58589156799,"min":45218,"median":48579}},"features":[{"properties":{"city":"MSU","geo_score":1.0,"year":2010,"id":"afbegdp64xj6","address":"East Lansing, MI, 48825","geo_precision":"zip","population/enrollment":45218},"type":"Feature","geometry":{"type":"Point","coordinates":[-84.464775,42.723784]}},{"properties":{"city":"East Lansing","geo_score":1.0,"year":2010,"id":"afbegdlabiq9","address":"East Lansing, MI, 48823","geo_precision":"zip","population/enrollment":48579},"type":"Feature","geometry":{"type":"Point","coordinates":[-84.503527,42.737334]}}],"is_temporal":false,"author":{"url":"","metadata":null,"contact_name":null,"contact_address":null,"source":null,"contact_phone":null},"source":"","pagination":{"sort":null,"start":0,"total":2,"limit":1000000},"state":"complete","tags":"","published":"2014-08-16T16:38:59-04:00","id":372300}