{"type":"FeatureCollection","data_type":"Dataset","url_type":null,"permissions":[{"permissions":{"download":true,"view":true},"group_id":"everyone"}],"classification":null,"title":"test12","count":2,"stream_id":373475,"contributor":{"url":"http://geocommons.com/users/41018","name":"lwieck"},"data_attributes":null,"calculation_params":null,"icon_link":null,"link":"http://geocommons.com/overlays/373475.json","extent":[-122.412,37.7526,-122.411,37.7527],"geometry_types":["point"],"unique_name":null,"name":"test12","feature_count":2,"description":"","next_feature":null,"is_raster":false,"short_classification":"Y","stats":{"gps coordinates":{"max":37.752745,"variance":1.3447999999681e-08,"mean":37.752663,"stdev":0.000115965512113218,"min":37.752581,"median":37.752745},"column_3":{"max":-122.411279,"variance":2.880000000123e-08,"mean":-122.411399,"stdev":0.000169705627488395,"min":-122.411519,"median":-122.411279}},"features":[{"properties":{"name":"El Tecolote","id":"afehibvzwwzw","gps coordinates":37.752745,"column_3":-122.411279},"type":"Feature","geometry":{"type":"Point","coordinates":[-122.411279,37.752745]}},{"properties":{"name":"Precita Eyes","id":"afehibs0ywkl","gps coordinates":37.752581,"column_3":-122.411519},"type":"Feature","geometry":{"type":"Point","coordinates":[-122.411519,37.752581]}}],"is_temporal":false,"author":{"url":"","metadata":"","contact_name":"","contact_address":"","source":"","contact_phone":""},"source":"","pagination":{"sort":null,"start":0,"total":2,"limit":1000000},"state":"complete","tags":"","published":"2014-08-16T18:31:11-04:00","id":373475}