{"type":"FeatureCollection","data_type":"Dataset","url_type":null,"permissions":[{"permissions":{"download":true,"view":true},"group_id":"everyone"}],"classification":null,"title":"cuisine muntapa","count":4,"stream_id":37361,"contributor":{"url":"http://geocommons.com/users/12695","name":"muntapa"},"data_attributes":null,"calculation_params":null,"icon_link":null,"link":"http://geocommons.com/overlays/37361.json","extent":[120.992,14.4589,121.068,14.5499],"geometry_types":["point"],"unique_name":null,"name":"cuisine muntapa","feature_count":4,"description":"","next_feature":null,"is_raster":false,"short_classification":"Y","stats":{"latitude":{"max":14.549897,"mean":14.5121325,"variance":0.00188634069366668,"stdev":0.0434320238265117,"min":14.458914,"median":14.54517},"longitude":{"max":121.06833,"mean":121.0417835,"variance":0.00114105470233337,"stdev":0.0337795012149879,"min":120.992266,"median":121.054416}},"features":[{"properties":{"name":"Sucat Polvoron","latitude":14.458914,"description":"Delicious delicacy","link":null,"longitude":121.052122,"id":"a62qooz204t6"},"type":"Feature","geometry":{"type":"Point","coordinates":[121.052122,14.458914]}},{"properties":{"name":"Dampa","latitude":14.494549,"description":"Fresh seafood market","link":"http://www.flickr.com/photos/tonigirl/170441389/","longitude":120.992266,"id":"a62qoompcc76"},"type":"Feature","geometry":{"type":"Point","coordinates":[120.992266,14.494549]}},{"properties":{"name":"Balot","latitude":14.54517,"description":"Exotic food","link":null,"longitude":121.06833,"id":"a62qook3vs05"},"type":"Feature","geometry":{"type":"Point","coordinates":[121.06833,14.54517]}},{"properties":{"name":"Serendra cuisine","latitude":14.549897,"description":"Pinoy food","link":null,"longitude":121.054416,"id":"a62qoonlk74k"},"type":"Feature","geometry":{"type":"Point","coordinates":[121.054416,14.549897]}}],"is_temporal":false,"author":{"url":"","metadata":"","contact_name":"","contact_address":"","source":"","contact_phone":""},"source":"","pagination":{"sort":null,"start":0,"total":4,"limit":1000000},"state":"complete","tags":"ncca_cultural_mapping_course","published":"2014-08-10T18:05:32-04:00","id":37361}