{"type":"FeatureCollection","data_type":"Dataset","url_type":null,"permissions":[{"permissions":{"download":true,"view":true},"group_id":"everyone"}],"classification":null,"title":"Valençay","count":1,"stream_id":376636,"contributor":{"url":"http://geocommons.com/users/42827","name":"jflacou"},"data_attributes":null,"calculation_params":null,"icon_link":null,"link":"http://geocommons.com/overlays/376636.json","extent":[1.5684,47.1606,1.5684,47.1606],"geometry_types":["point"],"unique_name":null,"name":"Valençay","feature_count":1,"description":"","next_feature":null,"is_raster":false,"short_classification":"Y","stats":{},"features":[{"properties":{"name":"Valençay","Adresse":"36600 Valençay","id":"afoj66xdolbb","GPS":"1.5684 - 47.16063"},"type":"Feature","geometry":{"type":"Point","coordinates":[1.5684,47.16063]}}],"is_temporal":false,"author":{"url":"","metadata":"","contact_name":"","contact_address":"","source":"","contact_phone":""},"source":"","pagination":{"sort":null,"start":0,"total":1,"limit":1000000},"state":"complete","tags":"","published":"2014-08-16T22:42:18-04:00","id":376636}