{"type":"FeatureCollection","data_type":"Dataset","url_type":null,"permissions":[{"permissions":{"download":true,"view":true},"group_id":"everyone"}],"classification":null,"title":"Nacimientos CyL","count":9,"stream_id":37794,"contributor":{"url":"http://geocommons.com/users/12776","name":"cursohelena09"},"data_attributes":null,"calculation_params":null,"icon_link":null,"link":"http://geocommons.com/overlays/37794.json","extent":[-5.74,40.65,-2.46,42.59],"geometry_types":["point"],"unique_name":null,"name":"Nacimientos CyL","feature_count":9,"description":"","next_feature":null,"is_raster":false,"short_classification":"Y","stats":{"longitud":{"max":-2.46,"mean":-4.57555555555556,"variance":1.12947777777778,"stdev":1.06276892021633,"min":-5.74,"median":-4.7},"latitud":{"max":42.59,"mean":41.6,"variance":0.435200000000002,"stdev":0.659696900098827,"min":40.65,"median":41.65},"2000":{"max":723.0,"mean":82.239,"variance":57738.10806625,"stdev":240.287552874155,"min":1.155,"median":2.553},"1999":{"max":615.0,"mean":70.1903333333333,"variance":41740.9131175,"stdev":204.305930206394,"min":1.166,"median":2.458},"2001":{"max":672.0,"mean":76.5452222222222,"variance":49861.9607636944,"stdev":223.297919299967,"min":1.119,"median":2.472}},"features":[{"properties":{"longitud":-4.7,"unidad":"Personas","provincias":"Avila","serie":"Nacimientos","latitud":40.65,"2000":1.16,"1999":1.171,"id":"a68g0mnjuqzu","2001":1.128,"fuente":"Direccion General de Estadistica"},"type":"Feature","geometry":{"type":"Point","coordinates":[-4.7,40.65]}},{"properties":{"longitud":-3.69,"unidad":"Personas","provincias":"Burgos","serie":"Nacimientos","latitud":42.34,"2000":2.779,"1999":2.655,"id":"a68g0mee1ihs","2001":2.671,"fuente":"Direccion General de Estadistica"},"type":"Feature","geometry":{"type":"Point","coordinates":[-3.69,42.34]}},{"properties":{"longitud":-5.57,"unidad":"Personas","provincias":"Leon","serie":"Nacimientos","latitud":42.59,"2000":3.2,"1999":3.155,"id":"a68g0mebn7qr","2001":3.188,"fuente":"Direccion General de Estadistica"},"type":"Feature","geometry":{"type":"Point","coordinates":[-5.57,42.59]}},{"properties":{"longitud":-4.53,"unidad":"Personas","provincias":"Palencia","serie":"Nacimientos","latitud":42.01,"2000":1.155,"1999":1.216,"id":"a68g0mhgs2if","2001":1.165,"fuente":"Direccion General de Estadistica"},"type":"Feature","geometry":{"type":"Point","coordinates":[-4.53,42.01]}},{"properties":{"longitud":-5.66,"unidad":"Personas","provincias":"Salamanca","serie":"Nacimientos","latitud":40.96,"2000":2.553,"1999":2.458,"id":"a68g0mknluht","2001":2.472,"fuente":"Direccion General de Estadistica"},"type":"Feature","geometry":{"type":"Point","coordinates":[-5.66,40.96]}},{"properties":{"longitud":-4.11,"unidad":"Personas","provincias":"Segovia","serie":"Nacimientos","latitud":40.94,"2000":1.194,"1999":1.175,"id":"a68g0mjxsn4y","2001":1.24,"fuente":"Direccion General de Estadistica"},"type":"Feature","geometry":{"type":"Point","coordinates":[-4.11,40.94]}},{"properties":{"longitud":-2.46,"unidad":"Personas","provincias":"Soria","serie":"Nacimientos","latitud":41.76,"2000":723.0,"1999":615.0,"id":"a68g0me6y5oz","2001":672.0,"fuente":"Direccion General de Estadistica"},"type":"Feature","geometry":{"type":"Point","coordinates":[-2.46,41.76]}},{"properties":{"longitud":-4.72,"unidad":"Personas","provincias":"Valladolid","serie":"Nacimientos","latitud":41.65,"2000":3.878,"1999":3.717,"id":"a68g0mkwsl4j","2001":3.924,"fuente":"Direccion General de Estadistica"},"type":"Feature","geometry":{"type":"Point","coordinates":[-4.72,41.65]}},{"properties":{"longitud":-5.74,"unidad":"Personas","provincias":"Zamora","serie":"Nacimientos","latitud":41.5,"2000":1.232,"1999":1.166,"id":"a68g0mp8z9bf","2001":1.119,"fuente":"Direccion General de Estadistica"},"type":"Feature","geometry":{"type":"Point","coordinates":[-5.74,41.5]}}],"is_temporal":false,"author":{"url":"","metadata":"","contact_name":"","contact_address":"","source":"","contact_phone":""},"source":"","pagination":{"sort":null,"start":0,"total":9,"limit":1000000},"state":"complete","tags":"dato,nacimientos","published":"2014-08-10T18:37:46-04:00","id":37794}