{"type":"FeatureCollection","data_type":"Dataset","url_type":null,"permissions":[{"permissions":{"download":true,"view":true},"group_id":"everyone"}],"classification":null,"title":"Eguzon-Chant么me","count":1,"stream_id":380001,"contributor":{"url":"http://geocommons.com/users/42827","name":"jflacou"},"data_attributes":null,"calculation_params":null,"icon_link":null,"link":"http://geocommons.com/overlays/380001.json","extent":[1.58184,46.4424,1.58184,46.4424],"geometry_types":["point"],"unique_name":null,"name":"Eguzon-Chant么me","feature_count":1,"description":"","next_feature":null,"is_raster":false,"short_classification":"Y","stats":{},"features":[{"properties":{"name":"Eguzon-Chant么me","Adresse":"36270 Eguzon-Chant么me","id":"afzl03sszw9s","GPS":"1.58184 - 46.44239"},"type":"Feature","geometry":{"type":"Point","coordinates":[1.58184,46.44239]}}],"is_temporal":false,"author":{"url":"","metadata":"","contact_name":"","contact_address":"","source":"","contact_phone":""},"source":"","pagination":{"sort":null,"start":0,"total":1,"limit":1000000},"state":"complete","tags":"","published":"2014-08-16T13:01:01-04:00","id":380001}