{"type":"FeatureCollection","data_type":"Dataset","url_type":null,"permissions":[{"permissions":{"download":true,"view":true},"group_id":"everyone"}],"classification":null,"title":"Winnipeg Centre","count":1,"stream_id":380230,"contributor":{"url":"http://geocommons.com/users/74787","name":"stevendosanjh"},"data_attributes":null,"calculation_params":null,"icon_link":null,"link":"http://geocommons.com/overlays/380230.json","extent":[-97.1684,49.8522,-97.1684,49.8522],"geometry_types":["point"],"unique_name":null,"name":"Winnipeg Centre","feature_count":1,"description":"","next_feature":null,"is_raster":false,"short_classification":"Y","stats":{"latitude":{"max":49.852215,"min":49.852215,"median":49.852215},"order":{"max":9999,"min":9999,"median":9999},"longitude":{"max":-97.168423,"min":-97.168423,"median":-97.168423},"identifying number":{"max":11041124,"min":11041124,"median":11041124}},"features":[{"properties":{"delete":null,"city":"Winnipeg","category":null,"subcategory":null,"latitude":49.852215,"photo url":null,"title":null,"directions":"FALSE","order":9999,"street1":null,"zipcode":"R3M 3Y8","photo height":null,"freeform address":"Winnipeg, MB, R3M 3Y8, CA","street2":null,"country":"CA","website":null,"description":null,"photo width":null,"neighborhood":null,"photo description":null,"identifying number":11041124,"longitude":-97.168423,"link":"http://www.communitywalk.com/map/1623097#0004Z7UT","id":"afzu4evz7pk4","phone number":null,"state":"MB","photo title":null},"type":"Feature","geometry":{"type":"Point","coordinates":[-97.168423,49.852215]}}],"is_temporal":false,"author":{"url":"","metadata":null,"contact_name":null,"contact_address":null,"source":null,"contact_phone":null},"source":"","pagination":{"sort":null,"start":0,"total":1,"limit":1000000},"state":"complete","tags":"","published":"2014-08-16T13:17:02-04:00","id":380230}