{"type":"FeatureCollection","data_type":"Dataset","url_type":null,"permissions":[{"permissions":{"download":true,"view":true},"group_id":"everyone"}],"classification":null,"title":"Pauvres Martins","count":2,"stream_id":382823,"contributor":{"url":"http://geocommons.com/users/42827","name":"jflacou"},"data_attributes":null,"calculation_params":null,"icon_link":null,"link":"http://geocommons.com/overlays/382823.json","extent":[1.56414,46.5666,1.96058,46.8291],"geometry_types":["point"],"unique_name":null,"name":"Pauvres Martins","feature_count":2,"description":"Darc au Pays 2013.","next_feature":null,"is_raster":false,"short_classification":"Y","stats":{"Date":{"max":"2030/01/16 00:00:00 -0500","variance":3732480000.0,"mean":"2030/01/15 12:00:00 -0500","stdev":61094.0258945177,"min":"2030/01/15 00:00:00 -0500","median":"2030/01/16 00:00:00 -0500"}},"features":[{"properties":{"Fanfare":"Jazz Combo Box","Site":"Niherne","Date":{"end_time":"2030/01/16 00:00:00 -0500","original":"Jeudi 15 août","granularity":"day","time":"2030/01/15 00:00:00 -0500"},"Artiste":"Pauvres Martins","id":"ag6bx7vemkj3","GPS":"1.56414 - 46.82909"},"type":"Feature","geometry":{"type":"Point","coordinates":[1.56414,46.82909]}},{"properties":{"Fanfare":"Jazz Combo Box","Site":"Le Magny","Date":{"end_time":"2030/01/17 00:00:00 -0500","original":"Vendredi 16 août","granularity":"day","time":"2030/01/16 00:00:00 -0500"},"Artiste":"Pauvres Martins","id":"ag6bx7nsmrfu","GPS":"1.96058 - 46.56655"},"type":"Feature","geometry":{"type":"Point","coordinates":[1.96058,46.56655]}}],"is_temporal":true,"author":{"url":"","metadata":"","contact_name":"","contact_address":"","source":"","contact_phone":""},"source":"","pagination":{"sort":null,"start":0,"total":2,"limit":1000000},"state":"complete","tags":"","published":"2014-08-16T16:34:44-04:00","id":382823}