{"type":"FeatureCollection","data_type":"Dataset","url_type":null,"permissions":[{"permissions":{"download":true,"view":true},"group_id":"everyone"}],"classification":null,"title":"Contractor Partial Responses Map Data","count":4,"stream_id":384429,"contributor":{"url":"http://geocommons.com/users/78641","name":"steelj15"},"data_attributes":null,"calculation_params":null,"icon_link":null,"link":"http://geocommons.com/overlays/384429.json","extent":[-86.7866,33.5271,-71.5889,42.3296],"geometry_types":["point"],"unique_name":null,"name":"Contractor Partial Responses Map Data","feature_count":4,"description":"","next_feature":null,"is_raster":false,"short_classification":"Y","stats":{},"features":[{"properties":{"name":"Craig Bozaich","company":"Pro Power Solutions","city":"Norcross","zip":"30093","response":"Yes","geo_score":1.0,"completed/partial":"Partial","id":"agao71kuxnqf","email address":"cbozaich@propowersolutions.com","address":"1785 Corporate Dr.","geo_precision":"range","state":"GA"},"type":"Feature","geometry":{"type":"Point","coordinates":[-84.148233,33.940187]}},{"properties":{"name":"Paul Golden","company":"Electronic Environments Corp.","city":"Marlborough","zip":"01752","response":"Yes","geo_score":1.0,"completed/partial":"Partial","id":"agao71le91m2","email address":"pgolden@eecnet.com","address":"410 Forest Street","geo_precision":"range","state":"MA"},"type":"Feature","geometry":{"type":"Point","coordinates":[-71.588852,42.329614]}},{"properties":{"name":"Ray Deane","company":"Temptrol","city":"Delanco","zip":"08705","response":"Yes","geo_score":0.88,"completed/partial":"Partial","id":"agao71ixh41a","email address":"rdeane@temptrolcorp.com","address":"801 Coppertown Road","geo_precision":"range","state":"NJ"},"type":"Feature","geometry":{"type":"Point","coordinates":[-74.936268,40.047492]}},{"properties":{"name":"Stuart Murray","company":"Miller Air","city":"Birmingham","zip":"35222","response":"Yes","geo_score":0.935,"completed/partial":"Partial","id":"agao71oe0b27","email address":"smurray@millerairconditioning.com","address":"462 35th Street North","geo_precision":"range","state":"AL"},"type":"Feature","geometry":{"type":"Point","coordinates":[-86.786611,33.527098]}}],"is_temporal":false,"author":{"url":"","metadata":"","contact_name":"","contact_address":"","source":"","contact_phone":""},"source":"","pagination":{"sort":null,"start":0,"total":4,"limit":1000000},"state":"complete","tags":"","published":"2014-08-16T18:15:39-04:00","id":384429}