{"type":"FeatureCollection","data_type":"Dataset","url_type":null,"permissions":[{"permissions":{"download":true,"view":true},"group_id":"everyone"}],"classification":null,"title":"Top_5_Call_Volume_by_Zip","count":5,"stream_id":385463,"contributor":{"url":"http://geocommons.com/users/73058","name":"yeimarielopez"},"data_attributes":null,"calculation_params":null,"icon_link":null,"link":"http://geocommons.com/overlays/385463.json","extent":[-83.3731,42.1382,-83.1804,42.3151],"geometry_types":["point"],"unique_name":null,"name":"Top_5_Call_Volume_by_Zip","feature_count":5,"description":"","next_feature":null,"is_raster":false,"short_classification":"Y","stats":{"call volume":{"max":3721,"variance":1545421.7,"mean":1535.2,"stdev":1243.14991050959,"min":746,"median":1198}},"features":[{"properties":{"geo_score":0.714,"zip code":"48180","call volume":3721,"id":"agd7prvgtu4e","geo_precision":"zip"},"type":"Feature","geometry":{"type":"Point","coordinates":[-83.249067,42.245837]}},{"properties":{"geo_score":0.714,"zip code":"48146","call volume":1236,"id":"agd7prw5mddt","geo_precision":"zip"},"type":"Feature","geometry":{"type":"Point","coordinates":[-83.180375,42.242038]}},{"properties":{"geo_score":0.714,"zip code":"48195","call volume":1198,"id":"agd7prpk4xfm","geo_precision":"zip"},"type":"Feature","geometry":{"type":"Point","coordinates":[-83.285939,42.257801]}},{"properties":{"geo_score":0.714,"zip code":"48183","call volume":775,"id":"agd7ps07v0nf","geo_precision":"zip"},"type":"Feature","geometry":{"type":"Point","coordinates":[-83.217937,42.138209]}},{"properties":{"geo_score":0.714,"zip code":"48185","call volume":746,"id":"agd7pry5op5w","geo_precision":"zip"},"type":"Feature","geometry":{"type":"Point","coordinates":[-83.373093,42.31507]}}],"is_temporal":false,"author":{"url":"","metadata":null,"contact_name":null,"contact_address":null,"source":null,"contact_phone":null},"source":"","pagination":{"sort":null,"start":0,"total":5,"limit":1000000},"state":"complete","tags":"","published":"2014-08-16T19:39:21-04:00","id":385463}