{"type":"FeatureCollection","data_type":"Dataset","url_type":null,"permissions":[{"permissions":{"download":true,"view":true},"group_id":"everyone"}],"classification":null,"title":"Musée du Machinisme agricole Prissac","count":1,"stream_id":386172,"contributor":{"url":"http://geocommons.com/users/42827","name":"jflacou"},"data_attributes":null,"calculation_params":null,"icon_link":null,"link":"http://geocommons.com/overlays/386172.json","extent":[1.30308,46.5106,1.30308,46.5106],"geometry_types":["point"],"unique_name":null,"name":"Musée du Machinisme agricole Prissac","feature_count":1,"description":"","next_feature":null,"is_raster":false,"short_classification":"Y","stats":{},"features":[{"properties":{"name":"Musée du Machinisme agricole, du facteur rural, Espace Gutenberg","Telephone":"02 54 25 06 85 ou 02 54 37 22 21","Adresse":"Route de Bélâbre","id":"aggjlkcdcpfj","GPS":"1.30308 - 46.51061"},"type":"Feature","geometry":{"type":"Point","coordinates":[1.30308,46.51061]}}],"is_temporal":false,"author":{"url":"","metadata":"","contact_name":"","contact_address":"","source":"","contact_phone":""},"source":"","pagination":{"sort":null,"start":0,"total":1,"limit":1000000},"state":"complete","tags":"","published":"2014-08-16T20:24:02-04:00","id":386172}