{"type":"FeatureCollection","data_type":"Dataset","url_type":null,"permissions":[{"permissions":{"download":true,"view":true},"group_id":"everyone"}],"classification":null,"title":"Musée de la vallée de la Creuse Eguzon","count":1,"stream_id":386175,"contributor":{"url":"http://geocommons.com/users/42827","name":"jflacou"},"data_attributes":null,"calculation_params":null,"icon_link":null,"link":"http://geocommons.com/overlays/386175.json","extent":[1.58125,46.4422,1.58125,46.4422],"geometry_types":["point"],"unique_name":null,"name":"Musée de la vallée de la Creuse Eguzon","feature_count":1,"description":"","next_feature":null,"is_raster":false,"short_classification":"Y","stats":{},"features":[{"properties":{"name":"Musée de la Vallée de la Creuse","Telephone":"02 54 47 47 75","Adresse":"2 rue de la gare","id":"aggjv002lkw0","GPS":"1.58125 - 46.44222"},"type":"Feature","geometry":{"type":"Point","coordinates":[1.58125,46.44222]}}],"is_temporal":false,"author":{"url":"","metadata":"","contact_name":"","contact_address":"","source":"","contact_phone":""},"source":"","pagination":{"sort":null,"start":0,"total":1,"limit":1000000},"state":"complete","tags":"","published":"2014-08-16T20:24:06-04:00","id":386175}