{"type":"FeatureCollection","data_type":"Dataset","url_type":null,"permissions":[{"permissions":{"download":true,"view":true},"group_id":"everyone"}],"classification":null,"title":"Sarnetki","count":1,"stream_id":391214,"contributor":{"url":"http://geocommons.com/users/81495","name":"pgljrk"},"data_attributes":null,"calculation_params":null,"icon_link":null,"link":"http://geocommons.com/overlays/391214.json","extent":[23.2108,54.0052,23.2108,54.0052],"geometry_types":["point"],"unique_name":null,"name":"Sarnetki","feature_count":1,"description":"","next_feature":null,"is_raster":false,"short_classification":"Y","stats":{"Id":{"max":0,"min":0,"median":0}},"features":[{"properties":{"Id":0,"id":"agxl8se33wbv"},"type":"Feature","geometry":{"type":"Point","coordinates":[23.2108218674745,54.0052347795085]}}],"is_temporal":false,"author":{"url":"","metadata":null,"contact_name":null,"contact_address":null,"source":null,"contact_phone":null},"source":"","pagination":{"sort":null,"start":0,"total":1,"limit":1000000},"state":"complete","tags":"","published":"2014-08-16T14:16:21-04:00","id":391214}