{"type":"FeatureCollection","data_type":"Dataset","url_type":null,"permissions":[{"permissions":{"download":true,"edit":true,"view":true},"group_id":82047},{"permissions":{"download":true,"view":true},"group_id":"everyone"}],"classification":null,"title":"Siquijor Pri K","count":3,"stream_id":393166,"contributor":{"url":"http://geocommons.com/users/80224","name":"marian002"},"data_attributes":null,"calculation_params":null,"icon_link":null,"link":"http://geocommons.com/overlays/393166.json","extent":[123.521,9.12829,123.633,9.24724],"geometry_types":["point"],"unique_name":null,"name":"Siquijor Pri K","feature_count":3,"description":"","next_feature":null,"is_raster":false,"short_classification":"Y","stats":{"latitude":{"max":9.247238,"mean":9.19727033333333,"variance":0.00380791584033328,"stdev":0.0617083125707816,"min":9.128294,"median":9.216279},"school.id":{"max":404648,"mean":404636.666666667,"variance":105.333333333333,"stdev":10.2632028788938,"min":404628,"median":404634},"type0":{"max":0,"mean":0.0,"variance":0.0,"stdev":0.0,"min":0,"median":0},"ref.num":{"max":172,"mean":169.666666666667,"variance":4.33333333333333,"stdev":2.08166599946613,"min":168,"median":169},"totalenr":{"max":46,"mean":38.6666666666667,"variance":56.3333333333333,"stdev":7.50555349946513,"min":31,"median":39},"longitude":{"max":123.632668,"mean":123.581489666667,"variance":0.00317319540833267,"stdev":0.0563311229102764,"min":123.521133,"median":123.590668}},"features":[{"properties":{"latitude":9.128294,"school.id":404628,"ref.num":168,"type":"Private","type0":0,"totalenr":31,"esss":"ES","longitude":123.632668,"curricularclass":"Kinder","id":"ah3envh1ushr","school.name":"Lazi Child Training Center"},"type":"Feature","geometry":{"type":"Point","coordinates":[123.632668,9.128294]}},{"properties":{"latitude":9.216279,"school.id":404634,"ref.num":169,"type":"Private","type0":0,"totalenr":46,"esss":"ES","longitude":123.521133,"curricularclass":"Kinder","id":"ah3envqske44","school.name":"St. Anne Ma'Ana Learning Center"},"type":"Feature","geometry":{"type":"Point","coordinates":[123.521133,9.216279]}},{"properties":{"latitude":9.247238,"school.id":404648,"ref.num":172,"type":"Private","type0":0,"totalenr":39,"esss":"ES","longitude":123.590668,"curricularclass":"Kinder","id":"ah3envi24nol","school.name":"Tanbongco Learning Center, Inc."},"type":"Feature","geometry":{"type":"Point","coordinates":[123.590668,9.247238]}}],"is_temporal":false,"author":{"url":"","metadata":"","contact_name":"","contact_address":"","source":"","contact_phone":""},"source":"","pagination":{"sort":null,"start":0,"total":3,"limit":1000000},"state":"complete","tags":"","published":"2014-08-16T16:14:25-04:00","id":393166}