{"type":"FeatureCollection","data_type":"Dataset","url_type":null,"permissions":[{"permissions":{"download":true,"view":true},"group_id":"everyone"}],"classification":null,"title":"PSC 2013 - Théâtre","count":3,"stream_id":393556,"contributor":{"url":"http://geocommons.com/users/42827","name":"jflacou"},"data_attributes":null,"calculation_params":null,"icon_link":null,"link":"http://geocommons.com/overlays/393556.json","extent":[1.69103,46.5814,1.99805,46.9409],"geometry_types":["point"],"unique_name":null,"name":"PSC 2013 - Théâtre","feature_count":3,"description":"","next_feature":null,"is_raster":false,"short_classification":"Y","stats":{},"features":[{"properties":{"Ville":"Châteauroux","Site":"Equinoxe - Scène Nationale","id":"ah49ycwr79gj"},"type":"Feature","geometry":{"type":"Point","coordinates":[1.69103,46.80925]}},{"properties":{"Ville":"Issoudun","Site":"Centre Culturel Albert Camus","id":"ah49ycucknb6"},"type":"Feature","geometry":{"type":"Point","coordinates":[1.99805,46.94089]}},{"properties":{"Ville":"La Châtre","Site":"Théâtre Maurice Sand","id":"ah49ycypn5ms"},"type":"Feature","geometry":{"type":"Point","coordinates":[1.98527778,46.58138889]}}],"is_temporal":false,"author":{"url":"","metadata":"","contact_name":"","contact_address":"","source":"","contact_phone":""},"source":"","pagination":{"sort":null,"start":0,"total":3,"limit":1000000},"state":"complete","tags":"","published":"2014-08-16T17:01:07-04:00","id":393556}