{"type":"FeatureCollection","data_type":"Dataset","url_type":null,"permissions":[{"permissions":{"download":true,"view":true},"group_id":"everyone"}],"classification":null,"title":"Vivosmuertos2","count":8,"stream_id":394388,"contributor":{"url":"http://geocommons.com/users/81507","name":"fdanielguerra"},"data_attributes":null,"calculation_params":null,"icon_link":null,"link":"http://geocommons.com/overlays/394388.json","extent":[-73.93,-42.55,-73.4,-41.84],"geometry_types":["point"],"unique_name":null,"name":"Vivosmuertos2","feature_count":8,"description":"","next_feature":null,"is_raster":false,"short_classification":"Y","stats":{"vivos":{"max":1563,"variance":475357.928571429,"mean":545.25,"stdev":689.462057383456,"min":8,"median":142},"muertos":{"max":262,"variance":8063.07142857143,"mean":41.75,"stdev":89.7946069013692,"min":0,"median":22},"lat":{"max":-41.84,"variance":0.103457142857142,"mean":-42.19,"stdev":0.321647544459991,"min":-42.55,"median":-42.15},"long":{"max":-73.4,"variance":0.0385410714285706,"mean":-73.67625,"stdev":0.196318800496974,"min":-73.93,"median":-73.64}},"features":[{"properties":{"vivos":14,"muertos":23,"id":"ah73ywycuj3m","lat":-41.87,"long":-73.85},"type":"Feature","geometry":{"type":"Point","coordinates":[-73.85,-41.87]}},{"properties":{"vivos":37,"muertos":22,"id":"ah73yx6eumcd","lat":-41.84,"long":-73.86},"type":"Feature","geometry":{"type":"Point","coordinates":[-73.86,-41.84]}},{"properties":{"vivos":64,"muertos":0,"id":"ah73yx4rjx3b","lat":-41.85,"long":-73.93},"type":"Feature","geometry":{"type":"Point","coordinates":[-73.93,-41.85]}},{"properties":{"vivos":142,"muertos":0,"id":"ah73ywzac2at","lat":-42.15,"long":-73.43},"type":"Feature","geometry":{"type":"Point","coordinates":[-73.43,-42.15]}},{"properties":{"vivos":8,"muertos":0,"id":"ah73yx20bpph","lat":-42.17,"long":-73.4},"type":"Feature","geometry":{"type":"Point","coordinates":[-73.4,-42.17]}},{"properties":{"vivos":1563,"muertos":262,"id":"ah73yx2hbhpq","lat":-42.55,"long":-73.68},"type":"Feature","geometry":{"type":"Point","coordinates":[-73.68,-42.55]}},{"properties":{"vivos":1382,"muertos":0,"id":"ah73yxb8z0f5","lat":-42.55,"long":-73.64},"type":"Feature","geometry":{"type":"Point","coordinates":[-73.64,-42.55]}},{"properties":{"vivos":1152,"muertos":27,"id":"ah73yxc5e207","lat":-42.54,"long":-73.62},"type":"Feature","geometry":{"type":"Point","coordinates":[-73.62,-42.54]}}],"is_temporal":false,"author":{"url":"","metadata":"","contact_name":"","contact_address":"","source":"","contact_phone":""},"source":"","pagination":{"sort":null,"start":0,"total":8,"limit":1000000},"state":"complete","tags":"comparation","published":"2014-08-16T17:55:49-04:00","id":394388}