{"type":"FeatureCollection","data_type":"Dataset","url_type":null,"permissions":[{"permissions":{"download":true,"view":true},"group_id":"everyone"}],"classification":null,"title":"Radio Balistiq","count":1,"stream_id":394673,"contributor":{"url":"http://geocommons.com/users/42827","name":"jflacou"},"data_attributes":null,"calculation_params":null,"icon_link":null,"link":"http://geocommons.com/overlays/394673.json","extent":[1.715,46.8122,1.715,46.8122],"geometry_types":["point"],"unique_name":null,"name":"Radio Balistiq","feature_count":1,"description":"","next_feature":null,"is_raster":false,"short_classification":"Y","stats":{},"features":[{"properties":{"name":"93 rue Ampère","Adresse":"36000 Châteauroux","id":"ah9b6zeo60u0","GPS":"1.715 - 46.81222"},"type":"Feature","geometry":{"type":"Point","coordinates":[1.715,46.81222]}}],"is_temporal":false,"author":{"url":"","metadata":"","contact_name":"","contact_address":"","source":"","contact_phone":""},"source":"","pagination":{"sort":null,"start":0,"total":1,"limit":1000000},"state":"complete","tags":"","published":"2014-08-16T18:16:50-04:00","id":394673}