{"type":"FeatureCollection","data_type":"Dataset","url_type":null,"permissions":[{"permissions":{"download":true,"view":true},"group_id":"everyone"}],"classification":null,"title":"Ponto_50_-_Condutora_bate_na_cerca_-_30-01-2011","count":1,"stream_id":394953,"contributor":{"url":"http://geocommons.com/users/62483","name":"caaete"},"data_attributes":null,"calculation_params":null,"icon_link":null,"link":"http://geocommons.com/overlays/394953.json","extent":[-54.5748,-25.443,-54.5748,-25.443],"geometry_types":["point"],"unique_name":null,"name":"Ponto_50_-_Condutora_bate_na_cerca_-_30-01-2011","feature_count":1,"description":"","next_feature":null,"is_raster":false,"short_classification":"Y","stats":{},"features":[{"properties":{"name":"Ponto 50 - Condutora bate na cerca - 30-01-2011","description":"30-JAN-11 4:48:29PM","id":"ahabsfx3k240"},"type":"Feature","geometry":{"type":"Point","coordinates":[-54.574762,-25.443005]}}],"is_temporal":false,"author":{"url":"","metadata":null,"contact_name":null,"contact_address":null,"source":null,"contact_phone":null},"source":"","pagination":{"sort":null,"start":0,"total":1,"limit":1000000},"state":"complete","tags":"","published":"2014-08-16T18:45:40-04:00","id":394953}