{"type":"FeatureCollection","data_type":"Dataset","url_type":null,"permissions":[{"permissions":{"download":true,"view":true},"group_id":"everyone"}],"classification":null,"title":"BO_SEOE","count":1,"stream_id":394949,"contributor":{"url":"http://geocommons.com/users/62483","name":"caaete"},"data_attributes":null,"calculation_params":null,"icon_link":null,"link":"http://geocommons.com/overlays/394949.json","extent":[-54.5221,-25.4315,-54.5221,-25.4315],"geometry_types":["point"],"unique_name":null,"name":"BO_SEOE","feature_count":1,"description":"","next_feature":null,"is_raster":false,"short_classification":"Y","stats":{},"features":[{"properties":{"name":"Ponto 39 - Três pescadores no Lago do Jacaré - 10-10-10","description":"10-OUT-10 17:32:43","id":"ahabs7qghajl"},"type":"Feature","geometry":{"type":"Point","coordinates":[-54.522062,-25.431489]}}],"is_temporal":false,"author":{"url":"","metadata":null,"contact_name":null,"contact_address":null,"source":null,"contact_phone":null},"source":"","pagination":{"sort":null,"start":0,"total":1,"limit":1000000},"state":"complete","tags":"","published":"2014-08-16T18:44:49-04:00","id":394949}