{"type":"FeatureCollection","data_type":"Dataset","url_type":null,"permissions":[{"permissions":{"download":true,"view":true},"group_id":"everyone"}],"classification":null,"title":"Cabulihan_Integrated_School_G8","count":4,"stream_id":395730,"contributor":{"url":"http://geocommons.com/users/81761","name":"Nonnie123"},"data_attributes":null,"calculation_params":null,"icon_link":null,"link":"http://geocommons.com/overlays/395730.json","extent":[123.594,9.25339,123.624,9.29316],"geometry_types":["point"],"unique_name":null,"name":"Cabulihan_Integrated_School_G8","feature_count":4,"description":"","next_feature":null,"is_raster":false,"short_classification":"Y","stats":{"typesch0":{"max":1,"variance":0.0,"mean":1.0,"stdev":0.0,"min":1,"median":1},"sch.id":{"max":120664,"variance":12.6666666666667,"mean":120659.0,"stdev":3.55902608401044,"min":120656,"median":120659},"enr":{"max":13,"variance":33.0,"mean":4.5,"stdev":5.74456264653803,"min":1,"median":3},"lat":{"max":9.293156,"variance":0.000287588630249986,"mean":9.27380075,"stdev":0.0169584383199039,"min":9.253386,"median":9.280281},"long":{"max":123.62426,"variance":0.000171059523666673,"mean":123.6097965,"stdev":0.0130789725768759,"min":123.593742,"median":123.615334}},"features":[{"properties":{"typesch0":1,"typesch":"Public","sch. name":"Bitaug ES","sch.id":120656,"id":"ahbwam4f619u","lat":9.293156,"enr":1,"long":123.62426},"type":"Feature","geometry":{"type":"Point","coordinates":[123.62426,9.293156]}},{"properties":{"typesch0":1,"typesch":"Public","sch. name":"Cabulihan Integrated School","sch.id":120657,"id":"ahbwam5hl0bx","lat":9.280281,"enr":13,"long":123.60585},"type":"Feature","geometry":{"type":"Point","coordinates":[123.60585,9.280281]}},{"properties":{"typesch0":1,"typesch":"Public","sch. name":"Larena Central ES","sch.id":120659,"id":"ahbwalyy0eai","lat":9.253386,"enr":3,"long":123.593742},"type":"Feature","geometry":{"type":"Point","coordinates":[123.593742,9.253386]}},{"properties":{"typesch0":1,"typesch":"Public","sch. name":"Ponong ES","sch.id":120664,"id":"ahbwam5o9jyp","lat":9.26838,"enr":1,"long":123.615334},"type":"Feature","geometry":{"type":"Point","coordinates":[123.615334,9.26838]}}],"is_temporal":false,"author":{"url":"","metadata":null,"contact_name":null,"contact_address":null,"source":null,"contact_phone":null},"source":"","pagination":{"sort":null,"start":0,"total":4,"limit":1000000},"state":"complete","tags":"","published":"2014-08-16T19:40:38-04:00","id":395730}