{"type":"FeatureCollection","data_type":"Dataset","url_type":null,"permissions":[{"permissions":{"download":true,"view":true},"group_id":"everyone"}],"classification":null,"title":"RMagents","count":3,"stream_id":397580,"contributor":{"url":"http://geocommons.com/users/83133","name":"eric3d"},"data_attributes":null,"calculation_params":null,"icon_link":null,"link":"http://geocommons.com/overlays/397580.json","extent":[-104.86,39.6652,-89.0356,42.1077],"geometry_types":["point"],"unique_name":null,"name":"RMagents","feature_count":3,"description":"Reverse Mortgage Agents","next_feature":null,"is_raster":false,"short_classification":"Y","stats":{},"features":[{"properties":{"company":"Security 1 Lending","name":"Larry McAnarney","cell":"815-703-4745","geo_score":1.0,"phone":"815-654-7100","id":"ahgojj06l3h1","address":"15473 E Eddy Rd, Monroe Center, IL 61052","geo_precision":"range","email":"lmcanarney@gmail.com"},"type":"Feature","geometry":{"type":"Point","coordinates":[-89.03559,42.107745]}},{"properties":{"company":"Alliance Guaranty Mortgage Corp","name":"Doug Jensen","cell":"303-549-8809","geo_score":0.761,"phone":"303-785-2800","id":"ahgojjbor0gw","address":"2821 S Parker Rd, Ste. 455, Aurora, CO 80014","geo_precision":"range","email":"djensen@allianceguaranty.com"},"type":"Feature","geometry":{"type":"Point","coordinates":[-104.859865,39.665249]}},{"properties":{"company":"Capital Mortgage of Iowa","name":"Scott Holliday","cell":"515-238-1260","geo_score":0.707,"phone":"515-555-1234","id":"ahgojj8fice0","address":"5500 Westown Parkway, #140, West Des Moines, IA 50266","geo_precision":"range","email":"sholliday@capmortgage.net"},"type":"Feature","geometry":{"type":"Point","coordinates":[-93.77798,41.595397]}}],"is_temporal":false,"author":{"url":"","metadata":"","contact_name":"","contact_address":"","source":"","contact_phone":""},"source":"","pagination":{"sort":null,"start":0,"total":3,"limit":1000000},"state":"complete","tags":"a,add,below,click,it,tag,to","published":"2013-01-01T17:00:00Z","id":397580}