{"type":"FeatureCollection","data_type":"Dataset","url_type":null,"permissions":[{"permissions":{"download":true,"view":true},"group_id":"everyone"}],"classification":null,"title":"DC_Facilities","count":5,"stream_id":397622,"contributor":{"url":"http://geocommons.com/users/83126","name":"rapsessions"},"data_attributes":null,"calculation_params":null,"icon_link":null,"link":"http://geocommons.com/overlays/397622.json","extent":[-77.2902,38.8049,-77.0394,38.9844],"geometry_types":["point"],"unique_name":null,"name":"DC_Facilities","feature_count":5,"description":"","next_feature":null,"is_raster":false,"short_classification":"Y","stats":{},"features":[{"properties":{"7255-a hanover parkway":"900 17th Street NW","md":"DC","geo_score":0.941,"greenbelt":"Washington","20770":"20006","id":"ahgpamqef9k5","omr":"OMR","geo_precision":"range"},"type":"Feature","geometry":{"type":"Point","coordinates":[-77.039446,38.902522]}},{"properties":{"7255-a hanover parkway":"7475 Wisconsin Ave","md":"MD","geo_score":1.0,"greenbelt":"Bethesda","20770":"20814","id":"ahgpamye0qie","omr":"Shugoll","geo_precision":"range"},"type":"Feature","geometry":{"type":"Point","coordinates":[-77.094081,38.984421]}},{"properties":{"7255-a hanover parkway":"9990 Lee Highway","md":"VA","geo_score":1.0,"greenbelt":"Fairfax","20770":"22030","id":"ahgpamziy85k","omr":"Metro Research","geo_precision":"range"},"type":"Feature","geometry":{"type":"Point","coordinates":[-77.290202,38.862877]}},{"properties":{"7255-a hanover parkway":"1800 Diagonal Road","md":"VA","geo_score":1.0,"greenbelt":"Alexandria","20770":"22314","id":"ahgpan3ydiq4","omr":"Metro Research","geo_precision":"range"},"type":"Feature","geometry":{"type":"Point","coordinates":[-77.063702,38.804884]}},{"properties":{"7255-a hanover parkway":"1199 N Fairfax","md":"VA","geo_score":0.585,"greenbelt":"Alexandria","20770":"22314","id":"ahgpamuxxgc9","omr":"Martin","geo_precision":"zip"},"type":"Feature","geometry":{"type":"Point","coordinates":[-77.063587,38.811436]}}],"is_temporal":false,"author":{"url":"","metadata":"","contact_name":"","contact_address":"","source":"","contact_phone":""},"source":"","pagination":{"sort":null,"start":0,"total":5,"limit":1000000},"state":"complete","tags":"","published":"2014-08-16T22:06:05-04:00","id":397622}