{"type":"FeatureCollection","data_type":"Dataset","url_type":null,"permissions":[{"permissions":{"download":true,"view":true},"group_id":"everyone"}],"classification":null,"title":"Villedieu sur Indre","count":1,"stream_id":398088,"contributor":{"url":"http://geocommons.com/users/42827","name":"jflacou"},"data_attributes":null,"calculation_params":null,"icon_link":null,"link":"http://geocommons.com/overlays/398088.json","extent":[1.53749,46.8474,1.53749,46.8474],"geometry_types":["point"],"unique_name":null,"name":"Villedieu sur Indre","feature_count":1,"description":"","next_feature":null,"is_raster":false,"short_classification":"Y","stats":{},"features":[{"properties":{"name":"Villedieu","Adresse":"36320 Villedieu sur Indre","id":"ahhzzl4jdy7j","GPS":"1.53749 - 46.84737"},"type":"Feature","geometry":{"type":"Point","coordinates":[1.53749,46.84737]}}],"is_temporal":false,"author":{"url":"","metadata":"","contact_name":"","contact_address":"","source":"","contact_phone":""},"source":"","pagination":{"sort":null,"start":0,"total":1,"limit":1000000},"state":"complete","tags":"","published":"2014-08-16T22:46:19-04:00","id":398088}