{"type":"FeatureCollection","data_type":"Dataset","url_type":null,"permissions":[{"permissions":{"download":true,"view":true},"group_id":"everyone"}],"classification":null,"title":"Region8-BoronganCity_1","count":1,"stream_id":398759,"contributor":{"url":"http://geocommons.com/users/80412","name":"Jun Payod"},"data_attributes":null,"calculation_params":null,"icon_link":null,"link":"http://geocommons.com/overlays/398759.json","extent":[125.436,11.6095,125.436,11.6095],"geometry_types":["point"],"unique_name":null,"name":"Region8-BoronganCity_1","feature_count":1,"description":"","next_feature":null,"is_raster":false,"short_classification":"Y","stats":{},"features":[{"properties":{"name":"Borongan City","description":"","id":"ahkc4dqssdwi"},"type":"Feature","geometry":{"type":"Point","coordinates":[125.436058,11.60953]}}],"is_temporal":false,"author":{"url":"","metadata":null,"contact_name":null,"contact_address":null,"source":null,"contact_phone":null},"source":"","pagination":{"sort":null,"start":0,"total":1,"limit":1000000},"state":"complete","tags":"","published":"2014-08-16T23:43:10-04:00","id":398759}