{"type":"FeatureCollection","data_type":"Dataset","url_type":null,"permissions":[{"permissions":{"download":true,"view":true},"group_id":"everyone"}],"classification":null,"title":"Bordaduría","count":1,"stream_id":399093,"contributor":{"url":"http://geocommons.com/users/69936","name":"eliaszr"},"data_attributes":null,"calculation_params":null,"icon_link":null,"link":"http://geocommons.com/overlays/399093.json","extent":[-71.5495,-16.3515,-71.5495,-16.3515],"geometry_types":["point"],"unique_name":null,"name":"Bordaduría","feature_count":1,"description":"","next_feature":null,"is_raster":false,"short_classification":"Y","stats":{"ruc":{"max":0,"min":0,"median":0},"establecimentos pblicos civiles":{"max":1,"min":1,"median":1},"manzana censal":{"max":4,"min":4,"median":4},"establecimientos principales":{"max":0,"min":0,"median":0},"formalidad":{"max":2,"min":2,"median":2},"numero de trabajadores mujeres":{"max":1,"min":1,"median":1},"lote":{"max":2,"min":2,"median":2},"establecimientos nicos":{"max":6,"min":6,"median":6},"niveles de venta mensuales":{"max":2,"min":2,"median":2},"permanencia del negocio":{"max":2,"min":2,"median":2},"piso":{"max":1,"min":1,"median":1},"numero frente":{"max":4,"min":4,"median":4},"zona censal":{"max":12,"min":12,"median":12},"estasblecimientos sucursales":{"max":0,"min":0,"median":0},"tamao de la empresa":{"max":1,"min":1,"median":1},"nivel educativo del empleador":{"max":4,"min":4,"median":4},"longitud":{"max":-71.549492,"min":-71.549492,"median":-71.549492},"total de establecimientos":{"max":7,"min":7,"median":7},"establecimientos de unidad auxiliar":{"max":0,"min":0,"median":0},"estructura demogrfica":{"max":3,"min":3,"median":3},"sexo del empleador":{"max":1,"min":1,"median":1},"telfono":{"max":975767521,"min":975767521,"median":975767521},"zonificacin":{"max":3,"min":3,"median":3},"categoria de ncleo urbano":{"max":2,"min":2,"median":2},"latitud":{"max":-16.351456,"min":-16.351456,"median":-16.351456},"numero de orden":{"max":5,"min":5,"median":5},"mercados":{"max":0,"min":0,"median":0},"total de empleados":{"max":2,"min":2,"median":2},"contabilidad":{"max":1,"min":1,"median":1},"edad del empleador":{"max":50,"min":50,"median":50},"numero de trabajadores hombres":{"max":1,"min":1,"median":1},"rama de actividad":{"max":4,"min":4,"median":4},"codigo de actividad":{"max":171207,"min":171207,"median":171207},"capacitacin Empresarial":{"max":6,"min":6,"median":6}},"features":[{"properties":{"actividad":"BORDADURIA","ruc":0,"fuente de financiamiento":"Prestamo Caja Municipal","manzana censal":4,"establecimentos pblicos civiles":1,"distrito":"Cayma","lote":2,"numero interior":null,"km":null,"numero de trabajadores mujeres":1,"formalidad":2,"establecimientos principales":0,"zona censal":12,"numero frente":4,"piso":1,"razon social o nombre del propietario":"DAVID CAYO HUAYAPA","permanencia del negocio":2,"niveles de venta mensuales":2,"establecimientos nicos":6,"longitud":-71.549492,"nivel educativo del empleador":4,"tamao de la empresa":1,"acceso telefonico":"SI","estasblecimientos sucursales":0,"zonificacin":3,"telfono":975767521,"sexo del empleador":1,"region de destino de mercaderia":"Cayma","estructura demogrfica":3,"establecimientos de unidad auxiliar":0,"total de establecimientos":7,"ciudad":"Arequipa","latitud":-16.351456,"nucleo urbano":"JOSE CARLOS MARIATEGUI","local respecto vivienda":"Dentro de su Vivienda en un Area de uso Exclusivo","manzana nueva":"NO","categoria de ncleo urbano":2,"descripcin de actividad":"CONFECCION Y BORDADO DE TRAJES TIPICOS","tipo de establecimiento":"Taller de Tejido y Costura","registro":"4C","numero de orden":5,"departamento":"Arequipa","numero de puerta":null,"pais de destino de mercaderia":"Perú","id":"ahlh8c678jwc","codigo de actividad":171207,"manzana":"I","rama de actividad":4,"numero de trabajadores hombres":1,"edad del empleador":50,"negocio a puerta cerrada":"Abierta","empresa de destino de mercaderia":"PUBLICO","contabilidad":1,"total de empleados":2,"mercados":0,"categora":"Único","antigedad del negocio":"0-2 años","capacitacin Empresarial":6,"ubigeo":"Cayma"},"type":"Feature","geometry":{"type":"Point","coordinates":[-71.549492,-16.351456]}}],"is_temporal":false,"author":{"url":"","metadata":"","contact_name":"","contact_address":"","source":"","contact_phone":""},"source":"","pagination":{"sort":null,"start":0,"total":1,"limit":1000000},"state":"complete","tags":"","published":"2014-08-17T00:04:07-04:00","id":399093}