{"type":"FeatureCollection","data_type":"Dataset","url_type":null,"permissions":[{"permissions":{"download":true,"view":true},"group_id":"everyone"}],"classification":null,"title":"Venta al por Mayor de Papel y Cartón","count":1,"stream_id":399197,"contributor":{"url":"http://geocommons.com/users/69936","name":"eliaszr"},"data_attributes":null,"calculation_params":null,"icon_link":null,"link":"http://geocommons.com/overlays/399197.json","extent":[-71.5445,-16.3648,-71.5445,-16.3648],"geometry_types":["point"],"unique_name":null,"name":"Venta al por Mayor de Papel y Cartón","feature_count":1,"description":"","next_feature":null,"is_raster":false,"short_classification":"Y","stats":{"ruc":{"max":10393291379,"min":10393291379,"median":10393291379},"establecimentos pblicos civiles":{"max":0,"min":0,"median":0},"manzana censal":{"max":40,"min":40,"median":40},"establecimientos principales":{"max":0,"min":0,"median":0},"formalidad":{"max":1,"min":1,"median":1},"numero de trabajadores mujeres":{"max":0,"min":0,"median":0},"establecimientos nicos":{"max":4,"min":4,"median":4},"niveles de venta mensuales":{"max":2,"min":2,"median":2},"permanencia del negocio":{"max":2,"min":2,"median":2},"piso":{"max":1,"min":1,"median":1},"numero frente":{"max":4,"min":4,"median":4},"zona censal":{"max":18,"min":18,"median":18},"estasblecimientos sucursales":{"max":0,"min":0,"median":0},"tamao de la empresa":{"max":1,"min":1,"median":1},"nivel educativo del empleador":{"max":2,"min":2,"median":2},"longitud":{"max":-71.544528,"min":-71.544528,"median":-71.544528},"total de establecimientos":{"max":4,"min":4,"median":4},"establecimientos de unidad auxiliar":{"max":0,"min":0,"median":0},"estructura demogrfica":{"max":2,"min":2,"median":2},"sexo del empleador":{"max":1,"min":1,"median":1},"telfono":{"max":0,"min":0,"median":0},"zonificacin":{"max":2,"min":2,"median":2},"categoria de ncleo urbano":{"max":2,"min":2,"median":2},"latitud":{"max":-16.364758,"min":-16.364758,"median":-16.364758},"numero de puerta":{"max":642,"min":642,"median":642},"numero de orden":{"max":3,"min":3,"median":3},"mercados":{"max":0,"min":0,"median":0},"total de empleados":{"max":2,"min":2,"median":2},"contabilidad":{"max":1,"min":1,"median":1},"edad del empleador":{"max":30,"min":30,"median":30},"numero de trabajadores hombres":{"max":2,"min":2,"median":2},"rama de actividad":{"max":7,"min":7,"median":7},"codigo de actividad":{"max":513915,"min":513915,"median":513915},"capacitacin Empresarial":{"max":6,"min":6,"median":6}},"features":[{"properties":{"actividad":"VENTA AL POR MAYOR DE PAPEL Y CARTON","ruc":10393291379,"fuente de financiamiento":"Propio","manzana censal":40,"establecimentos pblicos civiles":0,"distrito":"Cayma","lote":null,"numero interior":null,"km":null,"numero de trabajadores mujeres":0,"formalidad":1,"establecimientos principales":0,"zona censal":18,"numero frente":4,"piso":1,"razon social o nombre del propietario":"WILBER DEMETRIO SOTO CUELA","permanencia del negocio":2,"niveles de venta mensuales":2,"establecimientos nicos":4,"longitud":-71.544528,"nivel educativo del empleador":2,"tamao de la empresa":1,"acceso telefonico":"NO","estasblecimientos sucursales":0,"zonificacin":2,"telfono":0,"sexo del empleador":1,"region de destino de mercaderia":"Cayma","estructura demogrfica":2,"establecimientos de unidad auxiliar":0,"total de establecimientos":4,"ciudad":"Arequipa","latitud":-16.364758,"nucleo urbano":"LA TOMILLA","local respecto vivienda":"Independiente de su Vivienda","manzana nueva":"NO","categoria de ncleo urbano":2,"descripcin de actividad":"COMPRA Y VENTA DE CAJAS DE CARTON","tipo de establecimiento":"Deposito/Almacen","registro":"646A","numero de orden":3,"departamento":"Arequipa","numero de puerta":642,"pais de destino de mercaderia":"Perú","id":"ahlhgf7f2mk8","codigo de actividad":513915,"manzana":null,"rama de actividad":7,"numero de trabajadores hombres":2,"edad del empleador":30,"negocio a puerta cerrada":"Abierta","empresa de destino de mercaderia":"PUBLICO","contabilidad":1,"total de empleados":2,"mercados":0,"categora":"Único","antigedad del negocio":"0-2 años","capacitacin Empresarial":6,"ubigeo":"Cayma"},"type":"Feature","geometry":{"type":"Point","coordinates":[-71.544528,-16.364758]}}],"is_temporal":false,"author":{"url":"","metadata":"","contact_name":"","contact_address":"","source":"","contact_phone":""},"source":"","pagination":{"sort":null,"start":0,"total":1,"limit":1000000},"state":"complete","tags":"","published":"2014-08-17T00:07:02-04:00","id":399197}