{"type":"FeatureCollection","data_type":"Dataset","url_type":null,"permissions":[{"permissions":{"download":true,"view":true},"group_id":"everyone"}],"classification":null,"title":"Fabrica de Lejias y Otras Sustancias Quimicas","count":1,"stream_id":399136,"contributor":{"url":"http://geocommons.com/users/69936","name":"eliaszr"},"data_attributes":null,"calculation_params":null,"icon_link":null,"link":"http://geocommons.com/overlays/399136.json","extent":[-71.545,-16.3737,-71.545,-16.3737],"geometry_types":["point"],"unique_name":null,"name":"Fabrica de Lejias y Otras Sustancias Quimicas","feature_count":1,"description":"","next_feature":null,"is_raster":false,"short_classification":"Y","stats":{"ruc":{"max":20497261555,"min":20497261555,"median":20497261555},"establecimentos pblicos civiles":{"max":0,"min":0,"median":0},"manzana censal":{"max":20,"min":20,"median":20},"establecimientos principales":{"max":0,"min":0,"median":0},"formalidad":{"max":1,"min":1,"median":1},"numero de trabajadores mujeres":{"max":0,"min":0,"median":0},"establecimientos nicos":{"max":3,"min":3,"median":3},"niveles de venta mensuales":{"max":4,"min":4,"median":4},"permanencia del negocio":{"max":2,"min":2,"median":2},"piso":{"max":1,"min":1,"median":1},"numero frente":{"max":4,"min":4,"median":4},"zona censal":{"max":15,"min":15,"median":15},"estasblecimientos sucursales":{"max":0,"min":0,"median":0},"tamao de la empresa":{"max":1,"min":1,"median":1},"nivel educativo del empleador":{"max":4,"min":4,"median":4},"longitud":{"max":-71.544983,"min":-71.544983,"median":-71.544983},"total de establecimientos":{"max":3,"min":3,"median":3},"establecimientos de unidad auxiliar":{"max":0,"min":0,"median":0},"estructura demogrfica":{"max":3,"min":3,"median":3},"sexo del empleador":{"max":1,"min":1,"median":1},"telfono":{"max":286574,"min":286574,"median":286574},"zonificacin":{"max":4,"min":4,"median":4},"categoria de ncleo urbano":{"max":12,"min":12,"median":12},"latitud":{"max":-16.373708,"min":-16.373708,"median":-16.373708},"numero de puerta":{"max":930,"min":930,"median":930},"numero de orden":{"max":3,"min":3,"median":3},"mercados":{"max":0,"min":0,"median":0},"total de empleados":{"max":2,"min":2,"median":2},"contabilidad":{"max":4,"min":4,"median":4},"edad del empleador":{"max":53,"min":53,"median":53},"numero de trabajadores hombres":{"max":2,"min":2,"median":2},"rama de actividad":{"max":4,"min":4,"median":4},"codigo de actividad":{"max":241115,"min":241115,"median":241115},"capacitacin Empresarial":{"max":6,"min":6,"median":6}},"features":[{"properties":{"fuente de financiamiento":"Prestamo Banco","ruc":20497261555,"actividad":"FABRICA DE LEJIAS Y OTRAS SUSTANCIAS QUIMICAS N.C.P.","establecimentos pblicos civiles":0,"manzana censal":20,"establecimientos principales":0,"formalidad":1,"numero de trabajadores mujeres":0,"km":null,"numero interior":null,"lote":null,"distrito":"Cayma","establecimientos nicos":3,"niveles de venta mensuales":4,"permanencia del negocio":2,"razon social o nombre del propietario":"DELTA QUIMICA  SRL","piso":1,"numero frente":4,"zona censal":15,"estasblecimientos sucursales":0,"acceso telefonico":"SI","tamao de la empresa":1,"nivel educativo del empleador":4,"longitud":-71.544983,"total de establecimientos":3,"establecimientos de unidad auxiliar":0,"estructura demogrfica":3,"region de destino de mercaderia":"Cayma","sexo del empleador":1,"telfono":286574,"zonificacin":4,"ciudad":"Arequipa","categoria de ncleo urbano":12,"manzana nueva":"NO","local respecto vivienda":"Dentro de su Vivienda en un Area de uso Exclusivo","nucleo urbano":"VILLA EL MIRADOR","latitud":-16.373708,"pais de destino de mercaderia":"Perú","numero de puerta":930,"departamento":"Arequipa","numero de orden":3,"registro":"20A","tipo de establecimiento":"Deposito/Almacen","descripcin de actividad":"DEPOSITO DE INSUMOS QUIMICOS","id":"ahlhc16x52lm","mercados":0,"total de empleados":2,"contabilidad":4,"empresa de destino de mercaderia":"PUBLICO","negocio a puerta cerrada":"Cerrada","edad del empleador":53,"numero de trabajadores hombres":2,"rama de actividad":4,"manzana":null,"codigo de actividad":241115,"ubigeo":"Cayma","capacitacin Empresarial":6,"antigedad del negocio":"6-9 años","categora":"Único"},"type":"Feature","geometry":{"type":"Point","coordinates":[-71.544983,-16.373708]}}],"is_temporal":false,"author":{"url":"","metadata":"","contact_name":"","contact_address":"","source":"","contact_phone":""},"source":"","pagination":{"sort":null,"start":0,"total":1,"limit":1000000},"state":"complete","tags":"","published":"2014-08-17T00:05:47-04:00","id":399136}