{"type":"FeatureCollection","data_type":"Dataset","url_type":null,"permissions":[{"permissions":{"download":true,"view":true},"group_id":"everyone"}],"classification":null,"title":"Servicio de Lavado de Vehiculos","count":1,"stream_id":399180,"contributor":{"url":"http://geocommons.com/users/69936","name":"eliaszr"},"data_attributes":null,"calculation_params":null,"icon_link":null,"link":"http://geocommons.com/overlays/399180.json","extent":[-71.5438,-16.3599,-71.5438,-16.3599],"geometry_types":["point"],"unique_name":null,"name":"Servicio de Lavado de Vehiculos","feature_count":1,"description":"","next_feature":null,"is_raster":false,"short_classification":"Y","stats":{"ruc":{"max":20498607579,"min":20498607579,"median":20498607579},"establecimentos pblicos civiles":{"max":0,"min":0,"median":0},"manzana censal":{"max":8,"min":8,"median":8},"establecimientos principales":{"max":0,"min":0,"median":0},"formalidad":{"max":1,"min":1,"median":1},"numero de trabajadores mujeres":{"max":0,"min":0,"median":0},"establecimientos nicos":{"max":5,"min":5,"median":5},"niveles de venta mensuales":{"max":3,"min":3,"median":3},"permanencia del negocio":{"max":2,"min":2,"median":2},"piso":{"max":1,"min":1,"median":1},"numero frente":{"max":2,"min":2,"median":2},"zona censal":{"max":14,"min":14,"median":14},"estasblecimientos sucursales":{"max":0,"min":0,"median":0},"tamao de la empresa":{"max":1,"min":1,"median":1},"nivel educativo del empleador":{"max":3,"min":3,"median":3},"longitud":{"max":-71.543764,"min":-71.543764,"median":-71.543764},"total de establecimientos":{"max":5,"min":5,"median":5},"establecimientos de unidad auxiliar":{"max":0,"min":0,"median":0},"estructura demogrfica":{"max":4,"min":4,"median":4},"sexo del empleador":{"max":1,"min":1,"median":1},"telfono":{"max":959486078,"min":959486078,"median":959486078},"zonificacin":{"max":4,"min":4,"median":4},"categoria de ncleo urbano":{"max":3,"min":3,"median":3},"latitud":{"max":-16.359858,"min":-16.359858,"median":-16.359858},"numero de puerta":{"max":1007,"min":1007,"median":1007},"numero de orden":{"max":4,"min":4,"median":4},"mercados":{"max":0,"min":0,"median":0},"total de empleados":{"max":3,"min":3,"median":3},"contabilidad":{"max":4,"min":4,"median":4},"edad del empleador":{"max":58,"min":58,"median":58},"numero de trabajadores hombres":{"max":3,"min":3,"median":3},"rama de actividad":{"max":7,"min":7,"median":7},"codigo de actividad":{"max":502001,"min":502001,"median":502001},"capacitacin Empresarial":{"max":1,"min":1,"median":1}},"features":[{"properties":{"actividad":"SERVICIO DE LAVADO DE VEHICULOS","ruc":20498607579,"fuente de financiamiento":"Prestamo Banco","manzana censal":8,"establecimentos pblicos civiles":0,"distrito":"Cayma","lote":null,"numero interior":null,"km":null,"numero de trabajadores mujeres":0,"formalidad":1,"establecimientos principales":0,"zona censal":14,"numero frente":2,"piso":1,"razon social o nombre del propietario":"SERVICENTRO SAN ROMAN E.I.R.L.","permanencia del negocio":2,"niveles de venta mensuales":3,"establecimientos nicos":5,"longitud":-71.543764,"nivel educativo del empleador":3,"tamao de la empresa":1,"acceso telefonico":"SI","estasblecimientos sucursales":0,"zonificacin":4,"telfono":959486078,"sexo del empleador":1,"region de destino de mercaderia":"Cayma","estructura demogrfica":4,"establecimientos de unidad auxiliar":0,"total de establecimientos":5,"ciudad":"Arequipa","latitud":-16.359858,"nucleo urbano":"FRANCISCO BOLOGNESI","local respecto vivienda":"Independiente de su Vivienda","manzana nueva":"NO","categoria de ncleo urbano":3,"descripcin de actividad":"LAVADO Y ENGRASE DE AUTOS","tipo de establecimiento":"Lavado de Autos","registro":"71A","numero de orden":4,"departamento":"Arequipa","numero de puerta":1007,"pais de destino de mercaderia":"Perú","id":"ahlhf98atwj0","codigo de actividad":502001,"manzana":null,"rama de actividad":7,"numero de trabajadores hombres":3,"edad del empleador":58,"negocio a puerta cerrada":"Abierta","empresa de destino de mercaderia":"PUBLICO","contabilidad":4,"total de empleados":3,"mercados":0,"categora":"Único","antigedad del negocio":"6-9 años","capacitacin Empresarial":1,"ubigeo":"Cayma"},"type":"Feature","geometry":{"type":"Point","coordinates":[-71.543764,-16.359858]}}],"is_temporal":false,"author":{"url":"","metadata":"","contact_name":"","contact_address":"","source":"","contact_phone":""},"source":"","pagination":{"sort":null,"start":0,"total":1,"limit":1000000},"state":"complete","tags":"","published":"2014-08-17T00:06:29-04:00","id":399180}