{"type":"FeatureCollection","data_type":"Dataset","url_type":null,"permissions":[{"permissions":{"download":true,"view":true},"group_id":"everyone"}],"classification":null,"title":"Venta de Golosinas y Confitería","count":1,"stream_id":399221,"contributor":{"url":"http://geocommons.com/users/69936","name":"eliaszr"},"data_attributes":null,"calculation_params":null,"icon_link":null,"link":"http://geocommons.com/overlays/399221.json","extent":[-71.5475,-16.3305,-71.5475,-16.3305],"geometry_types":["point"],"unique_name":null,"name":"Venta de Golosinas y Confitería","feature_count":1,"description":"","next_feature":null,"is_raster":false,"short_classification":"Y","stats":{"ruc":{"max":10292896510,"min":10292896510,"median":10292896510},"establecimentos pblicos civiles":{"max":0,"min":0,"median":0},"manzana censal":{"max":51,"min":51,"median":51},"establecimientos principales":{"max":0,"min":0,"median":0},"formalidad":{"max":1,"min":1,"median":1},"numero de trabajadores mujeres":{"max":2,"min":2,"median":2},"lote":{"max":5,"min":5,"median":5},"establecimientos nicos":{"max":1,"min":1,"median":1},"niveles de venta mensuales":{"max":2,"min":2,"median":2},"permanencia del negocio":{"max":2,"min":2,"median":2},"piso":{"max":1,"min":1,"median":1},"numero frente":{"max":1,"min":1,"median":1},"zona censal":{"max":2,"min":2,"median":2},"estasblecimientos sucursales":{"max":0,"min":0,"median":0},"tamao de la empresa":{"max":2,"min":2,"median":2},"nivel educativo del empleador":{"max":3,"min":3,"median":3},"longitud":{"max":-71.547513,"min":-71.547513,"median":-71.547513},"total de establecimientos":{"max":1,"min":1,"median":1},"establecimientos de unidad auxiliar":{"max":0,"min":0,"median":0},"estructura demogrfica":{"max":2,"min":2,"median":2},"sexo del empleador":{"max":2,"min":2,"median":2},"telfono":{"max":0,"min":0,"median":0},"zonificacin":{"max":5,"min":5,"median":5},"categoria de ncleo urbano":{"max":12,"min":12,"median":12},"latitud":{"max":-16.330524,"min":-16.330524,"median":-16.330524},"numero de orden":{"max":1,"min":1,"median":1},"mercados":{"max":0,"min":0,"median":0},"total de empleados":{"max":6,"min":6,"median":6},"contabilidad":{"max":1,"min":1,"median":1},"edad del empleador":{"max":38,"min":38,"median":38},"numero de trabajadores hombres":{"max":4,"min":4,"median":4},"rama de actividad":{"max":7,"min":7,"median":7},"codigo de actividad":{"max":522007,"min":522007,"median":522007},"capacitacin Empresarial":{"max":6,"min":6,"median":6}},"features":[{"properties":{"actividad":"VENTA DE GOLOSINAS Y CONFITERIA","ruc":10292896510,"fuente de financiamiento":"Propio","manzana censal":51,"establecimentos pblicos civiles":0,"distrito":"Cayma","lote":5,"numero interior":null,"km":null,"numero de trabajadores mujeres":2,"formalidad":1,"establecimientos principales":0,"zona censal":2,"numero frente":1,"piso":1,"razon social o nombre del propietario":"YOLANDA INCA NEYRA","permanencia del negocio":2,"niveles de venta mensuales":2,"establecimientos nicos":1,"longitud":-71.547513,"nivel educativo del empleador":3,"tamao de la empresa":2,"acceso telefonico":"NO","estasblecimientos sucursales":0,"zonificacin":5,"telfono":0,"sexo del empleador":2,"region de destino de mercaderia":"Cayma","estructura demogrfica":2,"establecimientos de unidad auxiliar":0,"total de establecimientos":1,"ciudad":"Arequipa","latitud":-16.330524,"nucleo urbano":"DEAN VALDIVIA","local respecto vivienda":"Independiente de su Vivienda","manzana nueva":"NO","categoria de ncleo urbano":12,"descripcin de actividad":"PREPARACIÓN Y VENTA DE POLLOS A LA BRASA","tipo de establecimiento":"Restaurante","registro":"396A","numero de orden":1,"departamento":"Arequipa","numero de puerta":null,"pais de destino de mercaderia":"Perú","id":"ahlhi1lddqbe","codigo de actividad":522007,"manzana":"D-5","rama de actividad":7,"numero de trabajadores hombres":4,"edad del empleador":38,"negocio a puerta cerrada":"Abierta","empresa de destino de mercaderia":"PUBLICO","contabilidad":1,"total de empleados":6,"mercados":0,"categora":"Único","antigedad del negocio":"3-5 años","capacitacin Empresarial":6,"ubigeo":"Cayma"},"type":"Feature","geometry":{"type":"Point","coordinates":[-71.547513,-16.330524]}}],"is_temporal":false,"author":{"url":"","metadata":"","contact_name":"","contact_address":"","source":"","contact_phone":""},"source":"","pagination":{"sort":null,"start":0,"total":1,"limit":1000000},"state":"complete","tags":"","published":"2014-08-17T00:07:27-04:00","id":399221}