{"type":"FeatureCollection","data_type":"Dataset","url_type":null,"permissions":[{"permissions":{"download":true,"view":true},"group_id":"everyone"}],"classification":null,"title":"Venta de Frutas Oleaginosas","count":1,"stream_id":399219,"contributor":{"url":"http://geocommons.com/users/69936","name":"eliaszr"},"data_attributes":null,"calculation_params":null,"icon_link":null,"link":"http://geocommons.com/overlays/399219.json","extent":[-71.5446,-16.3652,-71.5446,-16.3652],"geometry_types":["point"],"unique_name":null,"name":"Venta de Frutas Oleaginosas","feature_count":1,"description":"","next_feature":null,"is_raster":false,"short_classification":"Y","stats":{"ruc":{"max":10292989143,"min":10292989143,"median":10292989143},"establecimentos pblicos civiles":{"max":0,"min":0,"median":0},"manzana censal":{"max":29,"min":29,"median":29},"establecimientos principales":{"max":0,"min":0,"median":0},"formalidad":{"max":1,"min":1,"median":1},"numero de trabajadores mujeres":{"max":0,"min":0,"median":0},"establecimientos nicos":{"max":30,"min":30,"median":30},"niveles de venta mensuales":{"max":2,"min":2,"median":2},"permanencia del negocio":{"max":2,"min":2,"median":2},"piso":{"max":1,"min":1,"median":1},"numero frente":{"max":4,"min":4,"median":4},"zona censal":{"max":20,"min":20,"median":20},"estasblecimientos sucursales":{"max":0,"min":0,"median":0},"tamao de la empresa":{"max":1,"min":1,"median":1},"nivel educativo del empleador":{"max":2,"min":2,"median":2},"longitud":{"max":-71.5446,"min":-71.5446,"median":-71.5446},"total de establecimientos":{"max":32,"min":32,"median":32},"establecimientos de unidad auxiliar":{"max":2,"min":2,"median":2},"estructura demogrfica":{"max":4,"min":4,"median":4},"sexo del empleador":{"max":1,"min":1,"median":1},"telfono":{"max":959251479,"min":959251479,"median":959251479},"zonificacin":{"max":2,"min":2,"median":2},"categoria de ncleo urbano":{"max":15,"min":15,"median":15},"latitud":{"max":-16.365222,"min":-16.365222,"median":-16.365222},"numero de puerta":{"max":406,"min":406,"median":406},"numero de orden":{"max":7,"min":7,"median":7},"mercados":{"max":0,"min":0,"median":0},"total de empleados":{"max":1,"min":1,"median":1},"contabilidad":{"max":1,"min":1,"median":1},"edad del empleador":{"max":56,"min":56,"median":56},"numero de trabajadores hombres":{"max":1,"min":1,"median":1},"rama de actividad":{"max":7,"min":7,"median":7},"codigo de actividad":{"max":512104,"min":512104,"median":512104},"capacitacin Empresarial":{"max":6,"min":6,"median":6}},"features":[{"properties":{"actividad":"VENTA DE FRUTAS OLEAGINOSAS","ruc":10292989143,"fuente de financiamiento":"Propio","manzana censal":29,"establecimentos pblicos civiles":0,"distrito":"Cayma","lote":null,"numero interior":null,"km":null,"numero de trabajadores mujeres":0,"formalidad":1,"establecimientos principales":0,"zona censal":20,"numero frente":4,"piso":1,"razon social o nombre del propietario":"HILBER SANTOS AYCHASI VILCA","permanencia del negocio":2,"niveles de venta mensuales":2,"establecimientos nicos":30,"longitud":-71.5446,"nivel educativo del empleador":2,"tamao de la empresa":1,"acceso telefonico":"SI","estasblecimientos sucursales":0,"zonificacin":2,"telfono":959251479,"sexo del empleador":1,"region de destino de mercaderia":"Cayma","estructura demogrfica":4,"establecimientos de unidad auxiliar":2,"total de establecimientos":32,"ciudad":"Arequipa","latitud":-16.365222,"nucleo urbano":"LA TOMILLA","local respecto vivienda":"Independiente de su Vivienda","manzana nueva":"NO","categoria de ncleo urbano":15,"descripcin de actividad":"VENTA DE FRUTAS AL POR MENOR","tipo de establecimiento":"Frutería","registro":"181C","numero de orden":7,"departamento":"Arequipa","numero de puerta":406,"pais de destino de mercaderia":"Perú","id":"ahlhhxd24e2a","codigo de actividad":512104,"manzana":null,"rama de actividad":7,"numero de trabajadores hombres":1,"edad del empleador":56,"negocio a puerta cerrada":"Abierta","empresa de destino de mercaderia":"PUBLICO","contabilidad":1,"total de empleados":1,"mercados":0,"categora":"Único","antigedad del negocio":"3-5 años","capacitacin Empresarial":6,"ubigeo":"Cayma"},"type":"Feature","geometry":{"type":"Point","coordinates":[-71.5446,-16.365222]}}],"is_temporal":false,"author":{"url":"","metadata":"","contact_name":"","contact_address":"","source":"","contact_phone":""},"source":"","pagination":{"sort":null,"start":0,"total":1,"limit":1000000},"state":"complete","tags":"","published":"2014-08-17T00:07:26-04:00","id":399219}