{"type":"FeatureCollection","data_type":"Dataset","url_type":null,"permissions":[{"permissions":{"download":true,"view":true},"group_id":"everyone"}],"classification":null,"title":"Venta de Articulos de ferreteria y Muebles","count":1,"stream_id":399207,"contributor":{"url":"http://geocommons.com/users/69936","name":"eliaszr"},"data_attributes":null,"calculation_params":null,"icon_link":null,"link":"http://geocommons.com/overlays/399207.json","extent":[-71.5508,-16.346,-71.5508,-16.346],"geometry_types":["point"],"unique_name":null,"name":"Venta de Articulos de ferreteria y Muebles","feature_count":1,"description":"","next_feature":null,"is_raster":false,"short_classification":"Y","stats":{"ruc":{"max":0,"min":0,"median":0},"establecimentos pblicos civiles":{"max":0,"min":0,"median":0},"manzana censal":{"max":36,"min":36,"median":36},"establecimientos principales":{"max":0,"min":0,"median":0},"formalidad":{"max":2,"min":2,"median":2},"numero de trabajadores mujeres":{"max":0,"min":0,"median":0},"lote":{"max":7,"min":7,"median":7},"establecimientos nicos":{"max":4,"min":4,"median":4},"niveles de venta mensuales":{"max":2,"min":2,"median":2},"permanencia del negocio":{"max":2,"min":2,"median":2},"piso":{"max":1,"min":1,"median":1},"numero frente":{"max":4,"min":4,"median":4},"zona censal":{"max":12,"min":12,"median":12},"estasblecimientos sucursales":{"max":0,"min":0,"median":0},"tamao de la empresa":{"max":1,"min":1,"median":1},"nivel educativo del empleador":{"max":4,"min":4,"median":4},"longitud":{"max":-71.550823,"min":-71.550823,"median":-71.550823},"total de establecimientos":{"max":4,"min":4,"median":4},"establecimientos de unidad auxiliar":{"max":0,"min":0,"median":0},"estructura demogrfica":{"max":2,"min":2,"median":2},"sexo del empleador":{"max":1,"min":1,"median":1},"telfono":{"max":1,"min":1,"median":1},"zonificacin":{"max":3,"min":3,"median":3},"categoria de ncleo urbano":{"max":15,"min":15,"median":15},"latitud":{"max":-16.345951,"min":-16.345951,"median":-16.345951},"numero de orden":{"max":3,"min":3,"median":3},"mercados":{"max":0,"min":0,"median":0},"total de empleados":{"max":1,"min":1,"median":1},"contabilidad":{"max":3,"min":3,"median":3},"edad del empleador":{"max":25,"min":25,"median":25},"numero de trabajadores hombres":{"max":1,"min":1,"median":1},"rama de actividad":{"max":7,"min":7,"median":7},"codigo de actividad":{"max":521902,"min":521902,"median":521902},"capacitacin Empresarial":{"max":6,"min":6,"median":6}},"features":[{"properties":{"actividad":"VENTA DE ARTICULOS DE FERRETERIA Y MUEBLES","ruc":0,"fuente de financiamiento":"Propio","manzana censal":36,"establecimentos pblicos civiles":0,"distrito":"Cayma","lote":7,"numero interior":null,"km":null,"numero de trabajadores mujeres":0,"formalidad":2,"establecimientos principales":0,"zona censal":12,"numero frente":4,"piso":1,"razon social o nombre del propietario":"JHON LOPEZ LARICO","permanencia del negocio":2,"niveles de venta mensuales":2,"establecimientos nicos":4,"longitud":-71.550823,"nivel educativo del empleador":4,"tamao de la empresa":1,"acceso telefonico":"NO QUISO DAR","estasblecimientos sucursales":0,"zonificacin":3,"telfono":1,"sexo del empleador":1,"region de destino de mercaderia":"Cayma","estructura demogrfica":2,"establecimientos de unidad auxiliar":0,"total de establecimientos":4,"ciudad":"Arequipa","latitud":-16.345951,"nucleo urbano":"CASIMIRO CUADROS I","local respecto vivienda":"Dentro de su Vivienda en un Area de uso Exclusivo","manzana nueva":"NO","categoria de ncleo urbano":15,"descripcin de actividad":"VENTA DE TUBOS CEMENTO PLASTICOS AL POR MENOR","tipo de establecimiento":"Ferretería","registro":"44C","numero de orden":3,"departamento":"Arequipa","numero de puerta":null,"pais de destino de mercaderia":"Perú","id":"ahlhh3mnm286","codigo de actividad":521902,"manzana":"L","rama de actividad":7,"numero de trabajadores hombres":1,"edad del empleador":25,"negocio a puerta cerrada":"Abierta","empresa de destino de mercaderia":"PUBLICO","contabilidad":3,"total de empleados":1,"mercados":0,"categora":"Único","antigedad del negocio":"10 años a +","capacitacin Empresarial":6,"ubigeo":"Cayma"},"type":"Feature","geometry":{"type":"Point","coordinates":[-71.550823,-16.345951]}}],"is_temporal":false,"author":{"url":"","metadata":"","contact_name":"","contact_address":"","source":"","contact_phone":""},"source":"","pagination":{"sort":null,"start":0,"total":1,"limit":1000000},"state":"complete","tags":"","published":"2014-08-17T00:07:16-04:00","id":399207}