{"type":"FeatureCollection","data_type":"Dataset","url_type":null,"permissions":[{"permissions":{"download":true,"view":true},"group_id":"everyone"}],"classification":null,"title":"Venta de Articulos Artesanales","count":1,"stream_id":399205,"contributor":{"url":"http://geocommons.com/users/69936","name":"eliaszr"},"data_attributes":null,"calculation_params":null,"icon_link":null,"link":"http://geocommons.com/overlays/399205.json","extent":[-71.5454,-16.3302,-71.5454,-16.3302],"geometry_types":["point"],"unique_name":null,"name":"Venta de Articulos Artesanales","feature_count":1,"description":"","next_feature":null,"is_raster":false,"short_classification":"Y","stats":{"ruc":{"max":1,"min":1,"median":1},"establecimentos pblicos civiles":{"max":0,"min":0,"median":0},"manzana censal":{"max":36,"min":36,"median":36},"establecimientos principales":{"max":0,"min":0,"median":0},"formalidad":{"max":3,"min":3,"median":3},"numero de trabajadores mujeres":{"max":0,"min":0,"median":0},"lote":{"max":10,"min":10,"median":10},"establecimientos nicos":{"max":2,"min":2,"median":2},"niveles de venta mensuales":{"max":1,"min":1,"median":1},"permanencia del negocio":{"max":2,"min":2,"median":2},"piso":{"max":1,"min":1,"median":1},"numero frente":{"max":3,"min":3,"median":3},"zona censal":{"max":2,"min":2,"median":2},"estasblecimientos sucursales":{"max":0,"min":0,"median":0},"tamao de la empresa":{"max":1,"min":1,"median":1},"nivel educativo del empleador":{"max":3,"min":3,"median":3},"longitud":{"max":-71.545386,"min":-71.545386,"median":-71.545386},"total de establecimientos":{"max":2,"min":2,"median":2},"establecimientos de unidad auxiliar":{"max":0,"min":0,"median":0},"estructura demogrfica":{"max":2,"min":2,"median":2},"sexo del empleador":{"max":1,"min":1,"median":1},"telfono":{"max":958992824,"min":958992824,"median":958992824},"zonificacin":{"max":5,"min":5,"median":5},"categoria de ncleo urbano":{"max":11,"min":11,"median":11},"latitud":{"max":-16.330154,"min":-16.330154,"median":-16.330154},"numero de orden":{"max":2,"min":2,"median":2},"mercados":{"max":0,"min":0,"median":0},"total de empleados":{"max":1,"min":1,"median":1},"contabilidad":{"max":1,"min":1,"median":1},"edad del empleador":{"max":44,"min":44,"median":44},"numero de trabajadores hombres":{"max":1,"min":1,"median":1},"rama de actividad":{"max":7,"min":7,"median":7},"codigo de actividad":{"max":523918,"min":523918,"median":523918},"capacitacin Empresarial":{"max":1,"min":1,"median":1}},"features":[{"properties":{"actividad":"VENTA DE ARTICULOS ARTESANALES","ruc":1,"fuente de financiamiento":"Propio","manzana censal":36,"establecimentos pblicos civiles":0,"distrito":"Cayma","lote":10,"numero interior":null,"km":null,"numero de trabajadores mujeres":0,"formalidad":3,"establecimientos principales":0,"zona censal":2,"numero frente":3,"piso":1,"razon social o nombre del propietario":"HIPOLITO GARATE MAQUERA","permanencia del negocio":2,"niveles de venta mensuales":1,"establecimientos nicos":2,"longitud":-71.545386,"nivel educativo del empleador":3,"tamao de la empresa":1,"acceso telefonico":"SI","estasblecimientos sucursales":0,"zonificacin":5,"telfono":958992824,"sexo del empleador":1,"region de destino de mercaderia":"Cayma","estructura demogrfica":2,"establecimientos de unidad auxiliar":0,"total de establecimientos":2,"ciudad":"Arequipa","latitud":-16.330154,"nucleo urbano":"DEAN VALDIVIA SECTOR CINCO","local respecto vivienda":"Ambiente Compartido para Negocio y Vivienda","manzana nueva":"NO","categoria de ncleo urbano":11,"descripcin de actividad":"ELABORACIÓN DE ARTESANIA","tipo de establecimiento":"Casa","registro":"372A","numero de orden":2,"departamento":"Arequipa","numero de puerta":null,"pais de destino de mercaderia":"Perú","id":"ahlhgyh4vss8","codigo de actividad":523918,"manzana":"R-5","rama de actividad":7,"numero de trabajadores hombres":1,"edad del empleador":44,"negocio a puerta cerrada":"Cerrada","empresa de destino de mercaderia":"PUBLICO","contabilidad":1,"total de empleados":1,"mercados":0,"categora":"Único","antigedad del negocio":"3-5 años","capacitacin Empresarial":1,"ubigeo":"Cayma"},"type":"Feature","geometry":{"type":"Point","coordinates":[-71.545386,-16.330154]}}],"is_temporal":false,"author":{"url":"","metadata":"","contact_name":"","contact_address":"","source":"","contact_phone":""},"source":"","pagination":{"sort":null,"start":0,"total":1,"limit":1000000},"state":"complete","tags":"","published":"2014-08-17T00:07:14-04:00","id":399205}