{"type":"FeatureCollection","data_type":"Dataset","url_type":null,"permissions":[{"permissions":{"download":true,"view":true},"group_id":"everyone"}],"classification":null,"title":"Venta de Partes Piezas y Acc de Vehiculos Automotores","count":1,"stream_id":399227,"contributor":{"url":"http://geocommons.com/users/69936","name":"eliaszr"},"data_attributes":null,"calculation_params":null,"icon_link":null,"link":"http://geocommons.com/overlays/399227.json","extent":[-71.5441,-16.3613,-71.5441,-16.3613],"geometry_types":["point"],"unique_name":null,"name":"Venta de Partes Piezas y Acc de Vehiculos Automotores","feature_count":1,"description":"","next_feature":null,"is_raster":false,"short_classification":"Y","stats":{"ruc":{"max":10293272218,"min":10293272218,"median":10293272218},"establecimentos pblicos civiles":{"max":0,"min":0,"median":0},"manzana censal":{"max":12,"min":12,"median":12},"establecimientos principales":{"max":0,"min":0,"median":0},"formalidad":{"max":1,"min":1,"median":1},"numero de trabajadores mujeres":{"max":0,"min":0,"median":0},"establecimientos nicos":{"max":20,"min":20,"median":20},"niveles de venta mensuales":{"max":2,"min":2,"median":2},"permanencia del negocio":{"max":2,"min":2,"median":2},"piso":{"max":1,"min":1,"median":1},"numero frente":{"max":4,"min":4,"median":4},"zona censal":{"max":20,"min":20,"median":20},"estasblecimientos sucursales":{"max":1,"min":1,"median":1},"tamao de la empresa":{"max":1,"min":1,"median":1},"nivel educativo del empleador":{"max":4,"min":4,"median":4},"longitud":{"max":-71.54405,"min":-71.54405,"median":-71.54405},"total de establecimientos":{"max":21,"min":21,"median":21},"establecimientos de unidad auxiliar":{"max":0,"min":0,"median":0},"estructura demogrfica":{"max":3,"min":3,"median":3},"sexo del empleador":{"max":1,"min":1,"median":1},"telfono":{"max":959537374,"min":959537374,"median":959537374},"zonificacin":{"max":2,"min":2,"median":2},"categoria de ncleo urbano":{"max":15,"min":15,"median":15},"latitud":{"max":-16.361322,"min":-16.361322,"median":-16.361322},"numero de puerta":{"max":838,"min":838,"median":838},"numero de orden":{"max":12,"min":12,"median":12},"mercados":{"max":0,"min":0,"median":0},"total de empleados":{"max":1,"min":1,"median":1},"contabilidad":{"max":3,"min":3,"median":3},"edad del empleador":{"max":46,"min":46,"median":46},"numero de trabajadores hombres":{"max":1,"min":1,"median":1},"rama de actividad":{"max":7,"min":7,"median":7},"codigo de actividad":{"max":503000,"min":503000,"median":503000},"capacitacin Empresarial":{"max":6,"min":6,"median":6}},"features":[{"properties":{"actividad":"VENTA DE PARTES, PIEZAS Y ACCESORIOS DE VEHICULOS AUTOMOTORES","ruc":10293272218,"fuente de financiamiento":"Propio","manzana censal":12,"establecimentos pblicos civiles":0,"distrito":"Cayma","lote":null,"numero interior":null,"km":null,"numero de trabajadores mujeres":0,"formalidad":1,"establecimientos principales":0,"zona censal":20,"numero frente":4,"piso":1,"razon social o nombre del propietario":"DARIO PONCE SERRANO","permanencia del negocio":2,"niveles de venta mensuales":2,"establecimientos nicos":20,"longitud":-71.54405,"nivel educativo del empleador":4,"tamao de la empresa":1,"acceso telefonico":"SI","estasblecimientos sucursales":1,"zonificacin":2,"telfono":959537374,"sexo del empleador":1,"region de destino de mercaderia":"Cayma","estructura demogrfica":3,"establecimientos de unidad auxiliar":0,"total de establecimientos":21,"ciudad":"Arequipa","latitud":-16.361322,"nucleo urbano":"LA TOMILLA","local respecto vivienda":"Independiente de su Vivienda","manzana nueva":"NO","categoria de ncleo urbano":15,"descripcin de actividad":"VENTA DE BATERIAS AL POR MENOR","tipo de establecimiento":"Casa","registro":"161C","numero de orden":12,"departamento":"Arequipa","numero de puerta":838,"pais de destino de mercaderia":"Perú","id":"ahlhiij80pyy","codigo de actividad":503000,"manzana":null,"rama de actividad":7,"numero de trabajadores hombres":1,"edad del empleador":46,"negocio a puerta cerrada":"Abierta","empresa de destino de mercaderia":"PUBLICO","contabilidad":3,"total de empleados":1,"mercados":0,"categora":"Único","antigedad del negocio":"3-5 años","capacitacin Empresarial":6,"ubigeo":"Cayma"},"type":"Feature","geometry":{"type":"Point","coordinates":[-71.54405,-16.361322]}}],"is_temporal":false,"author":{"url":"","metadata":"","contact_name":"","contact_address":"","source":"","contact_phone":""},"source":"","pagination":{"sort":null,"start":0,"total":1,"limit":1000000},"state":"complete","tags":"","published":"2014-08-17T00:07:35-04:00","id":399227}