{"type":"FeatureCollection","data_type":"Dataset","url_type":null,"permissions":[{"permissions":{"download":true,"view":true},"group_id":"everyone"}],"classification":null,"title":"Ben Franklin Submarine","count":1,"stream_id":4050,"contributor":{"url":"http://geocommons.com/users/900","name":"jeffryv"},"data_attributes":null,"calculation_params":null,"icon_link":null,"link":"http://geocommons.com/overlays/4050.json","extent":[-123.148,49.2778,-123.148,49.2778],"geometry_types":["point"],"unique_name":null,"name":"Ben Franklin Submarine","feature_count":1,"description":"Ben Franklin sub ","next_feature":null,"is_raster":false,"short_classification":"Y","stats":{},"features":[{"properties":{"name":"Ben Franklin Submarine","description":"<a href=\"http://picasaweb.google.com/JeffryVance/Vanierparkub/photo#5023033927692319122\"><img src=\"http://lh5.ggpht.com/JeffryVance/RbVmvnrV-ZI/AAAAAAAAABA/IZSzaSC06uQ/s400/DSCF0827.JPG\" alt=\"DSCF0827.JPG\"></a>Date: Jan 22, 2007 5:37 PMNumber of Comments on Photo:0<a href=\"http://picasaweb.google.com/JeffryVance/Vanierparkub/photo#5023033927692319122\">View Photo</a><a href=\"http://picasaweb.google.com/JeffryVance/Vanierparkub\"><img src=\"http://lh3.ggpht.com/JeffryVance/RbVmuXrV-YE/AAAAAAAAABE/cnifJgZpJQQ/s160-c/Vanierparkub.jpg\" width=\"160\" height=\"160\"></a><a href=\"http://picasaweb.google.com/JeffryVance/Vanierparkub\">vanierparkub</a>]]&gt;","id":"a65a0bv7c8um"},"type":"Feature","geometry":{"type":"Point","coordinates":[-123.147561103106,49.2777674706244]}}],"is_temporal":false,"author":{"url":"","metadata":"","contact_name":"","contact_address":"","source":"","contact_phone":""},"source":"","pagination":{"sort":null,"start":0,"total":1,"limit":1000000},"state":"complete","tags":"ben,sub,vancouver","published":"2014-08-11T03:29:26-04:00","id":4050}