{"type":"FeatureCollection","data_type":"Dataset","url_type":null,"permissions":[{"permissions":{"download":true,"view":true},"group_id":"everyone"}],"classification":null,"title":"\nAkash\n","count":4,"stream_id":44804,"contributor":{"url":"http://geocommons.com/users/11444","name":"platial"},"data_attributes":null,"calculation_params":null,"icon_link":null,"link":"http://geocommons.com/overlays/44804.json","extent":[-83.3771,33.9333,-83.3121,33.9585],"geometry_types":["point"],"unique_name":null,"name":"\nAkash\n","feature_count":4,"description":"\nA Map by Icesktr385\n\n\n","next_feature":null,"is_raster":false,"short_classification":"Y","stats":{},"features":[{"properties":{"name":"Downtown 3/8","description":"Posted by Icesktr385215 N Lumpkin St, Athens, GA <a title=\"Built for Community Mapping\" href=\"http://www.platial.com\"><img src=\"http://media.geocommons.com/platial/images/logotype_small.jpg\"></a>","id":"a6g127mnm96z"},"type":"Feature","geometry":{"type":"Point","coordinates":[-83.377118,33.958455]}},{"properties":{"name":"SLC","description":"Posted by Icesktr385<a title=\"Built for Community Mapping\" href=\"http://www.platial.com\"><img src=\"http://media.geocommons.com/platial/images/logotype_small.jpg\"></a>","id":"a6g127ialmzo"},"type":"Feature","geometry":{"type":"Point","coordinates":[-83.37658,33.94902]}},{"properties":{"name":"Walmart","description":"Posted by Icesktr3854375 Lexington Road, Athens, GA 30605 <a title=\"Built for Community Mapping\" href=\"http://www.platial.com\"><img src=\"http://media.geocommons.com/platial/images/logotype_small.jpg\"></a>","id":"a6g127czcor8"},"type":"Feature","geometry":{"type":"Point","coordinates":[-83.312144,33.933328]}},{"properties":{"name":"driving","description":"Posted by Icesktr385100 baxter st athens, ga<a title=\"Built for Community Mapping\" href=\"http://www.platial.com\"><img src=\"http://media.geocommons.com/platial/images/logotype_small.jpg\"></a>","id":"a6g127nibicd"},"type":"Feature","geometry":{"type":"Point","coordinates":[-83.37705,33.951375]}}],"is_temporal":false,"author":{"url":"http://www.platial.com/map/10159","metadata":null,"contact_name":"icesktr385","contact_address":null,"source":"platial:icesktr385","contact_phone":null},"source":"http://www.platial.com/map/10159","pagination":{"sort":null,"start":0,"total":4,"limit":1000000},"state":"complete","tags":"platial,platial:id=10159,platial:user=icesktr385","published":"2010-04-26T16:00:00Z","id":44804}