{"type":"FeatureCollection","data_type":"Dataset","url_type":null,"permissions":[{"permissions":{"download":true,"view":true},"group_id":"everyone"}],"classification":null,"title":"\nPlaces in Bahrain\n","count":9,"stream_id":45353,"contributor":{"url":"http://geocommons.com/users/11444","name":"platial"},"data_attributes":null,"calculation_params":null,"icon_link":null,"link":"http://geocommons.com/overlays/45353.json","extent":[50.5373,26.1311,50.5737,26.2376],"geometry_types":["point"],"unique_name":null,"name":"\nPlaces in Bahrain\n","feature_count":9,"description":"\nA Map by Ummair\n\n\n","next_feature":null,"is_raster":false,"short_classification":"Y","stats":{},"features":[{"properties":{"name":null,"description":"Posted by UmmairCosta Coffee<a title=\"Built for Community Mapping\" href=\"http://www.platial.com\"><img src=\"http://media.geocommons.com/platial/images/logotype_small.jpg\"></a>","id":"a6j2nu20h8za"},"type":"Feature","geometry":{"type":"Point","coordinates":[50.56654,26.13784]}},{"properties":{"name":null,"description":"Posted by UmmairThe Bahrain Mall<a title=\"Built for Community Mapping\" href=\"http://www.platial.com\"><img src=\"http://media.geocommons.com/platial/images/logotype_small.jpg\"></a>","id":"a6j2nu5utoh2"},"type":"Feature","geometry":{"type":"Point","coordinates":[50.5378,26.22926]}},{"properties":{"name":null,"description":"Posted by UmmairThe Seef Mall<a title=\"Built for Community Mapping\" href=\"http://www.platial.com\"><img src=\"http://media.geocommons.com/platial/images/logotype_small.jpg\"></a>","id":"a6j2nu5gjshc"},"type":"Feature","geometry":{"type":"Point","coordinates":[50.53731,26.23229]}},{"properties":{"name":null,"description":"Posted by UmmairBahrain Financial Harbour<a title=\"Built for Community Mapping\" href=\"http://www.platial.com\"><img src=\"http://media.geocommons.com/platial/images/logotype_small.jpg\"></a>","id":"a6j2nub1t2b7"},"type":"Feature","geometry":{"type":"Point","coordinates":[50.57373,26.23763]}},{"properties":{"name":null,"description":"Posted by Ummair<a title=\"Built for Community Mapping\" href=\"http://www.platial.com\"><img src=\"http://media.geocommons.com/platial/images/logotype_small.jpg\"></a>","id":"a6j2nuaq55do"},"type":"Feature","geometry":{"type":"Point","coordinates":[50.57373,26.23763]}},{"properties":{"name":null,"description":"Posted by UmmairBukwara Road<a title=\"Built for Community Mapping\" href=\"http://www.platial.com\"><img src=\"http://media.geocommons.com/platial/images/logotype_small.jpg\"></a>","id":"a6j2ntzh0ink"},"type":"Feature","geometry":{"type":"Point","coordinates":[50.55788,26.13105]}},{"properties":{"name":null,"description":"Posted by UmmairNational Stadium of Bahrain<a title=\"Built for Community Mapping\" href=\"http://www.platial.com\"><img src=\"http://media.geocommons.com/platial/images/logotype_small.jpg\"></a>","id":"a6j2nu8b5wl1"},"type":"Feature","geometry":{"type":"Point","coordinates":[50.54355,26.15374]}},{"properties":{"name":null,"description":"Posted by UmmairUniversity of Bahrain Isa Town campus <a title=\"Built for Community Mapping\" href=\"http://www.platial.com\"><img src=\"http://media.geocommons.com/platial/images/logotype_small.jpg\"></a>","id":"a6j2ntyrkoqx"},"type":"Feature","geometry":{"type":"Point","coordinates":[50.54483,26.16605]}},{"properties":{"name":null,"description":"Posted by UmmairPakistan Urdu School<a title=\"Built for Community Mapping\" href=\"http://www.platial.com\"><img src=\"http://media.geocommons.com/platial/images/logotype_small.jpg\"></a>","id":"a6j2nu90ddzg"},"type":"Feature","geometry":{"type":"Point","coordinates":[50.5489,26.15983]}}],"is_temporal":false,"author":{"url":"http://www.platial.com/map/49788","metadata":null,"contact_name":"ummair","contact_address":null,"source":"platial:ummair","contact_phone":null},"source":"http://www.platial.com/map/49788","pagination":{"sort":null,"start":0,"total":9,"limit":1000000},"state":"complete","tags":"platial,platial:id=49788,platial:user=ummair","published":"2010-04-26T16:00:00Z","id":45353}