{"type":"FeatureCollection","data_type":"Dataset","url_type":null,"permissions":[{"permissions":{"download":true,"view":true},"group_id":"everyone"}],"classification":null,"title":"\ntravel boyz\n","count":12,"stream_id":45928,"contributor":{"url":"http://geocommons.com/users/11444","name":"platial"},"data_attributes":null,"calculation_params":null,"icon_link":null,"link":"http://geocommons.com/overlays/45928.json","extent":[-118.213,25.8395,137.109,46.8001],"geometry_types":["point"],"unique_name":null,"name":"\ntravel boyz\n","feature_count":12,"description":"\nA Map by 1984doe\n\n\n","next_feature":null,"is_raster":false,"short_classification":"Y","stats":{},"features":[{"properties":{"name":null,"description":"Posted by 1984doe<a title=\"Built for Community Mapping\" href=\"http://www.platial.com\"><img src=\"http://media.geocommons.com/platial/images/logotype_small.jpg\"></a>","id":"a6jvrw9x0ivy"},"type":"Feature","geometry":{"type":"Point","coordinates":[1.75781,46.80006]}},{"properties":{"name":null,"description":"Posted by 1984doe<a title=\"Built for Community Mapping\" href=\"http://www.platial.com\"><img src=\"http://media.geocommons.com/platial/images/logotype_small.jpg\"></a>","id":"a6jvrvzucapu"},"type":"Feature","geometry":{"type":"Point","coordinates":[-80.15625,25.83945]}},{"properties":{"name":null,"description":"Posted by 1984doe<a title=\"Built for Community Mapping\" href=\"http://www.platial.com\"><img src=\"http://media.geocommons.com/platial/images/logotype_small.jpg\"></a>","id":"a6jvrwe453li"},"type":"Feature","geometry":{"type":"Point","coordinates":[-80.24414,34.45222]}},{"properties":{"name":null,"description":"Posted by 1984doe<a title=\"Built for Community Mapping\" href=\"http://www.platial.com\"><img src=\"http://media.geocommons.com/platial/images/logotype_small.jpg\"></a>","id":"a6jvrwbn9q3t"},"type":"Feature","geometry":{"type":"Point","coordinates":[-73.90503,40.75974]}},{"properties":{"name":null,"description":"Posted by 1984doe<a title=\"Built for Community Mapping\" href=\"http://www.platial.com\"><img src=\"http://media.geocommons.com/platial/images/logotype_small.jpg\"></a>","id":"a6jvrvy1u7es"},"type":"Feature","geometry":{"type":"Point","coordinates":[-81.10107,32.15701]}},{"properties":{"name":null,"description":"Posted by 1984doe<a title=\"Built for Community Mapping\" href=\"http://www.platial.com\"><img src=\"http://media.geocommons.com/platial/images/logotype_small.jpg\"></a>","id":"a6jvrw0q2gaw"},"type":"Feature","geometry":{"type":"Point","coordinates":[-118.21289,34.08906]}},{"properties":{"name":null,"description":"Posted by 1984doe<a title=\"Built for Community Mapping\" href=\"http://www.platial.com\"><img src=\"http://media.geocommons.com/platial/images/logotype_small.jpg\"></a>","id":"a6jvrw95s2lm"},"type":"Feature","geometry":{"type":"Point","coordinates":[-78.66211,36.31513]}},{"properties":{"name":null,"description":"Posted by 1984doe<a title=\"Built for Community Mapping\" href=\"http://www.platial.com\"><img src=\"http://media.geocommons.com/platial/images/logotype_small.jpg\"></a>","id":"a6jvrw1tan5i"},"type":"Feature","geometry":{"type":"Point","coordinates":[-98.87695,31.57854]}},{"properties":{"name":null,"description":"Posted by 1984doe<a title=\"Built for Community Mapping\" href=\"http://www.platial.com\"><img src=\"http://media.geocommons.com/platial/images/logotype_small.jpg\"></a>","id":"a6jvrw22x4vq"},"type":"Feature","geometry":{"type":"Point","coordinates":[-111.62109,34.59704]}},{"properties":{"name":null,"description":"Posted by 1984doe<a title=\"Built for Community Mapping\" href=\"http://www.platial.com\"><img src=\"http://media.geocommons.com/platial/images/logotype_small.jpg\"></a>","id":"a6jvrw58ejhl"},"type":"Feature","geometry":{"type":"Point","coordinates":[-86.48437,35.92464]}},{"properties":{"name":null,"description":"Posted by 1984doe<a title=\"Built for Community Mapping\" href=\"http://www.platial.com\"><img src=\"http://media.geocommons.com/platial/images/logotype_small.jpg\"></a>","id":"a6jvrvzak9oq"},"type":"Feature","geometry":{"type":"Point","coordinates":[-79.45312,43.89789]}},{"properties":{"name":null,"description":"Posted by 1984doe<a title=\"Built for Community Mapping\" href=\"http://www.platial.com\"><img src=\"http://media.geocommons.com/platial/images/logotype_small.jpg\"></a>","id":"a6jvrvz0ryzd"},"type":"Feature","geometry":{"type":"Point","coordinates":[137.10938,36.87962]}}],"is_temporal":false,"author":{"url":"http://www.platial.com/map/47508","metadata":null,"contact_name":"1984doe","contact_address":null,"source":"platial:1984doe","contact_phone":null},"source":"http://www.platial.com/map/47508","pagination":{"sort":null,"start":0,"total":12,"limit":1000000},"state":"complete","tags":"platial,platial:id=47508,platial:user=1984doe","published":"2010-04-26T16:00:00Z","id":45928}