{"type":"FeatureCollection","data_type":"Dataset","url_type":null,"permissions":[{"permissions":{"download":true,"view":true},"group_id":"everyone"}],"classification":null,"title":"\nsc365's places\n","count":12,"stream_id":45970,"contributor":{"url":"http://geocommons.com/users/11444","name":"platial"},"data_attributes":null,"calculation_params":null,"icon_link":null,"link":"http://geocommons.com/overlays/45970.json","extent":[-64.6165,18.3552,-64.3579,18.7276],"geometry_types":["point"],"unique_name":null,"name":"\nsc365's places\n","feature_count":12,"description":"\nA Map by Sc365\n\n\n","next_feature":null,"is_raster":false,"short_classification":"Y","stats":{},"features":[{"properties":{"name":null,"description":"Posted by Sc365<a title=\"Built for Community Mapping\" href=\"http://www.platial.com\"><img src=\"http://media.geocommons.com/platial/images/logotype_small.jpg\"></a>","id":"a6pekwwxahk7"},"type":"Feature","geometry":{"type":"Point","coordinates":[-64.61648,18.42651]}},{"properties":{"name":null,"description":"Posted by Sc365Mooring at Peter Island<a title=\"Built for Community Mapping\" href=\"http://www.platial.com\"><img src=\"http://media.geocommons.com/platial/images/logotype_small.jpg\"></a>","id":"a6pekwqf8x9x"},"type":"Feature","geometry":{"type":"Point","coordinates":[-64.57627,18.35731]}},{"properties":{"name":null,"description":"Posted by Sc365Deadman\\'s Beach<a title=\"Built for Community Mapping\" href=\"http://www.platial.com\"><img src=\"http://media.geocommons.com/platial/images/logotype_small.jpg\"></a>","id":"a6pekwwi6rls"},"type":"Feature","geometry":{"type":"Point","coordinates":[-64.57258,18.35521]}},{"properties":{"name":null,"description":"Posted by Sc365<a title=\"Built for Community Mapping\" href=\"http://www.platial.com\"><img src=\"http://media.geocommons.com/platial/images/logotype_small.jpg\"></a>","id":"a6pekx0j5yqf"},"type":"Feature","geometry":{"type":"Point","coordinates":[-64.52356,18.38092]}},{"properties":{"name":null,"description":"Posted by Sc365<a title=\"Built for Community Mapping\" href=\"http://www.platial.com\"><img src=\"http://media.geocommons.com/platial/images/logotype_small.jpg\"></a>","id":"a6pekwv7h4ai"},"type":"Feature","geometry":{"type":"Point","coordinates":[-64.48339,18.47733]}},{"properties":{"name":null,"description":"Posted by Sc365<a title=\"Built for Community Mapping\" href=\"http://www.platial.com\"><img src=\"http://media.geocommons.com/platial/images/logotype_small.jpg\"></a>","id":"a6pekx13x15b"},"type":"Feature","geometry":{"type":"Point","coordinates":[-64.4737,18.50643]}},{"properties":{"name":null,"description":"Posted by Sc365<a title=\"Built for Community Mapping\" href=\"http://www.platial.com\"><img src=\"http://media.geocommons.com/platial/images/logotype_small.jpg\"></a>","id":"a6pekx0tmnf1"},"type":"Feature","geometry":{"type":"Point","coordinates":[-64.40473,18.72637]}},{"properties":{"name":null,"description":"Posted by Sc365<a title=\"Built for Community Mapping\" href=\"http://www.platial.com\"><img src=\"http://media.geocommons.com/platial/images/logotype_small.jpg\"></a>","id":"a6pekwzjxgei"},"type":"Feature","geometry":{"type":"Point","coordinates":[-64.38005,18.52942]}},{"properties":{"name":null,"description":"Posted by Sc365Anagada Mooring<a title=\"Built for Community Mapping\" href=\"http://www.platial.com\"><img src=\"http://media.geocommons.com/platial/images/logotype_small.jpg\"></a>","id":"a6pekx073s6v"},"type":"Feature","geometry":{"type":"Point","coordinates":[-64.38671,18.72336]}},{"properties":{"name":null,"description":"Posted by Sc365SABA ROCK<a title=\"Built for Community Mapping\" href=\"http://www.platial.com\"><img src=\"http://media.geocommons.com/platial/images/logotype_small.jpg\"></a>","id":"a6pekwzsl5np"},"type":"Feature","geometry":{"type":"Point","coordinates":[-64.35787,18.50301]}},{"properties":{"name":null,"description":"Posted by Sc365Leverick Bay<a title=\"Built for Community Mapping\" href=\"http://www.platial.com\"><img src=\"http://media.geocommons.com/platial/images/logotype_small.jpg\"></a>","id":"a6pekx40n82z"},"type":"Feature","geometry":{"type":"Point","coordinates":[-64.38693,18.49823]}},{"properties":{"name":null,"description":"Posted by Sc365Beach<a title=\"Built for Community Mapping\" href=\"http://www.platial.com\"><img src=\"http://media.geocommons.com/platial/images/logotype_small.jpg\"></a>","id":"a6pekwzvq2df"},"type":"Feature","geometry":{"type":"Point","coordinates":[-64.40181,18.72759]}}],"is_temporal":false,"author":{"url":"http://www.platial.com/map/242401","metadata":null,"contact_name":"sc365","contact_address":null,"source":"platial:sc365","contact_phone":null},"source":"http://www.platial.com/map/242401","pagination":{"sort":null,"start":0,"total":12,"limit":1000000},"state":"complete","tags":"platial,platial:id=242401,platial:user=sc365","published":"2010-04-26T16:00:00Z","id":45970}