{"type":"FeatureCollection","data_type":"Dataset","url_type":null,"permissions":[{"permissions":{"download":true,"view":true},"group_id":"everyone"}],"classification":null,"title":"\nMy Location :) Jakarta\n","count":12,"stream_id":46093,"contributor":{"url":"http://geocommons.com/users/11444","name":"platial"},"data_attributes":null,"calculation_params":null,"icon_link":null,"link":"http://geocommons.com/overlays/46093.json","extent":[106.799,-6.23615,106.804,-6.22822],"geometry_types":["point"],"unique_name":null,"name":"\nMy Location :) Jakarta\n","feature_count":12,"description":"\nA Map by Mahardi\n\nGw Dimana ya???\n","next_feature":null,"is_raster":false,"short_classification":"Y","stats":{},"features":[{"properties":{"name":null,"description":"Posted by Mahardi<a title=\"Built for Community Mapping\" href=\"http://www.platial.com\"><img src=\"http://media.geocommons.com/platial/images/logotype_small.jpg\"></a>","id":"a6ep9i7tuvj0"},"type":"Feature","geometry":{"type":"Point","coordinates":[106.79925,-6.23517]}},{"properties":{"name":null,"description":"Posted by Mahardi<a title=\"Built for Community Mapping\" href=\"http://www.platial.com\"><img src=\"http://media.geocommons.com/platial/images/logotype_small.jpg\"></a>","id":"a6ep9ilhe7az"},"type":"Feature","geometry":{"type":"Point","coordinates":[106.79925,-6.23517]}},{"properties":{"name":null,"description":"Posted by Mahardi<a title=\"Built for Community Mapping\" href=\"http://www.platial.com\"><img src=\"http://media.geocommons.com/platial/images/logotype_small.jpg\"></a>","id":"a6ep9iknmjyu"},"type":"Feature","geometry":{"type":"Point","coordinates":[106.79925,-6.23517]}},{"properties":{"name":null,"description":"Posted by Mahardi<a title=\"Built for Community Mapping\" href=\"http://www.platial.com\"><img src=\"http://media.geocommons.com/platial/images/logotype_small.jpg\"></a>","id":"a6ep9ii29fe4"},"type":"Feature","geometry":{"type":"Point","coordinates":[106.79925,-6.23517]}},{"properties":{"name":null,"description":"Posted by Mahardi<a title=\"Built for Community Mapping\" href=\"http://www.platial.com\"><img src=\"http://media.geocommons.com/platial/images/logotype_small.jpg\"></a>","id":"a6ep9i5tamc0"},"type":"Feature","geometry":{"type":"Point","coordinates":[106.79925,-6.23517]}},{"properties":{"name":null,"description":"Posted by Mahardi<a title=\"Built for Community Mapping\" href=\"http://www.platial.com\"><img src=\"http://media.geocommons.com/platial/images/logotype_small.jpg\"></a>","id":"a6ep9i84u0lq"},"type":"Feature","geometry":{"type":"Point","coordinates":[106.79925,-6.23517]}},{"properties":{"name":null,"description":"Posted by Mahardi<a title=\"Built for Community Mapping\" href=\"http://www.platial.com\"><img src=\"http://media.geocommons.com/platial/images/logotype_small.jpg\"></a>","id":"a6ep9idg0uu2"},"type":"Feature","geometry":{"type":"Point","coordinates":[106.79925,-6.23517]}},{"properties":{"name":null,"description":"Posted by Mahardi<a title=\"Built for Community Mapping\" href=\"http://www.platial.com\"><img src=\"http://media.geocommons.com/platial/images/logotype_small.jpg\"></a>","id":"a6ep9ibvus9s"},"type":"Feature","geometry":{"type":"Point","coordinates":[106.80413,-6.22822]}},{"properties":{"name":null,"description":"Posted by Mahardi<a title=\"Built for Community Mapping\" href=\"http://www.platial.com\"><img src=\"http://media.geocommons.com/platial/images/logotype_small.jpg\"></a>","id":"a6ep9ig7w68m"},"type":"Feature","geometry":{"type":"Point","coordinates":[106.7992,-6.23615]}},{"properties":{"name":null,"description":"Posted by Mahardi<a title=\"Built for Community Mapping\" href=\"http://www.platial.com\"><img src=\"http://media.geocommons.com/platial/images/logotype_small.jpg\"></a>","id":"a6ep9ifgh54x"},"type":"Feature","geometry":{"type":"Point","coordinates":[106.79925,-6.23517]}},{"properties":{"name":null,"description":"Posted by Mahardi<a title=\"Built for Community Mapping\" href=\"http://www.platial.com\"><img src=\"http://media.geocommons.com/platial/images/logotype_small.jpg\"></a>","id":"a6ep9idx3xc3"},"type":"Feature","geometry":{"type":"Point","coordinates":[106.79925,-6.23517]}},{"properties":{"name":null,"description":"Posted by Mahardi<a title=\"Built for Community Mapping\" href=\"http://www.platial.com\"><img src=\"http://media.geocommons.com/platial/images/logotype_small.jpg\"></a>","id":"a6ep9i9gw38j"},"type":"Feature","geometry":{"type":"Point","coordinates":[106.79925,-6.23517]}}],"is_temporal":false,"author":{"url":"http://www.platial.com/map/34859","metadata":null,"contact_name":"mahardi","contact_address":null,"source":"platial:mahardi","contact_phone":null},"source":"http://www.platial.com/map/34859","pagination":{"sort":null,"start":0,"total":12,"limit":1000000},"state":"complete","tags":"platial,platial:id=34859,platial:user=mahardi","published":"2010-04-26T16:00:00Z","id":46093}