{"type":"FeatureCollection","data_type":"Dataset","url_type":null,"permissions":[{"permissions":{"download":true,"view":true},"group_id":"everyone"}],"classification":null,"title":"\nelmanoo's places\n","count":12,"stream_id":46196,"contributor":{"url":"http://geocommons.com/users/11444","name":"platial"},"data_attributes":null,"calculation_params":null,"icon_link":null,"link":"http://geocommons.com/overlays/46196.json","extent":[14.1724,49.838,16.6426,57.8221],"geometry_types":["point"],"unique_name":null,"name":"\nelmanoo's places\n","feature_count":12,"description":"\nA Map by Elmanoo\n\n\n","next_feature":null,"is_raster":false,"short_classification":"Y","stats":{},"features":[{"properties":{"name":null,"description":"Posted by Elmanoo<a title=\"Built for Community Mapping\" href=\"http://www.platial.com\"><img src=\"http://media.geocommons.com/platial/images/logotype_small.jpg\"></a>","id":"a6djirgv3eh8"},"type":"Feature","geometry":{"type":"Point","coordinates":[14.96887,57.67038]}},{"properties":{"name":null,"description":"Posted by Elmanoo<a title=\"Built for Community Mapping\" href=\"http://www.platial.com\"><img src=\"http://media.geocommons.com/platial/images/logotype_small.jpg\"></a>","id":"a6djir5544or"},"type":"Feature","geometry":{"type":"Point","coordinates":[14.69833,57.64834]}},{"properties":{"name":null,"description":"Posted by Elmanoo<a title=\"Built for Community Mapping\" href=\"http://www.platial.com\"><img src=\"http://media.geocommons.com/platial/images/logotype_small.jpg\"></a>","id":"a6djir1l98ff"},"type":"Feature","geometry":{"type":"Point","coordinates":[15.844,57.49701]}},{"properties":{"name":null,"description":"Posted by Elmanoo<a title=\"Built for Community Mapping\" href=\"http://www.platial.com\"><img src=\"http://media.geocommons.com/platial/images/logotype_small.jpg\"></a>","id":"a6djire9nan6"},"type":"Feature","geometry":{"type":"Point","coordinates":[16.34937,56.67962]}},{"properties":{"name":null,"description":"Posted by Elmanoo<a title=\"Built for Community Mapping\" href=\"http://www.platial.com\"><img src=\"http://media.geocommons.com/platial/images/logotype_small.jpg\"></a>","id":"a6djirf2gffu"},"type":"Feature","geometry":{"type":"Point","coordinates":[15.07324,57.43017]}},{"properties":{"name":null,"description":"Posted by Elmanoo<a title=\"Built for Community Mapping\" href=\"http://www.platial.com\"><img src=\"http://media.geocommons.com/platial/images/logotype_small.jpg\"></a>","id":"a6djire4dal0"},"type":"Feature","geometry":{"type":"Point","coordinates":[14.66675,57.38578]}},{"properties":{"name":null,"description":"Posted by Elmanoo<a title=\"Built for Community Mapping\" href=\"http://www.platial.com\"><img src=\"http://media.geocommons.com/platial/images/logotype_small.jpg\"></a>","id":"a6djirgm4ioi"},"type":"Feature","geometry":{"type":"Point","coordinates":[14.83154,56.873]}},{"properties":{"name":null,"description":"Posted by Elmanoo<a title=\"Built for Community Mapping\" href=\"http://www.platial.com\"><img src=\"http://media.geocommons.com/platial/images/logotype_small.jpg\"></a>","id":"a6djirgnhk6x"},"type":"Feature","geometry":{"type":"Point","coordinates":[16.45821,57.26605]}},{"properties":{"name":null,"description":"Posted by Elmanoo<a title=\"Built for Community Mapping\" href=\"http://www.platial.com\"><img src=\"http://media.geocommons.com/platial/images/logotype_small.jpg\"></a>","id":"a6djirgccmm2"},"type":"Feature","geometry":{"type":"Point","coordinates":[14.17236,57.75987]}},{"properties":{"name":null,"description":"Posted by Elmanoo<a title=\"Built for Community Mapping\" href=\"http://www.platial.com\"><img src=\"http://media.geocommons.com/platial/images/logotype_small.jpg\"></a>","id":"a6djirb6axrd"},"type":"Feature","geometry":{"type":"Point","coordinates":[16.64257,57.82209]}},{"properties":{"name":null,"description":"Posted by Elmanoo<a title=\"Built for Community Mapping\" href=\"http://www.platial.com\"><img src=\"http://media.geocommons.com/platial/images/logotype_small.jpg\"></a>","id":"a6djir7ev13g"},"type":"Feature","geometry":{"type":"Point","coordinates":[16.64257,57.82209]}},{"properties":{"name":null,"description":"Posted by Elmanoo<a title=\"Built for Community Mapping\" href=\"http://www.platial.com\"><img src=\"http://media.geocommons.com/platial/images/logotype_small.jpg\"></a>","id":"a6djir942qma"},"type":"Feature","geometry":{"type":"Point","coordinates":[15.38086,49.83798]}}],"is_temporal":false,"author":{"url":"http://www.platial.com/map/254074","metadata":null,"contact_name":"elmanoo","contact_address":null,"source":"platial:elmanoo","contact_phone":null},"source":"http://www.platial.com/map/254074","pagination":{"sort":null,"start":0,"total":12,"limit":1000000},"state":"complete","tags":"platial,platial:id=254074,platial:user=elmanoo","published":"2010-04-26T16:00:00Z","id":46196}