{"type":"FeatureCollection","data_type":"Dataset","url_type":null,"permissions":[{"permissions":{"download":true,"view":true},"group_id":"everyone"}],"classification":null,"title":"\nSunshine Map-- Spreading the Rays!\n","count":10,"stream_id":46365,"contributor":{"url":"http://geocommons.com/users/11444","name":"platial"},"data_attributes":null,"calculation_params":null,"icon_link":null,"link":"http://geocommons.com/overlays/46365.json","extent":[-118.213,38.6898,-75.9629,48.3124],"geometry_types":["point"],"unique_name":null,"name":"\nSunshine Map-- Spreading the Rays!\n","feature_count":10,"description":"\nA Map by Andilynn\n\n\n","next_feature":null,"is_raster":false,"short_classification":"Y","stats":{},"features":[{"properties":{"name":null,"description":"Posted by Andilynn<a title=\"Built for Community Mapping\" href=\"http://www.platial.com\"><img src=\"http://media.geocommons.com/platial/images/logotype_small.jpg\"></a>","id":"a6mspzof9ue5"},"type":"Feature","geometry":{"type":"Point","coordinates":[-117.73087,48.28685]}},{"properties":{"name":null,"description":"Posted by Andilynn<a title=\"Built for Community Mapping\" href=\"http://www.platial.com\"><img src=\"http://media.geocommons.com/platial/images/logotype_small.jpg\"></a>","id":"a6mspzg51btk"},"type":"Feature","geometry":{"type":"Point","coordinates":[-75.96291,42.12216]}},{"properties":{"name":null,"description":"Posted by Andilynn<a title=\"Built for Community Mapping\" href=\"http://www.platial.com\"><img src=\"http://media.geocommons.com/platial/images/logotype_small.jpg\"></a>","id":"a6mspzbitjnx"},"type":"Feature","geometry":{"type":"Point","coordinates":[-77.68433,38.6898]}},{"properties":{"name":null,"description":"Posted by Andilynn<a title=\"Built for Community Mapping\" href=\"http://www.platial.com\"><img src=\"http://media.geocommons.com/platial/images/logotype_small.jpg\"></a>","id":"a6mspzangk6b"},"type":"Feature","geometry":{"type":"Point","coordinates":[-111.44531,39.02772]}},{"properties":{"name":null,"description":"Posted by Andilynn<a title=\"Built for Community Mapping\" href=\"http://www.platial.com\"><img src=\"http://media.geocommons.com/platial/images/logotype_small.jpg\"></a>","id":"a6mspzedgcyf"},"type":"Feature","geometry":{"type":"Point","coordinates":[-111.44531,39.02772]}},{"properties":{"name":null,"description":"Posted by AndilynnCenterville, UT<a title=\"Built for Community Mapping\" href=\"http://www.platial.com\"><img src=\"http://media.geocommons.com/platial/images/logotype_small.jpg\"></a>","id":"a6mspzcffgs5"},"type":"Feature","geometry":{"type":"Point","coordinates":[-111.87653,40.9104]}},{"properties":{"name":null,"description":"Posted by Andilynn<a title=\"Built for Community Mapping\" href=\"http://www.platial.com\"><img src=\"http://media.geocommons.com/platial/images/logotype_small.jpg\"></a>","id":"a6mspzacuo4p"},"type":"Feature","geometry":{"type":"Point","coordinates":[-118.21289,47.5172]}},{"properties":{"name":null,"description":"Posted by Andilynn<a title=\"Built for Community Mapping\" href=\"http://www.platial.com\"><img src=\"http://media.geocommons.com/platial/images/logotype_small.jpg\"></a>","id":"a6mspz8vklzn"},"type":"Feature","geometry":{"type":"Point","coordinates":[-117.71851,48.31243]}},{"properties":{"name":null,"description":"Posted by Andilynn<a title=\"Built for Community Mapping\" href=\"http://www.platial.com\"><img src=\"http://media.geocommons.com/platial/images/logotype_small.jpg\"></a>","id":"a6mspzhlj96m"},"type":"Feature","geometry":{"type":"Point","coordinates":[-77.68433,38.6898]}},{"properties":{"name":null,"description":"Posted by Andilynn<a title=\"Built for Community Mapping\" href=\"http://www.platial.com\"><img src=\"http://media.geocommons.com/platial/images/logotype_small.jpg\"></a>","id":"a6mspzf4p7v8"},"type":"Feature","geometry":{"type":"Point","coordinates":[-75.96291,42.12216]}}],"is_temporal":false,"author":{"url":"http://www.platial.com/map/41020","metadata":null,"contact_name":"andilynn","contact_address":null,"source":"platial:andilynn","contact_phone":null},"source":"http://www.platial.com/map/41020","pagination":{"sort":null,"start":0,"total":10,"limit":1000000},"state":"complete","tags":"platial,platial:id=41020,platial:user=andilynn","published":"2010-04-26T16:00:00Z","id":46365}