{"type":"FeatureCollection","data_type":"Dataset","url_type":null,"permissions":[{"permissions":{"download":true,"view":true},"group_id":"everyone"}],"classification":null,"title":"\nThe Shwagnificent Take Over\n","count":11,"stream_id":47469,"contributor":{"url":"http://geocommons.com/users/11444","name":"platial"},"data_attributes":null,"calculation_params":null,"icon_link":null,"link":"http://geocommons.com/overlays/47469.json","extent":[-93.1256,29.9716,36.1231,38.8183],"geometry_types":["point"],"unique_name":null,"name":"\nThe Shwagnificent Take Over\n","feature_count":11,"description":"\nA Map by Mixtasixta\n\n\n","next_feature":null,"is_raster":false,"short_classification":"Y","stats":{},"features":[{"properties":{"name":null,"description":"Posted by Mixtasixta<a title=\"Built for Community Mapping\" href=\"http://www.platial.com\"><img src=\"http://media.geocommons.com/platial/images/logotype_small.jpg\"></a>","id":"a6dssuj9llv3"},"type":"Feature","geometry":{"type":"Point","coordinates":[-92.02286,30.21725]}},{"properties":{"name":null,"description":"Posted by Mixtasixta<a title=\"Built for Community Mapping\" href=\"http://www.platial.com\"><img src=\"http://media.geocommons.com/platial/images/logotype_small.jpg\"></a>","id":"a6dssufdyp8g"},"type":"Feature","geometry":{"type":"Point","coordinates":[-91.99127,30.21636]}},{"properties":{"name":null,"description":"Posted by Mixtasixta<a title=\"Built for Community Mapping\" href=\"http://www.platial.com\"><img src=\"http://media.geocommons.com/platial/images/logotype_small.jpg\"></a>","id":"a6dssufnf4xa"},"type":"Feature","geometry":{"type":"Point","coordinates":[-93.12561,30.18312]}},{"properties":{"name":null,"description":"Posted by Mixtasixta<a title=\"Built for Community Mapping\" href=\"http://www.platial.com\"><img src=\"http://media.geocommons.com/platial/images/logotype_small.jpg\"></a>","id":"a6dssuizynln"},"type":"Feature","geometry":{"type":"Point","coordinates":[-91.82236,30.00727]}},{"properties":{"name":null,"description":"Posted by Mixtasixta<a title=\"Built for Community Mapping\" href=\"http://www.platial.com\"><img src=\"http://media.geocommons.com/platial/images/logotype_small.jpg\"></a>","id":"a6dssuofsfu2"},"type":"Feature","geometry":{"type":"Point","coordinates":[-92.12997,29.97159]}},{"properties":{"name":null,"description":"Posted by Mixtasixta<a title=\"Built for Community Mapping\" href=\"http://www.platial.com\"><img src=\"http://media.geocommons.com/platial/images/logotype_small.jpg\"></a>","id":"a6dssuie6uy6"},"type":"Feature","geometry":{"type":"Point","coordinates":[-92.12997,29.97159]}},{"properties":{"name":null,"description":"Posted by Mixtasixta<a title=\"Built for Community Mapping\" href=\"http://www.platial.com\"><img src=\"http://media.geocommons.com/platial/images/logotype_small.jpg\"></a>","id":"a6dssuqh5r51"},"type":"Feature","geometry":{"type":"Point","coordinates":[-92.30576,30.00727]}},{"properties":{"name":null,"description":"Posted by Mixtasixta<a title=\"Built for Community Mapping\" href=\"http://www.platial.com\"><img src=\"http://media.geocommons.com/platial/images/logotype_small.jpg\"></a>","id":"a6dssunh2pdo"},"type":"Feature","geometry":{"type":"Point","coordinates":[-76.99219,38.57394]}},{"properties":{"name":null,"description":"Posted by Mixtasixta<a title=\"Built for Community Mapping\" href=\"http://www.platial.com\"><img src=\"http://media.geocommons.com/platial/images/logotype_small.jpg\"></a>","id":"a6dssui1wf5y"},"type":"Feature","geometry":{"type":"Point","coordinates":[-76.92078,38.81831]}},{"properties":{"name":null,"description":"Posted by Mixtasixta<a title=\"Built for Community Mapping\" href=\"http://www.platial.com\"><img src=\"http://media.geocommons.com/platial/images/logotype_small.jpg\"></a>","id":"a6dssui9awzt"},"type":"Feature","geometry":{"type":"Point","coordinates":[36.12305,33.72434]}},{"properties":{"name":null,"description":"Posted by Mixtasixta<a title=\"Built for Community Mapping\" href=\"http://www.platial.com\"><img src=\"http://media.geocommons.com/platial/images/logotype_small.jpg\"></a>","id":"a6dssulmbuh6"},"type":"Feature","geometry":{"type":"Point","coordinates":[36.12305,33.72434]}}],"is_temporal":false,"author":{"url":"http://www.platial.com/map/46878","metadata":null,"contact_name":"mixtasixta","contact_address":null,"source":"platial:mixtasixta","contact_phone":null},"source":"http://www.platial.com/map/46878","pagination":{"sort":null,"start":0,"total":11,"limit":1000000},"state":"complete","tags":"platial,platial:id=46878,platial:user=mixtasixta","published":"2010-04-27T16:00:00Z","id":47469}