{"type":"FeatureCollection","data_type":"Dataset","url_type":null,"permissions":[{"permissions":{"download":true,"view":true},"group_id":"everyone"}],"classification":null,"title":"\ntravel boyz\n","count":10,"stream_id":49165,"contributor":{"url":"http://geocommons.com/users/11444","name":"platial"},"data_attributes":null,"calculation_params":null,"icon_link":null,"link":"http://geocommons.com/overlays/49165.json","extent":[-118.257,25.6811,-74.0039,40.8138],"geometry_types":["point"],"unique_name":null,"name":"\ntravel boyz\n","feature_count":10,"description":"\nA Map by 1984doe\n\ngmg\n","next_feature":null,"is_raster":false,"short_classification":"Y","stats":{},"features":[{"properties":{"name":null,"description":"Posted by 1984doe<a title=\"Built for Community Mapping\" href=\"http://www.platial.com\"><img src=\"http://media.geocommons.com/platial/images/logotype_small.jpg\"></a>","id":"a6lrwxe0xsh3"},"type":"Feature","geometry":{"type":"Point","coordinates":[-77.16797,39.02772]}},{"properties":{"name":null,"description":"Posted by 1984doe<a title=\"Built for Community Mapping\" href=\"http://www.platial.com\"><img src=\"http://media.geocommons.com/platial/images/logotype_small.jpg\"></a>","id":"a6lrwxfc9w94"},"type":"Feature","geometry":{"type":"Point","coordinates":[-77.7832,37.64903]}},{"properties":{"name":null,"description":"Posted by 1984doe<a title=\"Built for Community Mapping\" href=\"http://www.platial.com\"><img src=\"http://media.geocommons.com/platial/images/logotype_small.jpg\"></a>","id":"a6lrwxmh6sm3"},"type":"Feature","geometry":{"type":"Point","coordinates":[-80.24414,25.68114]}},{"properties":{"name":null,"description":"Posted by 1984doe<a title=\"Built for Community Mapping\" href=\"http://www.platial.com\"><img src=\"http://media.geocommons.com/platial/images/logotype_small.jpg\"></a>","id":"a6lrwx8q8idu"},"type":"Feature","geometry":{"type":"Point","coordinates":[-118.25684,34.16182]}},{"properties":{"name":null,"description":"Posted by 1984doe<a title=\"Built for Community Mapping\" href=\"http://www.platial.com\"><img src=\"http://media.geocommons.com/platial/images/logotype_small.jpg\"></a>","id":"a6lrwxddcyxr"},"type":"Feature","geometry":{"type":"Point","coordinates":[-80.12878,25.94817]}},{"properties":{"name":null,"description":"Posted by 1984doe<a title=\"Built for Community Mapping\" href=\"http://www.platial.com\"><img src=\"http://media.geocommons.com/platial/images/logotype_small.jpg\"></a>","id":"a6lrwxhepknp"},"type":"Feature","geometry":{"type":"Point","coordinates":[-78.57422,36.03133]}},{"properties":{"name":null,"description":"Posted by 1984doe<a title=\"Built for Community Mapping\" href=\"http://www.platial.com\"><img src=\"http://media.geocommons.com/platial/images/logotype_small.jpg\"></a>","id":"a6lrwxh8cvcs"},"type":"Feature","geometry":{"type":"Point","coordinates":[-74.00391,40.81381]}},{"properties":{"name":null,"description":"Posted by 1984doe<a title=\"Built for Community Mapping\" href=\"http://www.platial.com\"><img src=\"http://media.geocommons.com/platial/images/logotype_small.jpg\"></a>","id":"a6lrwxlt4yud"},"type":"Feature","geometry":{"type":"Point","coordinates":[-75.19043,40.11169]}},{"properties":{"name":null,"description":"Posted by 1984doe<a title=\"Built for Community Mapping\" href=\"http://www.platial.com\"><img src=\"http://media.geocommons.com/platial/images/logotype_small.jpg\"></a>","id":"a6lrwxb6h3wb"},"type":"Feature","geometry":{"type":"Point","coordinates":[-79.62891,34.66936]}},{"properties":{"name":null,"description":"Posted by 1984doe<a title=\"Built for Community Mapping\" href=\"http://www.platial.com\"><img src=\"http://media.geocommons.com/platial/images/logotype_small.jpg\"></a>","id":"a6lrwxaezo9s"},"type":"Feature","geometry":{"type":"Point","coordinates":[-84.375,33.79741]}}],"is_temporal":false,"author":{"url":"http://www.platial.com/map/47416","metadata":null,"contact_name":"1984doe","contact_address":null,"source":"platial:1984doe","contact_phone":null},"source":"http://www.platial.com/map/47416","pagination":{"sort":null,"start":0,"total":10,"limit":1000000},"state":"complete","tags":"platial,platial:id=47416,platial:user=1984doe","published":"2010-04-27T16:00:00Z","id":49165}