{"type":"FeatureCollection","state":"complete","icon_link":null,"title":"L.A. Gray Lad Pad","count":9,"geometry_types":["point"],"unique_name":null,"url":"http://dotnet.slcgov.com/Police/TrafficAccidents/","pagination":{"sort":null,"start":0,"limit":1000000,"total":9},"feature_count":9,"data_type":"Dataset","stats":{"latitude":{"max":40.78,"mean":38.3586777777778,"stdev":6.88826843150327,"median":40.78,"min":20.0,"variance":47.4482419844445},"x":{"max":77.0,"mean":-82.8779555555556,"stdev":61.9772126399516,"median":-111.93,"min":-111.93,"variance":3841.17488661778},"y":{"max":40.78,"mean":38.3586777777778,"stdev":6.88826843150327,"median":40.78,"min":20.0,"variance":47.4482419844445},"end":{"max":18890,"mean":10703.8888888889,"stdev":4917.81205020191,"median":11134,"min":202,"variance":24184875.3611111},"start":{"max":18876,"mean":10692.2222222222,"stdev":4918.06114687937,"median":11120,"min":188,"variance":24187325.4444444},"index":{"max":8,"mean":4.0,"stdev":2.73861278752583,"median":4,"min":0,"variance":7.5},"longitude":{"max":77.0,"mean":-82.8779555555556,"stdev":61.9772126399516,"median":-111.93,"min":-111.93,"variance":3841.17488661778},"geoconfidence":{"max":0.736372,"mean":0.519994,"stdev":0.25077148998042,"median":0.666365,"min":0.140231,"variance":0.062886340187}},"next_feature":null,"is_raster":false,"link":"http://geocommons.com/overlays/496111.json","short_classification":"Y","name":"L.A. Gray Lad Pad","is_temporal":false,"description":"","permissions":[{"group_id":"everyone","permissions":{"download":true,"view":true}}],"classification":null,"published":"2015-08-29T13:17:58-04:00","extent":[-122.46,-30.0,159.0,53.4],"features":[{"properties":{"latitude":40.78,"x":-111.93,"georef":"Salt Lake City","y":40.78,"end":202,"start":188,"index":0,"xpath":null,"offset":null,"longitude":-111.93,"id":"a6200st50x6e","geoconfidence":0.736372,"style":"loc"},"type":"Feature","geometry":{"type":"Point","coordinates":[-111.93,40.78]}},{"properties":{"latitude":40.3981,"x":-75.9216,"georef":"SOUTH TEMPLE","y":40.3981,"end":10047,"start":10035,"index":1,"xpath":null,"offset":null,"longitude":-75.9216,"id":"a6200sk8zib2","geoconfidence":0.140231,"style":"loc"},"type":"Feature","geometry":{"type":"Point","coordinates":[-75.9216,40.3981]}},{"properties":{"latitude":40.78,"x":-111.93,"georef":"Salt Lake City","y":40.78,"end":13311,"start":13297,"index":2,"xpath":null,"offset":null,"longitude":-111.93,"id":"a6200sy13200","geoconfidence":0.666365,"style":"loc"},"type":"Feature","geometry":{"type":"Point","coordinates":[-111.93,40.78]}},{"properties":{"latitude":40.15,"georef":"TROOPER","x":-75.4,"y":40.15,"end":10690,"start":10683,"xpath":null,"index":3,"longitude":-75.4,"offset":null,"id":"a6200sw6nvb6","geoconfidence":0.196696,"style":"loc"},"type":"Feature","geometry":{"type":"Point","coordinates":[-75.4,40.15]}},{"properties":{"latitude":40.78,"georef":"Salt Lake City","x":-111.93,"y":40.78,"end":11134,"start":11120,"xpath":null,"index":4,"longitude":-111.93,"offset":null,"id":"a6200sounoho","geoconfidence":0.666365,"style":"loc"},"type":"Feature","geometry":{"type":"Point","coordinates":[-111.93,40.78]}},{"properties":{"latitude":40.78,"georef":"Salt Lake City","x":-111.93,"y":40.78,"end":8288,"start":8274,"xpath":null,"index":5,"longitude":-111.93,"offset":null,"id":"a6200stz22ay","geoconfidence":0.67284,"style":"loc"},"type":"Feature","geometry":{"type":"Point","coordinates":[-111.93,40.78]}},{"properties":{"latitude":20.0,"x":77.0,"georef":"IN","y":20.0,"end":11632,"start":11630,"index":6,"xpath":null,"offset":null,"longitude":77.0,"id":"a6200sivlgze","geoconfidence":0.22824,"style":"loc"},"type":"Feature","geometry":{"type":"Point","coordinates":[77.0,20.0]}},{"properties":{"latitude":40.78,"x":-111.93,"georef":"Salt Lake City","y":40.78,"end":12141,"start":12127,"index":7,"xpath":null,"offset":null,"longitude":-111.93,"id":"a6200spb0wep","geoconfidence":0.666365,"style":"loc"},"type":"Feature","geometry":{"type":"Point","coordinates":[-111.93,40.78]}},{"properties":{"latitude":40.78,"georef":"Salt Lake City","x":-111.93,"y":40.78,"end":18890,"start":18876,"xpath":null,"index":8,"longitude":-111.93,"offset":null,"id":"a6200sn6pscw","geoconfidence":0.706472,"style":"loc"},"type":"Feature","geometry":{"type":"Point","coordinates":[-111.93,40.78]}}],"url_type":"metacarta","author":{"metadata":"","url":"","contact_name":"","contact_address":"","contact_phone":"","source":""},"source":"","stream_id":496111,"tags":"sites,solar","contributor":{"url":"http://geocommons.com/users/108887","name":"padist"},"id":496111,"data_attributes":null,"calculation_params":null}