{"type":"FeatureCollection","data_type":"Dataset","url_type":null,"permissions":[{"permissions":{"download":true,"view":true},"group_id":"everyone"}],"classification":null,"title":"\nmamapatricia's places\n","count":9,"stream_id":49979,"contributor":{"url":"http://geocommons.com/users/11444","name":"platial"},"data_attributes":null,"calculation_params":null,"icon_link":null,"link":"http://geocommons.com/overlays/49979.json","extent":[-83.2151,41.4605,-81.3618,42.5498],"geometry_types":["point"],"unique_name":null,"name":"\nmamapatricia's places\n","feature_count":9,"description":"\nA Map by Mamapatricia\n\n\n","next_feature":null,"is_raster":false,"short_classification":"Y","stats":{},"features":[{"properties":{"name":null,"description":"Posted by Mamapatricia<a title=\"Built for Community Mapping\" href=\"http://www.platial.com\"><img src=\"http://media.geocommons.com/platial/images/logotype_small.jpg\"></a>","id":"a6bi0knynq67"},"type":"Feature","geometry":{"type":"Point","coordinates":[-82.97699,42.54701]}},{"properties":{"name":null,"description":"Posted by Mamapatricia<a title=\"Built for Community Mapping\" href=\"http://www.platial.com\"><img src=\"http://media.geocommons.com/platial/images/logotype_small.jpg\"></a>","id":"a6bi0kiaex6b"},"type":"Feature","geometry":{"type":"Point","coordinates":[-83.02321,42.54982]}},{"properties":{"name":null,"description":"Posted by Mamapatricia<a title=\"Built for Community Mapping\" href=\"http://www.platial.com\"><img src=\"http://media.geocommons.com/platial/images/logotype_small.jpg\"></a>","id":"a6bi0kh3gay0"},"type":"Feature","geometry":{"type":"Point","coordinates":[-83.02248,42.54826]}},{"properties":{"name":null,"description":"Posted by Mamapatricia<a title=\"Built for Community Mapping\" href=\"http://www.platial.com\"><img src=\"http://media.geocommons.com/platial/images/logotype_small.jpg\"></a>","id":"a6bi0ko9owb1"},"type":"Feature","geometry":{"type":"Point","coordinates":[-83.02248,42.54826]}},{"properties":{"name":null,"description":"Posted by Mamapatricia<a title=\"Built for Community Mapping\" href=\"http://www.platial.com\"><img src=\"http://media.geocommons.com/platial/images/logotype_small.jpg\"></a>","id":"a6bi0knrz87a"},"type":"Feature","geometry":{"type":"Point","coordinates":[-83.21515,42.45806]}},{"properties":{"name":null,"description":"Posted by Mamapatricia<a title=\"Built for Community Mapping\" href=\"http://www.platial.com\"><img src=\"http://media.geocommons.com/platial/images/logotype_small.jpg\"></a>","id":"a6bi0kr1m9d9"},"type":"Feature","geometry":{"type":"Point","coordinates":[-81.36183,41.47517]}},{"properties":{"name":null,"description":"Posted by Mamapatricia<a title=\"Built for Community Mapping\" href=\"http://www.platial.com\"><img src=\"http://media.geocommons.com/platial/images/logotype_small.jpg\"></a>","id":"a6bi0ki0op0y"},"type":"Feature","geometry":{"type":"Point","coordinates":[-81.74167,41.47387]}},{"properties":{"name":null,"description":"Posted by Mamapatricia<a title=\"Built for Community Mapping\" href=\"http://www.platial.com\"><img src=\"http://media.geocommons.com/platial/images/logotype_small.jpg\"></a>","id":"a6bi0kg0upb2"},"type":"Feature","geometry":{"type":"Point","coordinates":[-81.36176,41.47505]}},{"properties":{"name":null,"description":"Posted by Mamapatricia<a title=\"Built for Community Mapping\" href=\"http://www.platial.com\"><img src=\"http://media.geocommons.com/platial/images/logotype_small.jpg\"></a>","id":"a6bi0kgrjd2u"},"type":"Feature","geometry":{"type":"Point","coordinates":[-81.71609,41.46055]}}],"is_temporal":false,"author":{"url":"http://www.platial.com/map/253766","metadata":null,"contact_name":"mamapatricia","contact_address":null,"source":"platial:mamapatricia","contact_phone":null},"source":"http://www.platial.com/map/253766","pagination":{"sort":null,"start":0,"total":9,"limit":1000000},"state":"complete","tags":"platial,platial:id=253766,platial:user=mamapatricia","published":"2010-04-28T16:00:00Z","id":49979}