{"type":"FeatureCollection","data_type":"Dataset","url_type":null,"permissions":[{"permissions":{"download":true,"view":true},"group_id":"everyone"}],"classification":null,"title":"test1","count":13,"stream_id":5063,"contributor":{"url":"http://geocommons.com/users/1726","name":"lukasz"},"data_attributes":null,"calculation_params":null,"icon_link":null,"link":"http://geocommons.com/overlays/5063.json","extent":[22.6871,51.2097,22.7067,51.2214],"geometry_types":["point"],"unique_name":null,"name":"test1","feature_count":13,"description":"","next_feature":null,"is_raster":false,"short_classification":"Y","stats":{"Id":{"max":0,"mean":0.0,"variance":0.0,"stdev":0.0,"min":0,"median":0}},"features":[{"properties":{"Id":0,"id":"a64svd2lpq1c"},"type":"Feature","geometry":{"type":"Point","coordinates":[22.6871250840818,51.2186280241196]}},{"properties":{"Id":0,"id":"a64svd3djkp9"},"type":"Feature","geometry":{"type":"Point","coordinates":[22.7032861453544,51.2187780107672]}},{"properties":{"Id":0,"id":"a64svctphbsn"},"type":"Feature","geometry":{"type":"Point","coordinates":[22.7041860652396,51.2153658145356]}},{"properties":{"Id":0,"id":"a64svct3almn"},"type":"Feature","geometry":{"type":"Point","coordinates":[22.6969117128338,51.2109412084331]}},{"properties":{"Id":0,"id":"a64svd3690cj"},"type":"Feature","geometry":{"type":"Point","coordinates":[22.6937994898974,51.2182530575008]}},{"properties":{"Id":0,"id":"a64svd69qqnu"},"type":"Feature","geometry":{"type":"Point","coordinates":[22.6937244965736,51.2211403004659]}},{"properties":{"Id":0,"id":"a64svcx8zdk4"},"type":"Feature","geometry":{"type":"Point","coordinates":[22.7018612722027,51.2157032844926]}},{"properties":{"Id":0,"id":"a64svd2vgb58"},"type":"Feature","geometry":{"type":"Point","coordinates":[22.7005863856986,51.209666321929]}},{"properties":{"Id":0,"id":"a64svd366mca"},"type":"Feature","geometry":{"type":"Point","coordinates":[22.6934620199404,51.2148033646073]}},{"properties":{"Id":0,"id":"a64svcr7v37d"},"type":"Feature","geometry":{"type":"Point","coordinates":[22.6885124605715,51.2164532177303]}},{"properties":{"Id":0,"id":"a64svcsoudn5"},"type":"Feature","geometry":{"type":"Point","coordinates":[22.706660844924,51.2203153739045]}},{"properties":{"Id":0,"id":"a64svd6ylwak"},"type":"Feature","geometry":{"type":"Point","coordinates":[22.699161512547,51.2214027770991]}},{"properties":{"Id":0,"id":"a64svd3qmn1x"},"type":"Feature","geometry":{"type":"Point","coordinates":[22.6993489958564,51.218178064177]}}],"is_temporal":false,"author":{"url":"","metadata":"","contact_name":"","contact_address":"","source":"","contact_phone":""},"source":"","pagination":{"sort":null,"start":0,"total":13,"limit":1000000},"state":"complete","tags":"test","published":"2014-08-11T05:11:30-04:00","id":5063}