{"type":"FeatureCollection","data_type":"Dataset","url_type":null,"permissions":[{"permissions":{"download":true,"view":true},"group_id":"everyone"}],"classification":null,"title":"Golden Gate Schools","count":3,"stream_id":51342,"contributor":{"url":"http://geocommons.com/users/13276","name":"oaklandnorth"},"data_attributes":null,"calculation_params":null,"icon_link":null,"link":"http://geocommons.com/overlays/51342.json","extent":[-122.285,37.8383,-122.274,37.8471],"geometry_types":["point"],"unique_name":null,"name":"Golden Gate Schools","feature_count":3,"description":"These are the three schools located within the geographic boundaries of the Golden Gate neighborhood.","next_feature":null,"is_raster":false,"short_classification":"Y","stats":{"geo_score":{"max":0.902,"mean":0.869666666666667,"variance":0.00313633333333333,"stdev":0.0560029761113937,"min":0.805,"median":0.902}},"features":[{"properties":{"city":"Oakland","zip":"94608","geo_score":0.902,"street":"6200 San Pablo Avenue","id":"a6a0lhvm9el1","geo_precision":"range","school":"Berkley Maynard Academy - Aspire Charter","state":"CA"},"type":"Feature","geometry":{"type":"Point","coordinates":[-122.284527,37.84522]}},{"properties":{"city":"Oakland","zip":"94608","geo_score":0.902,"street":"1086 Alcatraz Avenue","id":"a6a0lhyop0ql","geo_precision":"range","school":"Civicorps Elementary - Charter","state":"CA"},"type":"Feature","geometry":{"type":"Point","coordinates":[-122.283647,37.847084]}},{"properties":{"city":"Oakland","zip":"94608","geo_score":0.805,"street":"915 54th Street","id":"a6a0li2h9qs2","geo_precision":"range","school":"Santa Fe Elementary - OUSD","state":"CA"},"type":"Feature","geometry":{"type":"Point","coordinates":[-122.274333,37.838279]}}],"is_temporal":false,"author":{"url":"","metadata":"","contact_name":"Oakland North","contact_address":"staff@oaklandnorth.net","source":"Google","contact_phone":""},"source":"","pagination":{"sort":null,"start":0,"total":3,"limit":1000000},"state":"complete","tags":"","published":"2014-08-10T11:55:38-04:00","id":51342}