{"type":"FeatureCollection","data_type":"Dataset","url_type":null,"permissions":[{"permissions":{"download":true,"view":true},"group_id":"everyone"}],"classification":null,"title":"Target, Target Retail Locations, India, 2008","count":4,"stream_id":5447,"contributor":{"url":"http://geocommons.com/users/143","name":"jennifer"},"data_attributes":null,"calculation_params":null,"icon_link":null,"link":"http://geocommons.com/overlays/5447.json","extent":[76.6456,12.3028,77.6625,13.0464],"geometry_types":["point"],"unique_name":null,"name":"Target, Target Retail Locations, India, 2008","feature_count":4,"description":"","next_feature":null,"is_raster":false,"short_classification":"Y","stats":{"latitude":{"max":13.046437,"mean":12.81858675,"variance":0.119854182434917,"stdev":0.346199628010945,"min":12.302783,"median":12.97077},"longitude":{"max":77.662494,"mean":77.38693275,"variance":0.244678234658252,"stdev":0.494649607963306,"min":76.645602,"median":77.62524}},"features":[{"properties":{"city":"Mysore","latitude":12.302783,"country":"India","area":"","postalcode":"","longitude":76.645602,"id":"a62cjl1ji6ch"},"type":"Feature","geometry":{"type":"Point","coordinates":[76.645602,12.302783]}},{"properties":{"city":"Bangalore","latitude":12.954357,"country":"India","area":"Embassy Golf Links","postalcode":"","longitude":77.62524,"id":"a62cjl1w17dr"},"type":"Feature","geometry":{"type":"Point","coordinates":[77.62524,12.954357]}},{"properties":{"city":"North Bangalore","latitude":13.046437,"country":"India","area":"Embassy Manyata Business Park","postalcode":"","longitude":77.614395,"id":"a62cjlc199vb"},"type":"Feature","geometry":{"type":"Point","coordinates":[77.614395,13.046437]}},{"properties":{"city":"Bangalore","latitude":12.97077,"country":"India","area":"Embassy Prime","postalcode":"560 093","longitude":77.662494,"id":"a62cjl2d92m8"},"type":"Feature","geometry":{"type":"Point","coordinates":[77.662494,12.97077]}}],"is_temporal":false,"author":{"url":"http://www.target.com","metadata":"","contact_name":"","contact_address":"","source":"Target Corporate Website","contact_phone":""},"source":"http://www.target.com","pagination":{"sort":null,"start":0,"total":4,"limit":1000000},"state":"complete","tags":"","published":"2014-08-11T05:59:55-04:00","id":5447}