{"type":"FeatureCollection","data_type":"Dataset","url_type":null,"permissions":[{"permissions":{"download":true,"view":true},"group_id":"everyone"}],"classification":null,"title":"missing link.kmz","count":1,"stream_id":56068,"contributor":{"url":"http://geocommons.com/users/14154","name":"burgean"},"data_attributes":null,"calculation_params":null,"icon_link":null,"link":"http://geocommons.com/overlays/56068.json","extent":[4.45032,50.8664,4.45032,50.8664],"geometry_types":["point"],"unique_name":null,"name":"missing link.kmz","feature_count":1,"description":"","next_feature":null,"is_raster":false,"short_classification":"Y","stats":{},"features":[{"properties":{"name":"missing link","id":"a6lp44ryej5y"},"type":"Feature","geometry":{"type":"Point","coordinates":[4.45032431774352,50.8663671867184]}}],"is_temporal":false,"author":{"url":"","metadata":"","contact_name":"","contact_address":"","source":"","contact_phone":""},"source":"","pagination":{"sort":null,"start":0,"total":1,"limit":1000000},"state":"complete","tags":"","published":"2014-08-10T16:49:26-04:00","id":56068}