{"type":"FeatureCollection","data_type":"Dataset","url_type":null,"permissions":[{"permissions":{"download":true,"view":true},"group_id":"everyone"}],"classification":null,"title":"7-9 H","count":10,"stream_id":56461,"contributor":{"url":"http://geocommons.com/users/14002","name":"shazard"},"data_attributes":null,"calculation_params":null,"icon_link":null,"link":"http://geocommons.com/overlays/56461.json","extent":[-87.2408,14.022,-87.1889,14.1114],"geometry_types":["point"],"unique_name":null,"name":"7-9 H","feature_count":10,"description":"","next_feature":null,"is_raster":false,"short_classification":"Y","stats":{"latitude":{"max":14.1114,"mean":14.073237646,"variance":0.000667634697675382,"stdev":0.0258386280145712,"min":14.02202046,"median":14.0791},"longitude":{"max":-87.1889,"mean":-87.215267253,"variance":0.000314598732419146,"stdev":0.0177369313134811,"min":-87.2407521,"median":-87.2199},"frequency":{"max":9,"mean":7.6,"variance":0.711111111111111,"stdev":0.843274042711568,"min":7,"median":7}},"features":[{"properties":{"latitude":14.0840312,"neighborhood":"21 de Febrero","longitude":-87.2271827,"id":"a6dyez96lxwg","frequency":9},"type":"Feature","geometry":{"type":"Point","coordinates":[-87.2271827,14.0840312]}},{"properties":{"latitude":14.0425115,"neighborhood":"Altos del Loarque","longitude":-87.2071676,"id":"a6dyez87m2bo","frequency":7},"type":"Feature","geometry":{"type":"Point","coordinates":[-87.2071676,14.0425115]}},{"properties":{"latitude":14.0796525,"neighborhood":"Arturo Quezada","longitude":-87.2407521,"id":"a6dyezd4o7zv","frequency":8},"type":"Feature","geometry":{"type":"Point","coordinates":[-87.2407521,14.0796525]}},{"properties":{"latitude":14.1005,"neighborhood":"Ayestas","longitude":-87.2199,"id":"a6dyezof3is5","frequency":7},"type":"Feature","geometry":{"type":"Point","coordinates":[-87.2199,14.1005]}},{"properties":{"latitude":14.0736665,"neighborhood":"Flor del Campo","longitude":-87.2281226,"id":"a6dyezjj90tk","frequency":7},"type":"Feature","geometry":{"type":"Point","coordinates":[-87.2281226,14.0736665]}},{"properties":{"latitude":14.0661943,"neighborhood":"La Joya","longitude":-87.1927928,"id":"a6dyezdk8e6f","frequency":7},"type":"Feature","geometry":{"type":"Point","coordinates":[-87.1927928,14.0661943]}},{"properties":{"latitude":14.0733,"neighborhood":"Miraflores","longitude":-87.1889,"id":"a6dyezjpwwwl","frequency":9},"type":"Feature","geometry":{"type":"Point","coordinates":[-87.1889,14.0733]}},{"properties":{"latitude":14.0791,"neighborhood":"Venezuela","longitude":-87.2244,"id":"a6dyezfa60w1","frequency":7},"type":"Feature","geometry":{"type":"Point","coordinates":[-87.2244,14.0791]}},{"properties":{"latitude":14.02202046,"neighborhood":"Villa Nueva","longitude":-87.19625473,"id":"a6dyezn1xb0o","frequency":8},"type":"Feature","geometry":{"type":"Point","coordinates":[-87.19625473,14.02202046]}},{"properties":{"latitude":14.1114,"neighborhood":"Villa union","longitude":-87.2272,"id":"a6dyezgss8x2","frequency":7},"type":"Feature","geometry":{"type":"Point","coordinates":[-87.2272,14.1114]}}],"is_temporal":false,"author":{"url":"","metadata":"","contact_name":"","contact_address":"","source":"","contact_phone":""},"source":"","pagination":{"sort":null,"start":0,"total":10,"limit":1000000},"state":"complete","tags":"","published":"2014-08-10T17:26:25-04:00","id":56461}