{"type":"FeatureCollection","data_type":"Dataset","url_type":null,"permissions":[{"permissions":{"download":true,"view":true},"group_id":"everyone"}],"classification":null,"title":"AFSS Continuing Facilities","count":3,"stream_id":58954,"contributor":{"url":"http://geocommons.com/users/14796","name":"enome2"},"data_attributes":null,"calculation_params":null,"icon_link":null,"link":"http://geocommons.com/overlays/58954.json","extent":[-93.5814,25.7739,-78.6389,45.57],"geometry_types":["point"],"unique_name":null,"name":"AFSS Continuing Facilities","feature_count":3,"description":"","next_feature":null,"is_raster":false,"short_classification":"Y","stats":{"lat":{"max":45.57,"mean":35.7052766666667,"variance":97.9748257830333,"stdev":9.89822336497986,"min":25.77389,"median":35.77194},"long":{"max":-78.63889,"mean":-84.1380566666667,"variance":67.4869145833333,"stdev":8.21504197088081,"min":-93.58139,"median":-80.19389}},"features":[{"properties":{"afss continuing facilities":"Miami","id":"a6809i1fbxoe","lat":25.77389,"long":-80.19389,"state":"FL"},"type":"Feature","geometry":{"type":"Point","coordinates":[-80.19389,25.77389]}},{"properties":{"afss continuing facilities":"Princeton","id":"a6809icclfj7","lat":45.57,"long":-93.58139,"state":"MN"},"type":"Feature","geometry":{"type":"Point","coordinates":[-93.58139,45.57]}},{"properties":{"afss continuing facilities":"Raleigh","id":"a6809i32q50e","lat":35.77194,"long":-78.63889,"state":"NC"},"type":"Feature","geometry":{"type":"Point","coordinates":[-78.63889,35.77194]}}],"is_temporal":false,"author":{"url":"","metadata":"","contact_name":"","contact_address":"","source":"","contact_phone":""},"source":"","pagination":{"sort":null,"start":0,"total":3,"limit":1000000},"state":"complete","tags":"","published":"2014-08-10T20:31:11-04:00","id":58954}