{"type":"FeatureCollection","data_type":"Dataset","url_type":null,"permissions":[{"permissions":{"download":true,"view":true},"group_id":"everyone"}],"classification":null,"title":"Place 1","count":1,"stream_id":60324,"contributor":{"url":"http://geocommons.com/users/15128","name":"shann039"},"data_attributes":null,"calculation_params":null,"icon_link":null,"link":"http://geocommons.com/overlays/60324.json","extent":[-93.2432,44.9721,-93.2432,44.9721],"geometry_types":["point"],"unique_name":null,"name":"Place 1","feature_count":1,"description":"","next_feature":null,"is_raster":false,"short_classification":"Y","stats":{},"features":[{"properties":{"name":"Place 1","id":"a6h0m6uyytt7"},"type":"Feature","geometry":{"type":"Point","coordinates":[-93.2432493323196,44.9721362042473]}}],"is_temporal":false,"author":{"url":"","metadata":"","contact_name":"","contact_address":"","source":"","contact_phone":""},"source":"","pagination":{"sort":null,"start":0,"total":1,"limit":1000000},"state":"complete","tags":"","published":"2014-08-10T11:18:25-04:00","id":60324}