{"type":"FeatureCollection","data_type":"Dataset","url_type":null,"permissions":[{"permissions":{"download":true,"view":true},"group_id":"everyone"}],"classification":null,"title":"bolig3 (delete this)","count":4,"stream_id":6209,"contributor":{"url":"http://geocommons.com/users/2","name":"data"},"data_attributes":null,"calculation_params":null,"icon_link":null,"link":"http://geocommons.com/overlays/6209.json","extent":[11.4252,55.4227,12.2269,55.7435],"geometry_types":["point"],"unique_name":null,"name":"bolig3 (delete this)","feature_count":4,"description":"","next_feature":null,"is_raster":false,"short_classification":"Y","stats":{"GRID_CODE0":{"max":4.0,"mean":2.5,"variance":1.66666666666667,"stdev":1.29099444873581,"min":1.0,"median":3.0},"POINTID0":{"max":246.0,"mean":185.75,"variance":3214.91666666667,"stdev":56.7002351553031,"min":116.0,"median":214.0}},"features":[{"properties":{"GRID_CODE0":1.0,"POINTID0":116.0,"id":"a655rrol8qyt"},"type":"Feature","geometry":{"type":"Point","coordinates":[11.43906496,55.74354808]}},{"properties":{"GRID_CODE0":2.0,"POINTID0":167.0,"id":"a655rrpx9v16"},"type":"Feature","geometry":{"type":"Point","coordinates":[12.22693178,55.63546149]}},{"properties":{"GRID_CODE0":3.0,"POINTID0":214.0,"id":"a655rrlgu6y0"},"type":"Feature","geometry":{"type":"Point","coordinates":[11.42515644,55.5191134]}},{"properties":{"GRID_CODE0":4.0,"POINTID0":246.0,"id":"a655rrspwlge"},"type":"Feature","geometry":{"type":"Point","coordinates":[11.73533859,55.42268194]}}],"is_temporal":false,"author":{"url":null,"metadata":null,"contact_name":"","contact_address":"","source":null,"contact_phone":""},"source":null,"pagination":{"sort":null,"start":0,"total":4,"limit":1000000},"state":"complete","tags":"","published":"2014-08-11T07:10:41-04:00","id":6209}