{"type":"FeatureCollection","data_type":"Dataset","url_type":null,"permissions":[{"permissions":{"download":true,"view":true},"group_id":"everyone"}],"classification":null,"title":"csvtokml","count":5,"stream_id":62482,"contributor":{"url":"http://geocommons.com/users/1142","name":"maartenzam"},"data_attributes":null,"calculation_params":null,"icon_link":null,"link":"http://geocommons.com/overlays/62482.json","extent":[55.3953,24.0937,55.8492,24.2276],"geometry_types":["point"],"unique_name":null,"name":"csvtokml","feature_count":5,"description":"","next_feature":null,"is_raster":false,"short_classification":"Y","stats":{"latitude":{"max":24.22757232,"mean":24.175545774,"variance":0.00248822219293013,"stdev":0.0498820828848408,"min":24.09365571,"median":24.17993467},"longitude":{"max":55.84923183,"mean":55.629022442,"variance":0.0366395342419567,"stdev":0.191414561206708,"min":55.39525614,"median":55.64141943}},"features":[{"properties":{"latitude":24.17993467,"water_type":"Potable","consultant":"ABC","longitude":55.64141943,"objectid":"R1","id":"a6hhkur1p2dj","contractor":"XYZ"},"type":"Feature","geometry":{"type":"Point","coordinates":[55.64141943,24.17993467]}},{"properties":{"latitude":24.22757232,"water_type":"Potable","consultant":"ABC","longitude":55.77668218,"objectid":"R2","id":"a6hhkuuit41h","contractor":"XYZ"},"type":"Feature","geometry":{"type":"Point","coordinates":[55.77668218,24.22757232]}},{"properties":{"latitude":24.09365571,"water_type":"Potable","consultant":"ABC","longitude":55.48252263,"objectid":"R3","id":"a6hhkum3gd5i","contractor":"XYZ"},"type":"Feature","geometry":{"type":"Point","coordinates":[55.48252263,24.09365571]}},{"properties":{"latitude":24.19819278,"water_type":"Potable","consultant":"ABC","longitude":55.39525614,"objectid":"R4","id":"a6hhkuq4fsi2","contractor":"XYZ"},"type":"Feature","geometry":{"type":"Point","coordinates":[55.39525614,24.19819278]}},{"properties":{"latitude":24.17837339,"water_type":"Potable","consultant":"ABC","longitude":55.84923183,"objectid":"R5","id":"a6hhkuowalzb","contractor":"XYZ"},"type":"Feature","geometry":{"type":"Point","coordinates":[55.84923183,24.17837339]}}],"is_temporal":false,"author":{"url":"","metadata":"","contact_name":"","contact_address":"","source":"","contact_phone":""},"source":"","pagination":{"sort":null,"start":0,"total":5,"limit":1000000},"state":"complete","tags":"","published":"2014-08-10T14:33:21-04:00","id":62482}