{"type":"FeatureCollection","data_type":"Dataset","url_type":null,"permissions":[{"permissions":{"download":true,"view":true},"group_id":"everyone"}],"classification":null,"title":"Scores = 99-90 94158","count":4,"stream_id":64431,"contributor":{"url":"http://geocommons.com/users/16107","name":"shwiners"},"data_attributes":null,"calculation_params":null,"icon_link":null,"link":"http://geocommons.com/overlays/64431.json","extent":[-122.394,37.7694,-122.387,37.7755],"geometry_types":["point"],"unique_name":null,"name":"Scores = 99-90 94158","feature_count":4,"description":"","next_feature":null,"is_raster":false,"short_classification":"Y","stats":{"2. inspection score":{"max":98,"mean":96.5,"variance":3.66666666666667,"stdev":1.91485421551268,"min":94,"median":98}},"features":[{"properties":{"1. restaurant":"JELLY'S A DANCE CAFE","2. inspection score":94,"3. inspection date":"6/30/10","4. address":"PIER 50","id":"a624ejgkh499","6. state":"CA"},"type":"Feature","geometry":{"type":"Point","coordinates":[-122.3872947,37.7755122]}},{"properties":{"1. restaurant":"MISSION BAY CAFE","2. inspection score":98,"3. inspection date":"3/25/10","4. address":"550 TERRY FRANCOIS ST","id":"a624eje0b62i","6. state":"CA"},"type":"Feature","geometry":{"type":"Point","coordinates":[-122.38698,37.7694339]}},{"properties":{"1. restaurant":"PANERA BREAD","2. inspection score":96,"3. inspection date":"2/16/10","4. address":"301 KING ST #A","id":"a624ejdwfql6","6. state":"CA"},"type":"Feature","geometry":{"type":"Point","coordinates":[-122.394228,37.775519]}},{"properties":{"1. restaurant":"PHIL'Z COFFEE","2. inspection score":98,"3. inspection date":"2/16/10","4. address":"201 BERRY ST","id":"a624ej2frkjx","6. state":"CA"},"type":"Feature","geometry":{"type":"Point","coordinates":[-122.393429,37.775221]}}],"is_temporal":false,"author":{"url":"http://sf.everyblock.com","metadata":"","contact_name":"","contact_address":"","source":"Every Block","contact_phone":""},"source":"http://sf.everyblock.com","pagination":{"sort":null,"start":0,"total":4,"limit":1000000},"state":"complete","tags":"94158,restaurant inspections,san francisco","published":"2010-09-27T16:00:00Z","id":64431}