{"type":"FeatureCollection","data_type":"Dataset","url_type":null,"permissions":[{"permissions":{"download":true,"view":true},"group_id":"everyone"}],"classification":null,"title":"Gap Retail Stores in Hawaii","count":3,"stream_id":6543,"contributor":{"url":"http://geocommons.com/users/2","name":"data"},"data_attributes":null,"calculation_params":null,"icon_link":null,"link":"http://geocommons.com/overlays/6543.json","extent":[-157.942,20.6873,-156.439,21.3862],"geometry_types":["point"],"unique_name":null,"name":"Gap Retail Stores in Hawaii","feature_count":3,"description":"This dataset explores Gap, Inc. retail stores in Hawaii    \n      \n      From www.gap.com:\n      \n      It was the summer of 1969: Man took his first walk on the moon. Nearly 450,000 people gathered in upstate New York to witness the historic Woodstock concert. And Doris and Don Fisher opened the first Gap store in San Francisco.\n      \n      Today, Gap Inc. is one of the world's largest specialty retailers, with more than 3,100 stores and fiscal 2006 revenues of $15.9 billion. We operate four of the most recognized apparel brands in the world — Gap, Banana Republic, Old Navy and Piperlime. \n      \n      \n      \n      Store locator website: http://www.gap.com/customerService/storeLocator.do?mlink=5058,805241,3&amp;clink=805241\n      \n      Accessed on 17 December 2007\n","next_feature":null,"is_raster":false,"short_classification":"Y","stats":{"long0":{"max":-156.439372,"mean":-157.407951,"variance":0.706057576203007,"stdev":0.840272322644872,"min":-157.941724,"median":-157.842757},"lat0":{"max":21.386178,"mean":21.1209993333333,"variance":0.143432923350334,"stdev":0.378725393062486,"min":20.687257,"median":21.289563}},"features":[{"properties":{"Gap Store0":"ALA MOANA","id":"a64aogg0fn79","long0":-157.842757,"lat0":21.289563},"type":"Feature","geometry":{"type":"Point","coordinates":[-157.842757,21.289563]}},{"properties":{"Gap Store0":"PEARL RIDGE","id":"a64aog8av1fy","long0":-157.941724,"lat0":21.386178},"type":"Feature","geometry":{"type":"Point","coordinates":[-157.941724,21.386178]}},{"properties":{"Gap Store0":"SHOPS AT WAILEA","id":"a64aogfasg3d","long0":-156.439372,"lat0":20.687257},"type":"Feature","geometry":{"type":"Point","coordinates":[-156.439372,20.687257]}}],"is_temporal":false,"author":{"url":"","metadata":"","contact_name":"","contact_address":"","source":"","contact_phone":""},"source":"","pagination":{"sort":null,"start":0,"total":3,"limit":1000000},"state":"complete","tags":"","published":"2014-08-11T07:28:14-04:00","id":6543}