{"type":"FeatureCollection","data_type":"Dataset","url_type":null,"permissions":[{"permissions":{"download":true,"view":true},"group_id":"everyone"}],"classification":null,"title":" Bridges, Kabul Afghanistan ","count":24,"stream_id":6606,"contributor":{"url":"http://geocommons.com/users/2","name":"data"},"data_attributes":null,"calculation_params":null,"icon_link":null,"link":"http://geocommons.com/overlays/6606.json","extent":[69.1066,34.4579,69.2767,34.5317],"geometry_types":["point"],"unique_name":null,"name":" Bridges, Kabul Afghanistan ","feature_count":24,"description":"This dataset shows the locations of Bridges in Kabul, Afghanistan. This dataset was released in 2004 and was found on-line at http://www.aims.org.af/index.aspx in Shape file format. This point data is intended for use within the city of Kabul, Afghanistan. This dataset may be used by any individual interested in the locations of Bridges in Kabul, Afghanistan for humanitarian, civil, or educational purposes.","next_feature":null,"is_raster":false,"short_classification":"Y","stats":{"ID0":{"max":24.0,"mean":12.5,"variance":50.0,"stdev":7.07106781186548,"min":1.0,"median":13.0}},"features":[{"properties":{"id":"a62u8gr1h79v","ID0":1.0},"type":"Feature","geometry":{"type":"Point","coordinates":[69.20231334,34.53165209]}},{"properties":{"id":"a62u8gv3a49m","ID0":2.0},"type":"Feature","geometry":{"type":"Point","coordinates":[69.1905288,34.52056065]}},{"properties":{"id":"a62u8gw11xn2","ID0":3.0},"type":"Feature","geometry":{"type":"Point","coordinates":[69.18117764,34.51590765]}},{"properties":{"id":"a62u8gk049ih","ID0":4.0},"type":"Feature","geometry":{"type":"Point","coordinates":[69.17639793,34.51813193]}},{"properties":{"id":"a62u8gtfjgbf","ID0":5.0},"type":"Feature","geometry":{"type":"Point","coordinates":[69.1716532,34.51522192]}},{"properties":{"id":"a62u8gkfo5gd","ID0":6.0},"type":"Feature","geometry":{"type":"Point","coordinates":[69.16817634,34.51270317]}},{"properties":{"id":"a62u8gslriff","ID0":7.0},"type":"Feature","geometry":{"type":"Point","coordinates":[69.16386197,34.51095762]}},{"properties":{"id":"a62u8guehu70","ID0":8.0},"type":"Feature","geometry":{"type":"Point","coordinates":[69.15544415,34.50331739]}},{"properties":{"id":"a62u8gszyjxc","ID0":9.0},"type":"Feature","geometry":{"type":"Point","coordinates":[69.15354777,34.50445764]}},{"properties":{"id":"a62u8gmxqbpa","ID0":10.0},"type":"Feature","geometry":{"type":"Point","coordinates":[69.14855315,34.50403979]}},{"properties":{"id":"a62u8ginoz2d","ID0":11.0},"type":"Feature","geometry":{"type":"Point","coordinates":[69.14171181,34.50328929]}},{"properties":{"id":"a62u8gmz8e88","ID0":12.0},"type":"Feature","geometry":{"type":"Point","coordinates":[69.1339905,34.50222253]}},{"properties":{"id":"a62u8gjtj8gu","ID0":13.0},"type":"Feature","geometry":{"type":"Point","coordinates":[69.12672894,34.50397635]}},{"properties":{"id":"a62u8gtzxa9m","ID0":14.0},"type":"Feature","geometry":{"type":"Point","coordinates":[69.12393247,34.50542281]}},{"properties":{"id":"a62u8gw4ndwi","ID0":15.0},"type":"Feature","geometry":{"type":"Point","coordinates":[69.12195134,34.50532121]}},{"properties":{"id":"a62u8gmytm9t","ID0":16.0},"type":"Feature","geometry":{"type":"Point","coordinates":[69.12068139,34.50527041]}},{"properties":{"id":"a62u8gk18v61","ID0":17.0},"type":"Feature","geometry":{"type":"Point","coordinates":[69.11671914,34.50542281]}},{"properties":{"id":"a62u8gn67eju","ID0":18.0},"type":"Feature","geometry":{"type":"Point","coordinates":[69.11043408,34.51069963]}},{"properties":{"id":"a62u8gks4rst","ID0":19.0},"type":"Feature","geometry":{"type":"Point","coordinates":[69.10662435,34.51091776]}},{"properties":{"id":"a62u8gov6us9","ID0":20.0},"type":"Feature","geometry":{"type":"Point","coordinates":[69.21076314,34.45794363]}},{"properties":{"id":"a62u8go34x29","ID0":21.0},"type":"Feature","geometry":{"type":"Point","coordinates":[69.23084073,34.45831445]}},{"properties":{"id":"a62u8gsgcv0l","ID0":22.0},"type":"Feature","geometry":{"type":"Point","coordinates":[69.26225501,34.46615478]}},{"properties":{"id":"a62u8gv5su07","ID0":23.0},"type":"Feature","geometry":{"type":"Point","coordinates":[69.27671924,34.49531151]}},{"properties":{"id":"a62u8ghc9hxg","ID0":24.0},"type":"Feature","geometry":{"type":"Point","coordinates":[69.14575628,34.4701943]}}],"is_temporal":false,"author":{"url":"http://www.aims.org.af/index.aspx ","metadata":null,"contact_name":"","contact_address":"","source":null,"contact_phone":""},"source":"http://www.aims.org.af/index.aspx ","pagination":{"sort":null,"start":0,"total":24,"limit":1000000},"state":"complete","tags":"afghanistan,bridges,infrastructure,kabul,transportation","published":"2014-08-11T07:29:11-04:00","id":6606}