{"type":"FeatureCollection","data_type":"Dataset","url_type":null,"permissions":[{"permissions":{"download":true,"view":true},"group_id":"everyone"}],"classification":null,"title":"American Home Property Inspection of Texas","count":1,"stream_id":67388,"contributor":{"url":"http://geocommons.com/users/11586","name":"bharken"},"data_attributes":null,"calculation_params":null,"icon_link":null,"link":"http://geocommons.com/overlays/67388.json","extent":[-95.3653,29.7574,-95.3653,29.7574],"geometry_types":["point"],"unique_name":null,"name":"American Home Property Inspection of Texas","feature_count":1,"description":"American Property Inspections of Texas is an independently owned and operated Houston inspection company serving the Greater Houston and surrounding areas with over 15 years experience in the design, construction and inspection of commercial and residential property.","next_feature":null,"is_raster":false,"short_classification":"Y","stats":{},"features":[{"properties":{"name":"American Home Property Inspection of Texas","city":"Houston","region":"US-TX","balloon_text":"<b><a href=\"http://maps.google.co.uk/maps/place?cid=11346069856834659959&amp;q=American+Home+Property+Inspections+of+Texas&amp;hl=en-GB&amp;cad=src:kml_balloon&amp;ei=05uxTMaAFZGTkAWVw9jWDw\">$[name]</a></b><img src=\"http://www.google.com/images/syt-star-on.gif\" alt=\"Rated 5.0 out of 5.0\"> <img src=\"http://www.google.com/images/syt-star-on.gif\" alt=\"\"> <img src=\"http://www.google.com/images/syt-star-on.gif\" alt=\"\"> <img src=\"http://www.google.com/images/syt-star-on.gif\" alt=\"\"> <img src=\"http://www.google.com/images/syt-star-on.gif\" alt=\"\"> 8 reviews945 McKinney St.Houston, TX 77002, United States(281) 744-3965<a href=\"http://www.apitx.net/\">apitx.net</a><a href=\"/maps/place?cid=11346069856834659959&amp;q=American+Home+Property+Inspections+of+Texas&amp;hl=en-GB&amp;cd=1&amp;cad=src:ppphoto&amp;ei=05uxTMaAFZGTkAWVw9jWDw\"><img src=\"http://lh3.googleusercontent.com/public/1thD7cNa5MlFP0osPsgpqfVWMpUsn5YfRxYdVsaDQL-OfSwftUw2nn0vGQA2OJkVMCFbQ4x8iIvyWbrO7qjZRBepmVcaMa5YXHjs2-BbihbJ6AukCis4nQox\"></a><b>Good Inspectors</b>  <img src=\"http://www.google.com/images/sy-star-on.gif\"><img src=\"http://www.google.com/images/sy-star-on.gif\"><img src=\"http://www.google.com/images/sy-star-on.gif\"><img src=\"http://www.google.com/images/sy-star-on.gif\"><img src=\"http://www.google.com/images/sy-star-on.gif\">  -  A2Z W.  -  15 Apr 2010Very good inspectors. I had them come out to my home and check my foundation and they check the whole house from top to bottom. They were very thorough and <b>...</b> <a href=\"http://maps.google.co.uk/local_url?q=http://www.insiderpages.com/b/15250691493&amp;dq=American+Home+Property+Inspections+of+Texas&amp;near=Houston,+TX&amp;output=kml&amp;ie=utf-8&amp;v=2.2&amp;cv=5.2.1.1588&amp;hl=en-GB&amp;s=ANYYN7nja0D7QfCCEzNX987MH6rWQ9ZtSA\">More from insiderpages.com »</a><a href=\"http://maps.google.co.uk/maps/place?cid=11346069856834659959&amp;q=American+Home+Property+Inspections+of+Texas&amp;hl=en-GB&amp;cad=src:kml_balloon&amp;ei=05uxTMaAFZGTkAWVw9jWDw&amp;dtab=2\">See all 8 reviews »</a>  $[geDirections]","contents":"American Home Property Inspection of Texas","id":"a62u6s5anhxp"},"type":"Feature","geometry":{"type":"Point","coordinates":[-95.365349,29.75735]}}],"is_temporal":false,"author":{"url":"http://bbs.keyhole.com/ubb/ubbthreads.php?ubb=showflat&Number=1371815&#Post1371815","metadata":"","contact_name":"","contact_address":"945 McKinney Street, Houston, TX 77002","source":"Google Earth Community","contact_phone":"(281) 744-3965"},"source":"http://bbs.keyhole.com/ubb/ubbthreads.php?ubb=showflat&Number=1371815&#Post1371815","pagination":{"sort":null,"start":0,"total":1,"limit":1000000},"state":"complete","tags":"home inspection,home inspector","published":"2014-08-10T20:50:55-04:00","id":67388}