{"type":"FeatureCollection","data_type":"Dataset","url_type":null,"permissions":[{"permissions":{"download":true,"view":true},"group_id":"everyone"}],"classification":null,"title":"Able Pasadena Movers","count":1,"stream_id":68233,"contributor":{"url":"http://geocommons.com/users/11586","name":"bharken"},"data_attributes":null,"calculation_params":null,"icon_link":null,"link":"http://geocommons.com/overlays/68233.json","extent":[-118.15,34.1362,-118.15,34.1362],"geometry_types":["point"],"unique_name":null,"name":"Able Pasadena Movers","feature_count":1,"description":"Able Pasadena Movers is a company serving the relocating needs of people living in Pasadena at affordable rates. We know that moving from one place to another is a great task. Able Pasadena Movers will take care of all of your moving tasks, packing up a whole house, throwing away items and lifting the heavy boxes and other things can cause a headache. Unlike most other Movers in Pasadena, we are here to help you and make your relocation a memorable and comfortable experience.","next_feature":null,"is_raster":false,"short_classification":"Y","stats":{},"features":[{"properties":{"name":"Able Pasadena Movers","city":"Pasadena","region":"US-CA","balloon_text":"<b><a href=\"http://maps.google.com/maps/place?cid=5574495317468483513&amp;q=able+pasadena+movers&amp;hl=en&amp;cad=src:kml_balloon&amp;ei=1De4TNX-LouQkQWf7_SCBg\">$[name]</a></b>3 reviews556 South Fair Oaks AvenuePasadena, CA 91105(626) 710-4388<a href=\"http://pasadenacamovers.info\">pasadenacamovers.info</a><a href=\"/maps/place?cid=5574495317468483513&amp;q=able+pasadena+movers&amp;hl=en&amp;cd=1&amp;cad=src:ppphoto&amp;ei=1De4TNX-LouQkQWf7_SCBg\"><img src=\"http://lh3.googleusercontent.com/public/PBmbL4IX4_6FV8HXJU4JCNaIoe6_scY722STItErCln3sP6Kcwdc6TMPpKEGJRBvmg3i4lugN_bhfccrKO5yjNBnzxGAQOok0L8YO5maXzYIbNhocMsvPKCg\"></a><b>Will Use Again.</b>  <img src=\"http://www.google.com/images/sy-star-on.gif\"><img src=\"http://www.google.com/images/sy-star-on.gif\"><img src=\"http://www.google.com/images/sy-star-on.gif\"><img src=\"http://www.google.com/images/sy-star-on.gif\"><img src=\"http://www.google.com/images/sy-star-on.gif\">  -  sal s.  -  Jul 8, 2010I was very pleased with this moving company. They did everything right from start to finsih. My furniture arrived on time and in perfect condition. <a href=\"http://maps.google.com/local_url?q=http://www.judysbook.com/members/164399/posts/2010/7/7879120/&amp;dq=able+pasadena+movers&amp;near=pasadena,+ca&amp;output=kml&amp;ie=utf-8&amp;v=2.2&amp;cv=5.2.1.1588&amp;hl=en&amp;s=ANYYN7n_5XlvhV3tCh5PhiRlNb37Pb5NnQ\">More from judysbook.com »</a>  $[geDirections]","contents":"Able Pasadena Movers","id":"a63bn2wbqpzm"},"type":"Feature","geometry":{"type":"Point","coordinates":[-118.150369,34.136212]}}],"is_temporal":false,"author":{"url":"http://bbs.keyhole.com/ubb/ubbthreads.php?ubb=showflat&Number=1373337&#Post1373337","metadata":"","contact_name":"","contact_address":"556 South Fair Oaks Avenue, Pasadena, CA 91105","source":"Google Earth Community","contact_phone":"(626) 710-4388"},"source":"http://bbs.keyhole.com/ubb/ubbthreads.php?ubb=showflat&Number=1373337&#Post1373337","pagination":{"sort":null,"start":0,"total":1,"limit":1000000},"state":"complete","tags":"affordable movers,mover,movers,moving,moving company,moving service,moving services","published":"2014-08-10T21:37:49-04:00","id":68233}