{"type":"FeatureCollection","data_type":"Dataset","url_type":null,"permissions":[{"permissions":{"download":true,"view":true},"group_id":"everyone"}],"classification":null,"title":"Mi prueba de Fusion Tables","count":2,"stream_id":68247,"contributor":{"url":"http://geocommons.com/users/15724","name":"damagedgoods"},"data_attributes":null,"calculation_params":null,"icon_link":null,"link":"http://geocommons.com/overlays/68247.json","extent":[-3.70274,40.4167,-3.70035,40.4884],"geometry_types":["point"],"unique_name":null,"name":"Mi prueba de Fusion Tables","feature_count":2,"description":"","next_feature":null,"is_raster":false,"short_classification":"Y","stats":{},"features":[{"properties":{"name":"Ubicacion 1","description":"<b>Text</b>: Ubicacion 1<b>Number</b>: 10<b>Location</b>: Puerta del sol 1, Madrid, Spain<b>Date</b>: 10/29/2010 23:00","id":"a67mk0weaqpc"},"type":"Feature","geometry":{"type":"Point","coordinates":[-3.7027412,40.488439]}},{"properties":{"name":"Ubicacion 2","description":"<b>Text</b>: Ubicacion 2<b>Number</b>: 20<b>Location</b>: Pricesa 12, Madrid, Spain<b>Date</b>: 10/29/10 22:30","id":"a67mk0z9fi6t"},"type":"Feature","geometry":{"type":"Point","coordinates":[-3.7003454,40.4166909]}}],"is_temporal":false,"author":{"url":"","metadata":"","contact_name":"","contact_address":"","source":"","contact_phone":""},"source":"","pagination":{"sort":null,"start":0,"total":2,"limit":1000000},"state":"complete","tags":"","published":"2014-08-10T21:38:49-04:00","id":68247}