{"type":"FeatureCollection","data_type":"Dataset","url_type":null,"permissions":[{"permissions":{"download":true,"view":true},"group_id":"everyone"}],"classification":null,"title":"Libraries","count":3,"stream_id":68258,"contributor":{"url":"http://geocommons.com/users/17182","name":"tkendrick114"},"data_attributes":null,"calculation_params":null,"icon_link":null,"link":"http://geocommons.com/overlays/68258.json","extent":[-93.2454,44.971,-93.2414,44.9747],"geometry_types":["point"],"unique_name":null,"name":"Libraries","feature_count":3,"description":"","next_feature":null,"is_raster":false,"short_classification":"Y","stats":{},"features":[{"properties":{"name":"Placemark 1","description":null,"id":"a65xzkxnuyu0"},"type":"Feature","geometry":{"type":"Point","coordinates":[-93.24543,44.973179]}},{"properties":{"name":"Placemark 2","description":null,"id":"a65xzkvjyhbt"},"type":"Feature","geometry":{"type":"Point","coordinates":[-93.242897,44.971039]}},{"properties":{"name":"Placemark 3","description":null,"id":"a65xzklwgqap"},"type":"Feature","geometry":{"type":"Point","coordinates":[-93.241417,44.974682]}}],"is_temporal":false,"author":{"url":"","metadata":"","contact_name":"","contact_address":"","source":"","contact_phone":""},"source":"","pagination":{"sort":null,"start":0,"total":3,"limit":1000000},"state":"complete","tags":"","published":"2014-08-10T21:39:39-04:00","id":68258}