{"type":"FeatureCollection","data_type":"Dataset","url_type":null,"permissions":[{"permissions":{"download":true,"view":true},"group_id":"everyone"}],"classification":null,"title":"noname","count":14,"stream_id":70520,"contributor":{"url":"http://geocommons.com/users/17605","name":"vongtv"},"data_attributes":null,"calculation_params":null,"icon_link":null,"link":"http://geocommons.com/overlays/70520.json","extent":[106.501,-7.7978,117.092,-0.5291],"geometry_types":["point"],"unique_name":null,"name":"noname","feature_count":14,"description":"","next_feature":null,"is_raster":false,"short_classification":"Y","stats":{"latitude":{"max":-0.5291,"mean":-6.38142142857143,"variance":3.15958432796703,"stdev":1.77752196272424,"min":-7.7978,"median":-6.569},"longitude":{"max":117.0919,"mean":109.312078571429,"variance":11.4542821171978,"stdev":3.38441754474796,"min":106.5008,"median":107.0405}},"features":[{"properties":{"latitude":-7.7978,"longitude":110.41,"id":"a69x8swtca1u"},"type":"Feature","geometry":{"type":"Point","coordinates":[110.41,-7.7978]}},{"properties":{"latitude":-7.7859,"longitude":110.3784,"id":"a69x8t2cbbqx"},"type":"Feature","geometry":{"type":"Point","coordinates":[110.3784,-7.7859]}},{"properties":{"latitude":-7.3219,"longitude":112.7172,"id":"a69x8t2f1964"},"type":"Feature","geometry":{"type":"Point","coordinates":[112.7172,-7.3219]}},{"properties":{"latitude":-7.3219,"longitude":112.7172,"id":"a69x8t9b0ymp"},"type":"Feature","geometry":{"type":"Point","coordinates":[112.7172,-7.3219]}},{"properties":{"latitude":-7.2227,"longitude":112.7352,"id":"a69x8swow7u3"},"type":"Feature","geometry":{"type":"Point","coordinates":[112.7352,-7.2227]}},{"properties":{"latitude":-6.7273,"longitude":107.0405,"id":"a69x8t7qcnjr"},"type":"Feature","geometry":{"type":"Point","coordinates":[107.0405,-6.7273]}},{"properties":{"latitude":-6.7273,"longitude":107.0405,"id":"a69x8sy31o7i"},"type":"Feature","geometry":{"type":"Point","coordinates":[107.0405,-6.7273]}},{"properties":{"latitude":-6.569,"longitude":106.7036,"id":"a69x8supx7x6"},"type":"Feature","geometry":{"type":"Point","coordinates":[106.7036,-6.569]}},{"properties":{"latitude":-6.3917,"longitude":106.8516,"id":"a69x8t9o7kt2"},"type":"Feature","geometry":{"type":"Point","coordinates":[106.8516,-6.3917]}},{"properties":{"latitude":-6.2925,"longitude":106.6662,"id":"a69x8svyhtl3"},"type":"Feature","geometry":{"type":"Point","coordinates":[106.6662,-6.2925]}},{"properties":{"latitude":-6.2539,"longitude":106.5008,"id":"a69x8t0u4tny"},"type":"Feature","geometry":{"type":"Point","coordinates":[106.5008,-6.2539]}},{"properties":{"latitude":-6.2471,"longitude":106.7831,"id":"a69x8t81s7qx"},"type":"Feature","geometry":{"type":"Point","coordinates":[106.7831,-6.2471]}},{"properties":{"latitude":-6.1518,"longitude":106.7329,"id":"a69x8t1dnjdl"},"type":"Feature","geometry":{"type":"Point","coordinates":[106.7329,-6.1518]}},{"properties":{"latitude":-0.5291,"longitude":117.0919,"id":"a69x8taj5mbz"},"type":"Feature","geometry":{"type":"Point","coordinates":[117.0919,-0.5291]}}],"is_temporal":false,"author":{"url":null,"metadata":null,"contact_name":null,"contact_address":null,"source":null,"contact_phone":null},"source":null,"pagination":{"sort":null,"start":0,"total":14,"limit":1000000},"state":"complete","tags":"","published":"2014-08-10T11:40:25-04:00","id":70520}