{"type":"FeatureCollection","data_type":"Dataset","url_type":null,"permissions":[{"permissions":{"download":true,"view":true},"group_id":"everyone"}],"classification":null,"title":"Example KML File","count":2,"stream_id":7084,"contributor":{"url":"http://geocommons.com/users/159","name":"ajturner"},"data_attributes":null,"calculation_params":null,"icon_link":null,"link":"http://geocommons.com/overlays/7084.json","extent":[-111.956,33.5024,-111.95,33.5043],"geometry_types":["point"],"unique_name":null,"name":"Example KML File","feature_count":2,"description":"","next_feature":null,"is_raster":false,"short_classification":"Y","stats":{"holeNumber":{"max":null,"min":null,"median":null},"holeYardage":{"max":null,"min":null,"median":null},"holePar":{"max":null,"min":null,"median":null}},"features":[{"properties":{"name":"By the lake","holeNumber":"5","holeYardage":"523","holePar":"5","id":"a622rqie5pyc"},"type":"Feature","geometry":{"type":"Point","coordinates":[-111.95,33.5024]}},{"properties":{"name":"Club house","holeNumber":"1","holeYardage":"234","holePar":"4","id":"a622rqlddt79"},"type":"Feature","geometry":{"type":"Point","coordinates":[-111.956,33.5043]}}],"is_temporal":false,"author":{"url":"","metadata":"","contact_name":"","contact_address":"","source":"","contact_phone":""},"source":"","pagination":{"sort":null,"start":0,"total":2,"limit":1000000},"state":"complete","tags":"demo,evacuation,national","published":"2008-11-18T12:00:00Z","id":7084}