{"type":"FeatureCollection","data_type":"Dataset","url_type":null,"permissions":[{"permissions":{"download":true,"view":true},"group_id":"everyone"}],"classification":null,"title":"Dataset for search term 'google'","count":18,"stream_id":71080,"contributor":{"url":"http://geocommons.com/users/17605","name":"vongtv"},"data_attributes":null,"calculation_params":null,"icon_link":null,"link":"http://geocommons.com/overlays/71080.json","extent":[-104.906,-6.9785,139.729,52.5244],"geometry_types":["point"],"unique_name":null,"name":"Dataset for search term 'google'","feature_count":18,"description":"","next_feature":null,"is_raster":false,"short_classification":"Y","stats":{},"features":[{"properties":{"latitude":-6.9785,"longitude":110.4101,"id":"a743mxp3u5bx"},"type":"Feature","geometry":{"type":"Point","coordinates":[110.4101,-6.9785]}},{"properties":{"latitude":18.5404,"longitude":73.8173,"id":"a743mxqw2img"},"type":"Feature","geometry":{"type":"Point","coordinates":[73.8173,18.5404]}},{"properties":{"latitude":22.8261,"longitude":113.6883,"id":"a743mxzir5uf"},"type":"Feature","geometry":{"type":"Point","coordinates":[113.6883,22.8261]}},{"properties":{"latitude":22.8261,"longitude":113.6883,"id":"a743mxqqrfoi"},"type":"Feature","geometry":{"type":"Point","coordinates":[113.6883,22.8261]}},{"properties":{"latitude":30.5761,"longitude":104.0587,"id":"a743mxyn8cld"},"type":"Feature","geometry":{"type":"Point","coordinates":[104.0587,30.5761]}},{"properties":{"latitude":30.5761,"longitude":104.0587,"id":"a743mxwdhyy9"},"type":"Feature","geometry":{"type":"Point","coordinates":[104.0587,30.5761]}},{"properties":{"latitude":35.1922,"longitude":136.9337,"id":"a743my2otyma"},"type":"Feature","geometry":{"type":"Point","coordinates":[136.9337,35.1922]}},{"properties":{"latitude":35.1946,"longitude":136.9349,"id":"a743mxqnu83a"},"type":"Feature","geometry":{"type":"Point","coordinates":[136.9349,35.1946]}},{"properties":{"latitude":35.2027,"longitude":136.9407,"id":"a743my3zh6ch"},"type":"Feature","geometry":{"type":"Point","coordinates":[136.9407,35.2027]}},{"properties":{"latitude":35.2062,"longitude":136.9437,"id":"a743my1ewedp"},"type":"Feature","geometry":{"type":"Point","coordinates":[136.9437,35.2062]}},{"properties":{"latitude":35.2241,"longitude":136.9469,"id":"a743mxyd6isq"},"type":"Feature","geometry":{"type":"Point","coordinates":[136.9469,35.2241]}},{"properties":{"latitude":35.2318,"longitude":136.9511,"id":"a743mxzee4k8"},"type":"Feature","geometry":{"type":"Point","coordinates":[136.9511,35.2318]}},{"properties":{"latitude":35.6606,"longitude":139.7293,"id":"a743my43f1lf"},"type":"Feature","geometry":{"type":"Point","coordinates":[139.7293,35.6606]}},{"properties":{"latitude":35.8765,"longitude":128.6262,"id":"a743my0o0159"},"type":"Feature","geometry":{"type":"Point","coordinates":[128.6262,35.8765]}},{"properties":{"latitude":37.3901,"longitude":-6.2007,"id":"a743mxxm6l1f"},"type":"Feature","geometry":{"type":"Point","coordinates":[-6.2007,37.3901]}},{"properties":{"latitude":40.4731,"longitude":-104.9061,"id":"a743mxrbwqsb"},"type":"Feature","geometry":{"type":"Point","coordinates":[-104.9061,40.4731]}},{"properties":{"latitude":52.0568,"longitude":4.2497,"id":"a743mxs6kxlh"},"type":"Feature","geometry":{"type":"Point","coordinates":[4.2497,52.0568]}},{"properties":{"latitude":52.5244,"longitude":13.4105,"id":"a743mxycfejs"},"type":"Feature","geometry":{"type":"Point","coordinates":[13.4105,52.5244]}}],"is_temporal":false,"author":{"url":"http://twitter.com","metadata":"","contact_name":"","contact_address":"","source":"","contact_phone":""},"source":"http://twitter.com","pagination":{"sort":null,"start":0,"total":18,"limit":1000000},"state":"complete","tags":"","published":"2014-08-10T12:05:23-04:00","id":71080}