{"type":"FeatureCollection","data_type":"Dataset","url_type":null,"permissions":[{"permissions":{"download":true,"view":true},"group_id":"everyone"}],"classification":null,"title":"Quality Home Remodeling","count":1,"stream_id":72388,"contributor":{"url":"http://geocommons.com/users/11586","name":"bharken"},"data_attributes":null,"calculation_params":null,"icon_link":null,"link":"http://geocommons.com/overlays/72388.json","extent":[-117.795,33.5464,-117.795,33.5464],"geometry_types":["point"],"unique_name":null,"name":"Quality Home Remodeling","feature_count":1,"description":"Quality Home Remodeling provides kitchen and bathroom make over. Their product line is a full range of hardwood kitchen cabinets and range hoods which are affordable. They offer kitchen cabinet and countertops, granite and tiles installation at discounted prices.","next_feature":null,"is_raster":false,"short_classification":"Y","stats":{},"features":[{"properties":{"name":"Quality Home Remodeling","city":"Laguna Beach","region":"US-CA","balloon_text":"<b><a href=\"http://maps.google.com/maps/place?cid=2636802037832154813&amp;q=quality+home+remodeling&amp;hl=en&amp;cad=src:kml_balloon&amp;ei=mnnOTKe-FYT4vAOK35C5Aw\">$[name]</a></b>668 North Coast HighwayLaguna Beach, CA 92651(949) 566-8433<a href=\"http://lagunaremodeling.net/\">lagunaremodeling.net</a><a href=\"/maps/place?cid=2636802037832154813&amp;q=quality+home+remodeling&amp;hl=en&amp;cd=1&amp;cad=src:ppphoto&amp;ei=mnnOTKe-FYT4vAOK35C5Aw\"><img src=\"http://lh6.googleusercontent.com/public/LD1lmQ2BIgBVXnmPoIFjAIaUyiWEXOdPzvUzcGMmffnyjYmmk5JvyW8fRQeYrpiPki3OAo2GjNdrxCQOL_HydwakcOXWbdgIf3EbppYncCx6uawzPofUKdVx\"></a>  $[geDirections]","contents":"Quality Home Remodeling","id":"a68m9r6bm9zd"},"type":"Feature","geometry":{"type":"Point","coordinates":[-117.794711,33.54642]}}],"is_temporal":false,"author":{"url":"http://bbs.keyhole.com/ubb/ubbthreads.php?ubb=showflat&Number=1377519&#Post1377519","metadata":"","contact_name":"","contact_address":"668 North Coast Highway, Laguna Beach, CA 92651","source":"Google Earth Community","contact_phone":"(949) 566-8433"},"source":"http://bbs.keyhole.com/ubb/ubbthreads.php?ubb=showflat&Number=1377519&#Post1377519","pagination":{"sort":null,"start":0,"total":1,"limit":1000000},"state":"complete","tags":"bathroom remodeling,home remodeling,kitchen remodeling","published":"2014-08-10T13:14:33-04:00","id":72388}