{"type":"FeatureCollection","data_type":"Dataset","url_type":null,"permissions":[{"permissions":{"download":true,"view":true},"group_id":"everyone"}],"classification":null,"title":"Dataset for search term 'oracle'","count":9,"stream_id":72391,"contributor":{"url":"http://geocommons.com/users/17605","name":"vongtv"},"data_attributes":null,"calculation_params":null,"icon_link":null,"link":"http://geocommons.com/overlays/72391.json","extent":[-122.693,-33.8052,151.179,50.0674],"geometry_types":["point"],"unique_name":null,"name":"Dataset for search term 'oracle'","feature_count":9,"description":"","next_feature":null,"is_raster":false,"short_classification":"Y","stats":{},"features":[{"properties":{"latitude":-33.8052,"longitude":151.1789,"id":"a6o6zqsjw6d7"},"type":"Feature","geometry":{"type":"Point","coordinates":[151.1789,-33.8052]}},{"properties":{"latitude":20.5612,"longitude":-103.4392,"id":"a6o6zqopneib"},"type":"Feature","geometry":{"type":"Point","coordinates":[-103.4392,20.5612]}},{"properties":{"latitude":36.4535,"longitude":136.5897,"id":"a6o6zqu3zseb"},"type":"Feature","geometry":{"type":"Point","coordinates":[136.5897,36.4535]}},{"properties":{"latitude":38.3272,"longitude":-122.6932,"id":"a6o6zqvxybmw"},"type":"Feature","geometry":{"type":"Point","coordinates":[-122.6932,38.3272]}},{"properties":{"latitude":39.0857,"longitude":-76.8614,"id":"a6o6zqpaz7pk"},"type":"Feature","geometry":{"type":"Point","coordinates":[-76.8614,39.0857]}},{"properties":{"latitude":39.9691,"longitude":-82.9996,"id":"a6o6zqisrqin"},"type":"Feature","geometry":{"type":"Point","coordinates":[-82.9996,39.9691]}},{"properties":{"latitude":41.9614,"longitude":-87.8849,"id":"a6o6zqhc3oqm"},"type":"Feature","geometry":{"type":"Point","coordinates":[-87.8849,41.9614]}},{"properties":{"latitude":41.9614,"longitude":-87.8849,"id":"a6o6zqj1w7vs"},"type":"Feature","geometry":{"type":"Point","coordinates":[-87.8849,41.9614]}},{"properties":{"latitude":50.0674,"longitude":8.2242,"id":"a6o6zqo54vcw"},"type":"Feature","geometry":{"type":"Point","coordinates":[8.2242,50.0674]}}],"is_temporal":false,"author":{"url":"http://twitter.com","metadata":"","contact_name":"","contact_address":"","source":"","contact_phone":""},"source":"http://twitter.com","pagination":{"sort":null,"start":0,"total":9,"limit":1000000},"state":"complete","tags":"","published":"2014-08-10T13:14:39-04:00","id":72391}