{"type":"FeatureCollection","data_type":"Dataset","url_type":null,"permissions":[{"permissions":{"download":true,"view":true},"group_id":"everyone"}],"classification":null,"title":"Historic State Capitals of Colorado, USA, 1859 - 2007","count":7,"stream_id":7319,"contributor":{"url":"http://geocommons.com/users/2","name":"data"},"data_attributes":null,"calculation_params":null,"icon_link":null,"link":"http://geocommons.com/overlays/7319.json","extent":[-105.211,38.8405,-104.844,39.7468],"geometry_types":["point"],"unique_name":null,"name":"Historic State Capitals of Colorado, USA, 1859 - 2007","feature_count":7,"description":"This dataset displays the Historical State Capitals for the State of Colorado. The locations of every city that were once a capital of Colorado are displayed along with other information:Name of the State  Brief history of the State Capital Longitude of the Capital Latitude of the Capital The Date the City became the Capital State of the Capital City Name of the Capital City Year that the Current Capital's State achieved it's Statehood Name of the State's Current CapitalInformation was obtained on January 10th, 2008 from wikipedia.orghttp://en.wikipedia.org/wiki/List_of_current_and_former_capital_cities_within_the_United_States#Former_national_capitals","next_feature":null,"is_raster":false,"short_classification":"Y","stats":{"Longitude0":{"max":-104.844293,"mean":-105.029312428571,"variance":0.0180208492842855,"stdev":0.134241756857863,"min":-105.210911,"median":-104.984768},"Date0":{"max":1876.0,"mean":1863.85714285714,"variance":35.1428571428571,"stdev":5.92814112035612,"min":1859.0,"median":1862.0},"Latitude0":{"max":39.746837,"mean":39.6130165714286,"variance":0.116061545691285,"stdev":0.340678067523116,"min":38.840474,"median":39.739242}},"features":[{"properties":{"Capital0":"Denver","Statehood ":"Statehood in 1876","State0":"Colorado","Capital St":"Colorado","Notes0":"Capital of the State of Colorado.","Longitude0":-104.984768,"Date0":1876.0,"Latitude0":39.739242,"id":"a64u2hw5650x","Current Ca":"Denver"},"type":"Feature","geometry":{"type":"Point","coordinates":[-104.984768,39.739242]}},{"properties":{"Capital0":"Denver City, Denver","Statehood ":"Statehood in 1876","State0":"Colorado","Capital St":"Colorado","Notes0":"Capitals of the Territory of Colorado.","Longitude0":-104.984768,"Date0":1867.0,"Latitude0":39.739242,"id":"a64u2hicyw1c","Current Ca":"Denver"},"type":"Feature","geometry":{"type":"Point","coordinates":[-104.984768,39.739242]}},{"properties":{"Capital0":"Golden City","Statehood ":"Statehood in 1876","State0":"Colorado","Capital St":"Colorado","Notes0":"Capitals of the Territory of Colorado.","Longitude0":-105.210911,"Date0":1862.0,"Latitude0":39.746837,"id":"a64u2htx9rv4","Current Ca":"Denver"},"type":"Feature","geometry":{"type":"Point","coordinates":[-105.210911,39.746837]}},{"properties":{"Capital0":"Denver City","Statehood ":"Statehood in 1876","State0":"Colorado","Capital St":"Colorado","Notes0":"Capitals of the Territory of Colorado.","Longitude0":-104.984768,"Date0":1861.0,"Latitude0":39.739242,"id":"a64u2hl3umfh","Current Ca":"Denver"},"type":"Feature","geometry":{"type":"Point","coordinates":[-104.984768,39.739242]}},{"properties":{"Capital0":"Colorado City","Statehood ":"Statehood in 1876","State0":"Colorado","Capital St":"Colorado","Notes0":"Capitals of the Territory of Colorado.","Longitude0":-104.844293,"Date0":1862.0,"Latitude0":38.840474,"id":"a64u2hvj3nh1","Current Ca":"Denver"},"type":"Feature","geometry":{"type":"Point","coordinates":[-104.844293,38.840474]}},{"properties":{"Capital0":"Golden City","Statehood ":"Statehood in 1876","State0":"Colorado","Capital St":"Colorado","Notes0":"Capitals of the extralegal Territory of Jefferson.","Longitude0":-105.210911,"Date0":1860.0,"Latitude0":39.746837,"id":"a64u2hqf8x32","Current Ca":"Denver"},"type":"Feature","geometry":{"type":"Point","coordinates":[-105.210911,39.746837]}},{"properties":{"Capital0":"Denver City","Statehood ":"Statehood in 1876","State0":"Colorado","Capital St":"Colorado","Notes0":"Capitals of the extralegal Territory of Jefferson.","Longitude0":-104.984768,"Date0":1859.0,"Latitude0":39.739242,"id":"a64u2hpsumoa","Current Ca":"Denver"},"type":"Feature","geometry":{"type":"Point","coordinates":[-104.984768,39.739242]}}],"is_temporal":false,"author":{"url":"http://en.wikipedia.org/wiki/List_of_current_and_former_capital_cities_within_the_United_States#Former_national_capitals","metadata":null,"contact_name":"","contact_address":"","source":"Wikipedia","contact_phone":""},"source":"http://en.wikipedia.org/wiki/List_of_current_and_former_capital_cities_within_the_United_States#Former_national_capitals","pagination":{"sort":null,"start":0,"total":7,"limit":1000000},"state":"complete","tags":"capitals,colorado,historic,of,state","published":"2008-01-10T12:00:00Z","id":7319}