{"type":"FeatureCollection","data_type":"Dataset","url_type":null,"permissions":[{"permissions":{"download":true,"view":true},"group_id":"everyone"}],"classification":null,"title":"Historic State Capitals of South Carolina, United States, 2008","count":6,"stream_id":7397,"contributor":{"url":"http://geocommons.com/users/2","name":"data"},"data_attributes":null,"calculation_params":null,"icon_link":null,"link":"http://geocommons.com/overlays/7397.json","extent":[-81.3114,29.8977,-79.9308,34.0003],"geometry_types":["point"],"unique_name":null,"name":"Historic State Capitals of South Carolina, United States, 2008","feature_count":6,"description":"This dataset displays the Historical State Capitals for the State of South Carolina. The locations of every city that were once a capital of South Carolina are displayed along with other information:Name of the State  Brief history of the State Capital Longitude of the Capital Latitude of the Capital The Date the City became the Capital State of the Capital City Name of the Capital City Year that the Current Capital's State achieved it's Statehood Name of the State's Current CapitalInformation was obtained on January 10th, 2008 from wikipedia.orghttp://en.wikipedia.org/wiki/List_of_current_and_former_capital_cities_within_the_United_States#Former_national_capitals","next_feature":null,"is_raster":false,"short_classification":"Y","stats":{"Longitude0":{"max":-79.930784,"mean":-80.3446278333333,"variance":0.418780705327367,"stdev":0.647132679848087,"min":-81.311425,"median":-79.930784},"Date0":{"max":1786.0,"mean":1702.66666666667,"variance":6489.46666666667,"stdev":80.5572260363195,"min":1565.0,"median":1712.0},"Latitude0":{"max":34.000349,"mean":32.5005865,"variance":1.8656845393015,"stdev":1.36590063302625,"min":29.897718,"median":32.776363}},"features":[{"properties":{"Capital0":"Columbia","Statehood ":"Statehood in 1776","State0":"South Carolina","Capital St":"South Carolina","Notes0":"Capitals of the State of South Carolina.","Longitude0":-81.033206,"Date0":1786.0,"Latitude0":34.000349,"id":"a64yhf5a0nsr","Current Ca":"Columbia"},"type":"Feature","geometry":{"type":"Point","coordinates":[-81.033206,34.000349]}},{"properties":{"Capital0":"Charlestown","Statehood ":"Statehood in 1776","State0":"South Carolina","Capital St":"South Carolina","Notes0":"Capitals of the State of South Carolina.","Longitude0":-79.930784,"Date0":1776.0,"Latitude0":32.776363,"id":"a64yhf5slriv","Current Ca":"Columbia"},"type":"Feature","geometry":{"type":"Point","coordinates":[-79.930784,32.776363]}},{"properties":{"Capital0":"Charlestown","Statehood ":"Statehood in 1776","State0":"South Carolina","Capital St":"South Carolina","Notes0":"Capital of the British Province of South Carolina.","Longitude0":-79.930784,"Date0":1712.0,"Latitude0":32.776363,"id":"a64yhf197hs3","Current Ca":"Columbia"},"type":"Feature","geometry":{"type":"Point","coordinates":[-79.930784,32.776363]}},{"properties":{"Capital0":"Charlestown","Statehood ":"Statehood in 1776","State0":"South Carolina","Capital St":"South Carolina","Notes0":"Capital of the British Province of Carolina.","Longitude0":-79.930784,"Date0":1707.0,"Latitude0":32.776363,"id":"a64yhex4qy17","Current Ca":"Columbia"},"type":"Feature","geometry":{"type":"Point","coordinates":[-79.930784,32.776363]}},{"properties":{"Capital0":"Charlestown","Statehood ":"Statehood in 1776","State0":"South Carolina","Capital St":"South Carolina","Notes0":"Capital of the English Province of Carolina.","Longitude0":-79.930784,"Date0":1670.0,"Latitude0":32.776363,"id":"a64yhevuklbg","Current Ca":"Columbia"},"type":"Feature","geometry":{"type":"Point","coordinates":[-79.930784,32.776363]}},{"properties":{"Capital0":"San Agustín","Statehood ":"Statehood in 1776","State0":"South Carolina","Capital St":"Florida","Notes0":"Capital of the Spanish colony of la Florida.[4]","Longitude0":-81.311425,"Date0":1565.0,"Latitude0":29.897718,"id":"a64yhf8ajnuh","Current Ca":"Columbia"},"type":"Feature","geometry":{"type":"Point","coordinates":[-81.311425,29.897718]}}],"is_temporal":false,"author":{"url":"http://en.wikipedia.org/wiki/List_of_current_and_former_capital_cities_within_the_United_States#Former_national_capitals","metadata":null,"contact_name":"","contact_address":"","source":"Wikipedia","contact_phone":""},"source":"http://en.wikipedia.org/wiki/List_of_current_and_former_capital_cities_within_the_United_States#Former_national_capitals","pagination":{"sort":null,"start":0,"total":6,"limit":1000000},"state":"complete","tags":"capitals,carolina,historic,of,south,state","published":"2008-01-10T12:00:00Z","id":7397}