{"type":"FeatureCollection","data_type":"Dataset","url_type":null,"permissions":[{"permissions":{"download":true,"view":true},"group_id":"everyone"}],"classification":null,"title":"NVN Small Business Showcase","count":1,"stream_id":75992,"contributor":{"url":"http://geocommons.com/users/18187","name":"mappingguy"},"data_attributes":null,"calculation_params":null,"icon_link":null,"link":"http://geocommons.com/overlays/75992.json","extent":[-123.126,49.2819,-123.126,49.2819],"geometry_types":["point"],"unique_name":null,"name":"NVN Small Business Showcase","feature_count":1,"description":"NVN Small Business Showcase","next_feature":null,"is_raster":false,"short_classification":"Y","stats":{"lat":{"max":49.281927,"min":49.281927,"median":49.281927},"long":{"max":-123.125523,"min":-123.125523,"median":-123.125523}},"features":[{"properties":{"date":{"end_time":"2010/12/10 00:00:00 -0500","original":"December 09, 2010 1000-1900","granularity":"day","time":"2010/12/09 00:00:00 -0500"},"event":"New Ventures Network Small Business Showcase","id":"a62cqkmkha2d","address":"955 Burrard Street, Vancouver, BC","lat":49.281927,"long":-123.125523},"type":"Feature","geometry":{"type":"Point","coordinates":[-123.125523,49.281927]}}],"is_temporal":true,"author":{"url":"","metadata":"","contact_name":"","contact_address":"","source":"","contact_phone":""},"source":"","pagination":{"sort":null,"start":0,"total":1,"limit":1000000},"state":"complete","tags":"business,nvn,showcase,small","published":"2010-11-21T06:26:34Z","id":75992}