{"type":"FeatureCollection","data_type":"Dataset","url_type":null,"permissions":[{"permissions":{"download":true,"view":true},"group_id":"everyone"}],"classification":null,"title":"Available - Bleach","count":2,"stream_id":76170,"contributor":{"url":"http://geocommons.com/users/18852","name":"youdop"},"data_attributes":null,"calculation_params":null,"icon_link":null,"link":"http://geocommons.com/overlays/76170.json","extent":[-72.3992,18.5411,-72.3992,18.5411],"geometry_types":["point"],"unique_name":null,"name":"Available - Bleach","feature_count":2,"description":"","next_feature":null,"is_raster":false,"short_classification":"Y","stats":{"geo_score":{"max":1.0,"mean":0.5,"variance":0.5,"stdev":0.707106781186548,"min":0.0,"median":1.0}},"features":[{"properties":{"name":"ADRA (Adventist Development &amp; Relief Agency) - 2010 Haiti Earthquake","status":"Open","available":"Avail","county":null,"org":"Faith-Based Disaster Relief/Recovery","country":"Haiti","city/town":"Carrefour","geo_score":1.0,"main phone":"U.S. 1-800-424-2372 / Haiti: 2234 0191","last update":"2010/03/07 LTel","item":"Cleaning, Cleaner, Bleach, Chlorine Bleach","id":"a63nqp5xdjo9","geo_precision":"zip"},"type":"Feature","geometry":{"type":"Point","coordinates":[-72.3992156982422,18.5411401488875]}},{"properties":{"name":"Action Against Hunger | ACF International - 2010 Haiti Earthquake","status":"Open","available":"Avail","county":null,"org":"International Humanitarian","country":"Haiti","city/town":null,"geo_score":0.0,"main phone":"877 777 1420","last update":"2010/11/05 LTel","item":"Cleaning, Cleaner, Bleach, Chlorine Bleach","id":"a63nqp73igsy","geo_precision":"unmatched"},"type":"Feature","geometry":null}],"is_temporal":false,"author":{"url":"","metadata":"","contact_name":"","contact_address":"","source":"","contact_phone":""},"source":"","pagination":{"sort":null,"start":0,"total":2,"limit":1000000},"state":"complete","tags":"","published":"2014-08-10T20:05:57-04:00","id":76170}