{"type":"FeatureCollection","data_type":"Dataset","url_type":null,"permissions":[{"permissions":{"download":true,"view":true},"group_id":"everyone"}],"classification":null,"title":"002","count":4,"stream_id":78988,"contributor":{"url":"http://geocommons.com/users/18700","name":"kikimwf"},"data_attributes":null,"calculation_params":null,"icon_link":null,"link":"http://geocommons.com/overlays/78988.json","extent":[113.73,23.05,121.09,39.13],"geometry_types":["point"],"unique_name":null,"name":"002","feature_count":4,"description":"","next_feature":null,"is_raster":false,"short_classification":"Y","stats":{"capacity (mn m2)":{"max":30,"mean":23.5,"variance":43.6666666666667,"stdev":6.60807586719967,"min":16,"median":28},"lon":{"max":121.09,"mean":117.5975,"variance":9.30329166666667,"stdev":3.0501297786597,"min":113.73,"median":118.37},"lat":{"max":39.13,"mean":31.245,"variance":43.1281,"stdev":6.56719879400647,"min":23.05,"median":31.45}},"features":[{"properties":{"city":"Wuhu","capacity (mn m2)":28,"lon":118.37,"provice":"Anhui","id":"a62vjhy6uh4z","group":"KNAUF","lat":31.35},"type":"Feature","geometry":{"type":"Point","coordinates":[118.37,31.35]}},{"properties":{"city":"Tianjin","capacity (mn m2)":20,"lon":117.2,"provice":"Tianjin","id":"a62vjhvrbbxb","group":"KNAUF","lat":39.13},"type":"Feature","geometry":{"type":"Point","coordinates":[117.2,39.13]}},{"properties":{"city":"Dongguan","capacity (mn m2)":16,"lon":113.73,"provice":"Guangdong","id":"a62vjhyks20g","group":"KNAUF","lat":23.05},"type":"Feature","geometry":{"type":"Point","coordinates":[113.73,23.05]}},{"properties":{"city":"Taicang","capacity (mn m2)":30,"lon":121.09,"provice":"Jiangsu","id":"a62vjhtmy0hr","group":"KNAUF","lat":31.45},"type":"Feature","geometry":{"type":"Point","coordinates":[121.09,31.45]}}],"is_temporal":false,"author":{"url":"","metadata":"","contact_name":"","contact_address":"","source":"","contact_phone":""},"source":"","pagination":{"sort":null,"start":0,"total":4,"limit":1000000},"state":"complete","tags":"","published":"2014-08-10T22:59:08-04:00","id":78988}