{"type":"FeatureCollection","data_type":"Dataset","url_type":null,"permissions":[{"permissions":{"download":true,"view":true},"group_id":"everyone"}],"classification":null,"title":"map","count":2,"stream_id":79672,"contributor":{"url":"http://geocommons.com/users/18920","name":"renee.lry509"},"data_attributes":null,"calculation_params":null,"icon_link":null,"link":"http://geocommons.com/overlays/79672.json","extent":[120.201,30.3077,120.201,30.3077],"geometry_types":["point"],"unique_name":null,"name":"map","feature_count":2,"description":"","next_feature":null,"is_raster":false,"short_classification":"Y","stats":{"latitude":{"max":30.307689,"min":30.307689,"median":30.307689},"longitude":{"max":120.201416,"min":120.201416,"median":120.201416}},"features":[{"properties":{"latitude":null,"longitude":null,"id":"a67fq5hhxmgn"},"type":"Feature","geometry":null},{"properties":{"latitude":30.307689,"longitude":120.201416,"id":"a67fq5ilfm4w"},"type":"Feature","geometry":{"type":"Point","coordinates":[120.201416,30.307689]}}],"is_temporal":false,"author":{"url":"","metadata":"","contact_name":"","contact_address":"","source":"","contact_phone":""},"source":"","pagination":{"sort":null,"start":0,"total":2,"limit":1000000},"state":"complete","tags":"","published":"2014-08-10T23:53:53-04:00","id":79672}