{"type":"FeatureCollection","data_type":"Dataset","url_type":null,"permissions":[{"permissions":{"download":true,"view":true},"group_id":"everyone"}],"classification":null,"title":"Airport of the Chinese cultural cities","count":4,"stream_id":80106,"contributor":{"url":"http://geocommons.com/users/18964","name":"tom198931"},"data_attributes":null,"calculation_params":null,"icon_link":null,"link":"http://geocommons.com/overlays/80106.json","extent":[108.761,30.237,120.438,40.1001],"geometry_types":["point"],"unique_name":null,"name":"Airport of the Chinese cultural cities","feature_count":4,"description":"","next_feature":null,"is_raster":false,"short_classification":"Y","stats":{"latitude":{"max":40.100135,"mean":34.87927075,"variance":16.3395467940009,"stdev":4.04222052763094,"min":30.237046,"median":34.737522},"longitude":{"max":120.437965,"mean":114.545624,"variance":25.6718503114887,"stdev":5.06673961354722,"min":108.760614,"median":116.592407}},"features":[{"properties":{"name":"Beijing Capital International Airport","latitude":40.100135,"longitude":116.592407,"id":"a66453vtljjt","location":"Beijing"},"type":"Feature","geometry":{"type":"Point","coordinates":[116.592407,40.100135]}},{"properties":{"name":"Luoyang Mengjin Airport","latitude":34.737522,"longitude":112.39151,"id":"a66453rwsbrh","location":"Henan"},"type":"Feature","geometry":{"type":"Point","coordinates":[112.39151,34.737522]}},{"properties":{"name":"Xianyang International Airport","latitude":34.44238,"longitude":108.760614,"id":"a66454124uf4","location":"Shanxi"},"type":"Feature","geometry":{"type":"Point","coordinates":[108.760614,34.44238]}},{"properties":{"name":"Xiaoshan Airport","latitude":30.237046,"longitude":120.437965,"id":"a664541a3kza","location":"Hangzhou"},"type":"Feature","geometry":{"type":"Point","coordinates":[120.437965,30.237046]}}],"is_temporal":false,"author":{"url":"","metadata":"","contact_name":"","contact_address":"","source":"","contact_phone":""},"source":"","pagination":{"sort":null,"start":0,"total":4,"limit":1000000},"state":"complete","tags":"","published":"2014-08-10T11:03:27-04:00","id":80106}