{"type":"FeatureCollection","url":"http://maps.google.ca/maps/ms?hl=en&ie=UTF8&vps=1&jsv=304d&msa=0&output=georss&msid=208195469145691961666.000497f07b00f3f74d1df","data_type":"Data Feed","url_type":"rss","permissions":[{"permissions":{"download":true,"view":true},"group_id":"everyone"}],"classification":null,"title":"Jim Shambo State Farm Insurance","count":1,"stream_id":81585,"contributor":{"url":"http://geocommons.com/users/19931","name":"jimshambo"},"data_attributes":null,"calculation_params":null,"icon_link":null,"link":"http://geocommons.com/overlays/81585.json","extent":[-84.0522,33.9551,-84.0522,33.9551],"geometry_types":["point"],"unique_name":null,"name":"Jim Shambo State Farm Insurance","feature_count":1,"description":"State Farm Insurance agent Jim Shambo provides free insurance quotes for auto insurance, home insurance, life insurance, renters insurance, business insurance and car insurance in Lawrenceville, GA","next_feature":null,"is_raster":false,"short_classification":"Y","stats":{"georss:elev":{"max":0.0,"min":0.0,"median":0.0}},"features":[{"properties":{"guid":"000497f07b0368e4aad6c","title":"Jim Shambo State Farm Insurance","published":{"end_time":"2010/12/21 14:16:59 -0500","original":"Tue, 21 Dec 2010 19:16:58 +0000","granularity":"sec","time":"2010/12/21 14:16:58 -0500"},"description":"<a href=\"http://www.insuringlawrenceville.com/\">State Farm Insurance</a> agent Jim Shambo provides free insurance quotes for auto insurance, home insurance, life insurance, renters insurance, business insurance and car insurance in Lawrenceville, GA. ","id":"a655nuyly9u1","georss:elev":0.0},"type":"Feature","geometry":{"type":"Point","coordinates":[-84.052177,33.955086]}}],"is_temporal":true,"author":{"url":"","metadata":"","contact_name":"","contact_address":"","source":"","contact_phone":""},"source":"","pagination":{"sort":null,"start":0,"total":1,"limit":1000000},"state":"complete","tags":"ga,insurance,lawrenceville,state farm","published":"2014-08-10T12:39:50-04:00","id":81585}