{"type":"FeatureCollection","data_type":"Dataset","url_type":null,"permissions":[{"permissions":{"download":true,"view":true},"group_id":"everyone"}],"classification":null,"title":"Excel Test","count":2,"stream_id":8317,"contributor":{"url":"http://geocommons.com/users/3619","name":"eric.franklin"},"data_attributes":null,"calculation_params":null,"icon_link":null,"link":"http://geocommons.com/overlays/8317.json","extent":[-77.4142,38.8749,-77.3112,38.9538],"geometry_types":["point"],"unique_name":null,"name":"Excel Test","feature_count":2,"description":"Excel Test","next_feature":null,"is_raster":false,"short_classification":"Y","stats":{"latitude":{"max":38.953757,"mean":38.9143075,"variance":0.00311252610049999,"stdev":0.0557900179288373,"min":38.874858,"median":38.953757},"longitude":{"max":-77.311156,"mean":-77.3626785,"variance":0.0053091360125009,"stdev":0.072863818267374,"min":-77.414201,"median":-77.311156}},"features":[{"properties":{"name":"3FH","latitude":38.874858,"longitude":-77.311156,"id":"a626dbtqsckd"},"type":"Feature","geometry":{"type":"Point","coordinates":[-77.311156,38.874858]}},{"properties":{"name":"DEP","latitude":38.953757,"longitude":-77.414201,"id":"a626dbz84lfz"},"type":"Feature","geometry":{"type":"Point","coordinates":[-77.414201,38.953757]}}],"is_temporal":false,"author":{"url":"","metadata":"","contact_name":"","contact_address":"","source":"","contact_phone":""},"source":"","pagination":{"sort":null,"start":0,"total":2,"limit":1000000},"state":"complete","tags":"excel,franklin","published":"2008-12-17T12:00:00Z","id":8317}