{"type":"FeatureCollection","data_type":"Dataset","url_type":null,"permissions":[{"permissions":{"download":true,"view":true},"group_id":"everyone"}],"classification":null,"title":"Preveza","count":1,"stream_id":8396,"contributor":{"url":"http://geocommons.com/users/3767","name":"ckaratzoglou"},"data_attributes":null,"calculation_params":null,"icon_link":null,"link":"http://geocommons.com/overlays/8396.json","extent":[20.6968,39.154,20.6968,39.154],"geometry_types":["point"],"unique_name":null,"name":"Preveza","feature_count":1,"description":"","next_feature":null,"is_raster":false,"short_classification":"Y","stats":{},"features":[{"properties":{"name":"Preveza, Greece","id":"a6euc5oqak2l"},"type":"Feature","geometry":{"type":"Point","coordinates":[20.69682,39.153954]}}],"is_temporal":false,"author":{"url":"","metadata":"","contact_name":"","contact_address":"","source":"","contact_phone":""},"source":"","pagination":{"sort":null,"start":0,"total":1,"limit":1000000},"state":"complete","tags":"ΥΠΗΡΕΣΙΕΣ","published":"2014-08-11T09:53:27-04:00","id":8396}