{"type":"FeatureCollection","data_type":"Dataset","url_type":null,"permissions":[{"permissions":{"download":true,"view":true},"group_id":"everyone"}],"classification":null,"title":"Austin Carpet Cleaning","count":1,"stream_id":84785,"contributor":{"url":"http://geocommons.com/users/20620","name":"befoundsmaps"},"data_attributes":null,"calculation_params":null,"icon_link":null,"link":"http://geocommons.com/overlays/84785.json","extent":[-97.7385,30.2653,-97.7385,30.2653],"geometry_types":["point"],"unique_name":null,"name":"Austin Carpet Cleaning","feature_count":1,"description":"Austin Carpet Cleaning has an outstanding record of success as well as vast experience in cleaning and maintaining all commercial and residential carpets, area rugs, wooden floors, upholstery, air ducts, tiles and grout, drapes, yards, moving home and automobile interiors.\n\nAustin Carpet Cleaning is well known for using only the most tried and tested cleaning methods, state of the art equipment and environment friendly chemicals and cleaning agents.","next_feature":null,"is_raster":false,"short_classification":"Y","stats":{},"features":[{"properties":{"city":"Austin","name":"Austin Carpet Cleaning","region":"US-TX","balloon_text":"<b><a href=\"http://maps.google.com/maps/place?cid=9476637926067007463&amp;q=Austin+Carpet+Cleaning&amp;hl=en&amp;cd=3&amp;cad=src:kml_balloon&amp;ei=6nwwTYPlM5DcugOygJHSAQ\">$[name]</a></b>3 reviews500 E 4th STAustin, TX 78701(512) 318-2649<a href=\"http://austintxcarpetcleaner.com/\">austintxcarpetcleaner.com</a><a href=\"/maps/place?cid=9476637926067007463&amp;q=Austin+Carpet+Cleaning&amp;hl=en&amp;cd=4&amp;cad=src:ppphoto&amp;ei=6nwwTYPlM5DcugOygJHSAQ\"><img src=\"http://lh3.googleusercontent.com/public/8AdpARUgntRCe5MdqsgbJRwAtvzBHpF9R1QvJT-2g4Wv1hqWb6rTKMRNOPlpCd13jVehBf1k5LhQBvZ8bKQDH-xirZeg0EADMLYzy_rUOzccgsPJ15XRPJbn\"></a>  $[geDirections]","contents":"Austin Carpet Cleaning","id":"a639v2z5z2yj"},"type":"Feature","geometry":{"type":"Point","coordinates":[-97.738464,30.265299]}}],"is_temporal":false,"author":{"url":"http://bbs.keyhole.com/ubb/ubbthreads.php?ubb=showflat&Number=1394135&#Post1394135","metadata":"","contact_name":"Justin Rey","contact_address":"500 E 4th St, \nAustin, TX 78701","source":"Google Earth Community","contact_phone":"512-318-2649"},"source":"http://bbs.keyhole.com/ubb/ubbthreads.php?ubb=showflat&Number=1394135&#Post1394135","pagination":{"sort":null,"start":0,"total":1,"limit":1000000},"state":"complete","tags":"carpet,cleaners,cleaning","published":"2014-08-10T17:13:14-04:00","id":84785}