{"type":"FeatureCollection","url":"http://maps.google.ca/maps/ms?vps=2&jsv=308a&hl=en&ie=UTF8&msa=0&output=georss&msid=201819128241354197215.00049a0edc5ec9904d1d6","data_type":"Data Feed","url_type":"rss","permissions":[{"permissions":{"download":true,"view":true},"group_id":"everyone"}],"classification":null,"title":"Josh Ragsdale State Farm Insurance","count":1,"stream_id":85468,"contributor":{"url":"http://geocommons.com/users/20915","name":"joshragsdale"},"data_attributes":null,"calculation_params":null,"icon_link":null,"link":"http://geocommons.com/overlays/85468.json","extent":[-96.7335,33.19,-96.7335,33.19],"geometry_types":["point"],"unique_name":null,"name":"Josh Ragsdale State Farm Insurance","feature_count":1,"description":"State Farm Insurance agent Josh Ragsdale provides free insurance quotes for auto insurance, home insurance, life insurance, renters insurance, business insurance and car insurance in McKinney, TX. (972) 347-6222. http://www.thanksjosh.com","next_feature":null,"is_raster":false,"short_classification":"Y","stats":{"published":{"max":"2011/01/17 13:22:04 -0500","min":"2011/01/17 13:22:04 -0500","median":"2011/01/17 13:22:04 -0500"},"georss:elev":{"max":0.0,"min":0.0,"median":0.0}},"features":[{"properties":{"title":"Josh Ragsdale State Farm Insurance","guid":"00049a0edc61778782090","published":{"end_time":"2011/01/17 13:22:05 -0500","original":"Mon, 17 Jan 2011 18:22:04 +0000","granularity":"sec","time":"2011/01/17 13:22:04 -0500"},"description":"State Farm Insurance agent Josh Ragsdale provides free insurance quotes for auto insurance, home insurance, life insurance, renters insurance, business insurance and car insurance in McKinney, TX. (972) 347-6222. http://www.thanksjosh.com","id":"a62pdqqcrumd","georss:elev":0.0},"type":"Feature","geometry":{"type":"Point","coordinates":[-96.733505,33.189953]}}],"is_temporal":true,"author":{"url":"","metadata":"","contact_name":"","contact_address":"","source":"","contact_phone":""},"source":"","pagination":{"sort":null,"start":0,"total":1,"limit":1000000},"state":"complete","tags":"farm,insurance,mckinney,state","published":"2014-08-10T18:22:55-04:00","id":85468}