{"type":"FeatureCollection","url":"http://maps.google.com/maps/ms?vps=1&jsv=310c&hl=en&ie=UTF8&msa=0&output=georss&msid=200867393817550685653.00049a9dacc6efa4a54f6","data_type":"Data Feed","url_type":"rss","permissions":[{"permissions":{"download":true,"view":true},"group_id":"everyone"}],"classification":null,"title":"Al Clark State Farm Insurance","count":1,"stream_id":87164,"contributor":{"url":"http://geocommons.com/users/21237","name":"alclark"},"data_attributes":null,"calculation_params":null,"icon_link":null,"link":"http://geocommons.com/overlays/87164.json","extent":[-97.1491,32.6737,-97.1491,32.6737],"geometry_types":["point"],"unique_name":null,"name":"Al Clark State Farm Insurance","feature_count":1,"description":"State Farm Insurance agent Al Clark providing free insurance quotes for auto insurance, home insurance, life insurance, renters insurance, business insurance and car insurance in Arlington, TX. Address: 2452 W Interstate 20, Arlington, TX 76017-1670. Phone: (817) 468-3033. Website: http://www.alclark.net/","next_feature":null,"is_raster":false,"short_classification":"Y","stats":{"published":{"max":"2011/01/24 15:45:06 -0500","min":"2011/01/24 15:45:06 -0500","median":"2011/01/24 15:45:06 -0500"},"georss:elev":{"max":0.0,"min":0.0,"median":0.0}},"features":[{"properties":{"title":"Al Clark State Farm Insurance","guid":"00049a9dacc800f858502","published":{"end_time":"2011/01/24 15:45:07 -0500","original":"Mon, 24 Jan 2011 20:45:06 +0000","granularity":"sec","time":"2011/01/24 15:45:06 -0500"},"description":"State Farm Insurance agent Al Clark providing free insurance quotes for auto insurance, home insurance, life insurance, renters insurance, business insurance and car insurance in Arlington, TX. Phone: (817) 468-3033. Website: http://www.alclark.net/","id":"a673ptd2f5jn","georss:elev":0.0},"type":"Feature","geometry":{"type":"Point","coordinates":[-97.149117,32.673717]}}],"is_temporal":true,"author":{"url":"","metadata":"","contact_name":"","contact_address":"","source":"","contact_phone":""},"source":"","pagination":{"sort":null,"start":0,"total":1,"limit":1000000},"state":"complete","tags":"al,arlington,clark,farm,insurance,quote,state,texas,tx","published":"2014-08-10T21:10:21-04:00","id":87164}