{"type":"FeatureCollection","data_type":"Dataset","url_type":null,"permissions":[{"permissions":{"download":true,"view":true},"group_id":"everyone"}],"classification":null,"title":"Green Party Foursquare","count":4,"stream_id":92209,"contributor":{"url":"http://geocommons.com/users/12003","name":"LauraHale"},"data_attributes":null,"calculation_params":null,"icon_link":null,"link":"http://geocommons.com/overlays/92209.json","extent":[144.967,-37.8175,144.967,-37.8175],"geometry_types":["point"],"unique_name":null,"name":"Green Party Foursquare","feature_count":4,"description":"","next_feature":null,"is_raster":false,"short_classification":"Y","stats":{"check ins":{"max":81,"mean":79.5,"variance":1.66666666666667,"stdev":1.29099444873581,"min":78,"median":80},"latitude":{"max":-37.817532,"mean":-37.817532,"variance":0.0,"stdev":0.0,"min":-37.817532,"median":-37.817532},"date":{"max":"2011/01/27 00:00:00 -0500","mean":"2011/01/21 06:00:00 -0500","variance":290511360000.0,"stdev":538991.057439732,"min":"2011/01/13 00:00:00 -0500","median":"2011/01/25 00:00:00 -0500"},"daily checkin count":{"max":1,"mean":1.0,"variance":0.0,"stdev":0.0,"min":1,"median":1},"longitude":{"max":144.967148,"mean":144.967148,"variance":0.0,"stdev":0.0,"min":144.967148,"median":144.967148},"people":{"max":7,"mean":7.0,"variance":0.0,"stdev":0.0,"min":7,"median":7},"daily people count":{"max":0,"mean":0.0,"variance":0.0,"stdev":0.0,"min":0,"median":0}},"features":[{"properties":{"check ins":78,"city":"Melbourne","name":"Australian Greens Victoria State Office","latitude":-37.817532,"date":{"end_time":"2011/01/14 00:00:00 -0500","original":"13-Jan-11","granularity":"day","time":"2011/01/13 00:00:00 -0500"},"daily checkin count":1,"longitude":144.967148,"people":7,"link":"http://foursquare.com/venue/1270192","id":"a678zigruuca","daily people count":0,"state":"Victoria","party":"Green"},"type":"Feature","geometry":{"type":"Point","coordinates":[144.967148,-37.817532]}},{"properties":{"check ins":79,"city":"Melbourne","name":"Australian Greens Victoria State Office","latitude":-37.817532,"date":{"end_time":"2011/01/21 00:00:00 -0500","original":"20-Jan-11","granularity":"day","time":"2011/01/20 00:00:00 -0500"},"daily checkin count":1,"longitude":144.967148,"people":7,"link":"http://foursquare.com/venue/1270192","id":"a678ziecoyw2","daily people count":0,"state":"Victoria","party":"Green"},"type":"Feature","geometry":{"type":"Point","coordinates":[144.967148,-37.817532]}},{"properties":{"check ins":80,"city":"Melbourne","name":"Australian Greens Victoria State Office","latitude":-37.817532,"date":{"end_time":"2011/01/26 00:00:00 -0500","original":"25-Jan-11","granularity":"day","time":"2011/01/25 00:00:00 -0500"},"daily checkin count":1,"longitude":144.967148,"people":7,"link":"http://foursquare.com/venue/1270192","id":"a678zifl17tf","daily people count":0,"state":"Victoria","party":"Green"},"type":"Feature","geometry":{"type":"Point","coordinates":[144.967148,-37.817532]}},{"properties":{"check ins":81,"city":"Melbourne","name":"Australian Greens Victoria State Office","latitude":-37.817532,"date":{"end_time":"2011/01/28 00:00:00 -0500","original":"27-Jan-11","granularity":"day","time":"2011/01/27 00:00:00 -0500"},"daily checkin count":1,"longitude":144.967148,"people":7,"link":"http://foursquare.com/venue/1270192","id":"a678zi9wtfla","daily people count":0,"state":"Victoria","party":"Green"},"type":"Feature","geometry":{"type":"Point","coordinates":[144.967148,-37.817532]}}],"is_temporal":true,"author":{"url":"","metadata":"","contact_name":"","contact_address":"","source":"","contact_phone":""},"source":"","pagination":{"sort":null,"start":0,"total":4,"limit":1000000},"state":"complete","tags":"#ausvotes,geen","published":"2014-08-10T13:52:09-04:00","id":92209}