{"type":"FeatureCollection","data_type":"Dataset","url_type":null,"permissions":[{"permissions":{"download":true,"view":true},"group_id":"everyone"}],"classification":null,"title":"Wal-Mart Locations, By Country ","count":13,"stream_id":9233,"contributor":{"url":"http://geocommons.com/users/2943","name":"Margot"},"data_attributes":null,"calculation_params":null,"icon_link":null,"link":"http://geocommons.com/overlays/9233.json","extent":[-101.956,-37.0907,139.838,54.3139],"geometry_types":["point"],"unique_name":null,"name":"Wal-Mart Locations, By Country ","feature_count":13,"description":"In 1991, Wal-Mart became an international company when we opened a Sam's Club near Mexico City. Just two years later, Wal-Mart International was created.\n\nToday, Wal-Mart International is a fast-growing part of Wal-Mart's overall operations, with over 3,500 stores and more than 680,000 associates in 15 markets outside the continental U.S.:\n\nMap shows the total number of &quot;retail units,&quot; which includes Wal-Mart Supercenters, Sam's Clubs, joint-ventures, and majority-owned subsidiaries, for each country where they have international operations. ","next_feature":null,"is_raster":false,"short_classification":"Y","stats":{"stores":{"max":1201,"mean":262.769230769231,"variance":96557.1923076923,"stdev":310.736531981182,"min":28,"median":164},"lat":{"max":54.313919,"mean":17.6437713846154,"variance":578.848770951274,"stdev":24.0592761934202,"min":-37.090698,"median":15.77625},"long":{"max":139.838287,"mean":-43.0237922307692,"variance":6031.85440380263,"stdev":77.6650140269261,"min":-101.956253,"median":-79.641721}},"features":[{"properties":{"country":"Argentina","stores":28,"id":"a62pqq6kyoqm","lat":-37.090698,"long":-63.584808},"type":"Feature","geometry":{"type":"Point","coordinates":[-63.584808,-37.090698]}},{"properties":{"country":"Brazil","stores":349,"id":"a62pqqaarc83","lat":-14.24292,"long":-54.387829},"type":"Feature","geometry":{"type":"Point","coordinates":[-54.387829,-14.24292]}},{"properties":{"country":"Canada","stores":310,"id":"a62pqqf4zp0m","lat":43.588208,"long":-79.641721},"type":"Feature","geometry":{"type":"Point","coordinates":[-79.641721,43.588208]}},{"properties":{"country":"China","stores":225,"id":"a62pqq4f8vql","lat":36.894451,"long":104.165649},"type":"Feature","geometry":{"type":"Point","coordinates":[104.165649,36.894451]}},{"properties":{"country":"Costa Rica","stores":164,"id":"a62pqq6yrmhz","lat":9.62489,"long":-84.253311},"type":"Feature","geometry":{"type":"Point","coordinates":[-84.253311,9.62489]}},{"properties":{"country":"El Salvador","stores":77,"id":"a62pqqd2ld4j","lat":13.79687,"long":-88.918793},"type":"Feature","geometry":{"type":"Point","coordinates":[-88.918793,13.79687]}},{"properties":{"country":"Guatemala","stores":160,"id":"a62pqq3m1fxa","lat":15.77625,"long":-90.232307},"type":"Feature","geometry":{"type":"Point","coordinates":[-90.232307,15.77625]}},{"properties":{"country":"Honduras","stores":50,"id":"a62pqqeejnt3","lat":14.50472,"long":-86.253098},"type":"Feature","geometry":{"type":"Point","coordinates":[-86.253098,14.50472]}},{"properties":{"country":"Japan","stores":387,"id":"a62pqq4xti6g","lat":37.487598,"long":139.838287},"type":"Feature","geometry":{"type":"Point","coordinates":[139.838287,37.487598]}},{"properties":{"country":"Mexico","stores":1201,"id":"a62pqqe4htia","lat":23.62574,"long":-101.956253},"type":"Feature","geometry":{"type":"Point","coordinates":[-101.956253,23.62574]}},{"properties":{"country":"Nicaragua","stores":51,"id":"a62pqqjhsywt","lat":12.86672,"long":-85.424049},"type":"Feature","geometry":{"type":"Point","coordinates":[-85.424049,12.86672]}},{"properties":{"country":"Puerto Rico","stores":56,"id":"a62pqq4ixq73","lat":18.22328,"long":-66.428886},"type":"Feature","geometry":{"type":"Point","coordinates":[-66.428886,18.22328]}},{"properties":{"country":"UK","stores":358,"id":"a62pqq5gk9gn","lat":54.313919,"long":-2.23218},"type":"Feature","geometry":{"type":"Point","coordinates":[-2.23218,54.313919]}}],"is_temporal":false,"author":{"url":"http://walmartstores.com/AboutUs/246.aspx","metadata":"http://walmartstores.com/AboutUs/246.aspx","contact_name":"","contact_address":"","source":"Walmartstores.com","contact_phone":""},"source":"http://walmartstores.com/AboutUs/246.aspx","pagination":{"sort":null,"start":0,"total":13,"limit":1000000},"state":"complete","tags":"countries,international,retail,stores,walmart,world","published":"2009-01-01T12:00:00Z","id":9233}