{"type":"FeatureCollection","data_type":"Dataset","url_type":null,"permissions":[{"permissions":{"download":true,"view":true},"group_id":"everyone"}],"classification":null,"title":"Faith Based","count":2,"stream_id":92429,"contributor":{"url":"http://geocommons.com/users/22017","name":"swiafe"},"data_attributes":null,"calculation_params":null,"icon_link":null,"link":"http://geocommons.com/overlays/92429.json","extent":[-117.259,34.0532,-90.2396,38.6171],"geometry_types":["point"],"unique_name":null,"name":"Faith Based","feature_count":2,"description":"","next_feature":null,"is_raster":false,"short_classification":"Y","stats":{"x":{"max":-90.239575,"mean":-103.749387,"variance":365.030040550688,"stdev":19.1057593555108,"min":-117.259199,"median":-90.239575},"y":{"max":38.617149,"mean":36.335197,"variance":10.414609860608,"stdev":3.22716746708441,"min":34.053245,"median":38.617149}},"features":[{"properties":{"city_1":"Loma Linda","nutritiond":"Y","zip":"92354.000000","fid_":null,"vegnutrirs":"Y","x":-117.259199,"state_1":"CA","y":34.053245,"_accredit":"ASPH","gis_cour":"Y","fbased":"Y","gisprogs":"Y","id":"a6gs4s8epuaj","address":"24951 North Circle Drive","school":"Loma Linda University School of Public Health","gislab":"Y","sch_pro":"S"},"type":"Feature","geometry":{"type":"Point","coordinates":[-117.259199,34.053245]}},{"properties":{"city_1":"St. Louis","nutritiond":"N","zip":"63104.000000","fid_":null,"vegnutrirs":"N","x":-90.239575,"state_1":"MO","y":38.617149,"_accredit":"ASPH","gis_cour":"N","fbased":"Y","gisprogs":"N","id":"a6gs4s4zupp0","address":"3545 Lafayette Ave","school":"Saint Louis University School of Public Health","gislab":"N","sch_pro":"S"},"type":"Feature","geometry":{"type":"Point","coordinates":[-90.239575,38.617149]}}],"is_temporal":false,"author":{"url":"","metadata":"","contact_name":"","contact_address":"","source":"","contact_phone":""},"source":"","pagination":{"sort":null,"start":0,"total":2,"limit":1000000},"state":"complete","tags":"","published":"2014-08-10T14:06:16-04:00","id":92429}