{"type":"FeatureCollection","data_type":"Dataset","url_type":null,"permissions":[{"permissions":{"download":true,"view":true},"group_id":"everyone"}],"classification":null,"title":"Perdekraal alternative access points","count":2,"stream_id":93350,"contributor":{"url":"http://geocommons.com/users/12617","name":"quintonl"},"data_attributes":null,"calculation_params":null,"icon_link":null,"link":"http://geocommons.com/overlays/93350.json","extent":[20.0839,-33.0695,20.1403,-33.049],"geometry_types":["point"],"unique_name":null,"name":"Perdekraal alternative access points","feature_count":2,"description":"","next_feature":null,"is_raster":false,"short_classification":"Y","stats":{"Id":{"max":0,"mean":0.0,"variance":0.0,"stdev":0.0,"min":0,"median":0}},"features":[{"properties":{"Id":0,"id":"a686o34n0wxg"},"type":"Feature","geometry":{"type":"Point","coordinates":[20.0838726386169,-33.0694963631154]}},{"properties":{"Id":0,"id":"a686o2tu236m"},"type":"Feature","geometry":{"type":"Point","coordinates":[20.1403069319827,-33.0489747810113]}}],"is_temporal":false,"author":{"url":"","metadata":"","contact_name":"","contact_address":"","source":"","contact_phone":""},"source":"","pagination":{"sort":null,"start":0,"total":2,"limit":1000000},"state":"complete","tags":"","published":"2014-08-10T15:18:17-04:00","id":93350}