{"type":"FeatureCollection","data_type":"Dataset","url_type":null,"permissions":[{"permissions":{"download":true,"view":true},"group_id":"everyone"}],"classification":null,"title":"Classeur1","count":1,"stream_id":94594,"contributor":{"url":"http://geocommons.com/users/22355","name":"anasovic"},"data_attributes":null,"calculation_params":null,"icon_link":null,"link":"http://geocommons.com/overlays/94594.json","extent":[-92.2425,34.1467,-92.2425,34.1467],"geometry_types":["point"],"unique_name":null,"name":"Classeur1","feature_count":1,"description":"","next_feature":null,"is_raster":false,"short_classification":"Y","stats":{},"features":[{"properties":{"ville":"Algiers","nom de l'tablissement":"Institut des finances et management (IFMA)","pays":"Algeria","geo_score":0.456,"adresse":"13 c avenue Messaoud-Taleb (ex Carnot), BP 351, El Biar","code postal":"16000","id":"a6ge5tjbxvj0","continent":"AFRIQUE","geo_precision":"street"},"type":"Feature","geometry":{"type":"Point","coordinates":[-92.242466,34.146682]}}],"is_temporal":false,"author":{"url":"","metadata":"","contact_name":"","contact_address":"","source":"","contact_phone":""},"source":"","pagination":{"sort":null,"start":0,"total":1,"limit":1000000},"state":"complete","tags":"","published":"2014-08-10T16:45:07-04:00","id":94594}