{"type":"FeatureCollection","data_type":"Dataset","url_type":null,"permissions":[{"permissions":{"download":true,"view":true},"group_id":"everyone"}],"classification":null,"title":"Sacramento Plumbing","count":1,"stream_id":95288,"contributor":{"url":"http://geocommons.com/users/20620","name":"befoundsmaps"},"data_attributes":null,"calculation_params":null,"icon_link":null,"link":"http://geocommons.com/overlays/95288.json","extent":[-121.49,38.5611,-121.49,38.5611],"geometry_types":["point"],"unique_name":null,"name":"Sacramento Plumbing","feature_count":1,"description":"When you need plumbing contractors, trust the honesty, integrity and craftsmanship of Sacramento Plumbing services.  We offer a 24-hour emergency repair service, the same day service with the highest quality in plumbing work.\n\nAt Sacramento, we install quality! Quality that will put your plumbing system on the path towards worry-free operation! If your faucet has a runny nose, the toilet has a wobbly seat or the pipes are leaking or anything in between, you can count on Sacramento Plumbing!","next_feature":null,"is_raster":false,"short_classification":"Y","stats":{},"features":[{"properties":{"city":"Sacramento","name":"Sacramento Plumbing","region":"US-CA","balloon_text":"<b><a href=\"http://maps.google.com/maps/place?cid=10261773133604706285&amp;q=Sacramento+Plumbing&amp;hl=en&amp;cd=1&amp;cad=src:kml_balloon&amp;ei=6ixlTe7FJsr5kAXavsS8DA\">$[name]</a></b><img src=\"http://www.google.com/images/syt-star-on.gif\" alt=\"Rated 5.0 out of 5.0\"> <img src=\"http://www.google.com/images/syt-star-on.gif\" alt=\"\"> <img src=\"http://www.google.com/images/syt-star-on.gif\" alt=\"\"> <img src=\"http://www.google.com/images/syt-star-on.gif\" alt=\"\"> <img src=\"http://www.google.com/images/syt-star-on.gif\" alt=\"\"> 5 reviews1712 BroadwaySacramento, CA 95818(916) 237-8559<a href=\"http://sacramentocaplumbing.net/\">sacramentocaplumbing.net</a><a href=\"/maps/place?cid=10261773133604706285&amp;q=Sacramento+Plumbing&amp;hl=en&amp;cd=2&amp;cad=src:ppphoto&amp;ei=6ixlTe7FJsr5kAXavsS8DA\"><img src=\"http://lh3.googleusercontent.com/public/KB00ayWBDUquqs3HDNLyRHUAkOBRY9Va_g9gEhAi9Jq2wp9R2khLHUqeO0FdrnCaOXjiE4Aq_WspmRUoISgvNzvEXjplbO4-X5ABGtddPwoVyUaLftlLl_3I\"></a><b>High skilled</b>  <img src=\"http://www.google.com/images/sy-star-on.gif\"><img src=\"http://www.google.com/images/sy-star-on.gif\"><img src=\"http://www.google.com/images/sy-star-on.gif\"><img src=\"http://www.google.com/images/sy-star-on.gif\"><img src=\"http://www.google.com/images/sy-star-on.gif\">  -  Gary C.  -  Sep 20, 2010The installation of the plumbing system of my house was perfectly done by this Sacramento plumbing company. They have highly skilled plumbers and high <b>...</b> <a href=\"http://maps.google.com/local_url?q=http://www.judysbook.com/members/208075/posts/2010/9/8865717/&amp;dq=Sacramento+Plumbing&amp;near=Sacramento,+CA&amp;output=kml&amp;ie=utf-8&amp;v=2.2&amp;cv=6.0.1.2032&amp;hl=en&amp;s=ANYYN7kiqLeSjzDr_5jS9xEix6WPl1ly1A\">More from judysbook.com »</a><a href=\"http://maps.google.com/maps/place?cid=10261773133604706285&amp;q=Sacramento+Plumbing&amp;hl=en&amp;cd=1&amp;cad=src:kml_balloon&amp;ei=6ixlTe7FJsr5kAXavsS8DA&amp;dtab=2\">See all 5 reviews »</a>  $[geDirections]","contents":"Sacramento Plumbing","id":"a676qvueh5ra"},"type":"Feature","geometry":{"type":"Point","coordinates":[-121.490461,38.561086]}}],"is_temporal":false,"author":{"url":"http://bbs.keyhole.com/ubb/ubbthreads.php?ubb=showflat&Number=1403149&#Post1403149","metadata":"","contact_name":"Freddie Minchi","contact_address":"1712 Broadway, \nSacramento, CA 95818","source":"Google Earth Community","contact_phone":"916-237-8559"},"source":"http://bbs.keyhole.com/ubb/ubbthreads.php?ubb=showflat&Number=1403149&#Post1403149","pagination":{"sort":null,"start":0,"total":1,"limit":1000000},"state":"complete","tags":"company,emergency,plumber,plumbing,service","published":"2014-08-10T18:01:18-04:00","id":95288}