{"type":"FeatureCollection","data_type":"Dataset","url_type":null,"permissions":[{"permissions":{"download":true,"view":true},"group_id":"everyone"}],"classification":null,"title":"Mock Data Set","count":2,"stream_id":96819,"contributor":{"url":"http://geocommons.com/users/22097","name":"jessharig"},"data_attributes":null,"calculation_params":null,"icon_link":null,"link":"http://geocommons.com/overlays/96819.json","extent":[-77.0294,38.9257,-71.4867,41.3654],"geometry_types":["point"],"unique_name":null,"name":"Mock Data Set","feature_count":2,"description":"","next_feature":null,"is_raster":false,"short_classification":"Y","stats":{},"features":[{"properties":{"city":"Narragansett","zip":"02882","geo_score":0.869,"id":"a6o01ch5i7pk","geo_precision":"zip","state":"RI"},"type":"Feature","geometry":{"type":"Point","coordinates":[-71.486723,41.36538]}},{"properties":{"city":"Washingto","zip":"20010","geo_score":0.886,"id":"a6o01cabfy71","geo_precision":"zip","state":"DC"},"type":"Feature","geometry":{"type":"Point","coordinates":[-77.029421,38.925667]}}],"is_temporal":false,"author":{"url":"","metadata":"","contact_name":"","contact_address":"","source":"","contact_phone":""},"source":"","pagination":{"sort":null,"start":0,"total":2,"limit":1000000},"state":"complete","tags":"nada","published":"2014-08-10T21:13:34-04:00","id":96819}