{"type":"FeatureCollection","data_type":"Dataset","url_type":null,"permissions":[{"permissions":{"download":true,"view":true},"group_id":"everyone"}],"classification":null,"title":"2010 Classroom Earth Course Grant Winners","count":10,"stream_id":98805,"contributor":{"url":"http://geocommons.com/users/22097","name":"jessharig"},"data_attributes":null,"calculation_params":null,"icon_link":null,"link":"http://geocommons.com/overlays/98805.json","extent":[-122.693,25.7743,-75.3266,47.64],"geometry_types":["point"],"unique_name":null,"name":"2010 Classroom Earth Course Grant Winners","feature_count":10,"description":"","next_feature":null,"is_raster":false,"short_classification":"Y","stats":{},"features":[{"properties":{"geo_score":0.714,"zip code":"36544","teacher":"Lynne Stewart","id":"a6p7tzl8d0ja","geo_precision":"zip"},"type":"Feature","geometry":{"type":"Point","coordinates":[-88.241948,30.452142]}},{"properties":{"geo_score":0.714,"zip code":"59436","teacher":"Raimun Hahn","id":"a6p7tzhw758h","geo_precision":"zip"},"type":"Feature","geometry":{"type":"Point","coordinates":[-111.859438,47.639953]}},{"properties":{"geo_score":0.714,"zip code":"19083","teacher":"Mitchell Trembicki","id":"a6p7tzaa3usa","geo_precision":"zip"},"type":"Feature","geometry":{"type":"Point","coordinates":[-75.326577,39.973167]}},{"properties":{"geo_score":0.714,"zip code":"55432","teacher":"Sada Ganske","id":"a6p7tzbwrhxy","geo_precision":"zip"},"type":"Feature","geometry":{"type":"Point","coordinates":[-93.263836,44.979965]}},{"properties":{"geo_score":0.714,"zip code":"60423","teacher":"Scott McCreary","id":"a6p7tziyxqz1","geo_precision":"zip"},"type":"Feature","geometry":{"type":"Point","coordinates":[-87.806994,41.502534]}},{"properties":{"geo_score":0.714,"zip code":"33101","teacher":"Remy Dou","id":"a6p7tzgi33qo","geo_precision":"zip"},"type":"Feature","geometry":{"type":"Point","coordinates":[-80.193659,25.774266]}},{"properties":{"geo_score":0.714,"zip code":"55199","teacher":"James Lorenz","id":"a6p7tz9hdmyj","geo_precision":"zip"},"type":"Feature","geometry":{"type":"Point","coordinates":[-93.093274,44.94441]}},{"properties":{"geo_score":0.714,"zip code":"97201","teacher":"Tom McKenna","id":"a6p7tzi8wlbl","geo_precision":"zip"},"type":"Feature","geometry":{"type":"Point","coordinates":[-122.693157,45.498931]}},{"properties":{"geo_score":0.714,"zip code":"54968","teacher":"Joe Waters","id":"a6p7tzf967oe","geo_precision":"zip"},"type":"Feature","geometry":{"type":"Point","coordinates":[-89.122651,43.832741]}},{"properties":{"geo_score":0.714,"zip code":"44026","teacher":"Michael B. Sustin","id":"a6p7tzn5ch8a","geo_precision":"zip"},"type":"Feature","geometry":{"type":"Point","coordinates":[-81.337887,41.534218]}}],"is_temporal":false,"author":{"url":"","metadata":"","contact_name":"","contact_address":"","source":"","contact_phone":""},"source":"","pagination":{"sort":null,"start":0,"total":10,"limit":1000000},"state":"complete","tags":"","published":"2014-08-10T22:58:51-04:00","id":98805}