{"type":"FeatureCollection","data_type":"Dataset","url_type":null,"permissions":[{"permissions":{"download":true,"view":true},"group_id":"everyone"}],"classification":null,"title":"Prueba","count":1,"stream_id":9978,"contributor":{"url":"http://geocommons.com/users/4958","name":"prueba-edars"},"data_attributes":null,"calculation_params":null,"icon_link":null,"link":"http://geocommons.com/overlays/9978.json","extent":[-2.7801,37.1411,-2.7801,37.1411],"geometry_types":["point"],"unique_name":null,"name":"Prueba","feature_count":1,"description":"","next_feature":null,"is_raster":false,"short_classification":"Y","stats":{},"features":[{"properties":{"name":"ABLA","description":"<img src=\"http://www.aguasdesevilla.com/uploads/pics/edar_sur_01.jpg\" width=\"300\" height=\"100\">2008\nDBO5 (mgO2/l)\nDQO (mgO2/l)\nSS (mg/l)\nJunio \n---\nJulio \n5427161\nAgosto \n1622592\nSeptiembre \n9119750.7\nOctubre \n145186\nNoviembre \n179367\nDiciembre \n399829\n","id":"a6nfltm5ox2c"},"type":"Feature","geometry":{"type":"Point","coordinates":[-2.78010399901996,37.1411450007925]}}],"is_temporal":false,"author":{"url":"","metadata":"","contact_name":"","contact_address":"","source":"","contact_phone":""},"source":"","pagination":{"sort":null,"start":0,"total":1,"limit":1000000},"state":"complete","tags":"","published":"2014-08-11T11:26:47-04:00","id":9978}