{"type":"FeatureCollection","data_type":"Dataset","url_type":null,"permissions":[{"permissions":{"download":true,"view":true},"group_id":"everyone"}],"classification":null,"title":"kcrex2","count":16,"stream_id":99931,"contributor":{"url":"http://geocommons.com/users/22998","name":"readkc"},"data_attributes":null,"calculation_params":null,"icon_link":null,"link":"http://geocommons.com/overlays/99931.json","extent":[-76.7738,36.8468,-76.2852,37.3482],"geometry_types":["point"],"unique_name":null,"name":"kcrex2","feature_count":16,"description":"","next_feature":null,"is_raster":false,"short_classification":"Y","stats":{},"features":[{"properties":{"geo_score":0.714,"23693":"23662","id":"a675fykj9vo8","geo_precision":"zip"},"type":"Feature","geometry":{"type":"Point","coordinates":[-76.365419,37.132326]}},{"properties":{"geo_score":0.714,"23693":"23553","id":"a675fyu2wgnl","geo_precision":"zip"},"type":"Feature","geometry":{"type":"Point","coordinates":[-76.285218,36.846815]}},{"properties":{"geo_score":0.714,"23693":"23662","id":"a675fyyem0nj","geo_precision":"zip"},"type":"Feature","geometry":{"type":"Point","coordinates":[-76.365419,37.132326]}},{"properties":{"geo_score":0.714,"23693":"23662","id":"a675fyr469yk","geo_precision":"zip"},"type":"Feature","geometry":{"type":"Point","coordinates":[-76.365419,37.132326]}},{"properties":{"geo_score":0.714,"23693":"23693","id":"a675fykmlq15","geo_precision":"zip"},"type":"Feature","geometry":{"type":"Point","coordinates":[-76.457449,37.123201]}},{"properties":{"geo_score":0.714,"23693":"23693","id":"a675fyraskak","geo_precision":"zip"},"type":"Feature","geometry":{"type":"Point","coordinates":[-76.457449,37.123201]}},{"properties":{"geo_score":0.714,"23693":"23606","id":"a675fykao681","geo_precision":"zip"},"type":"Feature","geometry":{"type":"Point","coordinates":[-76.504951,37.065147]}},{"properties":{"geo_score":0.714,"23693":"23662","id":"a675fyxbeul3","geo_precision":"zip"},"type":"Feature","geometry":{"type":"Point","coordinates":[-76.365419,37.132326]}},{"properties":{"geo_score":0.714,"23693":"23662","id":"a675fyqxwf7l","geo_precision":"zip"},"type":"Feature","geometry":{"type":"Point","coordinates":[-76.365419,37.132326]}},{"properties":{"geo_score":0.714,"23693":"23662","id":"a675fyu2yho2","geo_precision":"zip"},"type":"Feature","geometry":{"type":"Point","coordinates":[-76.365419,37.132326]}},{"properties":{"geo_score":0.714,"23693":"23188","id":"a675fz0jud5k","geo_precision":"zip"},"type":"Feature","geometry":{"type":"Point","coordinates":[-76.773832,37.34822]}},{"properties":{"geo_score":0.714,"23693":"23662","id":"a675fyvvwegc","geo_precision":"zip"},"type":"Feature","geometry":{"type":"Point","coordinates":[-76.365419,37.132326]}},{"properties":{"geo_score":0.714,"23693":"23662","id":"a675fyt1lrko","geo_precision":"zip"},"type":"Feature","geometry":{"type":"Point","coordinates":[-76.365419,37.132326]}},{"properties":{"geo_score":0.714,"23693":"23662","id":"a675fyuei2lz","geo_precision":"zip"},"type":"Feature","geometry":{"type":"Point","coordinates":[-76.365419,37.132326]}},{"properties":{"geo_score":0.714,"23693":"23666","id":"a675fyk7yucg","geo_precision":"zip"},"type":"Feature","geometry":{"type":"Point","coordinates":[-76.371056,37.048757]}},{"properties":{"geo_score":0.714,"23693":"23314","id":"a675fyxmbq6t","geo_precision":"zip"},"type":"Feature","geometry":{"type":"Point","coordinates":[-76.542783,36.956505]}}],"is_temporal":false,"author":{"url":"","metadata":"","contact_name":"","contact_address":"","source":"","contact_phone":""},"source":"","pagination":{"sort":null,"start":0,"total":16,"limit":1000000},"state":"complete","tags":"example","published":"2014-08-11T00:17:41-04:00","id":99931}