{"type":"FeatureCollection","data_attributes":null,"calculation_params":null,"title":"Warning Offsensive Signage, Road blocks &amp;amp; Firearms reported on easement.kmz","count":1,"icon_link":null,"extent":[150.961,-33.5611,150.961,-33.5611],"geometry_types":["point"],"unique_name":null,"feature_count":1,"link":"http://geocommons.com/overlays/101897.json","next_feature":null,"features":[{"properties":{"name":"Warning: Offsensive Signage, Road blocks &amp; Firearms reported on easement","id":"a6c78lymhkio"},"type":"Feature","geometry":{"type":"Point","coordinates":[150.960563003346,-33.5610772303526]}}],"is_raster":false,"name":"Warning Offsensive Signage, Road blocks &amp; Firearms reported on easement.kmz","state":"complete","short_classification":"Y","published":"2014-08-31T10:40:46-04:00","description":"","stats":{},"is_temporal":false,"pagination":{"sort":null,"start":0,"limit":1000000,"total":1},"author":{"metadata":"","contact_name":"","url":"","contact_address":"","contact_phone":"","source":""},"source":"","data_type":"Dataset","url_type":null,"permissions":[{"group_id":"everyone","permissions":{"download":true,"view":true}}],"classification":null,"tags":"","id":101897,"stream_id":101897,"contributor":{"name":"TheHills","url":"http://geocommons.com/users/23908"}}