{"type":"FeatureCollection","data_attributes":null,"calculation_params":null,"title":"Tobruk Easement- take LHS road, over grid down steep","count":1,"icon_link":null,"extent":[150.973,-33.4228,150.973,-33.4228],"geometry_types":["point"],"unique_name":null,"feature_count":1,"link":"http://geocommons.com/overlays/101912.json","next_feature":null,"features":[{"properties":{"name":"Tobruk Easement- take LHS road, over grid down steep","id":"a670d0mqof9f"},"type":"Feature","geometry":{"type":"Point","coordinates":[150.972826029518,-33.4228113851427]}}],"is_raster":false,"name":"Tobruk Easement- take LHS road, over grid down steep","state":"complete","short_classification":"Y","published":"2014-08-31T10:40:48-04:00","description":"","stats":{},"is_temporal":false,"pagination":{"sort":null,"start":0,"limit":1000000,"total":1},"author":{"metadata":"","contact_name":"","url":"","contact_address":"","contact_phone":"","source":""},"source":"","data_type":"Dataset","url_type":null,"permissions":[{"group_id":"everyone","permissions":{"download":true,"view":true}}],"classification":null,"tags":"","id":101912,"stream_id":101912,"contributor":{"name":"TheHills","url":"http://geocommons.com/users/23908"}}