{"type":"FeatureCollection","data_attributes":null,"calculation_params":null,"title":"Gate - lock","count":1,"icon_link":null,"extent":[150.903,-33.451,150.903,-33.451],"geometry_types":["point"],"unique_name":null,"feature_count":1,"link":"http://geocommons.com/overlays/101901.json","next_feature":null,"features":[{"properties":{"name":"Gate - lock?","id":"a66d276iq8s9"},"type":"Feature","geometry":{"type":"Point","coordinates":[150.902768526555,-33.4509621721745]}}],"is_raster":false,"name":"Gate - lock","state":"complete","short_classification":"Y","published":"2014-08-31T10:40:47-04:00","description":"","stats":{},"is_temporal":false,"pagination":{"sort":null,"start":0,"limit":1000000,"total":1},"author":{"metadata":"","contact_name":"","url":"","contact_address":"","contact_phone":"","source":""},"source":"","data_type":"Dataset","url_type":null,"permissions":[{"group_id":"everyone","permissions":{"download":true,"view":true}}],"classification":null,"tags":"","id":101901,"stream_id":101901,"contributor":{"name":"TheHills","url":"http://geocommons.com/users/23908"}}