{"type":"FeatureCollection","data_type":"Dataset","url_type":null,"permissions":[{"permissions":{"download":true,"view":true},"group_id":"everyone"}],"classification":null,"title":"Breakdown of Geothermal Electricity Production, World, 2009","count":11,"stream_id":10287,"contributor":{"url":"http://geocommons.com/users/955","name":"williambenjaminiv"},"data_attributes":null,"calculation_params":null,"icon_link":null,"link":"http://geocommons.com/overlays/10287.json","extent":[-101.956,-43.5877,170.367,64.9639],"geometry_types":["point"],"unique_name":null,"name":"Breakdown of Geothermal Electricity Production, World, 2009","feature_count":11,"description":"","next_feature":null,"is_raster":false,"short_classification":"Y","stats":{"lat":{"max":64.963943,"mean":18.5384334545455,"variance":822.237108263887,"stdev":28.674677125713,"min":-43.587711,"median":15.59305},"geotherm":{"max":28.7,"mean":8.80409090909091,"variance":78.2923040909091,"stdev":8.84829385197559,"min":1.44,"median":5.99},"long":{"max":170.366638,"mean":18.4190210909091,"variance":10947.7640457598,"stdev":104.631563334205,"min":-101.956253,"median":12.57341}},"features":[{"properties":{"country":"new zealand","id":"a62vbeh3nnrr","lat":-43.587711,"geotherm":4.87,"long":170.366638},"type":"Feature","geometry":{"type":"Point","coordinates":[170.366638,-43.587711]}},{"properties":{"country":"kenya","id":"a62vbeg8gjca","lat":-0.02435,"geotherm":1.44,"long":37.90395},"type":"Feature","geometry":{"type":"Point","coordinates":[37.90395,-0.02435]}},{"properties":{"country":"indonesia","id":"a62vbe773217","lat":0.10974,"geotherm":8.92,"long":113.917397},"type":"Feature","geometry":{"type":"Point","coordinates":[113.917397,0.10974]}},{"properties":{"country":"costa rica","id":"a62vbe98jidn","lat":9.62489,"geotherm":1.82,"long":-84.253311},"type":"Feature","geometry":{"type":"Point","coordinates":[-84.253311,9.62489]}},{"properties":{"country":"el salvador","id":"a62vbeimx1p7","lat":13.79687,"geotherm":1.69,"long":-88.918793},"type":"Feature","geometry":{"type":"Point","coordinates":[-88.918793,13.79687]}},{"properties":{"country":"philippines","id":"a62vbebht190","lat":15.59305,"geotherm":21.6,"long":120.739067},"type":"Feature","geometry":{"type":"Point","coordinates":[120.739067,15.59305]}},{"properties":{"country":"mexico","id":"a62vbeii26bp","lat":23.62574,"geotherm":10.67,"long":-101.956253},"type":"Feature","geometry":{"type":"Point","coordinates":[-101.956253,23.62574]}},{"properties":{"country":"japan","id":"a62vbecuw4h3","lat":37.487598,"geotherm":5.99,"long":139.838287},"type":"Feature","geometry":{"type":"Point","coordinates":[139.838287,37.487598]}},{"properties":{"country":"united states","id":"a62vbehheog8","lat":39.83,"geotherm":28.7,"long":-98.58},"type":"Feature","geometry":{"type":"Point","coordinates":[-98.58,39.83]}},{"properties":{"country":"italy","id":"a62vbe2wwwlv","lat":42.502998,"geotherm":8.885,"long":12.57341},"type":"Feature","geometry":{"type":"Point","coordinates":[12.57341,42.502998]}},{"properties":{"country":"iceland","id":"a62vbeimw6tp","lat":64.963943,"geotherm":2.26,"long":-19.02116},"type":"Feature","geometry":{"type":"Point","coordinates":[-19.02116,64.963943]}}],"is_temporal":false,"author":{"url":"","metadata":"","contact_name":"","contact_address":"","source":"","contact_phone":""},"source":"","pagination":{"sort":null,"start":0,"total":11,"limit":1000000},"state":"complete","tags":"electricity,energy,geothermal,infrastructure,production,world","published":"2014-08-10T11:21:52-04:00","id":10287}