{"type":"FeatureCollection","url":"http://maps.google.com/maps/ms?vps=2&jsv=323a&hl=en&ie=UTF8&msa=0&output=georss&msid=217049117307475984500.00049f3ac83bad6a7c25e","data_type":"Data Feed","url_type":"rss","permissions":[{"permissions":{"download":true,"view":true},"group_id":"everyone"}],"classification":null,"title":"Todd Scott State Farm Insurance","count":1,"stream_id":103383,"contributor":{"url":"http://geocommons.com/users/24225","name":"toddscott"},"data_attributes":null,"calculation_params":null,"icon_link":null,"link":"http://geocommons.com/overlays/103383.json","extent":[-122.005,37.3519,-122.005,37.3519],"geometry_types":["point"],"unique_name":null,"name":"Todd Scott State Farm Insurance","feature_count":1,"description":"State Farm Insurance agent Todd Scott providing free insurance quotes for auto insurance, home insurance, life insurance, renters insurance, commercial insurance and car insurance in Sunnyvale, CA.\nAddress: 1040 E El Camino Real, Sunnyvale, CA 94087\nPhone: (408) 248-9000\nWebsite: http://www.toddscottinsurance.com","next_feature":null,"is_raster":false,"short_classification":"Y","stats":{"published":{"max":"2011/03/24 09:52:03 -0400","min":"2011/03/24 09:52:03 -0400","median":"2011/03/24 09:52:03 -0400"},"georss:elev":{"max":0.0,"min":0.0,"median":0.0}},"features":[{"properties":{"title":"Todd Scott State Farm Insurance","guid":"00049f3ac83d82d70cfae","published":{"end_time":"2011/03/24 09:52:04 -0400","original":"Thu, 24 Mar 2011 13:52:03 +0000","granularity":"sec","time":"2011/03/24 09:52:03 -0400"},"description":"State Farm Insurance agent Todd Scott providing free insurance quotes for auto insurance, home insurance, life insurance, renters insurance, commercial insurance and car insurance in Sunnyvale, CA. <a href=\"http://www.toddscottinsurance.com\">Sunnyvale CA Auto Insurance</a>, <a href=\"http://www.toddscottinsurance.com\">Sunnyvale CA Home Insurance</a>, <a href=\"http://www.toddscottinsurance.com\">Sunnyvale CA State Farm</a>.Address: 1040 E El Camino Real, Sunnyvale, CA 94087Phone: (408) 248-9000Website: <a href=\"http://www.toddscottinsurance.com\">http://www.toddscottinsurance.com</a>","id":"a672wfsdx3q0","georss:elev":0.0},"type":"Feature","geometry":{"type":"Point","coordinates":[-122.004707,37.351864]}}],"is_temporal":true,"author":{"url":"","metadata":"","contact_name":"","contact_address":"","source":"","contact_phone":""},"source":"","pagination":{"sort":null,"start":0,"total":1,"limit":1000000},"state":"complete","tags":"california,farm,insurance,state,sunnyvale","published":"2014-08-13T02:03:05-04:00","id":103383}