{"type":"FeatureCollection","data_type":"Dataset","url_type":null,"permissions":[{"permissions":{"download":true,"view":true},"group_id":"everyone"}],"classification":null,"title":"detour9.kml","count":1,"stream_id":103574,"contributor":{"url":"http://geocommons.com/users/18705","name":"fmina"},"data_attributes":null,"calculation_params":null,"icon_link":null,"link":"http://geocommons.com/overlays/103574.json","extent":[-122.267,37.7942,-122.267,37.7942],"geometry_types":["point"],"unique_name":null,"name":"detour9.kml","feature_count":1,"description":"","next_feature":null,"is_raster":false,"short_classification":"Y","stats":{},"features":[{"properties":{"name":"detour9","description":"<b>Detour #9: Marathon (miles 17) and Half Marathon (mile 3 + 4):  Waterfront Warehouse district</b>\r\n<i>From 8:45am to 12:30pm:</i>\r\n\r\nIf you live east of Jackson, head down Madison, take a right on 5th to I-880 southbound. If you need to head northbound, get off at the next exit (16th Avenue) take right on Embarcadero to get to Jack London Square.  Or to get to I-880 northbound, take left on Embarcadero, follow it around for about a mile past Union Point Park, it will turn into East 7th Street, take a left on 23rd Avenue and follow signs back to I-880 Northbound.\r\n\r\nIf you live west of Jackson, take 4th Street westbound, left on Broadway and follow the signs to I-880 southbound. Or stay on 4th Street, right on Castro to get to I-980 northbound.\r\n<i>After 12:30pm:</i>  Runners will have cleared area; streets will be reopened to normal traffic.","id":"a6d7ur05a3ap"},"type":"Feature","geometry":{"type":"Point","coordinates":[-122.26703885658,37.7942231444833]}}],"is_temporal":false,"author":{"url":"","metadata":"","contact_name":"","contact_address":"","source":"","contact_phone":""},"source":"","pagination":{"sort":null,"start":0,"total":1,"limit":1000000},"state":"complete","tags":"","published":"2014-08-13T02:17:23-04:00","id":103574}