{"type":"FeatureCollection","data_type":"Dataset","url_type":null,"permissions":[{"permissions":{"download":true,"view":true},"group_id":"everyone"}],"classification":null,"title":"PWC HGs - 4","count":8,"stream_id":104874,"contributor":{"url":"http://geocommons.com/users/24568","name":"srfr"},"data_attributes":null,"calculation_params":null,"icon_link":null,"link":"http://geocommons.com/overlays/104874.json","extent":[-1.4253,50.9053,-1.3162,50.9611],"geometry_types":["point"],"unique_name":null,"name":"PWC HGs - 4","feature_count":8,"description":"","next_feature":null,"is_raster":false,"short_classification":"Y","stats":{"latitude":{"max":50.9611,"mean":50.929625,"variance":0.000277596428571452,"stdev":0.0166612253022235,"min":50.9053,"median":50.9249},"longitude":{"max":-1.3162,"mean":-1.3770375,"variance":0.00171482839285714,"stdev":0.0414104865083368,"min":-1.4253,"median":-1.3964},"housegroup":{"max":4,"mean":4.0,"variance":0.0,"stdev":0.0,"min":4,"median":4}},"features":[{"properties":{"latitude":50.9296,"postal code":"SO30 3JU","longitude":-1.3291,"id":"a6fumc90aipf","housegroup":4},"type":"Feature","geometry":{"type":"Point","coordinates":[-1.3291,50.9296]}},{"properties":{"latitude":50.9611,"postal code":"SO50 8QH","longitude":-1.3162,"id":"a6fumcatmrfw","housegroup":4},"type":"Feature","geometry":{"type":"Point","coordinates":[-1.3162,50.9611]}},{"properties":{"latitude":50.9249,"postal code":"SO17 1HR","longitude":-1.3964,"id":"a6fumcguxfbq","housegroup":4},"type":"Feature","geometry":{"type":"Point","coordinates":[-1.3964,50.9249]}},{"properties":{"latitude":50.9053,"postal code":"SO19 8RU","longitude":-1.3409,"id":"a6fumc6n94bh","housegroup":4},"type":"Feature","geometry":{"type":"Point","coordinates":[-1.3409,50.9053]}},{"properties":{"latitude":50.9449,"postal code":"SO16 8DG","longitude":-1.4253,"id":"a6fumcdi3084","housegroup":4},"type":"Feature","geometry":{"type":"Point","coordinates":[-1.4253,50.9449]}},{"properties":{"latitude":50.9245,"postal code":"SO17 1EX","longitude":-1.402,"id":"a6fumce0inhm","housegroup":4},"type":"Feature","geometry":{"type":"Point","coordinates":[-1.402,50.9245]}},{"properties":{"latitude":50.9236,"postal code":"SO17 1UZ","longitude":-1.4043,"id":"a6fumci71btz","housegroup":4},"type":"Feature","geometry":{"type":"Point","coordinates":[-1.4043,50.9236]}},{"properties":{"latitude":50.9231,"postal code":"SO17 1DL","longitude":-1.4021,"id":"a6fumcejkr8w","housegroup":4},"type":"Feature","geometry":{"type":"Point","coordinates":[-1.4021,50.9231]}}],"is_temporal":false,"author":{"url":"","metadata":"","contact_name":"","contact_address":"","source":"","contact_phone":""},"source":"","pagination":{"sort":null,"start":0,"total":8,"limit":1000000},"state":"complete","tags":"","published":"2014-08-13T04:03:19-04:00","id":104874}