{"type":"FeatureCollection","data_attributes":null,"calculation_params":null,"title":"VE Sample KML","count":1,"icon_link":null,"extent":[-0.152898,51.5139,-0.152898,51.5139],"geometry_types":["point"],"unique_name":null,"feature_count":1,"link":"http://geocommons.com/overlays/10558.json","next_feature":null,"features":[{"properties":{"name":"\"Selfridges\"","description":"\"Selfridges\"","id":"a66m5ydxf7fb"},"type":"Feature","geometry":{"type":"Point","coordinates":[-0.1528975,51.5139408333333]}}],"is_raster":false,"name":"VE Sample KML","state":"complete","short_classification":"Y","published":"2014-08-31T23:15:43-04:00","description":"","stats":{},"is_temporal":false,"pagination":{"sort":null,"start":0,"limit":1000000,"total":1},"author":{"metadata":"","contact_name":"","url":"","contact_address":"","contact_phone":"","source":""},"source":"","data_type":"Dataset","url_type":null,"permissions":[{"group_id":"everyone","permissions":{"download":true,"view":true}}],"classification":null,"tags":"","id":10558,"stream_id":10558,"contributor":{"name":"jaggi_taran","url":"http://geocommons.com/users/5311"}}