{"type":"FeatureCollection","data_type":"Dataset","url_type":null,"permissions":[{"permissions":{"download":true,"view":true},"group_id":"everyone"}],"classification":null,"title":"GPS points","count":5,"stream_id":106977,"contributor":{"url":"http://geocommons.com/users/18574","name":"GEO_481"},"data_attributes":null,"calculation_params":null,"icon_link":null,"link":"http://geocommons.com/overlays/106977.json","extent":[-78.7958,42.9971,-78.7773,43.0099],"geometry_types":["point"],"unique_name":null,"name":"GPS points","feature_count":5,"description":"","next_feature":null,"is_raster":false,"short_classification":"Y","stats":{"LONGITUDE":{"max":-78.77732,"mean":-78.786724,"variance":7.06797299999738e-05,"stdev":0.00840712376499679,"min":-78.79582,"median":-78.78992},"LATITUDE":{"max":43.00988,"mean":43.003218,"variance":3.43945700000027e-05,"stdev":0.00586468839751975,"min":42.9971,"median":43.00075},"Id":{"max":5,"mean":3.0,"variance":2.5,"stdev":1.58113883008419,"min":1,"median":3}},"features":[{"properties":{"LONGITUDE":-78.79582,"LATITUDE":43.00907,"Id":1,"id":"a6xbks65k6qh"},"type":"Feature","geometry":{"type":"Point","coordinates":[-78.79582,43.0090699990589]}},{"properties":{"LONGITUDE":-78.78992,"LATITUDE":43.00988,"Id":2,"id":"a6xbksdhr3uj"},"type":"Feature","geometry":{"type":"Point","coordinates":[-78.78992,43.0098799990589]}},{"properties":{"LONGITUDE":-78.77831,"LATITUDE":43.00075,"Id":3,"id":"a6xbks4af1e7"},"type":"Feature","geometry":{"type":"Point","coordinates":[-78.77831,43.000749999059]}},{"properties":{"LONGITUDE":-78.77732,"LATITUDE":42.99929,"Id":4,"id":"a6xbkryuhtgr"},"type":"Feature","geometry":{"type":"Point","coordinates":[-78.77732,42.999289999059]}},{"properties":{"LONGITUDE":-78.79225,"LATITUDE":42.9971,"Id":5,"id":"a6xbks75l4xz"},"type":"Feature","geometry":{"type":"Point","coordinates":[-78.79225,42.997099999059]}}],"is_temporal":false,"author":{"url":"","metadata":"","contact_name":"","contact_address":"","source":"","contact_phone":""},"source":"","pagination":{"sort":null,"start":0,"total":5,"limit":1000000},"state":"complete","tags":"","published":"2014-08-13T07:49:58-04:00","id":106977}