{"type":"FeatureCollection","data_type":"Dataset","url_type":null,"permissions":[{"permissions":{"download":true,"view":true},"group_id":"everyone"}],"classification":null,"title":"group4","count":4,"stream_id":10813,"contributor":{"url":"http://geocommons.com/users/5432","name":"celialarson"},"data_attributes":null,"calculation_params":null,"icon_link":null,"link":"http://geocommons.com/overlays/10813.json","extent":[-86.8742,35.9181,-86.7525,36.2253],"geometry_types":["point"],"unique_name":null,"name":"group4","feature_count":4,"description":"","next_feature":null,"is_raster":false,"short_classification":"Y","stats":{"lat":{"max":36.225278,"mean":36.12347925,"variance":0.0193628217082506,"stdev":0.139150356479064,"min":35.918139,"median":36.185261},"long":{"max":-86.752465,"mean":-86.800441,"variance":0.00269153716866651,"stdev":0.0518800266833636,"min":-86.874185,"median":-86.786386}},"features":[{"properties":{"name":"Alcohol and Drug Abuse Council-HIVSAen Murray","id":"a62uqiuees8w","group":"HIVSA","lat":35.918139,"long":-86.874185},"type":"Feature","geometry":{"type":"Point","coordinates":[-86.874185,35.918139]}},{"properties":{"name":"Nashville Cares","id":"a62uqit0uqha","group":"HIVSA","lat":36.225278,"long":-86.786386},"type":"Feature","geometry":{"type":"Point","coordinates":[-86.786386,36.225278]}},{"properties":{"name":"Street Works","id":"a62uqixx4dxu","group":"HIVSA","lat":36.185261,"long":-86.752465},"type":"Feature","geometry":{"type":"Point","coordinates":[-86.752465,36.185261]}},{"properties":{"name":"W.O.M.E.N.","id":"a62uqiq7npgb","group":"HIVSA","lat":36.165239,"long":-86.788728},"type":"Feature","geometry":{"type":"Point","coordinates":[-86.788728,36.165239]}}],"is_temporal":false,"author":{"url":"","metadata":"","contact_name":"","contact_address":"","source":"","contact_phone":""},"source":"","pagination":{"sort":null,"start":0,"total":4,"limit":1000000},"state":"complete","tags":"hiv_sa","published":"2014-08-10T12:18:13-04:00","id":10813}