{"type":"FeatureCollection","data_type":"Dataset","url_type":null,"permissions":[{"permissions":{"download":true,"view":true},"group_id":"everyone"}],"classification":null,"title":"GPSout2","count":7,"stream_id":108282,"contributor":{"url":"http://geocommons.com/users/24983","name":"kmseitz"},"data_attributes":null,"calculation_params":null,"icon_link":null,"link":"http://geocommons.com/overlays/108282.json","extent":[-78.7947,42.9977,-78.7781,43.0111],"geometry_types":["point"],"unique_name":null,"name":"GPSout2","feature_count":7,"description":"","next_feature":null,"is_raster":false,"short_classification":"Y","stats":{"LONGITUDE":{"max":-78.77808,"mean":-78.7865014285714,"variance":4.0558180952358e-05,"stdev":0.00636853051750229,"min":-78.79471,"median":-78.78529},"LATITUDE":{"max":43.01106,"mean":43.0025085714286,"variance":2.16126476190594e-05,"stdev":0.00464894048349292,"min":42.99773,"median":43.00323},"ID":{"max":7,"mean":4.0,"variance":4.66666666666667,"stdev":2.16024689946929,"min":1,"median":4}},"features":[{"properties":{"LONGITUDE":-78.79471,"LATITUDE":43.00423,"ID":1,"id":"a6n1eglun1y7"},"type":"Feature","geometry":{"type":"Point","coordinates":[-78.79471,43.00423]}},{"properties":{"LONGITUDE":-78.78529,"LATITUDE":43.00323,"ID":2,"id":"a6n1egkek1c7"},"type":"Feature","geometry":{"type":"Point","coordinates":[-78.78529,43.00323]}},{"properties":{"LONGITUDE":-78.7938,"LATITUDE":42.99894,"ID":3,"id":"a6n1egr5y3z8"},"type":"Feature","geometry":{"type":"Point","coordinates":[-78.7938,42.99894]}},{"properties":{"LONGITUDE":-78.78911,"LATITUDE":42.99854,"ID":4,"id":"a6n1eggr21ty"},"type":"Feature","geometry":{"type":"Point","coordinates":[-78.78911,42.99854]}},{"properties":{"LONGITUDE":-78.78032,"LATITUDE":42.99773,"ID":5,"id":"a6n1egimph9n"},"type":"Feature","geometry":{"type":"Point","coordinates":[-78.78032,42.99773]}},{"properties":{"LONGITUDE":-78.77808,"LATITUDE":43.00383,"ID":6,"id":"a6n1eglb6vnu"},"type":"Feature","geometry":{"type":"Point","coordinates":[-78.77808,43.00383]}},{"properties":{"LONGITUDE":-78.7842,"LATITUDE":43.01106,"ID":7,"id":"a6n1egvbchq6"},"type":"Feature","geometry":{"type":"Point","coordinates":[-78.7842,43.01106]}}],"is_temporal":false,"author":{"url":"","metadata":"","contact_name":"","contact_address":"","source":"","contact_phone":""},"source":"","pagination":{"sort":null,"start":0,"total":7,"limit":1000000},"state":"complete","tags":"","published":"2014-08-13T09:48:44-04:00","id":108282}