{"type":"FeatureCollection","data_type":"Dataset","url_type":null,"permissions":[{"permissions":{"download":true,"view":true},"group_id":"everyone"}],"classification":null,"title":"GeoCode Test","count":4,"stream_id":108464,"contributor":{"url":"http://geocommons.com/users/25307","name":"bdclassen@gmail.com"},"data_attributes":null,"calculation_params":null,"icon_link":null,"link":"http://geocommons.com/overlays/108464.json","extent":[123.06,48.25,123.58,49.15],"geometry_types":["point"],"unique_name":null,"name":"GeoCode Test","feature_count":4,"description":"","next_feature":null,"is_raster":false,"short_classification":"Y","stats":{"latitude":{"max":49.15,"mean":48.755,"variance":0.199033333333333,"stdev":0.446131520219468,"min":48.25,"median":49.11},"longitude":{"max":123.58,"mean":123.3075,"variance":0.0500916666666662,"stdev":0.223811676788022,"min":123.06,"median":123.38}},"features":[{"properties":{"city":"Vancouver","latitude":49.15,"country":"Canada","longitude":123.06,"id":"a6cufoimif9m","province":"British Columbia"},"type":"Feature","geometry":{"type":"Point","coordinates":[123.06,49.15]}},{"properties":{"city":"Crofton","latitude":48.51,"country":"Canada","longitude":123.38,"id":"a6cufoad0ust","province":"British Columbia"},"type":"Feature","geometry":{"type":"Point","coordinates":[123.38,48.51]}},{"properties":{"city":"Nanaimo","latitude":49.11,"country":"Canada","longitude":123.58,"id":"a6cufohekeib","province":"British Columbia"},"type":"Feature","geometry":{"type":"Point","coordinates":[123.58,49.11]}},{"properties":{"city":"Victoria","latitude":48.25,"country":"Canada","longitude":123.21,"id":"a6cufobla0rw","province":"British Columbia"},"type":"Feature","geometry":{"type":"Point","coordinates":[123.21,48.25]}}],"is_temporal":false,"author":{"url":"","metadata":"","contact_name":"","contact_address":"","source":"","contact_phone":""},"source":"","pagination":{"sort":null,"start":0,"total":4,"limit":1000000},"state":"complete","tags":"","published":"2014-08-13T10:06:00-04:00","id":108464}