{"type":"FeatureCollection","data_type":"Dataset","url_type":null,"permissions":[{"permissions":{"download":true,"view":true},"group_id":"everyone"}],"classification":null,"title":"7245","count":19,"stream_id":10888,"contributor":{"url":"http://geocommons.com/users/5416","name":"elena"},"data_attributes":null,"calculation_params":null,"icon_link":null,"link":"http://geocommons.com/overlays/10888.json","extent":[-5.2512,36.367,2.4609,48.8357],"geometry_types":["point"],"unique_name":null,"name":"7245","feature_count":19,"description":"","next_feature":null,"is_raster":false,"short_classification":"Y","stats":{"oficina":{"max":2,"mean":1.05263157894737,"variance":0.0526315789473684,"stdev":0.229415733870562,"min":1,"median":1},"lat":{"max":48.8357,"mean":37.2231052631579,"variance":7.93105077052632,"stdev":2.81621213166308,"min":36.367,"median":36.5977},"long":{"max":2.4609,"mean":-4.35363684210526,"variance":2.83570464912281,"stdev":1.68395506149149,"min":-5.2512,"median":-4.6364}},"features":[{"properties":{"oficina":1,"id":"a6kzde4jo5or","lat":36.367,"long":-5.2275},"type":"Feature","geometry":{"type":"Point","coordinates":[-5.2275,36.367]}},{"properties":{"oficina":1,"id":"a6kzde5lyunq","lat":36.3782,"long":-5.2512},"type":"Feature","geometry":{"type":"Point","coordinates":[-5.2512,36.3782]}},{"properties":{"oficina":1,"id":"a6kzde1l7k1i","lat":36.4253,"long":-5.1438},"type":"Feature","geometry":{"type":"Point","coordinates":[-5.1438,36.4253]}},{"properties":{"oficina":1,"id":"a6kzde1fq8p2","lat":36.4256,"long":-5.1431},"type":"Feature","geometry":{"type":"Point","coordinates":[-5.1431,36.4256]}},{"properties":{"oficina":1,"id":"a6kzdebzuk98","lat":36.4859,"long":-4.9899},"type":"Feature","geometry":{"type":"Point","coordinates":[-4.9899,36.4859]}},{"properties":{"oficina":1,"id":"a6kzde11q912","lat":36.5048,"long":-4.6805},"type":"Feature","geometry":{"type":"Point","coordinates":[-4.6805,36.5048]}},{"properties":{"oficina":1,"id":"a6kzde15lqz1","lat":36.5079,"long":-4.8833},"type":"Feature","geometry":{"type":"Point","coordinates":[-4.8833,36.5079]}},{"properties":{"oficina":1,"id":"a6kzde6k64er","lat":36.5104,"long":-4.893},"type":"Feature","geometry":{"type":"Point","coordinates":[-4.893,36.5104]}},{"properties":{"oficina":1,"id":"a6kzdea2sgnt","lat":36.5469,"long":-4.6186},"type":"Feature","geometry":{"type":"Point","coordinates":[-4.6186,36.5469]}},{"properties":{"oficina":1,"id":"a6kzde7wy8za","lat":36.5977,"long":-4.6364},"type":"Feature","geometry":{"type":"Point","coordinates":[-4.6364,36.5977]}},{"properties":{"oficina":1,"id":"a6kzddzbepvq","lat":36.6012,"long":-4.5327},"type":"Feature","geometry":{"type":"Point","coordinates":[-4.5327,36.6012]}},{"properties":{"oficina":1,"id":"a6kzde1clnsf","lat":36.624,"long":-4.5},"type":"Feature","geometry":{"type":"Point","coordinates":[-4.5,36.624]}},{"properties":{"oficina":1,"id":"a6kzddxtci5q","lat":36.6263,"long":-4.502},"type":"Feature","geometry":{"type":"Point","coordinates":[-4.502,36.6263]}},{"properties":{"oficina":1,"id":"a6kzde8n0q03","lat":36.6596,"long":-4.7579},"type":"Feature","geometry":{"type":"Point","coordinates":[-4.7579,36.6596]}},{"properties":{"oficina":1,"id":"a6kzddwgcfwr","lat":36.6618,"long":-4.5614},"type":"Feature","geometry":{"type":"Point","coordinates":[-4.5614,36.6618]}},{"properties":{"oficina":1,"id":"a6kzddxq8jm4","lat":36.7183,"long":-4.4201},"type":"Feature","geometry":{"type":"Point","coordinates":[-4.4201,36.7183]}},{"properties":{"oficina":1,"id":"a6kzdeb0inpk","lat":36.7454,"long":-3.8787},"type":"Feature","geometry":{"type":"Point","coordinates":[-3.8787,36.7454]}},{"properties":{"oficina":1,"id":"a6kzde47ffer","lat":37.017,"long":-4.5599},"type":"Feature","geometry":{"type":"Point","coordinates":[-4.5599,37.017]}},{"properties":{"oficina":2,"id":"a6kzddzvc6iv","lat":48.8357,"long":2.4609},"type":"Feature","geometry":{"type":"Point","coordinates":[2.4609,48.8357]}}],"is_temporal":false,"author":{"url":"","metadata":"","contact_name":"","contact_address":"","source":"","contact_phone":""},"source":"","pagination":{"sort":null,"start":0,"total":19,"limit":1000000},"state":"complete","tags":"","published":"2014-08-10T12:21:39-04:00","id":10888}