{"type":"FeatureCollection","data_type":"Dataset","url_type":null,"permissions":[{"permissions":{"download":true,"view":true},"group_id":"everyone"}],"classification":null,"title":"PWC HGs - Millman","count":7,"stream_id":109825,"contributor":{"url":"http://geocommons.com/users/24568","name":"srfr"},"data_attributes":null,"calculation_params":null,"icon_link":null,"link":"http://geocommons.com/overlays/109825.json","extent":[-1.4167,50.9131,-1.3595,50.9248],"geometry_types":null,"unique_name":null,"name":"PWC HGs - Millman","feature_count":7,"description":"","next_feature":null,"is_raster":false,"short_classification":"Y","stats":{"latitude":{"max":50.9248,"variance":2.23147619047545e-05,"mean":50.9199857142857,"stdev":0.00472385032624389,"min":50.9131,"median":50.9212},"longitude":{"max":-1.3595,"variance":0.000378252380952382,"mean":-1.39112857142857,"stdev":0.01944871154993,"min":-1.4167,"median":-1.3964},"hg":{"max":2,"variance":0.0,"mean":2.0,"stdev":0.0,"min":2,"median":2}},"features":[{"properties":{"latitude":50.9235,"postcode":"SO14 6WJ","longitude":-1.3964,"id":"a68mce6o2tl5","hg":2},"type":"Feature","geometry":{"type":"Point","coordinates":[-1.3964,50.9235]}},{"properties":{"latitude":50.9205,"postcode":"SO15 7NG","longitude":-1.4167,"id":"a68mce9tjjnt","hg":2},"type":"Feature","geometry":{"type":"Point","coordinates":[-1.4167,50.9205]}},{"properties":{"latitude":50.9231,"postcode":"SO17 1DL","longitude":-1.4021,"id":"a68mce5mokk8","hg":2},"type":"Feature","geometry":{"type":"Point","coordinates":[-1.4021,50.9231]}},{"properties":{"latitude":50.9248,"postcode":"SO17 1WH","longitude":-1.3986,"id":"a68mce8i3fsw","hg":2},"type":"Feature","geometry":{"type":"Point","coordinates":[-1.3986,50.9248]}},{"properties":{"latitude":50.9212,"postcode":"SO17 2GA","longitude":-1.3936,"id":"a68mce2edb61","hg":2},"type":"Feature","geometry":{"type":"Point","coordinates":[-1.3936,50.9212]}},{"properties":{"latitude":50.9137,"postcode":"SO19 4DF","longitude":-1.371,"id":"a68mce9ffql1","hg":2},"type":"Feature","geometry":{"type":"Point","coordinates":[-1.371,50.9137]}},{"properties":{"latitude":50.9131,"postcode":"SO19 7BX","longitude":-1.3595,"id":"a68mcebmtqgl","hg":2},"type":"Feature","geometry":{"type":"Point","coordinates":[-1.3595,50.9131]}}],"is_temporal":false,"author":{"url":"","metadata":"","contact_name":"","contact_address":"","source":"","contact_phone":""},"source":"","pagination":{"sort":null,"start":0,"total":7,"limit":1000000},"state":"complete","tags":"","published":"2014-08-13T11:57:55-04:00","id":109825}