{"type":"FeatureCollection","data_type":"Dataset","url_type":null,"permissions":[{"permissions":{"download":true,"view":true},"group_id":"everyone"}],"classification":null,"title":"7201","count":5,"stream_id":11039,"contributor":{"url":"http://geocommons.com/users/5416","name":"elena"},"data_attributes":null,"calculation_params":null,"icon_link":null,"link":"http://geocommons.com/overlays/11039.json","extent":[-6.94959,36.6819,2.46093,48.8358],"geometry_types":["point"],"unique_name":null,"name":"7201","feature_count":5,"description":"","next_feature":null,"is_raster":false,"short_classification":"Y","stats":{"oficina":{"max":2,"mean":1.2,"variance":0.2,"stdev":0.447213595499958,"min":1,"median":1},"lat":{"max":48.83579,"mean":39.5107684,"variance":27.2592881459478,"stdev":5.2210428216926,"min":36.681865,"median":37.387697},"long":{"max":2.46093,"mean":-4.524555,"variance":15.405824027758,"stdev":3.92502535377263,"min":-6.949594,"median":-6.001813}},"features":[{"properties":{"oficina":1,"id":"a6vsr73q7ngt","lat":36.681865,"long":-6.137444},"type":"Feature","geometry":{"type":"Point","coordinates":[-6.137444,36.681865]}},{"properties":{"oficina":1,"id":"a6vsr761e6t0","lat":37.256315,"long":-6.949594},"type":"Feature","geometry":{"type":"Point","coordinates":[-6.949594,37.256315]}},{"properties":{"oficina":1,"id":"a6vsr7buxeh7","lat":37.387697,"long":-6.001813},"type":"Feature","geometry":{"type":"Point","coordinates":[-6.001813,37.387697]}},{"properties":{"oficina":1,"id":"a6vsr75mbgdh","lat":37.392175,"long":-5.994854},"type":"Feature","geometry":{"type":"Point","coordinates":[-5.994854,37.392175]}},{"properties":{"oficina":2,"id":"a6vsr75jv3h8","lat":48.83579,"long":2.46093},"type":"Feature","geometry":{"type":"Point","coordinates":[2.46093,48.83579]}}],"is_temporal":false,"author":{"url":"","metadata":"","contact_name":"","contact_address":"","source":"","contact_phone":""},"source":"","pagination":{"sort":null,"start":0,"total":5,"limit":1000000},"state":"complete","tags":"","published":"2014-08-10T12:36:30-04:00","id":11039}