{"type":"FeatureCollection","data_type":"Dataset","url_type":null,"permissions":[{"permissions":{"download":true,"view":true},"group_id":"everyone"}],"classification":null,"title":"draft1","count":2,"stream_id":110482,"contributor":{"url":"http://geocommons.com/users/25868","name":"coatesd1"},"data_attributes":null,"calculation_params":null,"icon_link":null,"link":"http://geocommons.com/overlays/110482.json","extent":[-118.244,34.0522,-84.5555,42.7325],"geometry_types":["point"],"unique_name":null,"name":"draft1","feature_count":2,"description":"","next_feature":null,"is_raster":false,"short_classification":"Y","stats":{"championships":{"max":11,"mean":6.5,"variance":40.5,"stdev":6.36396103067893,"min":2,"median":11}},"features":[{"properties":{"city":"East Lansing","championships":2,"geo_score":0.805,"id":"a6jt2t49wk4t","geo_precision":"city","school":"MSU","state":"Michigan"},"type":"Feature","geometry":{"type":"Point","coordinates":[-84.555535,42.732535]}},{"properties":{"city":"Los Angelos","championships":11,"geo_score":0.843,"id":"a6jt2t9uyfqc","geo_precision":"city","school":"UCLA","state":"California"},"type":"Feature","geometry":{"type":"Point","coordinates":[-118.243685,34.052234]}}],"is_temporal":false,"author":{"url":"","metadata":"","contact_name":"","contact_address":"","source":"","contact_phone":""},"source":"","pagination":{"sort":null,"start":0,"total":2,"limit":1000000},"state":"complete","tags":"","published":"2014-08-12T21:56:46-04:00","id":110482}