{"type":"FeatureCollection","data_type":"Dataset","url_type":null,"permissions":[{"permissions":{"download":true,"view":true},"group_id":"everyone"}],"classification":null,"title":"7235","count":19,"stream_id":11087,"contributor":{"url":"http://geocommons.com/users/5416","name":"elena"},"data_attributes":null,"calculation_params":null,"icon_link":null,"link":"http://geocommons.com/overlays/11087.json","extent":[-6.00181,37.3877,2.46094,48.8358],"geometry_types":["point"],"unique_name":null,"name":"7235","feature_count":19,"description":"","next_feature":null,"is_raster":false,"short_classification":"Y","stats":{"oficina":{"max":2,"mean":1.05263157894737,"variance":0.0526315789473684,"stdev":0.229415733870562,"min":1,"median":1},"lat":{"max":48.8357974624309,"mean":37.9944063927595,"variance":6.89255730064241,"stdev":2.62536803146576,"min":37.387697,"median":37.390591},"long":{"max":2.4609375,"mean":-5.52715402631579,"variance":3.7428205837169,"stdev":1.9346370676995,"min":-6.001813,"median":-5.963001}},"features":[{"properties":{"oficina":1,"id":"a6divgzxh6m2","lat":37.387697,"long":-6.001813},"type":"Feature","geometry":{"type":"Point","coordinates":[-6.001813,37.387697]}},{"properties":{"oficina":1,"id":"a6divh20ui6x","lat":37.387697,"long":-6.001813},"type":"Feature","geometry":{"type":"Point","coordinates":[-6.001813,37.387697]}},{"properties":{"oficina":1,"id":"a6divgu14omn","lat":37.387697,"long":-6.001813},"type":"Feature","geometry":{"type":"Point","coordinates":[-6.001813,37.387697]}},{"properties":{"oficina":1,"id":"a6divgtx66gx","lat":37.387697,"long":-6.001813},"type":"Feature","geometry":{"type":"Point","coordinates":[-6.001813,37.387697]}},{"properties":{"oficina":1,"id":"a6divgr6ttkn","lat":37.387697,"long":-6.001813},"type":"Feature","geometry":{"type":"Point","coordinates":[-6.001813,37.387697]}},{"properties":{"oficina":1,"id":"a6divgp5cma1","lat":37.387697,"long":-6.001813},"type":"Feature","geometry":{"type":"Point","coordinates":[-6.001813,37.387697]}},{"properties":{"oficina":1,"id":"a6divgpswrm6","lat":37.387699,"long":-6.00179},"type":"Feature","geometry":{"type":"Point","coordinates":[-6.00179,37.387699]}},{"properties":{"oficina":1,"id":"a6divgrq3ub2","lat":37.387699,"long":-6.00179},"type":"Feature","geometry":{"type":"Point","coordinates":[-6.00179,37.387699]}},{"properties":{"oficina":1,"id":"a6divguigqgv","lat":37.389629,"long":-5.920171},"type":"Feature","geometry":{"type":"Point","coordinates":[-5.920171,37.389629]}},{"properties":{"oficina":1,"id":"a6divgoh2kyz","lat":37.390591,"long":-5.93735},"type":"Feature","geometry":{"type":"Point","coordinates":[-5.93735,37.390591]}},{"properties":{"oficina":1,"id":"a6divgph8hz0","lat":37.39065,"long":-5.96787},"type":"Feature","geometry":{"type":"Point","coordinates":[-5.96787,37.39065]}},{"properties":{"oficina":1,"id":"a6divgw4vopc","lat":37.393052,"long":-5.953584},"type":"Feature","geometry":{"type":"Point","coordinates":[-5.953584,37.393052]}},{"properties":{"oficina":1,"id":"a6divgoq5nw6","lat":37.394588,"long":-5.943118},"type":"Feature","geometry":{"type":"Point","coordinates":[-5.943118,37.394588]}},{"properties":{"oficina":1,"id":"a6divh2v7c70","lat":37.394978,"long":-5.921402},"type":"Feature","geometry":{"type":"Point","coordinates":[-5.921402,37.394978]}},{"properties":{"oficina":1,"id":"a6divgyn1ys3","lat":37.39819,"long":-5.959964},"type":"Feature","geometry":{"type":"Point","coordinates":[-5.959964,37.39819]}},{"properties":{"oficina":1,"id":"a6divgz2v5x8","lat":37.399209,"long":-5.963001},"type":"Feature","geometry":{"type":"Point","coordinates":[-5.963001,37.399209]}},{"properties":{"oficina":1,"id":"a6divgoiws9y","lat":37.400264,"long":-5.941614},"type":"Feature","geometry":{"type":"Point","coordinates":[-5.941614,37.400264]}},{"properties":{"oficina":1,"id":"a6divgp9lifx","lat":37.405193,"long":-5.954332},"type":"Feature","geometry":{"type":"Point","coordinates":[-5.954332,37.405193]}},{"properties":{"oficina":2,"id":"a6divgun789c","lat":48.8357974624309,"long":2.4609375},"type":"Feature","geometry":{"type":"Point","coordinates":[2.4609375,48.8357974624309]}}],"is_temporal":false,"author":{"url":"","metadata":"","contact_name":"","contact_address":"","source":"","contact_phone":""},"source":"","pagination":{"sort":null,"start":0,"total":19,"limit":1000000},"state":"complete","tags":"","published":"2014-08-10T12:45:30-04:00","id":11087}