{"type":"FeatureCollection","data_type":"Dataset","url_type":null,"permissions":[{"permissions":{"download":true,"view":true},"group_id":"everyone"}],"classification":null,"title":"Tiftickjian Law Firm, P.C.","count":1,"stream_id":112304,"contributor":{"url":"http://geocommons.com/users/11586","name":"bharken"},"data_attributes":null,"calculation_params":null,"icon_link":null,"link":"http://geocommons.com/overlays/112304.json","extent":[-104.933,39.7058,-104.933,39.7058],"geometry_types":["point"],"unique_name":null,"name":"Tiftickjian Law Firm, P.C.","feature_count":1,"description":"Denver DUI attorney and criminal defense lawyer Jay Tiftickjian has been given Martindale Hubbell's highest rating, AV, and appears in Colorado Super Lawyers as a rising star for DUI and criminal law.","next_feature":null,"is_raster":false,"short_classification":"Y","stats":{},"features":[{"properties":{"city":"Denver","name":"Tiftickjian Law Firm, P.C.","region":"US-CO","balloon_text":"<b><a href=\"http://maps.google.com/maps/place?cid=15564892544808135858&amp;q=Tiftickjian+Law+Firm,+P.C.&amp;hl=en&amp;cad=src:kml_balloon&amp;ei=oiXATaO0OIK0MOnbyeAP\">$[name]</a></b>600 S. Cherry Street #1105Denver, CO 80246(303) 991-5896<a href=\"http://www.criminallawdenver.com/\">criminallawdenver.com</a><a href=\"/maps/place?cid=15564892544808135858&amp;q=Tiftickjian+Law+Firm,+P.C.&amp;hl=en&amp;cd=1&amp;cad=src:ppphoto&amp;ei=oiXATaO0OIK0MOnbyeAP\"><img src=\"http://lh6.googleusercontent.com/public/Arguhj7CK9k9MyujrleNaS7ccxo4q9RsgDd2oFqfkuMAu7gUauApYGI79KjAuJQh6nWurNIK7s9_ailEgPiwARe8K0skJ2SegaJUdLlBfFrbW6JvjgAGMC5-\"></a>  $[geDirections]","contents":"Tiftickjian Law Firm, P.C.","id":"a64pvtzj0op5"},"type":"Feature","geometry":{"type":"Point","coordinates":[-104.932537,39.705818]}}],"is_temporal":false,"author":{"url":"http://bbs.keyhole.com/ubb/ubbthreads.php?ubb=showflat&Number=1418130&#Post1418130","metadata":"","contact_name":"Jay Tiftickjian","contact_address":"600 S. Cherry Street #1105, Denver, CO 80246","source":"Google Earth Community","contact_phone":"(303) 991-5896"},"source":"http://bbs.keyhole.com/ubb/ubbthreads.php?ubb=showflat&Number=1418130&#Post1418130","pagination":{"sort":null,"start":0,"total":1,"limit":1000000},"state":"complete","tags":"criminal defense lawyer,dui attorney,dui defense,dui lawyer","published":"2014-08-13T00:35:09-04:00","id":112304}