{"type":"FeatureCollection","data_type":"Dataset","url_type":null,"permissions":[{"permissions":{"download":true,"view":true},"group_id":"everyone"}],"classification":null,"title":"Pending promise","count":1,"stream_id":115089,"contributor":{"url":"http://geocommons.com/users/26368","name":"carolinebins"},"data_attributes":null,"calculation_params":null,"icon_link":null,"link":"http://geocommons.com/overlays/115089.json","extent":[-122.42,37.7636,-122.42,37.7636],"geometry_types":["point"],"unique_name":null,"name":"Pending promise","feature_count":1,"description":"","next_feature":null,"is_raster":false,"short_classification":"Y","stats":{"8. longitude":{"max":-122.42,"min":-122.42,"median":-122.42},"7. latitude":{"max":37.763614,"min":37.763614,"median":37.763614}},"features":[{"properties":{"9. zip code":"94110","4. square feet":"?","2. status":"Promise pending","8. longitude":-122.42,"3. description":"580 Valencia St\nSan Francisco, California 94110\nDescription Promise Pending Charles Phan of the Slanted Door closed for expansion in 2002 and moved temporarily to Brannon St. He then opened the Slanted Door at the Ferry Building in April 2004. He said in a press release that the Valencia Street property would be under construction shortly but so far nothing has happened. According to his business partner nothing will be done with the three spaces until Phan is done with other business prospects.","5. city":"SAN FRANCISCO","id":"a621ia1owi6q","6. state":"CA","7. latitude":37.763614,"1. address":"584, 582, 580 VALENCIA STREET"},"type":"Feature","geometry":{"type":"Point","coordinates":[-122.42,37.763614]}}],"is_temporal":false,"author":{"url":"","metadata":"","contact_name":"","contact_address":"","source":"","contact_phone":""},"source":"","pagination":{"sort":null,"start":0,"total":1,"limit":1000000},"state":"complete","tags":"vacancy,valencia","published":"2014-08-13T04:27:17-04:00","id":115089}