{"type":"FeatureCollection","data_type":"Dataset","url_type":null,"permissions":[{"permissions":{"download":true,"view":true},"group_id":"everyone"}],"classification":null,"title":"Pils producers","count":4,"stream_id":116950,"contributor":{"url":"http://geocommons.com/users/26886","name":"jdart"},"data_attributes":null,"calculation_params":null,"icon_link":null,"link":"http://geocommons.com/overlays/116950.json","extent":[-122.4,37.7856,-122.268,37.877],"geometry_types":["point"],"unique_name":null,"name":"Pils producers","feature_count":4,"description":"S.F. and East Bay breweries that produce Pils","next_feature":null,"is_raster":false,"short_classification":"Y","stats":{},"features":[{"properties":{"city":"Berkeley","name":"Trumer Brauerei","zip":"94710","column_7":null,"geo_score":0.785,"website":"http://trumer-international.com","phone":"(510) 526-1160","id":"a6730goipua8","geo_precision":"range","address":"1404 4th St."},"type":"Feature","geometry":{"type":"Point","coordinates":[-122.302965,37.876971]}},{"properties":{"city":"Berkeley","name":"Jupiter","zip":"94704","column_7":null,"geo_score":0.902,"website":"http://jupiterbeer.com","phone":"(510) 843-8277","id":"a6730gqn0dwc","geo_precision":"range","address":"2181 Shattuck Ave."},"type":"Feature","geometry":{"type":"Point","coordinates":[-122.268017,37.869662]}},{"properties":{"city":"San Francisco","name":"Thirsty Bear","zip":"94105","column_7":"Y","geo_score":0.902,"website":"http://thirstybear.com","phone":"(415) 974-0905","id":"a6730gpqcx7j","geo_precision":"range","address":"661  Howard St."},"type":"Feature","geometry":{"type":"Point","coordinates":[-122.399627,37.785642]}},{"properties":{"city":"San Francisco","name":"Gordon Biersch","zip":"94105","column_7":"Y","geo_score":0.902,"website":"http://gordonbierschrestaurants.com","phone":"(415) 243-8246","id":"a6730gpab7j9","geo_precision":"range","address":"2 Harrison St."},"type":"Feature","geometry":{"type":"Point","coordinates":[-122.388481,37.789572]}}],"is_temporal":false,"author":{"url":"","metadata":"","contact_name":"","contact_address":"","source":"google maps","contact_phone":""},"source":"","pagination":{"sort":null,"start":0,"total":4,"limit":1000000},"state":"complete","tags":"area,bay,beer,berkeley,breweries,california,francisco,oakland,pilsner,san","published":"2014-08-13T07:15:49-04:00","id":116950}