{"type":"FeatureCollection","data_type":"Dataset","url_type":null,"permissions":[{"permissions":{"download":true,"view":true},"group_id":"everyone"}],"classification":null,"title":"5-9 cases","count":8,"stream_id":117118,"contributor":{"url":"http://geocommons.com/users/26725","name":"tfmalm2"},"data_attributes":null,"calculation_params":null,"icon_link":null,"link":"http://geocommons.com/overlays/117118.json","extent":[-85.8187,37.9563,-84.1987,38.8846],"geometry_types":["point"],"unique_name":null,"name":"5-9 cases","feature_count":8,"description":"","next_feature":null,"is_raster":false,"short_classification":"Y","stats":{"5":{"max":8,"mean":6.0,"variance":1.42857142857143,"stdev":1.19522860933439,"min":5,"median":6}},"features":[{"properties":{"40383":"40383","ky":"KY","geo_score":0.795,"id":"a6evitmpcgm4","geo_precision":"range","905 pinckard pike":"1500 Midway Pike","5":5,"versailles":"Versailles"},"type":"Feature","geometry":{"type":"Point","coordinates":[-84.723624,38.088636]}},{"properties":{"40383":"40347","ky":"KY","geo_score":0.817,"id":"a6evitbuq5w2","geo_precision":"range","905 pinckard pike":"596 Moores Mill Road","5":5,"versailles":"Midway"},"type":"Feature","geometry":{"type":"Point","coordinates":[-84.63625,38.158946]}},{"properties":{"40383":"47274","ky":"IN","geo_score":0.508,"id":"a6evitf0yb54","geo_precision":"street","905 pinckard pike":"351 S. U.S. Hwy 31","5":5,"versailles":"Seymour"},"type":"Feature","geometry":{"type":"Point","coordinates":[-85.818657,38.884606]}},{"properties":{"40383":"40515","ky":"KY","geo_score":1.0,"id":"a6evitd4eycu","geo_precision":"range","905 pinckard pike":"4959 Old Richmond Rd","5":5,"versailles":"Lexington"},"type":"Feature","geometry":{"type":"Point","coordinates":[-84.414649,37.956257]}},{"properties":{"40383":"40510","ky":"KY","geo_score":0.916,"id":"a6evit8cb7ad","geo_precision":"range","905 pinckard pike":"2714 Elkchester Pike","5":6,"versailles":"Lexington"},"type":"Feature","geometry":{"type":"Point","coordinates":[-84.628413,38.0667]}},{"properties":{"40383":"40511","ky":"KY","geo_score":0.902,"id":"a6evitdzyb77","geo_precision":"street","905 pinckard pike":"3601 Spurr Road","5":7,"versailles":"Lexington"},"type":"Feature","geometry":{"type":"Point","coordinates":[-84.551786,38.111362]}},{"properties":{"40383":"40361","ky":"KY","geo_score":0.915,"id":"a6evit879to2","geo_precision":"range","905 pinckard pike":"2311 Winchester Road","5":7,"versailles":"Paris"},"type":"Feature","geometry":{"type":"Point","coordinates":[-84.198743,38.129587]}},{"properties":{"40383":"40511","ky":"KY","geo_score":1.0,"id":"a6evitknh0q7","geo_precision":"range","905 pinckard pike":"4915 Paris Pike","5":8,"versailles":"Lexington"},"type":"Feature","geometry":{"type":"Point","coordinates":[-84.38199,38.124546]}}],"is_temporal":false,"author":{"url":"","metadata":"","contact_name":"","contact_address":"","source":"","contact_phone":""},"source":"","pagination":{"sort":null,"start":0,"total":8,"limit":1000000},"state":"complete","tags":"","published":"2014-08-13T07:29:09-04:00","id":117118}