{"type":"FeatureCollection","data_type":"Dataset","url_type":null,"permissions":[{"permissions":{"download":true,"view":true},"group_id":"everyone"}],"classification":null,"title":"somepoint","count":1,"stream_id":11951,"contributor":{"url":"http://geocommons.com/users/962","name":"bazandar"},"data_attributes":null,"calculation_params":null,"icon_link":null,"link":"http://geocommons.com/overlays/11951.json","extent":[10.7163,59.9431,10.7163,59.9431],"geometry_types":["point"],"unique_name":null,"name":"somepoint","feature_count":1,"description":"some point on earth","next_feature":null,"is_raster":false,"short_classification":"Y","stats":{},"features":[{"properties":{"name":"Simula","description":"! Ole-Johan Dahl and Kristen Nygaard! Norwegian Computing CenterBEGIN  OutText(\"Hello World!\");  OutImage;END;","id":"a64r7jgg1djj"},"type":"Feature","geometry":{"type":"Point","coordinates":[10.716305,59.943104]}}],"is_temporal":false,"author":{"url":"","metadata":"","contact_name":"","contact_address":"","source":"","contact_phone":""},"source":"","pagination":{"sort":null,"start":0,"total":1,"limit":1000000},"state":"complete","tags":"point,some","published":"2009-04-20T12:00:00Z","id":11951}