{"type":"FeatureCollection","url":"http://open.kent.gov.uk/mashuphub/client/plugin/generate/entryid/197/pluginid/4?op=nearest&stid=40&uprn=44071662","data_type":"Data Feed","url_type":"rss","permissions":[{"permissions":{"download":true,"view":true},"group_id":"everyone"}],"classification":null,"title":"Archives and Local Studies Centres in Medway","count":1,"stream_id":120260,"contributor":{"url":"http://geocommons.com/users/22533","name":"noelito"},"data_attributes":null,"calculation_params":null,"icon_link":null,"link":"http://geocommons.com/overlays/120260.json","extent":[0.497301,51.3937,0.497301,51.3937],"geometry_types":["point"],"unique_name":null,"name":"Archives and Local Studies Centres in Medway","feature_count":1,"description":"","next_feature":null,"is_raster":false,"short_classification":"Y","stats":{},"features":[{"properties":{"title":"Medway Archives and Local Studies Centre","description":"Medway Archives And Local Studies Centre, Civic Centre, Esplanade, Strood, Rochester, Kent, ME2 4AUTelephone 01634 332714Email <a href=\"mailto:malsc@medway.gov.uk\">malsc@medway.gov.uk</a>Information Medway Archives and Local Studies Centre (MALSC) is the place to visit for anyone interested in researching the history, geography and people of Medway. The centre houses special collections on Charles Dickens, Chatham Dockyard and Medway’s naval history. Local and family historians, researchers, students and business users are encouraged to use the public searchroom in Strood, where an extensive range of resources is available.Opening times Monday 9am-5pm, Tuesday 9am-5pm, Wednesday CLOSED, Thursday 9am-5pm, Friday 9am-5pm, Saturday 9am-4pm, Sunday CLOSED. By appointment onlyWeb link <a href=\"http://www.medway.gov.uk/leisureandculture/libraries/archivesandlocalstudies.aspx\">http://www.medway.gov.uk/leisureandculture/libraries/archivesandlocalstudies.aspx</a>","id":"a67hb97kgs9s"},"type":"Feature","geometry":{"type":"Point","coordinates":[0.497300923282373,51.3937032341138]}}],"is_temporal":false,"author":{"url":"","metadata":"","contact_name":"","contact_address":"","source":"","contact_phone":""},"source":"","pagination":{"sort":null,"start":0,"total":1,"limit":1000000},"state":"complete","tags":"","published":"2014-08-12T21:19:05-04:00","id":120260}