{"type":"FeatureCollection","data_type":"Dataset","url_type":null,"permissions":[{"permissions":{"download":true,"view":true},"group_id":"everyone"}],"classification":null,"title":"2550","count":7,"stream_id":12214,"contributor":{"url":"http://geocommons.com/users/6287","name":"sickelsaz"},"data_attributes":null,"calculation_params":null,"icon_link":null,"link":"http://geocommons.com/overlays/12214.json","extent":[-89.3067,29.3347,-82.31,41.5731],"geometry_types":["point"],"unique_name":null,"name":"2550","feature_count":7,"description":"","next_feature":null,"is_raster":false,"short_classification":"Y","stats":{"latitude":{"max":41.5731,"mean":39.7082571428571,"variance":20.9279950728571,"stdev":4.57471256723929,"min":29.3347,"median":41.41},"x":{"max":-82.31,"mean":-83.5540857142857,"variance":6.84169460809525,"stdev":2.61566332086055,"min":-89.3067,"median":-82.31},"y":{"max":41.5731,"mean":39.7082571428571,"variance":20.9279950728571,"stdev":4.57471256723929,"min":29.3347,"median":41.41},"end":{"max":268.0,"mean":146.714285714286,"variance":8296.2380952381,"stdev":91.0836873168741,"min":37.0,"median":126.0},"start":{"max":259.0,"mean":137.571428571429,"variance":8332.95238095238,"stdev":91.2850063315569,"min":27.0,"median":117.0},"index":{"max":6.0,"mean":3.0,"variance":4.66666666666667,"stdev":2.16024689946929,"min":0.0,"median":3.0},"longitude":{"max":-82.31,"mean":-83.5540857142857,"variance":6.84169460809525,"stdev":2.61566332086055,"min":-89.3067,"median":-82.31},"geoconfidence":{"max":0.46577,"mean":0.397359285714286,"variance":0.00418179983757143,"stdev":0.0646668372318566,"min":0.327264,"median":0.357858}},"features":[{"properties":{"latitude":41.5731,"x":-84.0219,"georef":"WEST DELTA","y":41.5731,"end":37.0,"start":27.0,"index":0.0,"xpath":"","offset":"","longitude":-84.0219,"id":"a6aui5iqnv9p","geoconfidence":0.327264,"style":"loc"},"type":"Feature","geometry":{"type":"Point","coordinates":[-84.0219,41.5731]}},{"properties":{"latitude":41.41,"x":-82.31,"georef":"VERMILION","y":41.41,"end":62.0,"start":53.0,"index":1.0,"xpath":"","offset":"","longitude":-82.31,"id":"a6aui5bl1e12","geoconfidence":0.350945,"style":"loc"},"type":"Feature","geometry":{"type":"Point","coordinates":[-82.31,41.41]}},{"properties":{"latitude":29.3347,"x":-89.3067,"georef":"MAIN PASS","y":29.3347,"end":88.0,"start":79.0,"index":2.0,"xpath":"","offset":"","longitude":-89.3067,"id":"a6aui5m5n14c","geoconfidence":0.357858,"style":"loc"},"type":"Feature","geometry":{"type":"Point","coordinates":[-89.3067,29.3347]}},{"properties":{"latitude":41.41,"x":-82.31,"georef":"VERMILION","y":41.41,"end":126.0,"start":117.0,"index":3.0,"xpath":"","offset":"","longitude":-82.31,"id":"a6aui5iu2sca","geoconfidence":0.46577,"style":"loc"},"type":"Feature","geometry":{"type":"Point","coordinates":[-82.31,41.41]}},{"properties":{"latitude":41.41,"x":-82.31,"georef":"VERMILION","y":41.41,"end":210.0,"start":201.0,"index":4.0,"xpath":"","offset":"","longitude":-82.31,"id":"a6aui5dc6a1h","geoconfidence":0.348138,"style":"loc"},"type":"Feature","geometry":{"type":"Point","coordinates":[-82.31,41.41]}},{"properties":{"latitude":41.41,"x":-82.31,"georef":"VERMILION","y":41.41,"end":236.0,"start":227.0,"index":5.0,"xpath":"","offset":"","longitude":-82.31,"id":"a6aui5exciev","geoconfidence":0.46577,"style":"loc"},"type":"Feature","geometry":{"type":"Point","coordinates":[-82.31,41.41]}},{"properties":{"latitude":41.41,"x":-82.31,"georef":"VERMILION","y":41.41,"end":268.0,"start":259.0,"index":6.0,"xpath":"","offset":"","longitude":-82.31,"id":"a6aui5iubwuu","geoconfidence":0.46577,"style":"loc"},"type":"Feature","geometry":{"type":"Point","coordinates":[-82.31,41.41]}}],"is_temporal":false,"author":{"url":"","metadata":"","contact_name":"","contact_address":"","source":"","contact_phone":""},"source":"","pagination":{"sort":null,"start":0,"total":7,"limit":1000000},"state":"complete","tags":"","published":"2009-04-28T12:00:00Z","id":12214}