{"type":"FeatureCollection","data_type":"Dataset","url_type":null,"permissions":[{"permissions":{"download":true,"view":true},"group_id":"everyone"}],"classification":null,"title":"7220","count":18,"stream_id":12227,"contributor":{"url":"http://geocommons.com/users/6254","name":"isidorotapia"},"data_attributes":null,"calculation_params":null,"icon_link":null,"link":"http://geocommons.com/overlays/12227.json","extent":[-6.20947,36.1916,-5.81226,36.4726],"geometry_types":["point"],"unique_name":null,"name":"7220","feature_count":18,"description":"","next_feature":null,"is_raster":false,"short_classification":"Y","stats":{"tam":{"max":8.0,"mean":4.33333333333333,"variance":2.70588235294118,"stdev":1.64495664165995,"min":3.0,"median":4.0},"ent":{"max":1290.0,"mean":952.222222222222,"variance":185903.594771242,"stdev":431.165391434936,"min":152.0,"median":1162.0},"lat":{"max":36.47257,"mean":36.3925029336914,"variance":0.00831056090442614,"stdev":0.0911622778589156,"min":36.1916461785806,"median":36.422745},"long":{"max":-5.812263,"mean":-6.11607080317688,"variance":0.0138792565082132,"stdev":0.117810256379541,"min":-6.209472,"median":-6.151894}},"features":[{"properties":{"tam":5.0,"ent":1268.0,"id":"a64ia0hmuwnm","lat":36.1916461785806,"long":-5.92278957366943},"type":"Feature","geometry":{"type":"Point","coordinates":[-5.92278957366943,36.1916461785806]}},{"properties":{"tam":4.0,"ent":1289.0,"id":"a64ia0h3jq9w","lat":36.248965,"long":-5.965599},"type":"Feature","geometry":{"type":"Point","coordinates":[-5.965599,36.248965]}},{"properties":{"tam":3.0,"ent":1143.0,"id":"a64ia0gjt9v8","lat":36.2542406278642,"long":-5.9654688835144},"type":"Feature","geometry":{"type":"Point","coordinates":[-5.9654688835144,36.2542406278642]}},{"properties":{"tam":7.0,"ent":1161.0,"id":"a64ia0en8oej","lat":36.277815,"long":-6.087739},"type":"Feature","geometry":{"type":"Point","coordinates":[-6.087739,36.277815]}},{"properties":{"tam":5.0,"ent":1151.0,"id":"a64ia0b5cnx2","lat":36.345864,"long":-5.812263},"type":"Feature","geometry":{"type":"Point","coordinates":[-5.812263,36.345864]}},{"properties":{"tam":4.0,"ent":1270.0,"id":"a64ia0ldf2hv","lat":36.351871,"long":-6.150269},"type":"Feature","geometry":{"type":"Point","coordinates":[-6.150269,36.351871]}},{"properties":{"tam":3.0,"ent":381.0,"id":"a64ia0i72din","lat":36.418775,"long":-6.152434},"type":"Feature","geometry":{"type":"Point","coordinates":[-6.152434,36.418775]}},{"properties":{"tam":8.0,"ent":1162.0,"id":"a64ia0hjtk0i","lat":36.42086,"long":-6.148749},"type":"Feature","geometry":{"type":"Point","coordinates":[-6.148749,36.42086]}},{"properties":{"tam":3.0,"ent":1137.0,"id":"a64ia0epd3sl","lat":36.421175,"long":-6.143884},"type":"Feature","geometry":{"type":"Point","coordinates":[-6.143884,36.421175]}},{"properties":{"tam":6.0,"ent":161.0,"id":"a64ia0dlrx0j","lat":36.422745,"long":-6.151894},"type":"Feature","geometry":{"type":"Point","coordinates":[-6.151894,36.422745]}},{"properties":{"tam":3.0,"ent":369.0,"id":"a64ia0bsw511","lat":36.455016,"long":-6.209472},"type":"Feature","geometry":{"type":"Point","coordinates":[-6.209472,36.455016]}},{"properties":{"tam":3.0,"ent":1188.0,"id":"a64ia0guoebz","lat":36.455455,"long":-6.201169},"type":"Feature","geometry":{"type":"Point","coordinates":[-6.201169,36.455455]}},{"properties":{"tam":3.0,"ent":1184.0,"id":"a64ia0ia58mq","lat":36.465455,"long":-6.196739},"type":"Feature","geometry":{"type":"Point","coordinates":[-6.196739,36.465455]}},{"properties":{"tam":6.0,"ent":1290.0,"id":"a64ia0h09565","lat":36.465455,"long":-6.196739},"type":"Feature","geometry":{"type":"Point","coordinates":[-6.196739,36.465455]}},{"properties":{"tam":3.0,"ent":374.0,"id":"a64ia09j7rsa","lat":36.465455,"long":-6.196739},"type":"Feature","geometry":{"type":"Point","coordinates":[-6.196739,36.465455]}},{"properties":{"tam":3.0,"ent":1273.0,"id":"a64ia0nlzqx1","lat":36.465455,"long":-6.196739},"type":"Feature","geometry":{"type":"Point","coordinates":[-6.196739,36.465455]}},{"properties":{"tam":6.0,"ent":152.0,"id":"a64ia0kmwl4t","lat":36.466235,"long":-6.196024},"type":"Feature","geometry":{"type":"Point","coordinates":[-6.196024,36.466235]}},{"properties":{"tam":3.0,"ent":1187.0,"id":"a64ia0dm2ikq","lat":36.47257,"long":-6.194564},"type":"Feature","geometry":{"type":"Point","coordinates":[-6.194564,36.47257]}}],"is_temporal":false,"author":{"url":"","metadata":"","contact_name":"","contact_address":"","source":"","contact_phone":""},"source":"","pagination":{"sort":null,"start":0,"total":18,"limit":1000000},"state":"complete","tags":"","published":"2014-08-10T14:55:03-04:00","id":12227}