{"type":"FeatureCollection","data_type":"Dataset","url_type":null,"permissions":[{"permissions":{"download":true,"view":true},"group_id":"everyone"}],"classification":null,"title":"7218","count":20,"stream_id":12225,"contributor":{"url":"http://geocommons.com/users/6254","name":"isidorotapia"},"data_attributes":null,"calculation_params":null,"icon_link":null,"link":"http://geocommons.com/overlays/12225.json","extent":[-6.14582,36.4582,-5.72194,36.7575],"geometry_types":["point"],"unique_name":null,"name":"7218","feature_count":20,"description":"","next_feature":null,"is_raster":false,"short_classification":"Y","stats":{"tam":{"max":7.0,"mean":4.1,"variance":3.0421052631579,"stdev":1.74416319854476,"min":1.0,"median":4.0},"ent":{"max":1294.0,"mean":1203.6,"variance":2397.83157894737,"stdev":48.9676584997421,"min":1136.0,"median":1194.0},"lat":{"max":36.75755,"mean":36.6369289851782,"variance":0.0082807998606318,"stdev":0.0909989003264974,"min":36.458246,"median":36.68272018},"long":{"max":-5.721943,"mean":-6.00015547957485,"variance":0.0147385316304489,"stdev":0.121402354303567,"min":-6.1458206,"median":-5.969229}},"features":[{"properties":{"tam":5.0,"ent":1226.0,"id":"a68w3y46u8la","lat":36.458246,"long":-5.927932},"type":"Feature","geometry":{"type":"Point","coordinates":[-5.927932,36.458246]}},{"properties":{"tam":4.0,"ent":1155.0,"id":"a68w3y46cup8","lat":36.462064,"long":-5.721943},"type":"Feature","geometry":{"type":"Point","coordinates":[-5.721943,36.462064]}},{"properties":{"tam":3.0,"ent":1294.0,"id":"a68w3y70uk6z","lat":36.46318,"long":-5.928274},"type":"Feature","geometry":{"type":"Point","coordinates":[-5.928274,36.46318]}},{"properties":{"tam":5.0,"ent":1156.0,"id":"a68w3y8n3696","lat":36.521913,"long":-5.866532},"type":"Feature","geometry":{"type":"Point","coordinates":[-5.866532,36.521913]}},{"properties":{"tam":5.0,"ent":1144.0,"id":"a68w3xyal2qv","lat":36.60769,"long":-5.802474},"type":"Feature","geometry":{"type":"Point","coordinates":[-5.802474,36.60769]}},{"properties":{"tam":2.0,"ent":1262.0,"id":"a68w3y6moxsa","lat":36.608903,"long":-5.944237},"type":"Feature","geometry":{"type":"Point","coordinates":[-5.944237,36.608903]}},{"properties":{"tam":2.0,"ent":1272.0,"id":"a68w3xyfxanx","lat":36.619405,"long":-5.969229},"type":"Feature","geometry":{"type":"Point","coordinates":[-5.969229,36.619405]}},{"properties":{"tam":1.0,"ent":1261.0,"id":"a68w3xvlvok2","lat":36.64935,"long":-5.934649},"type":"Feature","geometry":{"type":"Point","coordinates":[-5.934649,36.64935]}},{"properties":{"tam":6.0,"ent":1164.0,"id":"a68w3y2do77y","lat":36.650655,"long":-5.932379},"type":"Feature","geometry":{"type":"Point","coordinates":[-5.932379,36.650655]}},{"properties":{"tam":4.0,"ent":1192.0,"id":"a68w3y260z3w","lat":36.6743737,"long":-6.1458206},"type":"Feature","geometry":{"type":"Point","coordinates":[-6.1458206,36.6743737]}},{"properties":{"tam":5.0,"ent":1206.0,"id":"a68w3y6ox6a9","lat":36.68272018,"long":-6.1205649},"type":"Feature","geometry":{"type":"Point","coordinates":[-6.1205649,36.68272018]}},{"properties":{"tam":4.0,"ent":1194.0,"id":"a68w3y1y25h0","lat":36.686161728,"long":-6.10170364},"type":"Feature","geometry":{"type":"Point","coordinates":[-6.10170364,36.686161728]}},{"properties":{"tam":3.0,"ent":1185.0,"id":"a68w3xwoisa8","lat":36.687065,"long":-6.109389},"type":"Feature","geometry":{"type":"Point","coordinates":[-6.109389,36.687065]}},{"properties":{"tam":7.0,"ent":1183.0,"id":"a68w3y3ww0c9","lat":36.687538302,"long":-6.135821342},"type":"Feature","geometry":{"type":"Point","coordinates":[-6.135821342,36.687538302]}},{"properties":{"tam":3.0,"ent":1136.0,"id":"a68w3y3fckym","lat":36.6903,"long":-6.098634},"type":"Feature","geometry":{"type":"Point","coordinates":[-6.098634,36.6903]}},{"properties":{"tam":3.0,"ent":1198.0,"id":"a68w3xw0yjcq","lat":36.6919947935644,"long":-6.11363410949707},"type":"Feature","geometry":{"type":"Point","coordinates":[-6.11363410949707,36.6919947935644]}},{"properties":{"tam":7.0,"ent":1209.0,"id":"a68w3y8kjcmc","lat":36.701655,"long":-6.098481},"type":"Feature","geometry":{"type":"Point","coordinates":[-6.098481,36.701655]}},{"properties":{"tam":7.0,"ent":1170.0,"id":"a68w3y1carj1","lat":36.71325,"long":-6.089154},"type":"Feature","geometry":{"type":"Point","coordinates":[-6.089154,36.71325]}},{"properties":{"tam":3.0,"ent":1172.0,"id":"a68w3xymi82a","lat":36.724565,"long":-5.930674},"type":"Feature","geometry":{"type":"Point","coordinates":[-5.930674,36.724565]}},{"properties":{"tam":3.0,"ent":1293.0,"id":"a68w3xut549t","lat":36.75755,"long":-6.031584},"type":"Feature","geometry":{"type":"Point","coordinates":[-6.031584,36.75755]}}],"is_temporal":false,"author":{"url":"","metadata":"","contact_name":"","contact_address":"","source":"","contact_phone":""},"source":"","pagination":{"sort":null,"start":0,"total":20,"limit":1000000},"state":"complete","tags":"","published":"2014-08-10T14:55:02-04:00","id":12225}