{"type":"FeatureCollection","data_type":"Dataset","url_type":null,"permissions":[{"permissions":{"download":true,"view":true},"group_id":"everyone"}],"classification":null,"title":"orangeminor","count":2,"stream_id":12480,"contributor":{"url":"http://geocommons.com/users/3995","name":"amazon"},"data_attributes":null,"calculation_params":null,"icon_link":null,"link":"http://geocommons.com/overlays/12480.json","extent":[66.4491,30.2099,67.0225,30.9295],"geometry_types":["point"],"unique_name":null,"name":"orangeminor","feature_count":2,"description":"","next_feature":null,"is_raster":false,"short_classification":"Y","stats":{"lat":{"max":30.9295,"mean":30.5697,"variance":0.25891208,"stdev":0.508834039741839,"min":30.2099,"median":30.9295},"long":{"max":67.0225,"mean":66.7358,"variance":0.164393779999996,"stdev":0.405455028332361,"min":66.4491,"median":67.0225}},"features":[{"properties":{"name":"Chaman","id":"a67xv7vm5af8","lat":30.9295,"long":66.4491},"type":"Feature","geometry":{"type":"Point","coordinates":[66.4491,30.9295]}},{"properties":{"name":"Quetta","id":"a67xv7uba6w2","lat":30.2099,"long":67.0225},"type":"Feature","geometry":{"type":"Point","coordinates":[67.0225,30.2099]}}],"is_temporal":false,"author":{"url":"","metadata":"","contact_name":"","contact_address":"","source":"","contact_phone":""},"source":"","pagination":{"sort":null,"start":0,"total":2,"limit":1000000},"state":"complete","tags":"","published":"2009-05-08T12:00:17Z","id":12480}