{"type":"FeatureCollection","data_type":"Dataset","url_type":null,"permissions":[{"permissions":{"download":true,"view":true},"group_id":"everyone"}],"classification":null,"title":"7213","count":17,"stream_id":12718,"contributor":{"url":"http://geocommons.com/users/6254","name":"isidorotapia"},"data_attributes":null,"calculation_params":null,"icon_link":null,"link":"http://geocommons.com/overlays/12718.json","extent":[-6.00181,37.3546,-5.95953,37.3877],"geometry_types":["point"],"unique_name":null,"name":"7213","feature_count":17,"description":"","next_feature":null,"is_raster":false,"short_classification":"Y","stats":{"tam":{"max":6.0,"mean":4.0,"variance":1.15625,"stdev":1.07529065838033,"min":2.0,"median":4.0},"ent":{"max":1120.0,"mean":569.529411764706,"variance":128189.889705882,"stdev":358.036156981222,"min":6.0,"median":383.0},"lat":{"max":37.387699,"mean":37.3773232117647,"variance":0.00014537694858736,"stdev":0.0120572363577795,"min":37.354599,"median":37.382469},"long":{"max":-5.959525,"mean":-5.98884435294118,"variance":0.000187909329867648,"stdev":0.0137080024025256,"min":-6.001813,"median":-5.985968}},"features":[{"properties":{"tam":4.0,"ent":6.0,"id":"a64g3xmjenyb","lat":37.354599,"long":-5.98142},"type":"Feature","geometry":{"type":"Point","coordinates":[-5.98142,37.354599]}},{"properties":{"tam":5.0,"ent":344.0,"id":"a64g3xh7tu1w","lat":37.359062,"long":-5.985968},"type":"Feature","geometry":{"type":"Point","coordinates":[-5.985968,37.359062]}},{"properties":{"tam":4.0,"ent":939.0,"id":"a64g3xcdnbnq","lat":37.359558,"long":-5.97809},"type":"Feature","geometry":{"type":"Point","coordinates":[-5.97809,37.359558]}},{"properties":{"tam":3.5,"ent":1120.0,"id":"a64g3x88d4yu","lat":37.36494,"long":-5.980489},"type":"Feature","geometry":{"type":"Point","coordinates":[-5.980489,37.36494]}},{"properties":{"tam":4.0,"ent":915.0,"id":"a64g3xc80xfc","lat":37.369695,"long":-5.976894},"type":"Feature","geometry":{"type":"Point","coordinates":[-5.976894,37.369695]}},{"properties":{"tam":3.0,"ent":176.0,"id":"a64g3xfmliu3","lat":37.3706176,"long":-5.959525},"type":"Feature","geometry":{"type":"Point","coordinates":[-5.959525,37.3706176]}},{"properties":{"tam":5.0,"ent":384.0,"id":"a64g3ximc0hl","lat":37.37344,"long":-5.98247},"type":"Feature","geometry":{"type":"Point","coordinates":[-5.98247,37.37344]}},{"properties":{"tam":4.0,"ent":934.0,"id":"a64g3xc4awbx","lat":37.378532,"long":-5.972663},"type":"Feature","geometry":{"type":"Point","coordinates":[-5.972663,37.378532]}},{"properties":{"tam":2.0,"ent":922.0,"id":"a64g3xlshwjj","lat":37.382469,"long":-5.9784},"type":"Feature","geometry":{"type":"Point","coordinates":[-5.9784,37.382469]}},{"properties":{"tam":4.0,"ent":342.0,"id":"a64g3x73t9nr","lat":37.387697,"long":-6.001813},"type":"Feature","geometry":{"type":"Point","coordinates":[-6.001813,37.387697]}},{"properties":{"tam":4.5,"ent":383.0,"id":"a64g3xea1a9j","lat":37.387697,"long":-6.001813},"type":"Feature","geometry":{"type":"Point","coordinates":[-6.001813,37.387697]}},{"properties":{"tam":3.0,"ent":966.0,"id":"a64g3xc7n27f","lat":37.387697,"long":-6.001813},"type":"Feature","geometry":{"type":"Point","coordinates":[-6.001813,37.387697]}},{"properties":{"tam":5.0,"ent":346.0,"id":"a64g3xe043fq","lat":37.387697,"long":-6.001813},"type":"Feature","geometry":{"type":"Point","coordinates":[-6.001813,37.387697]}},{"properties":{"tam":6.0,"ent":340.0,"id":"a64g3xb13kfz","lat":37.387697,"long":-6.001813},"type":"Feature","geometry":{"type":"Point","coordinates":[-6.001813,37.387697]}},{"properties":{"tam":5.0,"ent":365.0,"id":"a64g3xh6pqik","lat":37.387699,"long":-6.00179},"type":"Feature","geometry":{"type":"Point","coordinates":[-6.00179,37.387699]}},{"properties":{"tam":2.0,"ent":979.0,"id":"a64g3xa23h9y","lat":37.387699,"long":-6.00179},"type":"Feature","geometry":{"type":"Point","coordinates":[-6.00179,37.387699]}},{"properties":{"tam":4.0,"ent":221.0,"id":"a64g3xbku0cj","lat":37.387699,"long":-6.00179},"type":"Feature","geometry":{"type":"Point","coordinates":[-6.00179,37.387699]}}],"is_temporal":false,"author":{"url":"","metadata":"","contact_name":"","contact_address":"","source":"","contact_phone":""},"source":"","pagination":{"sort":null,"start":0,"total":17,"limit":1000000},"state":"complete","tags":"","published":"2014-08-10T15:23:59-04:00","id":12718}