{"type":"FeatureCollection","data_type":"Dataset","url_type":null,"permissions":[{"permissions":{"download":true,"view":true},"group_id":"everyone"}],"classification":null,"title":"7233","count":20,"stream_id":12722,"contributor":{"url":"http://geocommons.com/users/6254","name":"isidorotapia"},"data_attributes":null,"calculation_params":null,"icon_link":null,"link":"http://geocommons.com/overlays/12722.json","extent":[-5.54616,37.2613,-5.07607,37.5983],"geometry_types":["point"],"unique_name":null,"name":"7233","feature_count":20,"description":"","next_feature":null,"is_raster":false,"short_classification":"Y","stats":{"tam":{"max":7.0,"mean":4.075,"variance":2.13881578947368,"stdev":1.46246907299734,"min":2.0,"median":4.0},"ent":{"max":1515.0,"mean":728.7,"variance":104049.168421053,"stdev":322.566533324604,"min":142.0,"median":624.0},"lat":{"max":37.59832,"mean":37.4421297,"variance":0.0143304078828526,"stdev":0.119709681658806,"min":37.261315,"median":37.524932},"long":{"max":-5.076074,"mean":-5.2844635,"variance":0.0321355992963684,"stdev":0.179264049090632,"min":-5.546159,"median":-5.253009}},"features":[{"properties":{"tam":4.0,"ent":502.0,"id":"a6ivywqk7bpn","lat":37.261315,"long":-5.546159},"type":"Feature","geometry":{"type":"Point","coordinates":[-5.546159,37.261315]}},{"properties":{"tam":4.0,"ent":629.0,"id":"a6ivywsz5tw5","lat":37.263065,"long":-5.544624},"type":"Feature","geometry":{"type":"Point","coordinates":[-5.544624,37.263065]}},{"properties":{"tam":3.0,"ent":509.0,"id":"a6ivywwospee","lat":37.290677,"long":-5.496373},"type":"Feature","geometry":{"type":"Point","coordinates":[-5.496373,37.290677]}},{"properties":{"tam":3.5,"ent":624.0,"id":"a6ivywxmli20","lat":37.291126,"long":-5.495547},"type":"Feature","geometry":{"type":"Point","coordinates":[-5.495547,37.291126]}},{"properties":{"tam":3.0,"ent":515.0,"id":"a6ivywl7rwfc","lat":37.325565,"long":-5.418229},"type":"Feature","geometry":{"type":"Point","coordinates":[-5.418229,37.325565]}},{"properties":{"tam":5.0,"ent":506.0,"id":"a6ivyx16qit0","lat":37.329901,"long":-5.416212},"type":"Feature","geometry":{"type":"Point","coordinates":[-5.416212,37.329901]}},{"properties":{"tam":4.0,"ent":616.0,"id":"a6ivywv6mikh","lat":37.330186,"long":-5.413793},"type":"Feature","geometry":{"type":"Point","coordinates":[-5.413793,37.330186]}},{"properties":{"tam":2.0,"ent":505.0,"id":"a6ivywuju5wj","lat":37.35329,"long":-5.223369},"type":"Feature","geometry":{"type":"Point","coordinates":[-5.223369,37.35329]}},{"properties":{"tam":3.0,"ent":1005.0,"id":"a6ivywos8fy6","lat":37.462165,"long":-5.347889},"type":"Feature","geometry":{"type":"Point","coordinates":[-5.347889,37.462165]}},{"properties":{"tam":3.0,"ent":531.0,"id":"a6ivywu3z61y","lat":37.463539,"long":-5.34305},"type":"Feature","geometry":{"type":"Point","coordinates":[-5.34305,37.463539]}},{"properties":{"tam":3.0,"ent":1006.0,"id":"a6ivywyb76cq","lat":37.524932,"long":-5.253009},"type":"Feature","geometry":{"type":"Point","coordinates":[-5.253009,37.524932]}},{"properties":{"tam":3.0,"ent":1011.0,"id":"a6ivywpyv458","lat":37.53529,"long":-5.076074},"type":"Feature","geometry":{"type":"Point","coordinates":[-5.076074,37.53529]}},{"properties":{"tam":7.0,"ent":1004.0,"id":"a6ivywzcqy0r","lat":37.538655,"long":-5.077649},"type":"Feature","geometry":{"type":"Point","coordinates":[-5.077649,37.538655]}},{"properties":{"tam":5.5,"ent":589.0,"id":"a6ivywmieoa2","lat":37.53866,"long":-5.078219},"type":"Feature","geometry":{"type":"Point","coordinates":[-5.078219,37.53866]}},{"properties":{"tam":3.0,"ent":353.0,"id":"a6ivywz1u6aa","lat":37.540765,"long":-5.079084},"type":"Feature","geometry":{"type":"Point","coordinates":[-5.079084,37.540765]}},{"properties":{"tam":5.0,"ent":1009.0,"id":"a6ivywungo3f","lat":37.540765,"long":-5.079084},"type":"Feature","geometry":{"type":"Point","coordinates":[-5.079084,37.540765]}},{"properties":{"tam":7.0,"ent":1515.0,"id":"a6ivywxaz0uj","lat":37.542238,"long":-5.078609},"type":"Feature","geometry":{"type":"Point","coordinates":[-5.078609,37.542238]}},{"properties":{"tam":6.5,"ent":142.0,"id":"a6ivywrqgluc","lat":37.543755,"long":-5.085309},"type":"Feature","geometry":{"type":"Point","coordinates":[-5.085309,37.543755]}},{"properties":{"tam":4.0,"ent":1001.0,"id":"a6ivywvcs280","lat":37.568385,"long":-5.426524},"type":"Feature","geometry":{"type":"Point","coordinates":[-5.426524,37.568385]}},{"properties":{"tam":3.0,"ent":1002.0,"id":"a6ivywzizjg1","lat":37.59832,"long":-5.210464},"type":"Feature","geometry":{"type":"Point","coordinates":[-5.210464,37.59832]}}],"is_temporal":false,"author":{"url":"","metadata":"","contact_name":"","contact_address":"","source":"","contact_phone":""},"source":"","pagination":{"sort":null,"start":0,"total":20,"limit":1000000},"state":"complete","tags":"","published":"2014-08-10T15:23:59-04:00","id":12722}