{"type":"FeatureCollection","data_type":"Dataset","url_type":null,"permissions":[{"permissions":{"download":true,"view":true},"group_id":"everyone"}],"classification":null,"title":"7234","count":12,"stream_id":12953,"contributor":{"url":"http://geocommons.com/users/6716","name":"isidorotapia2"},"data_attributes":null,"calculation_params":null,"icon_link":null,"link":"http://geocommons.com/overlays/12953.json","extent":[-5.98304,37.3983,-5.92322,37.4847],"geometry_types":["point"],"unique_name":null,"name":"7234","feature_count":12,"description":"","next_feature":null,"is_raster":false,"short_classification":"Y","stats":{"tam":{"max":11.0,"mean":5.29166666666667,"variance":5.56628787878788,"stdev":2.35929817504865,"min":3.0,"median":4.5},"ent":{"max":950.0,"mean":397.833333333333,"variance":109443.424242424,"stdev":330.822345440002,"min":113.0,"median":269.0},"lat":{"max":37.4847344,"mean":37.4224374775,"variance":0.000459212185677978,"stdev":0.0214292367031114,"min":37.39832357,"median":37.41961184},"long":{"max":-5.923221,"mean":-5.9557140935,"variance":0.000490949680294988,"stdev":0.0221573843288189,"min":-5.983039,"median":-5.96443891}},"features":[{"properties":{"tam":8.5,"ent":254.0,"id":"a6wp5iupicok","lat":37.39832357,"long":-5.933218002},"type":"Feature","geometry":{"type":"Point","coordinates":[-5.933218002,37.39832357]}},{"properties":{"tam":4.0,"ent":173.0,"id":"a6wp5j22fai0","lat":37.407359,"long":-5.923221},"type":"Feature","geometry":{"type":"Point","coordinates":[-5.923221,37.407359]}},{"properties":{"tam":4.0,"ent":950.0,"id":"a6wp5izax7ip","lat":37.410309,"long":-5.92627},"type":"Feature","geometry":{"type":"Point","coordinates":[-5.92627,37.410309]}},{"properties":{"tam":4.0,"ent":297.0,"id":"a6wp5j2e4wd1","lat":37.413288,"long":-5.968},"type":"Feature","geometry":{"type":"Point","coordinates":[-5.968,37.413288]}},{"properties":{"tam":3.0,"ent":240.0,"id":"a6wp5ixunjj1","lat":37.41766905,"long":-5.962207317},"type":"Feature","geometry":{"type":"Point","coordinates":[-5.962207317,37.41766905]}},{"properties":{"tam":5.0,"ent":947.0,"id":"a6wp5ir8h0tb","lat":37.4186234,"long":-5.96443891},"type":"Feature","geometry":{"type":"Point","coordinates":[-5.96443891,37.4186234]}},{"properties":{"tam":4.5,"ent":113.0,"id":"a6wp5iqyvjxv","lat":37.41961184,"long":-5.968236923},"type":"Feature","geometry":{"type":"Point","coordinates":[-5.968236923,37.41961184]}},{"properties":{"tam":6.5,"ent":269.0,"id":"a6wp5j2l7q5o","lat":37.42027647,"long":-5.964953899},"type":"Feature","geometry":{"type":"Point","coordinates":[-5.964953899,37.42027647]}},{"properties":{"tam":4.5,"ent":140.0,"id":"a6wp5iv3q1u2","lat":37.423435,"long":-5.966649},"type":"Feature","geometry":{"type":"Point","coordinates":[-5.966649,37.423435]}},{"properties":{"tam":11.0,"ent":919.0,"id":"a6wp5ivpsgez","lat":37.424485,"long":-5.983039},"type":"Feature","geometry":{"type":"Point","coordinates":[-5.983039,37.424485]}},{"properties":{"tam":5.5,"ent":274.0,"id":"a6wp5ittue02","lat":37.431135,"long":-5.925979},"type":"Feature","geometry":{"type":"Point","coordinates":[-5.925979,37.431135]}},{"properties":{"tam":3.0,"ent":198.0,"id":"a6wp5iys8cg3","lat":37.4847344,"long":-5.982356071},"type":"Feature","geometry":{"type":"Point","coordinates":[-5.982356071,37.4847344]}}],"is_temporal":false,"author":{"url":"","metadata":"","contact_name":"","contact_address":"","source":"","contact_phone":""},"source":"","pagination":{"sort":null,"start":0,"total":12,"limit":1000000},"state":"complete","tags":"","published":"2014-08-10T15:36:34-04:00","id":12953}