{"type":"FeatureCollection","data_type":"Dataset","url_type":null,"permissions":[{"permissions":{"download":true,"view":true},"group_id":"everyone"}],"classification":null,"title":"7235","count":18,"stream_id":13046,"contributor":{"url":"http://geocommons.com/users/6716","name":"isidorotapia2"},"data_attributes":null,"calculation_params":null,"icon_link":null,"link":"http://geocommons.com/overlays/13046.json","extent":[-6.00229,37.389,-5.91846,37.4052],"geometry_types":["point"],"unique_name":null,"name":"7235","feature_count":18,"description":"","next_feature":null,"is_raster":false,"short_classification":"Y","stats":{"tam":{"max":5.0,"mean":3.72222222222222,"variance":0.712418300653595,"stdev":0.844048754903172,"min":2.0,"median":4.0},"ent":{"max":1609.0,"mean":785.944444444444,"variance":194409.349673203,"stdev":440.918756318216,"min":153.0,"median":968.0},"lat":{"max":37.40519306,"mean":37.3957016372222,"variance":2.67292186860751e-05,"stdev":0.00517003082061172,"min":37.38896437,"median":37.3962609},"long":{"max":-5.918455124,"mean":-5.94847842055556,"variance":0.000607938472921076,"stdev":0.024656408354038,"min":-6.002290249,"median":-5.941758156}},"features":[{"properties":{"tam":4.0,"ent":153.0,"id":"a68n19y43674","lat":37.38896437,"long":-6.002290249},"type":"Feature","geometry":{"type":"Point","coordinates":[-6.002290249,37.38896437]}},{"properties":{"tam":4.0,"ent":1115.0,"id":"a68n1a5y7cxh","lat":37.38898142,"long":-6.001088619},"type":"Feature","geometry":{"type":"Point","coordinates":[-6.001088619,37.38898142]}},{"properties":{"tam":4.5,"ent":154.0,"id":"a68n1a5fcoqk","lat":37.38962927,"long":-5.920171737},"type":"Feature","geometry":{"type":"Point","coordinates":[-5.920171737,37.38962927]}},{"properties":{"tam":3.0,"ent":985.0,"id":"a68n19vudiks","lat":37.38998729,"long":-5.923047066},"type":"Feature","geometry":{"type":"Point","coordinates":[-5.923047066,37.38998729]}},{"properties":{"tam":4.0,"ent":1111.0,"id":"a68n19wn9tg4","lat":37.390591,"long":-5.93735},"type":"Feature","geometry":{"type":"Point","coordinates":[-5.93735,37.390591]}},{"properties":{"tam":3.5,"ent":164.0,"id":"a68n19vcaeph","lat":37.39065,"long":-5.967877214},"type":"Feature","geometry":{"type":"Point","coordinates":[-5.967877214,37.39065]}},{"properties":{"tam":4.0,"ent":1609.0,"id":"a68n1aa9fr43","lat":37.393052,"long":-5.953584},"type":"Feature","geometry":{"type":"Point","coordinates":[-5.953584,37.393052]}},{"properties":{"tam":3.0,"ent":396.0,"id":"a68n19vw0sji","lat":37.394588,"long":-5.943118},"type":"Feature","geometry":{"type":"Point","coordinates":[-5.943118,37.394588]}},{"properties":{"tam":2.0,"ent":982.0,"id":"a68n1a5e41l3","lat":37.394978,"long":-5.921402},"type":"Feature","geometry":{"type":"Point","coordinates":[-5.921402,37.394978]}},{"properties":{"tam":4.0,"ent":175.0,"id":"a68n1a04tweb","lat":37.3962609,"long":-5.918455124},"type":"Feature","geometry":{"type":"Point","coordinates":[-5.918455124,37.3962609]}},{"properties":{"tam":2.0,"ent":981.0,"id":"a68n19z1b62o","lat":37.39784626,"long":-5.941758156},"type":"Feature","geometry":{"type":"Point","coordinates":[-5.941758156,37.39784626]}},{"properties":{"tam":5.0,"ent":912.0,"id":"a68n19tt8zn3","lat":37.39819,"long":-5.959964},"type":"Feature","geometry":{"type":"Point","coordinates":[-5.959964,37.39819]}},{"properties":{"tam":5.0,"ent":285.0,"id":"a68n1a4gjeue","lat":37.39920999,"long":-5.963001251},"type":"Feature","geometry":{"type":"Point","coordinates":[-5.963001251,37.39920999]}},{"properties":{"tam":4.0,"ent":1127.0,"id":"a68n1a8x332f","lat":37.400264,"long":-5.941614},"type":"Feature","geometry":{"type":"Point","coordinates":[-5.941614,37.400264]}},{"properties":{"tam":4.0,"ent":957.0,"id":"a68n19whf8rm","lat":37.40040324,"long":-5.9278965},"type":"Feature","geometry":{"type":"Point","coordinates":[-5.9278965,37.40040324]}},{"properties":{"tam":3.0,"ent":952.0,"id":"a68n1a4nz8tz","lat":37.40166465,"long":-5.939462185},"type":"Feature","geometry":{"type":"Point","coordinates":[-5.939462185,37.40166465]}},{"properties":{"tam":4.0,"ent":1121.0,"id":"a68n1a0llqso","lat":37.40217602,"long":-5.956199169},"type":"Feature","geometry":{"type":"Point","coordinates":[-5.956199169,37.40217602]}},{"properties":{"tam":4.0,"ent":968.0,"id":"a68n1a16ynti","lat":37.40519306,"long":-5.9543323},"type":"Feature","geometry":{"type":"Point","coordinates":[-5.9543323,37.40519306]}}],"is_temporal":false,"author":{"url":"","metadata":"","contact_name":"","contact_address":"","source":"","contact_phone":""},"source":"","pagination":{"sort":null,"start":0,"total":18,"limit":1000000},"state":"complete","tags":"","published":"2014-08-10T15:42:34-04:00","id":13046}