{"type":"FeatureCollection","data_type":"Dataset","url_type":null,"permissions":[{"permissions":{"download":true,"view":true},"group_id":"everyone"}],"classification":null,"title":"7224","count":17,"stream_id":13086,"contributor":{"url":"http://geocommons.com/users/6716","name":"isidorotapia2"},"data_attributes":null,"calculation_params":null,"icon_link":null,"link":"http://geocommons.com/overlays/13086.json","extent":[-5.43331,36.161,-5.28293,36.3409],"geometry_types":["point"],"unique_name":null,"name":"7224","feature_count":17,"description":"","next_feature":null,"is_raster":false,"short_classification":"Y","stats":{"tam":{"max":17.0,"mean":4.23529411764706,"variance":13.4411764705882,"stdev":3.66622100678454,"min":2.0,"median":3.0},"ent":{"max":1320.0,"mean":1221.64705882353,"variance":3159.49264705882,"stdev":56.2093644071771,"min":1135.0,"median":1233.0},"lat":{"max":36.34094,"mean":36.2160427072643,"variance":0.00376125909773994,"stdev":0.061329104817696,"min":36.1610058173948,"median":36.181388},"long":{"max":-5.28293,"mean":-5.34984095661917,"variance":0.00190473148027451,"stdev":0.0436432294895154,"min":-5.433307,"median":-5.34834623336791}},"features":[{"properties":{"tam":4.0,"ent":1248.0,"id":"a6hqqz179sqk","lat":36.1610058173948,"long":-5.35070657730102},"type":"Feature","geometry":{"type":"Point","coordinates":[-5.35070657730102,36.1610058173948]}},{"properties":{"tam":17.0,"ent":1175.0,"id":"a6hqqz0ij92h","lat":36.161698778762,"long":-5.34953713417053},"type":"Feature","geometry":{"type":"Point","coordinates":[-5.34953713417053,36.161698778762]}},{"properties":{"tam":3.0,"ent":1243.0,"id":"a6hqqz1my7v7","lat":36.1625649718573,"long":-5.34596443176269},"type":"Feature","geometry":{"type":"Point","coordinates":[-5.34596443176269,36.1625649718573]}},{"properties":{"tam":4.0,"ent":1239.0,"id":"a6hqqyxpixj2","lat":36.1664973681472,"long":-5.35952568054199},"type":"Feature","geometry":{"type":"Point","coordinates":[-5.35952568054199,36.1664973681472]}},{"properties":{"tam":3.0,"ent":1307.0,"id":"a6hqqyp6c8me","lat":36.1677965746652,"long":-5.34705877304077},"type":"Feature","geometry":{"type":"Point","coordinates":[-5.34705877304077,36.1677965746652]}},{"properties":{"tam":3.0,"ent":1191.0,"id":"a6hqqytymu54","lat":36.172958542446,"long":-5.34834623336791},"type":"Feature","geometry":{"type":"Point","coordinates":[-5.34834623336791,36.172958542446]}},{"properties":{"tam":4.0,"ent":1222.0,"id":"a6hqqyo5nsaz","lat":36.1731837212202,"long":-5.33774614334106},"type":"Feature","geometry":{"type":"Point","coordinates":[-5.33774614334106,36.1731837212202]}},{"properties":{"tam":2.0,"ent":1295.0,"id":"a6hqqytcipr9","lat":36.175747249,"long":-5.374932289},"type":"Feature","geometry":{"type":"Point","coordinates":[-5.374932289,36.175747249]}},{"properties":{"tam":2.0,"ent":1229.0,"id":"a6hqqyxl2m11","lat":36.181388,"long":-5.385665},"type":"Feature","geometry":{"type":"Point","coordinates":[-5.385665,36.181388]}},{"properties":{"tam":2.0,"ent":1139.0,"id":"a6hqqyrhan82","lat":36.20882,"long":-5.428649},"type":"Feature","geometry":{"type":"Point","coordinates":[-5.428649,36.20882]}},{"properties":{"tam":9.0,"ent":1233.0,"id":"a6hqqyzzioxy","lat":36.210788,"long":-5.389618},"type":"Feature","geometry":{"type":"Point","coordinates":[-5.389618,36.210788]}},{"properties":{"tam":4.0,"ent":1238.0,"id":"a6hqqywc8ymc","lat":36.21573,"long":-5.433307},"type":"Feature","geometry":{"type":"Point","coordinates":[-5.433307,36.21573]}},{"properties":{"tam":3.0,"ent":1320.0,"id":"a6hqqz1s8wqm","lat":36.276741,"long":-5.28293},"type":"Feature","geometry":{"type":"Point","coordinates":[-5.28293,36.276741]}},{"properties":{"tam":3.0,"ent":1135.0,"id":"a6hqqyuz9g6c","lat":36.293765,"long":-5.298709},"type":"Feature","geometry":{"type":"Point","coordinates":[-5.298709,36.293765]}},{"properties":{"tam":3.0,"ent":1240.0,"id":"a6hqqyv4jlko","lat":36.299281,"long":-5.304023},"type":"Feature","geometry":{"type":"Point","coordinates":[-5.304023,36.299281]}},{"properties":{"tam":2.0,"ent":1166.0,"id":"a6hqqyon1aij","lat":36.30382,"long":-5.291564},"type":"Feature","geometry":{"type":"Point","coordinates":[-5.291564,36.30382]}},{"properties":{"tam":4.0,"ent":1148.0,"id":"a6hqqz0yncsp","lat":36.34094,"long":-5.319014},"type":"Feature","geometry":{"type":"Point","coordinates":[-5.319014,36.34094]}}],"is_temporal":false,"author":{"url":"","metadata":"","contact_name":"","contact_address":"","source":"","contact_phone":""},"source":"","pagination":{"sort":null,"start":0,"total":17,"limit":1000000},"state":"complete","tags":"","published":"2014-08-10T15:44:05-04:00","id":13086}