{"type":"FeatureCollection","data_type":"Dataset","url_type":null,"permissions":[{"permissions":{"download":true,"view":true},"group_id":"everyone"}],"classification":null,"title":"Book4","count":1,"stream_id":135789,"contributor":{"url":"http://geocommons.com/users/30057","name":"junkchuk"},"data_attributes":null,"calculation_params":null,"icon_link":null,"link":"http://geocommons.com/overlays/135789.json","extent":[-75.1631,39.955,-75.1631,39.955],"geometry_types":["point"],"unique_name":null,"name":"Book4","feature_count":1,"description":"","next_feature":null,"is_raster":false,"short_classification":"Y","stats":{},"features":[{"properties":{"city":"Philadelphia","geo_score":0.625,"zip code":"19102","street address":"118 N. Broad St.","id":"a67f9617rg3w","geo_precision":"street","state":"PA"},"type":"Feature","geometry":{"type":"Point","coordinates":[-75.163086,39.955017]}}],"is_temporal":false,"author":{"url":"","metadata":"","contact_name":"","contact_address":"","source":"","contact_phone":""},"source":"","pagination":{"sort":null,"start":0,"total":1,"limit":1000000},"state":"complete","tags":"","published":"2014-08-13T04:49:36-04:00","id":135789}