{"type":"FeatureCollection","data_type":"Dataset","url_type":null,"permissions":[{"permissions":{"download":true,"view":true},"group_id":"everyone"}],"classification":null,"title":"oakland-zips-income-demo","count":14,"stream_id":137252,"contributor":{"url":"http://geocommons.com/users/30323","name":"keithibus"},"data_attributes":null,"calculation_params":null,"icon_link":null,"link":"http://geocommons.com/overlays/137252.json","extent":[-122.299,37.7425,-122.157,37.8431],"geometry_types":["point"],"unique_name":null,"name":"oakland-zips-income-demo","feature_count":14,"description":"","next_feature":null,"is_raster":false,"short_classification":"Y","stats":{"median household income 2008":{"max":94774,"mean":51500.7142857143,"variance":434805858.21978,"stdev":20851.9989022583,"min":24357,"median":43114}},"features":[{"properties":{"geo_score":0.714,"zip code":"94601","id":"a64n4nl4et3g","geo_precision":"zip","median household income 2008":40306},"type":"Feature","geometry":{"type":"Point","coordinates":[-122.223779,37.786027]}},{"properties":{"geo_score":0.714,"zip code":"94602","id":"a64n4nwx9ill","geo_precision":"zip","median household income 2008":67259},"type":"Feature","geometry":{"type":"Point","coordinates":[-122.204578,37.802777]}},{"properties":{"geo_score":0.714,"zip code":"94603","id":"a64n4ni3w7qy","geo_precision":"zip","median household income 2008":42255},"type":"Feature","geometry":{"type":"Point","coordinates":[-122.198428,37.761778]}},{"properties":{"geo_score":0.714,"zip code":"94605","id":"a64n4nicxsom","geo_precision":"zip","median household income 2008":57493},"type":"Feature","geometry":{"type":"Point","coordinates":[-122.156626,37.759322]}},{"properties":{"geo_score":0.714,"zip code":"94606","id":"a64n4no2r189","geo_precision":"zip","median household income 2008":39238},"type":"Feature","geometry":{"type":"Point","coordinates":[-122.243979,37.789927]}},{"properties":{"geo_score":0.714,"zip code":"94607","id":"a64n4nphxtyo","geo_precision":"zip","median household income 2008":25683},"type":"Feature","geometry":{"type":"Point","coordinates":[-122.29878,37.807967]}},{"properties":{"geo_score":0.714,"zip code":"94608","id":"a64n4nubvs62","geo_precision":"zip","median household income 2008":43114},"type":"Feature","geometry":{"type":"Point","coordinates":[-122.29548,37.833876]}},{"properties":{"geo_score":0.714,"zip code":"94609","id":"a64n4nq3nznq","geo_precision":"zip","median household income 2008":41821},"type":"Feature","geometry":{"type":"Point","coordinates":[-122.26328,37.834776]}},{"properties":{"geo_score":0.714,"zip code":"94610","id":"a64n4nn8ecby","geo_precision":"zip","median household income 2008":59655},"type":"Feature","geometry":{"type":"Point","coordinates":[-122.238779,37.811277]}},{"properties":{"geo_score":0.714,"zip code":"94611","id":"a64n4nkg12f6","geo_precision":"zip","median household income 2008":83712},"type":"Feature","geometry":{"type":"Point","coordinates":[-122.231635,37.824372]}},{"properties":{"geo_score":0.714,"zip code":"94612","id":"a64n4nvvbw1s","geo_precision":"zip","median household income 2008":24357},"type":"Feature","geometry":{"type":"Point","coordinates":[-122.27018,37.809435]}},{"properties":{"geo_score":0.714,"zip code":"94618","id":"a64n4ntluhrq","geo_precision":"zip","median household income 2008":94774},"type":"Feature","geometry":{"type":"Point","coordinates":[-122.240179,37.843126]}},{"properties":{"geo_score":0.714,"zip code":"94619","id":"a64n4ntru3f5","geo_precision":"zip","median household income 2008":65865},"type":"Feature","geometry":{"type":"Point","coordinates":[-122.167126,37.783877]}},{"properties":{"geo_score":0.714,"zip code":"94621","id":"a64n4ntoew0i","geo_precision":"zip","median household income 2008":35478},"type":"Feature","geometry":{"type":"Point","coordinates":[-122.196689,37.742529]}}],"is_temporal":false,"author":{"url":"","metadata":null,"contact_name":null,"contact_address":null,"source":null,"contact_phone":null},"source":"","pagination":{"sort":null,"start":0,"total":14,"limit":1000000},"state":"complete","tags":"","published":"2014-08-13T07:21:18-04:00","id":137252}