{"type":"FeatureCollection","data_type":"Dataset","url_type":null,"permissions":[{"permissions":{"download":true,"view":true},"group_id":"everyone"}],"classification":null,"title":"test","count":3,"stream_id":137284,"contributor":{"url":"http://geocommons.com/users/30336","name":"mhwinkler"},"data_attributes":null,"calculation_params":null,"icon_link":null,"link":"http://geocommons.com/overlays/137284.json","extent":[-118.64,33.7615,-118.137,34.2569],"geometry_types":["point"],"unique_name":null,"name":"test","feature_count":3,"description":"","next_feature":null,"is_raster":false,"short_classification":"Y","stats":{"latitude":{"max":34.256948,"mean":33.929168,"variance":0.0805940318290009,"stdev":0.283890880144116,"min":33.761505,"median":33.769051},"longitude":{"max":-118.136986,"mean":-118.320738333333,"variance":0.0771948912603345,"stdev":0.277839686258703,"min":-118.640367,"median":-118.184862}},"features":[{"properties":{"latitude":34.256948,"percentage":"60.34","longitude":-118.640367,"id":"0"},"type":"Feature","geometry":{"type":"Point","coordinates":[-118.640367,34.256948]}},{"properties":{"latitude":33.769051,"percentage":"24.35","longitude":-118.184862,"id":"1"},"type":"Feature","geometry":{"type":"Point","coordinates":[-118.184862,33.769051]}},{"properties":{"latitude":33.761505,"percentage":"23.32","longitude":-118.136986,"id":"2"},"type":"Feature","geometry":{"type":"Point","coordinates":[-118.136986,33.761505]}}],"is_temporal":false,"author":{"url":"","metadata":"","contact_name":"","contact_address":"","source":"","contact_phone":""},"source":"","pagination":{"sort":null,"start":0,"total":3,"limit":1000000},"state":"complete","tags":"","published":"2014-08-13T07:24:21-04:00","id":137284}