{"type":"FeatureCollection","data_type":"Dataset","url_type":null,"permissions":[{"permissions":{"download":true,"view":true},"group_id":"everyone"}],"classification":null,"title":"oaklandschools","count":7,"stream_id":137365,"contributor":{"url":"http://geocommons.com/users/30316","name":"addyh"},"data_attributes":null,"calculation_params":null,"icon_link":null,"link":"http://geocommons.com/overlays/137365.json","extent":[-122.476,33.5461,-76.8475,47.3523],"geometry_types":["point"],"unique_name":null,"name":"oaklandschools","feature_count":7,"description":"Oakland schools participating in Prescott Circus","next_feature":null,"is_raster":false,"short_classification":"Y","stats":{},"features":[{"properties":{"geo_score":0.265,"81.6% free/reduced lunch":"92.9% free/reduced lunch","preparatory literacy academy of cultural excellence (prescott elementary)":"Futures Elementary (Lockwood Elementary)","id":"a63ce87m0ofq","geo_precision":"street","212 students":"300 students","920 campbell st., oakland, ca 94607":"6701 International Blvd., Oakland, CA 94621"},"type":"Feature","geometry":{"type":"Point","coordinates":[-95.702469,39.15878]}},{"properties":{"geo_score":0.315,"81.6% free/reduced lunch":"41.6% free/reduced lunch","preparatory literacy academy of cultural excellence (prescott elementary)":"Piedmont Avenue Elementary","id":"a63ce8i1n1rd","geo_precision":"street","212 students":"357 students","920 campbell st., oakland, ca 94607":"5314 Piedmont Ave., Oakland, CA 94611"},"type":"Feature","geometry":{"type":"Point","coordinates":[-95.702469,39.15878]}},{"properties":{"geo_score":0.325,"81.6% free/reduced lunch":"90.4% free/reduced lunch","preparatory literacy academy of cultural excellence (prescott elementary)":"Garfield Elementary","id":"a63ce8j6i8ny","geo_precision":"street","212 students":"651 students","920 campbell st., oakland, ca 94607":"1640 22nd Ave., Oakland, CA 94606"},"type":"Feature","geometry":{"type":"Point","coordinates":[-95.702469,39.15878]}},{"properties":{"geo_score":0.616,"81.6% free/reduced lunch":"75.1% free/reduced lunch","preparatory literacy academy of cultural excellence (prescott elementary)":"Laurel Elementary","id":"a63ce8fkugod","geo_precision":"street","212 students":"457 students","920 campbell st., oakland, ca 94607":"3750 Brown Avenue, Oakland, CA 94619"},"type":"Feature","geometry":{"type":"Point","coordinates":[-76.847473,39.101358]}},{"properties":{"geo_score":0.348,"81.6% free/reduced lunch":"71.2% free/reduced lunch","preparatory literacy academy of cultural excellence (prescott elementary)":"Parker Elementary","id":"a63ce875rajs","geo_precision":"street","212 students":"230 students","920 campbell st., oakland, ca 94607":"7929 Ney Ave., Oakland, CA 94605"},"type":"Feature","geometry":{"type":"Point","coordinates":[-95.702469,39.15878]}},{"properties":{"geo_score":0.339,"81.6% free/reduced lunch":"81.8% free/reduced lunch","preparatory literacy academy of cultural excellence (prescott elementary)":"Manzanita Community School","id":"a63ce87pd8t0","geo_precision":"street","212 students":"290 students","920 campbell st., oakland, ca 94607":"2409 E. 27th St., Oakland, CA 94601"},"type":"Feature","geometry":{"type":"Point","coordinates":[-91.628419,33.54607]}},{"properties":{"geo_score":0.459,"81.6% free/reduced lunch":"87.7% free/reduced lunch","preparatory literacy academy of cultural excellence (prescott elementary)":"Manzanita Seed School","id":"a63ce8jnhqu9","geo_precision":"street","212 students":"219 students","920 campbell st., oakland, ca 94607":"2409 E. 27th St., Oakland, CA 94601"},"type":"Feature","geometry":{"type":"Point","coordinates":[-122.475916,47.352318]}}],"is_temporal":false,"author":{"url":"http://publicportal.ousd.k12.ca.us/199410811183734550/FlexBase/FlexBaseDisplay.asp?DirectoryID=3&DisplayType=C&Field0=&Submit=Submit","metadata":"","contact_name":"","contact_address":"","source":"Oakland Unified School District ","contact_phone":""},"source":"http://publicportal.ousd.k12.ca.us/199410811183734550/FlexBase/FlexBaseDisplay.asp?DirectoryID=3&DisplayType=C&Field0=&Submit=Submit","pagination":{"sort":null,"start":0,"total":7,"limit":1000000},"state":"complete","tags":"maps,oakland","published":"2011-07-22T03:39:19Z","id":137365}