{"type":"FeatureCollection","data_type":"Dataset","url_type":null,"permissions":[{"permissions":{"download":true,"view":true},"group_id":"everyone"}],"classification":null,"title":"Valley View Main Office","count":1,"stream_id":137641,"contributor":{"url":"http://geocommons.com/users/30159","name":"blanem"},"data_attributes":null,"calculation_params":null,"icon_link":null,"link":"http://geocommons.com/overlays/137641.json","extent":[-122.287,47.471,-122.287,47.471],"geometry_types":["point"],"unique_name":null,"name":"Valley View Main Office","feature_count":1,"description":"Main Office Location","next_feature":null,"is_raster":false,"short_classification":"Y","stats":{},"features":[{"properties":{"Name":"Valley View Main Office","id":"0"},"type":"Feature","geometry":{"type":"Point","coordinates":[-122.287126494929,47.4710227538116]}}],"is_temporal":false,"author":{"url":"","metadata":"","contact_name":"","contact_address":"","source":"","contact_phone":""},"source":"","pagination":{"sort":null,"start":0,"total":1,"limit":1000000},"state":"complete","tags":"valley,view","published":"2011-07-22T16:00:00Z","id":137641}