{"type":"FeatureCollection","data_type":"Dataset","url_type":null,"permissions":[{"permissions":{"download":true,"view":true},"group_id":"everyone"}],"classification":null,"title":"Kar_PHC","count":1,"stream_id":138191,"contributor":{"url":"http://geocommons.com/users/29139","name":"sabyasachi"},"data_attributes":null,"calculation_params":null,"icon_link":null,"link":"http://geocommons.com/overlays/138191.json","extent":[79.2985,10.4903,79.2985,10.4903],"geometry_types":["point"],"unique_name":null,"name":"Kar_PHC","feature_count":1,"description":"","next_feature":null,"is_raster":false,"short_classification":"Y","stats":{"latitude":{"max":10.49029035,"min":10.49029035,"median":10.49029035},"column_5":{"max":-56.1,"min":-56.1,"median":-56.1},"column_6":{"max":12,"min":12,"median":12},"longitude":{"max":79.29849906,"min":79.29849906,"median":79.29849906},"column_1":{"max":2,"min":2,"median":2},"column_2":{"max":2,"min":2,"median":2}},"features":[{"properties":{"column_4":"Karambayam","latitude":10.49029035,"column_5":-56.1,"column_6":12,"longitude":79.29849906,"column_1":2,"id":"a68vqw7z8m3y","column_2":2,"column_3":"Pattukottai"},"type":"Feature","geometry":{"type":"Point","coordinates":[79.29849906,10.49029035]}}],"is_temporal":false,"author":{"url":"","metadata":null,"contact_name":null,"contact_address":null,"source":null,"contact_phone":null},"source":"","pagination":{"sort":null,"start":0,"total":1,"limit":1000000},"state":"complete","tags":"","published":"2014-08-13T08:50:34-04:00","id":138191}