{"type":"FeatureCollection","data_type":"Dataset","url_type":null,"permissions":[{"permissions":{"download":true,"view":true},"group_id":"everyone"},{"permissions":{"download":true,"view":true},"group_id":31270}],"classification":null,"title":"AMDG_Water_Polo_Club_Carpool","count":12,"stream_id":142845,"contributor":{"url":"http://geocommons.com/users/31137","name":"jeff.carr@amdgpolo.com"},"data_attributes":null,"calculation_params":null,"icon_link":null,"link":"http://geocommons.com/overlays/142845.json","extent":[-84.7355,39.1202,-84.3477,39.3821],"geometry_types":["point"],"unique_name":null,"name":"AMDG_Water_Polo_Club_Carpool","feature_count":12,"description":"","next_feature":null,"is_raster":false,"short_classification":"Y","stats":{},"features":[{"properties":{"1122 herschel ave 45208":"3850 Drakewood Drive 45209","zink":"Young","geo_score":0.819,"adam":"Cameron","id":"a6b7ovbdb4wd","geo_precision":"range"},"type":"Feature","geometry":{"type":"Point","coordinates":[-84.433732,39.149105]}},{"properties":{"1122 herschel ave 45208":"310 Compton Hills Drive 45215","zink":"Hayes","geo_score":0.795,"adam":"Chris","id":"a6b7ov8xqx7b","geo_precision":"range"},"type":"Feature","geometry":{"type":"Point","coordinates":[-84.493452,39.226139]}},{"properties":{"1122 herschel ave 45208":"4122 Wenbrook Drive 45241","zink":"Dornoff","geo_score":0.641,"adam":"Eric","id":"a6b7ovma7mz7","geo_precision":"street"},"type":"Feature","geometry":{"type":"Point","coordinates":[-84.393169,39.264548]}},{"properties":{"1122 herschel ave 45208":"21 Camargo Canyon 45243","zink":"Nelson","geo_score":0.823,"adam":"Erik","id":"a6b7ovdngfi1","geo_precision":"range"},"type":"Feature","geometry":{"type":"Point","coordinates":[-84.381455,39.177219]}},{"properties":{"1122 herschel ave 45208":"6679 Cherry Laurel Dr 45044","zink":"Lindquist","geo_score":0.826,"adam":"Graham","id":"a6b7ovk1naux","geo_precision":"range"},"type":"Feature","geometry":{"type":"Point","coordinates":[-84.355034,39.38209]}},{"properties":{"1122 herschel ave 45208":"8656 Charleston Ridge Dr 45040","zink":"Kang","geo_score":0.828,"adam":"GunWoo","id":"a6b7ov8x5mzs","geo_precision":"range"},"type":"Feature","geometry":{"type":"Point","coordinates":[-84.347722,39.313199]}},{"properties":{"1122 herschel ave 45208":"9540 Ambleside Dr. 45241","zink":"Fogarty","geo_score":0.805,"adam":"Joshua","id":"a6b7ov8yysxd","geo_precision":"range"},"type":"Feature","geometry":{"type":"Point","coordinates":[-84.362128,39.309262]}},{"properties":{"1122 herschel ave 45208":"4040 Egbert Ave 45220","zink":"Chabot","geo_score":0.815,"adam":"Marshall","id":"a6b7ovj471la","geo_precision":"range"},"type":"Feature","geometry":{"type":"Point","coordinates":[-84.517739,39.160077]}},{"properties":{"1122 herschel ave 45208":"2194 Victory Parkway 45206","zink":"Frey","geo_score":0.805,"adam":"Mitchell","id":"a6b7ovlea6im","geo_precision":"range"},"type":"Feature","geometry":{"type":"Point","coordinates":[-84.485999,39.120183]}},{"properties":{"1122 herschel ave 45208":"10695 Stargate Lane 45240","zink":"Hessler","geo_score":0.824,"adam":"Robin","id":"a6b7ovc99twm","geo_precision":"range"},"type":"Feature","geometry":{"type":"Point","coordinates":[-84.54118,39.268065]}},{"properties":{"1122 herschel ave 45208":"539 Aston View Lane 45002","zink":"Kerr","geo_score":0.767,"adam":"Teddy","id":"a6b7ovn9p4c4","geo_precision":"range"},"type":"Feature","geometry":{"type":"Point","coordinates":[-84.735469,39.158111]}},{"properties":{"1122 herschel ave 45208":"39 Arcadia Pl 45208","zink":"Roberts","geo_score":0.816,"adam":"Mike","id":"a6b7ovhqmvjx","geo_precision":"range"},"type":"Feature","geometry":{"type":"Point","coordinates":[-84.438584,39.13524]}}],"is_temporal":false,"author":{"url":"","metadata":"","contact_name":"","contact_address":"","source":"","contact_phone":""},"source":"","pagination":{"sort":null,"start":0,"total":12,"limit":1000000},"state":"complete","tags":"","published":"2014-08-13T01:39:43-04:00","id":142845}