{"type":"FeatureCollection","data_type":"Dataset","url_type":null,"permissions":[{"permissions":{"download":true,"view":true},"group_id":"everyone"}],"classification":null,"title":"Book1","count":3,"stream_id":146782,"contributor":{"url":"http://geocommons.com/users/18734","name":"sar_mil"},"data_attributes":null,"calculation_params":null,"icon_link":null,"link":"http://geocommons.com/overlays/146782.json","extent":[-86.0502,32.2732,-86.0502,32.2732],"geometry_types":["point"],"unique_name":null,"name":"Book1","feature_count":3,"description":"","next_feature":null,"is_raster":false,"short_classification":"Y","stats":{"customer":{"max":3,"mean":2.0,"variance":1.0,"stdev":1.0,"min":1,"median":2}},"features":[{"properties":{"postcode":"E17 6AY","country":"England","geo_score":0.0,"town":"Walthamstow","customer":1,"id":"a6kkzpolux4e","address":"Chamberlain Place","geo_precision":"unmatched"},"type":"Feature","geometry":{"type":"Point","coordinates":[-91.185392,30.589661]}},{"properties":{"postcode":"W1B 5NH","country":"England","geo_score":0.714,"town":"London","customer":2,"id":"a6kkzpvy5mwc","address":"Warwick Street","geo_precision":"city"},"type":"Feature","geometry":{"type":"Point","coordinates":[-86.050237,32.273198]}},{"properties":{"postcode":"W5 3RH","country":"England","geo_score":0.0,"town":"Ealing","customer":3,"id":"a6kkzpqg8o4t","address":"Inglis Road","geo_precision":"unmatched"},"type":"Feature","geometry":{"type":"Point","coordinates":[-92.200471,33.350448]}}],"is_temporal":false,"author":{"url":"","metadata":"","contact_name":"","contact_address":"","source":"","contact_phone":""},"source":"","pagination":{"sort":null,"start":0,"total":3,"limit":1000000},"state":"complete","tags":"","published":"2014-08-13T08:37:02-04:00","id":146782}