{"type":"FeatureCollection","data_type":"Dataset","url_type":null,"permissions":[{"permissions":{"download":true,"view":true},"group_id":"everyone"}],"classification":null,"title":"LONG BEACH AIRPORT RUNWAY UNDERPASS","count":2,"stream_id":146884,"contributor":{"url":"http://geocommons.com/users/29098","name":"lastreetsblog"},"data_attributes":null,"calculation_params":null,"icon_link":null,"link":"http://geocommons.com/overlays/146884.json","extent":[-118.144,33.8089,-118.141,33.8113],"geometry_types":["point"],"unique_name":null,"name":"LONG BEACH AIRPORT RUNWAY UNDERPASS","feature_count":2,"description":"","next_feature":null,"is_raster":false,"short_classification":"Y","stats":{"Id":{"max":2,"mean":1.5,"variance":0.5,"stdev":0.707106781186548,"min":1,"median":2}},"features":[{"properties":{"CITY":"LONG BEACH","Id":1,"STREET_NAM":"LAKEWOOD BLVD","id":"0"},"type":"Feature","geometry":{"type":"Point","coordinates":[-118.141089236349,33.80889925998]}},{"properties":{"CITY":"LONG BEACH","Id":2,"STREET_NAM":"SPRING ST","id":"1"},"type":"Feature","geometry":{"type":"Point","coordinates":[-118.143940390298,33.8113107037236]}}],"is_temporal":false,"author":{"url":"","metadata":"","contact_name":"","contact_address":"","source":"","contact_phone":""},"source":"","pagination":{"sort":null,"start":0,"total":2,"limit":1000000},"state":"complete","tags":"beach,bicycle,long,streetsblog","published":"2014-08-13T08:45:04-04:00","id":146884}