{"type":"FeatureCollection","data_type":"Dataset","url_type":null,"permissions":[{"permissions":{"download":true,"view":true},"group_id":"everyone"}],"classification":null,"title":"geocode_IPG","count":2,"stream_id":147332,"contributor":{"url":"http://geocommons.com/users/31665","name":"nhall"},"data_attributes":null,"calculation_params":null,"icon_link":null,"link":"http://geocommons.com/overlays/147332.json","extent":[-71.1126,42.2145,-70.7384,42.3572],"geometry_types":["point"],"unique_name":null,"name":"geocode_IPG","feature_count":2,"description":"","next_feature":null,"is_raster":false,"short_classification":"Y","stats":{},"features":[{"properties":{"geo_score":0.714,"zip code":"2134","id":"a62i37dixrzl","geo_precision":"zip"},"type":"Feature","geometry":{"type":"Point","coordinates":[-71.112646,42.357169]}},{"properties":{"geo_score":0.714,"zip code":"2066","id":"a62i37lq79y6","geo_precision":"zip"},"type":"Feature","geometry":{"type":"Point","coordinates":[-70.738375,42.214546]}}],"is_temporal":false,"author":{"url":"","metadata":null,"contact_name":null,"contact_address":null,"source":null,"contact_phone":null},"source":"","pagination":{"sort":null,"start":0,"total":2,"limit":1000000},"state":"complete","tags":"","published":"2014-08-13T09:15:52-04:00","id":147332}