{"type":"FeatureCollection","data_type":"Dataset","url_type":null,"permissions":[{"permissions":{"download":true,"view":true},"group_id":"everyone"}],"classification":null,"title":"valuesTest","count":2,"stream_id":148281,"contributor":{"url":"http://geocommons.com/users/16669","name":"AKhabil"},"data_attributes":null,"calculation_params":null,"icon_link":null,"link":"http://geocommons.com/overlays/148281.json","extent":[-83.8316,37.3131,-83.7316,37.762],"geometry_types":["point"],"unique_name":null,"name":"valuesTest","feature_count":2,"description":"","next_feature":null,"is_raster":false,"short_classification":"Y","stats":{},"features":[{"properties":{"val":"coucou","me":"Algeeeeeeeeeee","geo_score":0.673,"id":"0","geo_precision":"city"},"type":"Feature","geometry":{"type":"Point","coordinates":[-83.731585,37.313145]}},{"properties":{"val":"30","me":"France","geo_score":0.653,"id":"1","geo_precision":"city"},"type":"Feature","geometry":{"type":"Point","coordinates":[-83.831585,37.762027]}}],"is_temporal":false,"author":{"url":"","metadata":"","contact_name":"","contact_address":"","source":"","contact_phone":""},"source":"","pagination":{"sort":null,"start":0,"total":2,"limit":1000000},"state":"complete","tags":"","published":"2014-08-13T10:27:51-04:00","id":148281}