{"type":"FeatureCollection","data_type":"Dataset","url_type":null,"permissions":[{"permissions":{"download":true,"view":true},"group_id":"everyone"}],"classification":null,"title":"grande arche","count":1,"stream_id":14857,"contributor":{"url":"http://geocommons.com/users/7750","name":"thomas_ruegmer"},"data_attributes":null,"calculation_params":null,"icon_link":null,"link":"http://geocommons.com/overlays/14857.json","extent":[2.2363,48.8923,2.2363,48.8923],"geometry_types":["point"],"unique_name":null,"name":"grande arche","feature_count":1,"description":"Grande Arche - La Défense, Paris","next_feature":null,"is_raster":false,"short_classification":"Y","stats":{},"features":[{"properties":{"title":"grande arche","summary":"<img src=\"http://www.printblogger.de/karte/grande_arche.jpg\" height=\"98\" width=\"130\">","id":"a635ul9urj1e"},"type":"Feature","geometry":{"type":"Point","coordinates":[2.23629713058472,48.8922751268137]}}],"is_temporal":false,"author":{"url":"","metadata":"","contact_name":"SteAm","contact_address":"","source":"SteAm","contact_phone":""},"source":"","pagination":{"sort":null,"start":0,"total":1,"limit":1000000},"state":"complete","tags":"","published":"2014-08-10T19:32:44-04:00","id":14857}