{"type":"FeatureCollection","data_type":"Dataset","url_type":null,"permissions":[{"permissions":{"download":true,"view":true},"group_id":"everyone"}],"classification":null,"title":"Furniture_shop","count":2,"stream_id":149824,"contributor":{"url":"http://geocommons.com/users/29139","name":"sabyasachi"},"data_attributes":null,"calculation_params":null,"icon_link":null,"link":"http://geocommons.com/overlays/149824.json","extent":[79.1121,10.7471,79.131,10.7884],"geometry_types":["point"],"unique_name":null,"name":"Furniture_shop","feature_count":2,"description":"","next_feature":null,"is_raster":false,"short_classification":"Y","stats":{"10.75513929":{"max":10.78840249,"mean":10.767753305,"variance":0.000852777682328442,"stdev":0.0292023574789509,"min":10.74710412,"median":10.78840249},"11":{"max":11,"mean":11.0,"variance":0.0,"stdev":0.0,"min":11,"median":11},"8":{"max":4,"mean":4.0,"variance":0.0,"stdev":0.0,"min":4,"median":4},"31.6":{"max":-16.2,"mean":-25.85,"variance":186.245,"stdev":13.6471608769004,"min":-35.5,"median":-16.2},"9360444493":{"max":9894776263,"mean":9842446547.5,"variance":5.47679824862188e+15,"stdev":74005393.3752256,"min":9790116832,"median":9894776263},"79.12221536":{"max":79.13095388,"mean":79.12150648,"variance":0.000178506733520235,"stdev":0.0133606412091724,"min":79.11205908,"median":79.13095388}},"features":[{"properties":{"10.75513929":10.74710412,"11":11,"8":4,"http://sughavazhvu.appspot.com/imageviewer?blobkey=agtzdwdoyxzhemh2dxiscxikymxvyl9zdg9yzriqna4m":"http://sughavazhvu.appspot.com/imageViewer?blobKey=agtzdWdoYXZhemh2dXISCxIKYmxvYl9zdG9yZRjLuw4M","monday, august 29, 2011 12:36:31 pm utc":"Monday, August 29, 2011 12:37:33 PM UTC","31.6":-16.2,"kaverinagar,tnj":"New bus stand,tnj","furn planet":"Home choice","9360444493":9790116832,"a.m.aliakpar":"Mohamadhu ussen","id":"a63hpqth6tr9","79.12221536":79.11205908},"type":"Feature","geometry":{"type":"Point","coordinates":[79.11205908,10.74710412]}},{"properties":{"10.75513929":10.78840249,"11":11,"8":4,"http://sughavazhvu.appspot.com/imageviewer?blobkey=agtzdwdoyxzhemh2dxiscxikymxvyl9zdg9yzriqna4m":"http://sughavazhvu.appspot.com/imageViewer?blobKey=agtzdWdoYXZhemh2dXISCxIKYmxvYl9zdG9yZRjGlA4M","monday, august 29, 2011 12:36:31 pm utc":"Monday, August 29, 2011 12:39:45 PM UTC","31.6":-35.5,"kaverinagar,tnj":"West mainstreet,tnj","furn planet":"Jayamangalam","9360444493":9894776263,"a.m.aliakpar":"Vallaban","id":"a63hpr23xrsl","79.12221536":79.13095388},"type":"Feature","geometry":{"type":"Point","coordinates":[79.13095388,10.78840249]}}],"is_temporal":false,"author":{"url":"","metadata":"","contact_name":"","contact_address":"","source":"","contact_phone":""},"source":"","pagination":{"sort":null,"start":0,"total":2,"limit":1000000},"state":"complete","tags":"furniture","published":"2014-08-13T12:09:19-04:00","id":149824}