{"type":"FeatureCollection","data_type":"Dataset","url_type":null,"permissions":[{"permissions":{"download":true,"view":true},"group_id":"everyone"}],"classification":null,"title":"Untere Bachgasse 2","count":1,"stream_id":154708,"contributor":{"url":"http://geocommons.com/users/32611","name":"chiller76"},"data_attributes":null,"calculation_params":null,"icon_link":null,"link":"http://geocommons.com/overlays/154708.json","extent":[10.1574,49.7376,10.1574,49.7376],"geometry_types":["point"],"unique_name":null,"name":"Untere Bachgasse 2","feature_count":1,"description":"Unsere Basis","next_feature":null,"is_raster":false,"short_classification":"Y","stats":{},"features":[{"properties":{"name":"Untere Bachgasse 2","description":"97318 Kitzingen","id":"0"},"type":"Feature","geometry":{"type":"Point","coordinates":[10.15743,49.737629]}}],"is_temporal":false,"author":{"url":"","metadata":"","contact_name":"","contact_address":"","source":"","contact_phone":""},"source":"","pagination":{"sort":null,"start":0,"total":1,"limit":1000000},"state":"complete","tags":"#snake","published":"2014-08-13T03:27:27-04:00","id":154708}