{"type":"FeatureCollection","data_type":"Dataset","url_type":null,"permissions":[{"permissions":{"download":true,"edit":true,"view":true},"group_id":30838},{"permissions":{"download":true,"view":true},"group_id":"everyone"}],"classification":null,"title":"sg ahp2009","count":1,"stream_id":158138,"contributor":{"url":"http://geocommons.com/users/30728","name":"jeejay70"},"data_attributes":null,"calculation_params":null,"icon_link":null,"link":"http://geocommons.com/overlays/158138.json","extent":[103.726,1.44528,103.726,1.44528],"geometry_types":["point"],"unique_name":null,"name":"sg ahp2009","feature_count":1,"description":"","next_feature":null,"is_raster":false,"short_classification":"Y","stats":{"STATUS_YR":{"max":2003,"min":2003,"median":2003},"DOC_AREA_H":{"max":131.0,"min":131.0,"median":131.0}},"features":[{"properties":{"NOTES":"Sungei Buloh Wetland Reserve became Singapore's first ASEAN Heritage Park.","ISO3":"SGP","COUNTRY":"Singapore","STATUS_YR":2003,"DOC_AREA_H":131.0,"id":"0","SOURCE":"Latest Info: Sungei Buloh Wetland Reserve Website \"An Asean Experience: Conference on ASEAN Heritage Parks at Khao Yai NP, Thailand, 20 - 24 Sept. 2004\" &amp; ASEAN Heritage Park list (see doc link), accessed 29/07/2005.","PAGE_URL":"<a href=\"http://bim.aseanbiodiversity.org/biss/initiatives/pa/ahp/ahpteaser.php?ahp=19\">View Profile</a>","NAME_ENG":"Sungei Buloh Wetland Reserve"},"type":"Feature","geometry":{"type":"Point","coordinates":[103.72615,1.44528]}}],"is_temporal":false,"author":{"url":"","metadata":"","contact_name":"","contact_address":"","source":"","contact_phone":""},"source":"","pagination":{"sort":null,"start":0,"total":1,"limit":1000000},"state":"complete","tags":"","published":"2014-08-13T08:45:59-04:00","id":158138}