{"type":"FeatureCollection","data_type":"Dataset","url_type":null,"permissions":[{"permissions":{"download":true,"edit":true,"view":true},"group_id":30838},{"permissions":{"download":true,"view":true},"group_id":"everyone"}],"classification":null,"title":"ph ahp2009","count":3,"stream_id":158132,"contributor":{"url":"http://geocommons.com/users/30728","name":"jeejay70"},"data_attributes":null,"calculation_params":null,"icon_link":null,"link":"http://geocommons.com/overlays/158132.json","extent":[121.134,6.94329,125.296,12.7585],"geometry_types":["point"],"unique_name":null,"name":"ph ahp2009","feature_count":3,"description":"","next_feature":null,"is_raster":false,"short_classification":"Y","stats":{"NOTES":{"max":"2009/12/01 00:00:00 -0500","mean":"1993/03/12 16:00:00 -0500","variance":2.0882957110272e+17,"stdev":456978742.506388,"min":"1984/11/01 00:00:00 -0500","median":"1984/11/01 00:00:00 -0500"},"STATUS_YR":{"max":2009,"mean":2005.66666666667,"variance":8.33333333333333,"stdev":2.88675134594813,"min":2004,"median":2004},"DOC_AREA_H":{"max":75445.0,"mean":59400.0,"variance":623042479.0,"stdev":24960.8188767917,"min":30642.0,"median":72113.0},"SOURCE":{"max":"2009/12/01 00:00:00 -0500","mean":"1993/03/31 08:00:00 -0500","variance":2.0755497397248e+17,"stdev":455582016.735165,"min":"1984/11/29 00:00:00 -0500","median":"1984/11/29 00:00:00 -0500"}},"features":[{"properties":{"NOTES":{"end_time":"1984/11/02 00:00:00 -0500","original":"Declared by Member States of the South East Asian Nations (ASEAN) in November 1984.","granularity":"day","time":"1984/11/01 00:00:00 -0500"},"ISO3":"PHL","COUNTRY":"Philippines","STATUS_YR":2004,"DOC_AREA_H":72113.0,"id":"0","SOURCE":{"end_time":"1984/11/30 00:00:00 -0500","original":"Latest Info: ASEAN Declaration on Heritage Parks and Reserves, Bangkok, 29th November 1984 & ASEAN Heritage Park list (see doc link), accessed 29/07/2005","granularity":"day","time":"1984/11/29 00:00:00 -0500"},"PAGE_URL":"<a href=\"http://bim.aseanbiodiversity.org/biss/initiatives/pa/ahp/ahpteaser.php?ahp=17\">View Profile</a>","NAME_ENG":"Mount Apo Natural Park"},"type":"Feature","geometry":{"type":"Point","coordinates":[125.29569,6.94329]}},{"properties":{"NOTES":{"end_time":"1984/11/02 00:00:00 -0500","original":"Declared by Member States of the South East Asian Nations (ASEAN) in November 1984.","granularity":"day","time":"1984/11/01 00:00:00 -0500"},"ISO3":"PHL","COUNTRY":"Philippines","STATUS_YR":2004,"DOC_AREA_H":75445.0,"id":"1","SOURCE":{"end_time":"1984/11/30 00:00:00 -0500","original":"Latest Info: ASEAN Declaration on Heritage Parks and Reserves, Bangkok, 29th November 1984 & ASEAN Heritage Park list (see doc link), accessed 29/07/2005","granularity":"day","time":"1984/11/29 00:00:00 -0500"},"PAGE_URL":"<a href=\"http://bim.aseanbiodiversity.org/biss/initiatives/pa/ahp/ahpteaser.php?ahp=18\">View Profile</a>","NAME_ENG":"Mounts Iglit-Baco National Park"},"type":"Feature","geometry":{"type":"Point","coordinates":[121.13357,12.75848]}},{"properties":{"NOTES":{"end_time":"2009/12/02 00:00:00 -0500","original":"Declared by Member States of the South East Asian Nations (ASEAN) in December 2009.","granularity":"day","time":"2009/12/01 00:00:00 -0500"},"ISO3":"PHL","COUNTRY":"Philippines","STATUS_YR":2009,"DOC_AREA_H":30642.0,"id":"2","SOURCE":{"end_time":"2009/12/02 00:00:00 -0500","original":"Latest Info: 11th annual meeting of ASEAN ministers of environment, held in Singapore, December 2009","granularity":"day","time":"2009/12/01 00:00:00 -0500"},"PAGE_URL":"<a href=\"http://bim.aseanbiodiversity.org/biss/initiatives/pa/ahp/ahpteaser.php?ahp=28\">View Profile</a>","NAME_ENG":"Mount Kitanglad Range"},"type":"Feature","geometry":{"type":"Point","coordinates":[124.87371,8.14005]}}],"is_temporal":true,"author":{"url":"","metadata":"","contact_name":"","contact_address":"","source":"","contact_phone":""},"source":"","pagination":{"sort":null,"start":0,"total":3,"limit":1000000},"state":"complete","tags":"","published":"2014-08-13T08:45:31-04:00","id":158132}