{"type":"FeatureCollection","data_type":"Dataset","url_type":null,"permissions":[{"permissions":{"download":true,"edit":true,"view":true},"group_id":30838},{"permissions":{"download":true,"view":true},"group_id":"everyone"}],"classification":null,"title":"my ahp2009","count":3,"stream_id":158126,"contributor":{"url":"http://geocommons.com/users/30728","name":"jeejay70"},"data_attributes":null,"calculation_params":null,"icon_link":null,"link":"http://geocommons.com/overlays/158126.json","extent":[102.485,4.10223,116.613,6.24736],"geometry_types":["point"],"unique_name":null,"name":"my ahp2009","feature_count":3,"description":"","next_feature":null,"is_raster":false,"short_classification":"Y","stats":{"NOTES":{"max":"1984/11/01 00:00:00 -0500","mean":"1984/11/01 00:00:00 -0500","variance":0.0,"stdev":0.0,"min":"1984/11/01 00:00:00 -0500","median":"1984/11/01 00:00:00 -0500"},"STATUS_YR":{"max":2004,"mean":2004.0,"variance":0.0,"stdev":0.0,"min":2004,"median":2004},"DOC_AREA_H":{"max":434300.0,"mean":188233.333333333,"variance":45515643333.3333,"stdev":213343.955464722,"min":55000.0,"median":75400.0},"SOURCE":{"max":"1984/11/29 00:00:00 -0500","mean":"1984/11/29 00:00:00 -0500","variance":0.0,"stdev":0.0,"min":"1984/11/29 00:00:00 -0500","median":"1984/11/29 00:00:00 -0500"}},"features":[{"properties":{"NOTES":{"end_time":"1984/11/02 00:00:00 -0500","original":"Declared by Member States of the South East Asian Nations (ASEAN) in November 1984.","granularity":"day","time":"1984/11/01 00:00:00 -0500"},"ISO3":"MYS","COUNTRY":"Malaysia","STATUS_YR":2004,"DOC_AREA_H":75400.0,"id":"0","SOURCE":{"end_time":"1984/11/30 00:00:00 -0500","original":"Latest Info: ASEAN Declaration on Heritage Parks and Reserves, Bangkok, 29th November 1984 & ASEAN Heritage Park list (see doc link), accessed 29/07/2005","granularity":"day","time":"1984/11/29 00:00:00 -0500"},"PAGE_URL":"<a href=\"http://bim.aseanbiodiversity.org/biss/initiatives/pa/ahp/ahpteaser.php?ahp=8\">View Profile</a>","NAME_ENG":"Kinabalu National Park"},"type":"Feature","geometry":{"type":"Point","coordinates":[116.61345,6.24736]}},{"properties":{"NOTES":{"end_time":"1984/11/02 00:00:00 -0500","original":"Declared by Member States of the South East Asian Nations (ASEAN) in November 1984.","granularity":"day","time":"1984/11/01 00:00:00 -0500"},"ISO3":"MYS","COUNTRY":"Malaysia","STATUS_YR":2004,"DOC_AREA_H":55000.0,"id":"1","SOURCE":{"end_time":"1984/11/30 00:00:00 -0500","original":"Latest Info: ASEAN Declaration on Heritage Parks and Reserves, Bangkok, 29th November 1984 & ASEAN Heritage Park list (see doc link), accessed 29/07/2005","granularity":"day","time":"1984/11/29 00:00:00 -0500"},"PAGE_URL":"<a href=\"http://bim.aseanbiodiversity.org/biss/initiatives/pa/ahp/ahpteaser.php?ahp=9\">View Profile</a>","NAME_ENG":"Mulu National Park"},"type":"Feature","geometry":{"type":"Point","coordinates":[114.8861,4.10223]}},{"properties":{"NOTES":{"end_time":"1984/11/02 00:00:00 -0500","original":"Declared by Member States of the South East Asian Nations (ASEAN) in November 1984.","granularity":"day","time":"1984/11/01 00:00:00 -0500"},"ISO3":"MYS","COUNTRY":"Malaysia","STATUS_YR":2004,"DOC_AREA_H":434300.0,"id":"2","SOURCE":{"end_time":"1984/11/30 00:00:00 -0500","original":"Latest Info: ASEAN Declaration on Heritage Parks and Reserves, Bangkok, 29th November 1984 & ASEAN Heritage Park list (see doc link), accessed 29/07/2005","granularity":"day","time":"1984/11/29 00:00:00 -0500"},"PAGE_URL":"<a href=\"http://bim.aseanbiodiversity.org/biss/initiatives/pa/ahp/ahpteaser.php?ahp=10\">View Profile</a>","NAME_ENG":"Taman Negara National Park"},"type":"Feature","geometry":{"type":"Point","coordinates":[102.48522,4.60732]}}],"is_temporal":true,"author":{"url":"","metadata":"","contact_name":"","contact_address":"","source":"","contact_phone":""},"source":"","pagination":{"sort":null,"start":0,"total":3,"limit":1000000},"state":"complete","tags":"","published":"2014-08-13T08:45:02-04:00","id":158126}