{"type":"FeatureCollection","data_type":"Dataset","url_type":null,"permissions":[{"permissions":{"download":true,"view":true},"group_id":"everyone"}],"classification":null,"title":"Ukraine regs Oblast FY11","count":7,"stream_id":158709,"contributor":{"url":"http://geocommons.com/users/32689","name":"kefinger"},"data_attributes":null,"calculation_params":null,"icon_link":null,"link":"http://geocommons.com/overlays/158709.json","extent":[24.6667,44.6,34.0,50.7833],"geometry_types":["point"],"unique_name":null,"name":"Ukraine regs Oblast FY11","feature_count":7,"description":"","next_feature":null,"is_raster":false,"short_classification":"Y","stats":{"oblast level regulations":{"max":1,"mean":1.0,"variance":0.0,"stdev":0.0,"min":1,"median":1}},"features":[{"properties":{"oblast level regulations":1,"city":"Crimea","geo_score":0.905,"country":"Ukraine","id":"a629ssmkv8oz","geo_precision":"zip"},"type":"Feature","geometry":{"type":"Point","coordinates":[34.0,45.0]}},{"properties":{"oblast level regulations":1,"city":"Ivano-Frankivsk","geo_score":1.0,"country":"Ukraine","id":"a629ssujmid3","geo_precision":"zip"},"type":"Feature","geometry":{"type":"Point","coordinates":[24.7072222,48.9172222]}},{"properties":{"oblast level regulations":1,"city":"Izmayil","geo_score":1.0,"country":"Ukraine","id":"a629ssr6hg47","geo_precision":"zip"},"type":"Feature","geometry":{"type":"Point","coordinates":[28.8333333,45.35]}},{"properties":{"oblast level regulations":1,"city":"Kirovohrad","geo_score":0.932,"country":"Ukraine","id":"a629ssrcunk1","geo_precision":"zip"},"type":"Feature","geometry":{"type":"Point","coordinates":[32.0,48.5]}},{"properties":{"oblast level regulations":1,"city":"Sevastopol","geo_score":1.0,"country":"Ukraine","id":"a629ssgn2m3c","geo_precision":"zip"},"type":"Feature","geometry":{"type":"Point","coordinates":[33.5333333,44.6]}},{"properties":{"oblast level regulations":1,"city":"Shyroka Balka","geo_score":0.929,"country":"Ukraine","id":"a629ssuwan9y","geo_precision":"zip"},"type":"Feature","geometry":{"type":"Point","coordinates":[33.2666667,47.6833333]}},{"properties":{"oblast level regulations":1,"city":"Vinnytsa","geo_score":0.946,"country":"Ukraine","id":"a629ssroszbb","geo_precision":"zip"},"type":"Feature","geometry":{"type":"Point","coordinates":[24.6666667,50.7833333]}}],"is_temporal":false,"author":{"url":"","metadata":"","contact_name":"","contact_address":"","source":"","contact_phone":""},"source":"","pagination":{"sort":null,"start":0,"total":7,"limit":1000000},"state":"complete","tags":"","published":"2014-08-13T09:47:26-04:00","id":158709}