{"type":"FeatureCollection","data_type":"Dataset","url_type":null,"permissions":[{"permissions":{"download":true,"view":true},"group_id":"everyone"}],"classification":null,"title":"AtlantaData","count":4,"stream_id":16413,"contributor":{"url":"http://geocommons.com/users/8657","name":"nav_bat@yahoo.com"},"data_attributes":null,"calculation_params":null,"icon_link":null,"link":"http://geocommons.com/overlays/16413.json","extent":[-84.3892,33.7769,-84.38,33.7844],"geometry_types":["point"],"unique_name":null,"name":"AtlantaData","feature_count":4,"description":"","next_feature":null,"is_raster":false,"short_classification":"Y","stats":{"braves":{"max":25.0,"mean":14.5,"variance":63.0,"stdev":7.93725393319377,"min":6.0,"median":15.0},"geo_score":{"max":1.0,"mean":0.92725,"variance":0.00745691666666666,"stdev":0.0863534403869739,"min":0.806,"median":0.976},"giants":{"max":33.0,"mean":19.25,"variance":111.583333333333,"stdev":10.5633012516605,"min":10.0,"median":22.0}},"features":[{"properties":{"city":"Atlanta","location name":"Blake's","braves":25.0,"zip":"30309","geo_score":0.927,"giants":10.0,"phone":"(404) 892-5786","id":"a62kd3chn3pt","geo_precision":"range","address":"227 10th St NE","location type":"Restaurant","website url":"www.blakesontheparkatlanta.com?","state":"GA"},"type":"Feature","geometry":{"type":"Point","coordinates":[-84.380011,33.781785]}},{"properties":{"city":"Atlanta","location name":"Halo","braves":15.0,"zip":"30308","geo_score":0.976,"giants":12.0,"phone":"(404) 962-7333","id":"a62kd3d418j2","geo_precision":"range","address":"817 W Peachtree St","location type":"Restaurant","website url":"www.halolounge.com","state":"GA"},"type":"Feature","geometry":{"type":"Point","coordinates":[-84.384455,33.776945]}},{"properties":{"city":"Atlanta","location name":"Laughing Skull Lounge","braves":12.0,"zip":"30309","geo_score":1.0,"giants":22.0,"phone":"(877) 523-3288","id":"a62kd3ayl2ho","geo_precision":"range","address":"878 Peachtree Street","location type":"Bar","website url":"www.vortexcomedy.com","state":"GA"},"type":"Feature","geometry":{"type":"Point","coordinates":[-84.384293,33.778695]}},{"properties":{"city":"Atlanta","location name":"Primal Atlanta","braves":6.0,"zip":"30309","geo_score":0.806,"giants":33.0,"phone":"(404) 745-9494","id":"a62kd3fqpx86","geo_precision":"street","address":"960 Spring St NW","location type":"Bar","website url":"www.primalatlanta.com","state":"GA"},"type":"Feature","geometry":{"type":"Point","coordinates":[-84.389206,33.784441]}}],"is_temporal":false,"author":{"url":"","metadata":"","contact_name":"","contact_address":"","source":"","contact_phone":""},"source":"","pagination":{"sort":null,"start":0,"total":4,"limit":1000000},"state":"complete","tags":"","published":"2014-08-10T21:43:40-04:00","id":16413}