{"type":"FeatureCollection","data_type":"Dataset","url_type":null,"permissions":[{"permissions":{"download":true,"view":true},"group_id":"everyone"}],"classification":null,"title":"europeBaghdad","count":1,"stream_id":164831,"contributor":{"url":"http://geocommons.com/users/34079","name":"pharma"},"data_attributes":null,"calculation_params":null,"icon_link":null,"link":"http://geocommons.com/overlays/164831.json","extent":[7.41667,46.95,7.41667,46.95],"geometry_types":["point"],"unique_name":null,"name":"europeBaghdad","feature_count":1,"description":"","next_feature":null,"is_raster":false,"short_classification":"Y","stats":{"link":{"max":1,"min":1,"median":1}},"features":[{"properties":{"title":"Europe","description":"Paracelsus puts mercury – which is now known to be poisonous in certain amounts – in his cures.","link":1,"id":"a6b1qsiw9ind"},"type":"Feature","geometry":{"type":"Point","coordinates":[7.416667,46.95]}}],"is_temporal":false,"author":{"url":"","metadata":null,"contact_name":null,"contact_address":null,"source":null,"contact_phone":null},"source":"","pagination":{"sort":null,"start":0,"total":1,"limit":1000000},"state":"complete","tags":"","published":"2014-08-13T04:08:29-04:00","id":164831}