{"type":"FeatureCollection","data_type":"Dataset","url_type":null,"permissions":[{"permissions":{"download":true,"view":true},"group_id":"everyone"}],"classification":null,"title":"P121054_update","count":4,"stream_id":165215,"contributor":{"url":"http://geocommons.com/users/27513","name":"zeus"},"data_attributes":null,"calculation_params":null,"icon_link":null,"link":"http://geocommons.com/overlays/165215.json","extent":[100.489,13.8419,100.616,14.0754],"geometry_types":["point"],"unique_name":null,"name":"P121054_update","feature_count":4,"description":"","next_feature":null,"is_raster":false,"short_classification":"Y","stats":{},"features":[{"properties":{"name":"ประกาศด่วน : องค์การนักศึกษามหาวิทยาลัยธรรมศาสตร์แจ้งว่าขอให้ผู้ที่นำรถเข้ามาจอดในมธ.รังสิต นำรถออกจากมหาวิทยาลัยโดยด่วนเนื่องจากเป็นสถานที่ลุ่มน้ำ อาจเกิดน้ำท่วมได้","id":"0"},"type":"Feature","geometry":{"type":"Point","coordinates":[100.616416207138,14.0754204150616]}},{"properties":{"name":"ประกาศ: ประตูน้ำจุฬาลงกรณ์ ตลาดรังสิต ขอกำลังขนกระสอบทราย 1000 คน ด่วนที่สุด ติดต่อคุณแบต 085-0585439","id":"1"},"type":"Feature","geometry":{"type":"Point","coordinates":[100.6154332909,13.9860128841618]}},{"properties":{"name":"มีรายงานว่า ท่าน้ำนนท์ใกล้วิกฤต ระดับน้ำเจ้าพระยาสูง","id":"2"},"type":"Feature","geometry":{"type":"Point","coordinates":[100.488580112762,13.8418893786622]}},{"properties":{"name":"รายงานว่า ที่หมู่บ้านชุมชนกฤษณา ต.สามโคก อ.สามโคก จ.ปทุมธานี ชาวบ้านรวมตัวกันพังเเนวกั้นน้ำที่หน่วยทหารนำมาวางทำกำแพงกั้นน้ำที่กำลังท่วมสูงขึ้น","id":"3"},"type":"Feature","geometry":{"type":"Point","coordinates":[100.525461852092,14.0413515370566]}}],"is_temporal":false,"author":{"url":"","metadata":null,"contact_name":null,"contact_address":null,"source":null,"contact_phone":null},"source":"","pagination":{"sort":null,"start":0,"total":4,"limit":1000000},"state":"complete","tags":"","published":"2014-08-13T04:35:36-04:00","id":165215}