{"type":"FeatureCollection","data_type":"Dataset","url_type":null,"permissions":[{"permissions":{"download":true,"view":true},"group_id":"everyone"}],"classification":null,"title":"Dump_GeoCommons_trial_1","count":7,"stream_id":165328,"contributor":{"url":"http://geocommons.com/users/34254","name":"rmeijerink"},"data_attributes":null,"calculation_params":null,"icon_link":null,"link":"http://geocommons.com/overlays/165328.json","extent":[-71.2537,41.6326,-71.2537,41.6326],"geometry_types":["point"],"unique_name":null,"name":"Dump_GeoCommons_trial_1","feature_count":7,"description":"","next_feature":null,"is_raster":false,"short_classification":"Y","stats":{"jaar":{"max":2011,"mean":2011.0,"variance":0.0,"stdev":0.0,"min":2011,"median":2011}},"features":[{"properties":{"persoon - geslacht":"M","huis adres - straatnaam":"Van der Goesstraat","persoon - nationaliteit":"Nederland","huis adres - land":"Nederland","geo_score":0.0,"huis adres - postcode":"3521TL","jaar":2011,"id":"a64r2op34v08","geo_precision":"unmatched","huis adres - woonplaats":"UTRECHT"},"type":"Feature","geometry":null},{"properties":{"persoon - geslacht":"M","huis adres - straatnaam":"Willem van Abcoudelaan","persoon - nationaliteit":"Nederland","huis adres - land":"Nederland","geo_score":0.0,"huis adres - postcode":"1391CC","jaar":2011,"id":"a64r2oujfq97","geo_precision":"unmatched","huis adres - woonplaats":"ABCOUDE"},"type":"Feature","geometry":null},{"properties":{"persoon - geslacht":"V","huis adres - straatnaam":"'s Gravelandseweg","persoon - nationaliteit":"Frankrijk","huis adres - land":"Nederland","geo_score":0.0,"huis adres - postcode":"1217EW","jaar":2011,"id":"a64r2olsaqyp","geo_precision":"unmatched","huis adres - woonplaats":"HILVERSUM"},"type":"Feature","geometry":null},{"properties":{"persoon - geslacht":"M","huis adres - straatnaam":"'s Gravelandseweg","persoon - nationaliteit":"Nederland","huis adres - land":"Nederland","geo_score":0.0,"huis adres - postcode":"1217EW","jaar":2011,"id":"a64r2ou6wgwh","geo_precision":"unmatched","huis adres - woonplaats":"HILVERSUM"},"type":"Feature","geometry":null},{"properties":{"persoon - geslacht":"M","huis adres - straatnaam":"'s Gravelandseweg","persoon - nationaliteit":"Nederland","huis adres - land":"Nederland","geo_score":0.0,"huis adres - postcode":"1217GA","jaar":2011,"id":"a64r2ool1riq","geo_precision":"unmatched","huis adres - woonplaats":"HILVERSUM"},"type":"Feature","geometry":null},{"properties":{"persoon - geslacht":"V","huis adres - straatnaam":"'s Gravenbroeksestraat","persoon - nationaliteit":"Nederland","huis adres - land":"Nederland","geo_score":0.714,"huis adres - postcode":"2811GD","jaar":2011,"id":"a64r2ora5rgu","geo_precision":"zip","huis adres - woonplaats":"REEUWIJK"},"type":"Feature","geometry":{"type":"Point","coordinates":[-71.253659,41.632602]}},{"properties":{"persoon - geslacht":"M","huis adres - straatnaam":"'s Gravenbroekseweg","persoon - nationaliteit":"Nederland","huis adres - land":"Nederland","geo_score":0.714,"huis adres - postcode":"2811 GE","jaar":2011,"id":"a64r2oljm5e4","geo_precision":"zip","huis adres - woonplaats":"REEUWIJK"},"type":"Feature","geometry":{"type":"Point","coordinates":[-71.253659,41.632602]}}],"is_temporal":false,"author":{"url":"","metadata":"","contact_name":"","contact_address":"","source":"","contact_phone":""},"source":"","pagination":{"sort":null,"start":0,"total":7,"limit":1000000},"state":"complete","tags":"","published":"2014-08-13T04:49:33-04:00","id":165328}