{"type":"FeatureCollection","data_type":"Dataset","url_type":null,"permissions":[{"permissions":{"download":true,"view":true},"group_id":"everyone"}],"classification":null,"title":"Askania_Nova","count":1,"stream_id":167533,"contributor":{"url":"http://geocommons.com/users/33921","name":"stelamarina"},"data_attributes":null,"calculation_params":null,"icon_link":null,"link":"http://geocommons.com/overlays/167533.json","extent":[33.9044,46.453,33.9044,46.453],"geometry_types":["point"],"unique_name":null,"name":"Askania_Nova","feature_count":1,"description":"","next_feature":null,"is_raster":false,"short_classification":"Y","stats":{},"features":[{"properties":{"name":"Askania Nova","id":"0"},"type":"Feature","geometry":{"type":"Point","coordinates":[33.9044111510105,46.4529824493089]}}],"is_temporal":false,"author":{"url":"","metadata":null,"contact_name":null,"contact_address":null,"source":null,"contact_phone":null},"source":"","pagination":{"sort":null,"start":0,"total":1,"limit":1000000},"state":"complete","tags":"","published":"2014-08-13T08:00:43-04:00","id":167533}