{"type":"FeatureCollection","data_type":"Dataset","url_type":null,"permissions":[{"permissions":{"download":true,"view":true},"group_id":"everyone"}],"classification":null,"title":"Tour Start End Pics","count":18,"stream_id":168230,"contributor":{"url":"http://geocommons.com/users/34666","name":"rorystierler"},"data_attributes":null,"calculation_params":null,"icon_link":null,"link":"http://geocommons.com/overlays/168230.json","extent":[-93.1984,44.8977,-93.1958,44.9024],"geometry_types":["point"],"unique_name":null,"name":"Tour Start End Pics","feature_count":18,"description":"","next_feature":null,"is_raster":false,"short_classification":"Y","stats":{"OBJECTID":{"max":18,"mean":9.5,"variance":28.5,"stdev":5.33853912601566,"min":1,"median":10}},"features":[{"properties":{"Name":"Start","OBJECTID":1,"id":"0"},"type":"Feature","geometry":{"type":"Point","coordinates":[-93.1984166098446,44.9017088472108]}},{"properties":{"Name":"Finish","OBJECTID":2,"id":"1"},"type":"Feature","geometry":{"type":"Point","coordinates":[-93.1982194902474,44.9017299339077]}},{"properties":{"Name":"1","OBJECTID":3,"id":"2"},"type":"Feature","geometry":{"type":"Point","coordinates":[-93.1983258836636,44.9016656453687]}},{"properties":{"Name":"2","OBJECTID":4,"id":"3"},"type":"Feature","geometry":{"type":"Point","coordinates":[-93.1977041131964,44.901051489565]}},{"properties":{"Name":"3","OBJECTID":5,"id":"4"},"type":"Feature","geometry":{"type":"Point","coordinates":[-93.197494004613,44.9007949156237]}},{"properties":{"Name":"4","OBJECTID":6,"id":"5"},"type":"Feature","geometry":{"type":"Point","coordinates":[-93.1972106900848,44.9001201426485]}},{"properties":{"Name":"5","OBJECTID":7,"id":"6"},"type":"Feature","geometry":{"type":"Point","coordinates":[-93.1966640270356,44.8992473698948]}},{"properties":{"Name":"6","OBJECTID":8,"id":"7"},"type":"Feature","geometry":{"type":"Point","coordinates":[-93.1961991257276,44.8991699242819]}},{"properties":{"Name":"7","OBJECTID":9,"id":"8"},"type":"Feature","geometry":{"type":"Point","coordinates":[-93.1967890212364,44.8984089522608]}},{"properties":{"Name":"8","OBJECTID":10,"id":"9"},"type":"Feature","geometry":{"type":"Point","coordinates":[-93.1966155409211,44.898019673996]}},{"properties":{"Name":"9","OBJECTID":11,"id":"10"},"type":"Feature","geometry":{"type":"Point","coordinates":[-93.1957950700044,44.8976775575654]}},{"properties":{"Name":"10","OBJECTID":12,"id":"11"},"type":"Feature","geometry":{"type":"Point","coordinates":[-93.1962523663656,44.9005066901964]}},{"properties":{"Name":"11","OBJECTID":13,"id":"12"},"type":"Feature","geometry":{"type":"Point","coordinates":[-93.1960764827048,44.9009498030124]}},{"properties":{"Name":"12","OBJECTID":14,"id":"13"},"type":"Feature","geometry":{"type":"Point","coordinates":[-93.1961706033723,44.901405034268]}},{"properties":{"Name":"13","OBJECTID":15,"id":"14"},"type":"Feature","geometry":{"type":"Point","coordinates":[-93.1964302695446,44.9016938221611]}},{"properties":{"Name":"14","OBJECTID":16,"id":"15"},"type":"Feature","geometry":{"type":"Point","coordinates":[-93.1968275509429,44.902116830155]}},{"properties":{"Name":"15","OBJECTID":17,"id":"16"},"type":"Feature","geometry":{"type":"Point","coordinates":[-93.1973371362258,44.9024050472218]}},{"properties":{"Name":"16","OBJECTID":18,"id":"17"},"type":"Feature","geometry":{"type":"Point","coordinates":[-93.1975510479477,44.9017060501319]}}],"is_temporal":false,"author":{"url":"","metadata":"","contact_name":"","contact_address":"","source":"","contact_phone":""},"source":"","pagination":{"sort":null,"start":0,"total":18,"limit":1000000},"state":"complete","tags":"","published":"2014-08-13T09:05:50-04:00","id":168230}