{"type":"FeatureCollection","data_type":"Dataset","url_type":null,"permissions":[{"permissions":{"download":true,"view":true},"group_id":"everyone"}],"classification":null,"title":"XanRainF3","count":4,"stream_id":168336,"contributor":{"url":"http://geocommons.com/users/33899","name":"lenincha"},"data_attributes":null,"calculation_params":null,"icon_link":null,"link":"http://geocommons.com/overlays/168336.json","extent":[143.1,-13.91,143.48,-13.7],"geometry_types":["point"],"unique_name":null,"name":"XanRainF3","feature_count":4,"description":"","next_feature":null,"is_raster":false,"short_classification":"Y","stats":{},"features":[{"properties":{"name":"Xanthorrhoea johnsonii","description":"NSW NSW 376986  \n  \t<img src=\"http://data.gbif.org/images/gbifSmall.gif\">\n  \t<b>Data retrieved from <a href=\"http://data.gbif.org\">GBIF Data Portal</a></b>\n  \tData Provider\n  \t\t\tData Resource  \t\t\t\n  \t\t\tInstitution Code\n  \t\t\tCollection Code\n  \t\t\tCatalogue Number\n  \t\t\tDate\n  \t\tNational Herbarium of New South Wales\n \t\t\t\tNSW herbarium collection \t\t\t\t\n \t\t\t\tNSW\n \t\t\t\tNSW\n \t\t\t\t376986\n \t\t\t\t25-07-1985\n \t\t\t<b>Portal URL</b>: <a href=\"http://data.gbif.org/occurrences/98824312\">http://data.gbif.org/occurrences/98824312</a>","id":"0"},"type":"Feature","geometry":{"type":"Point","coordinates":[143.1,-13.7]}},{"properties":{"name":"Xanthorrhoea pumilio","description":"NSW NSW 376936  \n  \t<img src=\"http://data.gbif.org/images/gbifSmall.gif\">\n  \t<b>Data retrieved from <a href=\"http://data.gbif.org\">GBIF Data Portal</a></b>\n  \tData Provider\n  \t\t\tData Resource  \t\t\t\n  \t\t\tInstitution Code\n  \t\t\tCollection Code\n  \t\t\tCatalogue Number\n  \t\t\tDate\n  \t\tNational Herbarium of New South Wales\n \t\t\t\tNSW herbarium collection \t\t\t\t\n \t\t\t\tNSW\n \t\t\t\tNSW\n \t\t\t\t376936\n \t\t\t\t25-07-1985\n \t\t\t<b>Portal URL</b>: <a href=\"http://data.gbif.org/occurrences/98826394\">http://data.gbif.org/occurrences/98826394</a>","id":"1"},"type":"Feature","geometry":{"type":"Point","coordinates":[143.1,-13.7]}},{"properties":{"name":"Xanthorrhoea johnsonii","description":"CBG 524269 47286  \n  \t<img src=\"http://data.gbif.org/images/gbifSmall.gif\">\n  \t<b>Data retrieved from <a href=\"http://data.gbif.org\">GBIF Data Portal</a></b>\n  \tData Provider\n  \t\t\tData Resource  \t\t\t\n  \t\t\tInstitution Code\n  \t\t\tCollection Code\n  \t\t\tCatalogue Number\n  \t\t\tDate\n  \t\tAustralian National Herbarium (CANB)\n \t\t\t\tAustralian National Herbarium (CANB) \t\t\t\t\n \t\t\t\tCBG\n \t\t\t\t524269\n \t\t\t\t47286\n \t\t\t\t24-06-1972\n \t\t\t<b>Portal URL</b>: <a href=\"http://data.gbif.org/occurrences/117554283\">http://data.gbif.org/occurrences/117554283</a>","id":"2"},"type":"Feature","geometry":{"type":"Point","coordinates":[143.25,-13.91]}},{"properties":{"name":"Xanthorrhoea johnsonii","description":"CBG 524276 7806197  \n  \t<img src=\"http://data.gbif.org/images/gbifSmall.gif\">\n  \t<b>Data retrieved from <a href=\"http://data.gbif.org\">GBIF Data Portal</a></b>\n  \tData Provider\n  \t\t\tData Resource  \t\t\t\n  \t\t\tInstitution Code\n  \t\t\tCollection Code\n  \t\t\tCatalogue Number\n  \t\t\tDate\n  \t\tAustralian National Herbarium (CANB)\n \t\t\t\tAustralian National Herbarium (CANB) \t\t\t\t\n \t\t\t\tCBG\n \t\t\t\t524276\n \t\t\t\t7806197\n \t\t\t\t22-07-1978\n \t\t\t<b>Portal URL</b>: <a href=\"http://data.gbif.org/occurrences/117554815\">http://data.gbif.org/occurrences/117554815</a>","id":"3"},"type":"Feature","geometry":{"type":"Point","coordinates":[143.48,-13.75]}}],"is_temporal":false,"author":{"url":"","metadata":null,"contact_name":null,"contact_address":null,"source":null,"contact_phone":null},"source":"","pagination":{"sort":null,"start":0,"total":4,"limit":1000000},"state":"complete","tags":"","published":"2014-08-13T09:12:26-04:00","id":168336}