{"type":"FeatureCollection","data_type":"Dataset","url_type":null,"permissions":[{"permissions":{"download":true,"view":true},"group_id":"everyone"}],"classification":null,"title":"DC_data","count":3,"stream_id":169221,"contributor":{"url":"http://geocommons.com/users/34859","name":"mihoinagaki"},"data_attributes":null,"calculation_params":null,"icon_link":null,"link":"http://geocommons.com/overlays/169221.json","extent":[-77.0435,38.8987,-77.0091,38.9002],"geometry_types":["point"],"unique_name":null,"name":"DC_data","feature_count":3,"description":"","next_feature":null,"is_raster":false,"short_classification":"Y","stats":{},"features":[{"properties":{"city":"Washington","name":"World Bank","column_5":null,"geo_score":0.457,"street address":"1818 H Street, NW","id":"a68ihr7msoys","geo_precision":"street","state":"DC"},"type":"Feature","geometry":{"type":"Point","coordinates":[-77.009063,38.900208]}},{"properties":{"city":"Washington","name":"White House","column_5":null,"geo_score":0.805,"street address":"1600 Pennsylvania Avenue NW","id":"a68ihrjwk84t","geo_precision":"range","state":"DC"},"type":"Feature","geometry":{"type":"Point","coordinates":[-77.037528,38.898746]}},{"properties":{"city":"Washington","name":"IMF","column_5":null,"geo_score":0.805,"street address":"1900 Pennsylvania Ave NW","id":"a68ihr9ai2i6","geo_precision":"range","state":"DC"},"type":"Feature","geometry":{"type":"Point","coordinates":[-77.043461,38.900202]}}],"is_temporal":false,"author":{"url":"","metadata":null,"contact_name":null,"contact_address":null,"source":null,"contact_phone":null},"source":"","pagination":{"sort":null,"start":0,"total":3,"limit":1000000},"state":"complete","tags":"","published":"2014-08-13T10:31:18-04:00","id":169221}