{"type":"FeatureCollection","data_type":"Dataset Analysis","url_type":null,"permissions":[{"permissions":{"download":true,"view":true},"group_id":"everyone"}],"classification":null,"title":"Clipped 'Target Store Locations' using 'New York'","count":3,"stream_id":169872,"contributor":{"url":"http://geocommons.com/users/185","name":"emily"},"data_attributes":null,"calculation_params":{"input":{"columns":[{"id":"169610"},{"id":"168581"}]},"calculation":"clip"},"icon_link":null,"link":"http://geocommons.com/overlays/169872.json","extent":[-77.6156,40.6501,-73.9496,43.1548],"geometry_types":["point"],"unique_name":"","name":"Clipped 'Target Store Locations' using 'New York'","feature_count":3,"description":"Dataset created by clipping 1) Target Store Locations  with 2) New York as the clipping dataset","next_feature":null,"is_raster":false,"short_classification":"Y","stats":{"date":{"max":"1992/03/11 00:00:00 -0500","mean":"1989/06/07 00:20:00 -0400","variance":7.91439538608e+15,"stdev":88962887.6896428,"min":"1986/07/23 00:00:00 -0400","median":"1989/07/19 00:00:00 -0400"},"geo_score":{"max":0.857,"mean":0.857,"variance":1.84889274661175e-32,"stdev":1.35973995551052e-16,"min":0.857,"median":0.857},"store":{"max":693,"mean":428.0,"variance":55749.0,"stdev":236.112261435106,"min":240,"median":351},"year_open":{"max":1992,"mean":1989.0,"variance":9.0,"stdev":3.0,"min":1986,"median":1989}},"features":[{"properties":{"city":"Brooklyn","date":{"end_time":"1986/07/24 00:00:00 -0400","original":"7/23/1986","granularity":"day","time":"1986/07/23 00:00:00 -0400"},"geo_score":0.857,"store":240,"year_open":1986,"id":"96","geo_precision":"zip","state":"Center"},"type":"Feature","geometry":{"type":"Point","coordinates":[-73.9495823,40.6501038]}},{"properties":{"city":"Rochester","date":{"end_time":"1989/07/20 00:00:00 -0400","original":"7/19/1989","granularity":"day","time":"1989/07/19 00:00:00 -0400"},"geo_score":0.857,"store":351,"year_open":1989,"id":"180","geo_precision":"zip","state":"Hills"},"type":"Feature","geometry":{"type":"Point","coordinates":[-77.6155568,43.1547845]}},{"properties":{"city":"Brooklyn","date":{"end_time":"1992/03/12 00:00:00 -0500","original":"3/11/1992","granularity":"day","time":"1992/03/11 00:00:00 -0500"},"geo_score":0.857,"store":693,"year_open":1992,"id":"283","geo_precision":"zip","state":"Park"},"type":"Feature","geometry":{"type":"Point","coordinates":[-73.9495823,40.6501038]}}],"is_temporal":true,"author":{"url":"","metadata":"","contact_name":"","contact_address":"","source":"","contact_phone":""},"source":"","pagination":{"sort":null,"start":0,"total":3,"limit":1000000},"state":"complete","tags":"","published":"2014-08-13T11:23:53-04:00","id":169872}