{"type":"FeatureCollection","data_type":"Dataset","url_type":null,"permissions":[{"permissions":{"download":true,"view":true},"group_id":"everyone"}],"classification":null,"title":"Dumboyee","count":12,"stream_id":185681,"contributor":{"url":"http://geocommons.com/users/37128","name":"james11son"},"data_attributes":null,"calculation_params":null,"icon_link":null,"link":"http://geocommons.com/overlays/185681.json","extent":[-10.77,8.4692,-10.768,8.47334],"geometry_types":["point"],"unique_name":null,"name":"Dumboyee","feature_count":12,"description":"","next_feature":null,"is_raster":false,"short_classification":"Y","stats":{},"features":[{"properties":{"name":"N 08° 28'9.13\"     W 10° 46' 8.61\"","description":null,"id":"0"},"type":"Feature","geometry":{"type":"Point","coordinates":[-10.769058,8.469203]}},{"properties":{"name":"N 08° 28'10.29\"     W 10° 46' 5.87\"","description":"","id":"1"},"type":"Feature","geometry":{"type":"Point","coordinates":[-10.768297,8.469525]}},{"properties":{"name":"N 08° 28'11.21\"     W 10° 46' 10.97\"","description":"","id":"2"},"type":"Feature","geometry":{"type":"Point","coordinates":[-10.769714,8.469781]}},{"properties":{"name":"N 08° 28'14.09\"    W 10°46' 11.36\"","description":"","id":"3"},"type":"Feature","geometry":{"type":"Point","coordinates":[-10.769822,8.470581]}},{"properties":{"name":"N 08°28'13.09\"     W 010°46' 4.86\"","description":"","id":"4"},"type":"Feature","geometry":{"type":"Point","coordinates":[-10.768017,8.470303]}},{"properties":{"name":"N 08° 28'17.72\"     W 10° 46' 5.03\"","description":"","id":"5"},"type":"Feature","geometry":{"type":"Point","coordinates":[-10.768064,8.471589]}},{"properties":{"name":"N 08° 28' 17.08\"     W 10° 46' 11.71\"","description":"","id":"6"},"type":"Feature","geometry":{"type":"Point","coordinates":[-10.769919,8.471411]}},{"properties":{"name":"N 08° 28' 19.84\"     W 10° 46' 11.88\"","description":"","id":"7"},"type":"Feature","geometry":{"type":"Point","coordinates":[-10.769967,8.472178]}},{"properties":{"name":"N 08° 28'22.46\"     W 10° 46' 11.89\"","description":"","id":"8"},"type":"Feature","geometry":{"type":"Point","coordinates":[-10.769969,8.472906]}},{"properties":{"name":"N 08° 28' 24.01\"     W 10° 46' 9.21\"","description":"","id":"9"},"type":"Feature","geometry":{"type":"Point","coordinates":[-10.769225,8.473336]}},{"properties":{"name":"N 08° 28' 20.36\"     W 10° 46' 6.18\"","description":"","id":"10"},"type":"Feature","geometry":{"type":"Point","coordinates":[-10.768383,8.472322]}},{"properties":{"name":"N 08° 28'23.31\"     W 10° 46' 7.45\"","description":"","id":"11"},"type":"Feature","geometry":{"type":"Point","coordinates":[-10.768736,8.473142]}}],"is_temporal":false,"author":{"url":"","metadata":null,"contact_name":null,"contact_address":null,"source":null,"contact_phone":null},"source":"","pagination":{"sort":null,"start":0,"total":12,"limit":1000000},"state":"complete","tags":"","published":"2014-08-13T06:02:42-04:00","id":185681}