{"type":"FeatureCollection","data_type":"Dataset","url_type":null,"permissions":[{"permissions":{"download":true,"view":true},"group_id":"everyone"}],"classification":null,"title":"Jagbwema_Area","count":11,"stream_id":186088,"contributor":{"url":"http://geocommons.com/users/37128","name":"james11son"},"data_attributes":null,"calculation_params":null,"icon_link":null,"link":"http://geocommons.com/overlays/186088.json","extent":[-10.8541,8.5827,-10.6574,8.663],"geometry_types":["point"],"unique_name":null,"name":"Jagbwema_Area","feature_count":11,"description":"","next_feature":null,"is_raster":false,"short_classification":"Y","stats":{},"features":[{"properties":{"name":"8.6630°N, 10.8541°W","description":"","id":"0"},"type":"Feature","geometry":{"type":"Point","coordinates":[-10.8541,8.663]}},{"properties":{"name":"8.6627°N, 10.7450°W","description":"","id":"1"},"type":"Feature","geometry":{"type":"Point","coordinates":[-10.745,8.6627]}},{"properties":{"name":"8.6084°N, 10.7447°W","description":"","id":"2"},"type":"Feature","geometry":{"type":"Point","coordinates":[-10.7447,8.6084]}},{"properties":{"name":"8.6088°N, 10.6630°W","description":"","id":"3"},"type":"Feature","geometry":{"type":"Point","coordinates":[-10.663,8.6088]}},{"properties":{"name":"8.6088°N, 10.6575°W","description":"","id":"4"},"type":"Feature","geometry":{"type":"Point","coordinates":[-10.6575,8.6088]}},{"properties":{"name":"8.5827°N, 10.6574°W","description":"","id":"5"},"type":"Feature","geometry":{"type":"Point","coordinates":[-10.6574,8.5827]}},{"properties":{"name":"8.5830°N, 10.7583°W","description":"","id":"6"},"type":"Feature","geometry":{"type":"Point","coordinates":[-10.7583,8.583]}},{"properties":{"name":"8.5829°N, 10.8536°W","description":"","id":"7"},"type":"Feature","geometry":{"type":"Point","coordinates":[-10.8536,8.5829]}},{"properties":{"name":"8.6124°N, 10.8538°W","description":"","id":"8"},"type":"Feature","geometry":{"type":"Point","coordinates":[-10.8538,8.6124]}},{"properties":{"name":"8.6260°N, 10.8538°W","description":"","id":"9"},"type":"Feature","geometry":{"type":"Point","coordinates":[-10.8538,8.626]}},{"properties":{"name":"8.6280°N, 10.8539°W","description":"","id":"10"},"type":"Feature","geometry":{"type":"Point","coordinates":[-10.8539,8.628]}}],"is_temporal":false,"author":{"url":"","metadata":null,"contact_name":null,"contact_address":null,"source":null,"contact_phone":null},"source":"","pagination":{"sort":null,"start":0,"total":11,"limit":1000000},"state":"complete","tags":"","published":"2014-08-13T06:42:29-04:00","id":186088}