{"type":"FeatureCollection","data_type":"Dataset","url_type":null,"permissions":[{"permissions":{"download":true,"view":true},"group_id":"everyone"}],"classification":null,"title":"IDB0_lines","count":1,"stream_id":186737,"contributor":{"url":"http://geocommons.com/users/13829","name":"frankwmoyer"},"data_attributes":null,"calculation_params":null,"icon_link":null,"link":"http://geocommons.com/overlays/186737.json","extent":[-87.5339,37.8616,-87.5339,37.8616],"geometry_types":["point"],"unique_name":"","name":"IDB0_lines","feature_count":1,"description":"","next_feature":null,"is_raster":false,"short_classification":"Y","stats":{"latitude":{"max":37.8616015,"min":37.8616015,"median":37.8616015},"longitude":{"max":-87.533896,"min":-87.533896,"median":-87.533896}},"features":[{"properties":{"latitude":37.8616015,"lines":"SRID=-1;LINESTRING(-88.511353 41.004775,-86.556439 34.718428)","note":"Default Feature","longitude":-87.533896,"id":"a6hfs7n131up"},"type":"Feature","geometry":{"type":"Point","coordinates":[-87.533896,37.8616015]}}],"is_temporal":false,"author":{"url":"","metadata":"","contact_name":"","contact_address":"","source":"","contact_phone":""},"source":"","pagination":{"sort":null,"start":0,"total":1,"limit":1000000},"state":"complete","tags":"","published":"2014-08-13T07:31:48-04:00","id":186737}