{"type":"FeatureCollection","data_type":"Dataset","url_type":null,"permissions":[{"permissions":{"download":true,"view":true},"group_id":"everyone"}],"classification":null,"title":"Feature Labels (NUMBER)","count":14,"stream_id":187414,"contributor":{"url":"http://geocommons.com/users/695","name":"Bill"},"data_attributes":null,"calculation_params":null,"icon_link":null,"link":"http://geocommons.com/overlays/187414.json","extent":[-96.654,32.7442,-96.5547,32.8269],"geometry_types":["point"],"unique_name":"","name":"Feature Labels (NUMBER)","feature_count":14,"description":"Exported from GIS.DBO.FIRE_DEPT_STATIONS_VW on 11/3/2010","next_feature":null,"is_raster":false,"short_classification":"Y","stats":{"name":{"max":7,"mean":4.0,"variance":4.30769230769231,"stdev":2.07549808665108,"min":1,"median":4}},"features":[{"properties":{"name":1,"id":"a6m51ok2tfg5"},"type":"Feature","geometry":{"type":"Point","coordinates":[-96.5982595181671,32.763574544643]}},{"properties":{"name":2,"id":"a6m51ooou9ab"},"type":"Feature","geometry":{"type":"Point","coordinates":[-96.6433701927753,32.8269295184971]}},{"properties":{"name":3,"id":"a6m51olgiro5"},"type":"Feature","geometry":{"type":"Point","coordinates":[-96.6540277258511,32.7867074827669]}},{"properties":{"name":4,"id":"a6m51omr7xnw"},"type":"Feature","geometry":{"type":"Point","coordinates":[-96.6221898304197,32.7591675912605]}},{"properties":{"name":5,"id":"a6m51oiwfnfa"},"type":"Feature","geometry":{"type":"Point","coordinates":[-96.61238185903,32.794570448797]}},{"properties":{"name":6,"id":"a6m51ogl55dk"},"type":"Feature","geometry":{"type":"Point","coordinates":[-96.6123330045805,32.8242082270781]}},{"properties":{"name":7,"id":"a6m51oobhmhd"},"type":"Feature","geometry":{"type":"Point","coordinates":[-96.5546774671456,32.7441941300763]}},{"properties":{"name":1,"id":"a6m51oi4ulgv"},"type":"Feature","geometry":{"type":"Point","coordinates":[-96.5982595181671,32.763574544643]}},{"properties":{"name":2,"id":"a6m51ofyi5za"},"type":"Feature","geometry":{"type":"Point","coordinates":[-96.6433701927753,32.8269295184971]}},{"properties":{"name":3,"id":"a6m51ona23bf"},"type":"Feature","geometry":{"type":"Point","coordinates":[-96.6540277258511,32.7867074827669]}},{"properties":{"name":4,"id":"a6m51ollgkon"},"type":"Feature","geometry":{"type":"Point","coordinates":[-96.6221898304197,32.7591675912605]}},{"properties":{"name":5,"id":"a6m51ofvpjlf"},"type":"Feature","geometry":{"type":"Point","coordinates":[-96.61238185903,32.794570448797]}},{"properties":{"name":6,"id":"a6m51oc5ytqe"},"type":"Feature","geometry":{"type":"Point","coordinates":[-96.6123330045805,32.8242082270781]}},{"properties":{"name":7,"id":"a6m51ooyuuhn"},"type":"Feature","geometry":{"type":"Point","coordinates":[-96.5546774671456,32.7441941300763]}}],"is_temporal":false,"author":{"url":"","metadata":"","contact_name":"","contact_address":"","source":"","contact_phone":""},"source":"","pagination":{"sort":null,"start":0,"total":14,"limit":1000000},"state":"complete","tags":"","published":"2014-08-13T08:35:50-04:00","id":187414}