{"type":"FeatureCollection","data_type":"Dataset","url_type":null,"permissions":[{"permissions":{"download":true,"view":true},"group_id":"everyone"}],"classification":null,"title":"PA German F facade brick","count":17,"stream_id":190362,"contributor":{"url":"http://geocommons.com/users/25903","name":"cmacneal"},"data_attributes":null,"calculation_params":null,"icon_link":null,"link":"http://geocommons.com/overlays/190362.json","extent":[-77.1524,40.8799,-76.9006,41.0131],"geometry_types":["point"],"unique_name":null,"name":"PA German F facade brick","feature_count":17,"description":"","next_feature":null,"is_raster":false,"short_classification":"Y","stats":{"lon":{"max":-76.90055,"mean":-76.9911605882353,"variance":0.0068931327183823,"stdev":0.0830248921612206,"min":-77.15235,"median":-76.9546},"lat":{"max":41.0131,"mean":40.9462223529412,"variance":0.00128166303161767,"stdev":0.0358003216691928,"min":40.8799,"median":40.94978}},"features":[{"properties":{"lon":-76.95137,"id":"a64sqnl84n4g","lat":40.94978},"type":"Feature","geometry":{"type":"Point","coordinates":[-76.95137,40.94978]}},{"properties":{"lon":-76.94853,"id":"a64sqnbdzmrr","lat":40.94987},"type":"Feature","geometry":{"type":"Point","coordinates":[-76.94853,40.94987]}},{"properties":{"lon":-76.92702,"id":"a64sqnlnes8r","lat":40.9301},"type":"Feature","geometry":{"type":"Point","coordinates":[-76.92702,40.9301]}},{"properties":{"lon":-76.93178,"id":"a64sqnhocxdk","lat":40.93035},"type":"Feature","geometry":{"type":"Point","coordinates":[-76.93178,40.93035]}},{"properties":{"lon":-76.939,"id":"a64sqncki2gv","lat":40.92732},"type":"Feature","geometry":{"type":"Point","coordinates":[-76.939,40.92732]}},{"properties":{"lon":-76.9546,"id":"a64sqnh2a8eu","lat":40.94832},"type":"Feature","geometry":{"type":"Point","coordinates":[-76.9546,40.94832]}},{"properties":{"lon":-77.13772,"id":"a64sqneojq3k","lat":40.8882},"type":"Feature","geometry":{"type":"Point","coordinates":[-77.13772,40.8882]}},{"properties":{"lon":-77.14383,"id":"a64sqnecywe1","lat":40.8799},"type":"Feature","geometry":{"type":"Point","coordinates":[-77.14383,40.8799]}},{"properties":{"lon":-77.15235,"id":"a64sqnjfl167","lat":40.9027},"type":"Feature","geometry":{"type":"Point","coordinates":[-77.15235,40.9027]}},{"properties":{"lon":-77.04383,"id":"a64sqnicjobk","lat":40.95402},"type":"Feature","geometry":{"type":"Point","coordinates":[-77.04383,40.95402]}},{"properties":{"lon":-77.00757,"id":"a64sqnfvr3pt","lat":40.94197},"type":"Feature","geometry":{"type":"Point","coordinates":[-77.00757,40.94197]}},{"properties":{"lon":-77.01117,"id":"a64sqnggaubp","lat":40.95642},"type":"Feature","geometry":{"type":"Point","coordinates":[-77.01117,40.95642]}},{"properties":{"lon":-77.00647,"id":"a64sqnki889v","lat":40.96833},"type":"Feature","geometry":{"type":"Point","coordinates":[-77.00647,40.96833]}},{"properties":{"lon":-76.96219,"id":"a64sqn8ueeu4","lat":40.96017},"type":"Feature","geometry":{"type":"Point","coordinates":[-76.96219,40.96017]}},{"properties":{"lon":-76.92927,"id":"a64sqnaevcc0","lat":40.98028},"type":"Feature","geometry":{"type":"Point","coordinates":[-76.92927,40.98028]}},{"properties":{"lon":-76.90055,"id":"a64sqnfqbmyy","lat":41.00495},"type":"Feature","geometry":{"type":"Point","coordinates":[-76.90055,41.00495]}},{"properties":{"lon":-76.90248,"id":"a64sqnhesuzp","lat":41.0131},"type":"Feature","geometry":{"type":"Point","coordinates":[-76.90248,41.0131]}}],"is_temporal":false,"author":{"url":"","metadata":"","contact_name":"","contact_address":"","source":"","contact_phone":""},"source":"","pagination":{"sort":null,"start":0,"total":17,"limit":1000000},"state":"complete","tags":"","published":"2014-08-12T21:24:14-04:00","id":190362}