{"type":"FeatureCollection","data_type":"Dataset","url_type":null,"permissions":[{"permissions":{"download":true,"view":true},"group_id":"everyone"}],"classification":null,"title":"World Cup Winners, World by Country, 1930-2006","count":7,"stream_id":19086,"contributor":{"url":"http://geocommons.com/users/185","name":"emily"},"data_attributes":null,"calculation_params":null,"icon_link":null,"link":"http://geocommons.com/overlays/19086.json","extent":[-63.5848,-37.0907,12.5735,52.8836],"geometry_types":["point"],"unique_name":null,"name":"World Cup Winners, World by Country, 1930-2006","feature_count":7,"description":"This dataset was created from a chart on the Wikipedia page for the World Cup. It shows points for the winning countries with the number of times won as well as the years won.","next_feature":null,"is_raster":false,"short_classification":"Y","stats":{"latitude":{"max":52.88356,"mean":15.5798138571429,"variance":1717.69286189434,"stdev":41.4450583531298,"min":-37.090698,"median":42.503819},"times":{"max":5.0,"mean":2.57142857142857,"variance":2.28571428571429,"stdev":1.51185789203691,"min":1.0,"median":2.0},"longitude":{"max":12.57347,"mean":-22.0768147142857,"variance":1151.76183315436,"stdev":33.9376167866037,"min":-63.584808,"median":-1.97406}},"features":[{"properties":{"latitude":-32.531509,"times":2.0,"year":"1930, 1950","longitude":-55.758331,"id":"a638tgcqahkk","winner":"Uruguay"},"type":"Feature","geometry":{"type":"Point","coordinates":[-55.758331,-32.531509]}},{"properties":{"latitude":42.503819,"times":4.0,"year":"1934, 1938, 1982, 2006","longitude":12.57347,"id":"a638tg90ud3v","winner":"Italy"},"type":"Feature","geometry":{"type":"Point","coordinates":[12.57347,42.503819]}},{"properties":{"latitude":50.825775,"times":3.0,"year":"1954, 1974, 1990","longitude":6.875665,"id":"a638tfwpzrso","winner":"West Germany"},"type":"Feature","geometry":{"type":"Point","coordinates":[6.875665,50.825775]}},{"properties":{"latitude":-14.24292,"times":5.0,"year":"1958, 1962, 1970, 1994, 2002","longitude":-54.387829,"id":"a638tg1i8ux6","winner":"Brazil"},"type":"Feature","geometry":{"type":"Point","coordinates":[-54.387829,-14.24292]}},{"properties":{"latitude":52.88356,"times":1.0,"year":"1966","longitude":-1.97406,"id":"a638tgamosow","winner":"England"},"type":"Feature","geometry":{"type":"Point","coordinates":[-1.97406,52.88356]}},{"properties":{"latitude":-37.090698,"times":2.0,"year":"1978, 1986","longitude":-63.584808,"id":"a638tg8my0j4","winner":"Argentina"},"type":"Feature","geometry":{"type":"Point","coordinates":[-63.584808,-37.090698]}},{"properties":{"latitude":46.71067,"times":1.0,"year":"1998","longitude":1.71819,"id":"a638tg7qtlgv","winner":"France"},"type":"Feature","geometry":{"type":"Point","coordinates":[1.71819,46.71067]}}],"is_temporal":false,"author":{"url":"http://en.wikipedia.org/wiki/FIFA_World_Cup","metadata":"","contact_name":"","contact_address":"","source":"wikipedia","contact_phone":""},"source":"http://en.wikipedia.org/wiki/FIFA_World_Cup","pagination":{"sort":null,"start":0,"total":7,"limit":1000000},"state":"complete","tags":"football,recreation,soccer,sports,world","published":"2009-12-13T21:20:00Z","id":19086}