{"type":"FeatureCollection","data_type":"Dataset","url_type":null,"permissions":[{"permissions":{"download":true,"view":true},"group_id":"everyone"}],"classification":null,"title":"PH_PTS","count":1,"stream_id":191880,"contributor":{"url":"http://geocommons.com/users/30728","name":"jeejay70"},"data_attributes":null,"calculation_params":null,"icon_link":null,"link":"http://geocommons.com/overlays/191880.json","extent":[120.739,15.5931,120.739,15.5931],"geometry_types":["point"],"unique_name":null,"name":"PH_PTS","feature_count":1,"description":"","next_feature":null,"is_raster":false,"short_classification":"Y","stats":{},"features":[{"properties":{"COUNTRY":"Philippines","ISO_2":"PH","ISO_3":"PHL","id":"0"},"type":"Feature","geometry":{"type":"Point","coordinates":[120.73905,15.59305]}}],"is_temporal":false,"author":{"url":"","metadata":null,"contact_name":null,"contact_address":null,"source":null,"contact_phone":null},"source":"","pagination":{"sort":null,"start":0,"total":1,"limit":1000000},"state":"complete","tags":"","published":"2014-08-12T23:30:11-04:00","id":191880}