{"type":"FeatureCollection","data_type":"Dataset","url_type":null,"permissions":[{"permissions":{"download":true,"view":true},"group_id":"everyone"}],"classification":null,"title":"iPhone WIFI","count":8,"stream_id":192037,"contributor":{"url":"http://geocommons.com/users/11038","name":"cmckechney"},"data_attributes":null,"calculation_params":null,"icon_link":null,"link":"http://geocommons.com/overlays/192037.json","extent":[-115.178,36.1119,-115.173,36.1189],"geometry_types":["point"],"unique_name":null,"name":"iPhone WIFI","feature_count":8,"description":"","next_feature":null,"is_raster":false,"short_classification":"Y","stats":{"weight":{"max":19,"mean":7.25,"variance":35.3571428571429,"stdev":5.94618725379069,"min":2,"median":7},"lng":{"max":-115.173351166667,"mean":-115.17601309046,"variance":2.30751063716641e-06,"stdev":0.00151904925435827,"min":-115.177674393946,"median":-115.175757142857},"error_index":{"max":3,"mean":0.5,"variance":1.14285714285714,"stdev":1.0690449676497,"min":0,"median":0},"lat":{"max":36.11887446125,"mean":36.1136667506259,"variance":4.89336914982582e-06,"stdev":0.0022120960986869,"min":36.1119485238095,"median":36.1134298333333},"ptimestamp":{"max":"2011/12/28 19:30:54 -0500","mean":"2011/12/27 11:40:34 -0500","variance":11046984402.2857,"stdev":105104.635493805,"min":"2011/12/25 18:25:14 -0500","median":"2011/12/27 17:26:04 -0500"}},"features":[{"properties":{"weight":2,"mac":"64:a0:e7:af:62:e0","lng":-115.176670876289,"id":"a62386zeazmy","error_index":0,"lat":36.1137824682343,"locked":"False","ptimestamp":{"end_time":"2011/12/28 19:30:55 -0500","original":"2011-12-28 19:30:54","granularity":"sec","time":"2011/12/28 19:30:54 -0500"}},"type":"Feature","geometry":{"type":"Point","coordinates":[-115.176670876289,36.1137824682343]}},{"properties":{"weight":3,"mac":"00:23:33:17:3e:20","lng":-115.173351166667,"id":"a62386vl60ex","error_index":3,"lat":36.1134298333333,"locked":"False","ptimestamp":{"end_time":"2011/12/28 19:30:20 -0500","original":"2011-12-28 19:30:19","granularity":"sec","time":"2011/12/28 19:30:19 -0500"}},"type":"Feature","geometry":{"type":"Point","coordinates":[-115.173351166667,36.1134298333333]}},{"properties":{"weight":7,"mac":"00:0b:86:7a:a1:30","lng":-115.175757142857,"id":"a623870fzgj5","error_index":0,"lat":36.1119485238095,"locked":"False","ptimestamp":{"end_time":"2011/12/28 17:00:22 -0500","original":"2011-12-28 17:00:21","granularity":"sec","time":"2011/12/28 17:00:21 -0500"}},"type":"Feature","geometry":{"type":"Point","coordinates":[-115.175757142857,36.1119485238095]}},{"properties":{"weight":9,"mac":"00:0b:86:7a:9f:20","lng":-115.174571177778,"id":"a62386tw46sd","error_index":0,"lat":36.1128958666667,"locked":"False","ptimestamp":{"end_time":"2011/12/27 17:26:05 -0500","original":"2011-12-27 17:26:04","granularity":"sec","time":"2011/12/27 17:26:04 -0500"}},"type":"Feature","geometry":{"type":"Point","coordinates":[-115.174571177778,36.1128958666667]}},{"properties":{"weight":19,"mac":"00:21:a0:27:fc:b0","lng":-115.177494886146,"id":"a623872tcxgz","error_index":1,"lat":36.1124156139025,"locked":"False","ptimestamp":{"end_time":"2011/12/26 22:52:55 -0500","original":"2011-12-26 22:52:54","granularity":"sec","time":"2011/12/26 22:52:54 -0500"}},"type":"Feature","geometry":{"type":"Point","coordinates":[-115.177494886146,36.1124156139025]}},{"properties":{"weight":12,"mac":"00:21:a0:27:1a:50","lng":-115.177674393946,"id":"a623870905z5","error_index":0,"lat":36.1122705378111,"locked":"False","ptimestamp":{"end_time":"2011/12/26 22:51:05 -0500","original":"2011-12-26 22:51:04","granularity":"sec","time":"2011/12/26 22:51:04 -0500"}},"type":"Feature","geometry":{"type":"Point","coordinates":[-115.177674393946,36.1122705378111]}},{"properties":{"weight":2,"mac":"00:21:a0:26:fb:00","lng":-115.1754626,"id":"a62386yysiid","error_index":0,"lat":36.1137167,"locked":"False","ptimestamp":{"end_time":"2011/12/26 03:47:47 -0500","original":"2011-12-26 03:47:46","granularity":"sec","time":"2011/12/26 03:47:46 -0500"}},"type":"Feature","geometry":{"type":"Point","coordinates":[-115.1754626,36.1137167]}},{"properties":{"weight":4,"mac":"00:27:0d:5f:57:a0","lng":-115.17712248,"id":"a623875e4lpv","error_index":0,"lat":36.11887446125,"locked":"False","ptimestamp":{"end_time":"2011/12/25 18:25:15 -0500","original":"2011-12-25 18:25:14","granularity":"sec","time":"2011/12/25 18:25:14 -0500"}},"type":"Feature","geometry":{"type":"Point","coordinates":[-115.17712248,36.11887446125]}}],"is_temporal":true,"author":{"url":"","metadata":"","contact_name":"","contact_address":"","source":"","contact_phone":""},"source":"","pagination":{"sort":null,"start":0,"total":8,"limit":1000000},"state":"complete","tags":"","published":"2014-08-12T23:43:04-04:00","id":192037}