{"type":"FeatureCollection","data_type":"Dataset","url_type":null,"permissions":[{"permissions":{"download":true,"view":true},"group_id":"everyone"}],"classification":null,"title":"test","count":4,"stream_id":19210,"contributor":{"url":"http://geocommons.com/users/7089","name":"galylee"},"data_attributes":null,"calculation_params":null,"icon_link":null,"link":"http://geocommons.com/overlays/19210.json","extent":[113.25,22.5455,121.458,39.9075],"geometry_types":["point"],"unique_name":null,"name":"test","feature_count":4,"description":"","next_feature":null,"is_raster":false,"short_classification":"Y","stats":{"geo_score":{"max":1.0,"mean":1.0,"variance":0.0,"stdev":0.0,"min":1.0,"median":1.0},"gdp":{"max":40.0,"mean":25.0,"variance":166.666666666667,"stdev":12.9099444873581,"min":10.0,"median":30.0}},"features":[{"properties":{"city":"beijing","geo_score":1.0,"gdp":20.0,"id":"a6zfje7fj6xu","geo_precision":"zip"},"type":"Feature","geometry":{"type":"Point","coordinates":[116.397228240967,39.9074977414405]}},{"properties":{"city":"guangzhou","geo_score":1.0,"gdp":10.0,"id":"a6zfjelbmb6e","geo_precision":"zip"},"type":"Feature","geometry":{"type":"Point","coordinates":[113.25,23.1166667]}},{"properties":{"city":"shanghai","geo_score":1.0,"gdp":30.0,"id":"a6zfjelpvw5p","geo_precision":"zip"},"type":"Feature","geometry":{"type":"Point","coordinates":[121.4580556,31.2222222]}},{"properties":{"city":"shenzhen","geo_score":1.0,"gdp":40.0,"id":"a6zfjen3loyo","geo_precision":"zip"},"type":"Feature","geometry":{"type":"Point","coordinates":[114.068298339844,22.5455376639819]}}],"is_temporal":false,"author":{"url":"","metadata":"","contact_name":"","contact_address":"","source":"","contact_phone":""},"source":"","pagination":{"sort":null,"start":0,"total":4,"limit":1000000},"state":"complete","tags":"","published":"2014-08-11T01:03:55-04:00","id":19210}