{"type":"FeatureCollection","data_type":"Dataset","url_type":null,"permissions":[{"permissions":{"download":true,"view":true},"group_id":"everyone"}],"classification":null,"title":"Broad Street Pumps - John Snow","count":8,"stream_id":193153,"contributor":{"url":"http://geocommons.com/users/159","name":"ajturner"},"data_attributes":null,"calculation_params":null,"icon_link":null,"link":"http://geocommons.com/overlays/193153.json","extent":[-0.138066,51.5095,-0.130024,51.5144],"geometry_types":["point"],"unique_name":"","name":"Broad Street Pumps - John Snow","feature_count":8,"description":"contains a number of GIS layers relating to John Snow's 1854 investigation of a Cholera outbreak in London - considered by many to be the first use of geographical analysis in an epidemiological study. More details on the history are available at http://en.wikipedia.org/wiki/1854_Broad_Street_cholera_outbreak","next_feature":null,"is_raster":false,"short_classification":"Y","stats":{"Id":{"max":0,"variance":0.0,"mean":0.0,"stdev":0.0,"min":0,"median":0}},"features":[{"properties":{"Id":0,"id":"0"},"type":"Feature","geometry":{"type":"Point","coordinates":[-0.136667876716998,51.5133411171264]}},{"properties":{"Id":0,"id":"1"},"type":"Feature","geometry":{"type":"Point","coordinates":[-0.139586169059146,51.5138759909098]}},{"properties":{"Id":0,"id":"2"},"type":"Feature","geometry":{"type":"Point","coordinates":[-0.139671022700271,51.5149055726104]}},{"properties":{"Id":0,"id":"3"},"type":"Feature","geometry":{"type":"Point","coordinates":[-0.13162985673562,51.5123540234819]}},{"properties":{"Id":0,"id":"4"},"type":"Feature","geometry":{"type":"Point","coordinates":[-0.133594411488385,51.5121388790537]}},{"properties":{"Id":0,"id":"5"},"type":"Feature","geometry":{"type":"Point","coordinates":[-0.135919147673632,51.5115423185446]}},{"properties":{"Id":0,"id":"6"},"type":"Feature","geometry":{"type":"Point","coordinates":[-0.133961736109809,51.5100193479995]}},{"properties":{"Id":0,"id":"7"},"type":"Feature","geometry":{"type":"Point","coordinates":[-0.138198768040845,51.5112952261304]}}],"is_temporal":false,"author":{"url":"http://www.r-bloggers.com/john-snow%E2%80%99s-famous-cholera-analysis-data-in-modern-gis-formats/","metadata":"","contact_name":"","contact_address":"","source":"R-Bloggers","contact_phone":""},"source":"http://www.r-bloggers.com/john-snow%E2%80%99s-famous-cholera-analysis-data-in-modern-gis-formats/","pagination":{"sort":null,"start":0,"total":8,"limit":1000000},"state":"complete","tags":"health,history","published":"2014-08-13T00:59:51-04:00","id":193153}