{"type":"FeatureCollection","data_type":"Dataset","url_type":null,"permissions":[{"permissions":{"download":true,"view":true},"group_id":"everyone"}],"classification":null,"title":"Ghana_Foundation_of_Human_Development_G","count":1,"stream_id":193574,"contributor":{"url":"http://geocommons.com/users/38201","name":"jonathan.yu"},"data_attributes":null,"calculation_params":null,"icon_link":null,"link":"http://geocommons.com/overlays/193574.json","extent":[-0.257581,5.54701,-0.257581,5.54701],"geometry_types":["point"],"unique_name":null,"name":"Ghana_Foundation_of_Human_Development_G","feature_count":1,"description":"","next_feature":null,"is_raster":false,"short_classification":"Y","stats":{"latitude":{"max":5.5470058,"min":5.5470058,"median":5.5470058},"longitude":{"max":-0.2575813,"min":-0.2575813,"median":-0.2575813}},"features":[{"properties":{"city":"Accra","latitude":5.5470058,"ngo name":"Ghana Foundation of Human Development (G.F.H.D.)","country":"Ghana","mission":"To sponsor able and disabled children through basic education; to establish a vocational training centre for girls; inter-cultural exchange programmes for youth; advocacy on social vices","longitude":-0.2575813,"id":"a63exqt26lg8","email address":"gfhd@hotmail.com","phone number":"(233) 24289048"},"type":"Feature","geometry":{"type":"Point","coordinates":[-0.2575813,5.5470058]}}],"is_temporal":false,"author":{"url":"","metadata":null,"contact_name":null,"contact_address":null,"source":null,"contact_phone":null},"source":"","pagination":{"sort":null,"start":0,"total":1,"limit":1000000},"state":"complete","tags":"","published":"2014-08-13T01:36:40-04:00","id":193574}