{"type":"FeatureCollection","data_type":"Dataset","url_type":null,"permissions":[{"permissions":{"download":true,"view":true},"group_id":"everyone"}],"classification":null,"title":"tiempo","count":3,"stream_id":19361,"contributor":{"url":"http://geocommons.com/users/4043","name":"seneca"},"data_attributes":null,"calculation_params":null,"icon_link":null,"link":"http://geocommons.com/overlays/19361.json","extent":[-86.2503,40.0,-80.967,44.2503],"geometry_types":["point"],"unique_name":null,"name":"tiempo","feature_count":3,"description":"","next_feature":null,"is_raster":false,"short_classification":"Y","stats":{"latitude":{"max":44.2503,"mean":41.4168666666667,"variance":6.02125836333334,"stdev":2.45382525118097,"min":40.0,"median":40.0003},"x":{"max":-80.967,"mean":-84.2392,"variance":8.17109462999999,"stdev":2.85851266045823,"min":-86.2503,"median":-85.5003},"y":{"max":44.2503,"mean":41.4168666666667,"variance":6.02125836333334,"stdev":2.45382525118097,"min":40.0,"median":40.0003},"end":{"max":1239.0,"mean":944.333333333333,"variance":88530.3333333333,"stdev":297.540473437368,"min":644.0,"median":950.0},"start":{"max":1232.0,"mean":938.0,"variance":87628.0,"stdev":296.020269576257,"min":640.0,"median":942.0},"index":{"max":2.0,"mean":1.0,"variance":1.0,"stdev":1.0,"min":0.0,"median":1.0},"longitude":{"max":-80.967,"mean":-84.2392,"variance":8.17109462999999,"stdev":2.85851266045823,"min":-86.2503,"median":-85.5003},"geoconfidence":{"max":0.773522,"mean":0.585781333333333,"variance":0.0879294948013334,"stdev":0.296529079183363,"min":0.24393,"median":0.739892}},"features":[{"properties":{"latitude":40.0,"georef":"Ohio","x":-80.967,"y":40.0,"end":644.0,"start":640.0,"xpath":null,"index":0.0,"longitude":-80.967,"offset":null,"id":"a65xzj6zjyi7","geoconfidence":0.773522,"style":"loc"},"type":"Feature","geometry":{"type":"Point","coordinates":[-80.967,40.0]}},{"properties":{"latitude":44.2503,"georef":"Michigan","x":-85.5003,"y":44.2503,"end":950.0,"start":942.0,"xpath":null,"index":1.0,"longitude":-85.5003,"offset":null,"id":"a65xzjliv8kk","geoconfidence":0.24393,"style":"loc"},"type":"Feature","geometry":{"type":"Point","coordinates":[-85.5003,44.2503]}},{"properties":{"latitude":40.0003,"georef":"Indiana","x":-86.2503,"y":40.0003,"end":1239.0,"start":1232.0,"xpath":null,"index":2.0,"longitude":-86.2503,"offset":null,"id":"a65xzjis6sja","geoconfidence":0.739892,"style":"loc"},"type":"Feature","geometry":{"type":"Point","coordinates":[-86.2503,40.0003]}}],"is_temporal":false,"author":{"url":"","metadata":"","contact_name":"","contact_address":"","source":"","contact_phone":""},"source":"","pagination":{"sort":null,"start":0,"total":3,"limit":1000000},"state":"complete","tags":"","published":"2014-08-11T01:12:29-04:00","id":19361}