{"type":"FeatureCollection","data_type":"Dataset","url_type":null,"permissions":[{"permissions":{"download":true,"view":true},"group_id":"everyone"}],"classification":null,"title":"Tamaulipas Warehouse","count":1,"stream_id":195073,"contributor":{"url":"http://geocommons.com/users/38242","name":"Amyruski"},"data_attributes":null,"calculation_params":null,"icon_link":null,"link":"http://geocommons.com/overlays/195073.json","extent":[-98.8333,26.3167,-98.8333,26.3167],"geometry_types":["point"],"unique_name":null,"name":"Tamaulipas Warehouse","feature_count":1,"description":"","next_feature":null,"is_raster":false,"short_classification":"Y","stats":{"latitude":{"max":26.31666756,"min":26.31666756,"median":26.31666756},"event id":{"max":3923104,"min":3923104,"median":3923104},"total involved":{"max":0,"min":0,"median":0},"dto injuries":{"max":0,"min":0,"median":0},"dto deaths":{"max":0,"min":0,"median":0},"civilian involved":{"max":0,"min":0,"median":0},"government involved":{"max":0,"min":0,"median":0},"government injuries":{"max":0,"min":0,"median":0},"civilian deaths":{"max":0,"min":0,"median":0},"civilian injuries":{"max":0,"min":0,"median":0},"government deaths":{"max":0,"min":0,"median":0},"dto involved":{"max":0,"min":0,"median":0},"longitude":{"max":-98.83333588,"min":-98.83333588,"median":-98.83333588},"total deaths":{"max":0,"min":0,"median":0},"total injuries":{"max":0,"min":0,"median":0}},"features":[{"properties":{"city":"Camargo","event type":"Military Operation","latitude":26.31666756,"event id":3923104,"region":"North America","details":"448 packages of marijuana, weighing 676.22 kilograms, were seized. About 838,100 doses of marijuana would have been produced from the seized marijuana.","event date":"11/10/2011 0:00","property":"Warehouse","total involved":0,"dto injuries":0,"dto deaths":0,"civilian involved":0,"government involved":0,"government injuries":0,"country":"Mexico","specific contraband":"Marijuana","contraband":"Drugs","event summary":"11/10/2011: On Thursday near the town of Guardados de ABajo, Camargo, Tamaulipas, Mexico, soldiers assigned to the 8th Military Zone IV Military Region participating in Operation Noreste found a pit used by organized crime as an underground warehouse while they were conducting a routine patrol. They seized 448 packages of marijuana, weighing 676.22 kilograms; 838,100 doses of marijuana would have been produced from the seized marijuana. No casualties were reported. No group claimed responsibility. No damages were reported.","civilian deaths":0,"civilian injuries":0,"government deaths":0,"dto involved":0,"longitude":-98.83333588,"contraband type":"Cannabis","id":"0","total deaths":0,"group":"Unknown","location":"The operation occurred near the town of Guardados de Abajo, Camargo, Tamaulipas, Mexico in an underground warehouse.","total injuries":0,"state":"Tamaulipas","basic title":"Soldiers Find Organized Crime Pit and Seize Marijuana in Camargo"},"type":"Feature","geometry":{"type":"Point","coordinates":[-98.83333588,26.31666756]}}],"is_temporal":false,"author":{"url":"","metadata":"","contact_name":"","contact_address":"","source":"","contact_phone":""},"source":"","pagination":{"sort":null,"start":0,"total":1,"limit":1000000},"state":"complete","tags":"","published":"2014-08-13T03:51:19-04:00","id":195073}