{"type":"FeatureCollection","data_type":"Dataset","url_type":null,"permissions":[{"permissions":{"download":true,"view":true},"group_id":"everyone"}],"classification":null,"title":"Rocky Mountain Youth Corps","count":4,"stream_id":195135,"contributor":{"url":"http://geocommons.com/users/37847","name":"KarmicVisions"},"data_attributes":null,"calculation_params":null,"icon_link":null,"link":"http://geocommons.com/overlays/195135.json","extent":[-105.726,36.1956,-105.381,36.3664],"geometry_types":["point"],"unique_name":null,"name":"Rocky Mountain Youth Corps","feature_count":4,"description":"","next_feature":null,"is_raster":false,"short_classification":"Y","stats":{"# of members":{"max":27,"mean":13.5,"variance":85.6666666666667,"stdev":9.25562891794321,"min":7,"median":12}},"features":[{"properties":{"city":"Taos","geo_score":0.878,"zip code":"87571","site address":"305 Don Fernando","# of members":7,"program":"Rocky Mountain Youth Corps","id":"a63213yiyesx","geo_precision":"zip","state":"NM","member sites":"Enos Garcia Elementary School"},"type":"Feature","geometry":{"type":"Point","coordinates":[-105.380843,36.366419]}},{"properties":{"city":"Ranchos de Taos","geo_score":0.879,"zip code":"87557","site address":"200 Sanders Lane","# of members":12,"program":"Rocky Mountain Youth Corps","id":"a632143185m6","geo_precision":"zip","state":"NM","member sites":"Ranchos Elementary School"},"type":"Feature","geometry":{"type":"Point","coordinates":[-105.596957,36.341415]}},{"properties":{"city":"Penasco","geo_score":0.893,"zip code":"87553","site address":"13 School Road","# of members":8,"program":"Rocky Mountain Youth Corps","id":"a632149xkhsy","geo_precision":"zip","state":"NM","member sites":"Penasco Elementary School;"},"type":"Feature","geometry":{"type":"Point","coordinates":[-105.725571,36.19558]}},{"properties":{"city":"Taos","geo_score":0.878,"zip code":"87571","site address":"1021 Salazar Road","# of members":27,"program":"Rocky Mountain Youth Corps","id":"a63214aj0plt","geo_precision":"zip","state":"NM","member sites":"Rocky Mountain Youth Corps"},"type":"Feature","geometry":{"type":"Point","coordinates":[-105.380843,36.366419]}}],"is_temporal":false,"author":{"url":"","metadata":"","contact_name":"","contact_address":"","source":"","contact_phone":""},"source":"","pagination":{"sort":null,"start":0,"total":4,"limit":1000000},"state":"complete","tags":"","published":"2014-08-13T03:56:57-04:00","id":195135}