{"type":"FeatureCollection","data_type":"Dataset","url_type":null,"permissions":[{"permissions":{"download":true,"view":true},"group_id":"everyone"}],"classification":null,"title":"Five or More Criminals Dead in Veracruz","count":1,"stream_id":195358,"contributor":{"url":"http://geocommons.com/users/38244","name":"nsnyder"},"data_attributes":null,"calculation_params":null,"icon_link":null,"link":"http://geocommons.com/overlays/195358.json","extent":[-96.9333,18.8833,-96.9333,18.8833],"geometry_types":["point"],"unique_name":null,"name":"Five or More Criminals Dead in Veracruz","feature_count":1,"description":"This data shows where five or more criminals were killed during a single event in Veracruz, Mexico from 09/15/2011 to 12/14/2011.","next_feature":null,"is_raster":false,"short_classification":"Y","stats":{"latitude":{"max":18.88333321,"min":18.88333321,"median":18.88333321},"event id":{"max":3865265,"min":3865265,"median":3865265},"event date":{"max":40836,"min":40836,"median":40836},"total involved":{"max":0,"min":0,"median":0},"dto injuries":{"max":2,"min":2,"median":2},"dto deaths":{"max":10,"min":10,"median":10},"civilian involved":{"max":0,"min":0,"median":0},"government involved":{"max":0,"min":0,"median":0},"government injuries":{"max":0,"min":0,"median":0},"civilian deaths":{"max":0,"min":0,"median":0},"civilian injuries":{"max":0,"min":0,"median":0},"government deaths":{"max":0,"min":0,"median":0},"dto involved":{"max":0,"min":0,"median":0},"longitude":{"max":-96.93333435,"min":-96.93333435,"median":-96.93333435},"total deaths":{"max":10,"min":10,"median":10},"total injuries":{"max":2,"min":2,"median":2}},"features":[{"properties":{"city":"Cordoba","event type":"Armed Assault","weapoon used":"Sidearms","latitude":18.88333321,"event id":3865265,"otype":"N/A","event date":40836,"total involved":0,"dto injuries":2,"dto deaths":10,"civilian involved":0,"government involved":0,"government injuries":0,"tacticspecs":"Armed gunmen opened fire on military personnel, when the officials responded to an anonymous caller reporting heavily armed men near a mall, on 11th avenue.","event summary":"10/20/2011: On Thursday evening at 2100, on 11th Avenue in Cordoba, Veracruz, Mexico, armed gunmen opened fire on military personnel, when the officials responded to an anonymous caller reporting heavily armed men near a mall, on 11th avenue. Ten gunmen were killed and two were injured in retaliatory fire. Two bodies were recovered in the street, their heads a few meters away in black bags.","agency":"N/A","civilian deaths":0,"civilian injuries":0,"government deaths":0,"dto involved":0,"longitude":-96.93333435,"attackdescribe":"Shooting / Firearms","id":"0","total deaths":10,"group":"N/A","total injuries":2,"state":"Veracruz"},"type":"Feature","geometry":{"type":"Point","coordinates":[-96.93333435,18.88333321]}}],"is_temporal":false,"author":{"url":"","metadata":"","contact_name":"","contact_address":"","source":"","contact_phone":""},"source":"","pagination":{"sort":null,"start":0,"total":1,"limit":1000000},"state":"complete","tags":"","published":"2012-01-13T16:07:36Z","id":195358}