{"type":"FeatureCollection","data_type":"Dataset","url_type":null,"permissions":[{"permissions":{"download":true,"view":true},"group_id":"everyone"}],"classification":null,"title":"testtest","count":1,"stream_id":195705,"contributor":{"url":"http://geocommons.com/users/38205","name":"DerNils"},"data_attributes":null,"calculation_params":null,"icon_link":null,"link":"http://geocommons.com/overlays/195705.json","extent":[7.47695,51.5125,7.47695,51.5125],"geometry_types":["point"],"unique_name":null,"name":"testtest","feature_count":1,"description":"","next_feature":null,"is_raster":false,"short_classification":"Y","stats":{},"features":[{"properties":{"dortmund":"Dortmund","geo_score":0.802,"gersdorffstrasse":"Duesseldorfer Strasse","germany":"Germany","20":"49","id":"a6e2kr4qerce","geo_precision":"zip"},"type":"Feature","geometry":{"type":"Point","coordinates":[7.47695,51.5125]}}],"is_temporal":false,"author":{"url":"","metadata":"","contact_name":"","contact_address":"","source":"","contact_phone":""},"source":"","pagination":{"sort":null,"start":0,"total":1,"limit":1000000},"state":"complete","tags":"","published":"2014-08-13T04:39:17-04:00","id":195705}