{"type":"FeatureCollection","data_type":"Dataset","url_type":null,"permissions":[{"permissions":{"download":true,"view":true},"group_id":"everyone"}],"classification":null,"title":"testtest","count":3,"stream_id":195711,"contributor":{"url":"http://geocommons.com/users/38205","name":"DerNils"},"data_attributes":null,"calculation_params":null,"icon_link":null,"link":"http://geocommons.com/overlays/195711.json","extent":[7.21667,51.4833,13.4,53.55],"geometry_types":["point"],"unique_name":null,"name":"testtest","feature_count":3,"description":"","next_feature":null,"is_raster":false,"short_classification":"Y","stats":{},"features":[{"properties":{"dortmund":"Bochum","geo_score":0.857,"germany":"Germany","id":"a65wloegwoxm","geo_precision":"zip"},"type":"Feature","geometry":{"type":"Point","coordinates":[7.2166667,51.4833333]}},{"properties":{"dortmund":"Hamburg","geo_score":0.857,"germany":"Germany","id":"a65wlofl19n0","geo_precision":"zip"},"type":"Feature","geometry":{"type":"Point","coordinates":[10.0,53.55]}},{"properties":{"dortmund":"Berlin","geo_score":0.857,"germany":"Germany","id":"a65wlorkb2ht","geo_precision":"zip"},"type":"Feature","geometry":{"type":"Point","coordinates":[13.4,52.5166667]}}],"is_temporal":false,"author":{"url":"","metadata":"","contact_name":"","contact_address":"","source":"","contact_phone":""},"source":"","pagination":{"sort":null,"start":0,"total":3,"limit":1000000},"state":"complete","tags":"","published":"2014-08-13T04:39:49-04:00","id":195711}