{"type":"FeatureCollection","data_type":"Dataset","url_type":null,"permissions":[{"permissions":{"download":true,"view":true},"group_id":"everyone"}],"classification":null,"title":"Single Line Geocoding","count":3,"stream_id":19595,"contributor":{"url":"http://geocommons.com/users/10308","name":"mrtester"},"data_attributes":null,"calculation_params":null,"icon_link":null,"link":"http://geocommons.com/overlays/19595.json","extent":[-123.119,-0.283333,36.0667,49.2497],"geometry_types":["point"],"unique_name":null,"name":"Single Line Geocoding","feature_count":3,"description":"Testing single line geocoding","next_feature":null,"is_raster":false,"short_classification":"Y","stats":{"geo_score":{"max":0.857,"mean":0.825333333333333,"variance":0.00300833333333333,"stdev":0.0548482755730144,"min":0.762,"median":0.857},"id":{"max":3.0,"mean":2.0,"variance":1.0,"stdev":1.0,"min":1.0,"median":2.0}},"features":[{"properties":{"city":"Toronto","geo_score":0.857,"id":"a65dh7sph0xz","geo_precision":"zip"},"type":"Feature","geometry":{"type":"Point","coordinates":[-79.416304194,43.700113788]}},{"properties":{"city":"Vancouver","geo_score":0.857,"id":"a65dh7viff5q","geo_precision":"zip"},"type":"Feature","geometry":{"type":"Point","coordinates":[-123.119340403,49.249657393]}},{"properties":{"city":"Niagra","geo_score":0.762,"id":"a65dh7yhvpa3","geo_precision":"zip"},"type":"Feature","geometry":{"type":"Point","coordinates":[36.0666667,-0.2833333]}}],"is_temporal":false,"author":{"url":"","metadata":"","contact_name":"Mr Tester","contact_address":"123 Testville\nTestland, Test 12345","source":"","contact_phone":"11111111"},"source":"","pagination":{"sort":null,"start":0,"total":3,"limit":1000000},"state":"complete","tags":"geocoding,line,single","published":"2009-12-30T16:40:53Z","id":19595}