{"type":"FeatureCollection","data_type":"Dataset","url_type":null,"permissions":[{"permissions":{"download":true,"view":true},"group_id":"everyone"}],"classification":null,"title":"romanicas","count":2,"stream_id":19891,"contributor":{"url":"http://geocommons.com/users/4043","name":"seneca"},"data_attributes":null,"calculation_params":null,"icon_link":null,"link":"http://geocommons.com/overlays/19891.json","extent":[-3.95332,43.3157,-3.59661,43.4703],"geometry_types":["point"],"unique_name":null,"name":"romanicas","feature_count":2,"description":"","next_feature":null,"is_raster":false,"short_classification":"Y","stats":{"latitude":{"max":43.470306,"mean":43.39301,"variance":0.0119493432320001,"stdev":0.109313051517191,"min":43.315714,"median":43.470306},"longitude":{"max":-3.596607,"mean":-3.7749635,"variance":0.0636220821845,"stdev":0.252234181237397,"min":-3.95332,"median":-3.596607}},"features":[{"properties":{"latitude":43.470306,"localidad":"bareyo","url":"http://www.circuloromanico.com/index.php?menu_id=9&amp;jera_id=928&amp;page_id=747","longitude":-3.596607,"id":"a6ofnichfosa"},"type":"Feature","geometry":{"type":"Point","coordinates":[-3.596607,43.470306]}},{"properties":{"latitude":43.315714,"localidad":"castañeda","url":"http://www.circuloromanico.com/index.php?menu_id=9&amp;jera_id=760&amp;page_id=601","longitude":-3.95332,"id":"a6ofni3sswv7"},"type":"Feature","geometry":{"type":"Point","coordinates":[-3.95332,43.315714]}}],"is_temporal":false,"author":{"url":"","metadata":"","contact_name":"","contact_address":"","source":"","contact_phone":""},"source":"","pagination":{"sort":null,"start":0,"total":2,"limit":1000000},"state":"complete","tags":"","published":"2014-08-11T01:28:20-04:00","id":19891}