{"type":"FeatureCollection","url":"http://api.flickr.com/services/feeds/geo/?id=75067987@N07&lang=en-us&format=rss_200","data_type":"Data Feed","url_type":"rss","permissions":[{"permissions":{"download":true,"view":true},"group_id":"everyone"}],"classification":null,"title":"geocommons - Flickr jrcecmlios, with geodata","count":2,"stream_id":199041,"contributor":{"url":"http://geocommons.com/users/38906","name":"jrcecml"},"data_attributes":null,"calculation_params":null,"icon_link":null,"link":"http://geocommons.com/overlays/199041.json","extent":[8.63102,45.8101,8.63103,45.8102],"geometry_types":["point"],"unique_name":null,"name":"geocommons - Flickr jrcecmlios, with geodata","feature_count":2,"description":"","next_feature":null,"is_raster":false,"short_classification":"Y","stats":{"published":{"max":"2012/01/24 12:28:28 -0500","mean":"2012/01/24 12:22:12 -0500","variance":282000.5,"stdev":531.037192671097,"min":"2012/01/24 12:15:57 -0500","median":"2012/01/24 12:28:28 -0500"}},"features":[{"properties":{"guid":"tag:flickr.com,2004:/photo/6755772053","title":"Power","published":{"end_time":"2012/01/24 12:28:29 -0500","original":"Tue, 24 Jan 2012 09:28:28 -0800","granularity":"sec","time":"2012/01/24 12:28:28 -0500"},"description":"<a href=\"http://www.flickr.com/people/75067987@N07/\">jrcecmlios</a> posted a photo:\n\t\n<a href=\"http://www.flickr.com/photos/75067987@N07/6755772053/\" title=\"Power\"><img src=\"http://farm8.staticflickr.com/7002/6755772053_bf9d0ca646_m.jpg\" width=\"240\" height=\"179\" alt=\"Power\"></a>","link":"http://www.flickr.com/photos/75067987@N07/6755772053/","id":"0"},"type":"Feature","geometry":{"type":"Point","coordinates":[8.631027,45.810091]}},{"properties":{"guid":"tag:flickr.com,2004:/photo/6755713107","title":"Pencil","published":{"end_time":"2012/01/24 12:15:58 -0500","original":"Tue, 24 Jan 2012 09:15:57 -0800","granularity":"sec","time":"2012/01/24 12:15:57 -0500"},"description":"<a href=\"http://www.flickr.com/people/75067987@N07/\">jrcecmlios</a> posted a photo:\n\t\n<a href=\"http://www.flickr.com/photos/75067987@N07/6755713107/\" title=\"Pencil\"><img src=\"http://farm8.staticflickr.com/7035/6755713107_e625c9bc71_m.jpg\" width=\"179\" height=\"240\" alt=\"Pencil\"></a>","link":"http://www.flickr.com/photos/75067987@N07/6755713107/","id":"1"},"type":"Feature","geometry":{"type":"Point","coordinates":[8.631023,45.810235]}}],"is_temporal":true,"author":{"url":"","metadata":"","contact_name":"","contact_address":"","source":"","contact_phone":""},"source":"","pagination":{"sort":null,"start":0,"total":2,"limit":1000000},"state":"complete","tags":"","published":"2014-08-13T10:01:14-04:00","id":199041}