{"type":"FeatureCollection","data_type":"Dataset","url_type":null,"permissions":[{"permissions":{"download":true,"view":true},"group_id":"everyone"}],"classification":null,"title":"20120201 Security Operations - Tanzania","count":6,"stream_id":201801,"contributor":{"url":"http://geocommons.com/users/33152","name":"rberntsson"},"data_attributes":null,"calculation_params":null,"icon_link":null,"link":"http://geocommons.com/overlays/201801.json","extent":[33.9199,-9.70316,39.2697,-3.36667],"geometry_types":["point"],"unique_name":null,"name":"20120201 Security Operations - Tanzania","feature_count":6,"description":"","next_feature":null,"is_raster":false,"short_classification":"Y","stats":{"latitude":{"max":-3.3666667,"mean":-6.07522723333333,"variance":5.80778146256677,"stdev":2.40993391248946,"min":-9.70316,"median":-6.369028},"event id":{"max":3770417,"mean":1891667.66666667,"variance":1647321270499.87,"stdev":1283480.14028261,"min":1018908,"median":1105285},"longitude":{"max":39.269661,"mean":36.7857887666667,"variance":4.83438240529413,"stdev":2.1987229032541,"min":33.919922,"median":36.6833333},"total deaths":{"max":0,"mean":0.0,"variance":0.0,"stdev":0.0,"min":0,"median":0},"total injuries":{"max":0,"mean":0.0,"variance":0.0,"stdev":0.0,"min":0,"median":0}},"features":[{"properties":{"city":"Dar es Salaam","event type":"Police Operation","latitude":-6.822921,"event id":1018908,"event date":"24-Aug","country":"Tanzania","event title":null,"longitude":39.269661,"id":"a640wru3ogjo","total deaths":null,"group":"Unknown","total injuries":null,"state":"Dar es Salaam"},"type":"Feature","geometry":{"type":"Point","coordinates":[39.269661,-6.822921]}},{"properties":{"city":"Songwe","event type":"Police Operation","latitude":-9.70316,"event id":1056827,"event date":"25-Apr","country":"Tanzania","event title":null,"longitude":33.919922,"id":"a640wrvlh250","total deaths":0,"group":"Unknown","total injuries":0,"state":"Mbeya"},"type":"Feature","geometry":{"type":"Point","coordinates":[33.919922,-9.70316]}},{"properties":{"city":"Unknown","event type":"Police Operation","latitude":-3.3666667,"event id":1094616,"event date":"21-Feb","country":"Tanzania","event title":null,"longitude":36.6833333,"id":"a640wrzx84vm","total deaths":0,"group":"Al Qaeda (Afghanistan)","total injuries":0,"state":"Arusha"},"type":"Feature","geometry":{"type":"Point","coordinates":[36.6833333,-3.3666667]}},{"properties":{"city":"Dar es Salaam","event type":"Police Operation","latitude":-6.822921,"event id":1105285,"event date":null,"country":"Tanzania","event title":null,"longitude":39.269661,"id":"a640wrynrbwg","total deaths":null,"group":"Unknown","total injuries":null,"state":"Dar es Salaam"},"type":"Feature","geometry":{"type":"Point","coordinates":[39.269661,-6.822921]}},{"properties":{"city":"Arusha","event type":"Police Operation","latitude":-3.3666667,"event id":3303953,"event date":"12-Sep","country":"Tanzania","event title":"Somali National Arrested in Arusha for Kampala Bombing","longitude":36.6833333,"id":"a640ws152ou3","total deaths":0,"group":"Unknown","total injuries":0,"state":"Arusha"},"type":"Feature","geometry":{"type":"Point","coordinates":[36.6833333,-3.3666667]}},{"properties":{"city":"Unknown","event type":"Police Operation","latitude":-6.369028,"event id":3770417,"event date":"26-Jun","country":"Tanzania","event title":"Police Arrest and Extradite Mohammed Ali Mohammed to Uganda","longitude":34.888822,"id":"a640ws0mv0dy","total deaths":0,"group":"Al Shabaab (The Young Islamic Movement)","total injuries":0,"state":"Unknown"},"type":"Feature","geometry":{"type":"Point","coordinates":[34.888822,-6.369028]}}],"is_temporal":false,"author":{"url":"","metadata":"","contact_name":"","contact_address":"","source":"","contact_phone":""},"source":"","pagination":{"sort":null,"start":0,"total":6,"limit":1000000},"state":"complete","tags":"","published":"2014-08-14T17:20:51-04:00","id":201801}