{"type":"FeatureCollection","data_type":"Dataset","url_type":null,"permissions":[{"permissions":{"download":true,"view":true},"group_id":"everyone"}],"classification":null,"title":"20120201 Violent Events - Tanzania","count":5,"stream_id":201868,"contributor":{"url":"http://geocommons.com/users/33152","name":"rberntsson"},"data_attributes":null,"calculation_params":null,"icon_link":null,"link":"http://geocommons.com/overlays/201868.json","extent":[0.0,-6.82292,39.2697,-1.34357],"geometry_types":["point"],"unique_name":null,"name":"20120201 Violent Events - Tanzania","feature_count":5,"description":"","next_feature":null,"is_raster":false,"short_classification":"Y","stats":{"latitude":{"max":-1.3435651,"mean":-4.54040004,"variance":8.5507978372455,"stdev":2.92417472755058,"min":-6.822921,"median":-6.369028},"event id":{"max":3348895,"mean":1937485.4,"variance":1485092101460.3,"stdev":1218643.54979637,"min":1019369,"median":1105706},"longitude":{"max":39.269661,"mean":36.43136572,"variance":6.75911323967725,"stdev":2.59982946357588,"min":34.3643423,"median":34.888822},"total deaths":{"max":12,"mean":3.6,"variance":26.3,"stdev":5.12835256198323,"min":0,"median":1},"total injuries":{"max":80,"mean":19.4,"variance":1166.8,"stdev":34.158454297582,"min":0,"median":7}},"features":[{"properties":{"city":"Dar es Salaam","event type":"Bombing","latitude":-6.822921,"event id":1019369,"event date":"7-Aug","country":"Tanzania","event title":"Al Qaeda Bombs American Embassy in Tanzania","longitude":39.269661,"id":"0","total deaths":12,"group":"Al Qaeda (Afghanistan)","total injuries":80,"state":"Dar es Salaam"},"type":"Feature","geometry":{"type":"Point","coordinates":[39.269661,-6.822921]}},{"properties":{"city":"Tarime","event type":"Armed Assault","latitude":-1.3435651,"event id":1021323,"event date":"7-Oct","country":"Tanzania","event title":null,"longitude":34.3643423,"id":"1","total deaths":1,"group":"Unknown","total injuries":10,"state":"Mara"},"type":"Feature","geometry":{"type":"Point","coordinates":[34.3643423,-1.3435651]}},{"properties":{"city":"Unknown","event type":"Hijacking","latitude":-6.369028,"event id":1105706,"event date":"4-Feb","country":"Tanzania","event title":null,"longitude":34.888822,"id":"3","total deaths":0,"group":"Pirates","total injuries":0,"state":"Unknown"},"type":"Feature","geometry":{"type":"Point","coordinates":[34.888822,-6.369028]}},{"properties":{"city":"Tarime","event type":"Armed Assault","latitude":-1.3435651,"event id":3192134,"event date":"4-Mar","country":"Tanzania","event title":"Five Killed, Seven Injured in Tanzania","longitude":34.3643423,"id":"4","total deaths":5,"group":"Unknown","total injuries":7,"state":"Mara"},"type":"Feature","geometry":{"type":"Point","coordinates":[34.3643423,-1.3435651]}},{"properties":{"city":"Dar es Salaam","event type":"Arson","latitude":-6.822921,"event id":3348895,"event date":"16-May","country":"Tanzania","event title":"US Embassy Targeted in Incendiary Attack in Tanzania","longitude":39.269661,"id":"5","total deaths":0,"group":"Al Qaeda (Afghanistan)","total injuries":0,"state":"Dar es Salaam"},"type":"Feature","geometry":{"type":"Point","coordinates":[39.269661,-6.822921]}}],"is_temporal":false,"author":{"url":"","metadata":"","contact_name":"","contact_address":"","source":"","contact_phone":""},"source":"","pagination":{"sort":null,"start":0,"total":5,"limit":1000000},"state":"complete","tags":"","published":"2014-08-14T17:27:07-04:00","id":201868}