{"type":"FeatureCollection","data_type":"Dataset","url_type":null,"permissions":[{"permissions":{"download":true,"view":true},"group_id":"everyone"}],"classification":null,"title":"HNDMIFIdesign","count":7,"stream_id":201914,"contributor":{"url":"http://geocommons.com/users/35812","name":"karenf"},"data_attributes":null,"calculation_params":null,"icon_link":null,"link":"http://geocommons.com/overlays/201914.json","extent":[-87.849,13.3333,-86.0,15.79],"geometry_types":["point"],"unique_name":null,"name":"HNDMIFIdesign","feature_count":7,"description":"","next_feature":null,"is_raster":false,"short_classification":"Y","stats":{"latitude":{"max":15.79,"mean":14.3192942857143,"variance":0.608418101928571,"stdev":0.780011603714054,"min":13.33333,"median":14.0818},"longitude":{"max":-86.0,"mean":-87.0194414285714,"variance":0.337837353680954,"stdev":0.581237777231448,"min":-87.849,"median":-87.20681}},"features":[{"properties":{"latitude":14.033,"description of target location":"Danli","level":"City","project number":"HO0154","longitude":-86.58333,"id":"a69yvxiha2vp","beneficiary country":"HO"},"type":"Feature","geometry":{"type":"Point","coordinates":[-86.58333,14.033]}},{"properties":{"latitude":13.33333,"description of target location":"Choluteca","level":"First order administrative division: Department","project number":"HO0154","longitude":-87.08333,"id":"a69yvxijgqes","beneficiary country":"HO"},"type":"Feature","geometry":{"type":"Point","coordinates":[-87.08333,13.33333]}},{"properties":{"latitude":14.83333,"description of target location":"Olancho","level":"First order administrative division: Department","project number":"HO0154","longitude":-86.0,"id":"a69yvxkbqk7o","beneficiary country":"HO"},"type":"Feature","geometry":{"type":"Point","coordinates":[-86.0,14.83333]}},{"properties":{"latitude":14.0818,"description of target location":"Tegucigalpa","level":"City","project number":"HO0154","longitude":-87.20681,"id":"a69yvxe05ibk","beneficiary country":"HO"},"type":"Feature","geometry":{"type":"Point","coordinates":[-87.20681,14.0818]}},{"properties":{"latitude":14.0818,"description of target location":"Tegucigalpa","level":"City","project number":"TC9810351","longitude":-87.20681,"id":"a69yvxk1cidq","beneficiary country":"HO"},"type":"Feature","geometry":{"type":"Point","coordinates":[-87.20681,14.0818]}},{"properties":{"latitude":14.0818,"description of target location":"Tegucigalpa","level":"City","project number":"HO0162","longitude":-87.20681,"id":"a69yvxlvcbcg","beneficiary country":"HO"},"type":"Feature","geometry":{"type":"Point","coordinates":[-87.20681,14.0818]}},{"properties":{"latitude":15.79,"description of target location":"Puerto Cortes","level":"Second level administrative division: Municipality","project number":"HO0169","longitude":-87.849,"id":"a69yvxgh9imo","beneficiary country":"HO"},"type":"Feature","geometry":{"type":"Point","coordinates":[-87.849,15.79]}}],"is_temporal":false,"author":{"url":"","metadata":null,"contact_name":null,"contact_address":null,"source":null,"contact_phone":null},"source":"","pagination":{"sort":null,"start":0,"total":7,"limit":1000000},"state":"complete","tags":"","published":"2014-08-14T17:29:03-04:00","id":201914}