{"type":"FeatureCollection","data_type":"Dataset","url_type":null,"permissions":[{"permissions":{"download":true,"view":true},"group_id":"everyone"}],"classification":null,"title":"Cianjur_70150","count":1,"stream_id":202569,"contributor":{"url":"http://geocommons.com/users/39459","name":"jafair"},"data_attributes":null,"calculation_params":null,"icon_link":null,"link":"http://geocommons.com/overlays/202569.json","extent":[107.111,-6.80116,107.111,-6.80116],"geometry_types":["point"],"unique_name":null,"name":"Cianjur_70150","feature_count":1,"description":"Gardu Induk Cianjur 70/150 KV","next_feature":null,"is_raster":false,"short_classification":"Y","stats":{},"features":[{"properties":{"name":"Cianjur 70/150","id":"0"},"type":"Feature","geometry":{"type":"Point","coordinates":[107.1107,-6.80116388888889]}}],"is_temporal":false,"author":{"url":"","metadata":null,"contact_name":null,"contact_address":null,"source":null,"contact_phone":null},"source":"","pagination":{"sort":null,"start":0,"total":1,"limit":1000000},"state":"complete","tags":"","published":"2014-08-14T18:20:12-04:00","id":202569}