{"type":"FeatureCollection","data_type":"Dataset","url_type":null,"permissions":[{"permissions":{"download":true,"view":true},"group_id":"everyone"}],"classification":null,"title":"test","count":3,"stream_id":202780,"contributor":{"url":"http://geocommons.com/users/38174","name":"onlyone509"},"data_attributes":null,"calculation_params":null,"icon_link":null,"link":"http://geocommons.com/overlays/202780.json","extent":[-80.3739,25.7565,-80.373,25.7582],"geometry_types":["point"],"unique_name":null,"name":"test","feature_count":3,"description":"test","next_feature":null,"is_raster":false,"short_classification":"Y","stats":{"25.7589592968917":{"max":25.7582102154118,"mean":25.7573324727186,"variance":7.65010487160106e-07,"stdev":0.00087464877931665,"min":25.7564609510391,"median":25.7573262517048},"-80.373886365128":{"max":-80.3730319545487,"mean":-80.3735060105214,"variance":1.8342505622197e-07,"stdev":0.000428281515153258,"min":-80.3738650149697,"median":-80.3736210620459}},"features":[{"properties":{"25.7589592968917":25.7573262517048,"id":"a67j6i99vaeh","ecs":"Library","-80.373886365128":-80.3738650149697},"type":"Feature","geometry":{"type":"Point","coordinates":[-80.3738650149697,25.7573262517048]}},{"properties":{"25.7589592968917":25.7582102154118,"id":"a67j6hxldkyj","ecs":"a lake","-80.373886365128":-80.3736210620459},"type":"Feature","geometry":{"type":"Point","coordinates":[-80.3736210620459,25.7582102154118]}},{"properties":{"25.7589592968917":25.7564609510391,"id":"a67j6i2rthke","ecs":"GC","-80.373886365128":-80.3730319545487},"type":"Feature","geometry":{"type":"Point","coordinates":[-80.3730319545487,25.7564609510391]}}],"is_temporal":false,"author":{"url":"","metadata":"","contact_name":"","contact_address":"","source":"","contact_phone":""},"source":"","pagination":{"sort":null,"start":0,"total":3,"limit":1000000},"state":"complete","tags":"fiu","published":"2014-08-14T18:36:56-04:00","id":202780}