{"type":"FeatureCollection","data_type":"Dataset","url_type":null,"permissions":[{"permissions":{"download":true,"view":true},"group_id":"everyone"}],"classification":null,"title":"Inlay_Lake","count":1,"stream_id":203150,"contributor":{"url":"http://geocommons.com/users/39658","name":"nanda78"},"data_attributes":null,"calculation_params":null,"icon_link":null,"link":"http://geocommons.com/overlays/203150.json","extent":[96.9102,20.5863,96.9102,20.5863],"geometry_types":["point"],"unique_name":null,"name":"Inlay_Lake","feature_count":1,"description":"","next_feature":null,"is_raster":false,"short_classification":"Y","stats":{},"features":[{"properties":{"name":"Inlay Lake","id":"0"},"type":"Feature","geometry":{"type":"Point","coordinates":[96.910180999862,20.5862909962242]}}],"is_temporal":false,"author":{"url":"","metadata":null,"contact_name":null,"contact_address":null,"source":null,"contact_phone":null},"source":"","pagination":{"sort":null,"start":0,"total":1,"limit":1000000},"state":"complete","tags":"","published":"2014-08-14T18:59:56-04:00","id":203150}