{"type":"FeatureCollection","data_type":"Dataset","url_type":null,"permissions":[{"permissions":{"download":true,"view":true},"group_id":"everyone"}],"classification":null,"title":"International Airports for Central African Republic","count":1,"stream_id":205653,"contributor":{"url":"http://geocommons.com/users/38656","name":"justgio"},"data_attributes":null,"calculation_params":null,"icon_link":null,"link":"http://geocommons.com/overlays/205653.json","extent":[18.5203,4.39611,18.5203,4.39611],"geometry_types":["point"],"unique_name":null,"name":"International Airports for Central African Republic","feature_count":1,"description":"This map presents international airports in the Central African Republic. ","next_feature":null,"is_raster":false,"short_classification":"Y","stats":{"lat":{"max":4.396111,"min":4.396111,"median":4.396111},"long":{"max":18.520279,"min":18.520279,"median":18.520279}},"features":[{"properties":{"airport name":"Bangui Airport","city":"Bangui","surface":"Paved","ariport code":"BGF","international":"Yes","country":"CAR","id":"a656pajvwpfr","lat":4.396111,"long":18.520279,"state":"Bangui"},"type":"Feature","geometry":{"type":"Point","coordinates":[18.520279,4.396111]}}],"is_temporal":false,"author":{"url":"","metadata":"","contact_name":"","contact_address":"","source":"","contact_phone":""},"source":"","pagination":{"sort":null,"start":0,"total":1,"limit":1000000},"state":"complete","tags":"","published":"2014-08-14T22:00:01-04:00","id":205653}