{"type":"FeatureCollection","data_type":"Dataset","url_type":null,"permissions":[{"permissions":{"download":true,"view":true},"group_id":"everyone"}],"classification":null,"title":"Testdatei London","count":8,"stream_id":20779,"contributor":{"url":"http://geocommons.com/users/10662","name":"fanny_ra"},"data_attributes":null,"calculation_params":null,"icon_link":null,"link":"http://geocommons.com/overlays/20779.json","extent":[-0.17783,51.4912,-0.098298,51.5151],"geometry_types":["point"],"unique_name":null,"name":"Testdatei London","feature_count":8,"description":"","next_feature":null,"is_raster":false,"short_classification":"Y","stats":{"latitude":{"max":51.515126,"mean":51.506970375,"variance":7.93202242678591e-05,"stdev":0.00890619022185464,"min":51.49123,"median":51.511914},"fotos":{"max":5.0,"mean":4.75,"variance":0.214285714285714,"stdev":0.462910049886276,"min":4.0,"median":5.0},"longitude":{"max":-0.098298,"mean":-0.128663625,"variance":0.000613418786839286,"stdev":0.0247672926828769,"min":-0.17783,"median":-0.122958}},"features":[{"properties":{"latitude":51.511914,"fotos":5.0,"longitude":-0.122958,"id":"a646f6cu7xmi","poi":"Covent Garden"},"type":"Feature","geometry":{"type":"Point","coordinates":[-0.122958,51.511914]}},{"properties":{"latitude":51.49123,"fotos":5.0,"longitude":-0.137662,"id":"a646f5ztovo3","poi":"Gastronomica"},"type":"Feature","geometry":{"type":"Point","coordinates":[-0.137662,51.49123]}},{"properties":{"latitude":51.504789,"fotos":4.0,"longitude":-0.127223,"id":"a646f6781oiv","poi":"Horse Guards Parade"},"type":"Feature","geometry":{"type":"Point","coordinates":[-0.127223,51.504789]}},{"properties":{"latitude":51.496067,"fotos":5.0,"longitude":-0.10864,"id":"a646f60ksf3e","poi":"Imperial War Museum"},"type":"Feature","geometry":{"type":"Point","coordinates":[-0.10864,51.496067]}},{"properties":{"latitude":51.515126,"fotos":5.0,"longitude":-0.143144,"id":"a646f68k615x","poi":"Oxford Street"},"type":"Feature","geometry":{"type":"Point","coordinates":[-0.143144,51.515126]}},{"properties":{"latitude":51.51321,"fotos":5.0,"longitude":-0.17783,"id":"a646f6dry9y6","poi":"Royal Court Appartments"},"type":"Feature","geometry":{"type":"Point","coordinates":[-0.17783,51.51321]}},{"properties":{"latitude":51.51383,"fotos":5.0,"longitude":-0.098298,"id":"a646f62zuwp4","poi":"St. Paul's Cathedral"},"type":"Feature","geometry":{"type":"Point","coordinates":[-0.098298,51.51383]}},{"properties":{"latitude":51.509597,"fotos":4.0,"longitude":-0.113554,"id":"a646f630rmm8","poi":"Themse"},"type":"Feature","geometry":{"type":"Point","coordinates":[-0.113554,51.509597]}}],"is_temporal":false,"author":{"url":"","metadata":"","contact_name":"","contact_address":"","source":"","contact_phone":""},"source":"","pagination":{"sort":null,"start":0,"total":8,"limit":1000000},"state":"complete","tags":"","published":"2014-08-10T12:10:15-04:00","id":20779}