{"type":"FeatureCollection","data_type":"Dataset","url_type":null,"permissions":[{"permissions":{"download":true,"view":true},"group_id":"everyone"}],"classification":null,"title":"Household income","count":14,"stream_id":20841,"contributor":{"url":"http://geocommons.com/users/10702","name":"rwadhawan"},"data_attributes":null,"calculation_params":null,"icon_link":null,"link":"http://geocommons.com/overlays/20841.json","extent":[-82.5773,27.8636,-82.3729,28.0774],"geometry_types":["point"],"unique_name":null,"name":"Household income","feature_count":14,"description":"","next_feature":null,"is_raster":false,"short_classification":"Y","stats":{"geo_score":{"max":0.714,"mean":0.714,"variance":5.30964070821835e-32,"stdev":2.30426576336549e-16,"min":0.714,"median":0.714},"income":{"max":593863.0,"mean":222464.142857143,"variance":31605678555.2088,"stdev":177779.859813222,"min":5337.0,"median":184743.0}},"features":[{"properties":{"zip":"33602","geo_score":0.714,"id":"a638t4tbozju","geo_precision":"zip","income":236178.0},"type":"Feature","geometry":{"type":"Point","coordinates":[-82.461517,27.950898]}},{"properties":{"zip":"33603","geo_score":0.714,"id":"a638t4qhodul","geo_precision":"zip","income":106585.0},"type":"Feature","geometry":{"type":"Point","coordinates":[-82.463804,27.986147]}},{"properties":{"zip":"33604","geo_score":0.714,"id":"a638t4m93wak","geo_precision":"zip","income":143918.0},"type":"Feature","geometry":{"type":"Point","coordinates":[-82.450928,28.025297]}},{"properties":{"zip":"33605","geo_score":0.714,"id":"a638t4vg3n7c","geo_precision":"zip","income":28984.0},"type":"Feature","geometry":{"type":"Point","coordinates":[-82.435094,27.965021]}},{"properties":{"zip":"33606","geo_score":0.714,"id":"a638t4njirph","geo_precision":"zip","income":593863.0},"type":"Feature","geometry":{"type":"Point","coordinates":[-82.465326,27.930552]}},{"properties":{"zip":"33607","geo_score":0.714,"id":"a638t4jm2xi2","geo_precision":"zip","income":146226.0},"type":"Feature","geometry":{"type":"Point","coordinates":[-82.556868,27.966697]}},{"properties":{"zip":"33609","geo_score":0.714,"id":"a638t4i41cs7","geo_precision":"zip","income":5337.0},"type":"Feature","geometry":{"type":"Point","coordinates":[-82.513067,27.942648]}},{"properties":{"zip":"33610","geo_score":0.714,"id":"a638t4t1rtao","geo_precision":"zip","income":119098.0},"type":"Feature","geometry":{"type":"Point","coordinates":[-82.390604,27.989714]}},{"properties":{"zip":"33611","geo_score":0.714,"id":"a638t4pk72bh","geo_precision":"zip","income":466020.0},"type":"Feature","geometry":{"type":"Point","coordinates":[-82.512017,27.942099]}},{"properties":{"zip":"33612","geo_score":0.714,"id":"a638t4i5wcqb","geo_precision":"zip","income":184743.0},"type":"Feature","geometry":{"type":"Point","coordinates":[-82.471761,28.074183]}},{"properties":{"zip":"33613","geo_score":0.714,"id":"a638t4o62c4l","geo_precision":"zip","income":378042.0},"type":"Feature","geometry":{"type":"Point","coordinates":[-82.444209,28.077403]}},{"properties":{"zip":"33614","geo_score":0.714,"id":"a638t4ri05b0","geo_precision":"zip","income":220004.0},"type":"Feature","geometry":{"type":"Point","coordinates":[-82.372871,27.972521]}},{"properties":{"zip":"33615","geo_score":0.714,"id":"a638t4voryx3","geo_precision":"zip","income":424821.0},"type":"Feature","geometry":{"type":"Point","coordinates":[-82.577319,28.010575]}},{"properties":{"zip":"33616","geo_score":0.714,"id":"a638t4n9blk0","geo_precision":"zip","income":60679.0},"type":"Feature","geometry":{"type":"Point","coordinates":[-82.526763,27.863635]}}],"is_temporal":false,"author":{"url":"","metadata":"","contact_name":"","contact_address":"","source":"","contact_phone":""},"source":"","pagination":{"sort":null,"start":0,"total":14,"limit":1000000},"state":"complete","tags":"","published":"2014-08-10T12:15:06-04:00","id":20841}