{"type":"FeatureCollection","data_type":"Dataset","url_type":null,"permissions":[{"permissions":{"download":true,"view":true},"group_id":"everyone"}],"classification":null,"title":"7_features_4_attributes_-_Copy","count":3,"stream_id":211673,"contributor":{"url":"http://geocommons.com/users/28467","name":"bheberto"},"data_attributes":null,"calculation_params":null,"icon_link":null,"link":"http://geocommons.com/overlays/211673.json","extent":[34.3406,31.4141,34.3854,31.4257],"geometry_types":["point"],"unique_name":null,"name":"7_features_4_attributes_-_Copy","feature_count":3,"description":"","next_feature":null,"is_raster":false,"short_classification":"Y","stats":{"latitude":{"max":31.425733,"mean":31.4204043333333,"variance":3.43859403333465e-05,"stdev":0.00586395262031904,"min":31.414122,"median":31.421358},"a":{"max":999,"mean":337.333333333333,"variance":328358.333333333,"stdev":573.02559570523,"min":4,"median":9},"b":{"max":9,"mean":3.0,"variance":27.0,"stdev":5.19615242270663,"min":0,"median":0},"longitude":{"max":34.385375,"mean":34.3671136666667,"variance":0.000551789382333332,"stdev":0.0234901975796998,"min":34.340614,"median":34.375352}},"features":[{"properties":{"latitude":31.421358,"a":999,"b":0,"longitude":34.385375,"id":"a64dqrdlqc4p"},"type":"Feature","geometry":{"type":"Point","coordinates":[34.385375,31.421358]}},{"properties":{"latitude":31.425733,"a":4,"b":0,"longitude":34.340614,"id":"a64dqrb21huf"},"type":"Feature","geometry":{"type":"Point","coordinates":[34.340614,31.425733]}},{"properties":{"latitude":31.414122,"a":9,"b":9,"longitude":34.375352,"id":"a64dqr88c1s3"},"type":"Feature","geometry":{"type":"Point","coordinates":[34.375352,31.414122]}}],"is_temporal":false,"author":{"url":"","metadata":null,"contact_name":null,"contact_address":null,"source":null,"contact_phone":null},"source":"","pagination":{"sort":null,"start":0,"total":3,"limit":1000000},"state":"complete","tags":"","published":"2014-08-14T17:40:05-04:00","id":211673}