{"type":"FeatureCollection","data_type":"Dataset","url_type":null,"permissions":[{"permissions":{"download":true,"view":true},"group_id":"everyone"}],"classification":null,"title":"Book2","count":2,"stream_id":214431,"contributor":{"url":"http://geocommons.com/users/41718","name":"bamostacho"},"data_attributes":null,"calculation_params":null,"icon_link":null,"link":"http://geocommons.com/overlays/214431.json","extent":[120.733,11.2267,122.925,13.9833],"geometry_types":["point"],"unique_name":null,"name":"Book2","feature_count":2,"description":"","next_feature":null,"is_raster":false,"short_classification":"Y","stats":{},"features":[{"properties":{"geo_score":1.0,"calaca":"Lemery","id":"a6eped4casut","geo_precision":"zip"},"type":"Feature","geometry":{"type":"Point","coordinates":[122.925,11.2266667]}},{"properties":{"geo_score":1.0,"calaca":"Balayan","id":"a6epecund7f7","geo_precision":"zip"},"type":"Feature","geometry":{"type":"Point","coordinates":[120.7333333,13.9833333]}}],"is_temporal":false,"author":{"url":"","metadata":"","contact_name":"","contact_address":"","source":"","contact_phone":""},"source":"","pagination":{"sort":null,"start":0,"total":2,"limit":1000000},"state":"complete","tags":"","published":"2014-08-14T21:53:03-04:00","id":214431}