{"type":"FeatureCollection","data_type":"Dataset","url_type":null,"permissions":[{"permissions":{"download":true,"view":true},"group_id":"everyone"}],"classification":null,"title":"Students","count":11,"stream_id":214626,"contributor":{"url":"http://geocommons.com/users/41694","name":"fairfur"},"data_attributes":null,"calculation_params":null,"icon_link":null,"link":"http://geocommons.com/overlays/214626.json","extent":[121.062,14.6492,121.074,14.6593],"geometry_types":["point"],"unique_name":null,"name":"Students","feature_count":11,"description":"","next_feature":null,"is_raster":false,"short_classification":"Y","stats":{"latitude":{"max":14.659264,"mean":14.654276,"variance":8.72499960000171e-06,"stdev":0.00295381102983954,"min":14.649216,"median":14.653534},"longitude":{"max":121.073498,"mean":121.068005727273,"variance":1.74581312181782e-05,"stdev":0.00417829285931206,"min":121.061964,"median":121.069395},"number of students":{"max":4,"mean":2.09090909090909,"variance":1.69090909090909,"stdev":1.300349603341,"min":1,"median":2}},"features":[{"properties":{"latitude":14.656503,"longitude":121.069513,"id":"a66a0po77vw0","building":"Eng'g","number of students":4},"type":"Feature","geometry":{"type":"Point","coordinates":[121.069513,14.656503]}},{"properties":{"latitude":14.657029,"longitude":121.063794,"id":"a66a0pox2wr9","building":"CSWCD","number of students":1},"type":"Feature","geometry":{"type":"Point","coordinates":[121.063794,14.657029]}},{"properties":{"latitude":14.656705,"longitude":121.064562,"id":"a66a0priv05k","building":"CMC","number of students":4},"type":"Feature","geometry":{"type":"Point","coordinates":[121.064562,14.656705]}},{"properties":{"latitude":14.65259,"longitude":121.067378,"id":"a66a0pmjqbs7","building":"CAL","number of students":1},"type":"Feature","geometry":{"type":"Point","coordinates":[121.067378,14.65259]}},{"properties":{"latitude":14.65165,"longitude":121.073107,"id":"a66a0ppn6qxx","building":"CHE","number of students":4},"type":"Feature","geometry":{"type":"Point","coordinates":[121.073107,14.65165]}},{"properties":{"latitude":14.649216,"longitude":121.069395,"id":"a66a0pco5dwy","building":"CS","number of students":2},"type":"Feature","geometry":{"type":"Point","coordinates":[121.069395,14.649216]}},{"properties":{"latitude":14.659264,"longitude":121.062801,"id":"a66a0ph265wt","building":"CHK","number of students":2},"type":"Feature","geometry":{"type":"Point","coordinates":[121.062801,14.659264]}},{"properties":{"latitude":14.653534,"longitude":121.069937,"id":"a66a0pby6mzw","building":"CSSP","number of students":2},"type":"Feature","geometry":{"type":"Point","coordinates":[121.069937,14.653534]}},{"properties":{"latitude":14.651738,"longitude":121.061964,"id":"a66a0pkpyrgo","building":"CFA","number of students":1},"type":"Feature","geometry":{"type":"Point","coordinates":[121.061964,14.651738]}},{"properties":{"latitude":14.655288,"longitude":121.073498,"id":"a66a0pknvzrx","building":"CBA","number of students":1},"type":"Feature","geometry":{"type":"Point","coordinates":[121.073498,14.655288]}},{"properties":{"latitude":14.653519,"longitude":121.072114,"id":"a66a0po0jkti","building":"Educ","number of students":1},"type":"Feature","geometry":{"type":"Point","coordinates":[121.072114,14.653519]}}],"is_temporal":false,"author":{"url":"","metadata":"","contact_name":"","contact_address":"","source":"","contact_phone":""},"source":"","pagination":{"sort":null,"start":0,"total":11,"limit":1000000},"state":"complete","tags":"","published":"2014-08-14T22:06:10-04:00","id":214626}