{"type":"FeatureCollection","data_type":"Dataset","url_type":null,"permissions":[{"permissions":{"download":true,"view":true},"group_id":"everyone"}],"classification":null,"title":"mbari","count":3,"stream_id":219475,"contributor":{"url":"http://geocommons.com/users/24977","name":"bhurwitz"},"data_attributes":null,"calculation_params":null,"icon_link":null,"link":"http://geocommons.com/overlays/219475.json","extent":[-129.428,33.2868,-121.847,36.7968],"geometry_types":["point"],"unique_name":null,"name":"mbari","feature_count":3,"description":"","next_feature":null,"is_raster":false,"short_classification":"Y","stats":{"latitude":{"max":36.79683,"mean":35.40333,"variance":3.47207175,"stdev":1.86334960487827,"min":33.28683,"median":36.12633},"longitude":{"max":-121.84667,"mean":-124.921833333333,"variance":15.9069284222333,"stdev":3.98834908480104,"min":-129.42833,"median":-123.4905}},"features":[{"properties":{"latitude":36.79683,"longitude":-121.84667,"id":"a625uypa9bzr"},"type":"Feature","geometry":{"type":"Point","coordinates":[-121.84667,36.79683]}},{"properties":{"latitude":36.12633,"longitude":-123.4905,"id":"a625uyasmyjb"},"type":"Feature","geometry":{"type":"Point","coordinates":[-123.4905,36.12633]}},{"properties":{"latitude":33.28683,"longitude":-129.42833,"id":"a625uyhrrqky"},"type":"Feature","geometry":{"type":"Point","coordinates":[-129.42833,33.28683]}}],"is_temporal":false,"author":{"url":"","metadata":"","contact_name":"","contact_address":"","source":"","contact_phone":""},"source":"","pagination":{"sort":null,"start":0,"total":3,"limit":1000000},"state":"complete","tags":"","published":"2014-08-15T04:12:22-04:00","id":219475}