{"type":"FeatureCollection","data_type":"Dataset","url_type":null,"permissions":[{"permissions":{"download":true,"view":true},"group_id":"everyone"}],"classification":null,"title":"robbery 2010","count":3,"stream_id":219963,"contributor":{"url":"http://geocommons.com/users/42302","name":"hillproject"},"data_attributes":null,"calculation_params":null,"icon_link":null,"link":"http://geocommons.com/overlays/219963.json","extent":[-83.2783,41.1088,-83.1759,41.1173],"geometry_types":["point"],"unique_name":null,"name":"robbery 2010","feature_count":3,"description":"","next_feature":null,"is_raster":false,"short_classification":"Y","stats":{"date":{"max":"2010/12/07 13:21:12 -0500","mean":"2010/08/12 17:35:46 -0400","variance":113717336525823.0,"stdev":10663833.106619,"min":"2010/04/05 15:47:09 -0400","median":"2010/08/24 22:38:57 -0400"},"unit":{"max":648,"mean":258.0,"variance":114075.0,"stdev":337.749907475931,"min":63,"median":63},"disposition":{"max":400,"mean":266.666666666667,"variance":13333.3333333333,"stdev":115.470053837925,"min":200,"median":200},"cfs":{"max":4,"mean":4.0,"variance":0.0,"stdev":0.0,"min":4,"median":4},"call#":{"max":10.011187,"mean":10.0072916666667,"variance":1.72463003333325e-05,"stdev":0.00415286652004763,"min":10.002922,"median":10.007766}},"features":[{"properties":{"officer":"JDW","city":"Tiffin","zip":"44883","date":{"end_time":"2010/12/07 13:21:13 -0500","original":"12/7/2010 1:21:12 PM","granularity":"sec","time":"2010/12/07 13:21:12 -0500"},"geo_score":0.582,"unit":648,"disposition":400,"cfs":4,"call#":10.011187,"id":"a64n95h0pmct","geo_precision":"street","address":"2801 W Sr 18","state":"OH","juris":"PD"},"type":"Feature","geometry":{"type":"Point","coordinates":[-83.278292,41.108823]}},{"properties":{"officer":"GTM","city":"Tiffin","zip":"44883","date":{"end_time":"2010/08/24 22:38:58 -0400","original":"8/24/2010 10:38:57 PM","granularity":"sec","time":"2010/08/24 22:38:57 -0400"},"geo_score":0.878,"unit":63,"disposition":200,"cfs":4,"call#":10.007766,"id":"a64n95b0m489","geo_precision":"range","address":"35 Fairfield Av","state":"OH","juris":"PD"},"type":"Feature","geometry":{"type":"Point","coordinates":[-83.191283,41.117335]}},{"properties":{"officer":"DGH","city":"Tiffin","zip":"44883","date":{"end_time":"2010/04/05 15:47:10 -0400","original":"4/5/2010 3:47:09 PM","granularity":"sec","time":"2010/04/05 15:47:09 -0400"},"geo_score":0.902,"unit":63,"disposition":200,"cfs":4,"call#":10.002922,"id":"a64n957ton1y","geo_precision":"range","address":"260 S Washington St","state":"OH","juris":"PD"},"type":"Feature","geometry":{"type":"Point","coordinates":[-83.175893,41.110366]}}],"is_temporal":true,"author":{"url":"","metadata":"","contact_name":"","contact_address":"","source":"","contact_phone":""},"source":"","pagination":{"sort":null,"start":0,"total":3,"limit":1000000},"state":"complete","tags":"","published":"2014-08-15T04:29:16-04:00","id":219963}