{"type":"FeatureCollection","data_type":"Dataset","url_type":null,"permissions":[{"permissions":{"download":true,"view":true},"group_id":"everyone"}],"classification":null,"title":"Alakuddi RMHC","count":1,"stream_id":220404,"contributor":{"url":"http://geocommons.com/users/29139","name":"sabyasachi"},"data_attributes":null,"calculation_params":null,"icon_link":null,"link":"http://geocommons.com/overlays/220404.json","extent":[79.0531,10.774,79.0531,10.774],"geometry_types":["point"],"unique_name":null,"name":"Alakuddi RMHC","feature_count":1,"description":"","next_feature":null,"is_raster":false,"short_classification":"Y","stats":{"latitude":{"max":10.77405,"min":10.77405,"median":10.77405},"longitude":{"max":79.05306,"min":79.05306,"median":79.05306}},"features":[{"properties":{"latitude":10.77405,"organisation_hh_id":"Alakuddi RMHC","longitude":79.05306,"id":"a6242t4q06dy"},"type":"Feature","geometry":{"type":"Point","coordinates":[79.05306,10.77405]}}],"is_temporal":false,"author":{"url":"","metadata":"","contact_name":"","contact_address":"","source":"","contact_phone":""},"source":"","pagination":{"sort":null,"start":0,"total":1,"limit":1000000},"state":"complete","tags":"alakuddi","published":"2014-08-14T15:21:11-04:00","id":220404}