{"type":"FeatureCollection","data_type":"Dataset","url_type":null,"permissions":[{"permissions":{"download":true,"view":true},"group_id":"everyone"}],"classification":null,"title":"Lower_North_Fork_Wildfire_2","count":1,"stream_id":220700,"contributor":{"url":"http://geocommons.com/users/28467","name":"bheberto"},"data_attributes":null,"calculation_params":null,"icon_link":null,"link":"http://geocommons.com/overlays/220700.json","extent":[-105.304,39.5467,-105.304,39.5467],"geometry_types":["point"],"unique_name":null,"name":"Lower_North_Fork_Wildfire_2","feature_count":1,"description":"","next_feature":null,"is_raster":false,"short_classification":"Y","stats":{},"features":[{"properties":{"name":"Evacuation Shelter as of 6:00PM on 3/27/12","description":"The West Jefferson Middle School will become the evacuation shelter at 6:00 PM.  The evacuation shelter located at Conifer High School will shut down at 6:00PM.  The move is being made in order to allow the Incident Management Team to set up their Command Post at the larger facilities available at Conifer High.  500+ firefighters will also be sharing Conifer High along with the Incident Management Team.","id":"0"},"type":"Feature","geometry":{"type":"Point","coordinates":[-105.304382,39.546726]}}],"is_temporal":false,"author":{"url":"","metadata":null,"contact_name":null,"contact_address":null,"source":null,"contact_phone":null},"source":"","pagination":{"sort":null,"start":0,"total":1,"limit":1000000},"state":"complete","tags":"","published":"2014-08-14T15:40:08-04:00","id":220700}