{"type":"FeatureCollection","data_type":"Dataset","url_type":null,"permissions":[{"permissions":{"download":true,"view":true},"group_id":"everyone"}],"classification":null,"title":"MT_Towns","count":8,"stream_id":227172,"contributor":{"url":"http://geocommons.com/users/18171","name":"clarefitz"},"data_attributes":null,"calculation_params":null,"icon_link":null,"link":"http://geocommons.com/overlays/227172.json","extent":[14.5164,35.8856,14.5164,35.8856],"geometry_types":["point"],"unique_name":null,"name":"MT_Towns","feature_count":8,"description":"","next_feature":null,"is_raster":false,"short_classification":"Y","stats":{},"features":[{"properties":{"geo_score":0.0,"town":"Florence","id":"a62jfrk9gcoe","geo_precision":"unmatched","state":"Montana"},"type":"Feature","geometry":null},{"properties":{"geo_score":0.945,"town":"Hamilton","id":"a62jfrirwkrn","geo_precision":"zip","state":"Montana"},"type":"Feature","geometry":{"type":"Point","coordinates":[14.5163889,35.8855556]}},{"properties":{"geo_score":0.0,"town":"Pablo","id":"a62jfrd6pqvt","geo_precision":"unmatched","state":"Montana"},"type":"Feature","geometry":null},{"properties":{"geo_score":0.0,"town":"Bozeman","id":"a62jfrml7x4m","geo_precision":"unmatched","state":"Montana"},"type":"Feature","geometry":null},{"properties":{"geo_score":0.0,"town":"Butte","id":"a62jfrg3ibsa","geo_precision":"unmatched","state":"Montana"},"type":"Feature","geometry":null},{"properties":{"geo_score":0.0,"town":"Helena","id":"a62jfrfnjtl3","geo_precision":"unmatched","state":"Montana"},"type":"Feature","geometry":null},{"properties":{"geo_score":0.0,"town":"Whitefish","id":"a62jfrco818f","geo_precision":"unmatched","state":"Montana"},"type":"Feature","geometry":null},{"properties":{"geo_score":0.0,"town":"Dillon","id":"a62jfre32s2q","geo_precision":"unmatched","state":"Montana"},"type":"Feature","geometry":null}],"is_temporal":false,"author":{"url":"","metadata":null,"contact_name":null,"contact_address":null,"source":null,"contact_phone":null},"source":"","pagination":{"sort":null,"start":0,"total":8,"limit":1000000},"state":"complete","tags":"","published":"2014-08-14T23:51:05-04:00","id":227172}