{"type":"FeatureCollection","data_type":"Dataset","url_type":null,"permissions":[{"permissions":{"download":true,"view":true},"group_id":"everyone"}],"classification":null,"title":"pre-1950","count":3,"stream_id":228299,"contributor":{"url":"http://geocommons.com/users/8981","name":"mgilbert"},"data_attributes":null,"calculation_params":null,"icon_link":null,"link":"http://geocommons.com/overlays/228299.json","extent":[100.393,45.0599,106.917,50.5212],"geometry_types":["point"],"unique_name":null,"name":"pre-1950","feature_count":3,"description":"","next_feature":null,"is_raster":false,"short_classification":"Y","stats":{"latitude":{"max":50.5212,"mean":47.8325766666667,"variance":7.46186241543333,"stdev":2.73164097484156,"min":45.05986,"median":47.91667},"longitude":{"max":106.91667,"mean":102.677603333333,"variance":13.5044731558333,"stdev":3.67484328316642,"min":100.39312,"median":100.72302}},"features":[{"properties":{"column_10":null,"latitude":50.5212,"column_11":null,"column_12":null,"column_7":null,"column_13":null,"column_8":null,"date range":"pre-1950","column_9":null,"general-specific":"Specific","longitude":100.39312,"id":"a6aenqdpqyf7","wetland type":"Lake","location":"Khovsgol Nuur"},"type":"Feature","geometry":{"type":"Point","coordinates":[100.39312,50.5212]}},{"properties":{"column_10":null,"latitude":45.05986,"column_11":null,"column_12":null,"column_7":null,"column_13":null,"column_8":null,"date range":"pre-1950","column_9":null,"general-specific":"Specific","longitude":100.72302,"id":"a6aenpznmafk","wetland type":"Lake","location":"Orog Nuur"},"type":"Feature","geometry":{"type":"Point","coordinates":[100.72302,45.05986]}},{"properties":{"column_10":null,"latitude":47.91667,"column_11":null,"column_12":null,"column_7":null,"column_13":null,"column_8":null,"date range":"pre-1950","column_9":null,"general-specific":"Specific","longitude":106.91667,"id":"a6aenq35ktyw","wetland type":"River","location":"Urguu (Ulaanbaatar)"},"type":"Feature","geometry":{"type":"Point","coordinates":[106.91667,47.91667]}}],"is_temporal":false,"author":{"url":"","metadata":"","contact_name":"","contact_address":"","source":"","contact_phone":""},"source":"","pagination":{"sort":null,"start":0,"total":3,"limit":1000000},"state":"complete","tags":"","published":"2014-08-15T00:52:12-04:00","id":228299}