{"type":"FeatureCollection","data_type":"Dataset","url_type":null,"permissions":[{"permissions":{"download":true,"view":true},"group_id":"everyone"}],"classification":null,"title":"Fasilitas Kesehatan","count":6,"stream_id":228238,"contributor":{"url":"http://geocommons.com/users/41143","name":"iqnaul"},"data_attributes":null,"calculation_params":null,"icon_link":null,"link":"http://geocommons.com/overlays/228238.json","extent":[110.362,-7.82568,110.403,-7.75782],"geometry_types":["point"],"unique_name":null,"name":"Fasilitas Kesehatan","feature_count":6,"description":"","next_feature":null,"is_raster":false,"short_classification":"Y","stats":{},"features":[{"properties":{"Keterangan":"Rumah Sakit Panti Rapih","Penjelasan":"http://www.pantirapih.or.id/","id":"0"},"type":"Feature","geometry":{"type":"Point","coordinates":[110.377513977014,-7.77262542068927]}},{"properties":{"Keterangan":"Rumah Sakit Bethesda","Penjelasan":"http://www.bethesda.or.id/","id":"1"},"type":"Feature","geometry":{"type":"Point","coordinates":[110.377267670378,-7.78344230492107]}},{"properties":{"Keterangan":"Rumah Sakit PKU Muhammadiyah","Penjelasan":"http://www.rspkujogja.com/","id":"2"},"type":"Feature","geometry":{"type":"Point","coordinates":[110.362369124903,-7.80095122764411]}},{"properties":{"Keterangan":"Rumah Sakit Sardjito","Penjelasan":"http://sardjitohospital.co.id/","id":"3"},"type":"Feature","geometry":{"type":"Point","coordinates":[110.374501460757,-7.76560510280157]}},{"properties":{"Keterangan":"JIH","Penjelasan":"http://www.rs-jih.com/","id":"4"},"type":"Feature","geometry":{"type":"Point","coordinates":[110.403471122601,-7.75782294037649]}},{"properties":{"Keterangan":"Rumah Sakit Umum Daerah Kota Yogyakarta","Penjelasan":null,"id":"5"},"type":"Feature","geometry":{"type":"Point","coordinates":[110.378032970088,-7.82568145363096]}}],"is_temporal":false,"author":{"url":"","metadata":"","contact_name":"","contact_address":"","source":"","contact_phone":""},"source":"","pagination":{"sort":null,"start":0,"total":6,"limit":1000000},"state":"complete","tags":"diy,indonesia,jogjakarta,yogyakarta","published":"2014-08-15T00:50:08-04:00","id":228238}