{"type":"FeatureCollection","data_type":"Dataset","url_type":null,"permissions":[{"permissions":{"download":true,"view":true},"group_id":"everyone"}],"classification":null,"title":"pacific coast geocommons error","count":1,"stream_id":230164,"contributor":{"url":"http://geocommons.com/users/3645","name":"semprebon"},"data_attributes":null,"calculation_params":null,"icon_link":null,"link":"http://geocommons.com/overlays/230164.json","extent":[-118.375,34.2838,-118.375,34.2838],"geometry_types":["point"],"unique_name":"","name":"pacific coast geocommons error","feature_count":1,"description":"","next_feature":null,"is_raster":false,"short_classification":"Y","stats":{},"features":[{"properties":{"city":"Thousand Oaks","name of competitor":"Pacific Coast Title","zip":"91362","geo_score":0.359,"street address":"1204 East Thousand Oaks","id":"a633wtadf2wo","geo_precision":"street"},"type":"Feature","geometry":{"type":"Point","coordinates":[-118.375278,34.283823]}}],"is_temporal":false,"author":{"url":"","metadata":"","contact_name":"","contact_address":"","source":"","contact_phone":""},"source":"","pagination":{"sort":null,"start":0,"total":1,"limit":1000000},"state":"complete","tags":"","published":"2014-08-14T15:04:23-04:00","id":230164}