{"type":"FeatureCollection","data_type":"Dataset","url_type":null,"permissions":[{"permissions":{"download":true,"view":true},"group_id":"everyone"}],"classification":null,"title":"SF S-M 2011","count":1,"stream_id":233345,"contributor":{"url":"http://geocommons.com/users/38281","name":"briantalbot"},"data_attributes":null,"calculation_params":null,"icon_link":null,"link":"http://geocommons.com/overlays/233345.json","extent":[-122.406,37.782,-122.406,37.782],"geometry_types":["point"],"unique_name":null,"name":"SF S-M 2011","feature_count":1,"description":"","next_feature":null,"is_raster":false,"short_classification":"Y","stats":{"latitude":{"max":37.781989,"min":37.781989,"median":37.781989},"longitude":{"max":-122.405515,"min":-122.405515,"median":-122.405515},"transaction sf":{"max":349286,"min":349286,"median":349286}},"features":[{"properties":{"name":"Wells Fargo Operations Center","latitude":37.781989,"class":"B","longitude":-122.405515,"id":"a63zpzpcvyhq","transaction date":"11/1/2011","transaction type":"Sold to User","transaction sf":349286,"tenant":"University of the Pacific"},"type":"Feature","geometry":{"type":"Point","coordinates":[-122.405515,37.781989]}}],"is_temporal":false,"author":{"url":"","metadata":"","contact_name":"","contact_address":"","source":"","contact_phone":""},"source":"","pagination":{"sort":null,"start":0,"total":1,"limit":1000000},"state":"complete","tags":"","published":"2014-08-14T19:18:27-04:00","id":233345}