{"type":"FeatureCollection","data_type":"Dataset","url_type":null,"permissions":[{"permissions":{"download":true,"view":true},"group_id":"everyone"}],"classification":null,"title":"population in California","count":1,"stream_id":235011,"contributor":{"url":"http://geocommons.com/users/43817","name":"axlpig"},"data_attributes":null,"calculation_params":null,"icon_link":null,"link":"http://geocommons.com/overlays/235011.json","extent":[-119.746,36.17,-119.746,36.17],"geometry_types":["point"],"unique_name":null,"name":"population in California","feature_count":1,"description":"","next_feature":null,"is_raster":false,"short_classification":"Y","stats":{"differnetincat1":{"max":0.017716744,"min":0.017716744,"median":0.017716744},"latitude":{"max":36.17,"min":36.17,"median":36.17},"age020cat12000":{"max":10725400,"min":10725400,"median":10725400},"cat12009":{"max":0.298931563,"min":0.298931563,"median":0.298931563},"cat12000":{"max":0.316648307,"min":0.316648307,"median":0.316648307},"differnetincat4":{"max":-0.015683092,"min":-0.015683092,"median":-0.015683092},"cat42009":{"max":0.148249981,"min":0.148249981,"median":0.148249981},"cat42000":{"max":0.132566889,"min":0.132566889,"median":0.132566889},"longitude":{"max":-119.7462,"min":-119.7462,"median":-119.7462},"age60cat42009":{"max":5479566,"min":5479566,"median":5479566},"age020cat12009":{"max":11049008,"min":11049008,"median":11049008},"age60cat42000":{"max":4490259,"min":4490259,"median":4490259}},"features":[{"properties":{"name":"state:","differnetincat1":0.017716744,"latitude":36.17,"age020cat12000":10725400,"cat12009":0.298931563,"cat12000":0.316648307,"differnetincat4":-0.015683092,"cat42009":0.148249981,"cat42000":0.132566889,"longitude":-119.7462,"age60cat42009":5479566,"id":"a69zwu8grj0v","state":"California","age020cat12009":11049008,"age60cat42000":4490259},"type":"Feature","geometry":{"type":"Point","coordinates":[-119.7462,36.17]}}],"is_temporal":false,"author":{"url":"","metadata":"","contact_name":"axlpig","contact_address":"","source":"","contact_phone":""},"source":"","pagination":{"sort":null,"start":0,"total":1,"limit":1000000},"state":"complete","tags":"","published":"2014-08-14T21:41:51-04:00","id":235011}