{"type":"FeatureCollection","data_type":"Dataset","url_type":null,"permissions":[{"permissions":{"download":true,"view":true},"group_id":"everyone"}],"classification":null,"title":"Address_SKED","count":1,"stream_id":236679,"contributor":{"url":"http://geocommons.com/users/44657","name":"UKAppCtr"},"data_attributes":null,"calculation_params":null,"icon_link":null,"link":"http://geocommons.com/overlays/236679.json","extent":[-84.6218,37.0621,-84.6218,37.0621],"geometry_types":["point"],"unique_name":null,"name":"Address_SKED","feature_count":1,"description":"","next_feature":null,"is_raster":false,"short_classification":"Y","stats":{},"features":[{"properties":{"city":"Somerset","zip":"42501","geo_score":0.678,"mission statement":"The Southeast Kentucky Economic Development Corporation (SKED) is a community development organization to create employment opportunities in a 42-county service area in Southern and Eastern Kentucky. It accomplishes this mission by recruiting new businesses, making direct loans, and providing economic development services to local communities.","website":"southeastkentucky.com","phone":"(606) 677-6100","street":"2292 South Highway 27","id":"a62j1js6s2p5","geo_precision":"street","state":"Kentucky"},"type":"Feature","geometry":{"type":"Point","coordinates":[-84.621844,37.062129]}}],"is_temporal":false,"author":{"url":"","metadata":null,"contact_name":null,"contact_address":null,"source":null,"contact_phone":null},"source":"","pagination":{"sort":null,"start":0,"total":1,"limit":1000000},"state":"complete","tags":"","published":"2014-08-15T00:40:55-04:00","id":236679}