{"type":"FeatureCollection","data_type":"Dataset","url_type":null,"permissions":[{"permissions":{"download":true,"view":true},"group_id":"everyone"}],"classification":null,"title":"Tel Aviv NonProfit Advice","count":2,"stream_id":237163,"contributor":{"url":"http://geocommons.com/users/159","name":"ajturner"},"data_attributes":null,"calculation_params":null,"icon_link":null,"link":"http://geocommons.com/overlays/237163.json","extent":[34.7751,32.058,34.7887,32.0621],"geometry_types":["point"],"unique_name":"","name":"Tel Aviv NonProfit Advice","feature_count":2,"description":"","next_feature":null,"is_raster":false,"short_classification":"Y","stats":{"lon":{"max":34.788743,"mean":34.7819415,"variance":9.25208044999491e-05,"stdev":0.00961877354447796,"min":34.77514,"median":34.788743},"lat":{"max":32.062062,"mean":32.0600175,"variance":8.35996050000185e-06,"stdev":0.00289135962827211,"min":32.057973,"median":32.062062}},"features":[{"properties":{"lon":34.788743,"name":"yedid","category":"Advice","fax":"03-6885124","phone":"03-6885126/7","id":"0","lat":32.062062,"address":"רח' השלושה 3, שכונת יד אליהו תל אביב","email":"Telaviv@yedid.org.il"},"type":"Feature","geometry":{"type":"Point","coordinates":[34.788743,32.062062]}},{"properties":{"lon":34.77514,"name":"בבית אחותי","category":"Advice","fax":null,"phone":"03-6870545","id":"1","lat":32.057973,"address":"רחוב מטלון 70, דרום תל אביב","email":null},"type":"Feature","geometry":{"type":"Point","coordinates":[34.77514,32.057973]}}],"is_temporal":false,"author":{"url":"http://hemshech.org","metadata":"","contact_name":"","contact_address":"","source":"","contact_phone":""},"source":"http://hemshech.org","pagination":{"sort":null,"start":0,"total":2,"limit":1000000},"state":"complete","tags":"","published":"2014-08-15T01:22:36-04:00","id":237163}