{"type":"FeatureCollection","data_type":"Dataset","url_type":null,"permissions":[{"permissions":{"download":true,"view":true},"group_id":"everyone"}],"classification":null,"title":"Address_KEF","count":1,"stream_id":237477,"contributor":{"url":"http://geocommons.com/users/44657","name":"UKAppCtr"},"data_attributes":null,"calculation_params":null,"icon_link":null,"link":"http://geocommons.com/overlays/237477.json","extent":[-84.4989,38.0465,-84.4989,38.0465],"geometry_types":["point"],"unique_name":null,"name":"Address_KEF","feature_count":1,"description":"","next_feature":null,"is_raster":false,"short_classification":"Y","stats":{},"features":[{"properties":{"city":"Lexington","zip":"40507","geo_score":1.0,"mission statement":"For the purpose of the Kentucky Enterprise Fund, companies must be categorized in one of the following industry sectors: Biosciences (BIO), Environmental and Energy Technologies (EET), Human Health and Development (HHD), Information Technology and Communications (ITC), Materials Science and Advanced Manufacturing (MSAM).","website":"http://startups.kstc.com/images/resource_docs/KEF%20Guidelines.pdf","phone":"(859) 233-3502","street":"200 West Vine Street","id":"a69ibwcz9tzp","geo_precision":"range","state":"Kentucky"},"type":"Feature","geometry":{"type":"Point","coordinates":[-84.498854,38.046526]}}],"is_temporal":false,"author":{"url":"","metadata":null,"contact_name":null,"contact_address":null,"source":null,"contact_phone":null},"source":"","pagination":{"sort":null,"start":0,"total":1,"limit":1000000},"state":"complete","tags":"","published":"2014-08-15T02:01:11-04:00","id":237477}