{"type":"FeatureCollection","data_type":"Dataset","url_type":null,"permissions":[{"permissions":{"download":true,"view":true},"group_id":"everyone"}],"classification":null,"title":"Eventos","count":1,"stream_id":242777,"contributor":{"url":"http://geocommons.com/users/41748","name":"pvista2010"},"data_attributes":null,"calculation_params":null,"icon_link":null,"link":"http://geocommons.com/overlays/242777.json","extent":[-46.7199,-23.3161,-46.7199,-23.3161],"geometry_types":["point"],"unique_name":null,"name":"Eventos","feature_count":1,"description":"","next_feature":null,"is_raster":false,"short_classification":"Y","stats":{},"features":[{"properties":{"description":"Kairos\nFestas e Eventos\nAv. Sete de Setembro","id":"0"},"type":"Feature","geometry":{"type":"Point","coordinates":[-46.7198963132719,-23.3161137809152]}}],"is_temporal":false,"author":{"url":"","metadata":null,"contact_name":null,"contact_address":null,"source":null,"contact_phone":null},"source":"","pagination":{"sort":null,"start":0,"total":1,"limit":1000000},"state":"complete","tags":"","published":"2014-08-14T19:00:31-04:00","id":242777}