{"type":"FeatureCollection","data_type":"Dataset","url_type":null,"permissions":[{"permissions":{"download":true,"view":true},"group_id":"everyone"}],"classification":null,"title":"NZCourse","count":27,"stream_id":242847,"contributor":{"url":"http://geocommons.com/users/45948","name":"jillaclark"},"data_attributes":null,"calculation_params":null,"icon_link":null,"link":"http://geocommons.com/overlays/242847.json","extent":[174.923,-41.2552,174.937,-41.2409],"geometry_types":["point"],"unique_name":null,"name":"NZCourse","feature_count":27,"description":"","next_feature":null,"is_raster":false,"short_classification":"Y","stats":{},"features":[{"properties":{"name":"W1","description":"Control point","id":"0"},"type":"Feature","geometry":{"type":"Point","coordinates":[174.9331,-41.251475]}},{"properties":{"name":"W10","description":"Control point","id":"1"},"type":"Feature","geometry":{"type":"Point","coordinates":[174.934833,-41.243564]}},{"properties":{"name":"W11","description":"Control point","id":"2"},"type":"Feature","geometry":{"type":"Point","coordinates":[174.931298,-41.254211]}},{"properties":{"name":"W12","description":"Control point","id":"3"},"type":"Feature","geometry":{"type":"Point","coordinates":[174.924902,-41.2461]}},{"properties":{"name":"W13","description":"Control point","id":"4"},"type":"Feature","geometry":{"type":"Point","coordinates":[174.928128,-41.252572]}},{"properties":{"name":"W14","description":"Control point","id":"5"},"type":"Feature","geometry":{"type":"Point","coordinates":[174.926615,-41.243599]}},{"properties":{"name":"W15","description":"Control point","id":"6"},"type":"Feature","geometry":{"type":"Point","coordinates":[174.925784,-41.247956]}},{"properties":{"name":"W16","description":"Control point","id":"7"},"type":"Feature","geometry":{"type":"Point","coordinates":[174.936145,-41.250336]}},{"properties":{"name":"W17","description":"Control point for enlarged prin","id":"8"},"type":"Feature","geometry":{"type":"Point","coordinates":[174.925822,-41.251861]}},{"properties":{"name":"W18","description":"Control point","id":"9"},"type":"Feature","geometry":{"type":"Point","coordinates":[174.932205,-41.245695]}},{"properties":{"name":"W2","description":"Control point","id":"10"},"type":"Feature","geometry":{"type":"Point","coordinates":[174.932959,-41.250373]}},{"properties":{"name":"W20","description":"Control point","id":"11"},"type":"Feature","geometry":{"type":"Point","coordinates":[174.923158,-41.243451]}},{"properties":{"name":"W21","description":"Control point","id":"12"},"type":"Feature","geometry":{"type":"Point","coordinates":[174.92381,-41.242024]}},{"properties":{"name":"W22","description":"Control point","id":"13"},"type":"Feature","geometry":{"type":"Point","coordinates":[174.932909,-41.255212]}},{"properties":{"name":"W23","description":"Control point","id":"14"},"type":"Feature","geometry":{"type":"Point","coordinates":[174.926824,-41.24087]}},{"properties":{"name":"W24","description":"Control point","id":"15"},"type":"Feature","geometry":{"type":"Point","coordinates":[174.928387,-41.2458]}},{"properties":{"name":"W25","description":"Control point","id":"16"},"type":"Feature","geometry":{"type":"Point","coordinates":[174.93708,-41.246846]}},{"properties":{"name":"W26","description":"Control point","id":"17"},"type":"Feature","geometry":{"type":"Point","coordinates":[174.929539,-41.245021]}},{"properties":{"name":"W3","description":"Control point","id":"18"},"type":"Feature","geometry":{"type":"Point","coordinates":[174.933139,-41.252769]}},{"properties":{"name":"W4","description":"Control point","id":"19"},"type":"Feature","geometry":{"type":"Point","coordinates":[174.936328,-41.244797]}},{"properties":{"name":"W5","description":"Control point","id":"20"},"type":"Feature","geometry":{"type":"Point","coordinates":[174.934706,-41.245784]}},{"properties":{"name":"W6","description":"Control point","id":"21"},"type":"Feature","geometry":{"type":"Point","coordinates":[174.927455,-41.251039]}},{"properties":{"name":"W7","description":"Control point","id":"22"},"type":"Feature","geometry":{"type":"Point","coordinates":[174.930977,-41.2532]}},{"properties":{"name":"W8","description":"Control point","id":"23"},"type":"Feature","geometry":{"type":"Point","coordinates":[174.925454,-41.243342]}},{"properties":{"name":"W9","description":"Control point","id":"24"},"type":"Feature","geometry":{"type":"Point","coordinates":[174.924955,-41.248025]}},{"properties":{"name":"WST","description":"Start","id":"25"},"type":"Feature","geometry":{"type":"Point","coordinates":[174.928434,-41.249732]}},{"properties":{"name":"NZPath","description":null,"id":"26"},"type":"Feature","geometry":null}],"is_temporal":false,"author":{"url":"","metadata":null,"contact_name":null,"contact_address":null,"source":null,"contact_phone":null},"source":"","pagination":{"sort":null,"start":0,"total":27,"limit":1000000},"state":"complete","tags":"","published":"2014-08-14T19:07:57-04:00","id":242847}