{"type":"FeatureCollection","data_type":"Dataset","url_type":null,"permissions":[{"permissions":{"download":true,"view":true},"group_id":"everyone"}],"classification":null,"title":"Pasta1","count":3,"stream_id":245129,"contributor":{"url":"http://geocommons.com/users/45972","name":"lvc.log@hotmail.com"},"data_attributes":null,"calculation_params":null,"icon_link":null,"link":"http://geocommons.com/overlays/245129.json","extent":[-51.23,-30.0331,-43.2075,-19.9208],"geometry_types":["point"],"unique_name":null,"name":"Pasta1","feature_count":3,"description":"","next_feature":null,"is_raster":false,"short_classification":"Y","stats":{"sales":{"max":550,"mean":283.333333333333,"variance":55833.3333333333,"stdev":236.29078131263,"min":100,"median":200}},"features":[{"properties":{"city":"Rio de Janeiro","sales":200,"geo_score":1.0,"country":"Brazil","id":"a62ssl1bxkx7","geo_precision":"zip"},"type":"Feature","geometry":{"type":"Point","coordinates":[-43.2075,-22.90277778]}},{"properties":{"city":"Belo Horizonte","sales":100,"geo_score":1.0,"country":"Brazil","id":"a62sslc0jlxx","geo_precision":"zip"},"type":"Feature","geometry":{"type":"Point","coordinates":[-43.93777778,-19.92083333]}},{"properties":{"city":"Porto Alegre","sales":550,"geo_score":1.0,"country":"Brazil","id":"a62ssl1qgre7","geo_precision":"zip"},"type":"Feature","geometry":{"type":"Point","coordinates":[-51.23,-30.03305556]}}],"is_temporal":false,"author":{"url":"","metadata":null,"contact_name":null,"contact_address":null,"source":null,"contact_phone":null},"source":"","pagination":{"sort":null,"start":0,"total":3,"limit":1000000},"state":"complete","tags":"","published":"2014-08-14T22:23:41-04:00","id":245129}