{"type":"FeatureCollection","data_type":"Dataset","url_type":null,"permissions":[{"permissions":{"download":true,"view":true},"group_id":"everyone"}],"classification":null,"title":"LATest2","count":12,"stream_id":246506,"contributor":{"url":"http://geocommons.com/users/185","name":"emily"},"data_attributes":null,"calculation_params":null,"icon_link":null,"link":"http://geocommons.com/overlays/246506.json","extent":[-103.284,1.90186,-71.9776,22.9377],"geometry_types":["point"],"unique_name":"","name":"LATest2","feature_count":12,"description":"","next_feature":null,"is_raster":false,"short_classification":"Y","stats":{},"features":[{"properties":{"name":"Mexico1","id":"0"},"type":"Feature","geometry":{"type":"Point","coordinates":[-100.492967810625,21.781210804315]}},{"properties":{"name":"Mexico2","id":"1"},"type":"Feature","geometry":{"type":"Point","coordinates":[-101.854425519001,22.937688163884]}},{"properties":{"name":"Mexico3","id":"2"},"type":"Feature","geometry":{"type":"Point","coordinates":[-101.873677370696,21.4280946371459]}},{"properties":{"name":"Mexico4","id":"3"},"type":"Feature","geometry":{"type":"Point","coordinates":[-100.564654363738,19.8781876513166]}},{"properties":{"name":"Mexico5","id":"4"},"type":"Feature","geometry":{"type":"Point","coordinates":[-102.332469992635,19.9754326176111]}},{"properties":{"name":"Mexico6","id":"5"},"type":"Feature","geometry":{"type":"Point","coordinates":[-103.284115692608,21.799269268269]}},{"properties":{"name":"Colombia1","id":"6"},"type":"Feature","geometry":{"type":"Point","coordinates":[-73.3120126670838,4.01881771964574]}},{"properties":{"name":"Colombia2","id":"7"},"type":"Feature","geometry":{"type":"Point","coordinates":[-73.5492584445811,1.90185797615887]}},{"properties":{"name":"Colombia3","id":"8"},"type":"Feature","geometry":{"type":"Point","coordinates":[-71.9775966624719,2.67886367506367]}},{"properties":{"name":"Colombia4","id":"9"},"type":"Feature","geometry":{"type":"Point","coordinates":[-74.7455908732487,3.06653102954054]}},{"properties":{"name":"Colombia5","id":"10"},"type":"Feature","geometry":{"type":"Point","coordinates":[-73.2241954501299,3.00194895137819]}},{"properties":{"name":"Colombia6","id":"11"},"type":"Feature","geometry":{"type":"Point","coordinates":[-72.1341639014158,4.24738367278851]}}],"is_temporal":false,"author":{"url":"","metadata":"","contact_name":"","contact_address":"","source":"","contact_phone":""},"source":"","pagination":{"sort":null,"start":0,"total":12,"limit":1000000},"state":"complete","tags":"","published":"2014-08-15T00:40:54-04:00","id":246506}