{"type":"FeatureCollection","data_type":"Dataset","url_type":null,"permissions":[{"permissions":{"download":true,"view":true},"group_id":"everyone"}],"classification":null,"title":"new_modest_office_branch_address_revised","count":1,"stream_id":246668,"contributor":{"url":"http://geocommons.com/users/39447","name":"sam.felipe"},"data_attributes":null,"calculation_params":null,"icon_link":null,"link":"http://geocommons.com/overlays/246668.json","extent":[-120.986,37.689,-120.986,37.689],"geometry_types":["point"],"unique_name":null,"name":"new_modest_office_branch_address_revised","feature_count":1,"description":"","next_feature":null,"is_raster":false,"short_classification":"Y","stats":{},"features":[{"properties":{"city":"Modesto","zip":"95350","geo_score":1.0,"id":"a61zo2k8s2nb","geo_precision":"range","address":"605 Sylvan Avenue","state":"ca"},"type":"Feature","geometry":{"type":"Point","coordinates":[-120.986205,37.688981]}}],"is_temporal":false,"author":{"url":"","metadata":null,"contact_name":null,"contact_address":null,"source":null,"contact_phone":null},"source":"","pagination":{"sort":null,"start":0,"total":1,"limit":1000000},"state":"complete","tags":"","published":"2014-08-15T00:51:50-04:00","id":246668}