{"type":"FeatureCollection","data_type":"Dataset","url_type":null,"permissions":[{"permissions":{"download":true,"view":true},"group_id":"everyone"}],"classification":null,"title":"5924","count":7,"stream_id":247407,"contributor":{"url":"http://geocommons.com/users/43719","name":"ythier"},"data_attributes":null,"calculation_params":null,"icon_link":null,"link":"http://geocommons.com/overlays/247407.json","extent":[7.07814,46.1051,7.88213,46.2934],"geometry_types":["point"],"unique_name":null,"name":"5924","feature_count":7,"description":"","next_feature":null,"is_raster":false,"short_classification":"Y","stats":{"latitude":{"max":46.29342288,"mean":46.2286930814286,"variance":0.00735640970940982,"stdev":0.0857695150354123,"min":46.1050903,"median":46.28254359},"longitude":{"max":7.882130721,"mean":7.42384225028572,"variance":0.07952884629124,"stdev":0.282008592584056,"min":7.078140969,"median":7.510897628}},"features":[{"properties":{"latitude":46.23085786,"longitude":7.359391348,"id":"a63c5m9invhg"},"type":"Feature","geometry":{"type":"Point","coordinates":[7.359391348,46.23085786]}},{"properties":{"latitude":46.29342288,"longitude":7.882130721,"id":"a63c5mdzi4r3"},"type":"Feature","geometry":{"type":"Point","coordinates":[7.882130721,46.29342288]}},{"properties":{"latitude":46.28254359,"longitude":7.510897628,"id":"a63c5m1w0eci"},"type":"Feature","geometry":{"type":"Point","coordinates":[7.510897628,46.28254359]}},{"properties":{"latitude":46.1050903,"longitude":7.078140969,"id":"a63c5m1emzt9"},"type":"Feature","geometry":{"type":"Point","coordinates":[7.078140969,46.1050903]}},{"properties":{"latitude":46.28805704,"longitude":7.522250031,"id":"a63c5m600hng"},"type":"Feature","geometry":{"type":"Point","coordinates":[7.522250031,46.28805704]}},{"properties":{"latitude":46.10921018,"longitude":7.08463032,"id":"a63c5m5p5uzr"},"type":"Feature","geometry":{"type":"Point","coordinates":[7.08463032,46.10921018]}},{"properties":{"latitude":46.29166972,"longitude":7.529454735,"id":"a63c5mecwy9b"},"type":"Feature","geometry":{"type":"Point","coordinates":[7.529454735,46.29166972]}}],"is_temporal":false,"author":{"url":"","metadata":null,"contact_name":null,"contact_address":null,"source":null,"contact_phone":null},"source":"","pagination":{"sort":null,"start":0,"total":7,"limit":1000000},"state":"complete","tags":"","published":"2014-08-15T01:35:44-04:00","id":247407}