{"type":"FeatureCollection","data_type":"Dataset","url_type":null,"permissions":[{"permissions":{"download":true,"view":true},"group_id":"everyone"}],"classification":null,"title":"\nenviortest\n","count":1,"stream_id":25092,"contributor":{"url":"http://geocommons.com/users/11444","name":"platial"},"data_attributes":null,"calculation_params":null,"icon_link":null,"link":"http://geocommons.com/overlays/25092.json","extent":[-84.2156,30.5632,-84.2156,30.5632],"geometry_types":["point"],"unique_name":null,"name":"\nenviortest\n","feature_count":1,"description":"\nA Map by Ffko\n\n\n","next_feature":null,"is_raster":false,"short_classification":"Y","stats":{},"features":[{"properties":{"name":"tallahassee","description":"Posted by Ffko<img src=\"http://media.geocommons.com/platial/images/categories/ICON_plain_pink_verD.gif\"> thomasville rd<a title=\"Built for Community Mapping\" href=\"http://www.platial.com\"><img src=\"http://media.geocommons.com/platial/images/logotype_small.jpg\"></a>","id":"abelzbkmmdkf"},"type":"Feature","geometry":{"type":"Point","coordinates":[-84.215632,30.56317]}}],"is_temporal":false,"author":{"url":null,"metadata":null,"contact_name":"ffko","contact_address":null,"source":"ffko","contact_phone":null},"source":null,"pagination":{"sort":null,"start":0,"total":1,"limit":1000000},"state":"complete","tags":"","published":"2014-08-10T18:11:24-04:00","id":25092}