{"type":"FeatureCollection","data_type":"Dataset","url_type":null,"permissions":[{"permissions":{"download":true,"view":true},"group_id":"everyone"}],"classification":null,"title":"fulcrum 20120612165313 damage assessment","count":3,"stream_id":251892,"contributor":{"url":"http://geocommons.com/users/47422","name":"5222454@comcast.net"},"data_attributes":null,"calculation_params":null,"icon_link":null,"link":"http://geocommons.com/overlays/251892.json","extent":[-72.5759,42.0838,-72.4982,42.1091],"geometry_types":["point"],"unique_name":null,"name":"fulcrum 20120612165313 damage assessment","feature_count":3,"description":"","next_feature":null,"is_raster":false,"short_classification":"Y","stats":{"latitude":{"max":42.109059,"variance":0.000211486369,"mean":42.100574,"stdev":0.0145425709212642,"min":42.083782,"median":42.108881},"date":{"max":"2012/06/12 00:00:00 -0400","variance":0.0,"mean":"2012/06/12 00:00:00 -0400","stdev":0.0,"min":"2012/06/12 00:00:00 -0400","median":"2012/06/12 00:00:00 -0400"},"id":{"max":3,"variance":1.0,"mean":2.0,"stdev":1.0,"min":1,"median":2},"created":{"max":"2012/06/12 23:13:28 -0400","variance":156767657.333333,"mean":"2012/06/12 19:12:44 -0400","stdev":12520.6891716604,"min":"2012/06/12 17:03:06 -0400","median":"2012/06/12 17:21:40 -0400"},"longitude":{"max":-72.498163,"variance":0.00200527544433312,"mean":-72.5498703333333,"stdev":0.0447803019678644,"min":-72.575922,"median":-72.575526},"updated":{"max":"2012/06/12 23:13:28 -0400","variance":122556897.0,"mean":"2012/06/12 21:26:01 -0400","stdev":11070.5418566572,"min":"2012/06/12 17:52:58 -0400","median":"2012/06/12 23:11:37 -0400"},"priority_level":{"max":3,"min":3,"median":3}},"features":[{"properties":{"type_of_damage":null,"latitude":42.108881,"add_photo_of_damage":null,"text":null,"date":{"end_time":"2012/06/13 00:00:00 -0400","original":"2012-06-12","granularity":"day","time":"2012/06/12 00:00:00 -0400"},"id":"a6efz6b43paw","longitude":-72.575922,"add_photo_of_damage_caption":null,"created":{"end_time":"2012/06/12 17:21:41 -0400","original":"2012-06-12 17:21:40","granularity":"sec","time":"2012/06/12 17:21:40 -0400"},"priority_level":null,"updated":{"end_time":"2012/06/12 23:11:38 -0400","original":"2012-06-12 23:11:37","granularity":"sec","time":"2012/06/12 23:11:37 -0400"}},"type":"Feature","geometry":{"type":"Point","coordinates":[-72.575922,42.108881]}},{"properties":{"type_of_damage":null,"latitude":42.109059,"add_photo_of_damage":"86FA70F3-C620-46EF-8B1B-9804CE12F980.jpg","text":"Test","date":{"end_time":"2012/06/13 00:00:00 -0400","original":"2012-06-12","granularity":"day","time":"2012/06/12 00:00:00 -0400"},"id":"a6efz636meo7","longitude":-72.575526,"add_photo_of_damage_caption":null,"created":{"end_time":"2012/06/12 17:03:07 -0400","original":"2012-06-12 17:03:06","granularity":"sec","time":"2012/06/12 17:03:06 -0400"},"priority_level":null,"updated":{"end_time":"2012/06/12 17:52:59 -0400","original":"2012-06-12 17:52:58","granularity":"sec","time":"2012/06/12 17:52:58 -0400"}},"type":"Feature","geometry":{"type":"Point","coordinates":[-72.575526,42.109059]}},{"properties":{"type_of_damage":"Broken Pole,Other","latitude":42.083782,"add_photo_of_damage":"B343D928-0446-4467-B2AF-C6D20B40AB32.jpg","text":null,"date":{"end_time":"2012/06/13 00:00:00 -0400","original":"2012-06-12","granularity":"day","time":"2012/06/12 00:00:00 -0400"},"id":"a6efz6bs5eyy","longitude":-72.498163,"add_photo_of_damage_caption":null,"created":{"end_time":"2012/06/12 23:13:29 -0400","original":"2012-06-12 23:13:28","granularity":"sec","time":"2012/06/12 23:13:28 -0400"},"priority_level":3,"updated":{"end_time":"2012/06/12 23:13:29 -0400","original":"2012-06-12 23:13:28","granularity":"sec","time":"2012/06/12 23:13:28 -0400"}},"type":"Feature","geometry":{"type":"Point","coordinates":[-72.498163,42.083782]}}],"is_temporal":true,"author":{"url":"","metadata":"","contact_name":"","contact_address":"","source":"","contact_phone":""},"source":"","pagination":{"sort":null,"start":0,"total":3,"limit":1000000},"state":"complete","tags":"","published":"2014-08-14T17:22:45-04:00","id":251892}