{"type":"FeatureCollection","data_type":"Dataset","url_type":null,"permissions":[{"permissions":{"download":true,"view":true},"group_id":"everyone"}],"classification":null,"title":"red cross","count":3,"stream_id":256808,"contributor":{"url":"http://geocommons.com/users/28467","name":"bheberto"},"data_attributes":null,"calculation_params":null,"icon_link":null,"link":"http://geocommons.com/overlays/256808.json","extent":[-105.148,38.8026,-104.749,38.9541],"geometry_types":["point"],"unique_name":null,"name":"red cross","feature_count":3,"description":"","next_feature":null,"is_raster":false,"short_classification":"Y","stats":{},"features":[{"properties":{"name":"Red Cross Shelter","description":"Summit Elementary School490 Meadow Park DriveDivide ,CO 80814Shelter Capacity : 93","id":"a6prwmo17xgb"},"type":"Feature","geometry":{"type":"Point","coordinates":[-105.148087,38.954067]}},{"properties":{"name":"Red Cross Shelter","description":"Cheyenne Mountain High School1200 Cresta RdColorado Springs ,CO 80906Shelter Capacity : 732","id":"a6prwmcblatp"},"type":"Feature","geometry":{"type":"Point","coordinates":[-104.858986,38.807125]}},{"properties":{"name":"Red Cross Shelter","description":"Ymca Southeast Family Center And Armed Services Ymca2190 Jet Wing DrColorado Springs ,CO 80916Shelter Capacity : 409Current Residents : 0","id":"a6prwmoi639b"},"type":"Feature","geometry":{"type":"Point","coordinates":[-104.749359,38.802563]}}],"is_temporal":false,"author":{"url":"","metadata":"","contact_name":"","contact_address":"","source":"","contact_phone":""},"source":"","pagination":{"sort":null,"start":0,"total":3,"limit":1000000},"state":"complete","tags":"","published":"2014-08-15T00:17:19-04:00","id":256808}