{"type":"FeatureCollection","data_type":"Dataset","url_type":null,"permissions":[{"permissions":{"download":true,"view":true},"group_id":"everyone"}],"classification":null,"title":"PE-M1088b","count":1,"stream_id":261901,"contributor":{"url":"http://geocommons.com/users/35812","name":"karenf"},"data_attributes":null,"calculation_params":null,"icon_link":null,"link":"http://geocommons.com/overlays/261901.json","extent":[-77.86,-6.22,-77.86,-6.22],"geometry_types":["point"],"unique_name":null,"name":"PE-M1088b","feature_count":1,"description":"","next_feature":null,"is_raster":false,"short_classification":"Y","stats":{"number of individuals beneficiaries":{"max":5000,"median":5000,"min":5000},"latitude":{"max":-6.22,"median":-6.22,"min":-6.22},"longitude":{"max":-77.86,"median":-77.86,"min":-77.86},"oap":{"max":372,"median":372,"min":372},"number of companies":{"max":3,"median":3,"min":3}},"features":[{"properties":{"city":"Chachapoyas","number of individuals beneficiaries":5000,"latitude":-6.22,"country":"PERU","project number":"PE-M1088","oap":372,"longitude":-77.86,"id":"a78xok7q3fjo","number of companies":3,"features of individuals":"Women, Men, Youth, Rural population, Indigenous population, Socially excluded population, Population with low educaction levels, Low income population","state":"Amazonas"},"type":"Feature","geometry":{"type":"Point","coordinates":[-77.86,-6.22]}}],"is_temporal":false,"author":{"url":"","metadata":null,"contact_name":null,"contact_address":null,"source":null,"contact_phone":null},"source":"","pagination":{"sort":null,"start":0,"total":1,"limit":1000000},"state":"complete","tags":"","published":"2014-08-14T17:27:26-04:00","id":261901}