{"type":"FeatureCollection","data_type":"Dataset","url_type":null,"permissions":[{"permissions":{"download":true,"view":true},"group_id":"everyone"}],"classification":null,"title":"Sightingsorig","count":7,"stream_id":262452,"contributor":{"url":"http://geocommons.com/users/35962","name":"ropadon"},"data_attributes":null,"calculation_params":null,"icon_link":null,"link":"http://geocommons.com/overlays/262452.json","extent":[118.512,7.59551,125.123,16.6709],"geometry_types":["point"],"unique_name":null,"name":"Sightingsorig","feature_count":7,"description":"","next_feature":null,"is_raster":false,"short_classification":"Y","stats":{"biktima":{"max":9,"variance":10.5714285714286,"mean":5.28571428571429,"stdev":3.25137333621173,"median":6,"min":0}},"features":[{"properties":{"name":"Sighting-6","biktima":5,"id":"a7b5jldzr2oc"},"type":"Feature","geometry":{"type":"Point","coordinates":[124.23660447503,9.87893083754573]}},{"properties":{"name":"Sighting-5","biktima":8,"id":"a7b5jle56i2t"},"type":"Feature","geometry":{"type":"Point","coordinates":[125.12340041311,12.0987269442503]}},{"properties":{"name":"Sighting-4","biktima":2,"id":"a7b5jldr9276"},"type":"Feature","geometry":{"type":"Point","coordinates":[122.507426548802,11.2129741119272]}},{"properties":{"name":"Sighting-3","biktima":9,"id":"a7b5jlfc67uv"},"type":"Feature","geometry":{"type":"Point","coordinates":[121.270085081223,16.6708957997186]}},{"properties":{"name":"Sighting-2","biktima":0,"id":"a7b5jld4h2v3"},"type":"Feature","geometry":{"type":"Point","coordinates":[124.861386906984,7.5955056279571]}},{"properties":{"name":"Sighting-1","biktima":6,"id":"a7b5jlnftmdz"},"type":"Feature","geometry":{"type":"Point","coordinates":[118.511976657602,9.63543807970624]}},{"properties":{"name":"Sighting-7","biktima":7,"id":"a7b5jliosi4z"},"type":"Feature","geometry":{"type":"Point","coordinates":[121.119124461231,12.9236541654245]}}],"is_temporal":false,"author":{"url":"","metadata":null,"contact_name":null,"contact_address":null,"source":null,"contact_phone":null},"source":"","pagination":{"sort":null,"start":0,"total":7,"limit":1000000},"state":"complete","tags":"","published":"2014-08-14T18:22:58-04:00","id":262452}