{"type":"FeatureCollection","data_type":"Dataset","url_type":null,"permissions":[{"permissions":{"download":true,"view":true},"group_id":"everyone"}],"classification":null,"title":"Les thermes","count":1,"stream_id":262909,"contributor":{"url":"http://geocommons.com/users/43512","name":"argentomagus"},"data_attributes":null,"calculation_params":null,"icon_link":null,"link":"http://geocommons.com/overlays/262909.json","extent":[1.5125,46.5961,1.5125,46.5961],"geometry_types":["point"],"unique_name":null,"name":"Les thermes","feature_count":1,"description":"","next_feature":null,"is_raster":false,"short_classification":"Y","stats":{},"features":[{"properties":{"Contacts":"<a href=\"mailto:info@argentomagus.fr\">Contacter le musée</a><a href=\"http://www.argentomagus.fr\">Site internet</a>","Site":"Les thermes","id":"a7d1brph5rcv","GPS":"1.51250 - 46.59611","Description":"A Argentomagus, un seul bâtiment thermal a été mis au jour. Son sol était fait de dalles calcaires épaisses de 3 cm et ses murs enduits de mortier de tuileau portaient encore une plinthe de marbre de 16 cm de hauteur. A proximité, ont été retrouvés deux blocs sculptés et un chapiteau appartenant à un pilastre qui devait encadrer une baie, peut-être celle qui donnait sur la piscine."},"type":"Feature","geometry":{"type":"Point","coordinates":[1.5125,46.59611]}}],"is_temporal":false,"author":{"url":"","metadata":"","contact_name":"","contact_address":"","source":"","contact_phone":""},"source":"","pagination":{"sort":null,"start":0,"total":1,"limit":1000000},"state":"complete","tags":"","published":"2014-08-14T18:53:02-04:00","id":262909}