{"type":"FeatureCollection","data_type":"Data Feed","url_type":"csv","permissions":[{"permissions":{"download":true,"view":true},"group_id":"everyone"}],"classification":null,"title":"fetch latest test 2","count":9,"stream_id":264927,"contributor":{"url":"http://geocommons.com/users/185","name":"emily"},"data_attributes":null,"calculation_params":null,"icon_link":null,"link":"http://geocommons.com/overlays/264927.json","extent":[-119.259,34.1698,-72.7567,41.5229],"geometry_types":["point"],"unique_name":"","name":"fetch latest test 2","feature_count":9,"description":"","next_feature":null,"is_raster":false,"short_classification":"Y","stats":{"latitude":{"max":41.52291025,"variance":6.07310622736208,"mean":37.6675247,"stdev":2.4643673077206,"min":34.16978002,"median":37.26898656},"number":{"max":8,"variance":4.77777777777778,"mean":4.44444444444444,"stdev":2.185812841434,"min":2,"median":4},"longitude":{"max":-72.75674326,"variance":325.90972779092,"mean":-101.791265564444,"stdev":18.0529700545622,"min":-119.2589342,"median":-111.9336881}},"features":[{"properties":{"latitude":34.16978002,"number":2,"longitude":-111.9336881,"id":"ahmn1oppluqo"},"type":"Feature","geometry":{"type":"Point","coordinates":[-111.9336881,34.16978002]}},{"properties":{"latitude":37.26898656,"number":2,"longitude":-119.2589342,"id":"ahmn1op0382d"},"type":"Feature","geometry":{"type":"Point","coordinates":[-119.2589342,37.26898656]}},{"properties":{"latitude":37.26898656,"number":2,"longitude":-119.2589342,"id":"ahmn1ojld6p5"},"type":"Feature","geometry":{"type":"Point","coordinates":[-119.2589342,37.26898656]}},{"properties":{"latitude":41.52291025,"number":2,"longitude":-72.75674326,"id":"ahmn1oj892tx"},"type":"Feature","geometry":{"type":"Point","coordinates":[-72.75674326,41.52291025]}},{"properties":{"latitude":39.74809298,"number":2,"longitude":-89.51209675,"id":"ahmn1ol2pwvq"},"type":"Feature","geometry":{"type":"Point","coordinates":[-89.51209675,39.74809298]}},{"properties":{"latitude":39.77088229,"number":1,"longitude":-86.44446803,"id":"ahmn1ol7rgb7"},"type":"Feature","geometry":{"type":"Point","coordinates":[-86.44446803,39.77088229]}},{"properties":{"latitude":37.81931706,"number":1,"longitude":-85.76390324,"id":"ahmn1oha9mnk"},"type":"Feature","geometry":{"type":"Point","coordinates":[-85.76390324,37.81931706]}},{"properties":{"latitude":34.16978002,"number":1,"longitude":-111.9336881,"id":"ahmn1ore0jcs"},"type":"Feature","geometry":{"type":"Point","coordinates":[-111.9336881,34.16978002]}},{"properties":{"latitude":37.26898656,"number":1,"longitude":-119.2589342,"id":"ahmn1oqmxxbi"},"type":"Feature","geometry":{"type":"Point","coordinates":[-119.2589342,37.26898656]}}],"is_temporal":false,"author":{"url":"","metadata":"","contact_name":"","contact_address":"","source":"","contact_phone":""},"source":"","pagination":{"sort":null,"start":0,"total":9,"limit":1000000},"state":"complete","tags":"","published":"2014-08-14T21:36:46-04:00","id":264927}