{"type":"FeatureCollection","data_type":"Dataset","url_type":null,"permissions":[{"permissions":{"download":true,"view":true},"group_id":"everyone"}],"classification":null,"title":"Police Stations - Jamestown","count":1,"stream_id":267842,"contributor":{"url":"http://geocommons.com/users/50478","name":"JamestownANC"},"data_attributes":null,"calculation_params":null,"icon_link":null,"link":"http://geocommons.com/overlays/267842.json","extent":[-79.5841,43.7435,-79.5841,43.7435],"geometry_types":["point"],"unique_name":null,"name":"Police Stations - Jamestown","feature_count":1,"description":"","next_feature":null,"is_raster":false,"short_classification":"Y","stats":{"latitude":{"max":43.74346843,"min":43.74346843,"median":43.74346843},"longitude":{"max":-79.58414161,"min":-79.58414161,"median":-79.58414161}},"features":[{"properties":{"neighbourhood name":"Rexdale","latitude":43.74346843,"establishment name":"Toronto Police Service 23 Division","accessibility":"Yes","website":"http://www.torontopolice.on.ca/d23/","parking available":"Yes","postal code":"M9V 0A1","phone":"416-808-2300","fax":"416-808-2302","capacity":null,"services":null,"business hours":null,"longitude":-79.58414161,"id":"a7vbt0pud63p","address":"5230 Finch Ave. W","personal requirements":null},"type":"Feature","geometry":{"type":"Point","coordinates":[-79.58414161,43.74346843]}}],"is_temporal":false,"author":{"url":"","metadata":"","contact_name":"","contact_address":"","source":"","contact_phone":""},"source":"","pagination":{"sort":null,"start":0,"total":1,"limit":1000000},"state":"complete","tags":"","published":"2014-08-15T01:26:53-04:00","id":267842}