{"type":"FeatureCollection","data_type":"Dataset","url_type":null,"permissions":[{"permissions":{"download":true,"view":true},"group_id":"everyone"}],"classification":null,"title":"Insurance Brokers - Bathurst and Finch","count":3,"stream_id":268234,"contributor":{"url":"http://geocommons.com/users/50477","name":"BathurstFinchANC"},"data_attributes":null,"calculation_params":null,"icon_link":null,"link":"http://geocommons.com/overlays/268234.json","extent":[-79.4516,43.7819,-79.4516,43.787],"geometry_types":["point"],"unique_name":null,"name":"Insurance Brokers - Bathurst and Finch","feature_count":3,"description":"","next_feature":null,"is_raster":false,"short_classification":"Y","stats":{"latitude":{"max":43.78702,"variance":6.79687633332618e-06,"mean":43.7842006666667,"stdev":0.00260708195753915,"min":43.781877,"median":43.783705},"longitude":{"max":-79.451644,"variance":0.0,"mean":-79.451644,"stdev":0.0,"min":-79.451644,"median":-79.451644}},"features":[{"properties":{"neighbourhood name":"Bathurst and Finch","additional information":null,"latitude":43.78702,"establishment name":"Gottesman Herman Insurance Brokers","accessibility":null,"website":null,"parking available":null,"postal code":"M2R 3E8","phone":"416-667-8080","fax":null,"capacity":null,"services":null,"hours of operation":"M-Sa: 9am - 5pm, Su: 10am - 4pm","longitude":-79.451644,"id":"a7vyrczllcrp","address":"238 Torresdale Ave."},"type":"Feature","geometry":{"type":"Point","coordinates":[-79.451644,43.78702]}},{"properties":{"neighbourhood name":"Bathurst and Finch","additional information":null,"latitude":43.783705,"establishment name":"The Leading Edge","accessibility":null,"website":null,"parking available":null,"postal code":"M3H 5T5","phone":"416-661-9155","fax":null,"capacity":null,"services":"insurance &amp; financial services","hours of operation":null,"longitude":-79.451644,"id":"a7vyrd8tpy00","address":"5050 Dufferin St."},"type":"Feature","geometry":{"type":"Point","coordinates":[-79.451644,43.783705]}},{"properties":{"neighbourhood name":"Bathurst and Finch","additional information":null,"latitude":43.781877,"establishment name":"Amero Insurance Agency","accessibility":null,"website":"http://ameroinsurance.ca/","parking available":null,"postal code":"M3H 5T5","phone":"416-273-4434","fax":null,"capacity":null,"services":"personal insurance; business insurance; travel insurance","hours of operation":null,"longitude":-79.451644,"id":"a7vyrd7zfkxa","address":"204-5000 Dufferin St."},"type":"Feature","geometry":{"type":"Point","coordinates":[-79.451644,43.781877]}}],"is_temporal":false,"author":{"url":"","metadata":"","contact_name":"","contact_address":"","source":"","contact_phone":""},"source":"","pagination":{"sort":null,"start":0,"total":3,"limit":1000000},"state":"complete","tags":"","published":"2014-08-15T01:51:51-04:00","id":268234}