{"type":"FeatureCollection","data_type":"Dataset","url_type":null,"permissions":[{"permissions":{"download":true,"view":true},"group_id":"everyone"}],"classification":null,"title":"Recreational Centres - Malvern","count":3,"stream_id":268784,"contributor":{"url":"http://geocommons.com/users/50468","name":"MalvernANC"},"data_attributes":null,"calculation_params":null,"icon_link":null,"link":"http://geocommons.com/overlays/268784.json","extent":[-79.2341,43.7931,79.2157,43.8144],"geometry_types":["point"],"unique_name":null,"name":"Recreational Centres - Malvern","feature_count":3,"description":"","next_feature":null,"is_raster":false,"short_classification":"Y","stats":{"latitude":{"max":43.81437262,"variance":0.000118216651192035,"mean":43.8051256833333,"stdev":0.0108727480975159,"min":43.79314781,"median":43.80785662},"longitude":{"max":79.21571437,"variance":8368.37950260327,"mean":-26.41495976,"stdev":91.4788472959912,"min":-79.23413539,"median":-79.22645826}},"features":[{"properties":{"neighbourhood name":"Malvern","latitude":43.79314781,"establishment name":"Burrows Hall CC","accessibility":"Yes","website":"http://www.toronto.ca/parks/prd/facilities/complex/591/index.htm","parking available":"Yes","postal code":"M1B 5Z6","phone":"416 396-4670","fax":null,"capacity":null,"services":null,"business hours":null,"longitude":-79.23413539,"id":"a7xiozmfbfgj","address":"1081 Progress Ave","personal requirements":null},"type":"Feature","geometry":{"type":"Point","coordinates":[-79.23413539,43.79314781]}},{"properties":{"neighbourhood name":"Malvern","latitude":43.80785662,"establishment name":"Malvern Recreation Centre","accessibility":"Yes","website":"http://www.toronto.ca/parks/prd/facilities/complex/702/index.htm","parking available":"Yes","postal code":"M1B3G5","phone":"416 396-4054","fax":null,"capacity":null,"services":"Library; Indoor Rinks 2; Multipurpose Rooms 7; Gymnasium","business hours":null,"longitude":79.21571437,"id":"a7xiozjxlqd6","address":"30 Sewells Rd.","personal requirements":null},"type":"Feature","geometry":{"type":"Point","coordinates":[79.21571437,43.80785662]}},{"properties":{"neighbourhood name":"Malvern","latitude":43.81437262,"establishment name":"Neilson House","accessibility":"Yes","website":"http://www.toronto.ca/parks/prd/facilities/complex/730/index.htm","parking available":"Yes","postal code":"M1B 5Z7","phone":null,"fax":null,"capacity":null,"services":"Multipurpose Rooms 2","business hours":null,"longitude":-79.22645826,"id":"a7xiozuvs6xt","address":"1575 Neilson Rd.","personal requirements":null},"type":"Feature","geometry":{"type":"Point","coordinates":[-79.22645826,43.81437262]}}],"is_temporal":false,"author":{"url":"","metadata":"","contact_name":"","contact_address":"","source":"","contact_phone":""},"source":"","pagination":{"sort":null,"start":0,"total":3,"limit":1000000},"state":"complete","tags":"","published":"2014-08-15T02:27:42-04:00","id":268784}