{"type":"FeatureCollection","data_type":"Dataset","url_type":null,"permissions":[{"permissions":{"download":true,"view":true},"group_id":"everyone"}],"classification":null,"title":"Insurance broker-Scarborough","count":3,"stream_id":269226,"contributor":{"url":"http://geocommons.com/users/50467","name":"ScarboroughVillageANC"},"data_attributes":null,"calculation_params":null,"icon_link":null,"link":"http://geocommons.com/overlays/269226.json","extent":[-79.2178,43.7378,-79.2172,43.7383],"geometry_types":["point"],"unique_name":null,"name":"Insurance broker-Scarborough","feature_count":3,"description":"","next_feature":null,"is_raster":false,"short_classification":"Y","stats":{"latitude":{"max":43.7383048,"variance":7.29643265335023e-08,"mean":43.7381488466667,"stdev":0.000270119096943371,"min":43.73783694,"median":43.7383048},"longitude":{"max":-79.21721701,"variance":9.46110725328676e-08,"mean":-79.2173945966667,"stdev":0.000307589129412708,"min":-79.21774977,"median":-79.21721701}},"features":[{"properties":{"neighbourhood name":null,"additional information":null,"latitude":43.73783694,"establishment name":"The Co-operators - Adele F Read CFP, CLU, CHFC, Agent","accessibility":null,"website":"localagent.cooperators.ca","parking available":null,"postal code":"M1M 1R4","phone":"416-264-5858","fax":null,"capacity":null,"services":"Auto insurance","hours of operation":null,"longitude":-79.21774977,"id":"a80e4kyrxyw4","address":"3473 Kingston Road"},"type":"Feature","geometry":{"type":"Point","coordinates":[-79.21774977,43.73783694]}},{"properties":{"neighbourhood name":null,"additional information":null,"latitude":43.7383048,"establishment name":"Maxwell Peter E","accessibility":null,"website":null,"parking available":null,"postal code":"M1M 1R4?","phone":"416-502-3944","fax":null,"capacity":null,"services":"Insurance Agent","hours of operation":null,"longitude":-79.21721701,"id":"a80e4kx4edxx","address":"3489 Kingston Road"},"type":"Feature","geometry":{"type":"Point","coordinates":[-79.21721701,43.7383048]}},{"properties":{"neighbourhood name":null,"additional information":null,"latitude":43.7383048,"establishment name":"Vaillancourt John W","accessibility":null,"website":null,"parking available":null,"postal code":"M1M 1R4","phone":"416-690-1708","fax":null,"capacity":null,"services":"Insurance Agency Attorney","hours of operation":null,"longitude":-79.21721701,"id":"a80e4l4y7fsp","address":"205-3489 Kingston Rd."},"type":"Feature","geometry":{"type":"Point","coordinates":[-79.21721701,43.7383048]}}],"is_temporal":false,"author":{"url":"","metadata":"","contact_name":"","contact_address":"","source":"","contact_phone":""},"source":"","pagination":{"sort":null,"start":0,"total":3,"limit":1000000},"state":"complete","tags":"","published":"2014-08-15T02:55:57-04:00","id":269226}