{"type":"FeatureCollection","data_type":"Dataset","url_type":null,"permissions":[{"permissions":{"download":true,"view":true},"group_id":"everyone"}],"classification":null,"title":"Paydayloans-Scarborough","count":4,"stream_id":269229,"contributor":{"url":"http://geocommons.com/users/50467","name":"ScarboroughVillageANC"},"data_attributes":null,"calculation_params":null,"icon_link":null,"link":"http://geocommons.com/overlays/269229.json","extent":[-79.2488,43.7101,-79.2155,43.7439],"geometry_types":["point"],"unique_name":null,"name":"Paydayloans-Scarborough","feature_count":4,"description":"","next_feature":null,"is_raster":false,"short_classification":"Y","stats":{"latitude":{"max":43.74393971,"variance":0.000370834962896542,"mean":43.7323318033333,"stdev":0.0192570756579638,"min":43.71010295,"median":43.74295275},"longitude":{"max":-79.21550947,"variance":0.000326645387557494,"mean":-79.2281134433333,"stdev":0.0180733336038898,"min":-79.2488203,"median":-79.22001056}},"features":[{"properties":{"neighbourhood name":null,"additional information":null,"latitude":null,"establishment name":"The Cash Store","accessibility":"Parking available","website":"cashstore.ca","parking available":null,"postal code":"M1J 3M5","phone":"416-264-9284","fax":null,"capacity":null,"services":"Payday loans,line of credit,check cashing","hours of operation":null,"longitude":null,"id":"a80e4sl8kqlm","address":"133-3227 Eglinton Ave. East"},"type":"Feature","geometry":null},{"properties":{"neighbourhood name":null,"additional information":null,"latitude":43.74295275,"establishment name":"Cash Money Western Union","accessibility":"Parking available","website":null,"parking available":null,"postal code":"M1J 2H3","phone":"416-261-6040","fax":null,"capacity":null,"services":null,"hours of operation":null,"longitude":-79.22001056,"id":"a80e4sr3nl2f","address":"3182 Eglinton Ave. East"},"type":"Feature","geometry":{"type":"Point","coordinates":[-79.22001056,43.74295275]}},{"properties":{"neighbourhood name":null,"additional information":"Cultural Services                  Tax Clinic Seasonal service","latitude":43.74393971,"establishment name":"Settlement Integration Place (SIP) and Catholic Cross","accessibility":"Parking available","website":null,"parking available":null,"postal code":"M1J 3N6","phone":"416-266-7200","fax":null,"capacity":null,"services":null,"hours of operation":null,"longitude":-79.21550947,"id":"a80e4stg5r99","address":"Markington Square 3227 Eglinton Ave. East"},"type":"Feature","geometry":{"type":"Point","coordinates":[-79.21550947,43.74393971]}},{"properties":{"neighbourhood name":null,"additional information":"Variety of services include bookkeeping (Bank and Credit Card Reconciliation, Inventory control), payroll (reparation of Employee Status Reports and Standard Payroll Reports (Summery and Register), Govt. Remittance of Statutory deductions (CPP, EI, Fed Tax, Prov Tax and EHT), WSIB Issue T4, T4A's, adjustments/summery for year end.   Tax Services","latitude":43.71010295,"establishment name":"ACT Finance Inc.","accessibility":null,"website":"http://www.actfinance.ca/","parking available":null,"postal code":"M1N 1V4","phone":"416-269-9787","fax":null,"capacity":null,"services":null,"hours of operation":null,"longitude":-79.2488203,"id":"a80e4smbpg6h","address":"2481 Kingston Road"},"type":"Feature","geometry":{"type":"Point","coordinates":[-79.2488203,43.71010295]}}],"is_temporal":false,"author":{"url":"","metadata":"","contact_name":"","contact_address":"","source":"","contact_phone":""},"source":"","pagination":{"sort":null,"start":0,"total":4,"limit":1000000},"state":"complete","tags":"","published":"2014-08-15T02:55:57-04:00","id":269229}