{"type":"FeatureCollection","data_type":"Dataset","url_type":null,"permissions":[{"permissions":{"download":true,"view":true},"group_id":"everyone"}],"classification":null,"title":"SCC_Competition_Assisted","count":4,"stream_id":270031,"contributor":{"url":"http://geocommons.com/users/46128","name":"johnwmeyer"},"data_attributes":null,"calculation_params":null,"icon_link":null,"link":"http://geocommons.com/overlays/270031.json","extent":[-81.4891,31.1676,-81.3768,31.2507],"geometry_types":["point"],"unique_name":null,"name":"SCC_Competition_Assisted","feature_count":4,"description":"","next_feature":null,"is_raster":false,"short_classification":"Y","stats":{"beds":{"max":50,"variance":174.916666666667,"mean":38.25,"stdev":13.2256064763272,"min":24,"median":49}},"features":[{"properties":{"city":"Brunswick","geo_score":0.611,"zip code":"31522","street":"1550 Glynco Parkway","beds":50,"id":"a82tjcakil48","geo_precision":"street","location":"Fairhaven","state":"GA"},"type":"Feature","geometry":{"type":"Point","coordinates":[-81.475237,31.250733]}},{"properties":{"city":"St. Simons","geo_score":0.944,"zip code":"31522","street":"2255 Frederica Road","beds":30,"id":"a82tjcblbmv1","geo_precision":"range","location":"Magnolia Manor","state":"GA"},"type":"Feature","geometry":{"type":"Point","coordinates":[-81.38453,31.16757]}},{"properties":{"city":"Brunswick","geo_score":0.878,"zip code":"31525","street":"890 Scranton Road","beds":49,"id":"a82tjc3dclg5","geo_precision":"range","location":"Benton House","state":"GA"},"type":"Feature","geometry":{"type":"Point","coordinates":[-81.489132,31.225252]}},{"properties":{"city":"St. Simons","geo_score":0.585,"zip code":"31522","street":"136 Marshs Edge Lane","beds":24,"id":"a82tjcabq282","geo_precision":"zip","location":"Marsh's Edge","state":"GA"},"type":"Feature","geometry":{"type":"Point","coordinates":[-81.376763,31.188564]}}],"is_temporal":false,"author":{"url":"","metadata":null,"contact_name":null,"contact_address":null,"source":null,"contact_phone":null},"source":"","pagination":{"sort":null,"start":0,"total":4,"limit":1000000},"state":"complete","tags":"","published":"2014-08-14T14:53:28-04:00","id":270031}