{"type":"FeatureCollection","data_type":"Dataset","url_type":null,"permissions":[{"permissions":{"download":true,"view":true},"group_id":"everyone"}],"classification":null,"title":"Libraries- Thorncliff Park","count":1,"stream_id":270290,"contributor":{"url":"http://geocommons.com/users/50476","name":"ThorncliffeParkANC"},"data_attributes":null,"calculation_params":null,"icon_link":null,"link":"http://geocommons.com/overlays/270290.json","extent":[-79.3423,43.7029,-79.3423,43.7029],"geometry_types":["point"],"unique_name":null,"name":"Libraries- Thorncliff Park","feature_count":1,"description":"","next_feature":null,"is_raster":false,"short_classification":"Y","stats":{"latitude":{"max":43.70289027,"min":43.70289027,"median":43.70289027},"longitude":{"max":-79.34231193,"min":-79.34231193,"median":-79.34231193}},"features":[{"properties":{"neighbourhood name":"Thorncliffe Park","latitude":43.70289027,"establishment name":"Thorncliffe Public Library","accessibility":"Yes","website":"http://www.torontopubliclibrary.ca/detail.jsp?R=LIB090","parking available":"Yes","postal code":"M4H 1J7","phone":"416-396-3865","fax":null,"capacity":null,"services":"#NAME?","business hours":"M-F: 9am-8:30pm, Sa: 9am-5pm","longitude":-79.34231193,"id":"a83hifqm858y","address":"48 Thorncliffe Park Dr.","personal requirements":null},"type":"Feature","geometry":{"type":"Point","coordinates":[-79.34231193,43.70289027]}}],"is_temporal":false,"author":{"url":"","metadata":"","contact_name":"","contact_address":"","source":"","contact_phone":""},"source":"","pagination":{"sort":null,"start":0,"total":1,"limit":1000000},"state":"complete","tags":"","published":"2014-08-14T15:12:08-04:00","id":270290}