{"type":"FeatureCollection","data_type":"Dataset","url_type":null,"permissions":[{"permissions":{"download":true,"view":true},"group_id":"everyone"}],"classification":null,"title":"Libraries- Dorset Park","count":1,"stream_id":270789,"contributor":{"url":"http://geocommons.com/users/50470","name":"DorsetParkANC"},"data_attributes":null,"calculation_params":null,"icon_link":null,"link":"http://geocommons.com/overlays/270789.json","extent":[-79.2773,43.749,-79.2773,43.749],"geometry_types":["point"],"unique_name":null,"name":"Libraries- Dorset Park","feature_count":1,"description":"","next_feature":null,"is_raster":false,"short_classification":"Y","stats":{"latitude":{"max":43.748991,"min":43.748991,"median":43.748991},"longitude":{"max":-79.27734,"min":-79.27734,"median":-79.27734}},"features":[{"properties":{"neighbourhood name":"Dorset Park","latitude":43.748991,"establishment name":"McGregor Park Library.","accessibility":"Wheelchair Access","website":"http://www.torontopubliclibrary.ca","parking available":null,"postal code":"M1P 2P5","phone":"416-396-8935","fax":null,"capacity":null,"services":null,"business hours":"Mon:  Closed  Tue:  12:30 p.m. - 8:30 p.m.\r\nWed:  10:00 a.m. - 6:00 p.m.  Thu:  12:30 p.m. - 8:30 p.m.\r\nFri:  10:00 a.m. - 6:00 p.m.  Sat:  9:00 a.m. - 5:00 p.m.\r\nSun:  1:30 p.m. - 5:00 p.m.","longitude":-79.27734,"id":"a865nziaka20","address":"2219 Lawrence Ave. East","personal requirements":null},"type":"Feature","geometry":{"type":"Point","coordinates":[-79.27734,43.748991]}}],"is_temporal":false,"author":{"url":"","metadata":"","contact_name":"","contact_address":"","source":"","contact_phone":""},"source":"","pagination":{"sort":null,"start":0,"total":1,"limit":1000000},"state":"complete","tags":"","published":"2014-08-14T15:45:02-04:00","id":270789}