{"type":"FeatureCollection","data_type":"Data Feed","url_type":"csv","permissions":[{"permissions":{"download":true,"edit":true,"view":true},"group_id":50480},{"permissions":{"download":true,"view":true},"group_id":"everyone"}],"classification":null,"title":"Pregnant Women","count":5,"stream_id":270905,"contributor":{"url":"http://geocommons.com/users/43038","name":"gamaly"},"data_attributes":null,"calculation_params":null,"icon_link":null,"link":"http://geocommons.com/overlays/270905.json","extent":[77.2904,28.5478,77.2934,28.5498],"geometry_types":["point"],"unique_name":null,"name":"Pregnant Women","feature_count":5,"description":"","next_feature":null,"is_raster":false,"short_classification":"Y","stats":{"timetable (month)":{"max":8,"variance":9.3,"mean":4.6,"stdev":3.04959013639538,"min":1,"median":5},"trimesters":{"max":3,"variance":1.0,"mean":2.0,"stdev":1.0,"min":1,"median":2},"lat":{"max":28.54977834,"variance":5.58544883429178e-07,"mean":28.548943686,"stdev":0.000747358604305308,"min":28.54783407,"median":28.54895767},"long":{"max":77.29342447,"variance":1.41756805598194e-06,"mean":77.291675584,"stdev":0.00119061667046197,"min":77.29036239,"median":77.29122112}},"features":[{"properties":{"name":"Person 1","timetable (month)":2,"known issues":"Anemia","weight":null,"trimesters":1,"mohalla":null,"vaccinations":"yes","plans for birth":"home","id":"a86l5fjma1jj","lat":28.54783407,"long":77.29110167},"type":"Feature","geometry":{"type":"Point","coordinates":[77.29110167,28.54783407]}},{"properties":{"name":"Person 2","timetable (month)":5,"known issues":"none","weight":null,"trimesters":2,"mohalla":null,"vaccinations":"no","plans for birth":"hospital","id":"a86l5fgr664e","lat":28.54895767,"long":77.29036239},"type":"Feature","geometry":{"type":"Point","coordinates":[77.29036239,28.54895767]}},{"properties":{"name":"Person 3","timetable (month)":7,"known issues":"none","weight":null,"trimesters":3,"mohalla":null,"vaccinations":"no","plans for birth":"none","id":"a86l5fii0o4w","lat":28.54944298,"long":77.29226827},"type":"Feature","geometry":{"type":"Point","coordinates":[77.29226827,28.54944298]}},{"properties":{"name":"Person 4","timetable (month)":8,"known issues":"none","weight":null,"trimesters":3,"mohalla":null,"vaccinations":"no","plans for birth":"none","id":"a86l5fgf4ui3","lat":28.54870537,"long":77.29122112},"type":"Feature","geometry":{"type":"Point","coordinates":[77.29122112,28.54870537]}},{"properties":{"name":"Person 5","timetable (month)":1,"known issues":"none","weight":null,"trimesters":1,"mohalla":null,"vaccinations":"yes","plans for birth":"private clinic","id":"a86l5fd3gfc6","lat":28.54977834,"long":77.29342447},"type":"Feature","geometry":{"type":"Point","coordinates":[77.29342447,28.54977834]}}],"is_temporal":false,"author":{"url":"","metadata":"","contact_name":"","contact_address":"","source":"","contact_phone":""},"source":"","pagination":{"sort":null,"start":0,"total":5,"limit":1000000},"state":"complete","tags":"pregnant","published":"2014-08-14T15:53:25-04:00","id":270905}