{"type":"FeatureCollection","data_type":"Dataset","url_type":null,"permissions":[{"permissions":{"download":true,"view":true},"group_id":"everyone"}],"classification":null,"title":"Health Centres - Lotherton","count":1,"stream_id":271475,"contributor":{"url":"http://geocommons.com/users/50469","name":"LothertonANC"},"data_attributes":null,"calculation_params":null,"icon_link":null,"link":"http://geocommons.com/overlays/271475.json","extent":[-79.4144,43.7225,-79.4144,43.7225],"geometry_types":["point"],"unique_name":null,"name":"Health Centres - Lotherton","feature_count":1,"description":"","next_feature":null,"is_raster":false,"short_classification":"Y","stats":{"latitude":{"max":43.72254756,"min":43.72254756,"median":43.72254756},"longitude":{"max":-79.41440457,"min":-79.41440457,"median":-79.41440457}},"features":[{"properties":{"neighbourhood name":"Lotherton","latitude":43.72254756,"establishment name":"Birth Control and V D Information Centre","accessibility":null,"website":"http://birthcontrolvd.org/","parking available":null,"postal code":"M6B 4E7","phone":"416-789-4541","fax":null,"capacity":null,"services":"Provides educational and clinical services by providing free reproductive and sexual health testing and councelling","business hours":"Office hours are 10am-5pm","longitude":-79.41440457,"id":"a88va99ouwe5","address":"403 - 960 Lawrence Ave. West","personal requirements":"All clinics are by appointment"},"type":"Feature","geometry":{"type":"Point","coordinates":[-79.41440457,43.72254756]}}],"is_temporal":false,"author":{"url":"","metadata":"","contact_name":"","contact_address":"","source":"","contact_phone":""},"source":"","pagination":{"sort":null,"start":0,"total":1,"limit":1000000},"state":"complete","tags":"","published":"2014-08-14T16:31:53-04:00","id":271475}