{"type":"FeatureCollection","data_type":"Dataset","url_type":null,"permissions":[{"permissions":{"download":true,"view":true},"group_id":"everyone"}],"classification":null,"title":"Human Assets- Steeles L'Amoreaux","count":4,"stream_id":271611,"contributor":{"url":"http://geocommons.com/users/50466","name":"SteelesAmoreauxANC"},"data_attributes":null,"calculation_params":null,"icon_link":null,"link":"http://geocommons.com/overlays/271611.json","extent":[-79.3041,43.7975,-79.3041,43.7975],"geometry_types":["point"],"unique_name":null,"name":"Human Assets- Steeles L'Amoreaux","feature_count":4,"description":"","next_feature":null,"is_raster":false,"short_classification":"Y","stats":{"latitude":{"max":43.79747473,"variance":0.0,"mean":43.79747473,"stdev":0.0,"min":43.79747473,"median":43.79747473},"longitude":{"max":-79.30409702,"variance":0.0,"mean":-79.30409702,"stdev":0.0,"min":-79.30409702,"median":-79.30409702}},"features":[{"properties":{"latitude":43.79747473,"neighbourhood":"Steeles - L'Amoreaux","postal code":"M1T 2T7","resident quotes":"\"I would talk about my neighbourhood in terms of the maintenance with engagement and diversity. Diversity and the commitment to engage as a community are not shown in every neighbourhood. Sometimes, it is not easy to find strategies to engage residents to a neighbourhood association, but I think my residential area has a well organized team to promote this association. The backbone of any neighbourhood organization is the residents that keep it firm.\" - Sellviya Nicholas Anton","anc office address":"6-331 Glendower Circuit","longitude":-79.30409702,"id":"a89fwv7zbgoa"},"type":"Feature","geometry":{"type":"Point","coordinates":[-79.30409702,43.79747473]}},{"properties":{"latitude":43.79747473,"neighbourhood":"Steeles - L'Amoreaux","postal code":"M1T 2T7","resident quotes":"\"This is a very multicultural and diverse neighbourhood.\" - Thevehi Rajanathen","anc office address":"6-331 Glendower Circuit","longitude":-79.30409702,"id":"a89fwv89qwu1"},"type":"Feature","geometry":{"type":"Point","coordinates":[-79.30409702,43.79747473]}},{"properties":{"latitude":43.79747473,"neighbourhood":"Steeles - L'Amoreaux","postal code":"M1T 2T7","resident quotes":"\"This is a harmony neighbourhood. There are many programs in place. But this is also a poverty neighbourhood.\" - Zhen Dong Hu","anc office address":"6-331 Glendower Circuit","longitude":-79.30409702,"id":"a89fwvan55vr"},"type":"Feature","geometry":{"type":"Point","coordinates":[-79.30409702,43.79747473]}},{"properties":{"latitude":43.79747473,"neighbourhood":"Steeles - L'Amoreaux","postal code":"M1T 2T7","resident quotes":"\"This neighbourhood is helpful and it helps reduce stress.\" - Kugenthra Mahendran","anc office address":"6-331 Glendower Circuit","longitude":-79.30409702,"id":"a89fwuvn4jed"},"type":"Feature","geometry":{"type":"Point","coordinates":[-79.30409702,43.79747473]}}],"is_temporal":false,"author":{"url":"","metadata":"","contact_name":"","contact_address":"","source":"","contact_phone":""},"source":"","pagination":{"sort":null,"start":0,"total":4,"limit":1000000},"state":"complete","tags":"","published":"2014-08-14T16:38:07-04:00","id":271611}