{"type":"FeatureCollection","data_type":"Dataset","url_type":null,"permissions":[{"permissions":{"download":true,"view":true},"group_id":"everyone"}],"classification":null,"title":"Daycares- Steeles L'Amoreaux","count":4,"stream_id":271614,"contributor":{"url":"http://geocommons.com/users/50466","name":"SteelesAmoreauxANC"},"data_attributes":null,"calculation_params":null,"icon_link":null,"link":"http://geocommons.com/overlays/271614.json","extent":[-79.3309,43.7973,-79.2791,43.827],"geometry_types":["point"],"unique_name":null,"name":"Daycares- Steeles L'Amoreaux","feature_count":4,"description":"","next_feature":null,"is_raster":false,"short_classification":"Y","stats":{"latitude":{"max":43.826957,"variance":0.000200821355666615,"mean":43.8105695,"stdev":0.0141711451783762,"min":43.797341,"median":43.817763},"longitude":{"max":-79.279064,"variance":0.000535264177583275,"mean":-79.29906025,"stdev":0.0231357770040964,"min":-79.33086,"median":-79.285251}},"features":[{"properties":{"neighbourhood name":"Steeles-L'Amoreaux","latitude":43.817763,"establishment name":"YMCA of Greater Toronto","accessibility":null,"website":"ymcagta.org","parking available":null,"postal code":"M1V 4P9","phone":"416-298-8911","fax":null,"capacity":null,"services":"Child care ages 2.5 to 12","business hours":"M-F: 7am-6pm","longitude":-79.285251,"id":"a89fxjawamo3","address":"410 Pt Royal Tr.","personal requirements":null},"type":"Feature","geometry":{"type":"Point","coordinates":[-79.285251,43.817763]}},{"properties":{"neighbourhood name":"Steeles-L'Amoreaux","latitude":43.797341,"establishment name":"Chester Le Child Care Centre","accessibility":"Yes","website":"http://www.chesterlecc.ca/","parking available":"Yes","postal code":"M1W 2N4","phone":"416-491-3456","fax":"416-491-1686","capacity":"10 Infant, 20 Toddler, 32 Preschool","services":"Child care fee subsidy may be available to help with the cost of child care","business hours":null,"longitude":-79.33086,"id":"a89fxjmz2jid","address":"142-160 Chester Le Blvd.","personal requirements":null},"type":"Feature","geometry":{"type":"Point","coordinates":[-79.33086,43.797341]}},{"properties":{"neighbourhood name":"Steeles-L'Amoreaux","latitude":43.826957,"establishment name":"Tinytodd's Montasory &amp; Daycare","accessibility":null,"website":null,"parking available":null,"postal code":"M1V 4E7","phone":"416-332-9404 ?","fax":null,"capacity":null,"services":null,"business hours":null,"longitude":-79.279064,"id":"a89fxjmprpfd","address":"410 Goldhawk Tr.","personal requirements":null},"type":"Feature","geometry":{"type":"Point","coordinates":[-79.279064,43.826957]}},{"properties":{"neighbourhood name":"Steeles-L'Amoreaux","latitude":43.800217,"establishment name":"St Nicholas Child Care Centre","accessibility":null,"website":"http://www.stnicholas-goc.com/home.html","parking available":null,"postal code":"M1T 3T4","phone":"416-850-5652","fax":"416-850-5653","capacity":null,"services":null,"business hours":null,"longitude":-79.301066,"id":"a89fxjai57op","address":"3840 Finch Ave. East","personal requirements":null},"type":"Feature","geometry":{"type":"Point","coordinates":[-79.301066,43.800217]}}],"is_temporal":false,"author":{"url":"","metadata":"","contact_name":"","contact_address":"","source":"","contact_phone":""},"source":"","pagination":{"sort":null,"start":0,"total":4,"limit":1000000},"state":"complete","tags":"","published":"2014-08-14T16:38:19-04:00","id":271614}