{"type":"FeatureCollection","data_type":"Data Feed","url_type":"rss","permissions":[{"permissions":{"download":true,"view":true},"group_id":"everyone"}],"classification":null,"title":"PD Near Me Data","count":1,"stream_id":272046,"contributor":{"url":"http://geocommons.com/users/50554","name":"drezac@edreach.us"},"data_attributes":null,"calculation_params":null,"icon_link":null,"link":"http://geocommons.com/overlays/272046.json","extent":[-122.444,48.5306,-122.444,48.5306],"geometry_types":["point"],"unique_name":null,"name":"PD Near Me Data","feature_count":1,"description":"","next_feature":null,"is_raster":false,"short_classification":"Y","stats":{"updated":{"max":"2012/09/03 18:30:48 -0400","min":"2012/09/03 18:30:48 -0400","median":"2012/09/03 18:30:48 -0400"}},"features":[{"properties":{"title":"9/3/2012 17:26:23","geo_score":0.333,"id":"a8c9q79prcoz","description":"date: 10/29/2012, titleofprofessionaldevelopmentevent: TechCon 2012, sponsoringcompany: Northern Illinois University, typeofevent: Conference, addressofevent: NIU-Naperville 1120 E. Diehl Rd. Naperville, IL 60563, eventtags: math, ethics, policy, social media, linktoconferencewebsite: http://illinoistechcon.com/, descriptionofevent: This one-day intensive conference focuses on the effective use of technology in education. TechCon is a must-attend event for all levels of education professionals — from the most technology-savvy pros to those who need exposure to this ever-changing and dynamic field., linktoresources: http://illinoistechcon.com/downloads","link:self (application/atom+xml)":"https://spreadsheets.google.com/feeds/list/0AmWzaaRnYL0HdDk5N3k4eWtIUzVsVTlPY0hoa1MzUlE/od6/public/basic/ba0fz","updated":{"end_time":"2012/09/03 18:30:49 -0400","original":"2012-09-03T22:30:48.334Z","granularity":"usec","time":"2012/09/03 18:30:48 -0400"},"geo_precision":"street"},"type":"Feature","geometry":{"type":"Point","coordinates":[-122.444241,48.530581]}}],"is_temporal":true,"author":{"url":"","metadata":"","contact_name":"redferntwo","contact_address":"","source":"redferntwo","contact_phone":""},"source":"","pagination":{"sort":null,"start":0,"total":1,"limit":1000000},"state":"complete","tags":"","published":"2012-09-03T16:00:00Z","id":272046}