{"type":"FeatureCollection","data_type":"Dataset","url_type":null,"permissions":[{"permissions":{"download":true,"view":true},"group_id":"everyone"}],"classification":null,"title":"UVints BC WineFromFruit","count":3,"stream_id":273205,"contributor":{"url":"http://geocommons.com/users/50905","name":"rdaudt"},"data_attributes":null,"calculation_params":null,"icon_link":null,"link":"http://geocommons.com/overlays/273205.json","extent":[-124.036,49.0456,-122.791,49.2266],"geometry_types":["point"],"unique_name":null,"name":"UVints BC WineFromFruit","feature_count":3,"description":"","next_feature":null,"is_raster":false,"short_classification":"Y","stats":{"latitude":{"max":49.22664,"variance":0.0105272233343336,"mean":49.1639973333333,"stdev":0.102602257939743,"min":49.045589,"median":49.219763},"pop 2011":{"max":473238,"variance":38157131469.0,"mean":263221.0,"stdev":195338.504829437,"min":86961,"median":229464},"longitude":{"max":-122.791267,"variance":0.452453701860997,"mean":-123.266162,"stdev":0.672646788337681,"min":-124.035878,"median":-122.971341}},"features":[{"properties":{"city":"Burnaby","business":"Chateau Vino Wine Cellar Limited","vineco":null,"flickr":null,"cellar craft":null,"latitude":49.219763,"twitter":null,"area type":"C","prov":"BC","wine from fruit":"Wine from fruit","regional district":"Greater Vancouver","old product":"OTHER","products":"Wine from fruit Unknown","marker":"purple_blank","yotube":null,"website":"http://www.chateauvino.com/","pop 2011":229464,"postal code":"V5E 1C5","winexpert":null,"winekitz":null,"full address":"6340 Kingsway,Burnaby,BC,V5E 1C5,Canada","phone":"604-439-8483","rj spagnols":null,"longitude":-122.971341,"googleplus":null,"id":"a8hq9i5egttv","address":"6340 Kingsway","unknown":"Unknown","email":"info@chateauvino.com","facebook":null},"type":"Feature","geometry":{"type":"Point","coordinates":[-122.971341,49.219763]}},{"properties":{"city":"Surrey","business":"D'vine Wine","vineco":null,"flickr":null,"cellar craft":null,"latitude":49.045589,"twitter":null,"area type":"C","prov":"BC","wine from fruit":"Wine from fruit","regional district":"Greater Vancouver","old product":"OTHER","products":"Wine from fruit","marker":"purple_blank","yotube":null,"website":"http://www.winekitz.com","pop 2011":473238,"postal code":"V4A 2J5","winexpert":null,"winekitz":null,"full address":"15562 24 Ave,Surrey,BC,V4A 2J5,Canada","phone":"250-753-5118","rj spagnols":null,"longitude":-122.791267,"googleplus":null,"id":"a8hq9i3ibtt8","address":"15562 24 Ave","unknown":null,"email":"dvinewines@shaw.ca","facebook":null},"type":"Feature","geometry":{"type":"Point","coordinates":[-122.791267,49.045589]}},{"properties":{"city":"Nanaimo","business":"Rainy Crick Wine","vineco":null,"flickr":null,"cellar craft":null,"latitude":49.22664,"twitter":null,"area type":"C","prov":"BC","wine from fruit":"Wine from fruit","regional district":"Nanaimo","old product":"OTHER","products":"Wine from fruit","marker":"purple_blank","yotube":null,"website":"http://www.rainycrickwine.ca/","pop 2011":86961,"postal code":"V9T 6N1","winexpert":null,"winekitz":null,"full address":"106-5070 Uplands Dr,Nanaimo,BC,V9T 6N1,Canada","phone":"250 756 9220","rj spagnols":null,"longitude":-124.035878,"googleplus":null,"id":"a8hq9hshp9lc","address":"106-5070 Uplands Dr","unknown":null,"email":"rainycrickwine@shaw.ca","facebook":null},"type":"Feature","geometry":{"type":"Point","coordinates":[-124.035878,49.22664]}}],"is_temporal":false,"author":{"url":"","metadata":"","contact_name":"","contact_address":"","source":"","contact_phone":""},"source":"","pagination":{"sort":null,"start":0,"total":3,"limit":1000000},"state":"complete","tags":"","published":"2014-08-14T18:52:28-04:00","id":273205}