{"type":"FeatureCollection","data_type":"Dataset","url_type":null,"permissions":[{"permissions":{"download":true,"view":true},"group_id":"everyone"}],"classification":null,"title":"Kerrville Fort Coordinates","count":5,"stream_id":273611,"contributor":{"url":"http://geocommons.com/users/51111","name":"WF01"},"data_attributes":null,"calculation_params":null,"icon_link":null,"link":"http://geocommons.com/overlays/273611.json","extent":[-111.3,39.187,-94.192,47.9996],"geometry_types":["point"],"unique_name":null,"name":"Kerrville Fort Coordinates","feature_count":5,"description":"","next_feature":null,"is_raster":false,"short_classification":"Y","stats":{"latitude":{"max":47.9996,"variance":13.548724067,"mean":45.25848,"stdev":3.68085914794359,"min":39.187,"median":47.2519},"longitude":{"max":-94.192,"variance":38.624827147,"mean":-102.23558,"stdev":6.21488754097771,"min":-111.3,"median":-101.2753}},"features":[{"properties":{"place":"Fort Pierre","latitude":44.3536,"longitude":-100.3733,"id":"a8isdtp3ai16"},"type":"Feature","geometry":{"type":"Point","coordinates":[-100.3733,44.3536]}},{"properties":{"place":"Fort Clark","latitude":47.2519,"longitude":-101.2753,"id":"a8isdti4h8qm"},"type":"Feature","geometry":{"type":"Point","coordinates":[-101.2753,47.2519]}},{"properties":{"place":"Fort Union","latitude":47.9996,"longitude":-104.0373,"id":"a8isdtoy8wy3"},"type":"Feature","geometry":{"type":"Point","coordinates":[-104.0373,47.9996]}},{"properties":{"place":"Fort MacKenzie","latitude":47.5003,"longitude":-111.3,"id":"a8isdtiqdhi6"},"type":"Feature","geometry":{"type":"Point","coordinates":[-111.3,47.5003]}},{"properties":{"place":"Fort Osage","latitude":39.187,"longitude":-94.192,"id":"a8isdtpx2q4r"},"type":"Feature","geometry":{"type":"Point","coordinates":[-94.192,39.187]}}],"is_temporal":false,"author":{"url":"","metadata":null,"contact_name":null,"contact_address":null,"source":null,"contact_phone":null},"source":"","pagination":{"sort":null,"start":0,"total":5,"limit":1000000},"state":"complete","tags":"","published":"2014-08-14T19:35:40-04:00","id":273611}