{"type":"FeatureCollection","data_type":"Dataset","url_type":null,"permissions":[{"permissions":{"download":true,"view":true},"group_id":"everyone"}],"classification":null,"title":"\nOntario MPP Constituency Offices\n","count":2,"stream_id":27423,"contributor":{"url":"http://geocommons.com/users/11444","name":"platial"},"data_attributes":null,"calculation_params":null,"icon_link":null,"link":"http://geocommons.com/overlays/27423.json","extent":[-79.3925,42.3833,-71.4167,43.7231],"geometry_types":["point"],"unique_name":null,"name":"\nOntario MPP Constituency Offices\n","feature_count":2,"description":"\nA Map by Rossinblu\n\nLocations of the Constitutency Offices for Ontario Members of Provincial Parliament (MPPs)\n","next_feature":null,"is_raster":false,"short_classification":"Y","stats":{},"features":[{"properties":{"name":"Title or search term","description":"Posted by RossinbluToronto<a title=\"Built for Community Mapping\" href=\"http://www.platial.com\"><img src=\"http://media.geocommons.com/platial/images/logotype_small.jpg\"></a>","id":"a635pf938bs6"},"type":"Feature","geometry":{"type":"Point","coordinates":[-79.392486,43.723057]}},{"properties":{"name":"Title or search term","description":"Posted by Rossinblusudbury<a title=\"Built for Community Mapping\" href=\"http://www.platial.com\"><img src=\"http://media.geocommons.com/platial/images/logotype_small.jpg\"></a>","id":"a635pfa3s2re"},"type":"Feature","geometry":{"type":"Point","coordinates":[-71.41667,42.38333]}}],"is_temporal":false,"author":{"url":"http://www.platial.com/map/93680","metadata":null,"contact_name":"rossinblu","contact_address":null,"source":"platial:rossinblu","contact_phone":null},"source":"http://www.platial.com/map/93680","pagination":{"sort":null,"start":0,"total":2,"limit":1000000},"state":"complete","tags":"platial,platial:id=93680,platial:user=rossinblu","published":"2010-03-02T17:00:00Z","id":27423}