{"type":"FeatureCollection","data_type":"Dataset","url_type":null,"permissions":[{"permissions":{"download":true,"view":true},"group_id":"everyone"}],"classification":null,"title":"Lisztomanias 2012 : jeudi 1er novembre","count":5,"stream_id":274876,"contributor":{"url":"http://geocommons.com/users/42827","name":"jflacou"},"data_attributes":null,"calculation_params":null,"icon_link":null,"link":"http://geocommons.com/overlays/274876.json","extent":[1.69103,46.8092,1.69466,46.8135],"geometry_types":["point"],"unique_name":null,"name":"Lisztomanias 2012 : jeudi 1er novembre","feature_count":5,"description":"","next_feature":null,"is_raster":false,"short_classification":"Y","stats":{},"features":[{"properties":{"Date et heure":"Jeudi 1er novembre : 10h-13h","Lieu":"Chapelle des Rédemptoristes","Artistes":"<b>Giovanni Bellucci</b>, piano","Pratique":"<a href=\"http://www.lisztomanias.fr/filesopen/DEPLIANT%20lisztomanias%202012.pdf\">Téléchargez le programme (Pdf, 1,4 Mo)</a>","Programme":"<b>Académie de piano</b>","id":"a8nu79r54y9p","GPS":"1.69166667 - 46.80916667"},"type":"Feature","geometry":{"type":"Point","coordinates":[1.69166667,46.80916667]}},{"properties":{"Date et heure":"Jeudi 1er novembre : 14h","Lieu":"Chapelle des Rédemptoristes","Artistes":"<b>Petra Mengeringhausen</b>","Pratique":"<a href=\"http://www.lisztomanias.fr/filesopen/DEPLIANT%20lisztomanias%202012.pdf\">Téléchargez le programme (Pdf, 1,4 Mo)</a>","Programme":"<b>Atelier \"Chopin pour les enfants\"</b> (7-11 ans - Inscription gratuite Office de Tourisme de Châteauroux)","id":"a8nu7a0bo25h","GPS":"1.69166667 - 46.80916667"},"type":"Feature","geometry":{"type":"Point","coordinates":[1.69166667,46.80916667]}},{"properties":{"Date et heure":"Jeudi 1er novembre : 16h","Lieu":"Salle Equinoxe","Artistes":"<b>Sélim Mazari</b> et <b>Paolo Rigutto</b>, piano (élèves de Brigitte Hengerer)","Pratique":"<a href=\"http://www.lisztomanias.fr/filesopen/DEPLIANT%20lisztomanias%202012.pdf\">Téléchargez le programme (Pdf, 1,4 Mo)</a>","Programme":"<b>Concert \"Hommage à Brigite Hengerer\"</b>(Chopin/Liszt/Debussy)","id":"a8nu79s81sr0","GPS":"1.69103 - 46.80925"},"type":"Feature","geometry":{"type":"Point","coordinates":[1.69103,46.80925]}},{"properties":{"Date et heure":"Jeudi 1er novembre : 18h","Lieu":"Musée Bertrand","Artistes":"<b>Wim Van Moerbeke</b>, piano Clementi 1821","Pratique":"<a href=\"http://www.lisztomanias.fr/filesopen/DEPLIANT%20lisztomanias%202012.pdf\">Téléchargez le programme (Pdf, 1,4 Mo)</a>","Programme":"<b>Récital \"La France de Liszt\"</b>(Chopin/Liszt)","id":"a8nu7a6szzke","GPS":"1.69466 - 46.81347"},"type":"Feature","geometry":{"type":"Point","coordinates":[1.69466,46.81347]}},{"properties":{"Date et heure":"Jeudi 1er novembre : 21h","Lieu":"Salle Equinoxe","Artistes":"<b>Bruno Rigutto, </b>piano - <b>Dominique de Williencourt, </b>violoncelle","Pratique":"<a href=\"http://www.lisztomanias.fr/filesopen/DEPLIANT%20lisztomanias%202012.pdf\">Téléchargez le programme (Pdf, 1,4 Mo)</a>","Programme":"<b>Concert \"Hommage à Brigitte Hengerer\"</b>(Liszt/Chopin/Franck/Debussy)<i>Pièces pour piano seul et pour piano et violoncelle</i>","id":"a8nu7a5zka0b","GPS":"1.69103 - 46.80925"},"type":"Feature","geometry":{"type":"Point","coordinates":[1.69103,46.80925]}}],"is_temporal":false,"author":{"url":"","metadata":"","contact_name":"","contact_address":"","source":"","contact_phone":""},"source":"","pagination":{"sort":null,"start":0,"total":5,"limit":1000000},"state":"complete","tags":"","published":"2014-08-14T21:37:16-04:00","id":274876}