{"type":"FeatureCollection","data_type":"Dataset","url_type":null,"permissions":[{"permissions":{"download":true,"edit":true,"view":true},"group_id":42518},{"permissions":{"download":true,"view":true},"group_id":"everyone"}],"classification":null,"title":"Q3 NoNo Competitors Pacific Coast 091812","count":2,"stream_id":275227,"contributor":{"url":"http://geocommons.com/users/39447","name":"sam.felipe"},"data_attributes":null,"calculation_params":null,"icon_link":null,"link":"http://geocommons.com/overlays/275227.json","extent":[-122.291,37.7857,-121.97,37.7868],"geometry_types":["point"],"unique_name":null,"name":"Q3 NoNo Competitors Pacific Coast 091812","feature_count":2,"description":"","next_feature":null,"is_raster":false,"short_classification":"Y","stats":{},"features":[{"properties":{"name of competitor":"Pacific Coast Title","city":"Walnut Creek","zip":"94537","geo_score":0.329,"street address":"1990 N. California Blvd","id":"a8otajykkipk","geo_precision":"street"},"type":"Feature","geometry":{"type":"Point","coordinates":[-122.291143,37.786815]}},{"properties":{"name of competitor":"Pacific Coast Title","city":"Danville","zip":"94526","geo_score":0.571,"street address":"318 Diablo Rd, ste B","id":"a8otak7eon0d","geo_precision":"street"},"type":"Feature","geometry":{"type":"Point","coordinates":[-121.969869,37.785685]}}],"is_temporal":false,"author":{"url":"","metadata":"","contact_name":"","contact_address":"","source":"","contact_phone":""},"source":"","pagination":{"sort":null,"start":0,"total":2,"limit":1000000},"state":"complete","tags":"stca","published":"2014-08-14T22:09:44-04:00","id":275227}