{"type":"FeatureCollection","data_type":"Dataset","url_type":null,"permissions":[{"permissions":{"download":true,"edit":true,"view":true},"group_id":42518},{"permissions":{"download":true,"view":true},"group_id":"everyone"}],"classification":null,"title":"Q3_LA_Competitors_Ticor_091812","count":2,"stream_id":275254,"contributor":{"url":"http://geocommons.com/users/39447","name":"sam.felipe"},"data_attributes":null,"calculation_params":null,"icon_link":null,"link":"http://geocommons.com/overlays/275254.json","extent":[-119.055,34.1479,-118.141,34.2191],"geometry_types":["point"],"unique_name":null,"name":"Q3_LA_Competitors_Ticor_091812","feature_count":2,"description":"","next_feature":null,"is_raster":false,"short_classification":"Y","stats":{},"features":[{"properties":{"name of competitor":"Ticor Title","city":"Camarillo","zip":"93010","geo_score":0.902,"street address":"330 North Lantana Street","id":"a8ovkxg489my","geo_precision":"range"},"type":"Feature","geometry":{"type":"Point","coordinates":[-119.054931,34.219106]}},{"properties":{"name of competitor":"Ticor Title","city":"Pasadena","zip":"91101","geo_score":0.61,"street address":"199 South Los Robles #120","id":"a8ovkxaank2s","geo_precision":"range"},"type":"Feature","geometry":{"type":"Point","coordinates":[-118.141387,34.147884]}}],"is_temporal":false,"author":{"url":"","metadata":"","contact_name":"","contact_address":"","source":"","contact_phone":""},"source":"","pagination":{"sort":null,"start":0,"total":2,"limit":1000000},"state":"complete","tags":"stca","published":"2014-08-14T22:10:11-04:00","id":275254}