{"type":"FeatureCollection","data_type":"Dataset","url_type":null,"permissions":[{"permissions":{"download":true,"view":true},"group_id":"everyone"}],"classification":null,"title":"NP1","count":1,"stream_id":275328,"contributor":{"url":"http://geocommons.com/users/3995","name":"amazon"},"data_attributes":null,"calculation_params":null,"icon_link":null,"link":"http://geocommons.com/overlays/275328.json","extent":[-84.5682,37.8796,-84.5682,37.8796],"geometry_types":["point"],"unique_name":null,"name":"NP1","feature_count":1,"description":"","next_feature":null,"is_raster":false,"short_classification":"Y","stats":{"total market value":{"max":467475.86,"min":467475.86,"median":467475.86},"market value of real estate":{"max":307475.86,"min":307475.86,"median":307475.86},"market value of tax credits":{"max":160000,"min":160000,"median":160000},"gross income":{"max":119665,"min":119665,"median":119665}},"features":[{"properties":{"name":"Nicholasville Green Townhomes","city":"Nicholasville","zip":"40356","market value of real estate":307475.86,"total market value":467475.86,"market value of tax credits":160000,"geo_score":1.0,"gross income":119665,"id":"a8ozvlp5r6bo","address":"108 North Central Ave","geo_precision":"range","state":"KY"},"type":"Feature","geometry":{"type":"Point","coordinates":[-84.568164,37.87959]}}],"is_temporal":false,"author":{"url":"","metadata":"","contact_name":"","contact_address":"","source":"","contact_phone":""},"source":"","pagination":{"sort":null,"start":0,"total":1,"limit":1000000},"state":"complete","tags":"","published":"2012-09-19T16:00:00Z","id":275328}