{"type":"FeatureCollection","data_type":"Dataset","url_type":null,"permissions":[{"permissions":{"download":true,"view":true},"group_id":"everyone"}],"classification":null,"title":"Birmingham MP's","count":10,"stream_id":275712,"contributor":{"url":"http://geocommons.com/users/51903","name":"rocketmandave1"},"data_attributes":null,"calculation_params":null,"icon_link":null,"link":"http://geocommons.com/overlays/275712.json","extent":[-1.96283,52.3979,-1.8014,52.5592],"geometry_types":["point"],"unique_name":null,"name":"Birmingham MP's","feature_count":10,"description":"","next_feature":null,"is_raster":false,"short_classification":"Y","stats":{"lattitude":{"max":52.55924,"variance":0.00245640989448902,"mean":52.4773856,"stdev":0.0495621820997524,"min":52.397929,"median":52.486583},"id":{"max":10,"variance":9.16666666666667,"mean":5.5,"stdev":3.02765035409749,"min":1,"median":6},"longitude":{"max":-1.801399,"variance":0.00324077883955556,"mean":-1.883741,"stdev":0.0569278388800731,"min":-1.962828,"median":-1.871467},"party":{"count":3,"counts_by_value":{"Liberal Democrat":1,"Conservative":1,"Labour":8},"list":["Labour","Conservative","Liberal Democrat"]}},"features":[{"properties":{"lattitude":52.455234,"mp":"Gisela Stuart","id":"a8qe17d622uh","internet":"http://www.giselastuartmp.co.uk","flag":"B17 0AQ","longitude":-1.962828,"constituency":"Edgbaston","party":"Labour","email":"stuartg@parliament.uk"},"type":"Feature","geometry":{"type":"Point","coordinates":[-1.962828,52.455234]}},{"properties":{"lattitude":52.521785,"mp":"Jack Dromey","id":"a8qe17g0towx","internet":null,"flag":"B23 6DE","longitude":-1.848228,"constituency":"Erdington","party":"Labour","email":"jack.dromey.mp@parliament.uk"},"type":"Feature","geometry":{"type":"Point","coordinates":[-1.848228,52.521785]}},{"properties":{"lattitude":52.441847,"mp":"Roger Godsiff","id":"a8qe1759nuom","internet":null,"flag":"B13 9JQ","longitude":-1.871467,"constituency":"Hall Green","party":"Labour","email":"novellm@parliament.uk"},"type":"Feature","geometry":{"type":"Point","coordinates":[-1.871467,52.441847]}},{"properties":{"lattitude":52.492773,"mp":"Liam Byrne","id":"a8qe17exwwls","internet":null,"flag":"B8 1PW","longitude":-1.853939,"constituency":"Hodge Hill","party":"Labour","email":"byrnel@parliament.uk"},"type":"Feature","geometry":{"type":"Point","coordinates":[-1.853939,52.492773]}},{"properties":{"lattitude":52.486583,"mp":"Shabana Mahmood","id":"a8qe175p8xxf","internet":"http://www.shabanamahmood.org","flag":"B19 3LZ","longitude":-1.901923,"constituency":"Ladywood","party":"Labour","email":"shabana.mahmood.mp@parliament.uk"},"type":"Feature","geometry":{"type":"Point","coordinates":[-1.901923,52.486583]}},{"properties":{"lattitude":52.397929,"mp":"Richard Burden","id":"a8qe17d2lale","internet":"http://www.richardburden.com","flag":"B38 8HR","longitude":-1.954528,"constituency":"Northfield","party":"Labour","email":"burdenr@parliament.uk"},"type":"Feature","geometry":{"type":"Point","coordinates":[-1.954528,52.397929]}},{"properties":{"lattitude":52.528485,"mp":"Khalid Mahmood","id":"a8qe17e81ro9","internet":"http://www.khalidmahmoodmp.co.uk","flag":"B42 1PB","longitude":-1.912635,"constituency":"Perry Barr","party":"Labour","email":"hmoodk@parliament.uk"},"type":"Feature","geometry":{"type":"Point","coordinates":[-1.912635,52.528485]}},{"properties":{"lattitude":52.431995,"mp":"Steve McCabe","id":"a8qe174vt79e","internet":"http://www.stevemccabe-mp.org.uk","flag":"B29 7SQ","longitude":-1.924268,"constituency":"Selly Oak","party":"Labour","email":"mccabes@parliament.uk"},"type":"Feature","geometry":{"type":"Point","coordinates":[-1.924268,52.431995]}},{"properties":{"lattitude":52.55924,"mp":"Andrew Mitchell","id":"a8qe17gy8wvh","internet":null,"flag":"B76 1NX","longitude":-1.801399,"constituency":"Sutton Coldfield","party":"Conservative","email":"andrewmitchellmp@parliament.uk"},"type":"Feature","geometry":{"type":"Point","coordinates":[-1.801399,52.55924]}},{"properties":{"lattitude":52.457985,"mp":"John Hemming","id":"a8qe179z04f9","internet":"http://www.john.hemming.name","flag":"B26 1JB","longitude":-1.806195,"constituency":"Yardley","party":"Liberal Democrat","email":"hemmingj@parliament.uk"},"type":"Feature","geometry":{"type":"Point","coordinates":[-1.806195,52.457985]}}],"is_temporal":false,"author":{"url":"","metadata":"","contact_name":"","contact_address":"","source":"","contact_phone":""},"source":"","pagination":{"sort":null,"start":0,"total":10,"limit":1000000},"state":"complete","tags":"","published":"2014-08-14T22:36:07-04:00","id":275712}