{"type":"FeatureCollection","data_type":"Dataset","url_type":null,"permissions":[{"permissions":{"download":true,"view":true},"group_id":"everyone"}],"classification":null,"title":"Les îles du Fouzon","count":1,"stream_id":278414,"contributor":{"url":"http://geocommons.com/users/42827","name":"jflacou"},"data_attributes":null,"calculation_params":null,"icon_link":null,"link":"http://geocommons.com/overlays/278414.json","extent":[1.60811,47.2181,1.60811,47.2181],"geometry_types":["point"],"unique_name":null,"name":"Les îles du Fouzon","feature_count":1,"description":"","next_feature":null,"is_raster":false,"short_classification":"Y","stats":{},"features":[{"properties":{"SURFACE":"33 ha","SITE":"Les îles du Fouzon","id":"a8x7ejgv8e0e","GPS":"1.60811 - 47.21806"},"type":"Feature","geometry":{"type":"Point","coordinates":[1.60811,47.21806]}}],"is_temporal":false,"author":{"url":"","metadata":"","contact_name":"","contact_address":"","source":"","contact_phone":""},"source":"","pagination":{"sort":null,"start":0,"total":1,"limit":1000000},"state":"complete","tags":"","published":"2014-08-15T02:14:45-04:00","id":278414}