{"type":"FeatureCollection","data_type":"Dataset","url_type":null,"permissions":[{"permissions":{"download":true,"view":true},"group_id":"everyone"}],"classification":null,"title":"Le parc des Parelles","count":1,"stream_id":278421,"contributor":{"url":"http://geocommons.com/users/42827","name":"jflacou"},"data_attributes":null,"calculation_params":null,"icon_link":null,"link":"http://geocommons.com/overlays/278421.json","extent":[1.937,46.4593,1.937,46.4593],"geometry_types":["point"],"unique_name":null,"name":"Le parc des Parelles","feature_count":1,"description":"","next_feature":null,"is_raster":false,"short_classification":"Y","stats":{},"features":[{"properties":{"SURFACE":"24 ha","SITE":"Le Parc des Parelles","id":"a8x7exqizbsi","GPS":"1.93700 - 46.45931"},"type":"Feature","geometry":{"type":"Point","coordinates":[1.937,46.45931]}}],"is_temporal":false,"author":{"url":"","metadata":"","contact_name":"","contact_address":"","source":"","contact_phone":""},"source":"","pagination":{"sort":null,"start":0,"total":1,"limit":1000000},"state":"complete","tags":"","published":"2014-08-15T02:14:46-04:00","id":278421}