{"type":"FeatureCollection","data_type":"Dataset","url_type":null,"permissions":[{"permissions":{"download":true,"view":true},"group_id":"everyone"}],"classification":null,"title":"mypostocdes","count":3,"stream_id":284372,"contributor":{"url":"http://geocommons.com/users/53756","name":"andrewbower"},"data_attributes":null,"calculation_params":null,"icon_link":null,"link":"http://geocommons.com/overlays/284372.json","extent":[-163.118947,40.455601,-81.084882,60.314735],"geometry_types":["point"],"unique_name":null,"name":"mypostocdes","feature_count":3,"description":"","next_feature":null,"is_raster":false,"short_classification":"Y","stats":{},"features":[{"properties":{"geo_score":0.592,"id":"a9clrqenmry9","sw115pd":"ec3n1dy","geo_precision":"city"},"type":"Feature","geometry":{"type":"Point","coordinates":[-163.118947,60.314735]}},{"properties":{"geo_score":0.0,"id":"a9clrqbgevvu","sw115pd":"sw11 4du","geo_precision":"unmatched"},"type":"Feature","geometry":null},{"properties":{"geo_score":0.264,"id":"a9clrq7cauv4","sw115pd":"sw1p1qt","geo_precision":"street"},"type":"Feature","geometry":{"type":"Point","coordinates":[-81.084882,40.455601]}}],"is_temporal":false,"author":{"url":"","metadata":null,"contact_name":null,"contact_address":null,"source":null,"contact_phone":null},"source":"","pagination":{"sort":null,"start":0,"total":3,"limit":1000000},"state":"verified","tags":"","published":"2014-08-14T20:08:53-04:00","id":284372}