{"type":"FeatureCollection","data_type":"Dataset","url_type":null,"permissions":[{"permissions":{"download":true,"view":true},"group_id":"everyone"}],"classification":null,"title":"mtsoDTRTMIAP","count":3,"stream_id":284917,"contributor":{"url":"http://geocommons.com/users/12008","name":"pantheon"},"data_attributes":null,"calculation_params":null,"icon_link":null,"link":"http://geocommons.com/overlays/284917.json","extent":[-83.7125,41.8044,-83.6319,41.9214],"geometry_types":["point"],"unique_name":null,"name":"mtsoDTRTMIAP","feature_count":3,"description":"","next_feature":null,"is_raster":false,"short_classification":"Y","stats":{"longitude cs":{"max":-83.63185883,"variance":0.00165279092411742,"mean":-83.6692657466667,"stdev":0.0406545314093942,"min":-83.71253204,"median":-83.66340637},"mtso lata":{"max":340,"variance":0.0,"mean":340.0,"stdev":0.0,"min":340,"median":340},"fa cs":{"max":10147144,"variance":1554710565.33333,"mean":10121485.3333333,"stdev":39429.8182259738,"min":10076084,"median":10141228},"lata cs":{"max":340,"variance":0.0,"mean":340.0,"stdev":0.0,"min":340,"median":340},"latitude cs":{"max":41.92139053,"variance":0.00393078811236971,"mean":41.87593333,"stdev":0.0626959975785513,"min":41.80440903,"median":41.90200043},"zip cs":{"max":49270,"variance":394581.333333333,"mean":48907.3333333333,"stdev":628.157092878313,"min":48182,"median":49270}},"features":[{"properties":{"longitude cs":-83.66340637,"umts mtso":"DTRTMIAP","state cs":"MI","mtso lata":340,"need by date":"3/31/2013","lata cs":340,"fa cs":10076084,"latitude cs":41.92139053,"ethernet bandwidth required":"2 * 100Mb/S EVCs","zip cs":49270,"id":"a9e6gp1ehj8t","city cs":"PETERSBURG","address cs":"15583 DUNBAR","county cs":"MONROE","swc cs":"PTBGMIXJ"},"type":"Feature","geometry":{"type":"Point","coordinates":[-83.66340637,41.92139053]}},{"properties":{"longitude cs":-83.71253204,"umts mtso":"DTRTMIAP","state cs":"MI","mtso lata":340,"need by date":"2014","lata cs":340,"fa cs":10141228,"latitude cs":41.90200043,"ethernet bandwidth required":"2 * 50Mb/S EVCs","zip cs":49270,"id":"a9e6gp0dtlz0","city cs":"PETERSBURG","address cs":"87 RAILROAD ST","county cs":"MONROE","swc cs":"PTBGMIXJ"},"type":"Feature","geometry":{"type":"Point","coordinates":[-83.71253204,41.90200043]}},{"properties":{"longitude cs":-83.63185883,"umts mtso":"DTRTMIAP","state cs":"MI","mtso lata":340,"need by date":"3/31/2013","lata cs":340,"fa cs":10147144,"latitude cs":41.80440903,"ethernet bandwidth required":"2 * 50Mb/S EVCs","zip cs":48182,"id":"a9e6gp3d9p49","city cs":"TEMPERANCE","address cs":"10483 SECOR ROAD","county cs":"MONROE","swc cs":"LMVLMIXI"},"type":"Feature","geometry":{"type":"Point","coordinates":[-83.63185883,41.80440903]}}],"is_temporal":false,"author":{"url":"","metadata":"","contact_name":"","contact_address":"","source":"","contact_phone":""},"source":"","pagination":{"sort":null,"start":0,"total":3,"limit":1000000},"state":"complete","tags":"","published":"2014-08-14T21:00:49-04:00","id":284917}