{"type":"FeatureCollection","data_type":"Dataset","url_type":null,"permissions":[{"permissions":{"download":true,"edit":true,"view":true},"group_id":55007},{"permissions":{"download":true,"view":true},"group_id":"everyone"}],"classification":null,"title":"National Program for Sustainable Upland Farming through the Establishment of &quot;Barangay Sagip Saka&quot;","count":3,"stream_id":285642,"contributor":{"url":"http://geocommons.com/users/53195","name":"konek3rio"},"data_attributes":null,"calculation_params":null,"icon_link":null,"link":"http://geocommons.com/overlays/285642.json","extent":[121.789,9.44945,125.687,18.1595],"geometry_types":["point"],"unique_name":null,"name":"National Program for Sustainable Upland Farming through the Establishment of \"Barangay Sagip Saka\"","feature_count":3,"description":"","next_feature":null,"is_raster":false,"short_classification":"Y","stats":{},"features":[{"properties":{"name":"Iloilo : National Program for Sustainable Upland Farming through the Establishment of \"Barangay Sagip Saka\"","description":"<b>FUNDING AGENCY</b>\nNational Program for Sustainable Upland Farming through the Establishment of \"Barangay Sagip Saka\" : WB/GEF<b>Project Cost (US $ '000)</b><b>Loan proceeds</b><b>Grant proceeds : </b>4,999.00 <b>GOP : </b>2,310.00 <b>Total : </b>7,309.00 <b>Project duration : </b>2010-2014 <b>Project location : </b>Region 2 - Cagayan; Region 6 - Iloilo; Region 13 - Surigao del Norte <a href=\"http://faspo.denr.gov.ph/Prog_Proj/factsheet_profileasof12092011/GIAHS.pdf\">Project Briefer</a><a href=\"http://faspo.denr.gov.ph/Prog_Proj/Program.htm\">For more info go to FASPO website</a>","id":"a9h6e5tukkmu"},"type":"Feature","geometry":{"type":"Point","coordinates":[122.897201560323,11.1316556273719]}},{"properties":{"name":"Cagayan : National Program for Sustainable Upland Farming through the Establishment of \"Barangay Sagip Saka\"","description":"<b>FUNDING AGENCY</b>\nNational Program for Sustainable Upland Farming through the Establishment of \"Barangay Sagip Saka\" : WB/GEF<b>Project Cost (US $ '000)</b><b>Loan proceeds</b><b>Grant proceeds : </b>4,999.00 <b>GOP : </b>2,310.00 <b>Total : </b>7,309.00 <b>Project duration : </b>2010-2014 <b>Project location : </b>Region 2 - Cagayan; Region 6 - Iloilo; Region 13 - Surigao del Norte <a href=\"http://faspo.denr.gov.ph/Prog_Proj/factsheet_profileasof12092011/GIAHS.pdf\">Project Briefer</a><a href=\"http://faspo.denr.gov.ph/Prog_Proj/Program.htm\">For more info go to FASPO website</a>","id":"a9h6e624rjux"},"type":"Feature","geometry":{"type":"Point","coordinates":[121.788792638652,18.1595206746703]}},{"properties":{"name":"Surigao Del Norte : National Program for Sustainable Upland Farming through the Establishment of \"Barangay Sagip Saka\"","description":"<b>FUNDING AGENCY</b>\nNational Program for Sustainable Upland Farming through the Establishment of \"Barangay Sagip Saka\" : WB/GEF<b>Project Cost (US $ '000)</b><b>Loan proceeds</b><b>Grant proceeds : </b>4,999.00 <b>GOP : </b>2,310.00 <b>Total : </b>7,309.00 <b>Project duration : </b>2010-2014 <b>Project location : </b>Region 2 - Cagayan; Region 6 - Iloilo; Region 13 - Surigao del Norte <a href=\"http://faspo.denr.gov.ph/Prog_Proj/factsheet_profileasof12092011/GIAHS.pdf\">Project Briefer</a><a href=\"http://faspo.denr.gov.ph/Prog_Proj/Program.htm\">For more info go to FASPO website</a>","id":"a9h6e5y4qxr4"},"type":"Feature","geometry":{"type":"Point","coordinates":[125.686771075142,9.44944944691965]}}],"is_temporal":false,"author":{"url":"http://bswm.da.gov.ph/unccdphilippines","metadata":"","contact_name":"Dr. Gina Nilo","contact_address":"Bureau of Soils and Water Management\r\nDepartment of Agriculture\r\nElliptical Road Visayas Avenue., \r\nDiliman Quezon City","source":"BSWM","contact_phone":""},"source":"http://bswm.da.gov.ph/unccdphilippines","pagination":{"sort":null,"start":0,"total":3,"limit":1000000},"state":"complete","tags":"","published":"2014-08-14T22:06:11-04:00","id":285642}