{"type":"FeatureCollection","data_type":"Dataset","url_type":null,"permissions":[{"permissions":{"download":true,"view":true},"group_id":"everyone"}],"classification":null,"title":"767-400ER Rons-Rads Oct_Nov","count":6,"stream_id":286537,"contributor":{"url":"http://geocommons.com/users/38310","name":"Dlforecastdemand"},"data_attributes":null,"calculation_params":null,"icon_link":null,"link":"http://geocommons.com/overlays/286537.json","extent":[-93.2218,33.6367,-0.461941,51.4706],"geometry_types":["point"],"unique_name":null,"name":"767-400ER Rons-Rads Oct_Nov","feature_count":6,"description":"","next_feature":null,"is_raster":false,"short_classification":"Y","stats":{"latitude":{"max":51.47060013,"variance":33.6516187197919,"mean":42.5342998516667,"stdev":5.80100152730473,"min":33.63669968,"median":42.36429977},"rons rads":{"max":92,"variance":1607.2,"mean":41.0,"stdev":40.0898989771738,"min":3,"median":28},"longitude":{"max":-0.461941004,"variance":1149.01085003304,"mean":-67.7082246556667,"stdev":33.8970625575881,"min":-93.22180176,"median":-73.77890015}},"features":[{"properties":{"latitude":33.63669968,"column_5":null,"airport code":"ATL","rons rads":92,"longitude":-84.42810059,"id":"a9jgl2tz57yg"},"type":"Feature","geometry":{"type":"Point","coordinates":[-84.42810059,33.63669968]}},{"properties":{"latitude":42.36429977,"column_5":null,"airport code":"BOS","rons rads":3,"longitude":-71.00520325,"id":"a9jgl2ywo6qb"},"type":"Feature","geometry":{"type":"Point","coordinates":[-71.00520325,42.36429977]}},{"properties":{"latitude":42.21239853,"column_5":null,"airport code":"DTW","rons rads":28,"longitude":-83.35340118,"id":"a9jgl2svo7xq"},"type":"Feature","geometry":{"type":"Point","coordinates":[-83.35340118,42.21239853]}},{"properties":{"latitude":40.63980103,"column_5":null,"airport code":"JFK","rons rads":90,"longitude":-73.77890015,"id":"a9jgl33xp1hu"},"type":"Feature","geometry":{"type":"Point","coordinates":[-73.77890015,40.63980103]}},{"properties":{"latitude":51.47060013,"column_5":null,"airport code":"LHR","rons rads":6,"longitude":-0.461941004,"id":"a9jgl2y7i76n"},"type":"Feature","geometry":{"type":"Point","coordinates":[-0.461941004,51.47060013]}},{"properties":{"latitude":44.88199997,"column_5":null,"airport code":"MSP","rons rads":27,"longitude":-93.22180176,"id":"a9jgl376zz5n"},"type":"Feature","geometry":{"type":"Point","coordinates":[-93.22180176,44.88199997]}}],"is_temporal":false,"author":{"url":"","metadata":"","contact_name":"","contact_address":"","source":"","contact_phone":""},"source":"","pagination":{"sort":null,"start":0,"total":6,"limit":1000000},"state":"complete","tags":"","published":"2014-08-14T23:23:04-04:00","id":286537}