{"type":"FeatureCollection","data_type":"Dataset","url_type":null,"permissions":[{"permissions":{"download":true,"view":true},"group_id":"everyone"}],"classification":null,"title":"GPS Reading near Bulwagan Ninoy","count":10,"stream_id":292725,"contributor":{"url":"http://geocommons.com/users/55243","name":"m_babylyn"},"data_attributes":null,"calculation_params":null,"icon_link":null,"link":"http://geocommons.com/overlays/292725.json","extent":[121.042,14.6518,121.043,14.6523],"geometry_types":["point"],"unique_name":null,"name":"GPS Reading near Bulwagan Ninoy","feature_count":10,"description":"uploaded 11-13-2012","next_feature":null,"is_raster":false,"short_classification":"Y","stats":{"lat":{"max":14.65233333,"variance":3.48080315566739e-08,"mean":14.652083333,"stdev":0.000186569106651326,"min":14.65177778,"median":14.65213889},"long":{"max":121.0429722,"variance":1.99109294332704e-07,"mean":121.04251389,"stdev":0.000446216645064596,"min":121.0416667,"median":121.04275}},"features":[{"properties":{"id":"aa03eqnutdii","species/features":"Ninoy Aquino Statute in Bulwagan Ninoy","lat":14.652,"long":121.0428333},"type":"Feature","geometry":{"type":"Point","coordinates":[121.0428333,14.652]}},{"properties":{"id":"aa03er5m03f0","species/features":"Heritage tree -Lumbang","lat":14.65177778,"long":121.0429722},"type":"Feature","geometry":{"type":"Point","coordinates":[121.0429722,14.65177778]}},{"properties":{"id":"aa03er8byspn","species/features":"Gmelina","lat":14.65183333,"long":121.0426667},"type":"Feature","geometry":{"type":"Point","coordinates":[121.0426667,14.65183333]}},{"properties":{"id":"aa03er9a4k7w","species/features":"Santol","lat":14.65211111,"long":121.0427778},"type":"Feature","geometry":{"type":"Point","coordinates":[121.0427778,14.65211111]}},{"properties":{"id":"aa03er1d4ptm","species/features":"Mahogany","lat":14.65213889,"long":121.0428611},"type":"Feature","geometry":{"type":"Point","coordinates":[121.0428611,14.65213889]}},{"properties":{"id":"aa03er8abeq5","species/features":"Ipil -ipil","lat":14.65230556,"long":121.04275},"type":"Feature","geometry":{"type":"Point","coordinates":[121.04275,14.65230556]}},{"properties":{"id":"aa03era6aa6z","species/features":"Alibangbang","lat":14.65233333,"long":121.0425278},"type":"Feature","geometry":{"type":"Point","coordinates":[121.0425278,14.65233333]}},{"properties":{"id":"aa03er11yiht","species/features":"Talisay","lat":14.65222222,"long":121.0421944},"type":"Feature","geometry":{"type":"Point","coordinates":[121.0421944,14.65222222]}},{"properties":{"id":"aa03er8moqpz","species/features":"Antipolo","lat":14.65213889,"long":121.0418889},"type":"Feature","geometry":{"type":"Point","coordinates":[121.0418889,14.65213889]}},{"properties":{"id":"aa03er3utb75","species/features":"Macopa","lat":14.65197222,"long":121.0416667},"type":"Feature","geometry":{"type":"Point","coordinates":[121.0416667,14.65197222]}}],"is_temporal":false,"author":{"url":"","metadata":"","contact_name":"","contact_address":"","source":"","contact_phone":""},"source":"","pagination":{"sort":null,"start":0,"total":10,"limit":1000000},"state":"complete","tags":"species,tree","published":"2012-11-13T17:00:00Z","id":292725}