{"type":"FeatureCollection","data_type":"Dataset","url_type":null,"permissions":[{"permissions":{"download":true,"view":true},"group_id":"everyone"}],"classification":null,"title":"ACB_PAWB","count":13,"stream_id":292750,"contributor":{"url":"http://geocommons.com/users/55788","name":"tintin"},"data_attributes":null,"calculation_params":null,"icon_link":null,"link":"http://geocommons.com/overlays/292750.json","extent":[121.042,14.6509,121.046,14.6525],"geometry_types":["point"],"unique_name":null,"name":"ACB_PAWB","feature_count":13,"description":"","next_feature":null,"is_raster":false,"short_classification":"Y","stats":{"lat":{"max":14.65246,"variance":2.27516666666443e-07,"mean":14.65181,"stdev":0.000476987071802206,"min":14.6509,"median":14.65177},"long":{"max":121.04579,"variance":1.14577692307713e-06,"mean":121.044714615385,"stdev":0.00107040969870285,"min":121.04241,"median":121.04515}},"features":[{"properties":{"points":"Guardhouse","id":"aa03ssays7z1","lat":14.65216,"long":121.04533},"type":"Feature","geometry":{"type":"Point","coordinates":[121.04533,14.65216]}},{"properties":{"points":"New NRED","id":"aa03srwr4073","lat":14.65173,"long":121.04514},"type":"Feature","geometry":{"type":"Point","coordinates":[121.04514,14.65173]}},{"properties":{"points":"Old NRED","id":"aa03ss5tusw6","lat":14.65177,"long":121.04523},"type":"Feature","geometry":{"type":"Point","coordinates":[121.04523,14.65177]}},{"properties":{"points":"Parking","id":"aa03srwi0w5a","lat":14.65204,"long":121.04507},"type":"Feature","geometry":{"type":"Point","coordinates":[121.04507,14.65204]}},{"properties":{"points":"Planning","id":"aa03srzgqp99","lat":14.6509,"long":121.04557},"type":"Feature","geometry":{"type":"Point","coordinates":[121.04557,14.6509]}},{"properties":{"points":"BPP","id":"aa03srxs240j","lat":14.65223,"long":121.04435},"type":"Feature","geometry":{"type":"Point","coordinates":[121.04435,14.65223]}},{"properties":{"points":"Bulwagan Ninoy","id":"aa03ss7el4cr","lat":14.65216,"long":121.04276},"type":"Feature","geometry":{"type":"Point","coordinates":[121.04276,14.65216]}},{"properties":{"points":"Cashier","id":"aa03ss14uikp","lat":14.65131,"long":121.04536},"type":"Feature","geometry":{"type":"Point","coordinates":[121.04536,14.65131]}},{"properties":{"points":"Basketball Court","id":"aa03ss93qgqc","lat":14.65233,"long":121.04386},"type":"Feature","geometry":{"type":"Point","coordinates":[121.04386,14.65233]}},{"properties":{"points":"Records","id":"aa03ss42r5yy","lat":14.65158,"long":121.04515},"type":"Feature","geometry":{"type":"Point","coordinates":[121.04515,14.65158]}},{"properties":{"points":"Restroom","id":"aa03srvsikr9","lat":14.65246,"long":121.04241},"type":"Feature","geometry":{"type":"Point","coordinates":[121.04241,14.65246]}},{"properties":{"points":"Wildlife Rescue","id":"aa03ssaso9vv","lat":14.65117,"long":121.04579},"type":"Feature","geometry":{"type":"Point","coordinates":[121.04579,14.65117]}},{"properties":{"points":"CMMO","id":"aa03ss0uochy","lat":14.65169,"long":121.04527},"type":"Feature","geometry":{"type":"Point","coordinates":[121.04527,14.65169]}}],"is_temporal":false,"author":{"url":"","metadata":"","contact_name":"","contact_address":"","source":"","contact_phone":""},"source":"","pagination":{"sort":null,"start":0,"total":13,"limit":1000000},"state":"complete","tags":"","published":"2014-08-14T19:21:46-04:00","id":292750}