{"type":"FeatureCollection","data_type":"Dataset","url_type":null,"permissions":[{"permissions":{"download":true,"view":true},"group_id":"everyone"}],"classification":null,"title":"Alojamiento","count":2,"stream_id":293803,"contributor":{"url":"http://geocommons.com/users/55396","name":"pep005"},"data_attributes":null,"calculation_params":null,"icon_link":null,"link":"http://geocommons.com/overlays/293803.json","extent":[3.1586,41.9697,3.20057,41.9753],"geometry_types":["point"],"unique_name":null,"name":"Alojamiento","feature_count":2,"description":"","next_feature":null,"is_raster":false,"short_classification":"Y","stats":{},"features":[{"properties":{"name":"ALOJAMIENTO: Hotel Mas Salvi","description":"<img src=\"http://assets.archivhadas.es/system/userfiles/image/Fotos%20Viajes%20y%20escapadas/mas%20salvi.jpg\" width=\"250\" height=\"\"><a href=\"http:/www.golfplatjadepals.com\"></a>\nHotel Mas Salvi****\nCarmany, 13\n972636478\n972637312\nwww.massalvi.com\ninfo@massalvi.com","id":"aa126dtymyv7"},"type":"Feature","geometry":{"type":"Point","coordinates":[3.1586,41.969656]}},{"properties":{"name":"ALOJAMIENTO: Hotel Restaurant Sa Punta","description":"<img src=\"http://photos0.hotelsearch.com/0004/0310/sa-punta-begur_big.jpg\" width=\"250\" height=\"\"><a href=\"http:/www.golfplatjadepals.com\"></a>\nHotel Restaurant Sa Punta****\nPlatja de Pals\n972636410\nwww.hotelsapunta.com\nsapunta@hotelsapunta.com","id":"aa126e4eu83m"},"type":"Feature","geometry":{"type":"Point","coordinates":[3.20057,41.975261]}}],"is_temporal":false,"author":{"url":"","metadata":null,"contact_name":null,"contact_address":null,"source":null,"contact_phone":null},"source":"","pagination":{"sort":null,"start":0,"total":2,"limit":1000000},"state":"complete","tags":"","published":"2014-08-14T20:26:31-04:00","id":293803}