{"type":"FeatureCollection","data_type":"Dataset","url_type":null,"permissions":[{"permissions":{"download":true,"view":true},"group_id":"everyone"}],"classification":null,"title":"Monumentos","count":7,"stream_id":297297,"contributor":{"url":"http://geocommons.com/users/56381","name":"phyllobates"},"data_attributes":null,"calculation_params":null,"icon_link":null,"link":"http://geocommons.com/overlays/297297.json","extent":[-3.60167,37.1721,-3.5926,37.1919],"geometry_types":["point"],"unique_name":null,"name":"Monumentos","feature_count":7,"description":"","next_feature":null,"is_raster":false,"short_classification":"Y","stats":{"name":{"max":0,"mean":0.0,"variance":0.0,"stdev":0.0,"median":0,"min":0}},"features":[{"properties":{"name":0,"description":" xmlns:fo=\"http://www.w3.org/1999/XSL/Format\" xmlns:msxsl=\"urn:schemas-microsoft-com:xslt\"&gt;\r\r\n\r\r\n0\r\r\n\r\r\nFID\r\r\n0\r\r\nId\r\r\n0\r\r\nNOMBRE\r\r\nMirador de San Nicolas\r\r\nOBSERVACIO\r\r\nMirador emblematico con las mejores vistas de la Alhambra\r\r\n\r\r\n","id":"aa6jmmombwl4"},"type":"Feature","geometry":{"type":"Point","coordinates":[-3.592676,37.181038]}},{"properties":{"name":0,"description":" xmlns:fo=\"http://www.w3.org/1999/XSL/Format\" xmlns:msxsl=\"urn:schemas-microsoft-com:xslt\"&gt;\r\r\n\r\r\n0\r\r\n\r\r\nFID\r\r\n1\r\r\nId\r\r\n0\r\r\nNOMBRE\r\r\nMirador de San Cristobal\r\r\nOBSERVACIO\r\r\nConocido mirador con vistas de la Alhambra y Ciudad de Granada\r\r\n\r\r\n","id":"aa6jmmwx6rjy"},"type":"Feature","geometry":{"type":"Point","coordinates":[-3.595991,37.183064]}},{"properties":{"name":0,"description":" xmlns:fo=\"http://www.w3.org/1999/XSL/Format\" xmlns:msxsl=\"urn:schemas-microsoft-com:xslt\"&gt;\r\r\n\r\r\n0\r\r\n\r\r\nFID\r\r\n2\r\r\nId\r\r\n0\r\r\nNOMBRE\r\r\nMonasterio de la Cartuja\r\r\nOBSERVACIO\r\r\nConstruido en el S.XVI. Estilo renacentista en el monasterio y Barroco la Iglesia\r\r\n\r\r\n","id":"aa6jmmwueb90"},"type":"Feature","geometry":{"type":"Point","coordinates":[-3.599544,37.191921]}},{"properties":{"name":0,"description":" xmlns:fo=\"http://www.w3.org/1999/XSL/Format\" xmlns:msxsl=\"urn:schemas-microsoft-com:xslt\"&gt;\r\r\n\r\r\n0\r\r\n\r\r\nFID\r\r\n3\r\r\nId\r\r\n0\r\r\nNOMBRE\r\r\nHospital Real\r\r\nOBSERVACIO\r\r\nContruido en 1492 como hospital y asilo de enfermos durante el asedio a Granada\r\r\n\r\r\n","id":"aa6jmmuxz3ue"},"type":"Feature","geometry":{"type":"Point","coordinates":[-3.60078,37.18475]}},{"properties":{"name":0,"description":" xmlns:fo=\"http://www.w3.org/1999/XSL/Format\" xmlns:msxsl=\"urn:schemas-microsoft-com:xslt\"&gt;\r\r\n\r\r\n0\r\r\n\r\r\nFID\r\r\n4\r\r\nId\r\r\n0\r\r\nNOMBRE\r\r\nJardines del Triunfo\r\r\nOBSERVACIO\r\r\nAntiguo cementerio nazari, actualmente jardines de uso publico\r\r\n\r\r\n","id":"aa6jmmohr4ya"},"type":"Feature","geometry":{"type":"Point","coordinates":[-3.601669,37.18406]}},{"properties":{"name":0,"description":" xmlns:fo=\"http://www.w3.org/1999/XSL/Format\" xmlns:msxsl=\"urn:schemas-microsoft-com:xslt\"&gt;\r\r\n\r\r\n0\r\r\n\r\r\nFID\r\r\n5\r\r\nId\r\r\n0\r\r\nNOMBRE\r\r\nFuente de las Batallas\r\r\nOBSERVACIO\r\r\nUbicada en la zona denominada Puerta Real.\r\r\n\r\r\n","id":"aa6jmmzkowpr"},"type":"Feature","geometry":{"type":"Point","coordinates":[-3.598636,37.172147]}},{"properties":{"name":0,"description":" xmlns:fo=\"http://www.w3.org/1999/XSL/Format\" xmlns:msxsl=\"urn:schemas-microsoft-com:xslt\"&gt;\r\r\n\r\r\n0\r\r\n\r\r\nFID\r\r\n6\r\r\nId\r\r\n0\r\r\nNOMBRE\r\r\nBañuelo. Baños Árabes\r\r\nOBSERVACIO\r\r\nconstruido en s. XI y es uno de los más viejos, completos baños publicos árabes conservados en España\r\r\n\r\r\n","id":"aa6jmn0c88rv"},"type":"Feature","geometry":{"type":"Point","coordinates":[-3.592597,37.178521]}}],"is_temporal":false,"author":{"url":"","metadata":null,"contact_name":null,"contact_address":null,"source":null,"contact_phone":null},"source":"","pagination":{"sort":null,"start":0,"total":7,"limit":1000000},"state":"complete","tags":"","published":"2014-08-15T00:22:12-04:00","id":297297}