{"type":"FeatureCollection","data_type":"Dataset","url_type":null,"permissions":[{"permissions":{"download":true,"view":true},"group_id":"everyone"}],"classification":null,"title":"simple","count":1,"stream_id":298709,"contributor":{"url":"http://geocommons.com/users/56781","name":"simple_simple"},"data_attributes":null,"calculation_params":null,"icon_link":null,"link":"http://geocommons.com/overlays/298709.json","extent":[124.637,11.1745,124.637,11.1745],"geometry_types":["point"],"unique_name":null,"name":"simple","feature_count":1,"description":"","next_feature":null,"is_raster":false,"short_classification":"Y","stats":{"lat":{"max":11.17448,"median":11.17448,"min":11.17448},"long":{"max":124.637286,"median":124.637286,"min":124.637286}},"features":[{"properties":{"column_1":"Species","id":"aab0biuucwe8","lat":11.17448,"long":124.637286},"type":"Feature","geometry":{"type":"Point","coordinates":[124.637286,11.17448]}}],"is_temporal":false,"author":{"url":"","metadata":null,"contact_name":null,"contact_address":null,"source":null,"contact_phone":null},"source":"","pagination":{"sort":null,"start":0,"total":1,"limit":1000000},"state":"complete","tags":"","published":"2014-08-15T01:40:25-04:00","id":298709}