{"type":"FeatureCollection","data_type":"Dataset","url_type":null,"permissions":[{"permissions":{"download":true,"edit":true,"view":true},"group_id":"everyone"}],"classification":null,"title":"Fulfulde","count":5,"stream_id":300263,"contributor":{"url":"http://geocommons.com/users/56939","name":"paburgess"},"data_attributes":null,"calculation_params":null,"icon_link":null,"link":"http://geocommons.com/overlays/300263.json","extent":[8.20056,13.6075,11.5319,14.0072],"geometry_types":["point"],"unique_name":null,"name":"Fulfulde","feature_count":5,"description":"","next_feature":null,"is_raster":false,"short_classification":"Y","stats":{"latitude (decimals)":{"max":14.00722222,"mean":13.821944444,"variance":0.0296189425751542,"stdev":0.172101547277049,"min":13.6075,"median":13.82194444},"longitude (decimals)":{"max":11.53194444,"mean":9.5534999994,"variance":1.94249986411434,"stdev":1.39373593772793,"min":8.200555556,"median":9.820555556}},"features":[{"properties":{"latitude (decimals)":13.82194444,"column_5":null,"language":"Fulfulde","longitude (decimals)":9.820555556,"imagine school":null,"id":"aadaj6cs73mm"},"type":"Feature","geometry":{"type":"Point","coordinates":[9.820555556,13.82194444]}},{"properties":{"latitude (decimals)":13.69916667,"column_5":null,"language":"Fulfulde","longitude (decimals)":9.989166667,"imagine school":null,"id":"aadaj6ifgow7"},"type":"Feature","geometry":{"type":"Point","coordinates":[9.989166667,13.69916667]}},{"properties":{"latitude (decimals)":13.97388889,"column_5":null,"language":"Fulfulde","longitude (decimals)":11.53194444,"imagine school":null,"id":"aadaj6flr5wk"},"type":"Feature","geometry":{"type":"Point","coordinates":[11.53194444,13.97388889]}},{"properties":{"latitude (decimals)":13.6075,"column_5":null,"language":"Fulfulde","longitude (decimals)":8.200555556,"imagine school":null,"id":"aadaj6povq10"},"type":"Feature","geometry":{"type":"Point","coordinates":[8.200555556,13.6075]}},{"properties":{"latitude (decimals)":14.00722222,"column_5":null,"language":"Fulfulde","longitude (decimals)":8.225277778,"imagine school":null,"id":"aadaj6ll72qw"},"type":"Feature","geometry":{"type":"Point","coordinates":[8.225277778,14.00722222]}}],"is_temporal":false,"author":{"url":"","metadata":"","contact_name":"","contact_address":"","source":"","contact_phone":""},"source":"","pagination":{"sort":null,"start":0,"total":5,"limit":1000000},"state":"complete","tags":"","published":"2014-08-16T13:02:46-04:00","id":300263}