{"type":"FeatureCollection","url":"http://www.worldweatheronline.com/v2/rss.ashx?locid=1008696&root_id=973187&wc=LOCAL_WEATHER","data_type":"Data Feed","url_type":"rss","permissions":[{"permissions":{"download":true,"view":true},"group_id":"everyone"}],"classification":null,"title":"Jakarta, Indonesia latest weather forecast","count":3,"stream_id":301454,"contributor":{"url":"http://geocommons.com/users/56311","name":"banjironline"},"data_attributes":null,"calculation_params":null,"icon_link":null,"link":"http://geocommons.com/overlays/301454.json","extent":[-92.8339,31.5024,-88.6525,45.0618],"geometry_types":["point"],"unique_name":null,"name":"Jakarta, Indonesia latest weather forecast","feature_count":3,"description":"","next_feature":null,"is_raster":false,"short_classification":"Y","stats":{},"features":[{"properties":{"title":"Current weather: Partly Cloudy","geo_score":0.323,"description":"<img src=\"http://www.worldweatheronline.com/images/wsymbols01_png_64/wsymbol_0004_black_low_cloud.png\"><b>Temp: </b>27°c (81°f)<b>Wind: </b>W at 7 mph (11 kmph)","link":"http://www.worldweatheronline.com/weather.aspx?q=Jakarta, Indonesia","id":"aahfvq54x3vl","geo_precision":"street"},"type":"Feature","geometry":{"type":"Point","coordinates":[-92.833886,45.061771]}},{"properties":{"title":"Today's weather: Sunny","geo_score":0.299,"description":"<img src=\"http://www.worldweatheronline.com/images/wsymbols01_png_64/wsymbol_0001_sunny.png\"><b>High: </b>35°c (95°f); <b>Low: </b>25°c (77°f)<b>Wind: </b>WSW at 12 mph (19 kmph)","link":"http://www.worldweatheronline.com/weather.aspx?q=Jakarta, Indonesia&amp;day=0","id":"aahfvpw89pc0","geo_precision":"street"},"type":"Feature","geometry":{"type":"Point","coordinates":[-88.652496,38.759549]}},{"properties":{"title":"Tomorrow's weather: Patchy rain nearby","geo_score":0.236,"description":"<img src=\"http://www.worldweatheronline.com/images/wsymbols01_png_64/wsymbol_0009_light_rain_showers.png\"><b>High: </b>33°c (91°f); <b>Low: </b>26°c (78°f)<b>Wind: </b>WNW at 10 mph (17 kmph)","link":"http://www.worldweatheronline.com/weather.aspx?q=Jakarta, Indonesia&amp;day=1","id":"aahfvq5265ca","geo_precision":"street"},"type":"Feature","geometry":{"type":"Point","coordinates":[-89.318584,31.502414]}}],"is_temporal":false,"author":{"url":"","metadata":"","contact_name":"","contact_address":"","source":"","contact_phone":""},"source":"","pagination":{"sort":null,"start":0,"total":3,"limit":1000000},"state":"complete","tags":"consultants,hkv,indonesia","published":"2014-08-16T14:24:06-04:00","id":301454}