{"type":"FeatureCollection","data_type":"Dataset","url_type":null,"permissions":[{"permissions":{"download":true,"view":true},"group_id":"everyone"}],"classification":null,"title":"Passage 2","count":1,"stream_id":303486,"contributor":{"url":"http://geocommons.com/users/54770","name":"ASehon"},"data_attributes":null,"calculation_params":null,"icon_link":null,"link":"http://geocommons.com/overlays/303486.json","extent":[-84.5051,38.0387,-84.5051,38.0387],"geometry_types":["point"],"unique_name":null,"name":"Passage 2","feature_count":1,"description":"While the majority of student-activists regroup in the Student Center, two stay behind in order to examine the Main Building for possible entranceways. President Wethington has had the building locked down and guards posted throughout in preparation for student action.","next_feature":null,"is_raster":false,"short_classification":"Y","stats":{},"features":[{"properties":{"name":"Passage","description":"While the majority of student-activists regroup in the Student Center, two stay behind in order to examine the Main Building for possible entranceways. President Wethington has had the building locked down and guards posted throughout in preparation for student action.","id":"aalcxd4kwgbi"},"type":"Feature","geometry":{"type":"Point","coordinates":[-84.505149665289,38.0387217759618]}}],"is_temporal":false,"author":{"url":"","metadata":null,"contact_name":null,"contact_address":null,"source":null,"contact_phone":null},"source":"","pagination":{"sort":null,"start":0,"total":1,"limit":1000000},"state":"complete","tags":"","published":"2014-08-16T17:16:45-04:00","id":303486}