{"type":"FeatureCollection","data_type":"Dataset","url_type":null,"permissions":[{"permissions":{"download":true,"view":true},"group_id":"everyone"}],"classification":null,"title":"rssToGeoRSS","count":2,"stream_id":303681,"contributor":{"url":"http://geocommons.com/users/56311","name":"banjironline"},"data_attributes":null,"calculation_params":null,"icon_link":null,"link":"http://geocommons.com/overlays/303681.json","extent":[106.845,-6.21462,106.845,-6.21462],"geometry_types":["point"],"unique_name":null,"name":"rssToGeoRSS","feature_count":2,"description":"","next_feature":null,"is_raster":false,"short_classification":"Y","stats":{},"features":[{"properties":{"name":"Current weather for Jakarta at 11:30pm","description":"&lt;b&gt;Temperature:&lt;/b&gt; 27.0&amp;#176;C\n        &lt;img align=\"top\" src=\"http://www.weatherzone.com.au/images/widgets/nav_trend_steady.gif\" alt=\"steady\"/&gt;\n        &lt;br /&gt;\n        &lt;b&gt;Feels like:&lt;/b&gt; 31.0&amp;#176;C&lt;br /&gt;\n        &lt;b&gt;Dew point:&lt;/b&gt; 25.0&amp;#176;C\n        &lt;img align=\"top\" src=\"http://www.weatherzone.com.au/images/widgets/nav_trend_steady.gif\" alt=\"steady\"/&gt;\n        &lt;br /&gt;\n        &lt;b&gt;Relative humidity:&lt;/b&gt; 89%&lt;br /&gt;\n        &lt;b&gt;Wind:&lt;/b&gt; WNW at 7 km/h, gusting to  km/h\n        &lt;img align=\"top\" src=\"http://www.weatherzone.com.au/images/widgets/nav_trend_steady.gif\" alt=\"steady\"/&gt;\n        &lt;br /&gt;\n        &lt;b&gt;Rain:&lt;/b&gt; mm since 9am&lt;br /&gt;\n        &lt;b&gt;Pressure:&lt;/b&gt; 1009.0 hPa\n        &lt;img align=\"top\" src=\"http://www.weatherzone.com.au/images/widgets/nav_trend_steady.gif\" alt=\"steady\"/&gt;\n        &lt;br /&gt;\n        &lt;br/&gt;&lt;br/&gt;&lt;br/&gt;Geolocation by geonames :&lt;br/&gt;Jakarta, Republic of Indonesia, capital of a political entity","id":"aamlcf020sru"},"type":"Feature","geometry":{"type":"Point","coordinates":[106.84513092041,-6.21462319703577]}},{"properties":{"name":"Jakarta weather forecast","description":"&lt;b&gt;Monday&lt;/b&gt;&lt;br /&gt;\n&lt;img src=\"http://www.weatherzone.com.au/images/icons/fcast_30/rain.gif\"&gt;&lt;br /&gt;\nRain&lt;br /&gt;\n23&amp;#176;C - 32&amp;#176;C&lt;br /&gt;&lt;br /&gt;\n&lt;b&gt;Tuesday&lt;/b&gt;&lt;br /&gt;\n&lt;img src=\"http://www.weatherzone.com.au/images/icons/fcast_30/thunderstorms.gif\"&gt;&lt;br /&gt;\nThunderstorms&lt;br /&gt;\n26&amp;#176;C - 32&amp;#176;C&lt;br /&gt;&lt;br /&gt;\n&lt;b&gt;Wednesday&lt;/b&gt;&lt;br /&gt;\n&lt;img src=\"http://www.weatherzone.com.au/images/icons/fcast_30/thunderstorms.gif\"&gt;&lt;br /&gt;\nThunderstorms&lt;br /&gt;\n25&amp;#176;C - 31&amp;#176;C&lt;br /&gt;&lt;br /&gt;\n&lt;b&gt;Thursday&lt;/b&gt;&lt;br /&gt;\n&lt;img src=\"http://www.weatherzone.com.au/images/icons/fcast_30/thunderstorms.gif\"&gt;&lt;br /&gt;\nThunderstorms&lt;br /&gt;\n25&amp;#176;C - 32&amp;#176;C&lt;br /&gt;&lt;br /&gt;\n        &lt;br/&gt;&lt;br/&gt;&lt;br/&gt;Geolocation by geonames :&lt;br/&gt;Jakarta, Republic of Indonesia, capital of a political entity","id":"aamlcf9p7rsz"},"type":"Feature","geometry":{"type":"Point","coordinates":[106.84513092041,-6.21462319703577]}}],"is_temporal":false,"author":{"url":"","metadata":null,"contact_name":null,"contact_address":null,"source":null,"contact_phone":null},"source":"","pagination":{"sort":null,"start":0,"total":2,"limit":1000000},"state":"complete","tags":"","published":"2014-08-16T17:35:47-04:00","id":303681}