{"type":"FeatureCollection","data_type":"Dataset","url_type":null,"permissions":[{"permissions":{"download":true,"view":true},"group_id":"everyone"}],"classification":null,"title":"Primary_Clinics-filtered","count":2,"stream_id":307450,"contributor":{"url":"http://geocommons.com/users/44653","name":"sandhuji"},"data_attributes":null,"calculation_params":null,"icon_link":null,"link":"http://geocommons.com/overlays/307450.json","extent":[-117.989,33.7038,-117.988,33.7049],"geometry_types":["point"],"unique_name":null,"name":"Primary_Clinics-filtered","feature_count":2,"description":"","next_feature":null,"is_raster":false,"short_classification":"Y","stats":{"facility status date":{"max":"2002/10/18 00:00:00 -0400","mean":"1989/05/04 00:30:00 -0400","variance":3.6066237915528e+17,"stdev":600551728.958697,"median":"2002/10/18 00:00:00 -0400","min":"1975/11/19 00:00:00 -0500"},"county number":{"max":30,"mean":30.0,"variance":0.0,"stdev":0.0,"median":30,"min":30},"oshpd-id":{"max":306304297,"mean":306303052.0,"variance":3100050.0,"stdev":1760.6958851545,"median":306304297,"min":306301807}},"features":[{"properties":{"city":"HUNTINGTON BEACH","county name":"ORANGE","county number":30,"facility status date":{"end_time":"2002/10/19 00:00:00 -0400","original":"2002-10-18","granularity":"day","time":"2002/10/18 00:00:00 -0400"},"license type desc":"Clinic","license category desc":"Community Clinic","facility status":"Open","geo_score":0.902,"zip code":"92647","facility name":"ALTAMED MEDICAL GROUP - COMMUNITY CARE DENTAL CENTER","id":"aaywjwzzbgei","oshpd-id":306304297,"address":"17752 BEACH BLVD","geo_precision":"range"},"type":"Feature","geometry":{"type":"Point","coordinates":[-117.988995,33.703782]}},{"properties":{"city":"HUNTINGTON BEACH","county name":"ORANGE","county number":30,"facility status date":{"end_time":"1975/11/20 00:00:00 -0500","original":"1975-11-19","granularity":"day","time":"1975/11/19 00:00:00 -0500"},"license type desc":"Clinic","license category desc":"Community Clinic","facility status":"Open","geo_score":0.785,"zip code":"92647","facility name":"ALTAMED MEDICAL GROUP - HUNTINGTON BEACH COMMUNITY CLINIC","id":"aaywjx2vmqak","oshpd-id":306301807,"address":"8041 NEWMAN","geo_precision":"range"},"type":"Feature","geometry":{"type":"Point","coordinates":[-117.988451,33.704875]}}],"is_temporal":true,"author":{"url":"","metadata":null,"contact_name":null,"contact_address":null,"source":null,"contact_phone":null},"source":"","pagination":{"sort":null,"start":0,"total":2,"limit":1000000},"state":"complete","tags":"","published":"2014-08-16T22:47:14-04:00","id":307450}