{"type":"FeatureCollection","data_type":"Dataset","url_type":null,"permissions":[{"permissions":{"download":true,"view":true},"group_id":"everyone"}],"classification":null,"title":"Stanford","count":11,"stream_id":310798,"contributor":{"url":"http://geocommons.com/users/15105","name":"frankwmoyer1"},"data_attributes":null,"calculation_params":null,"icon_link":null,"link":"http://geocommons.com/overlays/310798.json","extent":[-122.418,30.2669,-71.0603,47.6097],"geometry_types":["point"],"unique_name":null,"name":"Stanford","feature_count":11,"description":"","next_feature":null,"is_raster":false,"short_classification":"Y","stats":{"startup employees":{"max":2439,"mean":304.0,"variance":504178.2,"stdev":710.05506828696,"median":98,"min":21}},"features":[{"properties":{"city, state":"San Francisco, CA","startup employees":2439,"id":"abemhxdxd7x6"},"type":"Feature","geometry":{"type":"Point","coordinates":[-122.4183,37.775]}},{"properties":{"city, state":"Boston, MA","startup employees":132,"id":"abemhx7fji3o"},"type":"Feature","geometry":{"type":"Point","coordinates":[-71.0603,42.3583]}},{"properties":{"city, state":"New York, NY","startup employees":186,"id":"abemhx7k1199"},"type":"Feature","geometry":{"type":"Point","coordinates":[-73.9735,40.7697]}},{"properties":{"city, state":"Los Angeles, CA","startup employees":162,"id":"abemhxdbu24p"},"type":"Feature","geometry":{"type":"Point","coordinates":[-118.2428,34.0522]}},{"properties":{"city, state":"Washington, DC","startup employees":98,"id":"abemhxdnwuor"},"type":"Feature","geometry":{"type":"Point","coordinates":[-77.03,38.89]}},{"properties":{"city, state":"San Diego, CA","startup employees":59,"id":"abemhxej6cg4"},"type":"Feature","geometry":{"type":"Point","coordinates":[-117.1564,32.7153]}},{"properties":{"city, state":"Chicago, IL","startup employees":37,"id":"abemhx7k5v9r"},"type":"Feature","geometry":{"type":"Point","coordinates":[-87.65,41.85]}},{"properties":{"city, state":"Austin, TX","startup employees":43,"id":"abemhx9ucnoy"},"type":"Feature","geometry":{"type":"Point","coordinates":[-97.7428,30.2669]}},{"properties":{"city, state":"Denver, CO","startup employees":65,"id":"abemhxd3gres"},"type":"Feature","geometry":{"type":"Point","coordinates":[-104.9842,39.7392]}},{"properties":{"city, state":"Seattle, WA","startup employees":102,"id":"abemhx461c2n"},"type":"Feature","geometry":{"type":"Point","coordinates":[-122.3331,47.6097]}},{"properties":{"city, state":"Atlanta, GA","startup employees":21,"id":"abemhxci4j22"},"type":"Feature","geometry":{"type":"Point","coordinates":[-84.3881,33.7489]}}],"is_temporal":false,"author":{"url":"","metadata":"","contact_name":"","contact_address":"","source":"","contact_phone":""},"source":"","pagination":{"sort":null,"start":0,"total":11,"limit":1000000},"state":"complete","tags":"","published":"2014-08-16T13:58:29-04:00","id":310798}