{"type":"FeatureCollection","data_type":"Dataset","url_type":null,"permissions":[{"permissions":{"download":true,"view":true},"group_id":"everyone"}],"classification":null,"title":"123","count":3,"stream_id":313933,"contributor":{"url":"http://geocommons.com/users/59307","name":"stoetzel"},"data_attributes":null,"calculation_params":null,"icon_link":null,"link":"http://geocommons.com/overlays/313933.json","extent":[-79.7879,43.8994,14.5506,53.6333],"geometry_types":["point"],"unique_name":null,"name":"123","feature_count":3,"description":"","next_feature":null,"is_raster":false,"short_classification":"Y","stats":{"buy":{"max":610,"variance":24811.0,"mean":440.0,"stdev":157.515078643284,"min":299,"median":411},"sell":{"max":682,"variance":39170.3333333333,"mean":456.666666666667,"stdev":197.914964904965,"min":311,"median":377}},"features":[{"properties":{"city":"Frankfurt","geo_score":0.714,"buy":610,"sell":682,"id":"abop4p57lmua","geo_precision":"zip"},"type":"Feature","geometry":{"type":"Point","coordinates":[14.5506191253662,52.3471378230352]}},{"properties":{"city":"Dresden","geo_score":0.714,"buy":411,"sell":377,"id":"abop4pi4ip15","geo_precision":"zip"},"type":"Feature","geometry":{"type":"Point","coordinates":[7.3,53.6333333]}},{"properties":{"city":"Hamburg","geo_score":0.714,"buy":299,"sell":311,"id":"abop4piuxg7t","geo_precision":"zip"},"type":"Feature","geometry":{"type":"Point","coordinates":[-79.7878646850586,43.8993767148495]}}],"is_temporal":false,"author":{"url":"","metadata":null,"contact_name":null,"contact_address":null,"source":null,"contact_phone":null},"source":"","pagination":{"sort":null,"start":0,"total":3,"limit":1000000},"state":"complete","tags":"","published":"2014-08-16T18:37:10-04:00","id":313933}