{"type":"FeatureCollection","data_type":"Dataset","url_type":null,"permissions":[{"permissions":{"download":true,"view":true},"group_id":"everyone"}],"classification":null,"title":"Provageocommos","count":4,"stream_id":315090,"contributor":{"url":"http://geocommons.com/users/60023","name":"jrossinyol"},"data_attributes":null,"calculation_params":null,"icon_link":null,"link":"http://geocommons.com/overlays/315090.json","extent":[0.004438,41.0093,0.004449,41.0094],"geometry_types":["point"],"unique_name":null,"name":"Provageocommos","feature_count":4,"description":"","next_feature":null,"is_raster":false,"short_classification":"Y","stats":{"lat":{"max":41.00936,"variance":2.49166666673262e-09,"mean":41.0092925,"stdev":4.99165971069004e-05,"min":41.00925,"median":41.0093},"long":{"max":0.004449,"variance":2.69166666666649e-11,"mean":0.00444125,"stdev":5.18812747209095e-06,"min":0.004438,"median":0.004439}},"features":[{"properties":{"adreca":"Carrer2","establiment":"Merceria1","poblacio":"Prades3","id":"abrlg8i4ndlm","lat":41.00925,"long":0.004439},"type":"Feature","geometry":{"type":"Point","coordinates":[0.004439,41.00925]}},{"properties":{"adreca":"Carrer3","establiment":"Merceria3","poblacio":"Prades3","id":"abrlg8k6vlhd","lat":41.00926,"long":0.004438},"type":"Feature","geometry":{"type":"Point","coordinates":[0.004438,41.00926]}},{"properties":{"adreca":"Carrer4","establiment":"Merceria4","poblacio":"Prades4","id":"abrlg8lrruvt","lat":41.00936,"long":0.004439},"type":"Feature","geometry":{"type":"Point","coordinates":[0.004439,41.00936]}},{"properties":{"adreca":"Carrer5","establiment":"Merceria5","poblacio":"Prades5","id":"abrlg8fpwqgp","lat":41.0093,"long":0.004449},"type":"Feature","geometry":{"type":"Point","coordinates":[0.004449,41.0093]}}],"is_temporal":false,"author":{"url":"","metadata":null,"contact_name":null,"contact_address":null,"source":null,"contact_phone":null},"source":"","pagination":{"sort":null,"start":0,"total":4,"limit":1000000},"state":"complete","tags":"","published":"2014-08-16T19:57:56-04:00","id":315090}