{"type":"FeatureCollection","data_type":"Dataset","url_type":null,"permissions":[{"permissions":{"download":true,"view":true},"group_id":"everyone"}],"classification":null,"title":"punjab","count":1,"stream_id":315840,"contributor":{"url":"http://geocommons.com/users/57090","name":"kkmarchitects"},"data_attributes":null,"calculation_params":null,"icon_link":null,"link":"http://geocommons.com/overlays/315840.json","extent":[-73.217,41.6909,-73.217,41.6909],"geometry_types":["point"],"unique_name":null,"name":"punjab","feature_count":1,"description":"","next_feature":null,"is_raster":false,"short_classification":"Y","stats":{"latitude":{"max":41.69086954,"min":41.69086954,"median":41.69086954},"longitude":{"max":-73.21695346,"min":-73.21695346,"median":-73.21695346}},"features":[{"properties":{"name":"Punjab","latitude":41.69086954,"longitude":-73.21695346,"id":"abui2ziiha76"},"type":"Feature","geometry":{"type":"Point","coordinates":[-73.21695346,41.69086954]}}],"is_temporal":false,"author":{"url":"","metadata":null,"contact_name":null,"contact_address":null,"source":null,"contact_phone":null},"source":"","pagination":{"sort":null,"start":0,"total":1,"limit":1000000},"state":"complete","tags":"","published":"2014-08-16T20:59:03-04:00","id":315840}