{"type":"FeatureCollection","data_type":"Dataset","url_type":null,"permissions":[{"permissions":{"download":true,"view":true},"group_id":"everyone"}],"classification":null,"title":"SALADWORKS_LEHIGHVALLEY","count":5,"stream_id":317767,"contributor":{"url":"http://geocommons.com/users/59628","name":"alenamin"},"data_attributes":null,"calculation_params":null,"icon_link":null,"link":"http://geocommons.com/overlays/317767.json","extent":[-75.4768,40.6285,-75.2717,40.83],"geometry_types":["point"],"unique_name":null,"name":"SALADWORKS_LEHIGHVALLEY","feature_count":5,"description":"","next_feature":null,"is_raster":false,"short_classification":"Y","stats":{"latitude":{"max":40.83,"variance":0.00676923699999981,"mean":40.70222,"stdev":0.0822753729860875,"min":40.6285,"median":40.6821},"longitude":{"max":-75.2717,"variance":0.00863609300000017,"mean":-75.36116,"stdev":0.0929305816187555,"min":-75.4768,"median":-75.3147}},"features":[{"properties":{"latitude":40.6285,"longitude":-75.4768,"id":"ac00rqcns24a"},"type":"Feature","geometry":{"type":"Point","coordinates":[-75.4768,40.6285]}},{"properties":{"latitude":40.6387,"longitude":-75.4448,"id":"ac00rq0312hw"},"type":"Feature","geometry":{"type":"Point","coordinates":[-75.4448,40.6387]}},{"properties":{"latitude":40.7318,"longitude":-75.2717,"id":"ac00rq95cbt0"},"type":"Feature","geometry":{"type":"Point","coordinates":[-75.2717,40.7318]}},{"properties":{"latitude":40.83,"longitude":-75.2978,"id":"ac00rqaf1lfy"},"type":"Feature","geometry":{"type":"Point","coordinates":[-75.2978,40.83]}},{"properties":{"latitude":40.6821,"longitude":-75.3147,"id":"ac00rq5ld75e"},"type":"Feature","geometry":{"type":"Point","coordinates":[-75.3147,40.6821]}}],"is_temporal":false,"author":{"url":"","metadata":null,"contact_name":null,"contact_address":null,"source":null,"contact_phone":null},"source":"","pagination":{"sort":null,"start":0,"total":5,"limit":1000000},"state":"complete","tags":"","published":"2014-08-16T23:37:05-04:00","id":317767}