{"type":"FeatureCollection","data_type":"Dataset","url_type":null,"permissions":[{"permissions":{"download":true,"view":true},"group_id":"everyone"}],"classification":null,"title":"HITO_P","count":1,"stream_id":320908,"contributor":{"url":"http://geocommons.com/users/61664","name":"pakofx"},"data_attributes":null,"calculation_params":null,"icon_link":null,"link":"http://geocommons.com/overlays/320908.json","extent":[-76.8545,-2.6654,-76.8545,-2.6654],"geometry_types":["point"],"unique_name":null,"name":"HITO_P","feature_count":1,"description":"REQUIRED: A brief narrative summary of the data set.","next_feature":null,"is_raster":false,"short_classification":"Y","stats":{},"features":[{"properties":{"na3":null,"nam":"Río Checherta","descripcio":"MARCA IDENTIFICANDO LA LOCALIZACIÓN DE UN LÍMITE ESTABLECIDO","txt":null,"fcode":"ZB030","id":"ac6qdbhd660o","na2":"Hito No. 31"},"type":"Feature","geometry":{"type":"Point","coordinates":[-76.8545456343689,-2.66540394997252]}}],"is_temporal":false,"author":{"url":"","metadata":"","contact_name":"REQUIRED: The person responsible for the metadata information.","contact_address":", REQUIRED: The city of the address., REQUIRED: The state or province of the address., REQUIRED: The ZIP or other postal code of the address.","source":"REQUIRED: The organization responsible for the metadata information.","contact_phone":"REQUIRED: The telephone number by which individuals can speak to the organization or individual."},"source":"","pagination":{"sort":null,"start":0,"total":1,"limit":1000000},"state":"complete","tags":"","published":"2014-08-16T14:14:48-04:00","id":320908}