{"type":"FeatureCollection","data_type":"Dataset","url_type":null,"permissions":[{"permissions":{"download":true,"view":true},"group_id":"everyone"}],"classification":null,"title":"MTP 2013 mars","count":3,"stream_id":321648,"contributor":{"url":"http://geocommons.com/users/42827","name":"jflacou"},"data_attributes":null,"calculation_params":null,"icon_link":null,"link":"http://geocommons.com/overlays/321648.json","extent":[0.92877,46.7465,1.92335,47.1917],"geometry_types":["point"],"unique_name":null,"name":"MTP 2013 mars","feature_count":3,"description":"","next_feature":null,"is_raster":false,"short_classification":"Y","stats":{},"features":[{"properties":{"name":"VOUILLON","description":"Concert de musique médiévale et celtique avec l'Ensemble Pastourel, le 15 mars à 20 h 30 en l'église Saint-Saturnin.","id":"ac8an73qsxzr"},"type":"Feature","geometry":{"type":"Point","coordinates":[1.92335,46.82201]}},{"properties":{"name":"NEONS-SUR-CREUSE","description":"Concert avec les groupes \"The Run\" et \"Martine on the beach\", le 23 mars à 20 h 30, salle des associations.","id":"ac8an78fc5ka"},"type":"Feature","geometry":{"type":"Point","coordinates":[0.92877,46.74648]}},{"properties":{"name":"SAINT-CHRISTOPHE-EN-BAZELLE","description":"Spectacle avec la Compagnie \"Dandys Circus\", le 30 mars à 20 h 30, salle Beaulieu.","id":"ac8an7d5msa1"},"type":"Feature","geometry":{"type":"Point","coordinates":[1.71196,47.19171]}}],"is_temporal":false,"author":{"url":"","metadata":"","contact_name":"","contact_address":"","source":"","contact_phone":""},"source":"","pagination":{"sort":null,"start":0,"total":3,"limit":1000000},"state":"complete","tags":"","published":"2014-08-16T15:07:37-04:00","id":321648}