{"type":"FeatureCollection","data_type":"Dataset","url_type":null,"permissions":[{"permissions":{"download":true,"view":true},"group_id":"everyone"}],"classification":null,"title":"Macalelon_KC_SPs_with_geotagged","count":1,"stream_id":321990,"contributor":{"url":"http://geocommons.com/users/53738","name":"sambelamide"},"data_attributes":null,"calculation_params":null,"icon_link":null,"link":"http://geocommons.com/overlays/321990.json","extent":[122.132,13.7449,122.132,13.7449],"geometry_types":["point"],"unique_name":null,"name":"Macalelon_KC_SPs_with_geotagged","feature_count":1,"description":"","next_feature":null,"is_raster":false,"short_classification":"Y","stats":{"year funded":{"max":2011,"min":2011,"median":2011},"surveyor's o & m impression":{"max":2,"min":2,"median":2},"estimated total cost (p) 2nd mibf":{"max":5777900.0,"min":5777900.0,"median":5777900.0},"quantity":{"max":243,"min":243,"median":243},"community & lgu counterpart commitments (lcc)":{"max":1401146.0,"min":1401146.0,"median":1401146.0},"cycle":{"max":2,"min":2,"median":2},"no. of direct hh beneficiaries":{"max":329,"min":329,"median":329},"kalahi grant":{"max":4376754.0,"min":4376754.0,"median":4376754.0},"lat":{"max":13.744873,"min":13.744873,"median":13.744873},"long":{"max":122.132363,"min":122.132363,"median":122.132363}},"features":[{"properties":{"project name":"Construction of 243 Ln.m River Flood Control","year funded":2011,"fund source":"KC-AF","geotagged":"<a href=\"https://picasaweb.google.com/116819213269825706907/Castillo?authkey=Gv1sRgCOiEy_e_74elRA#5842137385082818066\"><img src=\"https://lh3.googleusercontent.com/-A9wiZW2BqbY/URNw_67kDhI/AAAAAAAAArA/UH-1nmsW9sY/s400/IMG_20130131_103240.jpg\" alt=\"IMG_20130131_103240.jpg\"></a>Date: Jan 31, 2013, 2:32 AMNumber of Comments on Photo:0<a href=\"https://picasaweb.google.com/116819213269825706907/Castillo?authkey=Gv1sRgCOiEy_e_74elRA#5842137385082818066\">View Photo</a>","surveyor's o & m impression":2,"estimated total cost (p) 2nd mibf":5777900.0,"quantity":243,"unit":"ln.m","community & lgu counterpart commitments (lcc)":1401146.0,"cycle":2,"major sp sub-category":"Flood Control","kalahi grant":4376754.0,"no. of direct hh beneficiaries":329,"id":"ac9irwp2yj46","lat":13.744873,"barangay":"Castillo","phase":"15 New","long":122.132363},"type":"Feature","geometry":{"type":"Point","coordinates":[122.132363,13.744873]}}],"is_temporal":false,"author":{"url":"","metadata":null,"contact_name":null,"contact_address":null,"source":null,"contact_phone":null},"source":"","pagination":{"sort":null,"start":0,"total":1,"limit":1000000},"state":"complete","tags":"","published":"2014-08-16T15:30:14-04:00","id":321990}