{"type":"FeatureCollection","data_type":"Dataset","url_type":null,"permissions":[{"permissions":{"download":true,"view":true},"group_id":"everyone"}],"classification":null,"title":"veg2","count":18,"stream_id":322415,"contributor":{"url":"http://geocommons.com/users/26034","name":"Desertification"},"data_attributes":null,"calculation_params":null,"icon_link":null,"link":"http://geocommons.com/overlays/322415.json","extent":[77.14,53.885,77.3465,53.9939],"geometry_types":["point"],"unique_name":null,"name":"veg2","feature_count":18,"description":"","next_feature":null,"is_raster":false,"short_classification":"Y","stats":{"x":{"max":77.34649,"variance":0.00501630213202617,"mean":77.1791055555555,"stdev":0.0708258577923782,"min":77.14004,"median":77.14896},"y":{"max":53.99394,"variance":0.00092864100000003,"mean":53.9094566666667,"stdev":0.0304736115352288,"min":53.88499,"median":53.90031}},"features":[{"properties":{"x":77.14004,"y":53.90182,"ID":"V1","id":"acay5frvve7i"},"type":"Feature","geometry":{"type":"Point","coordinates":[77.14004,53.90182]}},{"properties":{"x":77.14048,"y":53.90213,"ID":"V2","id":"acay5fq2c642"},"type":"Feature","geometry":{"type":"Point","coordinates":[77.14048,53.90213]}},{"properties":{"x":77.14347,"y":53.90031,"ID":"V3","id":"acay5ftz654n"},"type":"Feature","geometry":{"type":"Point","coordinates":[77.14347,53.90031]}},{"properties":{"x":77.14855,"y":53.89977,"ID":"V4","id":"acay5g5f13oj"},"type":"Feature","geometry":{"type":"Point","coordinates":[77.14855,53.89977]}},{"properties":{"x":77.14892,"y":53.89884,"ID":"V5","id":"acay5fw4e82a"},"type":"Feature","geometry":{"type":"Point","coordinates":[77.14892,53.89884]}},{"properties":{"x":77.14896,"y":53.89715,"ID":"V6","id":"acay5fzjbhc7"},"type":"Feature","geometry":{"type":"Point","coordinates":[77.14896,53.89715]}},{"properties":{"x":77.14147,"y":53.90661,"ID":"V7","id":"acay5fvg564s"},"type":"Feature","geometry":{"type":"Point","coordinates":[77.14147,53.90661]}},{"properties":{"x":77.14113,"y":53.90641,"ID":"V8","id":"acay5fu0wlk1"},"type":"Feature","geometry":{"type":"Point","coordinates":[77.14113,53.90641]}},{"properties":{"x":77.1447,"y":53.90617,"ID":"V9","id":"acay5fuhvhk3"},"type":"Feature","geometry":{"type":"Point","coordinates":[77.1447,53.90617]}},{"properties":{"x":77.17267,"y":53.89712,"ID":"V10","id":"acay5frodfjb"},"type":"Feature","geometry":{"type":"Point","coordinates":[77.17267,53.89712]}},{"properties":{"x":77.15044,"y":53.88968,"ID":"V11","id":"acay5fv97zve"},"type":"Feature","geometry":{"type":"Point","coordinates":[77.15044,53.88968]}},{"properties":{"x":77.14477,"y":53.88499,"ID":"V12","id":"acay5g159g4o"},"type":"Feature","geometry":{"type":"Point","coordinates":[77.14477,53.88499]}},{"properties":{"x":77.15079,"y":53.88609,"ID":"V13","id":"acay5g0dkiix"},"type":"Feature","geometry":{"type":"Point","coordinates":[77.15079,53.88609]}},{"properties":{"x":77.15525,"y":53.88653,"ID":"V14","id":"acay5g1y3nr5"},"type":"Feature","geometry":{"type":"Point","coordinates":[77.15525,53.88653]}},{"properties":{"x":77.15683,"y":53.88941,"ID":"V15","id":"acay5g3equ3m"},"type":"Feature","geometry":{"type":"Point","coordinates":[77.15683,53.88941]}},{"properties":{"x":77.34649,"y":53.99394,"ID":"V16","id":"acay5g3qymwc"},"type":"Feature","geometry":{"type":"Point","coordinates":[77.34649,53.99394]}},{"properties":{"x":77.32605,"y":53.95949,"ID":"V17","id":"acay5fwu1fkf"},"type":"Feature","geometry":{"type":"Point","coordinates":[77.32605,53.95949]}},{"properties":{"x":77.32289,"y":53.96376,"ID":"V18","id":"acay5fr4lcc4"},"type":"Feature","geometry":{"type":"Point","coordinates":[77.32289,53.96376]}}],"is_temporal":false,"author":{"url":"","metadata":"","contact_name":"","contact_address":"","source":"","contact_phone":""},"source":"","pagination":{"sort":null,"start":0,"total":18,"limit":1000000},"state":"complete","tags":"","published":"2014-08-16T15:50:22-04:00","id":322415}