{"type":"FeatureCollection","data_type":"Dataset","url_type":null,"permissions":[{"permissions":{"download":true,"view":true},"group_id":"everyone"}],"classification":null,"title":"Data map 3","count":10,"stream_id":322848,"contributor":{"url":"http://geocommons.com/users/16842","name":"david@villageearth.org"},"data_attributes":null,"calculation_params":null,"icon_link":null,"link":"http://geocommons.com/overlays/322848.json","extent":[-0.397,30.195,-0.216,39.884],"geometry_types":["point"],"unique_name":null,"name":"Data map 3","feature_count":10,"description":"","next_feature":null,"is_raster":false,"short_classification":"Y","stats":{"name":{"max":10,"variance":9.16666666666667,"mean":5.5,"stdev":3.02765035409749,"min":1,"median":6},"latitude":{"max":39.884,"variance":8.49845245555555,"mean":38.4747,"stdev":2.91521053365886,"min":30.195,"median":39.344},"longitude":{"max":-0.216,"variance":0.00363115555555556,"mean":-0.3274,"stdev":0.0602590703177169,"min":-0.397,"median":-0.326}},"features":[{"properties":{"name":1,"latitude":39.433,"longitude":-0.344,"id":"acbsvb82jj0r"},"type":"Feature","geometry":{"type":"Point","coordinates":[-0.344,39.433]}},{"properties":{"name":2,"latitude":39.428,"longitude":-0.326,"id":"acbsvbn3q7jw"},"type":"Feature","geometry":{"type":"Point","coordinates":[-0.326,39.428]}},{"properties":{"name":3,"latitude":39.33,"longitude":-0.292,"id":"acbsvbmfa53h"},"type":"Feature","geometry":{"type":"Point","coordinates":[-0.292,39.33]}},{"properties":{"name":4,"latitude":30.195,"longitude":-0.216,"id":"acbsvbex1898"},"type":"Feature","geometry":{"type":"Point","coordinates":[-0.216,30.195]}},{"properties":{"name":5,"latitude":39.884,"longitude":-0.289,"id":"acbsvbif49sz"},"type":"Feature","geometry":{"type":"Point","coordinates":[-0.289,39.884]}},{"properties":{"name":6,"latitude":39.217,"longitude":-0.268,"id":"acbsvbd9zemv"},"type":"Feature","geometry":{"type":"Point","coordinates":[-0.268,39.217]}},{"properties":{"name":7,"latitude":39.241,"longitude":-0.386,"id":"acbsvbnj9haw"},"type":"Feature","geometry":{"type":"Point","coordinates":[-0.386,39.241]}},{"properties":{"name":8,"latitude":39.287,"longitude":-0.365,"id":"acbsvbo5pmox"},"type":"Feature","geometry":{"type":"Point","coordinates":[-0.365,39.287]}},{"properties":{"name":9,"latitude":39.344,"longitude":-0.397,"id":"acbsvbk2qq3a"},"type":"Feature","geometry":{"type":"Point","coordinates":[-0.397,39.344]}},{"properties":{"name":10,"latitude":39.388,"longitude":-0.391,"id":"acbsvbkil8w7"},"type":"Feature","geometry":{"type":"Point","coordinates":[-0.391,39.388]}}],"is_temporal":false,"author":{"url":"","metadata":"","contact_name":"","contact_address":"","source":"","contact_phone":""},"source":"","pagination":{"sort":null,"start":0,"total":10,"limit":1000000},"state":"complete","tags":"","published":"2014-08-16T16:13:30-04:00","id":322848}