{"type":"FeatureCollection","data_type":"Dataset","url_type":null,"permissions":[{"permissions":{"download":true,"view":true},"group_id":"everyone"}],"classification":null,"title":"Rosen Mazda Sales by Zip","count":18,"stream_id":327295,"contributor":{"url":"http://geocommons.com/users/62916","name":"alexkim"},"data_attributes":null,"calculation_params":null,"icon_link":null,"link":"http://geocommons.com/overlays/327295.json","extent":[-88.3328,42.0445,-87.688,42.7299],"geometry_types":["point"],"unique_name":null,"name":"Rosen Mazda Sales by Zip","feature_count":18,"description":"","next_feature":null,"is_raster":false,"short_classification":"Y","stats":{"sales":{"max":6,"variance":2.29084967320261,"mean":2.05555555555556,"stdev":1.5135553089341,"min":1,"median":1}},"features":[{"properties":{"sales":2,"geo_score":0.714,"zip code":"53143","id":"acm9hj1et4t3","geo_precision":"zip"},"type":"Feature","geometry":{"type":"Point","coordinates":[-87.824828,42.53607]}},{"properties":{"sales":1,"geo_score":0.714,"zip code":"53406","id":"acm9hja42w3t","geo_precision":"zip"},"type":"Feature","geometry":{"type":"Point","coordinates":[-87.866213,42.72993]}},{"properties":{"sales":1,"geo_score":0.714,"zip code":"60021","id":"acm9hjbeb869","geo_precision":"zip"},"type":"Feature","geometry":{"type":"Point","coordinates":[-88.250406,42.213058]}},{"properties":{"sales":1,"geo_score":0.714,"zip code":"60025","id":"acm9hj4qtiv5","geo_precision":"zip"},"type":"Feature","geometry":{"type":"Point","coordinates":[-87.819714,42.082715]}},{"properties":{"sales":2,"geo_score":0.714,"zip code":"60030","id":"acm9hjan6a4u","geo_precision":"zip"},"type":"Feature","geometry":{"type":"Point","coordinates":[-87.982577,42.351689]}},{"properties":{"sales":6,"geo_score":0.714,"zip code":"60031","id":"acm9hix38m1k","geo_precision":"zip"},"type":"Feature","geometry":{"type":"Point","coordinates":[-87.986745,42.393077]}},{"properties":{"sales":1,"geo_score":0.714,"zip code":"60035","id":"acm9hivzcnf6","geo_precision":"zip"},"type":"Feature","geometry":{"type":"Point","coordinates":[-87.787009,42.163637]}},{"properties":{"sales":1,"geo_score":0.714,"zip code":"60061","id":"acm9hivn3ald","geo_precision":"zip"},"type":"Feature","geometry":{"type":"Point","coordinates":[-87.962973,42.231183]}},{"properties":{"sales":4,"geo_score":0.714,"zip code":"60073","id":"acm9hj7w0een","geo_precision":"zip"},"type":"Feature","geometry":{"type":"Point","coordinates":[-88.167861,42.326133]}},{"properties":{"sales":2,"geo_score":0.714,"zip code":"60083","id":"acm9hj2hbb51","geo_precision":"zip"},"type":"Feature","geometry":{"type":"Point","coordinates":[-87.952578,42.465298]}},{"properties":{"sales":4,"geo_score":0.714,"zip code":"60085","id":"acm9hix5dilb","geo_precision":"zip"},"type":"Feature","geometry":{"type":"Point","coordinates":[-87.88424,42.348355]}},{"properties":{"sales":4,"geo_score":0.714,"zip code":"60087","id":"acm9hj1n8qwg","geo_precision":"zip"},"type":"Feature","geometry":{"type":"Point","coordinates":[-87.868471,42.372921]}},{"properties":{"sales":1,"geo_score":0.714,"zip code":"60088","id":"acm9hj5x8vjb","geo_precision":"zip"},"type":"Feature","geometry":{"type":"Point","coordinates":[-87.85427,42.309272]}},{"properties":{"sales":1,"geo_score":0.714,"zip code":"60089","id":"acm9hj43z915","geo_precision":"zip"},"type":"Feature","geometry":{"type":"Point","coordinates":[-87.960771,42.180411]}},{"properties":{"sales":1,"geo_score":0.714,"zip code":"60091","id":"acm9hj0fw4d3","geo_precision":"zip"},"type":"Feature","geometry":{"type":"Point","coordinates":[-87.72836,42.079228]}},{"properties":{"sales":1,"geo_score":0.714,"zip code":"60097","id":"acm9hiwe0edx","geo_precision":"zip"},"type":"Feature","geometry":{"type":"Point","coordinates":[-88.332794,42.355165]}},{"properties":{"sales":3,"geo_score":0.714,"zip code":"60099","id":"acm9hj4vbrwq","geo_precision":"zip"},"type":"Feature","geometry":{"type":"Point","coordinates":[-87.857296,42.422244]}},{"properties":{"sales":1,"geo_score":0.714,"zip code":"60202","id":"acm9hj51jwy4","geo_precision":"zip"},"type":"Feature","geometry":{"type":"Point","coordinates":[-87.687969,42.044529]}}],"is_temporal":false,"author":{"url":"","metadata":"","contact_name":"","contact_address":"","source":"","contact_phone":""},"source":"","pagination":{"sort":null,"start":0,"total":18,"limit":1000000},"state":"complete","tags":"","published":"2014-08-16T22:06:02-04:00","id":327295}