{"type":"FeatureCollection","data_type":"Dataset","url_type":null,"permissions":[{"permissions":{"download":true,"view":true},"group_id":"everyone"}],"classification":null,"title":"Resenärsdata GIS","count":4,"stream_id":328447,"contributor":{"url":"http://geocommons.com/users/64107","name":"jacvik"},"data_attributes":null,"calculation_params":null,"icon_link":null,"link":"http://geocommons.com/overlays/328447.json","extent":[18.0759,59.2943,18.0906,59.3085],"geometry_types":["point"],"unique_name":null,"name":"Resenärsdata GIS","feature_count":4,"description":"","next_feature":null,"is_raster":false,"short_classification":"Y","stats":{"avstigande 16-17":{"max":7300,"variance":10029166.6666667,"mean":2725.0,"stdev":3166.88595731938,"min":500,"median":2400}},"features":[{"properties":{"geometry_id":"52","avstigande 16-17":500,"id":"acn01j4thmu9","station":"Globen - T/a"},"type":"Feature","geometry":{"type":"Point","coordinates":[18.077975,59.294298]}},{"properties":{"geometry_id":"148","avstigande 16-17":2400,"id":"acn01j27d4fx","station":"Skanstull - T/a"},"type":"Feature","geometry":{"type":"Point","coordinates":[18.075938,59.308522]}},{"properties":{"geometry_id":"158","avstigande 16-17":700,"id":"acn01j10tezl","station":"Skärmarbrink - T/a"},"type":"Feature","geometry":{"type":"Point","coordinates":[18.090584,59.295406]}},{"properties":{"geometry_id":"58","avstigande 16-17":7300,"id":"acn01j0dfoj9","station":"Gullmarsplan - T/a"},"type":"Feature","geometry":{"type":"Point","coordinates":[18.080633,59.299137]}}],"is_temporal":false,"author":{"url":"","metadata":"","contact_name":"","contact_address":"","source":"","contact_phone":""},"source":"","pagination":{"sort":null,"start":0,"total":4,"limit":1000000},"state":"complete","tags":"","published":"2014-08-16T23:27:15-04:00","id":328447}