{"type":"FeatureCollection","data_type":"Dataset","url_type":null,"permissions":[{"permissions":{"download":true,"view":true},"group_id":"everyone"}],"classification":null,"title":"zip7","count":14,"stream_id":328574,"contributor":{"url":"http://geocommons.com/users/64130","name":"castorrj1"},"data_attributes":null,"calculation_params":null,"icon_link":null,"link":"http://geocommons.com/overlays/328574.json","extent":[-80.1937,25.7743,-74.3468,42.092],"geometry_types":["point"],"unique_name":null,"name":"zip7","feature_count":14,"description":"","next_feature":null,"is_raster":false,"short_classification":"Y","stats":{},"features":[{"properties":{"zip":"7090","geo_score":0.714,"id":"acn9kr45qjm0","geo_precision":"zip"},"type":"Feature","geometry":{"type":"Point","coordinates":[-74.346764,40.652851]}},{"properties":{"zip":"15106","geo_score":0.714,"id":"acn9kr6pzskp","geo_precision":"zip"},"type":"Feature","geometry":{"type":"Point","coordinates":[-80.112556,40.399514]}},{"properties":{"zip":"15139","geo_score":0.714,"id":"acn9kr50n9bc","geo_precision":"zip"},"type":"Feature","geometry":{"type":"Point","coordinates":[-80.024817,40.434436]}},{"properties":{"zip":"15203","geo_score":0.714,"id":"acn9kr7m4fw8","geo_precision":"zip"},"type":"Feature","geometry":{"type":"Point","coordinates":[-79.979914,40.425369]}},{"properties":{"zip":"15209","geo_score":0.714,"id":"acn9krgx4wc3","geo_precision":"zip"},"type":"Feature","geometry":{"type":"Point","coordinates":[-79.978386,40.480069]}},{"properties":{"zip":"15212","geo_score":0.714,"id":"acn9kr8t06ai","geo_precision":"zip"},"type":"Feature","geometry":{"type":"Point","coordinates":[-79.989104,40.48529]}},{"properties":{"zip":"15227","geo_score":0.714,"id":"acn9krcw9oe2","geo_precision":"zip"},"type":"Feature","geometry":{"type":"Point","coordinates":[-79.990886,40.361181]}},{"properties":{"zip":"15233","geo_score":0.714,"id":"acn9krfixepi","geo_precision":"zip"},"type":"Feature","geometry":{"type":"Point","coordinates":[-80.024817,40.434436]}},{"properties":{"zip":"16156","geo_score":0.714,"id":"acn9krdjqha6","geo_precision":"zip"},"type":"Feature","geometry":{"type":"Point","coordinates":[-80.187839,41.117004]}},{"properties":{"zip":"16229","geo_score":0.714,"id":"acn9krggwoqz","geo_precision":"zip"},"type":"Feature","geometry":{"type":"Point","coordinates":[-79.642826,40.767009]}},{"properties":{"zip":"16505","geo_score":0.714,"id":"acn9kr9q80aq","geo_precision":"zip"},"type":"Feature","geometry":{"type":"Point","coordinates":[-80.173673,42.092002]}},{"properties":{"zip":"17331","geo_score":0.714,"id":"acn9krg11yp6","geo_precision":"zip"},"type":"Feature","geometry":{"type":"Point","coordinates":[-76.973313,39.825099]}},{"properties":{"zip":"28451","geo_score":0.714,"id":"acn9kr50db8d","geo_precision":"zip"},"type":"Feature","geometry":{"type":"Point","coordinates":[-77.965822,34.230726]}},{"properties":{"zip":"33139","geo_score":0.714,"id":"acn9krd03pc5","geo_precision":"zip"},"type":"Feature","geometry":{"type":"Point","coordinates":[-80.193659,25.774266]}}],"is_temporal":false,"author":{"url":"","metadata":"","contact_name":"","contact_address":"","source":"","contact_phone":""},"source":"","pagination":{"sort":null,"start":0,"total":14,"limit":1000000},"state":"complete","tags":"","published":"2014-08-16T23:39:26-04:00","id":328574}