{"type":"FeatureCollection","data_type":"Dataset","url_type":null,"permissions":[{"permissions":{"download":true,"view":true},"group_id":"everyone"}],"classification":null,"title":"Community BtG","count":3,"stream_id":329234,"contributor":{"url":"http://geocommons.com/users/54257","name":"matthew.dunlevy"},"data_attributes":null,"calculation_params":null,"icon_link":null,"link":"http://geocommons.com/overlays/329234.json","extent":[1.68025,-55.0,53.0,52.3277],"geometry_types":["point"],"unique_name":null,"name":"Community BtG","feature_count":3,"description":"","next_feature":null,"is_raster":false,"short_classification":"Y","stats":{"capacity (kwe)":{"max":6000,"variance":11004101.3333333,"mean":2182.66666666667,"stdev":3317.2430319971,"min":0,"median":548},"latitude":{"max":52.3276748,"variance":3839.74325932485,"mean":-19.2241084,"stdev":61.9656619372766,"min":-55.0,"median":-55.0},"longitude":{"max":53.0,"variance":877.905634761901,"mean":35.8934161333333,"stdev":29.6294724010047,"min":1.6802484,"median":53.0}},"features":[{"properties":{"capacity (kwe)":548,"category":"Community BtG","latitude":52.3276748,"postcode":"IP18 6JW","company name":"Adnams Brewery","longitude":1.6802484,"id":"acoenjg1r8n7"},"type":"Feature","geometry":{"type":"Point","coordinates":[1.6802484,52.3276748]}},{"properties":{"capacity (kwe)":6000,"category":null,"latitude":-55.0,"postcode":null,"company name":"Ignore me","longitude":53.0,"id":"acoenj9c5tkw"},"type":"Feature","geometry":{"type":"Point","coordinates":[53.0,-55.0]}},{"properties":{"capacity (kwe)":0,"category":null,"latitude":-55.0,"postcode":null,"company name":"Ignore me as well","longitude":53.0,"id":"acoenjc6t2k1"},"type":"Feature","geometry":{"type":"Point","coordinates":[53.0,-55.0]}}],"is_temporal":false,"author":{"url":"","metadata":"","contact_name":"","contact_address":"","source":"","contact_phone":""},"source":"","pagination":{"sort":null,"start":0,"total":3,"limit":1000000},"state":"complete","tags":"","published":"2014-08-17T00:18:23-04:00","id":329234}