{"type":"FeatureCollection","data_type":"Dataset","url_type":null,"permissions":[{"permissions":{"download":true,"view":true},"group_id":"everyone"}],"classification":null,"title":"Fetch CSV Module Example copy","count":16,"stream_id":334224,"contributor":{"url":"http://geocommons.com/users/66532","name":"MDatta"},"data_attributes":null,"calculation_params":null,"icon_link":null,"link":"http://geocommons.com/overlays/334224.json","extent":[-172.632,-66.181,-77.57,-41.41],"geometry_types":["point"],"unique_name":null,"name":"Fetch CSV Module Example copy","feature_count":16,"description":"Government scientific institutions collect a lot of data, and much of this data is available on the internet. Our example uses some data collected by the U.S. Coast Guard's ship Polar Star. This ship supports scientific and ice escort missions in the arctic and antarctic.\r\n\r\nThe CSV dataset contains various environmental readings recorded by the Polar Star in the antarctic. This data is somewhat more interesting because it includes geolocation data. This lets us display our final feed on a map.\r\n\r\n","next_feature":null,"is_raster":false,"short_classification":"Y","stats":{},"features":[{"properties":{"name":"02/17/02 18:46:21","description":"EqTemp: 0.33, JD: 48.782","id":"aczpgjgu3tum"},"type":"Feature","geometry":{"type":"Point","coordinates":[-171.932,-65.95]}},{"properties":{"name":"02/18/02 00:46:21","description":"EqTemp: 0.27, JD: 49.032","id":"aczpgjh4leqa"},"type":"Feature","geometry":{"type":"Point","coordinates":[-172.612,-66.181]}},{"properties":{"name":"02/19/02 00:46:21","description":"EqTemp: 0.50, JD: 50.032","id":"aczpgjsfa7d4"},"type":"Feature","geometry":{"type":"Point","coordinates":[-172.632,-65.249]}},{"properties":{"name":"02/20/02 00:46:21","description":"EqTemp: 0.27, JD: 51.032","id":"aczpgjocygol"},"type":"Feature","geometry":{"type":"Point","coordinates":[-170.625,-65.878]}},{"properties":{"name":"02/21/02 00:46:21","description":"EqTemp: 0.29, JD: 52.032","id":"aczpgjq09uoi"},"type":"Feature","geometry":{"type":"Point","coordinates":[-172.135,-65.783]}},{"properties":{"name":"02/22/02 00:46:21","description":"EqTemp: -0.15, JD: 53.032","id":"aczpgjssbv6t"},"type":"Feature","geometry":{"type":"Point","coordinates":[-160.432,-65.667]}},{"properties":{"name":"02/23/02 00:46:21","description":"EqTemp: -0.28, JD: 54.032","id":"aczpgji8x8i2"},"type":"Feature","geometry":{"type":"Point","coordinates":[-145.335,-65.425]}},{"properties":{"name":"02/24/02 00:46:21","description":"EqTemp: -0.09, JD: 55.032","id":"aczpgjpajzwp"},"type":"Feature","geometry":{"type":"Point","coordinates":[-131.424,-65.22]}},{"properties":{"name":"02/25/02 00:46:21","description":"EqTemp: 0.89, JD: 56.032","id":"aczpgjr9mc3g"},"type":"Feature","geometry":{"type":"Point","coordinates":[-116.672,-64.915]}},{"properties":{"name":"02/26/02 00:46:21","description":"EqTemp: 2.89, JD: 57.032","id":"aczpgjqxbvp6"},"type":"Feature","geometry":{"type":"Point","coordinates":[-105.042,-61.478]}},{"properties":{"name":"02/27/02 00:46:21","description":"EqTemp: 5.05, JD: 58.032","id":"aczpgjpb4edc"},"type":"Feature","geometry":{"type":"Point","coordinates":[-97.356,-58.105]}},{"properties":{"name":"02/28/02 00:46:21","description":"EqTemp: 6.62, JD: 59.032","id":"aczpgjjnzk8q"},"type":"Feature","geometry":{"type":"Point","coordinates":[-92.123,-55.028]}},{"properties":{"name":"03/01/02 00:46:21","description":"EqTemp: 7.81, JD: 60.032","id":"aczpgjub2y8l"},"type":"Feature","geometry":{"type":"Point","coordinates":[-87.691,-51.847]}},{"properties":{"name":"03/02/02 00:46:21","description":"EqTemp: 10.22, JD: 61.032","id":"aczpgjtbnamv"},"type":"Feature","geometry":{"type":"Point","coordinates":[-83.99,-48.439]}},{"properties":{"name":"03/03/02 00:46:21","description":"EqTemp: 13.44, JD: 62.032","id":"aczpgjknzelt"},"type":"Feature","geometry":{"type":"Point","coordinates":[-80.63,-45.015]}},{"properties":{"name":"03/04/02 00:46:21","description":"EqTemp: 16.49, JD: 63.032","id":"aczpgjiiknae"},"type":"Feature","geometry":{"type":"Point","coordinates":[-77.57,-41.41]}}],"is_temporal":false,"author":{"url":"","metadata":"","contact_name":"","contact_address":"","source":"","contact_phone":""},"source":"","pagination":{"sort":null,"start":0,"total":16,"limit":1000000},"state":"complete","tags":"","published":"2014-08-16T18:28:05-04:00","id":334224}