{"type":"FeatureCollection","data_type":"Dataset","url_type":null,"permissions":[{"permissions":{"download":true,"view":true},"group_id":"everyone"}],"classification":null,"title":"Workbook3","count":3,"stream_id":334968,"contributor":{"url":"http://geocommons.com/users/66435","name":"boyless123"},"data_attributes":null,"calculation_params":null,"icon_link":null,"link":"http://geocommons.com/overlays/334968.json","extent":[-96.9817,49.5478,-96.9817,49.5478],"geometry_types":["point"],"unique_name":null,"name":"Workbook3","feature_count":3,"description":"","next_feature":null,"is_raster":false,"short_classification":"Y","stats":{},"features":[{"properties":{"city":"Toronto","last name":"Sundin","country":"Canada","geo_score":0.857,"id":"ad0l6juqvn11","first name":"Mats","geo_precision":"zip"},"type":"Feature","geometry":{"type":"Point","coordinates":[-96.981734654,49.547791028]}},{"properties":{"city":null,"last name":null,"country":"Address","geo_score":0.0,"id":"ad0l6joqhd28","first name":null,"geo_precision":"unmatched"},"type":"Feature","geometry":null},{"properties":{"city":null,"last name":null,"country":"40 Bay St","geo_score":0.0,"id":"ad0l6jqkqrep","first name":null,"geo_precision":"unmatched"},"type":"Feature","geometry":null}],"is_temporal":false,"author":{"url":"","metadata":null,"contact_name":null,"contact_address":null,"source":null,"contact_phone":null},"source":"","pagination":{"sort":null,"start":0,"total":3,"limit":1000000},"state":"complete","tags":"","published":"2014-08-16T19:13:40-04:00","id":334968}