{"type":"FeatureCollection","data_type":"Dataset","url_type":null,"permissions":[{"permissions":{"download":true,"view":true},"group_id":"everyone"}],"classification":null,"title":"PIQS 3 - SOE","count":3,"stream_id":336613,"contributor":{"url":"http://geocommons.com/users/67454","name":"tomaj"},"data_attributes":null,"calculation_params":null,"icon_link":null,"link":"http://geocommons.com/overlays/336613.json","extent":[-118.109,33.6754,-117.805,34.1379],"geometry_types":["point"],"unique_name":null,"name":"PIQS 3 - SOE","feature_count":3,"description":"","next_feature":null,"is_raster":false,"short_classification":"Y","stats":{},"features":[{"properties":{"city":"Huntington Beach","name":"Mr. &amp; Mrs. Ramon Silver","zipcode":"92649-4219","geo_score":1.0,"id":"ad4t189id6m8","address":"17021 Westport Dr","phone number":"(714) 3778834","group":"Social Ecology","geo_precision":"range","state":"CA"},"type":"Feature","geometry":{"type":"Point","coordinates":[-118.054186,33.714955]}},{"properties":{"city":"Pasadena","name":"Mrs. Robin Wendy Radin, B.A. '75\nMr. Larry Peter Radin","zipcode":"91107-5154","geo_score":1.0,"id":"ad4t18gsita3","address":"1981 San Pasqual St","phone number":"(626) 2290560","group":"Social Ecology","geo_precision":"range","state":"CA"},"type":"Feature","geometry":{"type":"Point","coordinates":[-118.108694,34.1379]}},{"properties":{"city":"Irvine","name":"Mr. Peter Case Fildes, B.A. '78\nMrs. Karen M. Fildes","zipcode":"92614-7988","geo_score":1.0,"id":"ad4t18717ju3","address":"23 Bayside","phone number":"(949) 2621476","group":"Social Ecology","geo_precision":"range","state":"CA"},"type":"Feature","geometry":{"type":"Point","coordinates":[-117.80482,33.675405]}}],"is_temporal":false,"author":{"url":"","metadata":null,"contact_name":null,"contact_address":null,"source":null,"contact_phone":null},"source":"","pagination":{"sort":null,"start":0,"total":3,"limit":1000000},"state":"complete","tags":"","published":"2014-08-16T21:23:25-04:00","id":336613}