{"type":"FeatureCollection","data_type":"Dataset Analysis","url_type":null,"permissions":[{"permissions":{"download":true,"view":true},"group_id":"everyone"}],"classification":null,"title":"Filtered Features of 'CT ped fatalities for map09-11--child' based on 'Cttransit Bus Stops'","count":4,"stream_id":337977,"contributor":{"url":"http://geocommons.com/users/34264","name":"RenataPS"},"data_attributes":null,"calculation_params":{"input":{"min_distance":"0","unit":"miles","near_id":"232775","distance":".25","include_distance":true,"id":"337965"},"calculation":"buffer_intersect"},"icon_link":null,"link":"http://geocommons.com/overlays/337977.json","extent":[-73.0487,41.322,-72.6975,41.7544],"geometry_types":["point"],"unique_name":null,"name":"Filtered Features of 'CT ped fatalities for map09-11--child' based on 'Cttransit Bus Stops'","feature_count":4,"description":"Dataset created by filtering features of 'CT ped fatalities for map09-11--child' that are within a buffer of 0 to .25 miles around the features in 'Cttransit Bus Stops'","next_feature":null,"is_raster":false,"short_classification":"Y","stats":{"latitude":{"max":41.75435556,"variance":0.0348859164173742,"mean":41.5773666675,"stdev":0.186777719274474,"min":41.322,"median":41.6668},"longitud":{"max":-72.69748056,"variance":0.0221742801610841,"mean":-72.885370835,"stdev":0.148910309116206,"min":-73.04870278,"median":-72.8516},"distance":{"max":0.249468026028347,"variance":0.0130196554150258,"mean":0.0863004591272145,"stdev":0.114103704650751,"min":0.000912252702049005,"median":0.0799634370150275}},"features":[{"properties":{"latitude":41.322,"text 1":"SR-80","text 2":"15 year old male killed on 7/25/2009","longitud":-72.8516,"id":"ad7949ii2lyb","distance":0.000912252702049005},"type":"Feature","geometry":{"type":"Point","coordinates":[-72.8516,41.322]}},{"properties":{"latitude":41.56631111,"text 1":"WILLOW STREET","text 2":"3 year old male killed on 4/15/2010","longitud":-73.04870278,"id":"ad79498kivri","distance":0.249468026028347},"type":"Feature","geometry":{"type":"Point","coordinates":[-73.04870278,41.56631111]}},{"properties":{"latitude":41.6668,"text 1":"GEORGE STREET","text 2":"14 year old male killed on 3/5/2009","longitud":-72.9437,"id":"ad7949g62pbb","distance":0.0799634370150275},"type":"Feature","geometry":{"type":"Point","coordinates":[-72.9437,41.6668]}},{"properties":{"latitude":41.75435556,"text 1":"POPE PARK DRIVE","text 2":"3 year old male killed on 5/12/2011","longitud":-72.69748056,"id":"ad79498uz21j","distance":0.0148581207634345},"type":"Feature","geometry":{"type":"Point","coordinates":[-72.69748056,41.75435556]}}],"is_temporal":false,"author":{"url":"","metadata":"","contact_name":"","contact_address":"","source":"","contact_phone":""},"source":"","pagination":{"sort":null,"start":0,"total":4,"limit":1000000},"state":"complete","tags":"","published":"2014-08-16T22:51:35-04:00","id":337977}