{"type":"FeatureCollection","data_type":"Dataset","url_type":null,"permissions":[{"permissions":{"download":true,"view":true},"group_id":"everyone"}],"classification":null,"title":"oap project details construction 04012013","count":2,"stream_id":339222,"contributor":{"url":"http://geocommons.com/users/50798","name":"mglarson"},"data_attributes":null,"calculation_params":null,"icon_link":null,"link":"http://geocommons.com/overlays/339222.json","extent":[-86.7567,36.1568,-86.6212,36.1892],"geometry_types":["point"],"unique_name":null,"name":"oap project details construction 04012013","feature_count":2,"description":"","next_feature":null,"is_raster":false,"short_classification":"Y","stats":{"latitude":{"max":36.189152,"variance":0.000524588440499901,"mean":36.1729565,"stdev":0.0229038957494113,"min":36.156761,"median":36.189152},"longitude":{"max":-86.621189,"variance":0.00917795712800071,"mean":-86.688931,"stdev":0.0958016551422819,"min":-86.756673,"median":-86.621189}},"features":[{"properties":{"status":"Construction","project name":"Dodson Chapel Equalization Facility","latitude":36.189152,"description":"<a href=\"http://www.cleanwaternashville.org/projects/construction/dodson_chapel_eq\">Learn more about this project</a>","longitude":-86.621189,"mws project no.":"99-SC-009L","id":"adasdrb5heyi"},"type":"Feature","geometry":{"type":"Point","coordinates":[-86.621189,36.189152]}},{"properties":{"status":"Construction","project name":"Driftwood Equalization Facility","latitude":36.156761,"description":"<a href=\"www.cleanwaternashville.org/projects/construction/driftwood_eq\">Learn more about this project</a>","longitude":-86.756673,"mws project no.":"11-SC-067","id":"adasdr1izojf"},"type":"Feature","geometry":{"type":"Point","coordinates":[-86.756673,36.156761]}}],"is_temporal":false,"author":{"url":"","metadata":"","contact_name":"","contact_address":"","source":"","contact_phone":""},"source":"","pagination":{"sort":null,"start":0,"total":2,"limit":1000000},"state":"complete","tags":"","published":"2014-08-17T00:09:16-04:00","id":339222}