{"type":"FeatureCollection","data_type":"Dataset","url_type":null,"permissions":[{"permissions":{"download":true,"view":true},"group_id":"everyone"}],"classification":null,"title":"GlobalWatershedPointCA","count":1,"stream_id":339647,"contributor":{"url":"http://geocommons.com/users/68562","name":"rickpa84"},"data_attributes":null,"calculation_params":null,"icon_link":null,"link":"http://geocommons.com/overlays/339647.json","extent":[-116.815,32.711,-116.815,32.711],"geometry_types":["point"],"unique_name":null,"name":"GlobalWatershedPointCA","feature_count":1,"description":"","next_feature":null,"is_raster":false,"short_classification":"Y","stats":{"HydroID":{"max":1728479,"min":1728479,"median":1728479},"DrainID":{"max":1728480,"min":1728480,"median":1728480},"Longitude":{"max":-116.8153,"min":-116.8153,"median":-116.8153},"Latitude":{"max":32.711,"min":32.711,"median":32.711},"Measure":{"max":0.0,"min":0.0,"median":0.0}},"features":[{"properties":{"HydroID":1728479,"Name":"WatershedName","DrainID":1728480,"ReachCode":null,"Longitude":-116.8153,"Descript":"PUNIT_18A","Latitude":32.711,"Measure":0.0,"id":"adblrl4thozv","HUCID":"UNIT_18A"},"type":"Feature","geometry":{"type":"Point","coordinates":[-116.81526177223,32.7110205960625]}}],"is_temporal":false,"author":{"url":"","metadata":"","contact_name":"","contact_address":"","source":"","contact_phone":""},"source":"","pagination":{"sort":null,"start":0,"total":1,"limit":1000000},"state":"complete","tags":"","published":"2014-08-17T00:41:05-04:00","id":339647}