{"type":"FeatureCollection","data_type":"Dataset","url_type":null,"permissions":[{"permissions":{"download":true,"view":true},"group_id":"everyone"}],"classification":null,"title":"CT ped fatalities for map09-11--child","count":7,"stream_id":340376,"contributor":{"url":"http://geocommons.com/users/34264","name":"RenataPS"},"data_attributes":null,"calculation_params":null,"icon_link":null,"link":"http://geocommons.com/overlays/340376.json","extent":[-73.4591,41.322,-72.6975,41.7544],"geometry_types":["point"],"unique_name":null,"name":"CT ped fatalities for map09-11--child","feature_count":7,"description":"","next_feature":null,"is_raster":false,"short_classification":"Y","stats":{"latitude":{"max":41.75435556,"variance":0.0238076817229314,"mean":41.5645996028571,"stdev":0.15429738080386,"min":41.322,"median":41.6007},"longitud":{"max":-72.69748056,"variance":0.0655091144004834,"mean":-72.9671742071429,"stdev":0.255947483676795,"min":-73.45909722,"median":-72.9437}},"features":[{"properties":{"text 1":"GEORGE STREET","latitude":41.6668,"text 2":"14 year old male killed on 3/5/2009","longitud":-72.9437,"id":"adcgsepis84f"},"type":"Feature","geometry":{"type":"Point","coordinates":[-72.9437,41.6668]}},{"properties":{"text 1":"BROOKFIELD ROAD","latitude":41.6007,"text 2":"4 year old male killed on 9/10/2009","longitud":-73.0335,"id":"adcgseho7gt9"},"type":"Feature","geometry":{"type":"Point","coordinates":[-73.0335,41.6007]}},{"properties":{"text 1":"SR-80","latitude":41.322,"text 2":"15 year old male killed on 7/25/2009","longitud":-72.8516,"id":"adcgsejl0wia"},"type":"Feature","geometry":{"type":"Point","coordinates":[-72.8516,41.322]}},{"properties":{"text 1":"CHURCH STREET at ROWLEY STREET","latitude":41.64836111,"text 2":"14 year old male killed on 11/5/2010","longitud":-72.73613889,"id":"adcgsepdkcz9"},"type":"Feature","geometry":{"type":"Point","coordinates":[-72.73613889,41.64836111]}},{"properties":{"text 1":"WILLOW STREET","latitude":41.56631111,"text 2":"3 year old male killed on 4/15/2010","longitud":-73.04870278,"id":"adcgsetmnhvp"},"type":"Feature","geometry":{"type":"Point","coordinates":[-73.04870278,41.56631111]}},{"properties":{"text 1":"STEVENS STREET","latitude":41.39366944,"text 2":"4 year old male killed on 7/29/2010","longitud":-73.45909722,"id":"adcgseog9gg8"},"type":"Feature","geometry":{"type":"Point","coordinates":[-73.45909722,41.39366944]}},{"properties":{"text 1":"POPE PARK DRIVE","latitude":41.75435556,"text 2":"3 year old male killed on 5/12/2011","longitud":-72.69748056,"id":"adcgseokdohi"},"type":"Feature","geometry":{"type":"Point","coordinates":[-72.69748056,41.75435556]}}],"is_temporal":false,"author":{"url":"","metadata":"","contact_name":"","contact_address":"","source":"NHTSA's FARS database","contact_phone":""},"source":"","pagination":{"sort":null,"start":0,"total":7,"limit":1000000},"state":"complete","tags":"","published":"2014-08-16T13:27:02-04:00","id":340376}