{"type":"FeatureCollection","data_type":"Dataset","url_type":null,"permissions":[{"permissions":{"download":true,"view":true},"group_id":"everyone"}],"classification":null,"title":"saladworks_PA_creativeC","count":10,"stream_id":341590,"contributor":{"url":"http://geocommons.com/users/59628","name":"alenamin"},"data_attributes":null,"calculation_params":null,"icon_link":null,"link":"http://geocommons.com/overlays/341590.json","extent":[-76.7458,39.7685,-74.0815,40.8418],"geometry_types":["point"],"unique_name":null,"name":"saladworks_PA_creativeC","feature_count":10,"description":"","next_feature":null,"is_raster":false,"short_classification":"Y","stats":{"latitude":{"max":40.841799,"variance":0.150954020810544,"mean":40.1728909,"stdev":0.388528018050879,"min":39.7685,"median":40.0298},"longitude":{"max":-74.081543,"variance":0.806027385959216,"mean":-75.1869669,"stdev":0.897790279496953,"min":-76.7458,"median":-75.125732},"column_1":{"max":1,"variance":0.0,"mean":1.0,"stdev":0.0,"min":1,"median":1}},"features":[{"properties":{"column_5":"CBS","latitude":39.969319,"column_6":"14'x48'","creative":"C","column_1":1,"longitude":-75.125732,"id":"ade12s34y101","column_2":"178O","column_3":"Delaware &amp; Aramingo E/S F/N"},"type":"Feature","geometry":{"type":"Point","coordinates":[-75.125732,39.969319]}},{"properties":{"column_5":"Interstate","latitude":39.92941,"column_6":"14'x48'","creative":"C","column_1":1,"longitude":-75.08335,"id":"ade12ry2mhr4","column_2":"357C","column_3":"Rt 130, 0.3 Miles S/O Rts 30, 38 &amp; 70"},"type":"Feature","geometry":{"type":"Point","coordinates":[-75.08335,39.92941]}},{"properties":{"column_5":"ClearChannel","latitude":39.7685,"column_6":"14'x48'","creative":"C","column_1":1,"longitude":-75.5344,"id":"ade12sau17pp","column_2":"20438","column_3":"I-95 ES 0.3mi N/O US 202 Concord Pk F/S - 1"},"type":"Feature","geometry":{"type":"Point","coordinates":[-75.5344,39.7685]}},{"properties":{"column_5":"ClearChannel","latitude":39.9982,"column_6":"14'x48'","creative":"C","column_1":1,"longitude":-75.2324,"id":"ade12s35pm5w","column_2":"10431","column_3":"US 1 City Av SS 150ft W/O 51st St F/E - 1"},"type":"Feature","geometry":{"type":"Point","coordinates":[-75.2324,39.9982]}},{"properties":{"column_5":"Lamar","latitude":40.0474,"column_6":"10' 6\" x 22' 9\"","creative":"C","column_1":1,"longitude":-76.3931,"id":"ade12saoqxsf","column_2":"25022","column_3":"CENTERVILLE RD S/O US 30 F/N"},"type":"Feature","geometry":{"type":"Point","coordinates":[-76.3931,40.0474]}},{"properties":{"column_5":"Lamar","latitude":40.0298,"column_6":"10' 6\" x 22' 9\"","creative":"C","column_1":1,"longitude":-76.7458,"id":"ade12rxvd3cj","column_2":"22072","column_3":"83N 2.5M N/ NGEORGE N/ EMGVILLE WS #4 FN"},"type":"Feature","geometry":{"type":"Point","coordinates":[-76.7458,40.0298]}},{"properties":{"column_5":"Lamar","latitude":40.83,"column_6":"14'x48'","creative":"C","column_1":1,"longitude":-75.2978,"id":"ade12rxsxn1c","column_2":"60243","column_3":"RT. 33 .4 MILES S/O RT 512 @ MM 15 E/S"},"type":"Feature","geometry":{"type":"Point","coordinates":[-75.2978,40.83]}},{"properties":{"column_5":"CBS","latitude":40.841799,"column_6":"14'x48'","creative":"C","column_1":1,"longitude":-74.081543,"id":"ade12s63vviu","column_2":"287","column_3":"E/S Rt 17 S/O Moonachie Rd   Wood-Ridge F/N"},"type":"Feature","geometry":{"type":"Point","coordinates":[-74.081543,40.841799]}},{"properties":{"column_5":"CBS","latitude":39.885331,"column_6":"10'5x22'8","creative":"C","column_1":1,"longitude":-74.162854,"id":"ade12s6rtvlw","column_2":"5085","column_3":"E/S Rt 9 @  Serpentine Dr   Berkeley Twp F/N"},"type":"Feature","geometry":{"type":"Point","coordinates":[-74.162854,39.885331]}},{"properties":{"column_5":"CBS","latitude":40.42915,"column_6":"10'5x22'8","creative":"C","column_1":1,"longitude":-74.21269,"id":"ade12s0gs8fa","column_2":"6540","column_3":"E/S Rt 35 .10 mi N/O Broadway Keyport F/N"},"type":"Feature","geometry":{"type":"Point","coordinates":[-74.21269,40.42915]}}],"is_temporal":false,"author":{"url":"","metadata":null,"contact_name":null,"contact_address":null,"source":null,"contact_phone":null},"source":"","pagination":{"sort":null,"start":0,"total":10,"limit":1000000},"state":"complete","tags":"","published":"2014-08-16T14:38:42-04:00","id":341590}