{"type":"FeatureCollection","data_type":"Dataset","url_type":null,"permissions":[{"permissions":{"download":true,"view":true},"group_id":"everyone"}],"classification":null,"title":"tadpoles","count":5,"stream_id":342931,"contributor":{"url":"http://geocommons.com/users/69044","name":"tise8"},"data_attributes":null,"calculation_params":null,"icon_link":null,"link":"http://geocommons.com/overlays/342931.json","extent":[151.727,-32.8736,151.749,-32.8633],"geometry_types":["point"],"unique_name":null,"name":"tadpoles","feature_count":5,"description":"","next_feature":null,"is_raster":false,"short_classification":"Y","stats":{},"features":[{"properties":{"name":"Untitled Placemark","id":"adh83mo8e9zo"},"type":"Feature","geometry":{"type":"Point","coordinates":[151.746461089616,-32.8735571385609]}},{"properties":{"name":"Untitled Placemark","id":"adh83mngnz1o"},"type":"Feature","geometry":{"type":"Point","coordinates":[151.731537504507,-32.8654693795107]}},{"properties":{"name":"Untitled Placemark","id":"adh83mh07l51"},"type":"Feature","geometry":{"type":"Point","coordinates":[151.734951835177,-32.8666223949982]}},{"properties":{"name":"Untitled Placemark","id":"adh83mnxvhv6"},"type":"Feature","geometry":{"type":"Point","coordinates":[151.727057909971,-32.8633313132563]}},{"properties":{"name":"Untitled Placemark","id":"adh83mlsycdi"},"type":"Feature","geometry":{"type":"Point","coordinates":[151.749099595809,-32.8668187990665]}}],"is_temporal":false,"author":{"url":"","metadata":"","contact_name":"","contact_address":"","source":"","contact_phone":""},"source":"","pagination":{"sort":null,"start":0,"total":5,"limit":1000000},"state":"complete","tags":"","published":"2014-08-16T16:02:57-04:00","id":342931}