{"type":"FeatureCollection","data_type":"Dataset","url_type":null,"permissions":[{"permissions":{"download":true,"view":true},"group_id":"everyone"}],"classification":null,"title":"head office ilombok.net","count":1,"stream_id":344820,"contributor":{"url":"http://geocommons.com/users/67200","name":"hminandar"},"data_attributes":null,"calculation_params":null,"icon_link":null,"link":"http://geocommons.com/overlays/344820.json","extent":[116.141,-8.58823,116.141,-8.58823],"geometry_types":["point"],"unique_name":null,"name":"head office ilombok.net","feature_count":1,"description":"jl.Peternakan Gg.Mawar No.10, Mayura, Cakranegara, Mataram, Lombok","next_feature":null,"is_raster":false,"short_classification":"Y","stats":{},"features":[{"properties":{"name":"ilombok.net","description":"<a href=\"http://ilombok.net\">http://ilombok.net</a>","id":"adkn2sgk39yg"},"type":"Feature","geometry":{"type":"Point","coordinates":[116.14123504531,-8.58822733837897]}}],"is_temporal":false,"author":{"url":"http://ilombok.net","metadata":"","contact_name":"","contact_address":"","source":"","contact_phone":""},"source":"http://ilombok.net","pagination":{"sort":null,"start":0,"total":1,"limit":1000000},"state":"complete","tags":"","published":"2014-08-16T18:43:40-04:00","id":344820}