{"type":"FeatureCollection","data_type":"Dataset","url_type":null,"permissions":[{"permissions":{"download":true,"view":true},"group_id":"everyone"}],"classification":null,"title":"Book2","count":8,"stream_id":345487,"contributor":{"url":"http://geocommons.com/users/62476","name":"laura.jerzyk"},"data_attributes":null,"calculation_params":null,"icon_link":null,"link":"http://geocommons.com/overlays/345487.json","extent":[-85.6607,41.8128,-83.1508,43.0111],"geometry_types":["point"],"unique_name":null,"name":"Book2","feature_count":8,"description":"","next_feature":null,"is_raster":false,"short_classification":"Y","stats":{},"features":[{"properties":{"system affiliation (ahd master)":"Ascension Health","system zipcode (highest revenue hospital in state)":"48236","geo_score":0.714,"id":"admllxezpcnc","geo_precision":"zip"},"type":"Feature","geometry":{"type":"Point","coordinates":[-83.150823,42.239933]}},{"properties":{"system affiliation (ahd master)":"Henry Ford Health System","system zipcode (highest revenue hospital in state)":"48202","geo_score":0.714,"id":"admllx5236d3","geo_precision":"zip"},"type":"Feature","geometry":{"type":"Point","coordinates":[-83.150823,42.239933]}},{"properties":{"system affiliation (ahd master)":"McLaren Health Care","system zipcode (highest revenue hospital in state)":"48532","geo_score":0.714,"id":"admllxcbsmik","geo_precision":"zip"},"type":"Feature","geometry":{"type":"Point","coordinates":[-83.803045,43.011127]}},{"properties":{"system affiliation (ahd master)":"ProMedica Health System","system zipcode (highest revenue hospital in state)":"49221","geo_score":0.714,"id":"admllx76r4yy","geo_precision":"zip"},"type":"Feature","geometry":{"type":"Point","coordinates":[-84.041056,41.812827]}},{"properties":{"system affiliation (ahd master)":"Sparrow Health System","system zipcode (highest revenue hospital in state)":"48912","geo_score":0.714,"id":"admllxda61pa","geo_precision":"zip"},"type":"Feature","geometry":{"type":"Point","coordinates":[-84.524939,42.740054]}},{"properties":{"system affiliation (ahd master)":"Spectrum Health","system zipcode (highest revenue hospital in state)":"49503","geo_score":0.714,"id":"admllxfrlmk5","geo_precision":"zip"},"type":"Feature","geometry":{"type":"Point","coordinates":[-85.660693,42.956176]}},{"properties":{"system affiliation (ahd master)":"Trinity Health","system zipcode (highest revenue hospital in state)":"48197","geo_score":0.714,"id":"admllxgehvtz","geo_precision":"zip"},"type":"Feature","geometry":{"type":"Point","coordinates":[-83.620494,42.202139]}},{"properties":{"system affiliation (ahd master)":"Vanguard Health System","system zipcode (highest revenue hospital in state)":"48201","geo_score":0.714,"id":"admllx66zf5k","geo_precision":"zip"},"type":"Feature","geometry":{"type":"Point","coordinates":[-83.150823,42.239933]}}],"is_temporal":false,"author":{"url":"","metadata":"","contact_name":"","contact_address":"","source":"","contact_phone":""},"source":"","pagination":{"sort":null,"start":0,"total":8,"limit":1000000},"state":"complete","tags":"","published":"2014-08-16T19:29:24-04:00","id":345487}