{"type":"FeatureCollection","data_type":"Dataset","url_type":null,"permissions":[{"permissions":{"download":true,"view":true},"group_id":"everyone"}],"classification":null,"title":"plots-for-geo","count":1,"stream_id":347948,"contributor":{"url":"http://geocommons.com/users/66985","name":"octmaja"},"data_attributes":null,"calculation_params":null,"icon_link":null,"link":"http://geocommons.com/overlays/347948.json","extent":[2.90039,55.9246,2.90039,55.9246],"geometry_types":["point"],"unique_name":null,"name":"plots-for-geo","feature_count":1,"description":"","next_feature":null,"is_raster":false,"short_classification":"Y","stats":{"latitude":{"max":55.924586,"min":55.924586,"median":55.924586},"longitude":{"max":2.900391,"min":2.900391,"median":2.900391}},"features":[{"properties":{"latitude":55.924586,"trend uk":"<a>a<img src=\"https://dl.dropboxusercontent.com/u/19955579/trend.pdf\" width=\"275\"></a>","uk institutions":"<a>a<img src=\"https://dl.dropboxusercontent.com/u/19955579/indiv.pdf\" width=\"275\"></a>","london institutions":"<a>a<img src=\"https://dl.dropboxusercontent.com/u/19955579/London_indiv.pdf\" width=\"275\"></a>","longitude":2.900391,"id":"adqpeupu8ins"},"type":"Feature","geometry":{"type":"Point","coordinates":[2.900391,55.924586]}}],"is_temporal":false,"author":{"url":"","metadata":null,"contact_name":null,"contact_address":null,"source":null,"contact_phone":null},"source":"","pagination":{"sort":null,"start":0,"total":1,"limit":1000000},"state":"complete","tags":"","published":"2014-08-16T22:28:44-04:00","id":347948}