{"type":"FeatureCollection","data_type":"Dataset","url_type":null,"permissions":[{"permissions":{"download":true,"view":true},"group_id":"everyone"}],"classification":null,"title":"yac3","count":5,"stream_id":351791,"contributor":{"url":"http://geocommons.com/users/70877","name":"Alehop"},"data_attributes":null,"calculation_params":null,"icon_link":null,"link":"http://geocommons.com/overlays/351791.json","extent":[38.2493,-0.805092,39.6782,0.0],"geometry_types":["point"],"unique_name":null,"name":"yac3","feature_count":5,"description":"","next_feature":null,"is_raster":false,"short_classification":"Y","stats":{"x":{"max":39.678226,"variance":0.387608079779701,"mean":38.9051582,"stdev":0.622581785615112,"min":38.249336,"median":38.886757},"y":{"max":-0.0,"variance":0.1141697064403,"mean":-0.4624814,"stdev":0.337890080411219,"min":-0.805092,"median":-0.461855}},"features":[{"properties":{"pas":"Spain","x":38.249336,"y":-0.805092,"ciudad":"Crevillente","id":"adxgsz5fdg2f"},"type":"Feature","geometry":{"type":"Point","coordinates":[38.249336,-0.805092]}},{"properties":{"pas":"Spain","x":39.678226,"y":-0.279679,"ciudad":"Sagunto","id":"adxgszimvbgr"},"type":"Feature","geometry":{"type":"Point","coordinates":[39.678226,-0.279679]}},{"properties":{"pas":"Spain","x":38.886757,"y":-0.0,"ciudad":"Agres","id":"adxgsze9yipv"},"type":"Feature","geometry":{"type":"Point","coordinates":[38.886757,-0.0]}},{"properties":{"pas":"Spain","x":38.347075,"y":-0.765781,"ciudad":"Aspe","id":"adxgszitm4pl"},"type":"Feature","geometry":{"type":"Point","coordinates":[38.347075,-0.765781]}},{"properties":{"pas":"Spain","x":39.364397,"y":-0.461855,"ciudad":"Picapica","id":"adxgsz2dr36l"},"type":"Feature","geometry":{"type":"Point","coordinates":[39.364397,-0.461855]}}],"is_temporal":false,"author":{"url":"","metadata":null,"contact_name":null,"contact_address":null,"source":null,"contact_phone":null},"source":"","pagination":{"sort":null,"start":0,"total":5,"limit":1000000},"state":"complete","tags":"","published":"2014-08-16T16:29:44-04:00","id":351791}