{"type":"FeatureCollection","data_type":"Dataset","url_type":null,"permissions":[{"permissions":{"download":true,"view":true},"group_id":"everyone"}],"classification":null,"title":"Questura.kml","count":1,"stream_id":35187,"contributor":{"url":"http://geocommons.com/users/8612","name":"tderks"},"data_attributes":null,"calculation_params":null,"icon_link":null,"link":"http://geocommons.com/overlays/35187.json","extent":[12.218,45.4686,12.218,45.4686],"geometry_types":["point"],"unique_name":null,"name":"Questura.kml","feature_count":1,"description":"","next_feature":null,"is_raster":false,"short_classification":"Y","stats":{},"features":[{"properties":{"name":"Questura","id":"a69r62zp7x74"},"type":"Feature","geometry":{"type":"Point","coordinates":[12.2180034482454,45.4686436273501]}}],"is_temporal":false,"author":{"url":"","metadata":"","contact_name":"","contact_address":"","source":"","contact_phone":""},"source":"","pagination":{"sort":null,"start":0,"total":1,"limit":1000000},"state":"complete","tags":"","published":"2014-08-10T15:49:44-04:00","id":35187}