{"type":"FeatureCollection","data_type":"Dataset","url_type":null,"permissions":[{"permissions":{"download":true,"edit":true,"view":true},"group_id":59491},{"permissions":{"download":true,"view":true},"group_id":"everyone"}],"classification":null,"title":"SM week37","count":3,"stream_id":352136,"contributor":{"url":"http://geocommons.com/users/38169","name":"blewislao"},"data_attributes":null,"calculation_params":null,"icon_link":null,"link":"http://geocommons.com/overlays/352136.json","extent":[103.643,19.7877,103.645,19.7908],"geometry_types":["point"],"unique_name":null,"name":"SM week37","feature_count":3,"description":"","next_feature":null,"is_raster":false,"short_classification":"Y","stats":{"age":{"max":29.0,"variance":245.903333333333,"mean":11.0333333333333,"stdev":15.6813052177851,"min":0.1,"median":4.0},"lat":{"max":19.790755,"variance":2.72647433333671e-06,"mean":19.7888576666667,"stdev":0.00165120390422767,"min":19.787746,"median":19.788072},"long":{"max":103.645263,"variance":1.80328233332698e-06,"mean":103.644081333333,"stdev":0.00134286348275876,"min":103.642621,"median":103.64436}},"features":[{"properties":{"rx site":"Home","ref no":"SM045","type":"Blood Diarrhea","sex":"F","id":"adygbh89hqo2","lat":19.787746,"age":29.0,"long":103.645263},"type":"Feature","geometry":{"type":"Point","coordinates":[103.645263,19.787746]}},{"properties":{"rx site":"VHV","ref no":"SM048","type":"Watery Diarrhea","sex":"F","id":"adygbgtqzt1j","lat":19.788072,"age":4.0,"long":103.64436},"type":"Feature","geometry":{"type":"Point","coordinates":[103.64436,19.788072]}},{"properties":{"rx site":"VHV","ref no":"SM379","type":"Watery Diarrhea","sex":"M","id":"adygbh2k8qvc","lat":19.790755,"age":0.1,"long":103.642621},"type":"Feature","geometry":{"type":"Point","coordinates":[103.642621,19.790755]}}],"is_temporal":false,"author":{"url":"","metadata":"","contact_name":"","contact_address":"","source":"","contact_phone":""},"source":"","pagination":{"sort":null,"start":0,"total":3,"limit":1000000},"state":"complete","tags":"","published":"2014-08-16T16:58:43-04:00","id":352136}