{"type":"FeatureCollection","data_type":"Dataset","url_type":null,"permissions":[{"permissions":{"download":true,"view":true},"group_id":"everyone"}],"classification":null,"title":"IU_Address","count":2,"stream_id":352340,"contributor":{"url":"http://geocommons.com/users/69622","name":"livingontheedge"},"data_attributes":null,"calculation_params":null,"icon_link":null,"link":"http://geocommons.com/overlays/352340.json","extent":[-99.222446,19.276467,-99.222446,19.276467],"geometry_types":["point"],"unique_name":null,"name":"IU_Address","feature_count":2,"description":"","next_feature":null,"is_raster":false,"short_classification":"Y","stats":{"latitude":{"max":19.276467,"min":19.276467,"median":19.276467},"longitude":{"max":-99.222446,"min":-99.222446,"median":-99.222446}},"features":[{"properties":{"column_4":null,"latitude":19.276467,"longitude":-99.222446,"id":"adymw70ra1p9","column_3":null},"type":"Feature","geometry":{"type":"Point","coordinates":[-99.222446,19.276467]}},{"properties":{"column_4":"","latitude":"?","longitude":"","id":"adymw76bmssy","column_3":""},"type":"Feature","geometry":null}],"is_temporal":false,"author":{"url":"","metadata":null,"contact_name":null,"contact_address":null,"source":null,"contact_phone":null},"source":"","pagination":{"sort":null,"start":0,"total":2,"limit":1000000},"state":"geocoded","tags":"","published":"2014-08-16T17:07:52-04:00","id":352340}