{"type":"FeatureCollection","data_type":"Dataset","url_type":null,"permissions":[{"permissions":{"download":true,"view":true},"group_id":"everyone"}],"classification":null,"title":"OTHER exchange SCA filings 2008 to 2013","count":3,"stream_id":352878,"contributor":{"url":"http://geocommons.com/users/71070","name":"erik_a_hanson"},"data_attributes":null,"calculation_params":null,"icon_link":null,"link":"http://geocommons.com/overlays/352878.json","extent":[-118.242,34.0552,-74.0023,40.7148],"geometry_types":["point"],"unique_name":null,"name":"OTHER exchange SCA filings 2008 to 2013","feature_count":3,"description":"","next_feature":null,"is_raster":false,"short_classification":"Y","stats":{"date":{"max":"2011/04/01 00:00:00 -0400","variance":2.55663184896e+15,"mean":"2009/05/25 08:00:00 -0400","stdev":50563147.1425583,"min":"2008/06/12 00:00:00 -0400","median":"2008/07/01 00:00:00 -0400"}},"features":[{"properties":{"company":"China Intelligent Lighting and Electronics, Inc.","geometry_id":"adzqur35piqy","district court":"California Central District Court","date":{"end_time":"2011/04/02 00:00:00 -0400","original":"4/1/2011","granularity":"day","time":"2011/04/01 00:00:00 -0400"},"exchange":"Other","id":"adzs69632ncb","counter":"California Central District CourtOther","ticker":"CIL"},"type":"Feature","geometry":{"type":"Point","coordinates":[-118.242157,34.055162]}},{"properties":{"company":"European Aeronautic Defence &amp; Space Company (EADS)","geometry_id":"adzqur58sbbr","district court":"New York Southern District Court","date":{"end_time":"2008/06/13 00:00:00 -0400","original":"6/12/2008","granularity":"day","time":"2008/06/12 00:00:00 -0400"},"exchange":"Other","id":"adzs693d09zd","counter":"New York Southern District CourtOther","ticker":"EADS"},"type":"Feature","geometry":{"type":"Point","coordinates":[-74.002275,40.714813]}},{"properties":{"company":"Fimalac, S.A.","geometry_id":"adzqur58sbbr","district court":"New York Southern District Court","date":{"end_time":"2008/07/02 00:00:00 -0400","original":"7/1/2008","granularity":"day","time":"2008/07/01 00:00:00 -0400"},"exchange":"Other","id":"adzs695jk4aq","counter":"New York Southern District CourtOther","ticker":"FIM"},"type":"Feature","geometry":{"type":"Point","coordinates":[-74.002275,40.714813]}}],"is_temporal":true,"author":{"url":"http://securities.stanford.edu","metadata":"http://securities.stanford.edu/filings.html","contact_name":"","contact_address":"","source":" Stanford Securities Class Action Clearinghouse","contact_phone":""},"source":"http://securities.stanford.edu","pagination":{"sort":null,"start":0,"total":3,"limit":1000000},"state":"complete","tags":"","published":"2013-04-30T16:00:00Z","id":352878}