{"type":"FeatureCollection","data_type":"Dataset","url_type":null,"permissions":[{"permissions":{"download":true,"view":true},"group_id":"everyone"}],"classification":null,"title":"AFC East","count":3,"stream_id":352812,"contributor":{"url":"http://geocommons.com/users/71165","name":"pwnobles"},"data_attributes":null,"calculation_params":null,"icon_link":null,"link":"http://geocommons.com/overlays/352812.json","extent":[-80.2388,25.9579,-71.2644,42.0909],"geometry_types":["point"],"unique_name":null,"name":"AFC East","feature_count":3,"description":"","next_feature":null,"is_raster":false,"short_classification":"Y","stats":{"-78.786978":{"max":-71.26435,"variance":21.0701528977724,"mean":-75.1933916666667,"stdev":4.59022362176097,"min":-80.238842,"median":-74.076983},"42.773739":{"max":42.090925,"variance":80.4264202236703,"mean":36.2870126666667,"stdev":8.96807784442521,"min":25.957919,"median":40.812194}},"features":[{"properties":{"bills":"Patriots","-78.786978":-71.26435,"42.773739":42.090925,"id":"adzixkcq3bwo"},"type":"Feature","geometry":{"type":"Point","coordinates":[-71.26435,42.090925]}},{"properties":{"bills":"Dolphins","-78.786978":-80.238842,"42.773739":25.957919,"id":"adzixjxng2ir"},"type":"Feature","geometry":{"type":"Point","coordinates":[-80.238842,25.957919]}},{"properties":{"bills":"Jets","-78.786978":-74.076983,"42.773739":40.812194,"id":"adzixk8scck1"},"type":"Feature","geometry":{"type":"Point","coordinates":[-74.076983,40.812194]}}],"is_temporal":false,"author":{"url":"","metadata":"","contact_name":"","contact_address":"","source":"","contact_phone":""},"source":"","pagination":{"sort":null,"start":0,"total":3,"limit":1000000},"state":"complete","tags":"","published":"2014-08-16T17:46:44-04:00","id":352812}