{"type":"FeatureCollection","data_type":"Dataset","url_type":null,"permissions":[{"permissions":{"download":true,"view":true},"group_id":"everyone"}],"classification":null,"title":"Mason County","count":2,"stream_id":353361,"contributor":{"url":"http://geocommons.com/users/71218","name":"dr194-13ID@redcross.org"},"data_attributes":null,"calculation_params":null,"icon_link":null,"link":"http://geocommons.com/overlays/353361.json","extent":[-89.1441,37.7519,-88.924,37.8307],"geometry_types":["point"],"unique_name":null,"name":"Mason County","feature_count":2,"description":"","next_feature":null,"is_raster":false,"short_classification":"Y","stats":{},"features":[{"properties":{"geo_score":0.371,"id":"ae16hdpruplc","geo_precision":"street","address":"EAST STREET MANTANZAS BEACH IL"},"type":"Feature","geometry":{"type":"Point","coordinates":[-89.144082,37.830687]}},{"properties":{"geo_score":0.405,"id":"ae16hdt00668","geo_precision":"street","address":"12784 N. STATE ROUTE 78 MANTANZAS BEACH IL"},"type":"Feature","geometry":{"type":"Point","coordinates":[-88.924024,37.751951]}}],"is_temporal":false,"author":{"url":"","metadata":"","contact_name":"","contact_address":"","source":"","contact_phone":""},"source":"","pagination":{"sort":null,"start":0,"total":2,"limit":1000000},"state":"complete","tags":"","published":"2014-08-16T18:24:46-04:00","id":353361}