{"type":"FeatureCollection","data_type":"Dataset","url_type":null,"permissions":[{"permissions":{"download":true,"view":true},"group_id":"everyone"}],"classification":null,"title":"Export_Output_point","count":9,"stream_id":36420,"contributor":{"url":"http://geocommons.com/users/12528","name":"goglu"},"data_attributes":null,"calculation_params":null,"icon_link":null,"link":"http://geocommons.com/overlays/36420.json","extent":[-71.6484,48.4716,-71.4769,48.5201],"geometry_types":["point"],"unique_name":null,"name":"Export_Output_point","feature_count":9,"description":"Test pour finder","next_feature":null,"is_raster":false,"short_classification":"Y","stats":{"MAX_NO_N_1":{"max":3.0,"mean":2.44444444444444,"variance":0.277777777777778,"stdev":0.52704627669473,"min":2.0,"median":2.0},"MIN_NO_NIV":{"max":4.0,"mean":2.55555555555556,"variance":0.527777777777778,"stdev":0.726483157256779,"min":2.0,"median":2.0},"VA_QUALT_1":{"max":1200,"mean":988.888888888889,"variance":41111.1111111111,"stdev":202.758751009941,"min":800,"median":900},"OBJECTID_1":{"max":1520,"mean":1031.55555555556,"variance":219907.277777778,"stdev":468.942723344523,"min":29,"median":1080},"MAX_NO_NIV":{"max":4.0,"mean":2.55555555555556,"variance":0.527777777777778,"stdev":0.726483157256779,"min":2.0,"median":2.0},"OBJECTID":{"max":1520,"mean":1053.55555555556,"variance":211221.777777778,"stdev":459.588705015449,"min":29,"median":1052}},"features":[{"properties":{"MAX_NO_N_1":2.0,"CO_CLE_DOC":"CA44129177","MIN_NO_NIV":2.0,"VA_QUALT_1":1200,"OBJECTID_1":29,"MAX_NO_NIV":2.0,"OBJECTID":29,"id":"a66n2nvxwr12"},"type":"Feature","geometry":{"type":"Point","coordinates":[-71.476875970334,48.507019291227]}},{"properties":{"MAX_NO_N_1":2.0,"CO_CLE_DOC":"CA1412####259","MIN_NO_NIV":2.0,"VA_QUALT_1":800,"OBJECTID_1":732,"MAX_NO_NIV":2.0,"OBJECTID":732,"id":"a66n2o4ubw07"},"type":"Feature","geometry":{"type":"Point","coordinates":[-71.6480880289709,48.5200915216769]}},{"properties":{"MAX_NO_N_1":2.0,"CO_CLE_DOC":"CA44129464","MIN_NO_NIV":2.0,"VA_QUALT_1":800,"OBJECTID_1":784,"MAX_NO_NIV":2.0,"OBJECTID":1052,"id":"a66n2nwdj622"},"type":"Feature","geometry":{"type":"Point","coordinates":[-71.6483571785407,48.5201342307655]}},{"properties":{"MAX_NO_N_1":2.0,"CO_CLE_DOC":"CA44129266","MIN_NO_NIV":2.0,"VA_QUALT_1":800,"OBJECTID_1":1079,"MAX_NO_NIV":2.0,"OBJECTID":1044,"id":"a66n2o0clvlq"},"type":"Feature","geometry":{"type":"Point","coordinates":[-71.6483233623263,48.5201294433747]}},{"properties":{"MAX_NO_N_1":2.0,"CO_CLE_DOC":"CA44129311","MIN_NO_NIV":2.0,"VA_QUALT_1":800,"OBJECTID_1":1080,"MAX_NO_NIV":2.0,"OBJECTID":1045,"id":"a66n2o0qrqrv"},"type":"Feature","geometry":{"type":"Point","coordinates":[-71.6483571785407,48.5201342307655]}},{"properties":{"MAX_NO_N_1":3.0,"CO_CLE_DOC":"CA10L001##24","MIN_NO_NIV":4.0,"VA_QUALT_1":900,"OBJECTID_1":1172,"MAX_NO_NIV":4.0,"OBJECTID":1172,"id":"a66n2o1t4svr"},"type":"Feature","geometry":{"type":"Point","coordinates":[-71.549171134885,48.477469373844]}},{"properties":{"MAX_NO_N_1":3.0,"CO_CLE_DOC":"CA10L001##10","MIN_NO_NIV":3.0,"VA_QUALT_1":1200,"OBJECTID_1":1443,"MAX_NO_NIV":3.0,"OBJECTID":1443,"id":"a66n2o44atga"},"type":"Feature","geometry":{"type":"Point","coordinates":[-71.5287687432389,48.471638187918]}},{"properties":{"MAX_NO_N_1":3.0,"CO_CLE_DOC":"CA10L001##21","MIN_NO_NIV":3.0,"VA_QUALT_1":1200,"OBJECTID_1":1445,"MAX_NO_NIV":3.0,"OBJECTID":1445,"id":"a66n2o0kr3e0"},"type":"Feature","geometry":{"type":"Point","coordinates":[-71.5576748473252,48.4783774294982]}},{"properties":{"MAX_NO_N_1":3.0,"CO_CLE_DOC":"CA20L001##17","MIN_NO_NIV":3.0,"VA_QUALT_1":1200,"OBJECTID_1":1520,"MAX_NO_NIV":3.0,"OBJECTID":1520,"id":"a66n2o66vftv"},"type":"Feature","geometry":{"type":"Point","coordinates":[-71.631339734405,48.5000468311723]}}],"is_temporal":false,"author":{"url":"","metadata":"","contact_name":"","contact_address":"","source":"","contact_phone":""},"source":"","pagination":{"sort":null,"start":0,"total":9,"limit":1000000},"state":"complete","tags":"test_ged_point","published":"2010-04-08T14:11:43Z","id":36420}