{"type":"FeatureCollection","data_type":"Dataset","url_type":null,"permissions":[{"permissions":{"download":true,"view":true},"group_id":"everyone"}],"classification":null,"title":"Hotel_casa_de_shows","count":21,"stream_id":366010,"contributor":{"url":"http://geocommons.com/users/41748","name":"pvista2010"},"data_attributes":null,"calculation_params":null,"icon_link":null,"link":"http://geocommons.com/overlays/366010.json","extent":[-46.68,-23.5619,-46.6123,-23.4985],"geometry_types":["point"],"unique_name":null,"name":"Hotel_casa_de_shows","feature_count":21,"description":"","next_feature":null,"is_raster":false,"short_classification":"Y","stats":{},"features":[{"properties":{"description":"Ibis Styles","id":"aexzz6j89bqf"},"type":"Feature","geometry":{"type":"Point","coordinates":[-46.6737825056185,-23.5198362139707]}},{"properties":{"description":"Holiday Inn Parque Anhembi","id":"aexzz69yokka"},"type":"Feature","geometry":{"type":"Point","coordinates":[-46.639178003553,-23.5163999999952]}},{"properties":{"description":"Novotel Jaraguá São Paulo Conventions","id":"aexzz6g4b9xn"},"type":"Feature","geometry":{"type":"Point","coordinates":[-46.6432152976661,-23.5484424908604]}},{"properties":{"description":"Marabá Palace","id":"aexzz6itzy4e"},"type":"Feature","geometry":{"type":"Point","coordinates":[-46.640997,-23.542713]}},{"properties":{"description":"Tryp São Paulo Higienópolis","id":"aexzz6hendog"},"type":"Feature","geometry":{"type":"Point","coordinates":[-46.6559459156967,-23.545057474564]}},{"properties":{"description":"Novotel Center Norte","id":"aexzz6cclnel"},"type":"Feature","geometry":{"type":"Point","coordinates":[-46.620678,-23.511846]}},{"properties":{"description":"Mercure Nortel","id":"aexzz6j7j5lz"},"type":"Feature","geometry":{"type":"Point","coordinates":[-46.612306614766,-23.498498248995]}},{"properties":{"description":"Plaza Inn American Loft","id":"aexzz6fuibvn"},"type":"Feature","geometry":{"type":"Point","coordinates":[-46.6800166416459,-23.5282505281306]}},{"properties":{"description":"Luz Plaza","id":"aexzz66jwgct"},"type":"Feature","geometry":{"type":"Point","coordinates":[-46.637204674211,-23.5328333656674]}},{"properties":{"description":"Holiday Inn Express","id":"aexzz66g2ha9"},"type":"Feature","geometry":{"type":"Point","coordinates":[-46.6749603035868,-23.5325605139117]}},{"properties":{"description":"Bourbon Business","id":"aexzz6j0mtlo"},"type":"Feature","geometry":{"type":"Point","coordinates":[-46.6437443416377,-23.5421848092562]}},{"properties":{"description":"Comfort Downtown","id":"aexzz6i8asmr"},"type":"Feature","geometry":{"type":"Point","coordinates":[-46.6446254500401,-23.5453766256379]}},{"properties":{"description":"Hotel Ibis","id":"aexzz63fo96t"},"type":"Feature","geometry":{"type":"Point","coordinates":[-46.6549238378731,-23.519193163138]}},{"properties":{"description":"Higienópolis Convention","id":"aexzz6f968wo"},"type":"Feature","geometry":{"type":"Point","coordinates":[-46.6542931742796,-23.5357034513183]}},{"properties":{"description":"Brasilia Santana Gold Flat","id":"aexzz6iuz4rf"},"type":"Feature","geometry":{"type":"Point","coordinates":[-46.6240568270027,-23.5001218372055]}},{"properties":{"description":"Dan Inn Planalto","id":"aexzz69h1pm9"},"type":"Feature","geometry":{"type":"Point","coordinates":[-46.6365925663374,-23.5405263865414]}},{"properties":{"description":"Ibis Budget Centro","id":"aexzz6dzdczk"},"type":"Feature","geometry":{"type":"Point","coordinates":[-46.644363813155,-23.5397869893805]}},{"properties":{"description":"Adagio","id":"aexzz6757bxu"},"type":"Feature","geometry":{"type":"Point","coordinates":[-46.6630004563265,-23.5291820089903]}},{"properties":{"description":"Ibis Budget","id":"aexzz6ejko3i"},"type":"Feature","geometry":{"type":"Point","coordinates":[-46.6549929017605,-23.5546549771646]}},{"properties":{"description":"Ca´d´Oro","id":"aexzz6jnwvkv"},"type":"Feature","geometry":{"type":"Point","coordinates":[-46.6483400009564,-23.5504797053306]}},{"properties":{"description":"2 Hotéis","id":"aexzz6ez1lek"},"type":"Feature","geometry":{"type":"Point","coordinates":[-46.6539838399552,-23.5618982745169]}}],"is_temporal":false,"author":{"url":"","metadata":null,"contact_name":null,"contact_address":null,"source":null,"contact_phone":null},"source":"","pagination":{"sort":null,"start":0,"total":21,"limit":1000000},"state":"complete","tags":"","published":"2014-08-16T21:17:12-04:00","id":366010}