{"type":"FeatureCollection","data_type":"Dataset","url_type":null,"permissions":[{"permissions":{"download":true,"view":true},"group_id":"everyone"}],"classification":null,"title":"Brasília","count":1,"stream_id":366196,"contributor":{"url":"http://geocommons.com/users/41748","name":"pvista2010"},"data_attributes":null,"calculation_params":null,"icon_link":null,"link":"http://geocommons.com/overlays/366196.json","extent":[-47.9283,-15.781,-47.9283,-15.781],"geometry_types":["point"],"unique_name":null,"name":"Brasília","feature_count":1,"description":"","next_feature":null,"is_raster":false,"short_classification":"Y","stats":{},"features":[{"properties":{"description":"Brasília","id":"aeyeiiywd4jj"},"type":"Feature","geometry":{"type":"Point","coordinates":[-47.9283390578982,-15.7810187437488]}}],"is_temporal":false,"author":{"url":"","metadata":null,"contact_name":null,"contact_address":null,"source":null,"contact_phone":null},"source":"","pagination":{"sort":null,"start":0,"total":1,"limit":1000000},"state":"complete","tags":"","published":"2014-08-16T21:29:57-04:00","id":366196}