{"type":"FeatureCollection","data_type":"Dataset","url_type":null,"permissions":[{"permissions":{"download":true,"view":true},"group_id":"everyone"}],"classification":null,"title":"Luçay-le-Mâle","count":1,"stream_id":366757,"contributor":{"url":"http://geocommons.com/users/42827","name":"jflacou"},"data_attributes":null,"calculation_params":null,"icon_link":null,"link":"http://geocommons.com/overlays/366757.json","extent":[1.43944,47.1322,1.43944,47.1322],"geometry_types":["point"],"unique_name":null,"name":"Luçay-le-Mâle","feature_count":1,"description":"","next_feature":null,"is_raster":false,"short_classification":"Y","stats":{},"features":[{"properties":{"name":"Le Petit Théâtre des Forges","Telephone":"02 54 40 48 90","Adresse":"25 rue de la Gare","id":"aezndttbyuqs","GPS":"1.43944 - 47.13222"},"type":"Feature","geometry":{"type":"Point","coordinates":[1.43944,47.13222]}}],"is_temporal":false,"author":{"url":"","metadata":"","contact_name":"","contact_address":"","source":"","contact_phone":""},"source":"","pagination":{"sort":null,"start":0,"total":1,"limit":1000000},"state":"complete","tags":"","published":"2014-08-16T22:17:27-04:00","id":366757}