{"type":"FeatureCollection","data_type":"Dataset","url_type":null,"permissions":[{"permissions":{"download":true,"view":true},"group_id":"everyone"}],"classification":null,"title":"737-700 Rons-Rads","count":3,"stream_id":368271,"contributor":{"url":"http://geocommons.com/users/38310","name":"Dlforecastdemand"},"data_attributes":null,"calculation_params":null,"icon_link":null,"link":"http://geocommons.com/overlays/368271.json","extent":[-84.4281,32.8986,-74.1687,40.6925],"geometry_types":["point"],"unique_name":null,"name":"737-700 Rons-Rads","feature_count":3,"description":"","next_feature":null,"is_raster":false,"short_classification":"Y","stats":{"latitude":{"max":40.69250107,"variance":18.5123320289619,"mean":35.74260076,"stdev":4.30259596394571,"median":33.63669968,"min":32.89860153},"rons rads":{"max":62,"variance":324.333333333333,"mean":41.3333333333333,"stdev":18.0092568789868,"median":33,"min":29},"longitude":{"max":-74.16870117,"variance":26.4973879144429,"mean":-79.5457661966667,"stdev":5.14756135606394,"median":-80.04049683,"min":-84.42810059}},"features":[{"properties":{"latitude":33.63669968,"airport code":"ATL","rons rads":33,"longitude":-84.42810059,"id":"af48ygn33rk7"},"type":"Feature","geometry":{"type":"Point","coordinates":[-84.42810059,33.63669968]}},{"properties":{"latitude":32.89860153,"airport code":"CHS","rons rads":62,"longitude":-80.04049683,"id":"af48yglqlcs6"},"type":"Feature","geometry":{"type":"Point","coordinates":[-80.04049683,32.89860153]}},{"properties":{"latitude":40.69250107,"airport code":"EWR","rons rads":29,"longitude":-74.16870117,"id":"af48ygspbhq4"},"type":"Feature","geometry":{"type":"Point","coordinates":[-74.16870117,40.69250107]}}],"is_temporal":false,"author":{"url":"","metadata":"","contact_name":"","contact_address":"","source":"","contact_phone":""},"source":"","pagination":{"sort":null,"start":0,"total":3,"limit":1000000},"state":"complete","tags":"","published":"2014-08-16T23:57:13-04:00","id":368271}