{"type":"FeatureCollection","data_type":"Dataset","url_type":null,"permissions":[{"permissions":{"download":true,"view":true},"group_id":"everyone"}],"classification":null,"title":"Herb Chambers Sold into Gallery Norwood","count":15,"stream_id":368904,"contributor":{"url":"http://geocommons.com/users/62916","name":"alexkim"},"data_attributes":null,"calculation_params":null,"icon_link":null,"link":"http://geocommons.com/overlays/368904.json","extent":[-71.4292,42.0232,-70.6828,42.2798],"geometry_types":["point"],"unique_name":null,"name":"Herb Chambers Sold into Gallery Norwood","feature_count":15,"description":"","next_feature":null,"is_raster":false,"short_classification":"Y","stats":{"# sold":{"max":25,"variance":33.7809523809524,"mean":6.93333333333333,"stdev":5.81213836560628,"median":5,"min":1}},"features":[{"properties":{"geo_score":0.714,"zip code":"02067","id":"af57m7l2xjas","geo_precision":"zip","# sold":3},"type":"Feature","geometry":{"type":"Point","coordinates":[-71.184785,42.105288]}},{"properties":{"geo_score":0.714,"zip code":"02061","id":"af57m7raw733","geo_precision":"zip","# sold":4},"type":"Feature","geometry":{"type":"Point","coordinates":[-70.823035,42.154145]}},{"properties":{"geo_score":0.714,"zip code":"02043","id":"af57m7nb1ksy","geo_precision":"zip","# sold":7},"type":"Feature","geometry":{"type":"Point","coordinates":[-70.902823,42.2376]}},{"properties":{"geo_score":0.714,"zip code":"02492","id":"af57m7y1xfar","geo_precision":"zip","# sold":11},"type":"Feature","geometry":{"type":"Point","coordinates":[-71.25006,42.279797]}},{"properties":{"geo_score":0.714,"zip code":"02169","id":"af57m7saahyu","geo_precision":"zip","# sold":25},"type":"Feature","geometry":{"type":"Point","coordinates":[-70.961992,42.262322]}},{"properties":{"geo_score":0.714,"zip code":"02332","id":"af57m7xs2zld","geo_precision":"zip","# sold":5},"type":"Feature","geometry":{"type":"Point","coordinates":[-70.682815,42.023159]}},{"properties":{"geo_score":0.714,"zip code":"02184","id":"af57m7om9z18","geo_precision":"zip","# sold":8},"type":"Feature","geometry":{"type":"Point","coordinates":[-70.974492,42.2251]}},{"properties":{"geo_score":0.714,"zip code":"02186","id":"af57m7lza7b5","geo_precision":"zip","# sold":10},"type":"Feature","geometry":{"type":"Point","coordinates":[-71.080051,42.254266]}},{"properties":{"geo_score":0.714,"zip code":"02025","id":"af57m7qowsz9","geo_precision":"zip","# sold":4},"type":"Feature","geometry":{"type":"Point","coordinates":[-70.828655,42.243712]}},{"properties":{"geo_score":0.714,"zip code":"02021","id":"af57m7jn0xbh","geo_precision":"zip","# sold":7},"type":"Feature","geometry":{"type":"Point","coordinates":[-71.121185,42.179146]}},{"properties":{"geo_score":0.714,"zip code":"02038","id":"af57m7sd5ey9","geo_precision":"zip","# sold":1},"type":"Feature","geometry":{"type":"Point","coordinates":[-71.429226,42.102875]}},{"properties":{"geo_score":0.714,"zip code":"02052","id":"af57m7p3wd6e","geo_precision":"zip","# sold":2},"type":"Feature","geometry":{"type":"Point","coordinates":[-71.309934,42.181265]}},{"properties":{"geo_score":0.714,"zip code":"02030","id":"af57m7tdu4fl","geo_precision":"zip","# sold":9},"type":"Feature","geometry":{"type":"Point","coordinates":[-71.321447,42.245931]}},{"properties":{"geo_score":0.714,"zip code":"02066","id":"af57m7z4ylpd","geo_precision":"zip","# sold":3},"type":"Feature","geometry":{"type":"Point","coordinates":[-70.717818,42.191768]}},{"properties":{"geo_score":0.714,"zip code":"02090","id":"af57m7kunoom","geo_precision":"zip","# sold":5},"type":"Feature","geometry":{"type":"Point","coordinates":[-71.199238,42.220548]}}],"is_temporal":false,"author":{"url":"","metadata":"","contact_name":"","contact_address":"","source":"","contact_phone":""},"source":"","pagination":{"sort":null,"start":0,"total":15,"limit":1000000},"state":"complete","tags":"","published":"2014-08-17T00:44:24-04:00","id":368904}