{"type":"FeatureCollection","data_type":"Dataset","url_type":null,"permissions":[{"permissions":{"download":true,"view":true},"group_id":"everyone"}],"classification":null,"title":"zipcode","count":4,"stream_id":37054,"contributor":{"url":"http://geocommons.com/users/139","name":"Burkey"},"data_attributes":null,"calculation_params":null,"icon_link":null,"link":"http://geocommons.com/overlays/37054.json","extent":[-77.4047,38.8398,-77.0991,39.0807],"geometry_types":["point"],"unique_name":null,"name":"zipcode","feature_count":4,"description":"","next_feature":null,"is_raster":false,"short_classification":"Y","stats":{"geo_score":{"max":0.714,"mean":0.714,"variance":0.0,"stdev":0.0,"min":0.714,"median":0.714},"value":{"max":7,"mean":5.5,"variance":1.66666666666667,"stdev":1.29099444873581,"min":4,"median":6}},"features":[{"properties":{"zip":"20850","geo_score":0.714,"value":6,"id":"a6kb3stvlwt5","geo_precision":"zip"},"type":"Feature","geometry":{"type":"Point","coordinates":[-77.204425,39.080664]}},{"properties":{"zip":"20852","geo_score":0.714,"value":5,"id":"a6kb3t405zda","geo_precision":"zip"},"type":"Feature","geometry":{"type":"Point","coordinates":[-77.108034,39.037331]}},{"properties":{"zip":"22030","geo_score":0.714,"value":4,"id":"a6kb3sqt73cg","geo_precision":"zip"},"type":"Feature","geometry":{"type":"Point","coordinates":[-77.40471,38.839835]}},{"properties":{"zip":"22201","geo_score":0.714,"value":7,"id":"a6kb3t62yq7x","geo_precision":"zip"},"type":"Feature","geometry":{"type":"Point","coordinates":[-77.099113,38.885484]}}],"is_temporal":false,"author":{"url":"","metadata":"","contact_name":"","contact_address":"","source":"","contact_phone":""},"source":"","pagination":{"sort":null,"start":0,"total":4,"limit":1000000},"state":"complete","tags":"","published":"2014-08-10T17:48:10-04:00","id":37054}