{"type":"FeatureCollection","data_type":"Dataset","url_type":null,"permissions":[{"permissions":{"download":true,"view":true},"group_id":"everyone"}],"classification":null,"title":"katipuneros","count":3,"stream_id":37157,"contributor":{"url":"http://geocommons.com/users/12696","name":"katipuneros"},"data_attributes":null,"calculation_params":null,"icon_link":null,"link":"http://geocommons.com/overlays/37157.json","extent":[121.018,14.6405,121.065,14.6692],"geometry_types":["point"],"unique_name":null,"name":"katipuneros","feature_count":3,"description":"","next_feature":null,"is_raster":false,"short_classification":"Y","stats":{"latitude":{"max":14.6692,"mean":14.657738,"variance":0.000230116923999983,"stdev":0.0151696052684301,"min":14.640536,"median":14.663478},"longitude":{"max":121.065367,"mean":121.043557666667,"variance":0.00055971227433323,"stdev":0.0236582390370296,"min":121.018406,"median":121.0469}},"features":[{"properties":{"name":"San Pedro Bautista Church","latitude":14.640536,"description":"Second oldest church in the Philippines","link":"http://wikimapia.org/288963/Santuario-de-San-Pedro-Bautista-Parish-Church-Shrine","longitude":121.018406,"id":"a6cac02gv78i"},"type":"Feature","geometry":{"type":"Point","coordinates":[121.018406,14.640536]}},{"properties":{"name":"Iglesia ni Kristo","latitude":14.663478,"description":"Central temple of Iglesia","link":"http://www.panoramio.com/photo/1284025","longitude":121.065367,"id":"a6cac052pl09"},"type":"Feature","geometry":{"type":"Point","coordinates":[121.065367,14.663478]}},{"properties":{"name":"Sto. Domingo Church","latitude":14.6692,"description":"Our Lady  of La Naval","link":"http://photos-863.friendster.com/e1/photos/36/88/42018863/1_992565393l.jpg","longitude":121.0469,"id":"a6cac02w5t46"},"type":"Feature","geometry":{"type":"Point","coordinates":[121.0469,14.6692]}}],"is_temporal":false,"author":{"url":"","metadata":"","contact_name":"","contact_address":"","source":"","contact_phone":""},"source":"","pagination":{"sort":null,"start":0,"total":3,"limit":1000000},"state":"complete","tags":"ncca_cultural_mapping_course","published":"2014-08-10T17:53:03-04:00","id":37157}