{"type":"FeatureCollection","data_type":"Data Feed","url_type":"csv","permissions":[{"permissions":{"download":true,"view":true},"group_id":"everyone"}],"classification":null,"title":"Pollinate Test","count":5,"stream_id":372308,"contributor":{"url":"http://geocommons.com/users/69494","name":"pollinateenergy"},"data_attributes":null,"calculation_params":null,"icon_link":null,"link":"http://geocommons.com/overlays/372308.json","extent":[77.6367,13.0307,77.6388,13.0327],"geometry_types":["point"],"unique_name":null,"name":"Pollinate Test","feature_count":5,"description":"","next_feature":null,"is_raster":false,"short_classification":"Y","stats":{"opportunity":{"max":0.6,"mean":0.49,"variance":0.022,"stdev":0.148323969741913,"median":0.54,"min":0.23},"latitude":{"max":13.0326999,"mean":13.0318339,"variance":5.63462094999947e-07,"stdev":0.000750641122641137,"median":13.0319384,"min":13.0306656},"estimated size":{"max":300,"mean":158.6,"variance":10807.8,"stdev":103.960569448229,"median":126,"min":48},"longitude":{"max":77.6387832,"mean":77.6377049,"variance":7.96601534995672e-07,"stdev":0.000892525369384911,"median":77.6376999,"min":77.6366667},"systems sold":{"max":25,"mean":13.8,"variance":54.7,"stdev":7.39594483484024,"median":14,"min":5}},"features":[{"properties":{"opportunity":0.23,"latitude":13.0306656,"estimated size":300,"longitude":77.6366667,"id":"afblmjj1svut","systems sold":14,"community":"Elephant"},"type":"Feature","geometry":{"type":"Point","coordinates":[77.6366667,13.0306656]}},{"properties":{"opportunity":0.52,"latitude":13.0316999,"estimated size":48,"longitude":77.6376999,"id":"afblmjq78vfh","systems sold":5,"community":"Tiger"},"type":"Feature","geometry":{"type":"Point","coordinates":[77.6376999,13.0316999]}},{"properties":{"opportunity":0.6,"latitude":13.0326999,"estimated size":126,"longitude":77.6387832,"id":"afblmjjql67o","systems sold":15,"community":"Hippo"},"type":"Feature","geometry":{"type":"Point","coordinates":[77.6387832,13.0326999]}},{"properties":{"opportunity":0.56,"latitude":13.0321657,"estimated size":89,"longitude":77.6369999,"id":"afblmjfi1gsz","systems sold":10,"community":"Shark"},"type":"Feature","geometry":{"type":"Point","coordinates":[77.6369999,13.0321657]}},{"properties":{"opportunity":0.54,"latitude":13.0319384,"estimated size":230,"longitude":77.6383748,"id":"afblmjk7glib","systems sold":25,"community":"Ferret"},"type":"Feature","geometry":{"type":"Point","coordinates":[77.6383748,13.0319384]}},{"properties":{"opportunity":0.5,"latitude":13.0619355,"estimated size":100,"longitude":77.6383755,"id":"afblmjrekpou","systems sold":10,"community":"Whale"},"type":"Feature","geometry":{"type":"Point","coordinates":[77.6383755,13.0619355]}},{"properties":{"opportunity":1.0,"latitude":13.0411111,"estimated size":5,"longitude":77.6381111,"id":"afblmjmuju4k","systems sold":1,"community":"Bear"},"type":"Feature","geometry":{"type":"Point","coordinates":[77.6381111,13.0411111]}}],"is_temporal":false,"author":{"url":"","metadata":"","contact_name":"","contact_address":"","source":"","contact_phone":""},"source":"","pagination":{"sort":null,"start":0,"total":5,"limit":1000000},"state":"complete","tags":"","published":"2014-08-16T16:39:44-04:00","id":372308}