{"type":"FeatureCollection","data_type":"Dataset","url_type":null,"permissions":[{"permissions":{"download":true,"view":true},"group_id":"everyone"}],"classification":null,"title":"Yemen ports test 2","count":29,"stream_id":377429,"contributor":{"url":"http://geocommons.com/users/76494","name":"Alli15"},"data_attributes":null,"calculation_params":null,"icon_link":null,"link":"http://geocommons.com/overlays/377429.json","extent":[42.3833,12.1172,55.074,25.009],"geometry_types":["point"],"unique_name":null,"name":"Yemen ports test 2","feature_count":29,"description":"","next_feature":null,"is_raster":false,"short_classification":"Y","stats":{},"features":[{"properties":{"id":"afs4te5bxjo1"},"type":"Feature","geometry":{"type":"Point","coordinates":[52.1823,16.21079]}},{"properties":{"id":"afs4te0gjxj1"},"type":"Feature","geometry":{"type":"Point","coordinates":[43.41269,12.94223]}},{"properties":{"id":"afs4te0s39sk"},"type":"Feature","geometry":{"type":"Point","coordinates":[42.95111,14.80222]}},{"properties":{"id":"afs4te5ozi59"},"type":"Feature","geometry":{"type":"Point","coordinates":[42.8146,16.32253]}},{"properties":{"id":"afs4te3k4rx6"},"type":"Feature","geometry":{"type":"Point","coordinates":[42.8146,16.32253]}},{"properties":{"id":"afs4te2comou"},"type":"Feature","geometry":{"type":"Point","coordinates":[43.250556,13.806667]}},{"properties":{"id":"afs4tebq31aa"},"type":"Feature","geometry":{"type":"Point","coordinates":[45.03333,12.8]}},{"properties":{"id":"afs4te4qefzd"},"type":"Feature","geometry":{"type":"Point","coordinates":[43.41269,12.94223]}},{"properties":{"id":"afs4te5g3y2m"},"type":"Feature","geometry":{"type":"Point","coordinates":[42.3833,16.2536]}},{"properties":{"id":"afs4tdzvugey"},"type":"Feature","geometry":{"type":"Point","coordinates":[53.82374,12.46342]}},{"properties":{"id":"afs4te91fjdh"},"type":"Feature","geometry":{"type":"Point","coordinates":[55.07397,25.00901]}},{"properties":{"id":"afs4te8r6e2l"},"type":"Feature","geometry":{"type":"Point","coordinates":[42.4018,15.1859]}},{"properties":{"id":"afs4tdzfko24"},"type":"Feature","geometry":{"type":"Point","coordinates":[42.95111,14.80222]}},{"properties":{"id":"afs4te74yvge"},"type":"Feature","geometry":{"type":"Point","coordinates":[42.95111,14.80222]}},{"properties":{"id":"afs4te6efr26"},"type":"Feature","geometry":{"type":"Point","coordinates":[44.21972,15.47917]}},{"properties":{"id":"afs4te23q7yg"},"type":"Feature","geometry":{"type":"Point","coordinates":[45.03333,12.8]}},{"properties":{"id":"afs4te7hphbp"},"type":"Feature","geometry":{"type":"Point","coordinates":[45.03333,12.8]}},{"properties":{"id":"afs4te4w6lbx"},"type":"Feature","geometry":{"type":"Point","coordinates":[42.95111,14.80222]}},{"properties":{"id":"afs4te5yu7km"},"type":"Feature","geometry":{"type":"Point","coordinates":[42.95111,14.80222]}},{"properties":{"id":"afs4tdvyy9g1"},"type":"Feature","geometry":{"type":"Point","coordinates":[45.03333,12.8]}},{"properties":{"id":"afs4te0171n2"},"type":"Feature","geometry":{"type":"Point","coordinates":[49.15059,14.52123]}},{"properties":{"id":"afs4te3nh82w"},"type":"Feature","geometry":{"type":"Point","coordinates":[52.1823,16.21079]}},{"properties":{"id":"afs4te1yvff2"},"type":"Feature","geometry":{"type":"Point","coordinates":[45.03333,12.8]}},{"properties":{"id":"afs4te3cx0cb"},"type":"Feature","geometry":{"type":"Point","coordinates":[53.28002,12.11718]}},{"properties":{"id":"afs4teaq8o3i"},"type":"Feature","geometry":{"type":"Point","coordinates":[42.95111,14.80222]}},{"properties":{"id":"afs4tdvp84sq"},"type":"Feature","geometry":{"type":"Point","coordinates":[43.25,13.31667]}},{"properties":{"id":"afs4te5khal1"},"type":"Feature","geometry":{"type":"Point","coordinates":[44.02194,13.57889]}},{"properties":{"id":"afs4tdwqlw43"},"type":"Feature","geometry":{"type":"Point","coordinates":[48.57815,15.90708]}},{"properties":{"id":"afs4tdzi3vfz"},"type":"Feature","geometry":{"type":"Point","coordinates":[42.76623,14.01939]}}],"is_temporal":false,"author":{"url":"","metadata":"","contact_name":"","contact_address":"","source":"","contact_phone":""},"source":"","pagination":{"sort":null,"start":0,"total":29,"limit":1000000},"state":"complete","tags":"","published":"2014-08-16T23:40:05-04:00","id":377429}