{"type":"FeatureCollection","data_type":"Dataset","url_type":null,"permissions":[{"permissions":{"download":true,"view":true},"group_id":"everyone"}],"classification":null,"title":"La Ch창tre","count":1,"stream_id":380002,"contributor":{"url":"http://geocommons.com/users/42827","name":"jflacou"},"data_attributes":null,"calculation_params":null,"icon_link":null,"link":"http://geocommons.com/overlays/380002.json","extent":[1.98652,46.5817,1.98652,46.5817],"geometry_types":["point"],"unique_name":null,"name":"La Ch창tre","feature_count":1,"description":"","next_feature":null,"is_raster":false,"short_classification":"Y","stats":{},"features":[{"properties":{"name":"La Ch창tre","Adresse":"36400 La Ch창tre","id":"afzl06fypvtl","GPS":"1.98652 - 46.58175"},"type":"Feature","geometry":{"type":"Point","coordinates":[1.98652,46.58175]}}],"is_temporal":false,"author":{"url":"","metadata":"","contact_name":"","contact_address":"","source":"","contact_phone":""},"source":"","pagination":{"sort":null,"start":0,"total":1,"limit":1000000},"state":"complete","tags":"","published":"2014-08-16T13:01:01-04:00","id":380002}