{"type":"FeatureCollection","data_type":"Dataset","url_type":null,"permissions":[{"permissions":{"download":true,"view":true},"group_id":"everyone"}],"classification":null,"title":"Ardentes","count":1,"stream_id":380005,"contributor":{"url":"http://geocommons.com/users/42827","name":"jflacou"},"data_attributes":null,"calculation_params":null,"icon_link":null,"link":"http://geocommons.com/overlays/380005.json","extent":[1.83094,46.7421,1.83094,46.7421],"geometry_types":["point"],"unique_name":null,"name":"Ardentes","feature_count":1,"description":"","next_feature":null,"is_raster":false,"short_classification":"Y","stats":{},"features":[{"properties":{"name":"Ardentes","Adresse":"36120 Ardentes","id":"afzl0cyle6ci","GPS":"1.83094 - 46.74205"},"type":"Feature","geometry":{"type":"Point","coordinates":[1.83094,46.74205]}}],"is_temporal":false,"author":{"url":"","metadata":"","contact_name":"","contact_address":"","source":"","contact_phone":""},"source":"","pagination":{"sort":null,"start":0,"total":1,"limit":1000000},"state":"complete","tags":"","published":"2014-08-16T13:01:02-04:00","id":380005}