{"type":"FeatureCollection","data_type":"Dataset","url_type":null,"permissions":[{"permissions":{"download":true,"view":true},"group_id":"everyone"}],"classification":null,"title":"Monc","count":1,"stream_id":380220,"contributor":{"url":"http://geocommons.com/users/74787","name":"stevendosanjh"},"data_attributes":null,"calculation_params":null,"icon_link":null,"link":"http://geocommons.com/overlays/380220.json","extent":[-64.8344,46.0807,-64.8344,46.0807],"geometry_types":["point"],"unique_name":null,"name":"Monc","feature_count":1,"description":"","next_feature":null,"is_raster":false,"short_classification":"Y","stats":{"latitude":{"max":46.080698,"min":46.080698,"median":46.080698},"order":{"max":9999,"min":9999,"median":9999},"longitude":{"max":-64.834421,"min":-64.834421,"median":-64.834421},"identifying number":{"max":11040809,"min":11040809,"median":11040809}},"features":[{"properties":{"delete":null,"city":"Moncton","category":null,"subcategory":null,"latitude":46.080698,"photo url":null,"title":null,"directions":"FALSE","order":9999,"street1":null,"zipcode":"E1E 4N4","photo height":null,"freeform address":"Moncton, NB, E1E 4N4, CA","street2":null,"country":"CA","website":null,"description":null,"photo width":null,"neighborhood":null,"photo description":null,"identifying number":11040809,"longitude":-64.834421,"link":"http://www.communitywalk.com/map/1623078#0004Z7PY","id":"afztk6jyhgih","phone number":null,"state":"NB","photo title":null},"type":"Feature","geometry":{"type":"Point","coordinates":[-64.834421,46.080698]}}],"is_temporal":false,"author":{"url":"","metadata":null,"contact_name":null,"contact_address":null,"source":null,"contact_phone":null},"source":"","pagination":{"sort":null,"start":0,"total":1,"limit":1000000},"state":"complete","tags":"","published":"2014-08-16T13:16:44-04:00","id":380220}