{"type":"FeatureCollection","data_type":"Dataset","url_type":null,"permissions":[{"permissions":{"download":true,"view":true},"group_id":"everyone"}],"classification":null,"title":"Montreal Centre","count":1,"stream_id":380565,"contributor":{"url":"http://geocommons.com/users/74787","name":"stevendosanjh"},"data_attributes":null,"calculation_params":null,"icon_link":null,"link":"http://geocommons.com/overlays/380565.json","extent":[-73.5668,45.5019,-73.5668,45.5019],"geometry_types":["point"],"unique_name":null,"name":"Montreal Centre","feature_count":1,"description":"","next_feature":null,"is_raster":false,"short_classification":"Y","stats":{"latitude":{"max":45.501943,"min":45.501943,"median":45.501943},"longitude":{"max":-73.566779,"min":-73.566779,"median":-73.566779}},"features":[{"properties":{"city":"Montreal","latitude":45.501943,"title":null,"zipcode":"H3B 1S6","freeform address":"Montreal, QC, H3B 1S6, CA","country":"CA","longitude":-73.566779,"id":"ag0kxeyazr10","state":"QC"},"type":"Feature","geometry":{"type":"Point","coordinates":[-73.566779,45.501943]}}],"is_temporal":false,"author":{"url":"","metadata":null,"contact_name":null,"contact_address":null,"source":null,"contact_phone":null},"source":"","pagination":{"sort":null,"start":0,"total":1,"limit":1000000},"state":"complete","tags":"","published":"2014-08-16T13:49:33-04:00","id":380565}