{"type":"FeatureCollection","data_type":"Dataset","url_type":null,"permissions":[{"permissions":{"download":true,"view":true},"group_id":"everyone"}],"classification":null,"title":"short","count":8,"stream_id":384455,"contributor":{"url":"http://geocommons.com/users/71458","name":"feelwinds"},"data_attributes":null,"calculation_params":null,"icon_link":null,"link":"http://geocommons.com/overlays/384455.json","extent":[121.401,31.1911,121.649,31.3179],"geometry_types":["point"],"unique_name":null,"name":"short","feature_count":8,"description":"","next_feature":null,"is_raster":false,"short_classification":"Y","stats":{"f_customer_longitude":{"max":121.649081,"variance":0.00602121639203641,"mean":121.4855982625,"stdev":0.0775964972923161,"min":121.401379,"median":121.4809321},"f_order_time":{"max":"2013/08/01 07:30:00 -0400","variance":0.0,"mean":"2013/08/01 07:30:00 -0400","stdev":0.0,"min":"2013/08/01 07:30:00 -0400","median":"2013/08/01 07:30:00 -0400"},"f_customer_latitude":{"max":31.317895,"variance":0.00168250000839926,"mean":31.25609256375,"stdev":0.0410182887063717,"min":31.19106895,"median":31.264781}},"features":[{"properties":{"f_customer_longitude":121.4809321,"f_order_time":{"end_time":"2013/08/01 07:31:00 -0400","original":"2013/8/1 7:30","granularity":"min","time":"2013/08/01 07:30:00 -0400"},"id":"agap6zpg7xzt","f_customer_latitude":31.28773061},"type":"Feature","geometry":{"type":"Point","coordinates":[121.4809321,31.28773061]}},{"properties":{"f_customer_longitude":121.649081,"f_order_time":{"end_time":"2013/08/01 07:31:00 -0400","original":"2013/8/1 7:30","granularity":"min","time":"2013/08/01 07:30:00 -0400"},"id":"agap6zjfj6qm","f_customer_latitude":31.210697},"type":"Feature","geometry":{"type":"Point","coordinates":[121.649081,31.210697]}},{"properties":{"f_customer_longitude":121.457374,"f_order_time":{"end_time":"2013/08/01 07:31:00 -0400","original":"2013/8/1 7:30","granularity":"min","time":"2013/08/01 07:30:00 -0400"},"id":"agap6zg3f9ns","f_customer_latitude":31.264781},"type":"Feature","geometry":{"type":"Point","coordinates":[121.457374,31.264781]}},{"properties":{"f_customer_longitude":121.518632,"f_order_time":{"end_time":"2013/08/01 07:31:00 -0400","original":"2013/8/1 7:30","granularity":"min","time":"2013/08/01 07:30:00 -0400"},"id":"agap6zfjp662","f_customer_latitude":31.317895},"type":"Feature","geometry":{"type":"Point","coordinates":[121.518632,31.317895]}},{"properties":{"f_customer_longitude":121.442558,"f_order_time":{"end_time":"2013/08/01 07:31:00 -0400","original":"2013/8/1 7:30","granularity":"min","time":"2013/08/01 07:30:00 -0400"},"id":"agap6zetyb9f","f_customer_latitude":31.24318895},"type":"Feature","geometry":{"type":"Point","coordinates":[121.442558,31.24318895]}},{"properties":{"f_customer_longitude":121.511606,"f_order_time":{"end_time":"2013/08/01 07:31:00 -0400","original":"2013/8/1 7:30","granularity":"min","time":"2013/08/01 07:30:00 -0400"},"id":"agap6znoqxrr","f_customer_latitude":31.19106895},"type":"Feature","geometry":{"type":"Point","coordinates":[121.511606,31.19106895]}},{"properties":{"f_customer_longitude":121.401379,"f_order_time":{"end_time":"2013/08/01 07:31:00 -0400","original":"2013/8/1 7:30","granularity":"min","time":"2013/08/01 07:30:00 -0400"},"id":"agap6zu5t8pr","f_customer_latitude":31.276729},"type":"Feature","geometry":{"type":"Point","coordinates":[121.401379,31.276729]}},{"properties":{"f_customer_longitude":121.423224,"f_order_time":{"end_time":"2013/08/01 07:31:00 -0400","original":"2013/8/1 7:30","granularity":"min","time":"2013/08/01 07:30:00 -0400"},"id":"agap6zpm3jhz","f_customer_latitude":31.25665},"type":"Feature","geometry":{"type":"Point","coordinates":[121.423224,31.25665]}}],"is_temporal":true,"author":{"url":"","metadata":"","contact_name":"","contact_address":"","source":"","contact_phone":""},"source":"","pagination":{"sort":null,"start":0,"total":8,"limit":1000000},"state":"complete","tags":"","published":"2014-08-16T18:17:40-04:00","id":384455}