{"type":"FeatureCollection","data_type":"Dataset","url_type":null,"permissions":[{"permissions":{"download":true,"view":true},"group_id":"everyone"}],"classification":null,"title":"ako-Population","count":14,"stream_id":387423,"contributor":{"url":"http://geocommons.com/users/68961","name":"uako"},"data_attributes":null,"calculation_params":null,"icon_link":null,"link":"http://geocommons.com/overlays/387423.json","extent":[93.3859,11.9633,98.6671,26.093],"geometry_types":["point"],"unique_name":null,"name":"ako-Population","feature_count":14,"description":"","next_feature":null,"is_raster":false,"short_classification":"Y","stats":{"latitude":{"max":26.09301524,"variance":13.2874039442414,"mean":19.5361183357143,"stdev":3.64518915068085,"min":11.96333253,"median":19.41842857},"area sq mile":{"max":60155.23,"variance":234449538.074579,"mean":18684.4635714286,"stdev":15311.7451021945,"min":3967.86,"median":14650.87},"population":{"max":7051348,"variance":5755154164673.1,"mean":3546766.21428571,"stdev":2398990.23855311,"min":276693,"median":4675555},"longitude":{"max":98.66713336,"variance":2.81304289160535,"mean":96.2621755792857,"stdev":1.67721283431929,"min":93.38588717,"median":96.25193786}},"features":[{"properties":{"latitude":17.09018552,"area sq mile":13525.88,"name 1":"Ayeyarwady","population":7051348,"longitude":95.13540982,"id":"agk232473nnc","column_2":null},"type":"Feature","geometry":{"type":"Point","coordinates":[95.13540982,17.09018552]}},{"properties":{"latitude":18.13050041,"area sq mile":15213.33,"name 1":"Bago","population":4977966,"longitude":95.97484967,"id":"agk2323x0b3d","column_2":null},"type":"Feature","geometry":{"type":"Point","coordinates":[95.97484967,18.13050041]}},{"properties":{"latitude":22.37953974,"area sq mile":13906.97,"name 1":"Chin","population":487361,"longitude":93.38588717,"id":"agk2324wluym","column_2":null},"type":"Feature","geometry":{"type":"Point","coordinates":[93.38588717,22.37953974]}},{"properties":{"latitude":26.09301524,"area sq mile":34379.22,"name 1":"Kachin","population":1254381,"longitude":97.31069096,"id":"agk23249qg19","column_2":null},"type":"Feature","geometry":{"type":"Point","coordinates":[97.31069096,26.09301524]}},{"properties":{"latitude":19.23962582,"area sq mile":4529.56,"name 1":"Kayah","population":276693,"longitude":97.36174018,"id":"agk23216qdys","column_2":null},"type":"Feature","geometry":{"type":"Point","coordinates":[97.36174018,19.23962582]}},{"properties":{"latitude":17.35719651,"area sq mile":11730.85,"name 1":"Kayin","population":1347732,"longitude":97.66586007,"id":"agk231vzxu4h","column_2":null},"type":"Feature","geometry":{"type":"Point","coordinates":[97.66586007,17.35719651]}},{"properties":{"latitude":20.76360521,"area sq mile":17305.32,"name 1":"Magway","population":4770905,"longitude":94.87901389,"id":"agk232awvwkc","column_2":null},"type":"Feature","geometry":{"type":"Point","coordinates":[94.87901389,20.76360521]}},{"properties":{"latitude":21.5256194,"area sq mile":14650.87,"name 1":"Mandalay","population":6935357,"longitude":95.86082451,"id":"agk2320yqgg4","column_2":null},"type":"Feature","geometry":{"type":"Point","coordinates":[95.86082451,21.5256194]}},{"properties":{"latitude":16.29778589,"area sq mile":4747.76,"name 1":"Mon","population":2518152,"longitude":97.55524108,"id":"agk2329n85wb","column_2":null},"type":"Feature","geometry":{"type":"Point","coordinates":[97.55524108,16.29778589]}},{"properties":{"latitude":19.41842857,"area sq mile":14200.08,"name 1":"Rakhine","population":2649802,"longitude":93.54921345,"id":"agk2326i9s3c","column_2":null},"type":"Feature","geometry":{"type":"Point","coordinates":[93.54921345,19.41842857]}},{"properties":{"latitude":24.48805588,"area sq mile":36534.0,"name 1":"Sagaing","population":5449934,"longitude":95.52360588,"id":"agk231wqdh1v","column_2":null},"type":"Feature","geometry":{"type":"Point","coordinates":[95.52360588,24.48805588]}},{"properties":{"latitude":21.72256065,"area sq mile":60155.23,"name 1":"Shan","population":4675555,"longitude":98.66713336,"id":"agk232aek9gl","column_2":null},"type":"Feature","geometry":{"type":"Point","coordinates":[98.66713336,21.72256065]}},{"properties":{"latitude":11.96333253,"area sq mile":16735.56,"name 1":"Tanintharyi","population":1328813,"longitude":98.54905021,"id":"agk231zy92r7","column_2":null},"type":"Feature","geometry":{"type":"Point","coordinates":[98.54905021,11.96333253]}},{"properties":{"latitude":17.03620533,"area sq mile":3967.86,"name 1":"Yangon","population":5930728,"longitude":96.25193786,"id":"agk231zl25nl","column_2":null},"type":"Feature","geometry":{"type":"Point","coordinates":[96.25193786,17.03620533]}}],"is_temporal":false,"author":{"url":"","metadata":null,"contact_name":null,"contact_address":null,"source":null,"contact_phone":null},"source":"","pagination":{"sort":null,"start":0,"total":14,"limit":1000000},"state":"complete","tags":"","published":"2014-08-16T21:36:36-04:00","id":387423}