{"type":"FeatureCollection","data_type":"Dataset","url_type":null,"permissions":[{"permissions":{"download":true,"view":true},"group_id":"everyone"}],"classification":null,"title":"Ports","count":3,"stream_id":390506,"contributor":{"url":"http://geocommons.com/users/81252","name":"bryan0010165"},"data_attributes":null,"calculation_params":null,"icon_link":null,"link":"http://geocommons.com/overlays/390506.json","extent":[-1.08843,50.812,1.33317,51.1283],"geometry_types":["point"],"unique_name":null,"name":"Ports","feature_count":3,"description":"","next_feature":null,"is_raster":false,"short_classification":"Y","stats":{"latitude":{"max":51.128305,"variance":0.0302528514253331,"mean":51.0119696666667,"stdev":0.17393346838758,"min":50.812019,"median":51.095585},"longitude":{"max":1.33317,"variance":1.79915685218033,"mean":0.455592333333333,"stdev":1.34132652705459,"min":-1.088434,"median":1.122041}},"features":[{"properties":{"name":"PORT","city":"PORTSMOUTH FERRY PORT","opening hours":null,"latitude":50.812019,"postcode":"PO2 8SP","contact":null,"longitude":-1.088434,"id":"agu7fgcbt8ua","phone number":null,"group":"PORT","location":"Portsmouth Ferryport, C/O Ferry Terminal, Hampshire PO2 8SP"},"type":"Feature","geometry":{"type":"Point","coordinates":[-1.088434,50.812019]}},{"properties":{"name":"PORT","city":"DOVER DFDS FERRIES","opening hours":null,"latitude":51.128305,"postcode":"CT16 1JA","contact":null,"longitude":1.33317,"id":"agu7fg10tybr","phone number":null,"group":"PORT","location":"Passenger Services Building, Eastern Docks, Dover, Kent, CT16 1JA"},"type":"Feature","geometry":{"type":"Point","coordinates":[1.33317,51.128305]}},{"properties":{"name":"PORT","city":"EUROTUNNEL","opening hours":null,"latitude":51.095585,"postcode":"CT18 8XX","contact":null,"longitude":1.122041,"id":"agu7ffxpfjtd","phone number":"Tel: 08443353535","group":"PORT","location":"Eurotunnel Le Shuttle, UK Terminal, Ashfor Road, Folkestone, CT18 8XX"},"type":"Feature","geometry":{"type":"Point","coordinates":[1.122041,51.095585]}}],"is_temporal":false,"author":{"url":"","metadata":"","contact_name":"","contact_address":"","source":"","contact_phone":""},"source":"","pagination":{"sort":null,"start":0,"total":3,"limit":1000000},"state":"complete","tags":"","published":"2014-08-16T13:26:57-04:00","id":390506}