{"type":"FeatureCollection","data_type":"Dataset","url_type":null,"permissions":[{"permissions":{"download":true,"view":true},"group_id":"everyone"}],"classification":null,"title":"Zik Tesseau","count":1,"stream_id":392039,"contributor":{"url":"http://geocommons.com/users/42827","name":"jflacou"},"data_attributes":null,"calculation_params":null,"icon_link":null,"link":"http://geocommons.com/overlays/392039.json","extent":[1.44916,46.8836,1.44916,46.8836],"geometry_types":["point"],"unique_name":null,"name":"Zik Tesseau","feature_count":1,"description":"","next_feature":null,"is_raster":false,"short_classification":"Y","stats":{},"features":[{"properties":{"name":"Zik à Tesseau","Adresse":"ZA Les Terres Rouges","id":"agzyb85k9xyv","GPS":"1.44916 - 46.88361"},"type":"Feature","geometry":{"type":"Point","coordinates":[1.44916,46.88361]}}],"is_temporal":false,"author":{"url":"","metadata":"","contact_name":"","contact_address":"","source":"","contact_phone":""},"source":"","pagination":{"sort":null,"start":0,"total":1,"limit":1000000},"state":"complete","tags":"","published":"2014-08-16T15:14:24-04:00","id":392039}