{"type":"FeatureCollection","data_type":"Dataset","url_type":null,"permissions":[{"permissions":{"download":true,"view":true},"group_id":"everyone"}],"classification":null,"title":"Collégiens au théâtre - septembre 2013","count":1,"stream_id":393251,"contributor":{"url":"http://geocommons.com/users/42827","name":"jflacou"},"data_attributes":null,"calculation_params":null,"icon_link":null,"link":"http://geocommons.com/overlays/393251.json","extent":[1.69055,46.8089,1.69055,46.8089],"geometry_types":["point"],"unique_name":null,"name":"Collégiens au théâtre - septembre 2013","feature_count":1,"description":"","next_feature":null,"is_raster":false,"short_classification":"Y","stats":{"Date":{"max":"2013/09/29 00:00:00 -0400","min":"2013/09/29 00:00:00 -0400","median":"2013/09/29 00:00:00 -0400"}},"features":[{"properties":{"Lieu":"Equinoxe","Style":"Arts de la piste","Date":{"end_time":"2013/09/30 00:00:00 -0400","original":"28-29 septembre 2013","granularity":"day","time":"2013/09/29 00:00:00 -0400"},"id":"ah3lrsmt7j1m","Spectacle":"Extrémités","GPS":"1.69055 - 46.80888"},"type":"Feature","geometry":{"type":"Point","coordinates":[1.69055,46.80888]}}],"is_temporal":true,"author":{"url":"","metadata":"","contact_name":"","contact_address":"","source":"","contact_phone":""},"source":"","pagination":{"sort":null,"start":0,"total":1,"limit":1000000},"state":"complete","tags":"","published":"2014-08-16T16:22:48-04:00","id":393251}