{"type":"FeatureCollection","data_type":"Dataset","url_type":null,"permissions":[{"permissions":{"download":true,"view":true},"group_id":"everyone"}],"classification":null,"title":"Ponto_099_Barracâo_de_Reciclagem_linhões","count":1,"stream_id":394960,"contributor":{"url":"http://geocommons.com/users/62483","name":"caaete"},"data_attributes":null,"calculation_params":null,"icon_link":null,"link":"http://geocommons.com/overlays/394960.json","extent":[-54.5572,-25.4494,-54.5572,-25.4494],"geometry_types":["point"],"unique_name":null,"name":"Ponto_099_Barracâo_de_Reciclagem_linhões","feature_count":1,"description":"","next_feature":null,"is_raster":false,"short_classification":"Y","stats":{},"features":[{"properties":{"name":"Ponto 099 Barracâo de Reciclagem","description":"23-NOV-10 23:18:40","id":"ahabsxombz9e"},"type":"Feature","geometry":{"type":"Point","coordinates":[-54.557222,-25.449357]}}],"is_temporal":false,"author":{"url":"","metadata":null,"contact_name":null,"contact_address":null,"source":null,"contact_phone":null},"source":"","pagination":{"sort":null,"start":0,"total":1,"limit":1000000},"state":"complete","tags":"","published":"2014-08-16T18:45:43-04:00","id":394960}