{"type":"FeatureCollection","data_type":"Dataset","url_type":null,"permissions":[{"permissions":{"download":true,"view":true},"group_id":"everyone"}],"classification":null,"title":"DC9-50 Rons-Rads Nov13","count":4,"stream_id":395025,"contributor":{"url":"http://geocommons.com/users/38310","name":"Dlforecastdemand"},"data_attributes":null,"calculation_params":null,"icon_link":null,"link":"http://geocommons.com/overlays/395025.json","extent":[-84.4281,32.1276,-80.0405,42.2124],"geometry_types":["point"],"unique_name":null,"name":"DC9-50 Rons-Rads Nov13","feature_count":4,"description":"","next_feature":null,"is_raster":false,"short_classification":"Y","stats":{"latitude":{"max":42.21239853,"variance":22.1174300611663,"mean":35.21882534,"stdev":4.70291718629685,"min":32.12760162,"median":33.63669968},"rons rads":{"max":63,"variance":852.916666666667,"mean":38.25,"stdev":29.2047370586805,"min":1,"median":60},"longitude":{"max":-80.04049683,"variance":3.9804880733065,"mean":-82.256025315,"stdev":1.99511605509717,"min":-84.42810059,"median":-81.20210266}},"features":[{"properties":{"latitude":33.63669968,"airport code":"ATL","rons rads":63,"longitude":-84.42810059,"id":"ahae9txow57e"},"type":"Feature","geometry":{"type":"Point","coordinates":[-84.42810059,33.63669968]}},{"properties":{"latitude":32.89860153,"airport code":"CHS","rons rads":1,"longitude":-80.04049683,"id":"ahae9ttvitf0"},"type":"Feature","geometry":{"type":"Point","coordinates":[-80.04049683,32.89860153]}},{"properties":{"latitude":42.21239853,"airport code":"DTW","rons rads":60,"longitude":-83.35340118,"id":"ahae9tvgb4ke"},"type":"Feature","geometry":{"type":"Point","coordinates":[-83.35340118,42.21239853]}},{"properties":{"latitude":32.12760162,"airport code":"SAV","rons rads":29,"longitude":-81.20210266,"id":"ahae9ty8mbr3"},"type":"Feature","geometry":{"type":"Point","coordinates":[-81.20210266,32.12760162]}}],"is_temporal":false,"author":{"url":"","metadata":"","contact_name":"","contact_address":"","source":"","contact_phone":""},"source":"","pagination":{"sort":null,"start":0,"total":4,"limit":1000000},"state":"complete","tags":"","published":"2014-08-16T18:48:40-04:00","id":395025}