{"type":"FeatureCollection","data_type":"Dataset","url_type":null,"permissions":[{"permissions":{"download":true,"view":true},"group_id":"everyone"}],"classification":null,"title":"San_Antonio_NHS_School_Poing","count":1,"stream_id":395680,"contributor":{"url":"http://geocommons.com/users/81761","name":"Nonnie123"},"data_attributes":null,"calculation_params":null,"icon_link":null,"link":"http://geocommons.com/overlays/395680.json","extent":[123.537,9.17536,123.537,9.17536],"geometry_types":["point"],"unique_name":null,"name":"San_Antonio_NHS_School_Poing","feature_count":1,"description":"","next_feature":null,"is_raster":false,"short_classification":"Y","stats":{"typesch0":{"max":1,"min":1,"median":1},"sch.id":{"max":303298,"min":303298,"median":303298},"lat":{"max":9.175356,"min":9.175356,"median":9.175356},"long":{"max":123.53727,"min":123.53727,"median":123.53727}},"features":[{"properties":{"typesch0":1,"typesch":"Public","sch. name":"San Antonio NHS","sch.id":303298,"id":"ahbubaoc1yer","lat":9.175356,"long":123.53727},"type":"Feature","geometry":{"type":"Point","coordinates":[123.53727,9.175356]}}],"is_temporal":false,"author":{"url":"","metadata":null,"contact_name":null,"contact_address":null,"source":null,"contact_phone":null},"source":"","pagination":{"sort":null,"start":0,"total":1,"limit":1000000},"state":"complete","tags":"","published":"2014-08-16T19:40:00-04:00","id":395680}