{"type":"FeatureCollection","data_type":"Dataset","url_type":null,"permissions":[{"permissions":{"download":true,"view":true},"group_id":"everyone"}],"classification":null,"title":"Candaping_HS_School_Point","count":1,"stream_id":395716,"contributor":{"url":"http://geocommons.com/users/81761","name":"Nonnie123"},"data_attributes":null,"calculation_params":null,"icon_link":null,"link":"http://geocommons.com/overlays/395716.json","extent":[123.654,9.16498,123.654,9.16498],"geometry_types":["point"],"unique_name":null,"name":"Candaping_HS_School_Point","feature_count":1,"description":"","next_feature":null,"is_raster":false,"short_classification":"Y","stats":{"typesch0":{"max":1,"min":1,"median":1},"sch.id":{"max":303304,"min":303304,"median":303304},"lat":{"max":9.164976,"min":9.164976,"median":9.164976},"long":{"max":123.65361,"min":123.65361,"median":123.65361}},"features":[{"properties":{"typesch0":1,"typesch":"Public","sch. name":"Candaping High School","sch.id":303304,"id":"ahbvwqzdv0kc","lat":9.164976,"long":123.65361},"type":"Feature","geometry":{"type":"Point","coordinates":[123.65361,9.164976]}}],"is_temporal":false,"author":{"url":"","metadata":null,"contact_name":null,"contact_address":null,"source":null,"contact_phone":null},"source":"","pagination":{"sort":null,"start":0,"total":1,"limit":1000000},"state":"complete","tags":"","published":"2014-08-16T19:40:33-04:00","id":395716}