{"type":"FeatureCollection","data_type":"Dataset","url_type":null,"permissions":[{"permissions":{"download":true,"view":true},"group_id":"everyone"}],"classification":null,"title":"Kinamandagan_HS_School_Point","count":1,"stream_id":395749,"contributor":{"url":"http://geocommons.com/users/81761","name":"Nonnie123"},"data_attributes":null,"calculation_params":null,"icon_link":null,"link":"http://geocommons.com/overlays/395749.json","extent":[123.604,9.13778,123.604,9.13778],"geometry_types":["point"],"unique_name":null,"name":"Kinamandagan_HS_School_Point","feature_count":1,"description":"","next_feature":null,"is_raster":false,"short_classification":"Y","stats":{"typesch0":{"max":1,"min":1,"median":1},"sch.id":{"max":303294,"min":303294,"median":303294},"lat":{"max":9.137775,"min":9.137775,"median":9.137775},"long":{"max":123.603905,"min":123.603905,"median":123.603905}},"features":[{"properties":{"typesch0":1,"typesch":"Public","sch. name":"Kinamandagan High School","sch.id":303294,"id":"ahbxaph56znp","lat":9.137775,"long":123.603905},"type":"Feature","geometry":{"type":"Point","coordinates":[123.603905,9.137775]}}],"is_temporal":false,"author":{"url":"","metadata":null,"contact_name":null,"contact_address":null,"source":null,"contact_phone":null},"source":"","pagination":{"sort":null,"start":0,"total":1,"limit":1000000},"state":"complete","tags":"","published":"2014-08-16T19:42:23-04:00","id":395749}