{"type":"FeatureCollection","data_type":"Dataset","url_type":null,"permissions":[{"permissions":{"download":true,"view":true},"group_id":"everyone"}],"classification":null,"title":"Dentista","count":1,"stream_id":399115,"contributor":{"url":"http://geocommons.com/users/69936","name":"eliaszr"},"data_attributes":null,"calculation_params":null,"icon_link":null,"link":"http://geocommons.com/overlays/399115.json","extent":[-71.5488,-16.334,-71.5488,-16.334],"geometry_types":["point"],"unique_name":null,"name":"Dentista","feature_count":1,"description":"","next_feature":null,"is_raster":false,"short_classification":"Y","stats":{"ruc":{"max":10292511685,"min":10292511685,"median":10292511685},"establecimentos pblicos civiles":{"max":0,"min":0,"median":0},"manzana censal":{"max":5,"min":5,"median":5},"establecimientos principales":{"max":0,"min":0,"median":0},"formalidad":{"max":1,"min":1,"median":1},"numero de trabajadores mujeres":{"max":0,"min":0,"median":0},"lote":{"max":11,"min":11,"median":11},"establecimientos nicos":{"max":3,"min":3,"median":3},"niveles de venta mensuales":{"max":2,"min":2,"median":2},"permanencia del negocio":{"max":2,"min":2,"median":2},"piso":{"max":1,"min":1,"median":1},"numero frente":{"max":2,"min":2,"median":2},"zona censal":{"max":10,"min":10,"median":10},"estasblecimientos sucursales":{"max":0,"min":0,"median":0},"tamao de la empresa":{"max":1,"min":1,"median":1},"nivel educativo del empleador":{"max":4,"min":4,"median":4},"longitud":{"max":-71.548823,"min":-71.548823,"median":-71.548823},"total de establecimientos":{"max":3,"min":3,"median":3},"establecimientos de unidad auxiliar":{"max":0,"min":0,"median":0},"estructura demogrfica":{"max":2,"min":2,"median":2},"sexo del empleador":{"max":1,"min":1,"median":1},"telfono":{"max":959247091,"min":959247091,"median":959247091},"zonificacin":{"max":5,"min":5,"median":5},"categoria de ncleo urbano":{"max":15,"min":15,"median":15},"latitud":{"max":-16.334023,"min":-16.334023,"median":-16.334023},"numero de orden":{"max":2,"min":2,"median":2},"mercados":{"max":0,"min":0,"median":0},"total de empleados":{"max":1,"min":1,"median":1},"contabilidad":{"max":2,"min":2,"median":2},"edad del empleador":{"max":41,"min":41,"median":41},"numero de trabajadores hombres":{"max":1,"min":1,"median":1},"rama de actividad":{"max":14,"min":14,"median":14},"codigo de actividad":{"max":851240,"min":851240,"median":851240},"capacitacin Empresarial":{"max":6,"min":6,"median":6}},"features":[{"properties":{"actividad":"DENTISTA ODONTOLOGIA GENERAL","ruc":10292511685,"fuente de financiamiento":"Propio","manzana censal":5,"establecimentos pblicos civiles":0,"distrito":"Cayma","lote":11,"numero interior":null,"km":null,"numero de trabajadores mujeres":0,"formalidad":1,"establecimientos principales":0,"zona censal":10,"numero frente":2,"piso":1,"razon social o nombre del propietario":"RICARDO SAMUEL OMEZ LINARES","permanencia del negocio":2,"niveles de venta mensuales":2,"establecimientos nicos":3,"longitud":-71.548823,"nivel educativo del empleador":4,"tamao de la empresa":1,"acceso telefonico":"SI","estasblecimientos sucursales":0,"zonificacin":5,"telfono":959247091,"sexo del empleador":1,"region de destino de mercaderia":"Cayma","estructura demogrfica":2,"establecimientos de unidad auxiliar":0,"total de establecimientos":3,"ciudad":"Arequipa","latitud":-16.334023,"nucleo urbano":"DEAN VALDIVIA","local respecto vivienda":"Ambiente Compartido para Negocio y Vivienda","manzana nueva":"NO","categoria de ncleo urbano":15,"descripcin de actividad":"SERVICIO ODONTÓLOGICO","tipo de establecimiento":"Consultorio Dental","registro":"137A","numero de orden":2,"departamento":"Arequipa","numero de puerta":null,"pais de destino de mercaderia":"Perú","id":"ahlhabzq8ljn","codigo de actividad":851240,"manzana":"O-4","rama de actividad":14,"numero de trabajadores hombres":1,"edad del empleador":41,"negocio a puerta cerrada":"Cerrada","empresa de destino de mercaderia":"PUBLICO","contabilidad":2,"total de empleados":1,"mercados":0,"categora":"Único","antigedad del negocio":"3-5 años","capacitacin Empresarial":6,"ubigeo":"Cayma"},"type":"Feature","geometry":{"type":"Point","coordinates":[-71.548823,-16.334023]}}],"is_temporal":false,"author":{"url":"","metadata":"","contact_name":"","contact_address":"","source":"","contact_phone":""},"source":"","pagination":{"sort":null,"start":0,"total":1,"limit":1000000},"state":"complete","tags":"","published":"2014-08-17T00:05:22-04:00","id":399115}