{"type":"FeatureCollection","data_type":"Dataset","url_type":null,"permissions":[{"permissions":{"download":true,"view":true},"group_id":"everyone"}],"classification":null,"title":"Fabrica de Productos Primarios de Metal Ferroso","count":1,"stream_id":399144,"contributor":{"url":"http://geocommons.com/users/69936","name":"eliaszr"},"data_attributes":null,"calculation_params":null,"icon_link":null,"link":"http://geocommons.com/overlays/399144.json","extent":[-71.5442,-16.3666,-71.5442,-16.3666],"geometry_types":["point"],"unique_name":null,"name":"Fabrica de Productos Primarios de Metal Ferroso","feature_count":1,"description":"","next_feature":null,"is_raster":false,"short_classification":"Y","stats":{"ruc":{"max":10293227867,"min":10293227867,"median":10293227867},"establecimentos pblicos civiles":{"max":0,"min":0,"median":0},"manzana censal":{"max":16,"min":16,"median":16},"establecimientos principales":{"max":0,"min":0,"median":0},"formalidad":{"max":1,"min":1,"median":1},"numero de trabajadores mujeres":{"max":0,"min":0,"median":0},"establecimientos nicos":{"max":12,"min":12,"median":12},"niveles de venta mensuales":{"max":3,"min":3,"median":3},"permanencia del negocio":{"max":2,"min":2,"median":2},"piso":{"max":1,"min":1,"median":1},"numero frente":{"max":4,"min":4,"median":4},"zona censal":{"max":6,"min":6,"median":6},"estasblecimientos sucursales":{"max":0,"min":0,"median":0},"tamao de la empresa":{"max":1,"min":1,"median":1},"nivel educativo del empleador":{"max":2,"min":2,"median":2},"longitud":{"max":-71.544222,"min":-71.544222,"median":-71.544222},"total de establecimientos":{"max":12,"min":12,"median":12},"establecimientos de unidad auxiliar":{"max":0,"min":0,"median":0},"estructura demogrfica":{"max":3,"min":3,"median":3},"sexo del empleador":{"max":1,"min":1,"median":1},"telfono":{"max":0,"min":0,"median":0},"zonificacin":{"max":4,"min":4,"median":4},"categoria de ncleo urbano":{"max":2,"min":2,"median":2},"latitud":{"max":-16.366561,"min":-16.366561,"median":-16.366561},"numero de puerta":{"max":106,"min":106,"median":106},"numero de orden":{"max":8,"min":8,"median":8},"mercados":{"max":0,"min":0,"median":0},"total de empleados":{"max":2,"min":2,"median":2},"contabilidad":{"max":1,"min":1,"median":1},"edad del empleador":{"max":54,"min":54,"median":54},"numero de trabajadores hombres":{"max":2,"min":2,"median":2},"rama de actividad":{"max":4,"min":4,"median":4},"codigo de actividad":{"max":271011,"min":271011,"median":271011},"capacitacin Empresarial":{"max":6,"min":6,"median":6}},"features":[{"properties":{"actividad":"FABRICA DE PRODUCTOS PRIMARIOS DE METAL FERROSO","ruc":10293227867,"fuente de financiamiento":"Prestamo Caja Municipal","manzana censal":16,"establecimentos pblicos civiles":0,"distrito":"Cayma","lote":null,"numero interior":null,"km":null,"numero de trabajadores mujeres":0,"formalidad":1,"establecimientos principales":0,"zona censal":6,"numero frente":4,"piso":1,"razon social o nombre del propietario":"JUAN COAQUIRA FLORES","permanencia del negocio":2,"niveles de venta mensuales":3,"establecimientos nicos":12,"longitud":-71.544222,"nivel educativo del empleador":2,"tamao de la empresa":1,"acceso telefonico":"NO","estasblecimientos sucursales":0,"zonificacin":4,"telfono":0,"sexo del empleador":1,"region de destino de mercaderia":"Cayma","estructura demogrfica":3,"establecimientos de unidad auxiliar":0,"total de establecimientos":12,"ciudad":"Arequipa","latitud":-16.366561,"nucleo urbano":"FRANCISCO BOLOGNESI","local respecto vivienda":"Independiente de su Vivienda","manzana nueva":"NO SABE","categoria de ncleo urbano":2,"descripcin de actividad":"FABRICACION DE PIEZAS DE MATERIAL FERROSO","tipo de establecimiento":"Taller de Mecanica Industrial","registro":"320B","numero de orden":8,"departamento":"Arequipa","numero de puerta":106,"pais de destino de mercaderia":"Perú","id":"ahlhcj3m21ga","codigo de actividad":271011,"manzana":null,"rama de actividad":4,"numero de trabajadores hombres":2,"edad del empleador":54,"negocio a puerta cerrada":"Abierta","empresa de destino de mercaderia":"PUBLICO","contabilidad":1,"total de empleados":2,"mercados":0,"categora":"Único","antigedad del negocio":"10 años a +","capacitacin Empresarial":6,"ubigeo":"Cayma"},"type":"Feature","geometry":{"type":"Point","coordinates":[-71.544222,-16.366561]}}],"is_temporal":false,"author":{"url":"","metadata":"","contact_name":"","contact_address":"","source":"","contact_phone":""},"source":"","pagination":{"sort":null,"start":0,"total":1,"limit":1000000},"state":"complete","tags":"","published":"2014-08-17T00:05:55-04:00","id":399144}