{"type":"FeatureCollection","data_type":"Dataset","url_type":null,"permissions":[{"permissions":{"download":true,"view":true},"group_id":"everyone"}],"classification":null,"title":"LLOMA_DE_BETXÌ2","count":5,"stream_id":400067,"contributor":{"url":"http://geocommons.com/users/83742","name":"martinaparini"},"data_attributes":null,"calculation_params":null,"icon_link":null,"link":"http://geocommons.com/overlays/400067.json","extent":[-0.50917,39.5267,-0.507825,39.5294],"geometry_types":["point"],"unique_name":null,"name":"LLOMA_DE_BETXÌ2","feature_count":5,"description":"","next_feature":null,"is_raster":false,"short_classification":"Y","stats":{},"features":[{"properties":{"name":"alta_resoluciòn_wgs84","id":"ahmxd5nnt58n"},"type":"Feature","geometry":{"type":"Point","coordinates":[-0.508504438425311,39.5294023932197]}},{"properties":{"name":"wgs84","id":"ahmxd5g0wcal"},"type":"Feature","geometry":{"type":"Point","coordinates":[-0.5078249627941,39.5285589999837]}},{"properties":{"name":"ed50_etrs89","id":"ahmxd5o3ebw1"},"type":"Feature","geometry":{"type":"Point","coordinates":[-0.50917,39.52671]}},{"properties":{"name":"ed50_ed50","id":"ahmxd5nl1z4h"},"type":"Feature","geometry":{"type":"Point","coordinates":[-0.50796,39.52789]}},{"properties":{"name":"LLOMA DE BETXÌ","id":"ahmxd5gioepx"},"type":"Feature","geometry":null}],"is_temporal":false,"author":{"url":"","metadata":null,"contact_name":null,"contact_address":null,"source":null,"contact_phone":null},"source":"","pagination":{"sort":null,"start":0,"total":5,"limit":1000000},"state":"complete","tags":"","published":"2014-08-17T22:41:18-04:00","id":400067}