{"type":"FeatureCollection","data_type":"Dataset","url_type":null,"permissions":[{"permissions":{"download":true,"view":true},"group_id":"everyone"}],"classification":null,"title":"\ntravel memory\n","count":11,"stream_id":45843,"contributor":{"url":"http://geocommons.com/users/11444","name":"platial"},"data_attributes":null,"calculation_params":null,"icon_link":null,"link":"http://geocommons.com/overlays/45843.json","extent":[-123.936,35.6185,140.762,49.3521],"geometry_types":["point"],"unique_name":null,"name":"\ntravel memory\n","feature_count":11,"description":"\nA Map by 7kamado\n\n\n","next_feature":null,"is_raster":false,"short_classification":"Y","stats":{},"features":[{"properties":{"name":null,"description":"Posted by 7kamado<a title=\"Built for Community Mapping\" href=\"http://www.platial.com\"><img src=\"http://media.geocommons.com/platial/images/logotype_small.jpg\"></a>","id":"a63s07541fc3"},"type":"Feature","geometry":{"type":"Point","coordinates":[-123.06061,49.33765]}},{"properties":{"name":null,"description":"Posted by 7kamado<a title=\"Built for Community Mapping\" href=\"http://www.platial.com\"><img src=\"http://media.geocommons.com/platial/images/logotype_small.jpg\"></a>","id":"a63s07249lvs"},"type":"Feature","geometry":{"type":"Point","coordinates":[-123.93591,49.16386]}},{"properties":{"name":null,"description":"Posted by 7kamado<a title=\"Built for Community Mapping\" href=\"http://www.platial.com\"><img src=\"http://media.geocommons.com/platial/images/logotype_small.jpg\"></a>","id":"a63s072rpgy0"},"type":"Feature","geometry":{"type":"Point","coordinates":[-123.14198,49.30201]}},{"properties":{"name":null,"description":"Posted by 7kamado<a title=\"Built for Community Mapping\" href=\"http://www.platial.com\"><img src=\"http://media.geocommons.com/platial/images/logotype_small.jpg\"></a>","id":"a63s070sximt"},"type":"Feature","geometry":{"type":"Point","coordinates":[-123.35861,48.42669]}},{"properties":{"name":null,"description":"Posted by 7kamado<a title=\"Built for Community Mapping\" href=\"http://www.platial.com\"><img src=\"http://media.geocommons.com/platial/images/logotype_small.jpg\"></a>","id":"a63s07anyzrp"},"type":"Feature","geometry":{"type":"Point","coordinates":[139.5196,35.67427]}},{"properties":{"name":null,"description":"Posted by 7kamado<a title=\"Built for Community Mapping\" href=\"http://www.platial.com\"><img src=\"http://media.geocommons.com/platial/images/logotype_small.jpg\"></a>","id":"a63s076x7nue"},"type":"Feature","geometry":{"type":"Point","coordinates":[139.51604,35.67533]}},{"properties":{"name":null,"description":"Posted by 7kamado<a title=\"Built for Community Mapping\" href=\"http://www.platial.com\"><img src=\"http://media.geocommons.com/platial/images/logotype_small.jpg\"></a>","id":"a63s0702rvjw"},"type":"Feature","geometry":{"type":"Point","coordinates":[140.76199,37.93174]}},{"properties":{"name":null,"description":"Posted by 7kamado<a title=\"Built for Community Mapping\" href=\"http://www.platial.com\"><img src=\"http://media.geocommons.com/platial/images/logotype_small.jpg\"></a>","id":"a63s07bj04x6"},"type":"Feature","geometry":{"type":"Point","coordinates":[-123.717,48.9221]}},{"properties":{"name":null,"description":"Posted by 7kamado<a title=\"Built for Community Mapping\" href=\"http://www.platial.com\"><img src=\"http://media.geocommons.com/platial/images/logotype_small.jpg\"></a>","id":"a63s06xm40vn"},"type":"Feature","geometry":{"type":"Point","coordinates":[-123.34833,48.44776]}},{"properties":{"name":null,"description":"Posted by 7kamado<a title=\"Built for Community Mapping\" href=\"http://www.platial.com\"><img src=\"http://media.geocommons.com/platial/images/logotype_small.jpg\"></a>","id":"a63s073rs3ig"},"type":"Feature","geometry":{"type":"Point","coordinates":[139.73195,35.61855]}},{"properties":{"name":null,"description":"Posted by 7kamado<a title=\"Built for Community Mapping\" href=\"http://www.platial.com\"><img src=\"http://media.geocommons.com/platial/images/logotype_small.jpg\"></a>","id":"a63s075m8ymt"},"type":"Feature","geometry":{"type":"Point","coordinates":[-123.11382,49.35208]}}],"is_temporal":false,"author":{"url":"http://www.platial.com/map/36882","metadata":null,"contact_name":"7kamado","contact_address":null,"source":"platial:7kamado","contact_phone":null},"source":"http://www.platial.com/map/36882","pagination":{"sort":null,"start":0,"total":11,"limit":1000000},"state":"complete","tags":"platial,platial:id=36882,platial:user=7kamado","published":"2010-04-26T16:00:00Z","id":45843}