{"type":"FeatureCollection","data_type":"Dataset","url_type":null,"permissions":[{"permissions":{"download":true,"view":true},"group_id":"everyone"}],"classification":null,"title":"\nvisitors maps\n","count":12,"stream_id":45943,"contributor":{"url":"http://geocommons.com/users/11444","name":"platial"},"data_attributes":null,"calculation_params":null,"icon_link":null,"link":"http://geocommons.com/overlays/45943.json","extent":[42.6093,20.0161,59.7656,38.2046],"geometry_types":["point"],"unique_name":null,"name":"\nvisitors maps\n","feature_count":12,"description":"\nA Map by Ramoody5\n\n\n","next_feature":null,"is_raster":false,"short_classification":"Y","stats":{},"features":[{"properties":{"name":null,"description":"Posted by Ramoody5<a title=\"Built for Community Mapping\" href=\"http://www.platial.com\"><img src=\"http://media.geocommons.com/platial/images/logotype_small.jpg\"></a>","id":"a67gr0allfa0"},"type":"Feature","geometry":{"type":"Point","coordinates":[44.71436,37.54458]}},{"properties":{"name":null,"description":"Posted by Ramoody5<a title=\"Built for Community Mapping\" href=\"http://www.platial.com\"><img src=\"http://media.geocommons.com/platial/images/logotype_small.jpg\"></a>","id":"a67gqzwow9vc"},"type":"Feature","geometry":{"type":"Point","coordinates":[44.76706,38.2046]}},{"properties":{"name":null,"description":"Posted by Ramoody5<a title=\"Built for Community Mapping\" href=\"http://www.platial.com\"><img src=\"http://media.geocommons.com/platial/images/logotype_small.jpg\"></a>","id":"a67gqzx5jsl6"},"type":"Feature","geometry":{"type":"Point","coordinates":[44.76706,38.2046]}},{"properties":{"name":null,"description":"Posted by Ramoody5<a title=\"Built for Community Mapping\" href=\"http://www.platial.com\"><img src=\"http://media.geocommons.com/platial/images/logotype_small.jpg\"></a>","id":"a67gqzylwm8j"},"type":"Feature","geometry":{"type":"Point","coordinates":[46.75781,24.52713]}},{"properties":{"name":null,"description":"Posted by Ramoody5<a title=\"Built for Community Mapping\" href=\"http://www.platial.com\"><img src=\"http://media.geocommons.com/platial/images/logotype_small.jpg\"></a>","id":"a67gr04jslpl"},"type":"Feature","geometry":{"type":"Point","coordinates":[55.5049,25.39448]}},{"properties":{"name":null,"description":"Posted by Ramoody5<a title=\"Built for Community Mapping\" href=\"http://www.platial.com\"><img src=\"http://media.geocommons.com/platial/images/logotype_small.jpg\"></a>","id":"a67gr05fznh2"},"type":"Feature","geometry":{"type":"Point","coordinates":[55.32715,25.03584]}},{"properties":{"name":null,"description":"Posted by Ramoody5<a title=\"Built for Community Mapping\" href=\"http://www.platial.com\"><img src=\"http://media.geocommons.com/platial/images/logotype_small.jpg\"></a>","id":"a67gr0admfgh"},"type":"Feature","geometry":{"type":"Point","coordinates":[53.26172,35.38905]}},{"properties":{"name":null,"description":"Posted by Ramoody5<a title=\"Built for Community Mapping\" href=\"http://www.platial.com\"><img src=\"http://media.geocommons.com/platial/images/logotype_small.jpg\"></a>","id":"a67gr0aji5fs"},"type":"Feature","geometry":{"type":"Point","coordinates":[54.7998,29.03696]}},{"properties":{"name":null,"description":"Posted by Ramoody5<a title=\"Built for Community Mapping\" href=\"http://www.platial.com\"><img src=\"http://media.geocommons.com/platial/images/logotype_small.jpg\"></a>","id":"a67gqzwi5yob"},"type":"Feature","geometry":{"type":"Point","coordinates":[59.76563,30.44867]}},{"properties":{"name":null,"description":"Posted by Ramoody5<a title=\"Built for Community Mapping\" href=\"http://www.platial.com\"><img src=\"http://media.geocommons.com/platial/images/logotype_small.jpg\"></a>","id":"a67gr08w80je"},"type":"Feature","geometry":{"type":"Point","coordinates":[50.97656,36.10238]}},{"properties":{"name":null,"description":"Posted by Ramoody5<a title=\"Built for Community Mapping\" href=\"http://www.platial.com\"><img src=\"http://media.geocommons.com/platial/images/logotype_small.jpg\"></a>","id":"a67gqzv4at6j"},"type":"Feature","geometry":{"type":"Point","coordinates":[53.26172,35.38905]}},{"properties":{"name":null,"description":"Posted by Ramoody5<a title=\"Built for Community Mapping\" href=\"http://www.platial.com\"><img src=\"http://media.geocommons.com/platial/images/logotype_small.jpg\"></a>","id":"a67gqzzwiyee"},"type":"Feature","geometry":{"type":"Point","coordinates":[42.60935,20.01613]}}],"is_temporal":false,"author":{"url":"http://www.platial.com/map/17101","metadata":null,"contact_name":"ramoody5","contact_address":null,"source":"platial:ramoody5","contact_phone":null},"source":"http://www.platial.com/map/17101","pagination":{"sort":null,"start":0,"total":12,"limit":1000000},"state":"complete","tags":"platial,platial:id=17101,platial:user=ramoody5","published":"2010-04-26T16:00:00Z","id":45943}