{"type":"FeatureCollection","data_type":"Dataset","url_type":null,"permissions":[{"permissions":{"download":true,"view":true},"group_id":"everyone"}],"classification":null,"title":"\nbeate's places\n","count":12,"stream_id":46250,"contributor":{"url":"http://geocommons.com/users/11444","name":"platial"},"data_attributes":null,"calculation_params":null,"icon_link":null,"link":"http://geocommons.com/overlays/46250.json","extent":[10.4531,59.811,11.1707,59.9283],"geometry_types":["point"],"unique_name":null,"name":"\nbeate's places\n","feature_count":12,"description":"\nA Map by Beate\n\n\n","next_feature":null,"is_raster":false,"short_classification":"Y","stats":{},"features":[{"properties":{"name":null,"description":"Posted by Beate<a title=\"Built for Community Mapping\" href=\"http://www.platial.com\"><img src=\"http://media.geocommons.com/platial/images/logotype_small.jpg\"></a>","id":"a6d2qez6pe0y"},"type":"Feature","geometry":{"type":"Point","coordinates":[10.77261,59.92599]}},{"properties":{"name":null,"description":"Posted by BeateVeldig fin bro!<a title=\"Built for Community Mapping\" href=\"http://www.platial.com\"><img src=\"http://media.geocommons.com/platial/images/logotype_small.jpg\"></a>","id":"a6d2qet4mznk"},"type":"Feature","geometry":{"type":"Point","coordinates":[11.17069,59.92827]}},{"properties":{"name":null,"description":"Posted by Beate<a title=\"Built for Community Mapping\" href=\"http://www.platial.com\"><img src=\"http://media.geocommons.com/platial/images/logotype_small.jpg\"></a>","id":"a6d2qeybwv47"},"type":"Feature","geometry":{"type":"Point","coordinates":[10.75119,59.91949]}},{"properties":{"name":null,"description":"Posted by Beate<a title=\"Built for Community Mapping\" href=\"http://www.platial.com\"><img src=\"http://media.geocommons.com/platial/images/logotype_small.jpg\"></a>","id":"a6d2qenpqsa3"},"type":"Feature","geometry":{"type":"Point","coordinates":[10.45313,59.81102]}},{"properties":{"name":null,"description":"Posted by Beate<a title=\"Built for Community Mapping\" href=\"http://www.platial.com\"><img src=\"http://media.geocommons.com/platial/images/logotype_small.jpg\"></a>","id":"a6d2qep6uq2x"},"type":"Feature","geometry":{"type":"Point","coordinates":[10.61554,59.88894]}},{"properties":{"name":null,"description":"Posted by Beate<a title=\"Built for Community Mapping\" href=\"http://www.platial.com\"><img src=\"http://media.geocommons.com/platial/images/logotype_small.jpg\"></a>","id":"a6d2qex9t9x9"},"type":"Feature","geometry":{"type":"Point","coordinates":[10.6806,59.90162]}},{"properties":{"name":null,"description":"Posted by Beate<a title=\"Built for Community Mapping\" href=\"http://www.platial.com\"><img src=\"http://media.geocommons.com/platial/images/logotype_small.jpg\"></a>","id":"a6d2qeufnzqy"},"type":"Feature","geometry":{"type":"Point","coordinates":[10.68077,59.90598]}},{"properties":{"name":null,"description":"Posted by BeateBeate<a title=\"Built for Community Mapping\" href=\"http://www.platial.com\"><img src=\"http://media.geocommons.com/platial/images/logotype_small.jpg\"></a>","id":"a6d2qf0c8c42"},"type":"Feature","geometry":{"type":"Point","coordinates":[10.76797,59.9105]}},{"properties":{"name":null,"description":"Posted by Beate<a title=\"Built for Community Mapping\" href=\"http://www.platial.com\"><img src=\"http://media.geocommons.com/platial/images/logotype_small.jpg\"></a>","id":"a6d2qeywo5fd"},"type":"Feature","geometry":{"type":"Point","coordinates":[10.77046,59.9127]}},{"properties":{"name":null,"description":"Posted by BeateBeate<a title=\"Built for Community Mapping\" href=\"http://www.platial.com\"><img src=\"http://media.geocommons.com/platial/images/logotype_small.jpg\"></a>","id":"a6d2qetlc1lb"},"type":"Feature","geometry":{"type":"Point","coordinates":[10.76463,59.92831]}},{"properties":{"name":"Poly bodd 1","description":"Posted by Beate<a title=\"Built for Community Mapping\" href=\"http://www.platial.com\"><img src=\"http://media.geocommons.com/platial/images/logotype_small.jpg\"></a>","id":"a6d2qeq4gawj"},"type":"Feature","geometry":{"type":"Point","coordinates":[10.80878,59.89084]}},{"properties":{"name":"Poly bodd 2","description":"Posted by Beate<a title=\"Built for Community Mapping\" href=\"http://www.platial.com\"><img src=\"http://media.geocommons.com/platial/images/logotype_small.jpg\"></a>","id":"a6d2qeom2f2j"},"type":"Feature","geometry":{"type":"Point","coordinates":[10.77433,59.92175]}}],"is_temporal":false,"author":{"url":"http://www.platial.com/map/242038","metadata":null,"contact_name":"beate","contact_address":null,"source":"platial:beate","contact_phone":null},"source":"http://www.platial.com/map/242038","pagination":{"sort":null,"start":0,"total":12,"limit":1000000},"state":"complete","tags":"platial,platial:id=242038,platial:user=beate","published":"2010-04-26T16:00:00Z","id":46250}