{"type":"FeatureCollection","data_type":"Dataset","url_type":null,"permissions":[{"permissions":{"download":true,"view":true},"group_id":"everyone"}],"classification":null,"title":"\ngiswalker's places\n","count":11,"stream_id":47038,"contributor":{"url":"http://geocommons.com/users/11444","name":"platial"},"data_attributes":null,"calculation_params":null,"icon_link":null,"link":"http://geocommons.com/overlays/47038.json","extent":[-122.846,42.4315,-71.4688,45.373],"geometry_types":["point"],"unique_name":null,"name":"\ngiswalker's places\n","feature_count":11,"description":"\nA Map by Giswalker\n\n\n","next_feature":null,"is_raster":false,"short_classification":"Y","stats":{},"features":[{"properties":{"name":null,"description":"Posted by Giswalker<a title=\"Built for Community Mapping\" href=\"http://www.platial.com\"><img src=\"http://media.geocommons.com/platial/images/logotype_small.jpg\"></a>","id":"a689vi429sro"},"type":"Feature","geometry":{"type":"Point","coordinates":[-71.46881,42.43157]}},{"properties":{"name":null,"description":"Posted by Giswalker<a title=\"Built for Community Mapping\" href=\"http://www.platial.com\"><img src=\"http://media.geocommons.com/platial/images/logotype_small.jpg\"></a>","id":"a689vi82q96y"},"type":"Feature","geometry":{"type":"Point","coordinates":[-71.46881,42.43157]}},{"properties":{"name":null,"description":"Posted by Giswalker<a title=\"Built for Community Mapping\" href=\"http://www.platial.com\"><img src=\"http://media.geocommons.com/platial/images/logotype_small.jpg\"></a>","id":"a689vidf8db9"},"type":"Feature","geometry":{"type":"Point","coordinates":[-71.46971,42.43261]}},{"properties":{"name":null,"description":"Posted by Giswalker<a title=\"Built for Community Mapping\" href=\"http://www.platial.com\"><img src=\"http://media.geocommons.com/platial/images/logotype_small.jpg\"></a>","id":"a689vi085ba8"},"type":"Feature","geometry":{"type":"Point","coordinates":[-71.47134,42.43147]}},{"properties":{"name":null,"description":"Posted by Giswalker<a title=\"Built for Community Mapping\" href=\"http://www.platial.com\"><img src=\"http://media.geocommons.com/platial/images/logotype_small.jpg\"></a>","id":"a689vi4i8rfm"},"type":"Feature","geometry":{"type":"Point","coordinates":[-122.83989,45.36011]}},{"properties":{"name":null,"description":"Posted by Giswalker<a title=\"Built for Community Mapping\" href=\"http://www.platial.com\"><img src=\"http://media.geocommons.com/platial/images/logotype_small.jpg\"></a>","id":"a689vi8o1ane"},"type":"Feature","geometry":{"type":"Point","coordinates":[-122.8244,45.37144]}},{"properties":{"name":null,"description":"Posted by Giswalker<a title=\"Built for Community Mapping\" href=\"http://www.platial.com\"><img src=\"http://media.geocommons.com/platial/images/logotype_small.jpg\"></a>","id":"a689vi3ndlv6"},"type":"Feature","geometry":{"type":"Point","coordinates":[-122.82376,45.37301]}},{"properties":{"name":null,"description":"Posted by Giswalker<a title=\"Built for Community Mapping\" href=\"http://www.platial.com\"><img src=\"http://media.geocommons.com/platial/images/logotype_small.jpg\"></a>","id":"a689vi945eao"},"type":"Feature","geometry":{"type":"Point","coordinates":[-122.84294,45.3618]}},{"properties":{"name":null,"description":"Posted by Giswalker<a title=\"Built for Community Mapping\" href=\"http://www.platial.com\"><img src=\"http://media.geocommons.com/platial/images/logotype_small.jpg\"></a>","id":"a689vi2hzrj9"},"type":"Feature","geometry":{"type":"Point","coordinates":[-122.83989,45.36011]}},{"properties":{"name":null,"description":"Posted by Giswalker<a title=\"Built for Community Mapping\" href=\"http://www.platial.com\"><img src=\"http://media.geocommons.com/platial/images/logotype_small.jpg\"></a>","id":"a689vi2yxqh7"},"type":"Feature","geometry":{"type":"Point","coordinates":[-122.8244,45.37144]}},{"properties":{"name":null,"description":"Posted by Giswalker<a title=\"Built for Community Mapping\" href=\"http://www.platial.com\"><img src=\"http://media.geocommons.com/platial/images/logotype_small.jpg\"></a>","id":"a689vi3btrcq"},"type":"Feature","geometry":{"type":"Point","coordinates":[-122.84629,45.36035]}}],"is_temporal":false,"author":{"url":"http://www.platial.com/map/250227","metadata":null,"contact_name":"giswalker","contact_address":null,"source":"platial:giswalker","contact_phone":null},"source":"http://www.platial.com/map/250227","pagination":{"sort":null,"start":0,"total":11,"limit":1000000},"state":"complete","tags":"platial,platial:id=250227,platial:user=giswalker","published":"2010-04-27T16:00:00Z","id":47038}