{"type":"FeatureCollection","data_type":"Dataset","url_type":null,"permissions":[{"permissions":{"download":true,"view":true},"group_id":"everyone"}],"classification":null,"title":"\nsevilla\n","count":10,"stream_id":47694,"contributor":{"url":"http://geocommons.com/users/11444","name":"platial"},"data_attributes":null,"calculation_params":null,"icon_link":null,"link":"http://geocommons.com/overlays/47694.json","extent":[-6.01617,37.3935,-5.9616,37.4007],"geometry_types":["point"],"unique_name":null,"name":"\nsevilla\n","feature_count":10,"description":"\nA Map by Javimarsan\n\n\n","next_feature":null,"is_raster":false,"short_classification":"Y","stats":{},"features":[{"properties":{"name":null,"description":"Posted by Javimarsan<a title=\"Built for Community Mapping\" href=\"http://www.platial.com\"><img src=\"http://media.geocommons.com/platial/images/logotype_small.jpg\"></a>","id":"a6452ztf8c6f"},"type":"Feature","geometry":{"type":"Point","coordinates":[-5.98996,37.39707]}},{"properties":{"name":null,"description":"Posted by Javimarsan<a title=\"Built for Community Mapping\" href=\"http://www.platial.com\"><img src=\"http://media.geocommons.com/platial/images/logotype_small.jpg\"></a>","id":"a6452zulotxs"},"type":"Feature","geometry":{"type":"Point","coordinates":[-5.98996,37.39707]}},{"properties":{"name":null,"description":"Posted by Javimarsan<a title=\"Built for Community Mapping\" href=\"http://www.platial.com\"><img src=\"http://media.geocommons.com/platial/images/logotype_small.jpg\"></a>","id":"a6452zuri8m6"},"type":"Feature","geometry":{"type":"Point","coordinates":[-5.98996,37.39707]}},{"properties":{"name":null,"description":"Posted by Javimarsan<a title=\"Built for Community Mapping\" href=\"http://www.platial.com\"><img src=\"http://media.geocommons.com/platial/images/logotype_small.jpg\"></a>","id":"a6452zs5z4eu"},"type":"Feature","geometry":{"type":"Point","coordinates":[-5.98815,37.39778]}},{"properties":{"name":null,"description":"Posted by Javimarsan<a title=\"Built for Community Mapping\" href=\"http://www.platial.com\"><img src=\"http://media.geocommons.com/platial/images/logotype_small.jpg\"></a>","id":"a6452zv9wa7m"},"type":"Feature","geometry":{"type":"Point","coordinates":[-6.01617,37.39587]}},{"properties":{"name":null,"description":"Posted by Javimarsan<a title=\"Built for Community Mapping\" href=\"http://www.platial.com\"><img src=\"http://media.geocommons.com/platial/images/logotype_small.jpg\"></a>","id":"a6452zw4nu63"},"type":"Feature","geometry":{"type":"Point","coordinates":[-5.99212,37.40073]}},{"properties":{"name":null,"description":"Posted by Javimarsan<a title=\"Built for Community Mapping\" href=\"http://www.platial.com\"><img src=\"http://media.geocommons.com/platial/images/logotype_small.jpg\"></a>","id":"a645302qgfjx"},"type":"Feature","geometry":{"type":"Point","coordinates":[-5.98996,37.39707]}},{"properties":{"name":null,"description":"Posted by Javimarsan<a title=\"Built for Community Mapping\" href=\"http://www.platial.com\"><img src=\"http://media.geocommons.com/platial/images/logotype_small.jpg\"></a>","id":"a645301997bk"},"type":"Feature","geometry":{"type":"Point","coordinates":[-5.9616,37.39352]}},{"properties":{"name":null,"description":"Posted by Javimarsan<a title=\"Built for Community Mapping\" href=\"http://www.platial.com\"><img src=\"http://media.geocommons.com/platial/images/logotype_small.jpg\"></a>","id":"a645302wim3c"},"type":"Feature","geometry":{"type":"Point","coordinates":[-5.9616,37.39352]}},{"properties":{"name":null,"description":"Posted by Javimarsan<a title=\"Built for Community Mapping\" href=\"http://www.platial.com\"><img src=\"http://media.geocommons.com/platial/images/logotype_small.jpg\"></a>","id":"a6452zzt7r68"},"type":"Feature","geometry":{"type":"Point","coordinates":[-5.9616,37.39352]}}],"is_temporal":false,"author":{"url":"http://www.platial.com/map/30055","metadata":null,"contact_name":"javimarsan","contact_address":null,"source":"platial:javimarsan","contact_phone":null},"source":"http://www.platial.com/map/30055","pagination":{"sort":null,"start":0,"total":10,"limit":1000000},"state":"complete","tags":"platial,platial:id=30055,platial:user=javimarsan","published":"2010-04-27T16:00:00Z","id":47694}