{"type":"FeatureCollection","data_type":"Dataset","url_type":null,"permissions":[{"permissions":{"download":true,"view":true},"group_id":"everyone"}],"classification":null,"title":"\nLayer of Beaches and Swimming Holes\n","count":4,"stream_id":47859,"contributor":{"url":"http://geocommons.com/users/11444","name":"platial"},"data_attributes":null,"calculation_params":null,"icon_link":null,"link":"http://geocommons.com/overlays/47859.json","extent":[-122.883,38.5065,-69.9955,42.8196],"geometry_types":["point"],"unique_name":null,"name":"\nLayer of Beaches and Swimming Holes\n","feature_count":4,"description":"\nA Map by System\n\n\n","next_feature":null,"is_raster":false,"short_classification":"Y","stats":{},"features":[{"properties":{"name":"Coney Island - Brighton Beach","description":"Posted by <a title=\"http://blogs.law.harvard.edu/busybody/\" href=\"http://blogs.law.harvard.edu/busybody/\">Nakedbrunch</a><img src=\"http://media.geocommons.com/platial/images/categories/ICON_recreation_verD.gif\"> <img src=\"http://media.geocommons.com/platial/images/categories/ICON_nature_verD.gif\"> Sun, sand, surf, the Cyclone and the incomparable Nathan\\'s!<a title=\"Built for Community Mapping\" href=\"http://www.platial.com\"><img src=\"http://media.geocommons.com/platial/images/logotype_small.jpg\"></a>","id":"a63awv94h0tn"},"type":"Feature","geometry":{"type":"Point","coordinates":[-73.96133,40.57641]}},{"properties":{"name":"Newcomb Hollow Beach","description":"Posted by <a title=\"http://blogs.law.harvard.edu/busybody/\" href=\"http://blogs.law.harvard.edu/busybody/\">Nakedbrunch</a><img src=\"http://media.geocommons.com/platial/img/2008/06/0/Picture_554.png\"><img src=\"http://media.geocommons.com/platial/images/categories/ICON_recreation_verD.gif\"> <img src=\"http://media.geocommons.com/platial/images/categories/ICON_nature_verD.gif\"> Wellfleet, Mass.<a title=\"Built for Community Mapping\" href=\"http://www.platial.com\"><img src=\"http://media.geocommons.com/platial/images/logotype_small.jpg\"></a>","id":"a63awv6jqjid"},"type":"Feature","geometry":{"type":"Point","coordinates":[-69.99551,41.96255]}},{"properties":{"name":"The Ledges","description":"Posted by <a title=\"http://blogs.law.harvard.edu/busybody/\" href=\"http://blogs.law.harvard.edu/busybody/\">Nakedbrunch</a>Harriman Reservoir, Wilmington, VT<a title=\"Built for Community Mapping\" href=\"http://www.platial.com\"><img src=\"http://media.geocommons.com/platial/images/logotype_small.jpg\"></a>","id":"a63awv1vvo0l"},"type":"Feature","geometry":{"type":"Point","coordinates":[-72.87369,42.81958]}},{"properties":{"name":"Wohler Bridge","description":"Posted by <a title=\"http://blogs.law.harvard.edu/busybody/\" href=\"http://blogs.law.harvard.edu/busybody/\">Nakedbrunch</a>Guerneville, Sonoma County, CA<a title=\"Built for Community Mapping\" href=\"http://www.platial.com\"><img src=\"http://media.geocommons.com/platial/images/logotype_small.jpg\"></a>","id":"a63awuz3kk02"},"type":"Feature","geometry":{"type":"Point","coordinates":[-122.88315,38.50653]}}],"is_temporal":false,"author":{"url":"http://www.platial.com/map/112091","metadata":null,"contact_name":"system","contact_address":null,"source":"platial:system","contact_phone":null},"source":"http://www.platial.com/map/112091","pagination":{"sort":null,"start":0,"total":4,"limit":1000000},"state":"complete","tags":"platial,platial:id=112091,platial:user=system","published":"2010-04-27T16:00:00Z","id":47859}