{"type":"FeatureCollection","data_type":"Dataset","url_type":null,"permissions":[{"permissions":{"download":true,"view":true},"group_id":"everyone"}],"classification":null,"title":"\nbriconcella's places\n","count":10,"stream_id":49375,"contributor":{"url":"http://geocommons.com/users/11444","name":"platial"},"data_attributes":null,"calculation_params":null,"icon_link":null,"link":"http://geocommons.com/overlays/49375.json","extent":[-79.6357,33.6604,10.5029,48.8885],"geometry_types":["point"],"unique_name":null,"name":"\nbriconcella's places\n","feature_count":10,"description":"\nA Map by Briconcella\n\n\n","next_feature":null,"is_raster":false,"short_classification":"Y","stats":{},"features":[{"properties":{"name":null,"description":"Posted by Briconcella<a title=\"Built for Community Mapping\" href=\"http://www.platial.com\"><img src=\"http://media.geocommons.com/platial/images/logotype_small.jpg\"></a>","id":"a63fd8vplbrp"},"type":"Feature","geometry":{"type":"Point","coordinates":[2.27063,48.88851]}},{"properties":{"name":null,"description":"Posted by Briconcella<a title=\"Built for Community Mapping\" href=\"http://www.platial.com\"><img src=\"http://media.geocommons.com/platial/images/logotype_small.jpg\"></a>","id":"a63fd8v7qg05"},"type":"Feature","geometry":{"type":"Point","coordinates":[-79.63571,39.21314]}},{"properties":{"name":null,"description":"Posted by Briconcella<a title=\"Built for Community Mapping\" href=\"http://www.platial.com\"><img src=\"http://media.geocommons.com/platial/images/logotype_small.jpg\"></a>","id":"a63fd8x5n012"},"type":"Feature","geometry":{"type":"Point","coordinates":[2.36755,48.86031]}},{"properties":{"name":null,"description":"Posted by Briconcella<a title=\"Built for Community Mapping\" href=\"http://www.platial.com\"><img src=\"http://media.geocommons.com/platial/images/logotype_small.jpg\"></a>","id":"a63fd8pkkev7"},"type":"Feature","geometry":{"type":"Point","coordinates":[2.36755,48.86031]}},{"properties":{"name":null,"description":"Posted by Briconcella<a title=\"Built for Community Mapping\" href=\"http://www.platial.com\"><img src=\"http://media.geocommons.com/platial/images/logotype_small.jpg\"></a>","id":"a63fd8m8cimw"},"type":"Feature","geometry":{"type":"Point","coordinates":[2.36755,48.86031]}},{"properties":{"name":null,"description":"Posted by Briconcella<a title=\"Built for Community Mapping\" href=\"http://www.platial.com\"><img src=\"http://media.geocommons.com/platial/images/logotype_small.jpg\"></a>","id":"a63fd8nqtwab"},"type":"Feature","geometry":{"type":"Point","coordinates":[2.36755,48.86031]}},{"properties":{"name":null,"description":"Posted by Briconcella<a title=\"Built for Community Mapping\" href=\"http://www.platial.com\"><img src=\"http://media.geocommons.com/platial/images/logotype_small.jpg\"></a>","id":"a63fd8qmjwna"},"type":"Feature","geometry":{"type":"Point","coordinates":[2.10938,41.36032]}},{"properties":{"name":null,"description":"Posted by Briconcella<a title=\"Built for Community Mapping\" href=\"http://www.platial.com\"><img src=\"http://media.geocommons.com/platial/images/logotype_small.jpg\"></a>","id":"a63fd8yx1emx"},"type":"Feature","geometry":{"type":"Point","coordinates":[-7.34985,33.66035]}},{"properties":{"name":null,"description":"Posted by Briconcella<a title=\"Built for Community Mapping\" href=\"http://www.platial.com\"><img src=\"http://media.geocommons.com/platial/images/logotype_small.jpg\"></a>","id":"a63fd8lx6pg5"},"type":"Feature","geometry":{"type":"Point","coordinates":[10.50293,36.63316]}},{"properties":{"name":null,"description":"Posted by Briconcella<a title=\"Built for Community Mapping\" href=\"http://www.platial.com\"><img src=\"http://media.geocommons.com/platial/images/logotype_small.jpg\"></a>","id":"a63fd8m1drxf"},"type":"Feature","geometry":{"type":"Point","coordinates":[2.36481,48.86471]}}],"is_temporal":false,"author":{"url":"http://www.platial.com/map/227685","metadata":null,"contact_name":"briconcella","contact_address":null,"source":"platial:briconcella","contact_phone":null},"source":"http://www.platial.com/map/227685","pagination":{"sort":null,"start":0,"total":10,"limit":1000000},"state":"complete","tags":"platial,platial:id=227685,platial:user=briconcella","published":"2010-04-27T16:00:00Z","id":49375}