{"type":"FeatureCollection","data_type":"Dataset","url_type":null,"permissions":[{"permissions":{"download":true,"view":true},"group_id":"everyone"}],"classification":null,"title":"\n@a5y\n","count":10,"stream_id":49517,"contributor":{"url":"http://geocommons.com/users/11444","name":"platial"},"data_attributes":null,"calculation_params":null,"icon_link":null,"link":"http://geocommons.com/overlays/49517.json","extent":[-6.93657,52.8273,-6.25254,53.3909],"geometry_types":["point"],"unique_name":null,"name":"\n@a5y\n","feature_count":10,"description":"\nA Map by Afivey\n\n\n","next_feature":null,"is_raster":false,"short_classification":"Y","stats":{},"features":[{"properties":{"name":null,"description":"Posted by AfiveyMy window\nSeptember 2006-2007<a title=\"Built for Community Mapping\" href=\"http://www.platial.com\"><img src=\"http://media.geocommons.com/platial/images/logotype_small.jpg\"></a>","id":"a7ma3ax6e665"},"type":"Feature","geometry":{"type":"Point","coordinates":[-6.93657,52.82726]}},{"properties":{"name":null,"description":"Posted by AfiveyGraffiti Wall.<a title=\"Built for Community Mapping\" href=\"http://www.platial.com\"><img src=\"http://media.geocommons.com/platial/images/logotype_small.jpg\"></a>","id":"a7ma3asa7n5y"},"type":"Feature","geometry":{"type":"Point","coordinates":[-6.36177,53.38267]}},{"properties":{"name":null,"description":"Posted by AfiveyGraffiti Wall.<a title=\"Built for Community Mapping\" href=\"http://www.platial.com\"><img src=\"http://media.geocommons.com/platial/images/logotype_small.jpg\"></a>","id":"a7ma3b412oi1"},"type":"Feature","geometry":{"type":"Point","coordinates":[-6.35767,53.38205]}},{"properties":{"name":null,"description":"Posted by AfiveyFingal Library.<a title=\"Built for Community Mapping\" href=\"http://www.platial.com\"><img src=\"http://media.geocommons.com/platial/images/logotype_small.jpg\"></a>","id":"a7ma3aydovt1"},"type":"Feature","geometry":{"type":"Point","coordinates":[-6.39092,53.39089]}},{"properties":{"name":null,"description":"Posted by AfiveyBarnies Coffeeshop R.I.P.\n200?-2007<a title=\"Built for Community Mapping\" href=\"http://www.platial.com\"><img src=\"http://media.geocommons.com/platial/images/logotype_small.jpg\"></a>","id":"a7ma3b076dqp"},"type":"Feature","geometry":{"type":"Point","coordinates":[-6.25954,53.34648]}},{"properties":{"name":null,"description":"Posted by AfiveyB.C.F.E. Arts block.<a title=\"Built for Community Mapping\" href=\"http://www.platial.com\"><img src=\"http://media.geocommons.com/platial/images/logotype_small.jpg\"></a>","id":"a7ma3ardceax"},"type":"Feature","geometry":{"type":"Point","coordinates":[-6.35008,53.34501]}},{"properties":{"name":null,"description":"Posted by Afivey78A Bus stop<a title=\"Built for Community Mapping\" href=\"http://www.platial.com\"><img src=\"http://media.geocommons.com/platial/images/logotype_small.jpg\"></a>","id":"a7ma3b1uz8jw"},"type":"Feature","geometry":{"type":"Point","coordinates":[-6.34733,53.34252]}},{"properties":{"name":null,"description":"Posted by AfiveyB.C.F.E. Main block<a title=\"Built for Community Mapping\" href=\"http://www.platial.com\"><img src=\"http://media.geocommons.com/platial/images/logotype_small.jpg\"></a>","id":"a7ma3b13jfjp"},"type":"Feature","geometry":{"type":"Point","coordinates":[-6.35233,53.3405]}},{"properties":{"name":null,"description":"Posted by AfiveyBus Arás bus station<a title=\"Built for Community Mapping\" href=\"http://www.platial.com\"><img src=\"http://media.geocommons.com/platial/images/logotype_small.jpg\"></a>","id":"a7ma3b2uu0oc"},"type":"Feature","geometry":{"type":"Point","coordinates":[-6.25254,53.3498]}},{"properties":{"name":null,"description":"Posted by AfiveyGraffiti wall<a title=\"Built for Community Mapping\" href=\"http://www.platial.com\"><img src=\"http://media.geocommons.com/platial/images/logotype_small.jpg\"></a>","id":"a7ma3avusoyn"},"type":"Feature","geometry":{"type":"Point","coordinates":[-6.36424,53.38266]}}],"is_temporal":false,"author":{"url":"http://www.platial.com/map/27664","metadata":null,"contact_name":"afivey","contact_address":null,"source":"platial:afivey","contact_phone":null},"source":"http://www.platial.com/map/27664","pagination":{"sort":null,"start":0,"total":10,"limit":1000000},"state":"complete","tags":"platial,platial:id=27664,platial:user=afivey","published":"2010-04-28T16:00:00Z","id":49517}