{"type":"FeatureCollection","data_type":"Dataset","url_type":null,"permissions":[{"permissions":{"download":true,"view":true},"group_id":"everyone"}],"classification":null,"title":"\nDominion\n","count":2,"stream_id":49895,"contributor":{"url":"http://geocommons.com/users/11444","name":"platial"},"data_attributes":null,"calculation_params":null,"icon_link":null,"link":"http://geocommons.com/overlays/49895.json","extent":[-79.6835,43.5794,-79.5778,43.5903],"geometry_types":["point"],"unique_name":null,"name":"\nDominion\n","feature_count":2,"description":"\nA Map by Ulhasvashi\n\nDominion, Mississauga\n","next_feature":null,"is_raster":false,"short_classification":"Y","stats":{},"features":[{"properties":{"name":null,"description":"Posted by Ulhasvashi<a title=\"Built for Community Mapping\" href=\"http://www.platial.com\"><img src=\"http://media.geocommons.com/platial/images/logotype_small.jpg\"></a>","id":"a6dwfrfl48wb"},"type":"Feature","geometry":{"type":"Point","coordinates":[-79.683502,43.579366]}},{"properties":{"name":null,"description":"Posted by Ulhasvashi<a title=\"Built for Community Mapping\" href=\"http://www.platial.com\"><img src=\"http://media.geocommons.com/platial/images/logotype_small.jpg\"></a>","id":"a6dwfrqj82jm"},"type":"Feature","geometry":{"type":"Point","coordinates":[-79.577786,43.59031]}}],"is_temporal":false,"author":{"url":"http://www.platial.com/map/9979","metadata":null,"contact_name":"ulhasvashi","contact_address":null,"source":"platial:ulhasvashi","contact_phone":null},"source":"http://www.platial.com/map/9979","pagination":{"sort":null,"start":0,"total":2,"limit":1000000},"state":"complete","tags":"platial,platial:id=9979,platial:user=ulhasvashi","published":"2010-04-28T16:00:00Z","id":49895}