{"type":"FeatureCollection","state":"complete","icon_link":null,"title":"SPS-10 Section Locations UPLOAD FILE","count":12,"geometry_types":["point"],"unique_name":null,"pagination":{"sort":null,"start":0,"limit":1000000,"total":12},"feature_count":12,"data_type":"Dataset","stats":{"latitude":{"max":50.225806,"mean":38.47549475,"stdev":6.63465864424452,"median":35.50795,"min":30.88076,"variance":44.0186953256486},"longitude":{"max":-79.322806,"mean":-102.497488666667,"stdev":14.5812821429104,"median":-99.442806,"min":-120.687381,"variance":212.613788931156}},"next_feature":null,"is_raster":false,"link":"http://geocommons.com/overlays/501592.json","short_classification":"Y","name":"SPS-10 Section Locations UPLOAD FILE","is_temporal":false,"description":"","permissions":[{"group_id":"everyone","permissions":{"download":true,"view":true}}],"classification":null,"published":"2015-08-29T13:38:18-04:00","extent":[-120.687,30.8808,-79.3228,50.2258],"features":[{"properties":{"latitude":34.98873,"longitude":-105.23389,"id":"aujqlqnnrdwy"},"type":"Feature","geometry":{"type":"Point","coordinates":[-105.23389,34.98873]}},{"properties":{"latitude":33.54227,"longitude":-99.3378,"id":"aujqlqqv6jkf"},"type":"Feature","geometry":{"type":"Point","coordinates":[-99.3378,33.54227]}},{"properties":{"latitude":35.50795,"longitude":-97.7907,"id":"aujqlqkjij9i"},"type":"Feature","geometry":{"type":"Point","coordinates":[-97.7907,35.50795]}},{"properties":{"latitude":31.71415,"longitude":-81.72592,"id":"aujqlqw8hvfm"},"type":"Feature","geometry":{"type":"Point","coordinates":[-81.72592,31.71415]}},{"properties":{"latitude":30.88076,"longitude":-85.52525,"id":"aujqlqyfzkh8"},"type":"Feature","geometry":{"type":"Point","coordinates":[-85.52525,30.88076]}},{"properties":{"latitude":47.695452,"longitude":-117.200697,"id":"aujqlqq9flew"},"type":"Feature","geometry":{"type":"Point","coordinates":[-117.200697,47.695452]}},{"properties":{"latitude":39.231536,"longitude":-119.810669,"id":"aujqlqr419mn"},"type":"Feature","geometry":{"type":"Point","coordinates":[-119.810669,39.231536]}},{"properties":{"latitude":34.991056,"longitude":-109.963056,"id":"aujqlqriab3l"},"type":"Feature","geometry":{"type":"Point","coordinates":[-109.963056,34.991056]}},{"properties":{"latitude":33.651944,"longitude":-113.928889,"id":"aujqlqnuj00q"},"type":"Feature","geometry":{"type":"Point","coordinates":[-113.928889,33.651944]}},{"properties":{"latitude":45.136089,"longitude":-120.687381,"id":"aujqlqltbmtx"},"type":"Feature","geometry":{"type":"Point","coordinates":[-120.687381,45.136089]}},{"properties":{"latitude":50.225806,"longitude":-99.442806,"id":"aujqlqrm23c1"},"type":"Feature","geometry":{"type":"Point","coordinates":[-99.442806,50.225806]}},{"properties":{"latitude":44.140194,"longitude":-79.322806,"id":"aujqlqmfrraz"},"type":"Feature","geometry":{"type":"Point","coordinates":[-79.322806,44.140194]}}],"url_type":null,"author":{"metadata":"","url":"","contact_name":"","contact_address":"","contact_phone":"","source":""},"source":"","stream_id":501592,"tags":"","contributor":{"url":"http://geocommons.com/users/112948","name":"TheLos"},"id":501592,"data_attributes":null,"calculation_params":null}