{"type":"FeatureCollection","data_type":"Dataset","url_type":null,"permissions":[{"permissions":{"download":true,"view":true},"group_id":"everyone"}],"classification":null,"title":"Justin's Google Latitude Location History","count":2,"stream_id":51250,"contributor":{"url":"http://geocommons.com/users/13198","name":"justinblase"},"data_attributes":null,"calculation_params":null,"icon_link":null,"link":"http://geocommons.com/overlays/51250.json","extent":[-93.1311,44.802,-93.0748,44.8479],"geometry_types":["point"],"unique_name":null,"name":"Justin's Google Latitude Location History","feature_count":2,"description":"The history of Google latitude locations for Justin Blase","next_feature":null,"is_raster":false,"short_classification":"Y","stats":{"accuracy":{"max":2941,"mean":1545.5,"variance":3894840.5,"stdev":1973.53502629165,"min":150,"median":2941}},"features":[{"properties":{"timestamp":"1273036604464","name":{"end_time":"2010/05/05 00:16:45 -0400","original":"Wed May 05 00:16:44 -0400 2010","granularity":"sec","time":"2010/05/05 00:16:44 -0400"},"accuracy":2941,"geo_score":0.592,"description":"70th St E, Inver Grove Heights, MN","id":"a62vr0qm1y4l","geo_precision":"street"},"type":"Feature","geometry":{"type":"Point","coordinates":[-93.074767,44.847864]}},{"properties":{"timestamp":"1273038156560","name":{"end_time":"2010/05/05 00:42:37 -0400","original":"Wed May 05 00:42:36 -0400 2010","granularity":"sec","time":"2010/05/05 00:42:36 -0400"},"accuracy":150,"geo_score":0.714,"description":"Curry Trail, Eagan, MN","id":"a62vr0k7j3s2","geo_precision":"street"},"type":"Feature","geometry":{"type":"Point","coordinates":[-93.131053,44.801992]}}],"is_temporal":true,"author":{"url":"","metadata":"","contact_name":"","contact_address":"","source":"","contact_phone":""},"source":"","pagination":{"sort":null,"start":0,"total":2,"limit":1000000},"state":"complete","tags":"blase,google,justin,latitude","published":"2010-05-05T05:53:51Z","id":51250}