{"type":"FeatureCollection","data_type":"Dataset","url_type":null,"permissions":[{"permissions":{"download":true,"view":true},"group_id":"everyone"}],"classification":null,"title":"Depot","count":2,"stream_id":53445,"contributor":{"url":"http://geocommons.com/users/12296","name":"hoangchi"},"data_attributes":null,"calculation_params":null,"icon_link":null,"link":"http://geocommons.com/overlays/53445.json","extent":[-121.5,38.5615,-121.446,38.5838],"geometry_types":["point"],"unique_name":null,"name":"Depot","feature_count":2,"description":"","next_feature":null,"is_raster":false,"short_classification":"Y","stats":{},"features":[{"properties":{"name":"4818 Folsom Blvd","description":"Sacramento, CA 95819<img src=\"http://cbk0.google.com/cbk?output=thumbnail&amp;w=90&amp;h=68&amp;ll=38.561534,-121.446122\">","id":"a662uliwyyf0"},"type":"Feature","geometry":{"type":"Point","coordinates":[-121.446121,38.561535]}},{"properties":{"name":"Depot Bikes and Cafes","description":null,"id":"a662uljrutij"},"type":"Feature","geometry":{"type":"Point","coordinates":[-121.499687,38.583794]}}],"is_temporal":false,"author":{"url":"","metadata":"","contact_name":"","contact_address":"","source":"","contact_phone":""},"source":"","pagination":{"sort":null,"start":0,"total":2,"limit":1000000},"state":"complete","tags":"","published":"2014-08-10T13:29:01-04:00","id":53445}