{"type":"FeatureCollection","url":"http://votegeorgia.ge/rssbuilder/georss/?lang=eng&cat=3","data_type":"Data Feed","url_type":"rss","permissions":[{"permissions":{"download":true,"view":true},"group_id":"everyone"}],"classification":null,"title":"Campaigns and Media Usage - Pre-elections Period","count":0,"stream_id":54418,"contributor":{"url":"http://geocommons.com/users/12886","name":"crrccenters"},"data_attributes":null,"calculation_params":null,"icon_link":null,"link":"http://geocommons.com/overlays/54418.json","extent":[41.6428,41.6404,44.7757,41.71],"geometry_types":["point"],"unique_name":null,"name":"Campaigns and Media Usage - Pre-elections Period","feature_count":0,"description":"","next_feature":null,"is_raster":false,"short_classification":"Y","stats":{},"features":[{"properties":{"title":"Restriction of Live TV Debates in Batumi","description":"Restriction of Live TV Debates in BatumiThe issue with free use of media in # 79 Batumi election district is particularly important. The Ajara TV restricts any live TV debates. According to the information of ISFED’s LTO not only political parties are restricted from organizing the talk-shows via the local TV, but the representatives of the civil society as well. For example, when ISFED Ajara-Guria coordinator applied to Ajara TV for arrangement of a special talk-show on TV for increasing voter awareness on elections, after citing many reasons and stretching the time, the TV refused to cooperate with the organization. Read more at: http://isfed.ge/pdf/isfed_election_update_I_eng.pdfTime: 2010-05-30 01:32:53Source: ISFEDCategory: Campaigns &amp; Media - Pre-electionDistrict: Batumi","link":"http://www.electionsportal.ge/","id":"a62z4k3oo3ad"},"type":"Feature","geometry":{"type":"Point","coordinates":[41.6427613046,41.6404394391]}},{"properties":{"title":"Pre-Election Environment Monitoring Report","description":"Pre-Election Environment Monitoring ReportOn April 23 GYLA published the first interim report on the pre-election campaign violations. GYLA is observing pre-election environment in Tbilisi and the following regions of Georgia:\r\nAdjara, Guria, Imereti, Shida Kartli, Kvemo Kartli, Kakheti, Mtskheta-Mtianeti and Tbilisi. Totally, the monitoring is carried out in the capital and 36 municipalities of the country. Read the report at: http://www.gyla.ge/attachments/712_GYLA%20shualeduri%20I%20ENG%2023.04.10.pdf.Time: 2010-05-29 22:08:03Source: GYLACategory: Campaigns &amp; Media - Pre-electionDistrict: Mtatsminda","link":"http://www.gyla.ge/","id":"a62z4k5nz4j7"},"type":"Feature","geometry":{"type":"Point","coordinates":[44.7757205445,41.7099972479]}}],"is_temporal":false,"author":{"url":"","metadata":"","contact_name":"","contact_address":"","source":"","contact_phone":""},"source":"","pagination":{"sort":null,"start":0,"total":0,"limit":1000000},"state":"complete","tags":"campaigns,elections,georgia,local,media,pre-elections","published":"2014-08-10T14:35:44-04:00","id":54418}