{"type":"FeatureCollection","data_type":"Dataset","url_type":null,"permissions":[{"permissions":{"download":true,"view":true},"group_id":"everyone"}],"classification":null,"title":"DChaptaw","count":3,"stream_id":55324,"contributor":{"url":"http://geocommons.com/users/14025","name":"jeremy.morley"},"data_attributes":null,"calculation_params":null,"icon_link":null,"link":"http://geocommons.com/overlays/55324.json","extent":[-149.362,41.6779,-0.61838,60.1196],"geometry_types":["point"],"unique_name":null,"name":"DChaptaw","feature_count":3,"description":"","next_feature":null,"is_raster":false,"short_classification":"Y","stats":{"latitude":{"max":60.1196,"mean":50.9938,"variance":85.05117823,"stdev":9.22231956885034,"min":41.6779,"median":51.1839},"woeid":{"max":2491103,"mean":1655556.33333333,"variance":2003483223142.33,"stdev":1415444.53199069,"min":21280,"median":2454286},"longitude":{"max":-0.61838,"mean":-75.6658266666667,"variance":5532.53557739213,"stdev":74.3810162433408,"min":-149.362,"median":-77.0171}},"features":[{"properties":{"name":"Godalming, England, GB","latitude":51.1839,"woeid":21280,"type":"Town","longitude":-0.61838,"id":"a6ey0s09dd0j"},"type":"Feature","geometry":{"type":"Point","coordinates":[-0.61838,51.1839]}},{"properties":{"name":"Morris Run, PA, US","latitude":41.6779,"woeid":2454286,"type":"Town","longitude":-77.0171,"id":"a6ey0rzahfkr"},"type":"Feature","geometry":{"type":"Point","coordinates":[-77.0171,41.6779]}},{"properties":{"name":"Seward, AK, US","latitude":60.1196,"woeid":2491103,"type":"Town","longitude":-149.362,"id":"a6ey0s7t0y25"},"type":"Feature","geometry":{"type":"Point","coordinates":[-149.362,60.1196]}}],"is_temporal":false,"author":{"url":"","metadata":"","contact_name":"","contact_address":"","source":"","contact_phone":""},"source":"","pagination":{"sort":null,"start":0,"total":3,"limit":1000000},"state":"complete","tags":"","published":"2014-08-10T15:50:51-04:00","id":55324}