{"type":"FeatureCollection","data_type":"Dataset","url_type":null,"permissions":[{"permissions":{"download":true,"view":true},"group_id":"everyone"}],"classification":null,"title":"DC and Atlanta","count":2,"stream_id":55839,"contributor":{"url":"http://geocommons.com/users/8","name":"derek"},"data_attributes":null,"calculation_params":null,"icon_link":null,"link":"http://geocommons.com/overlays/55839.json","extent":[-84.23,33.44,-77.02,38.53],"geometry_types":["point"],"unique_name":null,"name":"DC and Atlanta","feature_count":2,"description":"","next_feature":null,"is_raster":false,"short_classification":"Y","stats":{"latitude":{"max":38.53,"mean":35.985,"variance":12.95405,"stdev":3.59917351623953,"min":33.44,"median":38.53},"longitude":{"max":-77.02,"mean":-80.625,"variance":25.9920500000001,"stdev":5.09823989235501,"min":-84.23,"median":-77.02}},"features":[{"properties":{"name":"atlanta","latitude":33.44,"longitude":-84.23,"id":"a63nmtpm3b7s"},"type":"Feature","geometry":{"type":"Point","coordinates":[-84.23,33.44]}},{"properties":{"name":"dc","latitude":38.53,"longitude":-77.02,"id":"a63nmtxj18dm"},"type":"Feature","geometry":{"type":"Point","coordinates":[-77.02,38.53]}}],"is_temporal":false,"author":{"url":"","metadata":"","contact_name":"","contact_address":"","source":"","contact_phone":""},"source":"","pagination":{"sort":null,"start":0,"total":2,"limit":1000000},"state":"complete","tags":"","published":"2014-08-10T16:30:08-04:00","id":55839}