{"type":"FeatureCollection","data_type":"Dataset","url_type":null,"permissions":[{"permissions":{"download":true,"view":true},"group_id":"everyone"}],"classification":null,"title":"COMARCA DE MÁGINA","count":15,"stream_id":5662,"contributor":{"url":"http://geocommons.com/users/2395","name":"folio"},"data_attributes":null,"calculation_params":null,"icon_link":null,"link":"http://geocommons.com/overlays/5662.json","extent":[-3.69278,37.5397,-3.20011,37.864],"geometry_types":["point"],"unique_name":null,"name":"COMARCA DE MÁGINA","feature_count":15,"description":"Comarca de Mágina. Población 2007","next_feature":null,"is_raster":false,"short_classification":"Y","stats":{"lon":{"max":-3.200111,"mean":-3.47419726666667,"variance":0.0198673050753524,"stdev":0.140951428071348,"min":-3.69278,"median":-3.468246},"habitantes":{"max":12168,"mean":3056.66666666667,"variance":8170422.0952381,"stdev":2858.39502085315,"min":478,"median":2060},"mujeres":{"max":6082,"mean":1555.06666666667,"variance":2042838.35238095,"stdev":1429.2789624076,"min":244,"median":1023},"hombres":{"max":6086,"mean":1501.6,"variance":2044301.4,"stdev":1429.7906839814,"min":234,"median":1028},"lat":{"max":37.864012,"mean":37.742366,"variance":0.007447620224,"stdev":0.0862995957348585,"min":37.539677,"median":37.746829}},"features":[{"properties":{"lon":-3.468246,"habitantes":1272,"poblacion":"Albanchez","mujeres":658,"hombres":614,"id":"a645qo1xatm7","lat":37.802189},"type":"Feature","geometry":{"type":"Point","coordinates":[-3.468246,37.802189]}},{"properties":{"lon":-3.411255,"habitantes":3161,"poblacion":"Bedmar Garciez","mujeres":1589,"hombres":1572,"id":"a645qo7gbyp9","lat":37.864012},"type":"Feature","geometry":{"type":"Point","coordinates":[-3.411255,37.864012]}},{"properties":{"lon":-3.382072,"habitantes":1894,"poblacion":"Belmez de la Moraleda","mujeres":982,"hombres":912,"id":"a645qnxo4ucg","lat":37.729181},"type":"Feature","geometry":{"type":"Point","coordinates":[-3.382072,37.729181]}},{"properties":{"lon":-3.286285,"habitantes":2157,"poblacion":"Cabra del Santo Cristo","mujeres":1129,"hombres":1028,"id":"a645qochivt9","lat":37.715875},"type":"Feature","geometry":{"type":"Point","coordinates":[-3.286285,37.715875]}},{"properties":{"lon":-3.4552,"habitantes":2943,"poblacion":"Cambil","mujeres":1546,"hombres":1397,"id":"a645qo80wa5k","lat":37.72022},"type":"Feature","geometry":{"type":"Point","coordinates":[-3.4552,37.72022]}},{"properties":{"lon":-3.479919,"habitantes":1985,"poblacion":"Campillo de Arenas","mujeres":1017,"hombres":968,"id":"a645qo3502id","lat":37.695231},"type":"Feature","geometry":{"type":"Point","coordinates":[-3.479919,37.695231]}},{"properties":{"lon":-3.635788,"habitantes":1507,"poblacion":"Carcheles","mujeres":772,"hombres":735,"id":"a645qo78nepj","lat":37.658548},"type":"Feature","geometry":{"type":"Point","coordinates":[-3.635788,37.658548]}},{"properties":{"lon":-3.4552,"habitantes":6221,"poblacion":"Huelma","mujeres":3150,"hombres":3071,"id":"a645qodqwse0","lat":37.655558},"type":"Feature","geometry":{"type":"Point","coordinates":[-3.4552,37.655558]}},{"properties":{"lon":-3.476486,"habitantes":1489,"poblacion":"Jimena","mujeres":722,"hombres":767,"id":"a645qo9iw557","lat":37.846664},"type":"Feature","geometry":{"type":"Point","coordinates":[-3.476486,37.846664]}},{"properties":{"lon":-3.352203,"habitantes":12168,"poblacion":"Jodar","mujeres":6082,"hombres":6086,"id":"a645qo4fjcw5","lat":37.854254},"type":"Feature","geometry":{"type":"Point","coordinates":[-3.352203,37.854254]}},{"properties":{"lon":-3.69278,"habitantes":3678,"poblacion":"La Guardia","mujeres":1935,"hombres":1743,"id":"a645qo6srbwc","lat":37.746829},"type":"Feature","geometry":{"type":"Point","coordinates":[-3.69278,37.746829]}},{"properties":{"lon":-3.200111,"habitantes":478,"poblacion":"Larva","mujeres":244,"hombres":234,"id":"a645qo7kcnyp","lat":37.764201},"type":"Feature","geometry":{"type":"Point","coordinates":[-3.200111,37.764201]}},{"properties":{"lon":-3.653641,"habitantes":2060,"poblacion":"Noalejo","mujeres":1023,"hombres":1037,"id":"a645qo8yrdm3","lat":37.539677},"type":"Feature","geometry":{"type":"Point","coordinates":[-3.653641,37.539677]}},{"properties":{"lon":-3.653641,"habitantes":3172,"poblacion":"Pegalajar","mujeres":1628,"hombres":1544,"id":"a645qo0eug0w","lat":37.748458},"type":"Feature","geometry":{"type":"Point","coordinates":[-3.653641,37.748458]}},{"properties":{"lon":-3.510132,"habitantes":1665,"poblacion":"Torres","mujeres":849,"hombres":816,"id":"a645qo9icu21","lat":37.794593},"type":"Feature","geometry":{"type":"Point","coordinates":[-3.510132,37.794593]}}],"is_temporal":false,"author":{"url":"","metadata":"","contact_name":"","contact_address":"","source":"","contact_phone":""},"source":"","pagination":{"sort":null,"start":0,"total":15,"limit":1000000},"state":"complete","tags":"mágina","published":"2014-08-11T06:18:34-04:00","id":5662}