{"type":"FeatureCollection","data_type":"Dataset","url_type":null,"permissions":[{"permissions":{"download":true,"view":true},"group_id":"everyone"}],"classification":null,"title":"OpenLayers export","count":1,"stream_id":57588,"contributor":{"url":"http://geocommons.com/users/14521","name":"ariadne"},"data_attributes":null,"calculation_params":null,"icon_link":null,"link":"http://geocommons.com/overlays/57588.json","extent":[8.43793,40.6375,8.43793,40.6375],"geometry_types":["point"],"unique_name":null,"name":"OpenLayers export","feature_count":1,"description":"Exported on Fri Jul 02 2010 11:57:06 GMT 0200 (ora legale Europa occidentale)","next_feature":null,"is_raster":false,"short_classification":"Y","stats":{},"features":[{"properties":{"name":"Estrazione del sughero","description":"Localit Su Preideru","id":"a66elvo82s1i"},"type":"Feature","geometry":{"type":"Point","coordinates":[8.43793107816355,40.6375176371186]}}],"is_temporal":false,"author":{"url":"","metadata":"","contact_name":"","contact_address":"","source":"","contact_phone":""},"source":"","pagination":{"sort":null,"start":0,"total":1,"limit":1000000},"state":"complete","tags":"","published":"2014-08-10T18:38:54-04:00","id":57588}