{"type":"FeatureCollection","data_type":"Dataset","url_type":null,"permissions":[{"permissions":{"download":true,"view":true},"group_id":"everyone"}],"classification":null,"title":"STH_hospital location","count":1,"stream_id":57840,"contributor":{"url":"http://geocommons.com/users/14342","name":"koskinas"},"data_attributes":null,"calculation_params":null,"icon_link":null,"link":"http://geocommons.com/overlays/57840.json","extent":[-81.4982,41.1055,-81.4982,41.1055],"geometry_types":["point"],"unique_name":null,"name":"STH_hospital location","feature_count":1,"description":"location of STH (St. thomas hospital)\n\nsumma","next_feature":null,"is_raster":false,"short_classification":"Y","stats":{"geo_score":{"max":0.714,"min":0.714,"median":0.714}},"features":[{"properties":{"geo_score":0.714,"sth":"44310","id":"a6b6wct7cekk","geo_precision":"zip"},"type":"Feature","geometry":{"type":"Point","coordinates":[-81.498182,41.105505]}}],"is_temporal":false,"author":{"url":"","metadata":"","contact_name":"","contact_address":"","source":"","contact_phone":""},"source":"","pagination":{"sort":null,"start":0,"total":1,"limit":1000000},"state":"complete","tags":"","published":"2014-08-10T18:49:03-04:00","id":57840}