{"type":"FeatureCollection","data_type":"Dataset","url_type":null,"permissions":[{"permissions":{"download":true,"view":true},"group_id":"everyone"}],"classification":null,"title":"TestGeocode6","count":1,"stream_id":58086,"contributor":{"url":"http://geocommons.com/users/14486","name":"laural"},"data_attributes":null,"calculation_params":null,"icon_link":null,"link":"http://geocommons.com/overlays/58086.json","extent":[-76.993,38.8786,-76.993,38.8786],"geometry_types":["point"],"unique_name":null,"name":"TestGeocode6","feature_count":1,"description":"","next_feature":null,"is_raster":false,"short_classification":"Y","stats":{"lat":{"max":38.878606,"min":38.878606,"median":38.878606},"police district":{"max":1,"min":1,"median":1},"long":{"max":-76.99303,"min":-76.99303,"median":-76.99303}},"features":[{"properties":{"mobile radar camera locations (active locations vary)":"9th Street SE and I-695, Washington, DC","id":"a6djy1gpbhd4","lat":38.878606,"direction":"(eastbound)","police district":1,"long":-76.99303},"type":"Feature","geometry":{"type":"Point","coordinates":[-76.99303,38.878606]}}],"is_temporal":false,"author":{"url":"","metadata":"","contact_name":"","contact_address":"","source":"","contact_phone":""},"source":"","pagination":{"sort":null,"start":0,"total":1,"limit":1000000},"state":"complete","tags":"","published":"2014-08-10T18:59:42-04:00","id":58086}