{"type":"FeatureCollection","data_type":"Dataset","url_type":null,"permissions":[{"permissions":{"download":true,"view":true},"group_id":"everyone"}],"classification":null,"title":"Hubs","count":3,"stream_id":58952,"contributor":{"url":"http://geocommons.com/users/14796","name":"enome2"},"data_attributes":null,"calculation_params":null,"icon_link":null,"link":"http://geocommons.com/overlays/58952.json","extent":[-112.468,32.7253,-77.4878,39.0436],"geometry_types":["point"],"unique_name":null,"name":"Hubs","feature_count":3,"description":"","next_feature":null,"is_raster":false,"short_classification":"Y","stats":{"lat":{"max":39.04361,"mean":35.4362966666667,"variance":10.5828342832333,"stdev":3.25312684708625,"min":32.72528,"median":34.54},"long":{"max":-77.48778,"mean":-95.7587066666667,"variance":307.729639376133,"stdev":17.5422244705777,"min":-112.46778,"median":-97.32056}},"features":[{"properties":{"afss continuing facilities":"Ashburn (Hub)","id":"a6k48qw3icpq","lat":39.04361,"long":-77.48778,"state":"VA"},"type":"Feature","geometry":{"type":"Point","coordinates":[-77.48778,39.04361]}},{"properties":{"afss continuing facilities":"Fort Worth (Hub)","id":"a6k48r6usuia","lat":32.72528,"long":-97.32056,"state":"TX"},"type":"Feature","geometry":{"type":"Point","coordinates":[-97.32056,32.72528]}},{"properties":{"afss continuing facilities":"Prescott (Hub)","id":"a6k48qzpyeub","lat":34.54,"long":-112.46778,"state":"AZ"},"type":"Feature","geometry":{"type":"Point","coordinates":[-112.46778,34.54]}}],"is_temporal":false,"author":{"url":"","metadata":"","contact_name":"","contact_address":"","source":"","contact_phone":""},"source":"","pagination":{"sort":null,"start":0,"total":3,"limit":1000000},"state":"complete","tags":"","published":"2014-08-10T20:30:06-04:00","id":58952}