{"type":"FeatureCollection","data_type":"Dataset","url_type":null,"permissions":[{"permissions":{"download":true,"view":true},"group_id":"everyone"}],"classification":null,"title":"Australia Elections - National Party","count":4,"stream_id":59130,"contributor":{"url":"http://geocommons.com/users/12003","name":"LauraHale"},"data_attributes":null,"calculation_params":null,"icon_link":null,"link":"http://geocommons.com/overlays/59130.json","extent":[151.207,-36.8474,174.766,-27.9853],"geometry_types":["point"],"unique_name":null,"name":"Australia Elections - National Party","feature_count":4,"description":"","next_feature":null,"is_raster":false,"short_classification":"Y","stats":{"latitude":{"max":-27.9852778,"mean":-32.0695767,"variance":16.3152060310041,"stdev":4.03920858968735,"min":-36.847385,"median":-29.578505},"national party":{"max":3,"mean":1.75,"variance":0.916666666666667,"stdev":0.957427107756338,"min":1,"median":2},"longitude":{"max":174.765735,"mean":158.1068726,"variance":124.266206871733,"stdev":11.1474753586511,"min":151.207114,"median":153.3919444}},"features":[{"properties":{"city":"Auckland","latitude":-36.847385,"country":"New Zealand","national party":1,"longitude":174.765735,"id":"a69hhw7u5vrk","state":"Auckland"},"type":"Feature","geometry":{"type":"Point","coordinates":[174.765735,-36.847385]}},{"properties":{"city":"Cowper","latitude":-29.578505,"country":"Australia","national party":1,"longitude":153.062697,"id":"a69hhvzcnghe","state":"New South Wales"},"type":"Feature","geometry":{"type":"Point","coordinates":[153.062697,-29.578505]}},{"properties":{"city":"Gold Coast","latitude":-27.9852778,"country":"Australia","national party":2,"longitude":153.3919444,"id":"a69hhw8i14qn","state":"Queensland"},"type":"Feature","geometry":{"type":"Point","coordinates":[153.3919444,-27.9852778]}},{"properties":{"city":"Sydney","latitude":-33.867139,"country":"Australia","national party":3,"longitude":151.207114,"id":"a69hhw9o8wgo","state":"New South Wales"},"type":"Feature","geometry":{"type":"Point","coordinates":[151.207114,-33.867139]}}],"is_temporal":false,"author":{"url":"","metadata":"","contact_name":"","contact_address":"","source":"","contact_phone":""},"source":"","pagination":{"sort":null,"start":0,"total":4,"limit":1000000},"state":"complete","tags":"","published":"2014-08-10T20:41:40-04:00","id":59130}