{"type":"FeatureCollection","data_type":"Dataset","url_type":null,"permissions":[{"permissions":{"download":true,"view":true},"group_id":"everyone"}],"classification":null,"title":"Roster - Seniors","count":3,"stream_id":5945,"contributor":{"url":"http://geocommons.com/users/143","name":"jennifer"},"data_attributes":null,"calculation_params":null,"icon_link":null,"link":"http://geocommons.com/overlays/5945.json","extent":[-89.3867,40.7764,-73.4662,43.0729],"geometry_types":["point"],"unique_name":null,"name":"Roster - Seniors","feature_count":3,"description":"","next_feature":null,"is_raster":false,"short_classification":"Y","stats":{"latitude":{"max":43.072925,"mean":41.7948733333333,"variance":1.36907280965833,"stdev":1.17007384795077,"min":40.77636,"median":41.535335},"inches":{"max":71,"mean":69.0,"variance":3.0,"stdev":1.73205080756888,"min":68,"median":68},"longitude":{"max":-73.466224,"mean":-78.9186006666667,"variance":82.2328595833083,"stdev":9.06823354260951,"min":-89.386659,"median":-73.902919}},"features":[{"properties":{"name":"Bonnie Scott","latitude":40.77636,"inches":68,"highschoollastcollege":"Bethpage","year":"SR","height":"5'8","homestate":"NY","longitude":-73.466224,"id":"a6hc9r7iwdv7","hometown":"Plainview"},"type":"Feature","geometry":{"type":"Point","coordinates":[-73.466224,40.77636]}},{"properties":{"name":"Elizabeth Austin","latitude":43.072925,"inches":68,"highschoollastcollege":"Madison West","year":"SR","height":"5'8","homestate":"WI","longitude":-89.386659,"id":"a6hc9rgp7kg8","hometown":"Madison"},"type":"Feature","geometry":{"type":"Point","coordinates":[-89.386659,43.072925]}},{"properties":{"name":"Karri Hester","latitude":41.535335,"inches":71,"highschoollastcollege":"The Hotchkiss School","year":"SR","height":"5'11","homestate":"NY","longitude":-73.902919,"id":"a6hc9rgt3uod","hometown":"Fishkill"},"type":"Feature","geometry":{"type":"Point","coordinates":[-73.902919,41.535335]}}],"is_temporal":false,"author":{"url":"","metadata":"","contact_name":"","contact_address":"","source":"","contact_phone":""},"source":"","pagination":{"sort":null,"start":0,"total":3,"limit":1000000},"state":"complete","tags":"","published":"2014-08-11T06:35:09-04:00","id":5945}