{"type":"FeatureCollection","data_type":"Dataset","url_type":null,"permissions":[{"permissions":{"download":true,"view":true},"group_id":"everyone"}],"classification":null,"title":"Workbook4","count":4,"stream_id":60472,"contributor":{"url":"http://geocommons.com/users/15170","name":"kqian"},"data_attributes":null,"calculation_params":null,"icon_link":null,"link":"http://geocommons.com/overlays/60472.json","extent":[-122.297,33.888,-118.13,37.8606],"geometry_types":["point"],"unique_name":null,"name":"Workbook4","feature_count":4,"description":"","next_feature":null,"is_raster":false,"short_classification":"Y","stats":{},"features":[{"properties":{"City":"Oakland","geo_score":0.857,"Client Name":"Aspire","State":"CA","id":"a684p444gvjs","geo_precision":"city"},"type":"Feature","geometry":{"type":"Point","coordinates":[-122.270803,37.804372]}},{"properties":{"City":"Oakland","geo_score":0.857,"Client Name":"Bay Area Teacher Training BATTI","State":"CA","id":"a684p42jmdfj","geo_precision":"city"},"type":"Feature","geometry":{"type":"Point","coordinates":[-122.270803,37.804372]}},{"properties":{"City":"Bellflower","geo_score":0.857,"Client Name":"Bellflower USD","State":"CA","id":"a684p47gbtjq","geo_precision":"city"},"type":"Feature","geometry":{"type":"Point","coordinates":[-118.12965,33.888014]}},{"properties":{"City":"Berkeley","geo_score":0.857,"Client Name":"Berkeley USD","State":"CA","id":"a684p4d8i7q0","geo_precision":"city"},"type":"Feature","geometry":{"type":"Point","coordinates":[-122.29673,37.860576]}}],"is_temporal":false,"author":{"url":"","metadata":"","contact_name":"","contact_address":"","source":"","contact_phone":""},"source":"","pagination":{"sort":null,"start":0,"total":4,"limit":1000000},"state":"complete","tags":"","published":"2014-08-10T12:06:44-04:00","id":60472}