{"type":"FeatureCollection","data_type":"Dataset","url_type":null,"permissions":[{"permissions":{"download":true,"view":true},"group_id":"everyone"}],"classification":null,"title":"Proposed O&amp;M Building Location","count":1,"stream_id":63060,"contributor":{"url":"http://geocommons.com/users/12617","name":"quintonl"},"data_attributes":null,"calculation_params":null,"icon_link":null,"link":"http://geocommons.com/overlays/63060.json","extent":[18.0887,-32.8593,18.0887,-32.8593],"geometry_types":["point"],"unique_name":null,"name":"Proposed O&M Building Location","feature_count":1,"description":"","next_feature":null,"is_raster":false,"short_classification":"Y","stats":{"Id":{"max":0,"min":0,"median":0}},"features":[{"properties":{"Id":0,"id":"a6l2oydobdy0"},"type":"Feature","geometry":{"type":"Point","coordinates":[18.0887299277331,-32.8592825192306]}}],"is_temporal":false,"author":{"url":"","metadata":"","contact_name":"","contact_address":"","source":"","contact_phone":""},"source":"","pagination":{"sort":null,"start":0,"total":1,"limit":1000000},"state":"complete","tags":"","published":"2014-08-10T15:29:01-04:00","id":63060}