{"type":"FeatureCollection","data_type":"Dataset","url_type":null,"permissions":[{"permissions":{"download":true,"view":true},"group_id":"everyone"}],"classification":null,"title":"Testing 123","count":8,"stream_id":6372,"contributor":{"url":"http://geocommons.com/users/2","name":"data"},"data_attributes":null,"calculation_params":null,"icon_link":null,"link":"http://geocommons.com/overlays/6372.json","extent":[-98.577,29.9844,-90.1675,41.3392],"geometry_types":["point"],"unique_name":null,"name":"Testing 123","feature_count":8,"description":"random test zips","next_feature":null,"is_raster":false,"short_classification":"Y","stats":{"z coordina":{"max":0.0,"mean":0.0,"variance":0.0,"stdev":0.0,"min":0.0,"median":0.0},"name0":{"max":null,"min":null,"median":null}},"features":[{"properties":{"descriptio":" 67357","z coordina":0.0,"name0":"67357","id":"a645mzyyzo8a"},"type":"Feature","geometry":{"type":"Point","coordinates":[-95.2531,37.3448]}},{"properties":{"descriptio":" 67578","z coordina":0.0,"name0":"67578","id":"a645mzxw4fsr"},"type":"Feature","geometry":{"type":"Point","coordinates":[-98.577,37.9335]}},{"properties":{"descriptio":" 68050","z coordina":0.0,"name0":"68050","id":"a645mzv9mslf"},"type":"Feature","geometry":{"type":"Point","coordinates":[-96.8452,41.3129]}},{"properties":{"descriptio":" 68122","z coordina":0.0,"name0":"68122","id":"a645mzs17iou"},"type":"Feature","geometry":{"type":"Point","coordinates":[-96.0495,41.3392]}},{"properties":{"descriptio":" 68130","z coordina":0.0,"name0":"68130","id":"a645mzrbrbcy"},"type":"Feature","geometry":{"type":"Point","coordinates":[-96.1844,41.2359]}},{"properties":{"descriptio":" 68130","z coordina":0.0,"name0":"68130","id":"a645mzpdalxm"},"type":"Feature","geometry":{"type":"Point","coordinates":[-96.1844,41.2359]}},{"properties":{"descriptio":" 68130","z coordina":0.0,"name0":"68130","id":"a645n0076i30"},"type":"Feature","geometry":{"type":"Point","coordinates":[-96.1844,41.2359]}},{"properties":{"descriptio":" 70001","z coordina":0.0,"name0":"70001","id":"a645mzpwfsun"},"type":"Feature","geometry":{"type":"Point","coordinates":[-90.1675,29.9844]}}],"is_temporal":false,"author":{"url":null,"metadata":null,"contact_name":"","contact_address":"","source":null,"contact_phone":""},"source":null,"pagination":{"sort":null,"start":0,"total":8,"limit":1000000},"state":"complete","tags":"","published":"2014-08-11T07:24:05-04:00","id":6372}