{"type":"FeatureCollection","data_type":"Dataset","url_type":null,"permissions":[{"permissions":{"download":true,"view":true},"group_id":"everyone"}],"classification":null,"title":"Los Angeles Home Alarm Security System","count":1,"stream_id":64376,"contributor":{"url":"http://geocommons.com/users/11586","name":"bharken"},"data_attributes":null,"calculation_params":null,"icon_link":null,"link":"http://geocommons.com/overlays/64376.json","extent":[-118.253,34.0564,-118.253,34.0564],"geometry_types":["point"],"unique_name":null,"name":"Los Angeles Home Alarm Security System","feature_count":1,"description":"Their state-of-the-art system includes Front and Back Doors Protection, Infrared Interior Motion Detector, Digital Keypad with Police , Fire, and Medical Emergenct Buttons, Interior Siren, Control Panel with Battery Back-up and Lawn Sign and Window Decals.\n\nYour home security system is monitored by ADT professionals 24 hours a days, 7 days a week. As an added benefit, installing a Security System may qualify you for a Homeowners Insurance discount.","next_feature":null,"is_raster":false,"short_classification":"Y","stats":{},"features":[{"properties":{"city":"Los Angeles","name":"Los Angeles Home Alarm Security System","region":"US-CA","balloon_text":"<b><a href=\"http://maps.google.co.uk/maps/place?cid=2478464944555389015&amp;q=los+angeles+home+alarm+security&amp;hl=en-GB&amp;cd=4&amp;cad=src:kml_balloon&amp;ei=T0adTOmdGYSAvQOl_qjtCg\">$[name]</a></b>1 review202 S Figueroa St.Los Angeles, CA 90007, United States(213) 814-4990<a href=\"http://losangeleshomealarm.net/\">losangeleshomealarm.net</a><a href=\"/maps/place?cid=2478464944555389015&amp;q=los+angeles+home+alarm+security&amp;hl=en-GB&amp;cd=5&amp;cad=src:ppphoto&amp;ei=T0adTOmdGYSAvQOl_qjtCg\"><img src=\"http://lh3.googleusercontent.com/Lfn6wsvzYcR0KyuMeVvJrx-dZkX6Jc7a5jQxEoeIQ0DgCLAWDRrrM5SgH7WDtRwG7qEyLOmG5qpqHt2k3n7ZAMq6GAZ8RQhLRmLbXBi1U-igSygu2Bg_ZA\"></a>  $[geDirections]","contents":"Los Angeles Home Alarm Security System","id":"a632bmnic7zi"},"type":"Feature","geometry":{"type":"Point","coordinates":[-118.253268,34.056381]}}],"is_temporal":false,"author":{"url":"http://bbs.keyhole.com/ubb/ubbthreads.php?ubb=showflat&Number=1367614&#Post1367614","metadata":"","contact_name":"","contact_address":"202 South Figueroa Street, Los Angeles, CA 90007","source":"Google Earth Community","contact_phone":"(213) 814-4990"},"source":"http://bbs.keyhole.com/ubb/ubbthreads.php?ubb=showflat&Number=1367614&#Post1367614","pagination":{"sort":null,"start":0,"total":1,"limit":1000000},"state":"complete","tags":"alarm","published":"2014-08-10T17:23:55-04:00","id":64376}