{"type":"FeatureCollection","data_type":"Dataset","url_type":null,"permissions":[{"permissions":{"download":true,"view":true},"group_id":"everyone"}],"classification":null,"title":"Scores = 69 &amp; Below","count":1,"stream_id":64433,"contributor":{"url":"http://geocommons.com/users/16107","name":"shwiners"},"data_attributes":null,"calculation_params":null,"icon_link":null,"link":"http://geocommons.com/overlays/64433.json","extent":[-122.407,37.7126,-122.407,37.7126],"geometry_types":["point"],"unique_name":null,"name":"Scores = 69 & Below","feature_count":1,"description":"","next_feature":null,"is_raster":false,"short_classification":"Y","stats":{"2. inspection score":{"max":57,"min":57,"median":57}},"features":[{"properties":{"1. restaurant":"G &amp; L RESTAURANT","2. inspection score":57,"3. inspection date":"3/23/10","4. address":"198 LELAND AVE","5. city":"SAN FRANCISCO","id":"a655dci824a5"},"type":"Feature","geometry":{"type":"Point","coordinates":[-122.407377,37.7125747]}}],"is_temporal":false,"author":{"url":"http://sf.everyblock.com","metadata":"","contact_name":"","contact_address":"","source":"Every Block","contact_phone":""},"source":"http://sf.everyblock.com","pagination":{"sort":null,"start":0,"total":1,"limit":1000000},"state":"complete","tags":"94134,restaurant inspections,san francisco","published":"2010-09-26T16:00:00Z","id":64433}