{"type":"FeatureCollection","data_type":"Dataset","url_type":null,"permissions":[{"permissions":{"download":true,"view":true},"group_id":"everyone"}],"classification":null,"title":"Score: 69 &amp; Below 94117","count":1,"stream_id":64829,"contributor":{"url":"http://geocommons.com/users/16258","name":"FayAbuelgasim"},"data_attributes":null,"calculation_params":null,"icon_link":null,"link":"http://geocommons.com/overlays/64829.json","extent":[-122.457,37.7657,-122.457,37.7657],"geometry_types":["point"],"unique_name":null,"name":"Score: 69 & Below 94117","feature_count":1,"description":"","next_feature":null,"is_raster":false,"short_classification":"Y","stats":{"2. inspection score":{"max":66,"min":66,"median":66}},"features":[{"properties":{"1. restaurant":"NEW GANGES","3. inspection date":"6/21/2010","2. inspection score":66,"4. address":"775 FREDERICK STREET","id":"a6rega8lwemr"},"type":"Feature","geometry":{"type":"Point","coordinates":[-122.457206,37.76573]}}],"is_temporal":false,"author":{"url":"http://sf.everyblock.com","metadata":"","contact_name":"","contact_address":"","source":"EveryBlock","contact_phone":""},"source":"http://sf.everyblock.com","pagination":{"sort":null,"start":0,"total":1,"limit":1000000},"state":"complete","tags":"restaurantinspections,sanfrancisco","published":"2010-09-28T16:00:00Z","id":64829}