{"type":"FeatureCollection","data_type":"Dataset","url_type":null,"permissions":[{"permissions":{"download":true,"view":true},"group_id":"everyone"}],"classification":null,"title":"94129 Scores = 69 &amp; Below","count":1,"stream_id":65340,"contributor":{"url":"http://geocommons.com/users/16252","name":"lollymr"},"data_attributes":null,"calculation_params":null,"icon_link":null,"link":"http://geocommons.com/overlays/65340.json","extent":[-122.467,37.7981,-122.467,37.7981],"geometry_types":["point"],"unique_name":null,"name":"94129 Scores = 69 & Below","feature_count":1,"description":"","next_feature":null,"is_raster":false,"short_classification":"Y","stats":{"2. inspection score":{"max":55,"min":55,"median":55}},"features":[{"properties":{"1. restaurant":"LIVERPOOL LIL's","3. inspection date":"7/23/10","2. inspection score":55,"4. address":"2942 Lyon Street","id":"a673sxqjt0r2"},"type":"Feature","geometry":{"type":"Point","coordinates":[-122.4665384,37.7980847]}}],"is_temporal":false,"author":{"url":"http://sf.everyblock.com","metadata":"","contact_name":"","contact_address":"","source":"Every Block","contact_phone":""},"source":"http://sf.everyblock.com","pagination":{"sort":null,"start":0,"total":1,"limit":1000000},"state":"complete","tags":"94129,restaurant inspections,san francisco","published":"2010-10-01T16:00:00Z","id":65340}