{"type":"FeatureCollection","data_type":"Dataset","url_type":null,"permissions":[{"permissions":{"download":true,"view":true},"group_id":"everyone"}],"classification":null,"title":"prueba2_pedro","count":4,"stream_id":66009,"contributor":{"url":"http://geocommons.com/users/16744","name":"pedrorod"},"data_attributes":null,"calculation_params":null,"icon_link":null,"link":"http://geocommons.com/overlays/66009.json","extent":[-91.1947,31.2171,-84.8517,40.072],"geometry_types":["point"],"unique_name":null,"name":"prueba2_pedro","feature_count":4,"description":"","next_feature":null,"is_raster":false,"short_classification":"Y","stats":{"geo_score":{"max":0.536,"mean":0.41325,"variance":0.02555025,"stdev":0.159844455643604,"min":0.2,"median":0.536},"codigo postal":{"max":null,"min":null,"median":null}},"features":[{"properties":{"nombre":"Antigua IBERTASA Barcelona","geo_score":0.381,"ciudad":"Barcelona","codigo postal":"8021","id":"a73rstmu9g5p","direccion":"Aribau 195","geo_precision":"street","estado":null},"type":"Feature","geometry":{"type":"Point","coordinates":[-84.851693,40.071982]}},{"properties":{"nombre":"IBERTASA Barcelona","geo_score":0.536,"ciudad":"Barcelona","codigo postal":"8037","id":"a73rstrevst3","direccion":"Roger de Lluria 118","geo_precision":"street","estado":null},"type":"Feature","geometry":{"type":"Point","coordinates":[-87.304377,31.217101]}},{"properties":{"nombre":"IBERTASA Madrid","geo_score":0.536,"ciudad":"Madrid","codigo postal":"28016","id":"a73rstoedy8h","direccion":"Rodriguez Marin 61","geo_precision":"street","estado":null},"type":"Feature","geometry":{"type":"Point","coordinates":[-91.19475,33.61166]}},{"properties":{"nombre":"IBERTASA Valencia","geo_score":0.2,"ciudad":"Valencia","codigo postal":"46004","id":"a73rsu14mtyi","direccion":"Ruzafa 28","geo_precision":"street","estado":null},"type":"Feature","geometry":{"type":"Point","coordinates":[-87.308599,36.565986]}}],"is_temporal":false,"author":{"url":"","metadata":"","contact_name":"","contact_address":"","source":"","contact_phone":""},"source":"","pagination":{"sort":null,"start":0,"total":4,"limit":1000000},"state":"complete","tags":"","published":"2014-08-10T19:14:47-04:00","id":66009}