{"type":"FeatureCollection","data_type":"Dataset","url_type":null,"permissions":[{"permissions":{"download":true,"view":true},"group_id":"everyone"}],"classification":null,"title":"Ice Rinks, Idaho, 2007","count":6,"stream_id":6627,"contributor":{"url":"http://geocommons.com/users/2","name":"data"},"data_attributes":null,"calculation_params":null,"icon_link":null,"link":"http://geocommons.com/overlays/6627.json","extent":[-116.98,43.47,-112.04,46.72],"geometry_types":["point"],"unique_name":null,"name":"Ice Rinks, Idaho, 2007","feature_count":6,"description":"This dataset displays all of the ice rinks in Idaho. The data has been geocoded according to the street address of the ice rink to obtain the longitude and latitude measurements. The data was collected from arenamaps.com, and accessed on 10, 4, 2007.","next_feature":null,"is_raster":false,"short_classification":"Y","stats":{"Longitude0":{"max":-112.04,"mean":-115.306666666667,"variance":3.30458666666666,"stdev":1.81785221254828,"min":-116.98,"median":-116.1},"Latitude0":{"max":46.72,"mean":44.325,"variance":1.66547,"stdev":1.2905308985065,"min":43.47,"median":43.7}},"features":[{"properties":{"Ice Rink0":"Idaho Ice World","Telephone0":"208-331-0044","Notes0":"","Longitude0":-116.16,"Latitude0":43.54,"id":"a678hxdhrfjg","Address0":"7072 S. Eisenman Rd. Boise, ID 83716"},"type":"Feature","geometry":{"type":"Point","coordinates":[-116.16,43.5400009155273]}},{"properties":{"Ice Rink0":"Joe Marmo &amp; Wayne Lehto Ice Rink","Telephone0":"208-529-0941","Notes0":"Tautphaus Park","Longitude0":-112.04,"Latitude0":43.47,"id":"a678hx6z6nnd","Address0":"Rogers St. &amp; Carnival Way Idaho Falls, ID 83405"},"type":"Feature","geometry":{"type":"Point","coordinates":[-112.04,43.4700012207031]}},{"properties":{"Ice Rink0":"Manchester Ice &amp; Event Centre","Telephone0":"208-634-3570","Notes0":"","Longitude0":-116.1,"Latitude0":44.91,"id":"a678hxkctbiu","Address0":"200 E. Lake St. McCall, ID 83638"},"type":"Feature","geometry":{"type":"Point","coordinates":[-116.1,44.9099998474121]}},{"properties":{"Ice Rink0":"Palouse Ice Rink","Telephone0":"208-882-7188","Notes0":"Rotary Veterans Memorial Pavilion","Longitude0":-116.98,"Latitude0":46.72,"id":"a678hxhaulc6","Address0":"E. White Ave. (Latah County Fairgrounds) Moscow, ID 83843"},"type":"Feature","geometry":{"type":"Point","coordinates":[-116.98,46.7200012207031]}},{"properties":{"Ice Rink0":"Qwest Arena (formerly Bank of America Centre)","Telephone0":"208-424-2200","Notes0":"(Home of the Idaho Steelheads)","Longitude0":-116.2,"Latitude0":43.61,"id":"a678hxfhe0yf","Address0":"233 S. Capitol Blvd. Boise, ID 83702"},"type":"Feature","geometry":{"type":"Point","coordinates":[-116.2,43.6100006103516]}},{"properties":{"Ice Rink0":"Sun Valley Skating Center","Telephone0":"208-622-2194","Notes0":"","Longitude0":-114.36,"Latitude0":43.7,"id":"a678hxda7l6c","Address0":"Dollar Loop Rd. Sun Valley, ID 83353"},"type":"Feature","geometry":{"type":"Point","coordinates":[-114.36,43.7000007629395]}}],"is_temporal":false,"author":{"url":null,"metadata":null,"contact_name":"","contact_address":"","source":"Arenamaps.com","contact_phone":""},"source":null,"pagination":{"sort":null,"start":0,"total":6,"limit":1000000},"state":"complete","tags":"and,canada,hockey,ice,recreation,rink,skating,sports,us","published":"2007-10-04T12:00:00Z","id":6627}