{"type":"FeatureCollection","data_type":"Dataset","url_type":null,"permissions":[{"permissions":{"download":true,"view":true},"group_id":"everyone"}],"classification":null,"title":"maximum temperature","count":15,"stream_id":6677,"contributor":{"url":"http://geocommons.com/users/2","name":"data"},"data_attributes":null,"calculation_params":null,"icon_link":null,"link":"http://geocommons.com/overlays/6677.json","extent":[-100.322,40.0009,-100.008,40.5251],"geometry_types":["point"],"unique_name":null,"name":"maximum temperature","feature_count":15,"description":"upper mississipi","next_feature":null,"is_raster":false,"short_classification":"Y","stats":{"Region0":{"max":null,"min":null,"median":null},"Maximum Te":{"max":null,"min":null,"median":null}},"features":[{"properties":{"id":"a63qghwj3y99","Region0":"71","Maximum Te":"71"},"type":"Feature","geometry":{"type":"Point","coordinates":[-100.321942,40.52505]}},{"properties":{"id":"a63qghv7chsi","Region0":"71","Maximum Te":"71"},"type":"Feature","geometry":{"type":"Point","coordinates":[-100.261944,40.48286]}},{"properties":{"id":"a63qghp40xfa","Region0":"71","Maximum Te":"71"},"type":"Feature","geometry":{"type":"Point","coordinates":[-100.319675,40.481146]}},{"properties":{"id":"a63qghuf3w4j","Region0":"71","Maximum Te":"71"},"type":"Feature","geometry":{"type":"Point","coordinates":[-100.201996,40.44064]}},{"properties":{"id":"a63qghtgjn4s","Region0":"71","Maximum Te":"71"},"type":"Feature","geometry":{"type":"Point","coordinates":[-100.259704,40.438945]}},{"properties":{"id":"a63qghsrwfmg","Region0":"71","Maximum Te":"71"},"type":"Feature","geometry":{"type":"Point","coordinates":[-100.317409,40.437231]}},{"properties":{"id":"a63qghvx1lia","Region0":"71","Maximum Te":"71"},"type":"Feature","geometry":{"type":"Point","coordinates":[-100.199782,40.396715]}},{"properties":{"id":"a63qgi24l756","Region0":"71","Maximum Te":"71"},"type":"Feature","geometry":{"type":"Point","coordinates":[-100.257465,40.39502]}},{"properties":{"id":"a63qgi2deow5","Region0":"71","Maximum Te":"71"},"type":"Feature","geometry":{"type":"Point","coordinates":[-100.197569,40.352779]}},{"properties":{"id":"a63qghvamruu","Region0":"71","Maximum Te":"71"},"type":"Feature","geometry":{"type":"Point","coordinates":[-100.124645,40.046626]}},{"properties":{"id":"a63qghq9vcjg","Region0":"71","Maximum Te":"71"},"type":"Feature","geometry":{"type":"Point","coordinates":[-100.182134,40.044953]}},{"properties":{"id":"a63qghttkc50","Region0":"71","Maximum Te":"71"},"type":"Feature","geometry":{"type":"Point","coordinates":[-100.007536,40.005902]}},{"properties":{"id":"a63qgi2ijiwm","Region0":"71","Maximum Te":"71"},"type":"Feature","geometry":{"type":"Point","coordinates":[-100.065005,40.004266]}},{"properties":{"id":"a63qghrzz8fk","Region0":"71","Maximum Te":"71"},"type":"Feature","geometry":{"type":"Point","coordinates":[-100.122471,40.002611]}},{"properties":{"id":"a63qghqudlyw","Region0":"71","Maximum Te":"71"},"type":"Feature","geometry":{"type":"Point","coordinates":[-100.179936,40.000938]}}],"is_temporal":false,"author":{"url":null,"metadata":null,"contact_name":"","contact_address":"","source":null,"contact_phone":""},"source":null,"pagination":{"sort":null,"start":0,"total":15,"limit":1000000},"state":"complete","tags":"climate,maximum,temperature,weather","published":"2014-08-11T07:29:51-04:00","id":6677}