{"type":"FeatureCollection","data_type":"Dataset","url_type":null,"permissions":[{"permissions":{"download":true,"view":true},"group_id":"everyone"}],"classification":null,"title":"Provincial Stations","count":3,"stream_id":68527,"contributor":{"url":"http://geocommons.com/users/16869","name":"mickcote"},"data_attributes":null,"calculation_params":null,"icon_link":null,"link":"http://geocommons.com/overlays/68527.json","extent":[-66.12,43.836,-63.2803,45.3652],"geometry_types":["point"],"unique_name":null,"name":"Provincial Stations","feature_count":3,"description":"created with batchgeo.com","next_feature":null,"is_raster":false,"short_classification":"Y","stats":{},"features":[{"properties":{"name":null,"description":"&lt;div class=\"markerLabel\"&gt;&lt;div class=\"address\"&gt;170 Thompson Run&lt;br&gt;Halifax &lt;/div&gt;&lt;div&gt;&lt;span class=\"l\"&gt;Station:&lt;/span&gt;&amp;nbsp;CIRH-FM&lt;/div&gt;&lt;div&gt;&lt;span class=\"l\"&gt;Website:&lt;/span&gt;&amp;nbsp;http://www.informationradio.ca/halifax.htm&lt;/div&gt;&lt;div&gt;&lt;span class=\"l\"&gt;Frequency:&lt;/span&gt;&amp;nbsp;107.7 FM&lt;/div&gt;&lt;div&gt;&lt;span class=\"l\"&gt;Postal Code:&lt;/span&gt;&amp;nbsp;B4B 1T7&lt;/div&gt;&lt;div&gt;&lt;span class=\"l\"&gt;Owner:&lt;/span&gt;&amp;nbsp;Instant Information Services&lt;/div&gt;&lt;div&gt;&lt;span class=\"l\"&gt;Genre:&lt;/span&gt;&amp;nbsp;tourist information&lt;/div&gt;&lt;div&gt;&lt;span class=\"l\"&gt;Province:&lt;/span&gt;&amp;nbsp;Nova Scotia&lt;/div&gt;&lt;a href=\"http://maps.google.com/?q=170%20Thompson%20Run%20Halifax%20\" target=\"_blank\" class=\"marker\"&gt;...&lt;/a&gt;&lt;/div&gt;","id":"a66cpfhiwjtm"},"type":"Feature","geometry":{"type":"Point","coordinates":[-63.7759974,44.7543078]}},{"properties":{"name":null,"description":"&lt;div class=\"markerLabel\"&gt;&lt;div class=\"address\"&gt;695 Prince St.&lt;br&gt;Truro &lt;/div&gt;&lt;div&gt;&lt;span class=\"l\"&gt;Station:&lt;/span&gt;&amp;nbsp;CJIS-FM&lt;/div&gt;&lt;div&gt;&lt;span class=\"l\"&gt;Website:&lt;/span&gt;&amp;nbsp;http://www.truro.ca/local-radio-station.html&lt;/div&gt;&lt;div&gt;&lt;span class=\"l\"&gt;Frequency:&lt;/span&gt;&amp;nbsp;107.1 FM&lt;/div&gt;&lt;div&gt;&lt;span class=\"l\"&gt;Postal Code:&lt;/span&gt;&amp;nbsp;B2N 1G5&lt;/div&gt;&lt;div&gt;&lt;span class=\"l\"&gt;Owner:&lt;/span&gt;&amp;nbsp;Town of Truro&lt;/div&gt;&lt;div&gt;&lt;span class=\"l\"&gt;Genre:&lt;/span&gt;&amp;nbsp;tourist information&lt;/div&gt;&lt;div&gt;&lt;span class=\"l\"&gt;Province:&lt;/span&gt;&amp;nbsp;Nova Scotia&lt;/div&gt;&lt;a href=\"http://maps.google.com/?q=695%20Prince%20St.%20Truro%20\" target=\"_blank\" class=\"marker\"&gt;...&lt;/a&gt;&lt;/div&gt;","id":"a66cpfe1ke3c"},"type":"Feature","geometry":{"type":"Point","coordinates":[-63.2802906,45.3651681]}},{"properties":{"name":null,"description":"&lt;div class=\"markerLabel\"&gt;&lt;div class=\"address\"&gt;328 Main St.&lt;br&gt;Yarmouth &lt;/div&gt;&lt;div&gt;&lt;span class=\"l\"&gt;Station:&lt;/span&gt;&amp;nbsp;CJLS-FM-3&lt;/div&gt;&lt;div&gt;&lt;span class=\"l\"&gt;Website:&lt;/span&gt;&amp;nbsp;http://www.cjls.com/&lt;/div&gt;&lt;div&gt;&lt;span class=\"l\"&gt;Frequency:&lt;/span&gt;&amp;nbsp;95.5 FM&lt;/div&gt;&lt;div&gt;&lt;span class=\"l\"&gt;Postal Code:&lt;/span&gt;&amp;nbsp;B5A 1E4&lt;/div&gt;&lt;div&gt;&lt;span class=\"l\"&gt;Owner:&lt;/span&gt;&amp;nbsp;Ray Zinck &amp; Chris Perry&lt;/div&gt;&lt;div&gt;&lt;span class=\"l\"&gt;Genre:&lt;/span&gt;&amp;nbsp;Provincial station&lt;/div&gt;&lt;div&gt;&lt;span class=\"l\"&gt;Province:&lt;/span&gt;&amp;nbsp;Nova Scotia&lt;/div&gt;&lt;a href=\"http://maps.google.com/?q=328%20Main%20St.%20Yarmouth%20\" target=\"_blank\" class=\"marker\"&gt;...&lt;/a&gt;&lt;/div&gt;","id":"a66cpf2dmibf"},"type":"Feature","geometry":{"type":"Point","coordinates":[-66.1199823,43.8359654]}}],"is_temporal":false,"author":{"url":"","metadata":"","contact_name":"","contact_address":"","source":"","contact_phone":""},"source":"","pagination":{"sort":null,"start":0,"total":3,"limit":1000000},"state":"complete","tags":"","published":"2014-08-10T21:52:56-04:00","id":68527}