{"type":"FeatureCollection","data_type":"Dataset","url_type":null,"permissions":[{"permissions":{"download":true,"view":true},"group_id":"everyone"}],"classification":null,"title":"Largest Military Contractors, USA, 2002","count":10,"stream_id":6856,"contributor":{"url":"http://geocommons.com/users/2","name":"data"},"data_attributes":null,"calculation_params":null,"icon_link":null,"link":"http://geocommons.com/overlays/6856.json","extent":[-118.598,32.6137,-71.2718,42.407],"geometry_types":["point"],"unique_name":null,"name":"Largest Military Contractors, USA, 2002","feature_count":10,"description":"This data set illustrates the top ten military contractors, by contract value, campaign contribution, and major weapons.http://www.cdi.org/news/mrp/contractors.pdfAugust 28, 2007","next_feature":null,"is_raster":false,"short_classification":"Y","stats":{"LONGITUDE0":{"max":-71.27181,"mean":-86.39894,"variance":299.330112933467,"stdev":17.3011592944943,"min":-118.59766,"median":-77.21722},"CAMPAIGN C":{"max":8.7,"mean":2.925,"variance":7.94736111111111,"stdev":2.81910643841468,"min":-1.0,"median":2.3},"LATITUDE0":{"max":42.40704,"mean":38.404218,"variance":14.6340739985289,"stdev":3.82545082291341,"min":32.61371,"median":39.03},"CONTRACT V":{"max":17.0,"mean":6.74,"variance":34.5693333333333,"stdev":5.87956914521237,"min":1.7,"median":7.0}},"features":[{"properties":{"LONGITUDE0":-118.59766,"COMPANY0":"Health Net, Inc.","CAMPAIGN C":-1.0,"LATITUDE0":34.17906,"CONTRACT V":1.7,"MAJOR WEAP":"Health care services/ support","id":"a63anyondeel","STATE0":"CA"},"type":"Feature","geometry":{"type":"Point","coordinates":[-118.59766,34.17906]}},{"properties":{"LONGITUDE0":-83.65165,"COMPANY0":"L-3 Communications Holdings, Inc.","CAMPAIGN C":0.05,"LATITUDE0":32.61371,"CONTRACT V":1.7,"MAJOR WEAP":"Acoustic undersea warfare systems","id":"a63anyi7nbzt","STATE0":"GA"},"type":"Feature","geometry":{"type":"Point","coordinates":[-83.65165,32.61371]}},{"properties":{"LONGITUDE0":-87.63885,"COMPANY0":"Boeing Company","CAMPAIGN C":1.1,"LATITUDE0":41.88323,"CONTRACT V":16.6,"MAJOR WEAP":"F/A-18 Super Hornet, F-15 Eagle, F-22 Raptor, V-22 Osprey, RAH-66 Comanche, C-17","id":"a63anykm3ib1","STATE0":"IL"},"type":"Feature","geometry":{"type":"Point","coordinates":[-87.63885,41.88323]}},{"properties":{"LONGITUDE0":-81.49734,"COMPANY0":"TRW Inc.","CAMPAIGN C":2.0,"LATITUDE0":41.51105,"CONTRACT V":2.0,"MAJOR WEAP":"Electronic Systems and Support","id":"a63anyjgm0mo","STATE0":"OH"},"type":"Feature","geometry":{"type":"Point","coordinates":[-81.49734,41.51105]}},{"properties":{"LONGITUDE0":-72.6855,"COMPANY0":"United Technologies Corporation","CAMPAIGN C":2.2,"LATITUDE0":41.7636,"CONTRACT V":3.6,"MAJOR WEAP":"RAH-66 Comamche","id":"a63anyko6uix","STATE0":"CT"},"type":"Feature","geometry":{"type":"Point","coordinates":[-72.6855,41.7636]}},{"properties":{"LONGITUDE0":-117.22254,"COMPANY0":"Science Applications International Corpo","CAMPAIGN C":2.3,"LATITUDE0":32.88956,"CONTRACT V":2.1,"MAJOR WEAP":"Prorammatic, Logistical and technical support","id":"a63anyedsvgj","STATE0":"CA"},"type":"Feature","geometry":{"type":"Point","coordinates":[-117.22254,32.88956]}},{"properties":{"LONGITUDE0":-71.27181,"COMPANY0":"Raytheon Company","CAMPAIGN C":4.0,"LATITUDE0":42.40704,"CONTRACT V":7.0,"MAJOR WEAP":"Tomahawk Missiles","id":"a63anyk4p9hc","STATE0":"MA"},"type":"Feature","geometry":{"type":"Point","coordinates":[-71.27181,42.40704]}},{"properties":{"LONGITUDE0":-77.06865,"COMPANY0":"Northrop Grumman Corporation","CAMPAIGN C":4.8,"LATITUDE0":38.89399,"CONTRACT V":8.7,"MAJOR WEAP":"E-2C Hawkeye, EA-6B Prowler, F/A-18 Super Hornet, B-2 Bomber, E-8C JSTARS, LPD-1","id":"a63any9vwx0z","STATE0":"VA"},"type":"Feature","geometry":{"type":"Point","coordinates":[-77.06865,38.89399]}},{"properties":{"LONGITUDE0":-77.21722,"COMPANY0":"General Dynamics Corporation","CAMPAIGN C":5.1,"LATITUDE0":38.87094,"CONTRACT V":7.0,"MAJOR WEAP":"NSSN Submarine, M1A2 Abrams, IAV Stryker","id":"a63anyi2nlpu","STATE0":"VA"},"type":"Feature","geometry":{"type":"Point","coordinates":[-77.21722,38.87094]}},{"properties":{"LONGITUDE0":-77.13818,"COMPANY0":"Lockheed Martin Corporation","CAMPAIGN C":8.7,"LATITUDE0":39.03,"CONTRACT V":17.0,"MAJOR WEAP":"F-16 Falcon, F-22 Raptor, C-130J, hercules, AH-64 Apache, Trident missiles, spac","id":"a63anyd4i7fv","STATE0":"MD"},"type":"Feature","geometry":{"type":"Point","coordinates":[-77.13818,39.03]}}],"is_temporal":false,"author":{"url":"http://www.cdi.org/news/mrp/contractors.pdfAugust","metadata":null,"contact_name":"","contact_address":"","source":"CDC","contact_phone":""},"source":"http://www.cdi.org/news/mrp/contractors.pdfAugust","pagination":{"sort":null,"start":0,"total":10,"limit":1000000},"state":"complete","tags":"contractors,military","published":"2007-08-29T12:00:00Z","id":6856}