{"type":"FeatureCollection","data_type":"Dataset","url_type":null,"permissions":[{"permissions":{"download":true,"view":true},"group_id":"everyone"}],"classification":null,"title":"Diamond Limo Long Beach","count":1,"stream_id":68731,"contributor":{"url":"http://geocommons.com/users/11586","name":"bharken"},"data_attributes":null,"calculation_params":null,"icon_link":null,"link":"http://geocommons.com/overlays/68731.json","extent":[-118.192,33.7678,-118.192,33.7678],"geometry_types":["point"],"unique_name":null,"name":"Diamond Limo Long Beach","feature_count":1,"description":"Diamond Limo Long Beach provides excellence in luxury ground transportation along with consistent and professional service each and every time. They establish relationships of trust with their customers and strive to bring them the very best Long Beach limo experience possible.","next_feature":null,"is_raster":false,"short_classification":"Y","stats":{},"features":[{"properties":{"name":"Diamond Limo Long Beach","city":"Long Beach","region":"US-CA","balloon_text":"<b><a href=\"http://maps.google.co.uk/maps/place?cid=3683374032552170384&amp;q=diamond+limo+long+beach&amp;hl=en-GB&amp;cad=src:kml_balloon&amp;ei=tfe-TPG0I4_guwPh_vWsDg\">$[name]</a></b>1 review65 Pine Ave.Long Beach, CA 90802, United States(562) 200-0158<a href=\"http://www.diamondlimolongbeach.com/\">diamondlimolongbeach.com</a><a href=\"/maps/place?cid=3683374032552170384&amp;q=diamond+limo+long+beach&amp;hl=en-GB&amp;cd=1&amp;cad=src:ppphoto&amp;ei=tfe-TPG0I4_guwPh_vWsDg\"><img src=\"http://lh4.googleusercontent.com/public/6WYK5WngzCxs0TZtICxVP3pch_-hj6pk3_2ScAvuBoR6w_NnJ1r-2uGGDPRuxBxBY89RgOlXVBsi_UJRYT8zQBj_u1m3r_Yq73VDf1jAY1fBoR9sbf4yYRHj\"></a>  $[geDirections]","contents":"Diamond Limo Long Beach","id":"a699ip7xz057"},"type":"Feature","geometry":{"type":"Point","coordinates":[-118.192404,33.767829]}}],"is_temporal":false,"author":{"url":"http://bbs.keyhole.com/ubb/ubbthreads.php?ubb=showflat&Number=1374632&#Post1374632","metadata":"","contact_name":"","contact_address":"65 Pine Avenue, Long Beach, CA 90802","source":"Google Earth","contact_phone":"(562) 200-0158"},"source":"http://bbs.keyhole.com/ubb/ubbthreads.php?ubb=showflat&Number=1374632&#Post1374632","pagination":{"sort":null,"start":0,"total":1,"limit":1000000},"state":"complete","tags":"limo,limo service,limo services,limos,limousine,limousine service,limousine services,limousines","published":"2014-08-10T22:02:16-04:00","id":68731}