{"type":"FeatureCollection","data_type":"Dataset","url_type":null,"permissions":[{"permissions":{"download":true,"view":true},"group_id":"everyone"}],"classification":null,"title":"Lake Superior.kmz","count":1,"stream_id":69226,"contributor":{"url":"http://geocommons.com/users/16734","name":"sczunyi"},"data_attributes":null,"calculation_params":null,"icon_link":null,"link":"http://geocommons.com/overlays/69226.json","extent":[-87.0694,47.521,-87.0694,47.521],"geometry_types":["point"],"unique_name":null,"name":"Lake Superior.kmz","feature_count":1,"description":"","next_feature":null,"is_raster":false,"short_classification":"Y","stats":{},"features":[{"properties":{"name":"Lake Superior","id":"a6zuqiwf2mf8"},"type":"Feature","geometry":{"type":"Point","coordinates":[-87.0694313349134,47.5209613729368]}}],"is_temporal":false,"author":{"url":"","metadata":"","contact_name":"","contact_address":"","source":"","contact_phone":""},"source":"","pagination":{"sort":null,"start":0,"total":1,"limit":1000000},"state":"complete","tags":"","published":"2014-08-10T22:28:08-04:00","id":69226}