{"type":"FeatureCollection","data_type":"Dataset","url_type":null,"permissions":[{"permissions":{"download":true,"view":true},"group_id":"everyone"}],"classification":null,"title":"Dataset for search term 'Cisco'","count":16,"stream_id":70498,"contributor":{"url":"http://geocommons.com/users/17605","name":"vongtv"},"data_attributes":null,"calculation_params":null,"icon_link":null,"link":"http://geocommons.com/overlays/70498.json","extent":[-121.924,-33.387,126.978,51.4642],"geometry_types":["point"],"unique_name":null,"name":"Dataset for search term 'Cisco'","feature_count":16,"description":"","next_feature":null,"is_raster":false,"short_classification":"Y","stats":{},"features":[{"properties":{"latitude":-33.387,"longitude":-70.5899,"id":"a6fgc1wsa1tk"},"type":"Feature","geometry":{"type":"Point","coordinates":[-70.5899,-33.387]}},{"properties":{"latitude":-23.6504,"longitude":-46.7185,"id":"a6fgc1rspq4z"},"type":"Feature","geometry":{"type":"Point","coordinates":[-46.7185,-23.6504]}},{"properties":{"latitude":6.5172,"longitude":3.3319,"id":"a6fgc1w7elow"},"type":"Feature","geometry":{"type":"Point","coordinates":[3.3319,6.5172]}},{"properties":{"latitude":28.3198,"longitude":-80.729,"id":"a6fgc219ay7x"},"type":"Feature","geometry":{"type":"Point","coordinates":[-80.729,28.3198]}},{"properties":{"latitude":31.4287,"longitude":-98.6133,"id":"a6fgc1luozpw"},"type":"Feature","geometry":{"type":"Point","coordinates":[-98.6133,31.4287]}},{"properties":{"latitude":33.7645,"longitude":-118.1955,"id":"a6fgc1n53cd2"},"type":"Feature","geometry":{"type":"Point","coordinates":[-118.1955,33.7645]}},{"properties":{"latitude":33.7645,"longitude":-118.1955,"id":"a6fgc1wton25"},"type":"Feature","geometry":{"type":"Point","coordinates":[-118.1955,33.7645]}},{"properties":{"latitude":33.7801,"longitude":-118.1583,"id":"a6fgc1npnqcg"},"type":"Feature","geometry":{"type":"Point","coordinates":[-118.1583,33.7801]}},{"properties":{"latitude":33.7801,"longitude":-118.1583,"id":"a6fgc1s6mvo4"},"type":"Feature","geometry":{"type":"Point","coordinates":[-118.1583,33.7801]}},{"properties":{"latitude":33.7801,"longitude":-118.1583,"id":"a6fgc1u49xl7"},"type":"Feature","geometry":{"type":"Point","coordinates":[-118.1583,33.7801]}},{"properties":{"latitude":37.3721,"longitude":-121.9237,"id":"a6fgc1nfz6pv"},"type":"Feature","geometry":{"type":"Point","coordinates":[-121.9237,37.3721]}},{"properties":{"latitude":37.3721,"longitude":-121.9236,"id":"a6fgc1nt11yn"},"type":"Feature","geometry":{"type":"Point","coordinates":[-121.9236,37.3721]}},{"properties":{"latitude":37.3721,"longitude":-121.9236,"id":"a6fgc1vjbfsz"},"type":"Feature","geometry":{"type":"Point","coordinates":[-121.9236,37.3721]}},{"properties":{"latitude":37.5684,"longitude":126.9783,"id":"a6fgc1rds8ry"},"type":"Feature","geometry":{"type":"Point","coordinates":[126.9783,37.5684]}},{"properties":{"latitude":43.7294,"longitude":-79.7572,"id":"a6fgc1nmpekv"},"type":"Feature","geometry":{"type":"Point","coordinates":[-79.7572,43.7294]}},{"properties":{"latitude":51.4642,"longitude":-0.1695,"id":"a6fgc1le1qkk"},"type":"Feature","geometry":{"type":"Point","coordinates":[-0.1695,51.4642]}}],"is_temporal":false,"author":{"url":"http://twitter.com","metadata":"","contact_name":"","contact_address":"","source":"","contact_phone":""},"source":"http://twitter.com","pagination":{"sort":null,"start":0,"total":16,"limit":1000000},"state":"complete","tags":"","published":"2014-08-10T11:39:34-04:00","id":70498}