{"type":"FeatureCollection","data_type":"Dataset","url_type":null,"permissions":[{"permissions":{"download":true,"view":true},"group_id":"everyone"}],"classification":null,"title":"Watch the World Series: Mission District_readersuggestions","count":3,"stream_id":70699,"contributor":{"url":"http://geocommons.com/users/17687","name":"hhunterr"},"data_attributes":null,"calculation_params":null,"icon_link":null,"link":"http://geocommons.com/overlays/70699.json","extent":[-122.42,37.7499,-122.419,37.7516],"geometry_types":["point"],"unique_name":null,"name":"Watch the World Series: Mission District_readersuggestions","feature_count":3,"description":"Watch the World Series in San Francisco's Mission Disitrct","next_feature":null,"is_raster":false,"short_classification":"Y","stats":{},"features":[{"properties":{"bar name":null,"street address":"2832 Mission St.","bar specials":null,"id":"a63nyduwexqm","tv setup":null},"type":"Feature","geometry":null},{"properties":{"bar name":"Pi Bar","street address":"1432 Valencia St","bar specials":null,"id":"a63nye8h6e4u","tv setup":null},"type":"Feature","geometry":{"type":"Point","coordinates":[-122.4204691,37.7498943]}},{"properties":{"bar name":"Rosamunde's","street address":"2832 Mission Street","bar specials":null,"id":"a63nye9hi7f2","tv setup":null},"type":"Feature","geometry":{"type":"Point","coordinates":[-122.418692,37.7515687]}}],"is_temporal":false,"author":{"url":"","metadata":"","contact_name":"","contact_address":"","source":"","contact_phone":""},"source":"","pagination":{"sort":null,"start":0,"total":3,"limit":1000000},"state":"complete","tags":"giants,series,watch,world","published":"2010-10-27T17:09:49Z","id":70699}