{"type":"FeatureCollection","data_type":"Dataset","url_type":null,"permissions":[{"permissions":{"download":true,"view":true},"group_id":"everyone"}],"classification":null,"title":"Dataset for search term 'coca'","count":2,"stream_id":70823,"contributor":{"url":"http://geocommons.com/users/17605","name":"vongtv"},"data_attributes":null,"calculation_params":null,"icon_link":null,"link":"http://geocommons.com/overlays/70823.json","extent":[-69.3071,-21.1275,-47.9815,10.059],"geometry_types":["point"],"unique_name":null,"name":"Dataset for search term 'coca'","feature_count":2,"description":"","next_feature":null,"is_raster":false,"short_classification":"Y","stats":{},"features":[{"properties":{"latitude":-21.1275,"longitude":-47.9815,"id":"a6w26l5nbolh"},"type":"Feature","geometry":{"type":"Point","coordinates":[-47.9815,-21.1275]}},{"properties":{"latitude":10.059,"longitude":-69.3071,"id":"a6w26ljt5pta"},"type":"Feature","geometry":{"type":"Point","coordinates":[-69.3071,10.059]}}],"is_temporal":false,"author":{"url":"http://twitter.com","metadata":"","contact_name":"","contact_address":"","source":"","contact_phone":""},"source":"http://twitter.com","pagination":{"sort":null,"start":0,"total":2,"limit":1000000},"state":"complete","tags":"","published":"2014-08-10T11:56:34-04:00","id":70823}