{"type":"FeatureCollection","data_type":"Dataset","url_type":null,"permissions":[{"permissions":{"download":true,"view":true},"group_id":"everyone"}],"classification":null,"title":"Dataset for search term 'twitter'","count":8,"stream_id":71034,"contributor":{"url":"http://geocommons.com/users/17605","name":"vongtv"},"data_attributes":null,"calculation_params":null,"icon_link":null,"link":"http://geocommons.com/overlays/71034.json","extent":[-122.273,19.4885,139.576,41.0781],"geometry_types":["point"],"unique_name":null,"name":"Dataset for search term 'twitter'","feature_count":8,"description":"","next_feature":null,"is_raster":false,"short_classification":"Y","stats":{},"features":[{"properties":{"latitude":19.4885,"longitude":-99.0545,"id":"a6cha8rah0hh"},"type":"Feature","geometry":{"type":"Point","coordinates":[-99.0545,19.4885]}},{"properties":{"latitude":32.7236,"longitude":-117.1648,"id":"a6cha8s27rmq"},"type":"Feature","geometry":{"type":"Point","coordinates":[-117.1648,32.7236]}},{"properties":{"latitude":35.7051,"longitude":139.5759,"id":"a6cha8sq373s"},"type":"Feature","geometry":{"type":"Point","coordinates":[139.5759,35.7051]}},{"properties":{"latitude":35.9733,"longitude":-79.9893,"id":"a6cha93og31p"},"type":"Feature","geometry":{"type":"Point","coordinates":[-79.9893,35.9733]}},{"properties":{"latitude":35.9733,"longitude":-79.9893,"id":"a6cha8y4fyri"},"type":"Feature","geometry":{"type":"Point","coordinates":[-79.9893,35.9733]}},{"properties":{"latitude":37.8639,"longitude":-122.2735,"id":"a6cha94m847a"},"type":"Feature","geometry":{"type":"Point","coordinates":[-122.2735,37.8639]}},{"properties":{"latitude":41.0781,"longitude":-81.5135,"id":"a6cha8uelp0v"},"type":"Feature","geometry":{"type":"Point","coordinates":[-81.5135,41.0781]}},{"properties":{"latitude":41.0781,"longitude":-81.5135,"id":"a6cha8t6evj7"},"type":"Feature","geometry":{"type":"Point","coordinates":[-81.5135,41.0781]}}],"is_temporal":false,"author":{"url":"http://twitter.com","metadata":"","contact_name":"","contact_address":"","source":"","contact_phone":""},"source":"http://twitter.com","pagination":{"sort":null,"start":0,"total":8,"limit":1000000},"state":"complete","tags":"","published":"2014-08-10T12:03:09-04:00","id":71034}