{"type":"FeatureCollection","data_type":"Dataset","url_type":null,"permissions":[{"permissions":{"download":true,"view":true},"group_id":"everyone"}],"classification":null,"title":"Family Tree 1","count":1,"stream_id":71912,"contributor":{"url":"http://geocommons.com/users/17872","name":"rossnixon"},"data_attributes":null,"calculation_params":null,"icon_link":null,"link":"http://geocommons.com/overlays/71912.json","extent":[175.612,-40.355,175.612,-40.355],"geometry_types":["point"],"unique_name":null,"name":"Family Tree 1","feature_count":1,"description":"test only","next_feature":null,"is_raster":false,"short_classification":"Y","stats":{"latitude":{"max":-40.355,"min":-40.355,"median":-40.355},"longitude":{"max":175.611667,"min":175.611667,"median":175.611667}},"features":[{"properties":{"latitude":-40.355,"longitude":175.611667,"id":"a69prxri5ky0","person":"Me"},"type":"Feature","geometry":{"type":"Point","coordinates":[175.611667,-40.355]}}],"is_temporal":false,"author":{"url":"","metadata":"","contact_name":"","contact_address":"","source":"","contact_phone":""},"source":"","pagination":{"sort":null,"start":0,"total":1,"limit":1000000},"state":"complete","tags":"","published":"2014-08-10T12:52:56-04:00","id":71912}