{"type":"FeatureCollection","data_type":"Dataset","url_type":null,"permissions":[{"permissions":{"download":true,"view":true},"group_id":"everyone"}],"classification":null,"title":"geo","count":2,"stream_id":71941,"contributor":{"url":"http://geocommons.com/users/17886","name":"samdelagarza"},"data_attributes":null,"calculation_params":null,"icon_link":null,"link":"http://geocommons.com/overlays/71941.json","extent":[-85.7786,34.3759,-85.7786,34.3759],"geometry_types":["point"],"unique_name":null,"name":"geo","feature_count":2,"description":"","next_feature":null,"is_raster":false,"short_classification":"Y","stats":{"geo_score":{"max":0.625,"mean":0.625,"variance":0.0,"stdev":0.0,"min":0.625,"median":0.625}},"features":[{"properties":{"frisco":"Cleburne","tx":"tx","geo_score":0.625,"11709 harbor rd":"706 N. Wilhite","id":"a66w0jhfqu9v","geo_precision":"city"},"type":"Feature","geometry":{"type":"Point","coordinates":[-85.778579,34.375923]}},{"properties":{"frisco":"Cleburne","tx":"tx","geo_score":0.625,"11709 harbor rd":"715 N. Wilhite","id":"a66w0j6ri8pa","geo_precision":"city"},"type":"Feature","geometry":{"type":"Point","coordinates":[-85.778579,34.375923]}}],"is_temporal":false,"author":{"url":"","metadata":"","contact_name":"","contact_address":"","source":"","contact_phone":""},"source":"","pagination":{"sort":null,"start":0,"total":2,"limit":1000000},"state":"complete","tags":"","published":"2014-08-10T12:53:39-04:00","id":71941}