{"type":"FeatureCollection","data_type":"Dataset","url_type":null,"permissions":[{"permissions":{"download":true,"view":true},"group_id":"everyone"}],"classification":null,"title":"Dataset for search term 'cisco'","count":11,"stream_id":72357,"contributor":{"url":"http://geocommons.com/users/17605","name":"vongtv"},"data_attributes":null,"calculation_params":null,"icon_link":null,"link":"http://geocommons.com/overlays/72357.json","extent":[-121.958,-6.2194,139.992,43.789],"geometry_types":["point"],"unique_name":null,"name":"Dataset for search term 'cisco'","feature_count":11,"description":"","next_feature":null,"is_raster":false,"short_classification":"Y","stats":{},"features":[{"properties":{"latitude":-6.2194,"longitude":106.8343,"id":"a72iej85k0gt"},"type":"Feature","geometry":{"type":"Point","coordinates":[106.8343,-6.2194]}},{"properties":{"latitude":-6.2005,"longitude":106.7841,"id":"a72iejccxttf"},"type":"Feature","geometry":{"type":"Point","coordinates":[106.7841,-6.2005]}},{"properties":{"latitude":1.2793,"longitude":103.8465,"id":"a72iej4xsdqf"},"type":"Feature","geometry":{"type":"Point","coordinates":[103.8465,1.2793]}},{"properties":{"latitude":27.8487,"longitude":-82.6478,"id":"a72iejbhwgi4"},"type":"Feature","geometry":{"type":"Point","coordinates":[-82.6478,27.8487]}},{"properties":{"latitude":29.9427,"longitude":-90.0646,"id":"a72iej8dfv7f"},"type":"Feature","geometry":{"type":"Point","coordinates":[-90.0646,29.9427]}},{"properties":{"latitude":29.9427,"longitude":-90.0646,"id":"a72iejhs0ts6"},"type":"Feature","geometry":{"type":"Point","coordinates":[-90.0646,29.9427]}},{"properties":{"latitude":35.9522,"longitude":139.9924,"id":"a72iejcfmnwv"},"type":"Feature","geometry":{"type":"Point","coordinates":[139.9924,35.9522]}},{"properties":{"latitude":37.4104,"longitude":-121.9577,"id":"a72iejeumw6j"},"type":"Feature","geometry":{"type":"Point","coordinates":[-121.9577,37.4104]}},{"properties":{"latitude":38.9175,"longitude":-77.2167,"id":"a72iej31t1wa"},"type":"Feature","geometry":{"type":"Point","coordinates":[-77.2167,38.9175]}},{"properties":{"latitude":39.0857,"longitude":-76.8614,"id":"a72iej5qfw1l"},"type":"Feature","geometry":{"type":"Point","coordinates":[-76.8614,39.0857]}},{"properties":{"latitude":43.789,"longitude":11.252,"id":"a72iejbba8d3"},"type":"Feature","geometry":{"type":"Point","coordinates":[11.252,43.789]}}],"is_temporal":false,"author":{"url":"http://twitter.com","metadata":"","contact_name":"","contact_address":"","source":"","contact_phone":""},"source":"http://twitter.com","pagination":{"sort":null,"start":0,"total":11,"limit":1000000},"state":"complete","tags":"","published":"2014-08-10T13:13:34-04:00","id":72357}