{"type":"FeatureCollection","data_type":"Dataset","url_type":null,"permissions":[{"permissions":{"download":true,"view":true},"group_id":"everyone"}],"classification":null,"title":"Temporary Points","count":15,"stream_id":7337,"contributor":{"url":"http://geocommons.com/users/2","name":"data"},"data_attributes":null,"calculation_params":null,"icon_link":null,"link":"http://geocommons.com/overlays/7337.json","extent":[-4.25,-33.8833,151.217,55.8333],"geometry_types":["point"],"unique_name":null,"name":"Temporary Points","feature_count":15,"description":"","next_feature":null,"is_raster":false,"short_classification":"Y","stats":{"default0":{"max":14.0,"mean":1.86666666666667,"variance":11.2666666666667,"stdev":3.35658556671309,"min":1.0,"median":1.0}},"features":[{"properties":{"default0":1.0,"id":"a6p0jt032irq"},"type":"Feature","geometry":{"type":"Point","coordinates":[-1.1333333,50.8]}},{"properties":{"default0":1.0,"id":"a6p0jt2yayty"},"type":"Feature","geometry":{"type":"Point","coordinates":[1.4333333,43.6]}},{"properties":{"default0":1.0,"id":"a6p0jt7scsip"},"type":"Feature","geometry":{"type":"Point","coordinates":[10.0166667,48.4]}},{"properties":{"default0":1.0,"id":"a6p0jt0kr5yy"},"type":"Feature","geometry":{"type":"Point","coordinates":[9.2,45.4666667]}},{"properties":{"default0":1.0,"id":"a6p0jt283w6h"},"type":"Feature","geometry":{"type":"Point","coordinates":[-4.25,55.8333333]}},{"properties":{"default0":1.0,"id":"a6p0jtexy2u1"},"type":"Feature","geometry":{"type":"Point","coordinates":[-1.4,50.9]}},{"properties":{"default0":1.0,"id":"a6p0jt8e4y1o"},"type":"Feature","geometry":{"type":"Point","coordinates":[12.4833333,41.9]}},{"properties":{"default0":1.0,"id":"a6p0jt92qvxw"},"type":"Feature","geometry":{"type":"Point","coordinates":[9.2,45.4666667]}},{"properties":{"default0":1.0,"id":"a6p0jt64cub1"},"type":"Feature","geometry":{"type":"Point","coordinates":[151.2166667,-33.8833333]}},{"properties":{"default0":1.0,"id":"a6p0jt07uj0r"},"type":"Feature","geometry":{"type":"Point","coordinates":[-1.0833333,53.9666667]}},{"properties":{"default0":1.0,"id":"a6p0jtc0yefo"},"type":"Feature","geometry":{"type":"Point","coordinates":[-0.15,50.8333333]}},{"properties":{"default0":1.0,"id":"a6p0jt43drx3"},"type":"Feature","geometry":{"type":"Point","coordinates":[-0.15,50.8333333]}},{"properties":{"default0":1.0,"id":"a6p0jt2z8b8t"},"type":"Feature","geometry":{"type":"Point","coordinates":[13.4,52.5166667]}},{"properties":{"default0":1.0,"id":"a6p0jt718vuv"},"type":"Feature","geometry":{"type":"Point","coordinates":[-0.1166667,51.5]}},{"properties":{"default0":14.0,"id":"a6p0jt5bifp9"},"type":"Feature","geometry":{"type":"Point","coordinates":[-0.1166667,51.5]}}],"is_temporal":false,"author":{"url":null,"metadata":null,"contact_name":"","contact_address":"","source":null,"contact_phone":""},"source":null,"pagination":{"sort":null,"start":0,"total":15,"limit":1000000},"state":"complete","tags":"","published":"2014-08-11T08:11:53-04:00","id":7337}