{"type":"FeatureCollection","data_type":"Dataset","url_type":null,"permissions":[{"permissions":{"download":true,"view":true},"group_id":"everyone"}],"classification":null,"title":"Historic State Capitals, Pennsylvania, 1.10.2008","count":5,"stream_id":7399,"contributor":{"url":"http://geocommons.com/users/2","name":"data"},"data_attributes":null,"calculation_params":null,"icon_link":null,"link":"http://geocommons.com/overlays/7399.json","extent":[-76.8835,39.9524,-75.1635,40.2644],"geometry_types":["point"],"unique_name":null,"name":"Historic State Capitals, Pennsylvania, 1.10.2008","feature_count":5,"description":"This dataset displays the Historical State Capitals for the State of Pennsylvania. The locations of every city that were once a capital of Pennsylvania are displayed along with other information:Name of the State  Brief history of the State Capital Longitude of the Capital Latitude of the Capital The Date the City became the Capital State of the Capital City Name of the Capital City Year that the Current Capital's State achieved it's Statehood Name of the State's Current CapitalInformation was obtained on January 10th, 2008 from wikipedia.orghttp://en.wikipedia.org/wiki/List_of_current_and_former_capital_cities_within_the_United_States#Former_national_capitals","next_feature":null,"is_raster":false,"short_classification":"Y","stats":{"Longitude0":{"max":-75.163523,"mean":-75.7350812,"variance":0.654887798046204,"stdev":0.809251381244545,"min":-76.883503,"median":-75.163523},"Date0":{"max":1812.0,"mean":1755.2,"variance":3314.7,"stdev":57.5734313724655,"min":1682.0,"median":1776.0},"Latitude0":{"max":40.264401,"mean":40.0319234,"variance":0.0182700169087999,"stdev":0.135166626460824,"min":39.952351,"median":39.952351}},"features":[{"properties":{"Capital0":"Philadelphia","Statehood ":"Statehood in 1776","State0":"Pennsylvania","Capital St":"Pennsylvania","Notes0":"Capital of the English proprietary Colony of Pennsylvania.","Longitude0":-75.163523,"Date0":1682.0,"Latitude0":39.952351,"id":"a62mzw6p3kg4","Current Ca":"Harrisburg"},"type":"Feature","geometry":{"type":"Point","coordinates":[-75.163523,39.952351]}},{"properties":{"Capital0":"Philadelphia","Statehood ":"Statehood in 1776","State0":"Pennsylvania","Capital St":"Pennsylvania","Notes0":"Capital of the British proprietary Colony of Pennsylvania.","Longitude0":-75.163523,"Date0":1707.0,"Latitude0":39.952351,"id":"a62mzw6ysvi9","Current Ca":"Harrisburg"},"type":"Feature","geometry":{"type":"Point","coordinates":[-75.163523,39.952351]}},{"properties":{"Capital0":"Philadelphia","Statehood ":"Statehood in 1776","State0":"Pennsylvania","Capital St":"Pennsylvania","Notes0":"Capital of the Commonwealth of Pennsylvania. (Capital of the United States of Am","Longitude0":-75.163523,"Date0":1776.0,"Latitude0":39.952351,"id":"a62mzw8p4z58","Current Ca":"Harrisburg"},"type":"Feature","geometry":{"type":"Point","coordinates":[-75.163523,39.952351]}},{"properties":{"Capital0":"Lancaster","Statehood ":"Statehood in 1776","State0":"Pennsylvania","Capital St":"Pennsylvania","Notes0":"Capital of the Commonwealth of Pennsylvania. (Capital of the United States of Am","Longitude0":-76.301334,"Date0":1799.0,"Latitude0":40.038163,"id":"a62mzw9g54uc","Current Ca":"Harrisburg"},"type":"Feature","geometry":{"type":"Point","coordinates":[-76.301334,40.038163]}},{"properties":{"Capital0":"Harrisburg","Statehood ":"Statehood in 1776","State0":"Pennsylvania","Capital St":"Pennsylvania","Notes0":"Capital of the Commonwealth of Pennsylvania.","Longitude0":-76.883503,"Date0":1812.0,"Latitude0":40.264401,"id":"a62mzwhp4kkz","Current Ca":"Harrisburg"},"type":"Feature","geometry":{"type":"Point","coordinates":[-76.883503,40.264401]}}],"is_temporal":false,"author":{"url":"http://en.wikipedia.org/wiki/List_of_current_and_former_capital_cities_within_the_United_States#Former_national_capitals","metadata":null,"contact_name":"","contact_address":"","source":"Wikipedia","contact_phone":""},"source":"http://en.wikipedia.org/wiki/List_of_current_and_former_capital_cities_within_the_United_States#Former_national_capitals","pagination":{"sort":null,"start":0,"total":5,"limit":1000000},"state":"complete","tags":"capitals,historic,of,pennsylvania,state","published":"2008-01-10T12:00:00Z","id":7399}