{"type":"FeatureCollection","data_type":"Dataset","url_type":null,"permissions":[{"permissions":{"download":true,"edit":true,"view":true},"group_id":13923},{"permissions":{"download":true,"view":true},"group_id":"everyone"}],"classification":null,"title":"Zambezi river expedition","count":4,"stream_id":76333,"contributor":{"url":"http://geocommons.com/users/695","name":"Bill"},"data_attributes":null,"calculation_params":null,"icon_link":null,"link":"http://geocommons.com/overlays/76333.json","extent":[22.6881,-17.9114,25.8631,-13.0956],"geometry_types":["point"],"unique_name":null,"name":"Zambezi river expedition","feature_count":4,"description":"","next_feature":null,"is_raster":false,"short_classification":"Y","stats":{"latitude":{"max":-13.095556,"mean":-15.45991475,"variance":4.17967788172758,"stdev":2.04442605190982,"min":-17.911389,"median":-14.7325},"longitude":{"max":25.863056,"mean":23.72388925,"variance":2.09621005979425,"stdev":1.44782943049043,"min":22.688056,"median":23.296667},"distance (km)":{"max":470,"mean":235.5,"variance":36871.0,"stdev":192.018228301378,"min":0,"median":245}},"features":[{"properties":{"latitude":-17.911389,"longitude":25.863056,"id":"a64nhva981rs","distance (km)":470},"type":"Feature","geometry":{"type":"Point","coordinates":[25.863056,-17.911389]}},{"properties":{"latitude":-16.100214,"longitude":23.296667,"id":"a64nhv79phzh","distance (km)":227},"type":"Feature","geometry":{"type":"Point","coordinates":[23.296667,-16.100214]}},{"properties":{"latitude":-14.7325,"longitude":23.047778,"id":"a64nhvak0eb4","distance (km)":245},"type":"Feature","geometry":{"type":"Point","coordinates":[23.047778,-14.7325]}},{"properties":{"latitude":-13.095556,"longitude":22.688056,"id":"a64nhvbbqwqp","distance (km)":0},"type":"Feature","geometry":{"type":"Point","coordinates":[22.688056,-13.095556]}}],"is_temporal":false,"author":{"url":"","metadata":"","contact_name":"","contact_address":"","source":"","contact_phone":""},"source":"","pagination":{"sort":null,"start":0,"total":4,"limit":1000000},"state":"complete","tags":"","published":"2014-08-10T20:12:22-04:00","id":76333}