{"type":"FeatureCollection","data_type":"Dataset","url_type":null,"permissions":[{"permissions":{"download":true,"view":true},"group_id":"everyone"}],"classification":null,"title":"projectPS","count":4,"stream_id":77500,"contributor":{"url":"http://geocommons.com/users/641","name":"keump"},"data_attributes":null,"calculation_params":null,"icon_link":null,"link":"http://geocommons.com/overlays/77500.json","extent":[-122.401,47.5233,-122.378,47.6332],"geometry_types":["point"],"unique_name":null,"name":"projectPS","feature_count":4,"description":"","next_feature":null,"is_raster":false,"short_classification":"Y","stats":{},"features":[{"properties":{"NAME":"53rd Ave Pump Station","id":"a62va3ceo5hh"},"type":"Feature","geometry":{"type":"Point","coordinates":[-122.401210686842,47.5835279448588]}},{"properties":{"NAME":"Barton Pump Station","id":"a62va3cyflrw"},"type":"Feature","geometry":{"type":"Point","coordinates":[-122.393533291198,47.5233398003212]}},{"properties":{"NAME":"Interbay Pump Station","id":"a62va3fb24xm"},"type":"Feature","geometry":{"type":"Point","coordinates":[-122.377717557062,47.6331594799735]}},{"properties":{"NAME":"Murray Pump Station","id":"a62va3eg9bdu"},"type":"Feature","geometry":{"type":"Point","coordinates":[-122.396674012115,47.5398449706369]}}],"is_temporal":false,"author":{"url":"","metadata":"","contact_name":"","contact_address":"","source":"","contact_phone":""},"source":"","pagination":{"sort":null,"start":0,"total":4,"limit":1000000},"state":"complete","tags":"","published":"2014-08-10T21:19:38-04:00","id":77500}