{"type":"FeatureCollection","data_type":"Dataset","url_type":null,"permissions":[{"permissions":{"download":true,"view":true},"group_id":"everyone"}],"classification":null,"title":"Discussions &quot;frontière linguistique&quot; wikipedia FR","count":3,"stream_id":7796,"contributor":{"url":"http://geocommons.com/users/1713","name":"alexcyclo"},"data_attributes":null,"calculation_params":null,"icon_link":null,"link":"http://geocommons.com/overlays/7796.json","extent":[4.3333,50.0833,5.2167,50.8333],"geometry_types":["point"],"unique_name":null,"name":"Discussions \"frontière linguistique\" wikipedia FR","feature_count":3,"description":"","next_feature":null,"is_raster":false,"short_classification":"Y","stats":{"fr":{"max":7,"mean":3.0,"variance":12.0,"stdev":3.46410161513775,"min":1,"median":1},"lat":{"max":50.833302,"mean":50.4777683333333,"variance":0.141761814400333,"stdev":0.376512701512622,"min":50.083302,"median":50.516701},"long":{"max":5.2167,"mean":4.71666666666667,"variance":0.205307223333333,"stdev":0.453108401305177,"min":4.3333,"median":4.6}},"features":[{"properties":{"city":"Brussels","fr":7,"id":"a638tu9vcjbq","lat":50.833302,"long":4.3333},"type":"Feature","geometry":{"type":"Point","coordinates":[4.3333,50.833302]}},{"properties":{"city":"Sombreffe","fr":1,"id":"a638tu74uuk3","lat":50.516701,"long":4.6},"type":"Feature","geometry":{"type":"Point","coordinates":[4.6,50.516701]}},{"properties":{"city":"Tellin","fr":1,"id":"a638tuc8tjvs","lat":50.083302,"long":5.2167},"type":"Feature","geometry":{"type":"Point","coordinates":[5.2167,50.083302]}}],"is_temporal":false,"author":{"url":"","metadata":"","contact_name":"","contact_address":"","source":"","contact_phone":""},"source":"","pagination":{"sort":null,"start":0,"total":3,"limit":1000000},"state":"complete","tags":"","published":"2014-08-11T08:55:33-04:00","id":7796}