{"type":"FeatureCollection","data_type":"Dataset","url_type":null,"permissions":[{"permissions":{"download":true,"view":true},"group_id":"everyone"}],"classification":null,"title":"006","count":6,"stream_id":78992,"contributor":{"url":"http://geocommons.com/users/18700","name":"kikimwf"},"data_attributes":null,"calculation_params":null,"icon_link":null,"link":"http://geocommons.com/overlays/78992.json","extent":[104.07,29.57,121.47,36.19],"geometry_types":["point"],"unique_name":null,"name":"006","feature_count":6,"description":"","next_feature":null,"is_raster":false,"short_classification":"Y","stats":{"capacity (mn m2)":{"max":60,"mean":36.0,"variance":530.0,"stdev":23.0217288664427,"min":10,"median":30},"lon":{"max":121.47,"mean":114.142,"variance":68.72417,"stdev":8.29000422195309,"min":104.07,"median":117.12},"lat":{"max":36.19,"mean":31.778,"variance":6.54231999999999,"stdev":2.55779592618332,"min":29.57,"median":31.23}},"features":[{"properties":{"city":null,"capacity (mn m2)":null,"lon":null,"provice":null,"id":"a6jrbfu24u5x","group":null,"lat":null},"type":"Feature","geometry":null},{"properties":{"city":"Chengdu","capacity (mn m2)":10,"lon":104.07,"provice":"Sichuan","id":"a6jrbfrc3i02","group":"LAFARGE","lat":30.67},"type":"Feature","geometry":{"type":"Point","coordinates":[104.07,30.67]}},{"properties":{"city":"Chongqing","capacity (mn m2)":20,"lon":106.58,"provice":"Chongqing","id":"a6jrbftrfb3r","group":"LAFARGE","lat":29.57},"type":"Feature","geometry":{"type":"Point","coordinates":[106.58,29.57]}},{"properties":{"city":"Shanghai","capacity (mn m2)":60,"lon":121.47,"provice":"Shanghai","id":"a6jrbfmrui3m","group":"LAFARGE","lat":31.23},"type":"Feature","geometry":{"type":"Point","coordinates":[121.47,31.23]}},{"properties":{"city":"Tai'an","capacity (mn m2)":60,"lon":117.12,"provice":"Shandong","id":"a6jrbfw4n7hw","group":"LAFARGE","lat":36.19},"type":"Feature","geometry":{"type":"Point","coordinates":[117.12,36.19]}},{"properties":{"city":"Shanghai","capacity (mn m2)":30,"lon":121.47,"provice":"Shanghai","id":"a6jrbfviykh4","group":"LAFARGE","lat":31.23},"type":"Feature","geometry":{"type":"Point","coordinates":[121.47,31.23]}}],"is_temporal":false,"author":{"url":"","metadata":"","contact_name":"","contact_address":"","source":"","contact_phone":""},"source":"","pagination":{"sort":null,"start":0,"total":6,"limit":1000000},"state":"complete","tags":"","published":"2014-08-10T22:59:13-04:00","id":78992}