{"type":"FeatureCollection","data_type":"Dataset","url_type":null,"permissions":[{"permissions":{"download":true,"view":true},"group_id":"everyone"}],"classification":null,"title":"Existing Substation","count":1,"stream_id":79993,"contributor":{"url":"http://geocommons.com/users/12617","name":"quintonl"},"data_attributes":null,"calculation_params":null,"icon_link":null,"link":"http://geocommons.com/overlays/79993.json","extent":[25.9245,-28.9082,25.9245,-28.9082],"geometry_types":["point"],"unique_name":null,"name":"Existing Substation","feature_count":1,"description":"","next_feature":null,"is_raster":false,"short_classification":"Y","stats":{},"features":[{"properties":{"Name":"132kV","id":"a6gb0lxjfq25"},"type":"Feature","geometry":{"type":"Point","coordinates":[25.9245268452122,-28.9082230294756]}}],"is_temporal":false,"author":{"url":"","metadata":"","contact_name":"","contact_address":"","source":"","contact_phone":""},"source":"","pagination":{"sort":null,"start":0,"total":1,"limit":1000000},"state":"complete","tags":"","published":"2014-08-11T00:09:06-04:00","id":79993}