{"type":"FeatureCollection","data_type":"Dataset","url_type":null,"permissions":[{"permissions":{"download":true,"view":true},"group_id":"everyone"}],"classification":null,"title":"Polygons on-off\t\t\t\t","count":18,"stream_id":80349,"contributor":{"url":"http://geocommons.com/users/19707","name":"caughron"},"data_attributes":null,"calculation_params":null,"icon_link":null,"link":"http://geocommons.com/overlays/80349.json","extent":[-119.047,34.9946,-118.566,35.4216],"geometry_types":["point"],"unique_name":null,"name":"Polygons on-off\t\t\t\t","feature_count":18,"description":"","next_feature":null,"is_raster":false,"short_classification":"Y","stats":{},"features":[{"properties":{"name":"Air-5","id":"a67g9iiy9mfq"},"type":"Feature","geometry":null},{"properties":{"name":"Air-5","id":"a67g9ikuri6t"},"type":"Feature","geometry":null},{"properties":{"name":"Air-5","id":"a67g9imbjogt"},"type":"Feature","geometry":null},{"properties":{"name":"Air-5","id":"a67g9ilvoxn1"},"type":"Feature","geometry":null},{"properties":{"name":"Air-5","id":"a67g9ipp7zge"},"type":"Feature","geometry":null},{"properties":{"name":"H-407","id":"a67g9ilb187e"},"type":"Feature","geometry":null},{"properties":{"name":"H-407","id":"a67g9ihibc71"},"type":"Feature","geometry":null},{"properties":{"name":"H-407","id":"a67g9iusx2yz"},"type":"Feature","geometry":null},{"properties":{"name":"H-407","id":"a67g9it8dlxv"},"type":"Feature","geometry":null},{"properties":{"name":"H-407","id":"a67g9iug8d5j"},"type":"Feature","geometry":null},{"properties":{"name":"H-408","id":"a67g9iuk4r8t"},"type":"Feature","geometry":null},{"properties":{"name":"H-408","id":"a67g9inh9srd"},"type":"Feature","geometry":null},{"properties":{"name":"H-408","id":"a67g9iuza1tv"},"type":"Feature","geometry":null},{"properties":{"name":"H-408","id":"a67g9ir5qp8q"},"type":"Feature","geometry":null},{"properties":{"name":"H-408","id":"a67g9ix3dvi6"},"type":"Feature","geometry":null},{"properties":{"name":"KCSO - Air5","id":"a67g9iviz9ep"},"type":"Feature","geometry":{"type":"Point","coordinates":[-119.046865,35.421587]}},{"properties":{"name":"Keene - H408","id":"a67g9itd9cxl"},"type":"Feature","geometry":{"type":"Point","coordinates":[-118.566102,35.22507]}},{"properties":{"name":"Wheeler Ridge - H407","id":"a67g9imedtq2"},"type":"Feature","geometry":{"type":"Point","coordinates":[-118.9493,34.994617]}}],"is_temporal":false,"author":{"url":"","metadata":"","contact_name":"","contact_address":"","source":"","contact_phone":""},"source":"","pagination":{"sort":null,"start":0,"total":18,"limit":1000000},"state":"complete","tags":"","published":"2014-08-10T11:14:00-04:00","id":80349}