{"type":"FeatureCollection","data_type":"Dataset","url_type":null,"permissions":[{"permissions":{"download":true,"view":true},"group_id":"everyone"}],"classification":null,"title":"zus","count":16,"stream_id":80636,"contributor":{"url":"http://geocommons.com/users/19760","name":"jvinzent"},"data_attributes":null,"calculation_params":null,"icon_link":null,"link":"http://geocommons.com/overlays/80636.json","extent":[5.30502,43.229,5.48827,43.3754],"geometry_types":["point"],"unique_name":null,"name":"zus","feature_count":16,"description":"","next_feature":null,"is_raster":false,"short_classification":"Y","stats":{"population en zus":{"max":48758,"mean":13466.5625,"variance":247417305.595833,"stdev":15729.5043022923,"min":0,"median":9710},"lng":{"max":5.4882679,"mean":5.3945423875,"variance":0.00180445296358783,"stdev":0.0424788531340929,"min":5.305023,"median":5.38872},"population":{"max":86826,"mean":52440.1875,"variance":376022878.5625,"stdev":19391.3093565778,"min":17383,"median":50140},"lat":{"max":43.3753856,"mean":43.30475745,"variance":0.00175003363846803,"stdev":0.0418334033813653,"min":43.2290357,"median":43.305868}},"features":[{"properties":{"population en zus":5904,"lng":5.4463322,"population":75329,"arrondissement":"9e","id":"a69i6gnier3b","lat":43.2290357},"type":"Feature","geometry":{"type":"Point","coordinates":[5.4463322,43.2290357]}},{"properties":{"population en zus":0,"lng":5.3782513,"population":77882,"arrondissement":"8e","id":"a69i6h0pjwe2","lat":43.2370789},"type":"Feature","geometry":{"type":"Point","coordinates":[5.3782513,43.2370789]}},{"properties":{"population en zus":412,"lng":5.4306141,"population":50140,"arrondissement":"10e","id":"a69i6h1hzx32","lat":43.2731832},"type":"Feature","geometry":{"type":"Point","coordinates":[5.4306141,43.2731832]}},{"properties":{"population en zus":0,"lng":5.3547034,"population":35444,"arrondissement":"7e","id":"a69i6go7svvb","lat":43.2839895},"type":"Feature","geometry":{"type":"Point","coordinates":[5.3547034,43.2839895]}},{"properties":{"population en zus":14687,"lng":5.4882679,"population":55699,"arrondissement":"11e","id":"a69i6gp0a600","lat":43.2848916},"type":"Feature","geometry":{"type":"Point","coordinates":[5.4882679,43.2848916]}},{"properties":{"population en zus":1524,"lng":5.3808683,"population":43217,"arrondissement":"6e","id":"a69i6gn5s8c4","lat":43.2875818},"type":"Feature","geometry":{"type":"Point","coordinates":[5.3808683,43.2875818]}},{"properties":{"population en zus":0,"lng":5.3965729,"population":44261,"arrondissement":"5e","id":"a69i6gxtlnws","lat":43.2916612},"type":"Feature","geometry":{"type":"Point","coordinates":[5.3965729,43.2916612]}},{"properties":{"population en zus":27778,"lng":5.3821768,"population":41027,"arrondissement":"1er","id":"a69i6gpo4eai","lat":43.300771},"type":"Feature","geometry":{"type":"Point","coordinates":[5.3821768,43.300771]}},{"properties":{"population en zus":0,"lng":5.4018087,"population":46617,"arrondissement":"4e","id":"a69i6gvyrnpn","lat":43.305868},"type":"Feature","geometry":{"type":"Point","coordinates":[5.4018087,43.305868]}},{"properties":{"population en zus":503,"lng":5.4253757,"population":57908,"arrondissement":"12e","id":"a69i6gs7wd07","lat":43.3071618},"type":"Feature","geometry":{"type":"Point","coordinates":[5.4253757,43.3071618]}},{"properties":{"population en zus":18287,"lng":5.3808683,"population":44651,"arrondissement":"3e","id":"a69i6gqvyqrv","lat":43.3116714},"type":"Feature","geometry":{"type":"Point","coordinates":[5.3808683,43.3116714]}},{"properties":{"population en zus":19356,"lng":5.3599355,"population":25559,"arrondissement":"2e","id":"a69i6gr71r8f","lat":43.3174701},"type":"Feature","geometry":{"type":"Point","coordinates":[5.3599355,43.3174701]}},{"properties":{"population en zus":39655,"lng":5.38872,"population":61317,"arrondissement":"14e","id":"a69i6gtl9r6b","lat":43.3426011},"type":"Feature","geometry":{"type":"Point","coordinates":[5.38872,43.3426011]}},{"properties":{"population en zus":48758,"lng":5.3677844,"population":75783,"arrondissement":"15e","id":"a69i6gv80pdc","lat":43.3628362},"type":"Feature","geometry":{"type":"Point","coordinates":[5.3677844,43.3628362]}},{"properties":{"population en zus":28891,"lng":5.4253757,"population":86826,"arrondissement":"13e","id":"a69i6gme9u8v","lat":43.3649321},"type":"Feature","geometry":{"type":"Point","coordinates":[5.4253757,43.3649321]}},{"properties":{"population en zus":9710,"lng":5.305023,"population":17383,"arrondissement":"16e","id":"a69i6gtftvjf","lat":43.3753856},"type":"Feature","geometry":{"type":"Point","coordinates":[5.305023,43.3753856]}}],"is_temporal":false,"author":{"url":"","metadata":"","contact_name":"","contact_address":"","source":"","contact_phone":""},"source":"","pagination":{"sort":null,"start":0,"total":16,"limit":1000000},"state":"complete","tags":"","published":"2014-08-10T11:32:21-04:00","id":80636}