{"type":"FeatureCollection","url":"http://maps.google.ca/maps/ms?vps=1&jsv=304d&hl=en&ie=UTF8&msa=0&output=georss&msid=208195469145691961666.000497efd9c72f3bacc4c","data_type":"Data Feed","url_type":"rss","permissions":[{"permissions":{"download":true,"view":true},"group_id":"everyone"}],"classification":null,"title":"Rodney Chew State Farm Insurance","count":1,"stream_id":81582,"contributor":{"url":"http://geocommons.com/users/19929","name":"rodneychew"},"data_attributes":null,"calculation_params":null,"icon_link":null,"link":"http://geocommons.com/overlays/81582.json","extent":[-97.5682,35.582,-97.5682,35.582],"geometry_types":["point"],"unique_name":null,"name":"Rodney Chew State Farm Insurance","feature_count":1,"description":"Oklahoma City State Farm Insurance Agent Rodney Chew provides free insurance quotes for auto insurance, home insurance, life insurance, commercial insurance, renters insurance and more.","next_feature":null,"is_raster":false,"short_classification":"Y","stats":{"georss:elev":{"max":0.0,"min":0.0,"median":0.0}},"features":[{"properties":{"guid":"000497efd9ca9dc553099","title":"Rodney Chew State Farm Insurance","published":{"end_time":"2010/12/21 13:31:54 -0500","original":"Tue, 21 Dec 2010 18:31:53 +0000","granularity":"sec","time":"2010/12/21 13:31:53 -0500"},"description":"Oklahoma City State Farm Insurance Agent Rodney Chew provides free insurance quotes for auto insurance, home insurance, life insurance, commercial insurance, renters insurance and more. <a href=\"http://www.rodchew.net/\">Rodney Chew State Farm Insurance</a>.","id":"a645tkwt1dik","georss:elev":0.0},"type":"Feature","geometry":{"type":"Point","coordinates":[-97.568161,35.58202]}}],"is_temporal":true,"author":{"url":"","metadata":"","contact_name":"","contact_address":"","source":"","contact_phone":""},"source":"","pagination":{"sort":null,"start":0,"total":1,"limit":1000000},"state":"complete","tags":"insurance,ok,oklahoma,rod chew","published":"2014-08-10T12:39:47-04:00","id":81582}