{"type":"FeatureCollection","data_type":"Dataset","url_type":null,"permissions":[{"permissions":{"download":true,"view":true},"group_id":"everyone"}],"classification":null,"title":"Fort Lauderdale Limo","count":1,"stream_id":81757,"contributor":{"url":"http://geocommons.com/users/11586","name":"bharken"},"data_attributes":null,"calculation_params":null,"icon_link":null,"link":"http://geocommons.com/overlays/81757.json","extent":[-80.1389,26.1193,-80.1389,26.1193],"geometry_types":["point"],"unique_name":null,"name":"Fort Lauderdale Limo","feature_count":1,"description":"Fort Lauderdale limo service is our specialty. It is our goal to help you make the most of the Fort Lauderdale limo nightlife. If you have plans to go out in a Fort Lauderdale limousine, let us be your designated driver with our luxury limousine service. Fort Lauderdale is a great place to rent a limousine. Not only do you look important riding around in one of our state of the art stretch limousines, but you can have as much fun as you want without having to worry about driving home. We have very reasonable rates that can turn a regular night out into a spectacular night out with our Fort Lauderdale Limo service.","next_feature":null,"is_raster":false,"short_classification":"Y","stats":{},"features":[{"properties":{"name":"Fort Lauderdale Limo","city":"Fort Lauderdale","region":"US-FL","balloon_text":"<b><a href=\"http://maps.google.com/maps/place?cid=4609228272408458976&amp;q=Fort+Lauderdale+Limo+(954)+606-0300&amp;hl=en&amp;cad=src:kml_balloon&amp;ei=bh8STcjSC5SwugOn-LH0Cw\">$[name]</a></b>401 East Las Olas BoulevardFort Lauderdale, FL 33301(954) 606-0300<a href=\"http://fortlauderdalefllimo.net/\">fortlauderdalefllimo.net</a><a href=\"/maps/place?cid=4609228272408458976&amp;q=Fort+Lauderdale+Limo+(954)+606-0300&amp;hl=en&amp;cd=1&amp;cad=src:ppphoto&amp;ei=bh8STcjSC5SwugOn-LH0Cw\"><img src=\"http://lh5.googleusercontent.com/public/z_t_H3Mkg4Qi3q6CY9u2KfgCJsfvs7OBpigLgM3wzFRh4GaXn490HmfX6m5KsQtr-UfqaJs3oM4A17fvQw7aZjRc0e20ESJpRYx4cflDYteVbWqTDVxiixxA\"></a>  $[geDirections]","contents":"Fort Lauderdale Limo","id":"a68wyhphdh9r"},"type":"Feature","geometry":{"type":"Point","coordinates":[-80.138923,26.119329]}}],"is_temporal":false,"author":{"url":"http://bbs.keyhole.com/ubb/ubbthreads.php?ubb=showflat&Number=1389162&#Post1389162","metadata":"","contact_name":"","contact_address":"401 East Las Olas Boulevard, Fort Lauderdale, FL 33301","source":"Google Earth Community","contact_phone":"(954) 606-0300"},"source":"http://bbs.keyhole.com/ubb/ubbthreads.php?ubb=showflat&Number=1389162&#Post1389162","pagination":{"sort":null,"start":0,"total":1,"limit":1000000},"state":"complete","tags":"limo,limo service,limo services,limos,limousine,limousine service,limousine services,limousines","published":"2014-08-10T12:56:33-04:00","id":81757}