{"type":"FeatureCollection","data_type":"Data Feed","url_type":"csv","permissions":[{"permissions":{"download":true,"view":true},"group_id":"everyone"}],"classification":null,"title":"Green Fire Showings","count":2,"stream_id":85503,"contributor":{"url":"http://geocommons.com/users/15391","name":"ecuadorn"},"data_attributes":null,"calculation_params":null,"icon_link":null,"link":"http://geocommons.com/overlays/85503.json","extent":[-122.47,35.0692,-106.654,37.7361],"geometry_types":["point"],"unique_name":null,"name":"Green Fire Showings","feature_count":2,"description":"","next_feature":null,"is_raster":false,"short_classification":"Y","stats":{"end date":{"max":"2011/02/27 00:00:00 -0500","mean":"2011/02/16 00:00:00 -0500","variance":1806520320000.0,"stdev":1344068.56967939,"min":"2011/02/05 00:00:00 -0500","median":"2011/02/27 00:00:00 -0500"},"start date":{"max":"2011/02/26 00:00:00 -0500","mean":"2011/02/15 12:00:00 -0500","variance":1646023680000.0,"stdev":1282974.54378487,"min":"2011/02/05 00:00:00 -0500","median":"2011/02/26 00:00:00 -0500"}},"features":[{"properties":{"end date":{"end_time":"2011/02/06 00:00:00 -0500","original":"2/5/2011","granularity":"day","time":"2011/02/05 00:00:00 -0500"},"start date":{"end_time":"2011/02/06 00:00:00 -0500","original":"2/5/2011","granularity":"day","time":"2011/02/05 00:00:00 -0500"},"url":null,"venue name":"National Hispanic Cultural Center","id":"a6fk9k014f5x","contact number":"(505) 246-2261","geocodeableaddress":"1701 4th St Albuquerque  NM USA"},"type":"Feature","geometry":{"type":"Point","coordinates":[-106.654465,35.069222]}},{"properties":{"end date":{"end_time":"2011/02/28 00:00:00 -0500","original":"2/27/2011","granularity":"day","time":"2011/02/27 00:00:00 -0500"},"start date":{"end_time":"2011/02/27 00:00:00 -0500","original":"2/26/2011","granularity":"day","time":"2011/02/26 00:00:00 -0500"},"url":null,"venue name":"Northern Sierra Partnership","id":"a6fk9juvqj45","contact number":null,"geocodeableaddress":"San Fransico  CA USA"},"type":"Feature","geometry":{"type":"Point","coordinates":[-122.469886,37.736112]}}],"is_temporal":true,"author":{"url":"","metadata":"","contact_name":"","contact_address":"","source":"","contact_phone":""},"source":"","pagination":{"sort":null,"start":0,"total":2,"limit":1000000},"state":"complete","tags":"","published":"2014-08-10T18:31:32-04:00","id":85503}