{"type":"FeatureCollection","data_type":"Dataset","url_type":null,"permissions":[{"permissions":{"download":true,"view":true},"group_id":"everyone"}],"classification":null,"title":"List1 GF 3feat","count":3,"stream_id":90111,"contributor":{"url":"http://geocommons.com/users/18452","name":"muellth"},"data_attributes":null,"calculation_params":null,"icon_link":null,"link":"http://geocommons.com/overlays/90111.json","extent":[8.51751,47.3057,8.72441,47.5799],"geometry_types":["point"],"unique_name":null,"name":"List1 GF 3feat","feature_count":3,"description":"","next_feature":null,"is_raster":false,"short_classification":"Y","stats":{"latitude":{"max":47.5798926,"mean":47.4316776,"variance":0.0191624556576403,"stdev":0.138428521835785,"min":47.3057368,"median":47.4094034},"longitude":{"max":8.7244135,"mean":8.58935706666667,"variance":0.0136988205130434,"stdev":0.117041960480177,"min":8.5175114,"median":8.5261463}},"features":[{"properties":{"latitude":47.3057368,"longitude":8.5261463,"id":"a6bxz8e7fkuw"},"type":"Feature","geometry":{"type":"Point","coordinates":[8.5261463,47.3057368]}},{"properties":{"latitude":47.5798926,"longitude":8.5175114,"id":"a6bxz8f7y8d1"},"type":"Feature","geometry":{"type":"Point","coordinates":[8.5175114,47.5798926]}},{"properties":{"latitude":47.4094034,"longitude":8.7244135,"id":"a6bxz8lp0kej"},"type":"Feature","geometry":{"type":"Point","coordinates":[8.7244135,47.4094034]}}],"is_temporal":false,"author":{"url":"","metadata":"","contact_name":"","contact_address":"","source":"","contact_phone":""},"source":"","pagination":{"sort":null,"start":0,"total":3,"limit":1000000},"state":"complete","tags":"","published":"2014-08-10T11:06:28-04:00","id":90111}