{"type":"FeatureCollection","data_type":"Dataset","url_type":null,"permissions":[{"permissions":{"download":true,"view":true},"group_id":"everyone"}],"classification":null,"title":"Foursquare - Autoracing","count":3,"stream_id":90876,"contributor":{"url":"http://geocommons.com/users/12003","name":"LauraHale"},"data_attributes":null,"calculation_params":null,"icon_link":null,"link":"http://geocommons.com/overlays/90876.json","extent":[149.135,-35.2195,149.135,-35.2195],"geometry_types":["point"],"unique_name":null,"name":"Foursquare - Autoracing","feature_count":3,"description":"","next_feature":null,"is_raster":false,"short_classification":"Y","stats":{"latitude":{"max":-35.21949,"mean":-35.21949,"variance":0.0,"stdev":0.0,"min":-35.21949,"median":-35.21949},"checkins count":{"max":2,"mean":1.66666666666667,"variance":0.333333333333333,"stdev":0.577350269189626,"min":1,"median":2},"date checked":{"max":"2011/01/08 00:00:00 -0500","mean":"2011/01/07 00:00:00 -0500","variance":7464960000.0,"stdev":86400.0,"min":"2011/01/06 00:00:00 -0500","median":"2011/01/07 00:00:00 -0500"},"longitude":{"max":149.13472,"mean":149.13472,"variance":0.0,"stdev":0.0,"min":149.13472,"median":149.13472}},"features":[{"properties":{"city":"Mitchell","latitude":-35.21949,"checkins count":2,"date checked":{"end_time":"2011/01/08 00:00:00 -0500","original":"7-Jan-11","granularity":"day","time":"2011/01/07 00:00:00 -0500"},"facility":"Exhibition Park in Canberra","team 1":null,"longitude":149.13472,"team 2":null,"league":"Street Machine Summernats Car Festival","link":"http://foursquare.com/venue/372519","id":"a6bemtc8ovq2","sport":"Auto racing","state":"Australian Capital Territory"},"type":"Feature","geometry":{"type":"Point","coordinates":[149.13472,-35.21949]}},{"properties":{"city":"Mitchell","latitude":-35.21949,"checkins count":2,"date checked":{"end_time":"2011/01/07 00:00:00 -0500","original":"6-Jan-11","granularity":"day","time":"2011/01/06 00:00:00 -0500"},"facility":"Exhibition Park in Canberra","team 1":null,"longitude":149.13472,"team 2":null,"league":"Street Machine Summernats Car Festival","link":"http://foursquare.com/venue/372519","id":"a6bemtscey7z","sport":"Auto racing","state":"Australian Capital Territory"},"type":"Feature","geometry":{"type":"Point","coordinates":[149.13472,-35.21949]}},{"properties":{"city":"Mitchell","latitude":-35.21949,"checkins count":1,"date checked":{"end_time":"2011/01/09 00:00:00 -0500","original":"8-Jan-11","granularity":"day","time":"2011/01/08 00:00:00 -0500"},"facility":"Exhibition Park in Canberra","team 1":null,"longitude":149.13472,"team 2":null,"league":"Street Machine Summernats Car Festival","link":"http://foursquare.com/venue/372519","id":"a6bemtljdrz6","sport":"Auto racing","state":"Australian Capital Territory"},"type":"Feature","geometry":{"type":"Point","coordinates":[149.13472,-35.21949]}}],"is_temporal":true,"author":{"url":"","metadata":"","contact_name":"","contact_address":"","source":"","contact_phone":""},"source":"","pagination":{"sort":null,"start":0,"total":3,"limit":1000000},"state":"complete","tags":"","published":"2014-08-10T12:21:43-04:00","id":90876}