{"type":"FeatureCollection","data_type":"Dataset","url_type":null,"permissions":[{"permissions":{"download":true,"view":true},"group_id":"everyone"}],"classification":null,"title":"Salem United Methodist Church","count":1,"stream_id":94523,"contributor":{"url":"http://geocommons.com/users/22324","name":"salemumcorange"},"data_attributes":null,"calculation_params":null,"icon_link":null,"link":"http://geocommons.com/overlays/94523.json","extent":[-93.7326,30.101,-93.7326,30.101],"geometry_types":["point"],"unique_name":null,"name":"Salem United Methodist Church","feature_count":1,"description":"Salem United Methodist Church, \r\n402 W. John Ave.\r\nOrange, TX 77630\r\n(409)883-2611\r\nsalemorange@sbcglobal.net","next_feature":null,"is_raster":false,"short_classification":"Y","stats":{},"features":[{"properties":{"name":"Salem United Methodist Church","description":"\r\n              <a href=\"http://www.salemumcorange.org\">Salem United Methodist Church</a><img src=\"http://www.salemumcorange.org/pictures/Salem_Small.jpg\">\r\n                 402 W.John Ave.\r\n                 Orange, Texas 77630\r\n               \t(409)883-2611\r\n                 E-mail: salemorange@sbcglobal.net\r\n                 Sunday School - 9:30 A.M.\r\n                 Sunday Worship - 11:00 A.M.\r\n                 Wacky Tuesday Bible Study - 12:00 Noon\r\n                 Wednesday Night \"Upbeat\" Bible Study - 6:00 P.M.\r\n\t\t\tGreetings from the Congregation and Ministries of Salem United Methodist Church. We welcome you to share the joy of our Lord through worship and teaching.\r\nHere, you will be part of a loving family dedicated to reaching out to all in need of care and healing. \r\n\r\nWe are an innovative and progressive community based church that has many active ministries that will appeal to all age groups. Whether it is traditional worship or simply fellowship we have something to meet your needs. Please visit our website at http://www.salemumcorange.org for more information. \r\n\r\nJoin us this Sunday in worship and take the first step towards spiritual rejuvenation.","id":"a6304k29u4fd"},"type":"Feature","geometry":{"type":"Point","coordinates":[-93.7326,30.10096]}}],"is_temporal":false,"author":{"url":"http://www.salemumcorange.org","metadata":"http://www.salemumcorange.org/salem.kml","contact_name":"Salem United Methodist Church","contact_address":"402 W. John Ave.\r\nOrange, TX 77630","source":"Salem United Methodist Church","contact_phone":"(409)883-2611"},"source":"http://www.salemumcorange.org","pagination":{"sort":null,"start":0,"total":1,"limit":1000000},"state":"complete","tags":"methodist church,orange texas,orange tx,salem united methodist church,umc,united methodist church","published":"2011-02-20T17:00:00Z","id":94523}