{"type":"FeatureCollection","url":"http://maps.google.com/maps/ms?vps=2&jsv=317d&hl=en&ie=UTF8&msa=0&output=georss&msid=209723771496233076694.00049dabef0370d6064bc","data_type":"Data Feed","url_type":"rss","permissions":[{"permissions":{"download":true,"view":true},"group_id":"everyone"}],"classification":null,"title":"Bradley Hamner State Farm Insurance","count":1,"stream_id":97617,"contributor":{"url":"http://geocommons.com/users/22948","name":"bradleyhamner"},"data_attributes":null,"calculation_params":null,"icon_link":null,"link":"http://geocommons.com/overlays/97617.json","extent":[-86.5675,34.6332,-86.5675,34.6332],"geometry_types":["point"],"unique_name":null,"name":"Bradley Hamner State Farm Insurance","feature_count":1,"description":"State Farm Insurance agent Bradley Hamner providing free insurance quotes for auto insurance, home insurance, life insurance, renters insurance, business insurance and car insurance in Huntsville, AL. ","next_feature":null,"is_raster":false,"short_classification":"Y","stats":{"published":{"max":"2011/03/04 13:01:21 -0500","min":"2011/03/04 13:01:21 -0500","median":"2011/03/04 13:01:21 -0500"},"georss:elev":{"max":0.0,"min":0.0,"median":0.0}},"features":[{"properties":{"title":"Bradley Hamner State Farm Insurance","guid":"00049dabef047292fb23e","published":{"end_time":"2011/03/04 13:01:22 -0500","original":"Fri, 04 Mar 2011 18:01:21 +0000","granularity":"sec","time":"2011/03/04 13:01:21 -0500"},"description":"State Farm Insurance agent Bradley Hamner providing free insurance quotes for auto insurance, home insurance, life insurance, renters insurance, business insurance and car insurance in Huntsville, AL. <a href=\"http://www.thehamneragency.com/\">Huntsville AL Auto Insurance</a>, <a href=\"http://www.thehamneragency.com/\">Huntsville AL Home Insurance</a>,<a href=\"http://www.thehamneragency.com/\">Huntsville AL Insurance</a>Address: 11310-C Memorial Parkway SW, Huntsville, AL 35803-2126Phone: (256) 489-1818Website: <a href=\"http://www.thehamneragency.com/\">www.thehamneragency.com</a>","id":"a62o8azds1uo","georss:elev":0.0},"type":"Feature","geometry":{"type":"Point","coordinates":[-86.567459,34.633244]}}],"is_temporal":true,"author":{"url":"","metadata":"","contact_name":"","contact_address":"","source":"","contact_phone":""},"source":"","pagination":{"sort":null,"start":0,"total":1,"limit":1000000},"state":"complete","tags":"al,farm,huntsville,insurance,state","published":"2014-08-10T21:57:41-04:00","id":97617}