{"type":"FeatureCollection","data_type":"Dataset","url_type":null,"permissions":[{"permissions":{"download":true,"view":true},"group_id":"everyone"}],"classification":null,"title":"2010 Planet Connect Student Grant Winners","count":10,"stream_id":98750,"contributor":{"url":"http://geocommons.com/users/22097","name":"jessharig"},"data_attributes":null,"calculation_params":null,"icon_link":null,"link":"http://geocommons.com/overlays/98750.json","extent":[-119.046,25.8951,-70.74,43.2795],"geometry_types":["point"],"unique_name":null,"name":"2010 Planet Connect Student Grant Winners","feature_count":10,"description":"","next_feature":null,"is_raster":false,"short_classification":"Y","stats":{},"features":[{"properties":{"geo_score":0.714,"zip code":"33010","id":"a65pmadd3psz","geo_precision":"zip","student":"Daniel Brooks"},"type":"Feature","geometry":{"type":"Point","coordinates":[-80.378108,25.895095]}},{"properties":{"geo_score":0.714,"zip code":"91784","id":"a65pmaojg9w4","geo_precision":"zip","student":"Kevin Dumler"},"type":"Feature","geometry":{"type":"Point","coordinates":[-116.246997,34.128118]}},{"properties":{"geo_score":0.714,"zip code":"03901","id":"a65pmafo2g6d","geo_precision":"zip","student":"Andrew Hayford"},"type":"Feature","geometry":{"type":"Point","coordinates":[-70.740013,43.279539]}},{"properties":{"geo_score":0.714,"zip code":"16509","id":"a65pmakvb4tm","geo_precision":"zip","student":"Laura Hurst"},"type":"Feature","geometry":{"type":"Point","coordinates":[-80.201452,42.068391]}},{"properties":{"geo_score":0.714,"zip code":"22009","id":"a65pmaqrijch","geo_precision":"zip","student":"Lisa Junta"},"type":"Feature","geometry":{"type":"Point","coordinates":[-77.288755,38.831813]}},{"properties":{"geo_score":0.714,"zip code":"70801","id":"a65pmafejzl9","geo_precision":"zip","student":"MerryJean losso"},"type":"Feature","geometry":{"type":"Point","coordinates":[-91.185607,30.44924]}},{"properties":{"geo_score":0.714,"zip code":"07001","id":"a65pmagsfgfz","geo_precision":"zip","student":"Sana Naseem"},"type":"Feature","geometry":{"type":"Point","coordinates":[-74.27524,40.582845]}},{"properties":{"geo_score":0.714,"zip code":"93257","id":"a65pmaijyqg3","geo_precision":"zip","student":"Reynaldo Pacheco"},"type":"Feature","geometry":{"type":"Point","coordinates":[-119.045658,36.114674]}},{"properties":{"geo_score":0.714,"zip code":"73003","id":"a65pmaqm83ob","geo_precision":"zip","student":"Sarah Reid"},"type":"Feature","geometry":{"type":"Point","coordinates":[-97.499681,35.674777]}},{"properties":{"geo_score":0.714,"zip code":"20601","id":"a65pmamna1et","geo_precision":"zip","student":"Mariama Souley Dounda"},"type":"Feature","geometry":{"type":"Point","coordinates":[-76.974419,38.672617]}}],"is_temporal":false,"author":{"url":"","metadata":"","contact_name":"","contact_address":"","source":"","contact_phone":""},"source":"","pagination":{"sort":null,"start":0,"total":10,"limit":1000000},"state":"complete","tags":"","published":"2014-08-10T22:56:24-04:00","id":98750}