{"type":"FeatureCollection","url":"http://maps.google.ca/maps/ms?vps=2&jsv=321b&hl=en&ie=UTF8&msa=0&output=georss&msid=209723771496233076694.00049e238dcd9d8e62515","data_type":"Data Feed","url_type":"rss","permissions":[{"permissions":{"download":true,"view":true},"group_id":"everyone"}],"classification":null,"title":"David Alberda Mortgage Alliance - Calgary Mortgages","count":1,"stream_id":99626,"contributor":{"url":"http://geocommons.com/users/23365","name":"davealberda"},"data_attributes":null,"calculation_params":null,"icon_link":null,"link":"http://geocommons.com/overlays/99626.json","extent":[-114.067,51.0111,-114.067,51.0111],"geometry_types":["point"],"unique_name":null,"name":"David Alberda Mortgage Alliance - Calgary Mortgages","feature_count":1,"description":"Providing value and the ultimate mortgages in Calgary, AB. Choosing the right mortgage broker will save you time and money. Calgary Mortgage, Calgary Mortgages, Calgary Mortgage Broker\nAddress: 4614 Macleod Trail Sw, Calgary, AB T2G 5E8\nPhone: 403 803-4675\nWebsite: http://www.alberdamortgage.com","next_feature":null,"is_raster":false,"short_classification":"Y","stats":{"published":{"max":"2011/03/10 11:44:07 -0500","min":"2011/03/10 11:44:07 -0500","median":"2011/03/10 11:44:07 -0500"},"georss:elev":{"max":0.0,"min":0.0,"median":0.0}},"features":[{"properties":{"title":"David Alberda Mortgage Alliance - Calgary Mortgages","guid":"00049e238dcf21a215f13","published":{"end_time":"2011/03/10 11:44:08 -0500","original":"Thu, 10 Mar 2011 16:44:07 +0000","granularity":"sec","time":"2011/03/10 11:44:07 -0500"},"description":"Providing value and the ultimate mortgages in Calgary, AB. Choosing the right mortgage broker will save you time and money. <a href=\"http://www.alberdamortgage.com\">Calgary Mortgage</a>, <a href=\"http://www.alberdamortgage.com\">Calgary Mortgages</a>, <a href=\"http://www.alberdamortgage.com\">Calgary Mortgage Broker</a>Address: 4614 Macleod Trail Sw, Calgary, AB T2G 5E8Phone: 403 803-4675Website: <a href=\"http://www.alberdamortgage.com\">http://www.alberdamortgage.com</a>","id":"a629ytudpy0v","georss:elev":0.0},"type":"Feature","geometry":{"type":"Point","coordinates":[-114.066772,51.011066]}}],"is_temporal":true,"author":{"url":"","metadata":"","contact_name":"","contact_address":"","source":"","contact_phone":""},"source":"","pagination":{"sort":null,"start":0,"total":1,"limit":1000000},"state":"complete","tags":"alberda,broker,calgary,dave,lender,mortgage,mortgages","published":"2014-08-10T23:57:43-04:00","id":99626}